Workbook

Sheet recreation_v2_10
A1: Evaluator | B1: Question | C1: status | D1: response_time | E1: answerability | F1: primary_kc_alignment | G1: secondary_kc_alignment | H1: synergy | I1: topic_alignment | J1: grade_alignment | K1: real_world_feasibility | L1: clarity | M1: conciseness_and_relevance | N1: language_quality | O1: content_appropriateness | P1: explanation
A2: TD | B2: Question 1 | C2: 0 | D2: 11.489272 | E2: 1 | F2: 1 | G2: 1 | H2: 1 | I2: 1 | J2: 0 | K2: 1 | L2: 1 | M2: 1 | N2: 1 | O2: 1 | P2: Grade Alignment: The problem uses 4-digit numbers (1562, 738) and requires multi-step operations that are typically beyond Primary 3 level. Primary 3 students usually work with 3-digit numbers and simpler single-step or two-step problems.
A3: TD | B3: Question 2 | C3: 0 | D3: 7.3595858 | E3: 0 | F3: 'NA | G3: 'NA | H3: 'NA | I3: 'NA | J3: 'NA | K3: 'NA | L3: 'NA | M3: 'NA | N3: 'NA | O3: 'NA | P3: Answerability: The problem cannot be solved as stated. To find average time per 10 metres, we need 202.457 / (500/10) = 202.457 / 50 = 4.04914 seconds. This requires division by 50, but the given information only allows division by whole numbers, not the result of 500/10. Primary KC Alignment: The problem requires 202.457 / 50 = 4.04914, which is division by 50. However, the intended primary KC is division by 10, 100, 1000 and their multiples. 50 is not 10, 100, 1000 or their multiples (multiples would be 20, 30, 200, 300, 2000, 3000, etc. but 50 is not among standard multiples typically covered).
A4: TD | B4: Question 3 | C4: 0 | D4: 5.4888599 | E4: 1 | F4: 0 | G4: 1 | H4: 'NA | I4: 1 | J4: 'NA | K4: 1 | L4: 1 | M4: 1 | N4: 1 | O4: 1 | P4: Primary KC Alignment: The problem requires dividing 12.000 by 10, but this is basic division by 10 which moves decimal point one place left. The intended primary KC specifies dividing decimals up to 3 decimal places by 10, 100, 1000 and their multiples, suggesting more complex operations with longer decimals or larger divisors. This problem only uses simple division by 10 with a result that has no decimal places after moving the decimal point.
A5: TD | B5: Question 4 | C5: 0 | D5: 2.7106245 | E5: 1 | F5: 1 | G5: 1 | H5: 1 | I5: 1 | J5: 1 | K5: 1 | L5: 1 | M5: 1 | N5: 1 | O5: 1
A6: TD | B6: Question 5 | C6: 0 | D6: 8.696775 | E6: 1 | F6: 1 | G6: 1 | H6: 1 | I6: 1 | J6: 1 | K6: 1 | L6: 1 | M6: 1 | N6: 1 | O6: 1
A7: TD | B7: Question 6 | C7: 0 | D7: 8.2287269 | E7: 1 | F7: 1 | G7: 1 | H7: 1 | I7: 1 | J7: 1 | K7: 1 | L7: 1 | M7: 1 | N7: 1 | O7: 1
A8: TD | B8: Question 7 | C8: 0 | D8: 7.4001384 | E8: 1 | F8: 1 | G8: 1 | H8: 1 | I8: 1 | J8: 1 | K8: 0 | L8: 1 | M8: 1 | N8: 1 | O8: 1 | P8: Real-world feasibility: The problem asks how many 45-minute dance routines can fit in 2 hours, which mathematically gives 2.67 routines. However, in reality, you cannot perform 2/3 of a dance routine - dance routines are complete performances that cannot be meaningfully fractioned. A dancer would only be able to perform 2 complete routines in 2 hours, making the mathematical answer unrealistic for the given context.
A9: TD | B9: Question 8 | C9: 0 | D9: 9.3756206 | E9: 1 | F9: 1 | G9: 1 | H9: 1 | I9: 1 | J9: 1 | K9: 1 | L9: 1 | M9: 1 | N9: 1 | O9: 1
A10: TD | B10: Question 9 | C10: 0 | D10: 5.9396985 | E10: 1 | F10: 1 | G10: 1 | H10: 1 | I10: 1 | J10: 0 | K10: 0 | L10: 1 | M10: 1 | N10: 1 | O10: 1 | P10: Grade Alignment: Matrix operations are typically introduced at A-level or equivalent advanced secondary level, not O-level 3/4. O-level students typically study basic algebra, geometry, and statistics. Real-World Plausibility: The impact factor matrix M with values like 0.5 and 0.8 as weightage for sports activities lacks clear real-world meaning. What does multiplying hours by these arbitrary factors represent in practical terms? The explanation of what C x M represents is not intuitive or realistic in a sports club context.
A11: TD | B11: Question 10 | C11: 0 | D11: 9.7642334 | E11: 1 | F11: 1 | G11: 1 | H11: 1 | I11: 1 | J11: 1 | K11: 1 | L11: 1 | M11: 1 | N11: 1 | O11: 1
A12: TD | B12: Question 11 | C12: 0 | D12: 9.7050951 | E12: 1 | F12: 1 | G12: 1 | H12: 1 | I12: 1 | J12: 1 | K12: 0 | L12: 1 | M12: 1 | N12: 1 | O12: 1 | P12: Real-world feasibility: Attending 5/3 sessions (approximately 1.67 sessions) is unrealistic - students typically attend complete sessions, not fractional portions of sessions.
A13: TD | B13: Question 12 | C13: 0 | D13: 4.4945402 | E13: 1 | F13: 1 | G13: 1 | H13: 1 | I13: 1 | J13: 0 | K13: 1 | L13: 1 | M13: 1 | N13: 1 | O13: 1 | P13: grade_alignment: The problem requires understanding of algebraic variables (x, n), algebraic expressions with variables, and algebraic manipulation which are typically introduced in Secondary 1/2 mathematics, not Primary 6. Primary 6 students in Singapore typically work with basic arithmetic and simple number patterns, not formal algebra with variables.
A14: TD | B14: Question 13 | C14: 0 | D14: 10.570142 | E14: 1 | F14: 1 | G14: 1 | H14: 1 | I14: 1 | J14: 0 | K14: 1 | L14: 1 | M14: 1 | N14: 1 | O14: 1 | P14: Grade Alignment: The calculation 5.30 / 4 = 1.325 results in a 3-decimal place answer, which is beyond Primary 4 level expectations for decimal precision.
A15: TD | B15: Question 14 | C15: 0 | D15: 10.282065 | E15: 1 | F15: 1 | G15: 1 | H15: 1 | I15: 1 | J15: 0 | K15: 1 | L15: 1 | M15: 1 | N15: 1 | O15: 1 | P15: Grade Alignment: The problem involves basic percentage calculation (15% increase) and simple subtraction, which are too elementary for Secondary O-level 1 students who should be working with advanced algebra, trigonometry, and complex mathematical concepts.
A16: TD | B16: Question 15 | C16: 0 | D16: 10.171179 | E16: 1 | F16: 1 | G16: 0 | H16: 'NA | I16: 1 | J16: 1 | K16: 1 | L16: 1 | M16: 1 | N16: 1 | O16: 1 | P16: The intended Secondary Knowledge Component is 'Finding mean deviation' which refers to calculating the average absolute deviation from the mean, but the problem only asks for calculating the mean in part (a). Mean deviation would require finding |xi - mean| for each value and then averaging those deviations.
A17: TD | B17: Question 16 | C17: 0 | D17: 10.177311 | E17: 0 | F17: 'NA | G17: 'NA | H17: 'NA | I17: 'NA | J17: 'NA | K17: 'NA | L17: 'NA | M17: 'NA | N17: 'NA | O17: 'NA | P17: Answerability: Logical inconsistency - if 2.35 points were wrongly added to 17.5 earned points, displayed score should be 19.85, not 17.5. Primary KC Alignment: Problem does not require multiplying decimals by 10/100/1000 or multiples - only decimal subtraction is needed. Synergy: Primary and secondary knowledge components cannot work in tandem since primary KC is not needed for solution.
A18: TD | B18: Question 17 | C18: 0 | D18: 10.726846 | E18: 0 | F18: 'NA | G18: 'NA | H18: 'NA | I18: 'NA | J18: 'NA | K18: 'NA | L18: 'NA | M18: 'NA | N18: 'NA | O18: 'NA | P18: The problem lacks essential information - the number of sessions Sarah attended last month is not provided. Without this information, it is impossible to calculate how many sessions she attended this month (5/3 times last month's sessions) and therefore impossible to determine the total paint used this month.
A19: TD | B19: Question 18 | C19: 0 | D19: 11.281861 | E19: 1 | F19: 1 | G19: 1 | H19: 1 | I19: 1 | J19: 1 | K19: 1 | L19: 1 | M19: 1 | N19: 1 | O19: 1
A20: TD | B20: Question 19 | C20: 0 | D20: 9.4469039 | E20: 1 | F20: 1 | G20: 1 | H20: 1 | I20: 1 | J20: 1 | K20: 1 | L20: 1 | M20: 1 | N20: 1 | O20: 1
A21: TD | B21: Question 20 | C21: 0 | D21: 7.7633095 | E21: 0 | F21: 'NA | G21: 'NA | H21: 'NA | I21: 'NA | J21: 'NA | K21: 'NA | L21: 'NA | M21: 'NA | N21: 'NA | O21: 'NA | P21: Answerability: The problem assumes painting completion is proportional to time spent without stating this relationship explicitly, creating ambiguity about how to solve it mathematically. Real-world feasibility: The assumption that painting progress is directly proportional to time spent is unrealistic - factors like complexity of different sections, drying time, and painting technique affect progress. Clarity: The connection between time spent and fraction of painting completed is not clearly established, making the problem ambiguous.
A22: TD | B22: Question 21 | C22: 0 | D22: 10.221833 | E22: 1 | F22: 1 | G22: 1 | H22: 1 | I22: 1 | J22: 1 | K22: 1 | L22: 1 | M22: 1 | N22: 1 | O22: 1
A23: TD | B23: Question 22 | C23: 0 | D23: 10.072337 | E23: 1 | F23: 0 | G23: 1 | H23: 'NA | I23: 1 | J23: 'NA | K23: 1 | L23: 1 | M23: 1 | N23: 1 | O23: 1 | P23: Primary KC alignment: Problem uses decimals with 3 decimal places (8.125, 8.085) but intended component specifies up to 2 decimal places only. Synergy: Part (a) calculates Mei's total score but this result is not used in part (b) which only compares final round scores - the two parts are independent rather than connected.
A24: TD | B24: Question 23 | C24: 0 | D24: 6.6962919 | E24: 0 | F24: 'NA | G24: 'NA | H24: 'NA | I24: 'NA | J24: 'NA | K24: 'NA | L24: 'NA | M24: 'NA | N24: 'NA | O24: 'NA | P24: Answerability: The problem is missing critical information - the number of practice days last month is not provided. Without this information, it is impossible to calculate the total hours each student spends practicing this month. The problem gives a ratio (9/5 times as many days) but no baseline number to multiply against.
A25: TD | B25: Question 24 | C25: 0 | D25: 11.906993 | E25: 1 | F25: 1 | G25: 1 | H25: 1 | I25: 1 | J25: 0 | K25: 0 | L25: 1 | M25: 1 | N25: 1 | O25: 1 | P25: Grade alignment: Direct proportion is too advanced for Secondary O-level 2 students. Real-world feasibility: The ratio of 6 mats for 8 participants (0.75 mats per person) is unrealistic - fitness classes typically use 1 mat per participant.
A26: TD | B26: Question 25 | C26: 0 | D26: 8.9400353 | E26: 1 | F26: 1 | G26: 1 | H26: 1 | I26: 1 | J26: 1 | K26: 1 | L26: 1 | M26: 1 | N26: 1 | O26: 1
A27: Minh | B27: Question 1 | C27: 0 | D27: 10.790107 | E27: 1 | F27: 0 | G27: 1 | H27: 'NA | I27: 1 | J27: 'NA | K27: 1 | L27: 1 | M27: 1 | N27: 1 | O27: 1 | P27: Primary KC specifies adding decimals up to 2 decimal places, but the problem includes 1.797 which has 3 decimal places, exceeding the specified limit.
A28: Minh | B28: Question 2 | C28: 0 | D28: 9.1472688 | E28: 1 | F28: 1 | G28: 1 | H28: 1 | I28: 1 | J28: 1 | K28: 1 | L28: 1 | M28: 1 | N28: 1 | O28: 1
A29: Minh | B29: Question 3 | C29: 0 | D29: 10.790239 | E29: 1 | F29: 1 | G29: 1 | H29: 1 | I29: 1 | J29: 1 | K29: 0 | L29: 1 | M29: 1 | N29: 1 | O29: 1 | P29: Real-world feasibility fails because 0.125 hours / 1000 students = 0.0001125 hours per student, which equals approximately 0.4 seconds. This duration is too brief for meaningful piano practice and does not represent a realistic educational scenario.
A30: Minh | B30: Question 4 | C30: 0 | D30: 12.334376 | E30: 1 | F30: 1 | G30: 1 | H30: 1 | I30: 1 | J30: 0 | K30: 1 | L30: 1 | M30: 1 | N30: 1 | O30: 1 | P30: Grade Alignment: Matrix operations including scalar multiplication and matrix subtraction are typically taught at A-level Secondary 5/6 in Singapore syllabus, not at O-level 3/4. O-level mathematics covers arithmetic, algebra, geometry and basic statistics but not matrix algebra.
A31: Minh | B31: Question 5 | C31: 0 | D31: 11.813534 | E31: 1 | F31: 1 | G31: 1 | H31: 1 | I31: 1 | J31: 1 | K31: 1 | L31: 1 | M31: 1 | N31: 1 | O31: 1
A32: Minh | B32: Question 6 | C32: 0 | D32: 9.7078769 | E32: 1 | F32: 1 | G32: 1 | H32: 1 | I32: 1 | J32: 1 | K32: 1 | L32: 1 | M32: 1 | N32: 1 | O32: 1
A33: Minh | B33: Question 7 | C33: 0 | D33: 9.7161987 | E33: 1 | F33: 1 | G33: 1 | H33: 1 | I33: 1 | J33: 1 | K33: 1 | L33: 1 | M33: 1 | N33: 1 | O33: 1
A34: Minh | B34: Question 8 | C34: 0 | D34: 9.9181993 | E34: 1 | F34: 1 | G34: 1 | H34: 1 | I34: 1 | J34: 1 | K34: 1 | L34: 1 | M34: 1 | N34: 1 | O34: 1
A35: Minh | B35: Question 9 | C35: 0 | D35: 9.9287775 | E35: 1 | F35: 1 | G35: 1 | H35: 1 | I35: 1 | J35: 1 | K35: 1 | L35: 1 | M35: 1 | N35: 1 | O35: 1
A36: Minh | B36: Question 10 | C36: 0 | D36: 4.5193596 | E36: 1 | F36: 1 | G36: 1 | H36: 1 | I36: 1 | J36: 0 | K36: 1 | L36: 1 | M36: 1 | N36: 1 | O36: 1 | P36: Grade Alignment: The problem uses terminology like lower quartile Q1, median Q2, upper quartile Q3, and interquartile range which are typically introduced at Primary 6 level in Singapore math syllabus, not Secondary O-level 3/4. The complexity and mathematical concepts required are below the intended grade level.
A37: Minh | B37: Question 11 | C37: 0 | D37: 2.7414355 | E37: 1 | F37: 1 | G37: 1 | H37: 1 | I37: 1 | J37: 1 | K37: 1 | L37: 1 | M37: 1 | N37: 1 | O37: 1
A38: Minh | B38: Question 12 | C38: 0 | D38: 12.432577 | E38: 0 | F38: 'NA | G38: 'NA | H38: 'NA | I38: 'NA | J38: 'NA | K38: 'NA | L38: 'NA | M38: 'NA | N38: 'NA | O38: 'NA | P38: Answerability: Problem contains conflicting information - using 5/6 ratio gives 20 painting students but using 3/4:2 ratio gives 9 painting students, making problem unsolvable. Secondary KC Alignment: Solution only requires fraction multiplication and ratio solving, not fraction division as intended. Synergy: Since secondary KC (fraction division) is not needed, primary and secondary KCs do not work in tandem. Grade Alignment: Complex ratio problem with conflicting constraints too advanced for Secondary O-level 1 students aged 13-14.
A39: Minh | B39: Question 13 | C39: 0 | D39: 11.611055 | E39: 1 | F39: 1 | G39: 1 | H39: 0 | I39: 1 | J39: 0 | K39: 1 | L39: 1 | M39: 1 | N39: 1 | O39: 1 | P39: Synergy: The two parts are not connected - part (b) does not use results from part (a), they are independent questions sharing only context. Grade Alignment: The problem involves basic inverse proportion (4*120=6*x) and simple division (36/6=6) which are too elementary for Secondary O-level 2 students who should handle more complex mathematical concepts.
A40: Minh | B40: Question 14 | C40: 0 | D40: 10.520213 | E40: 0 | F40: 'NA | G40: 'NA | H40: 'NA | I40: 'NA | J40: 'NA | K40: 'NA | L40: 'NA | M40: 'NA | N40: 'NA | O40: 'NA | P40: The problem is not answerable because 183 / 4 = 45.75, meaning 183 children cannot be divided equally into 4 groups with whole numbers of children per group.
A41: Minh | B41: Question 15 | C41: 0 | D41: 7.354491 | E41: 0 | F41: 'NA | G41: 'NA | H41: 'NA | I41: 'NA | J41: 'NA | K41: 'NA | L41: 'NA | M41: 'NA | N41: 'NA | O41: 'NA | P41: Answerability: The problem contains conflicting information. The first part asks to write equations with variables x and y, but the second part provides specific values (3 hours, 5 rackets) that make the total cost $22, which contradicts the given total of $28. Primary KC Alignment: The problem does not require solving linear equations in two variables as the primary skill. The second question can be answered with simple arithmetic (4*3 + 2*5 = 22) without any equation solving. The main focus is on setting up equations rather than solving them. Synergy: The two parts of the problem are disconnected. The first part asks for equation setup while the second part is a simple calculation that does not use the equations from the first part, failing to demonstrate how both knowledge components work together.
A42: Minh | B42: Question 16 | C42: 0 | D42: 2.7689791 | E42: 1 | F42: 1 | G42: 1 | H42: 1 | I42: 1 | J42: 1 | K42: 1 | L42: 1 | M42: 1 | N42: 1 | O42: 1
A43: Minh | B43: Question 17 | C43: 0 | D43: 10.49562 | E43: 1 | F43: 1 | G43: 0 | H43: 'NA | I43: 1 | J43: 1 | K43: 1 | L43: 1 | M43: 1 | N43: 1 | O43: 1 | P43: Secondary KC alignment: Problem only requires division (168/4=42, 42/6=7) but intended secondary KC is multiplication which is not needed. Synergy: No synergy exists since multiplication component is not utilized in the solution.
A44: Minh | B44: Question 18 | C44: 0 | D44: 4.2926898 | E44: 1 | F44: 1 | G44: 1 | H44: 1 | I44: 1 | J44: 1 | K44: 0 | L44: 1 | M44: 1 | N44: 1 | O44: 1 | P44: Real-world feasibility: Playing football for 12 hours in one week and 18 hours in another week is unrealistic for a primary school student. This amounts to 1.7-2.6 hours daily which is excessive and unhealthy for children, not reflecting typical recreational football playing patterns.
A45: Minh | B45: Question 19 | C45: 0 | D45: 2.7375066 | E45: 1 | F45: 1 | G45: 1 | H45: 1 | I45: 1 | J45: 1 | K45: 1 | L45: 1 | M45: 1 | N45: 1 | O45: 1
A46: Minh | B46: Question 20 | C46: 0 | D46: 4.7758963 | E46: 1 | F46: 1 | G46: 0 | H46: 'NA | I46: 1 | J46: 1 | K46: 1 | L46: 1 | M46: 1 | N46: 1 | O46: 1 | P46: Secondary Knowledge Component Alignment: The problem does not require subtracting decimals to solve. The solution only needs division: 36.84 / 6 = 6.14 per week, then 6.14 * 2 = 12.28 for remaining weeks. Synergy: Since decimal subtraction is not needed, the primary and secondary knowledge components are not used in tandem to solve the problem.
A47: Minh | B47: Question 21 | C47: 0 | D47: 2.8554132 | E47: 1 | F47: 1 | G47: 1 | H47: 1 | I47: 1 | J47: 1 | K47: 1 | L47: 1 | M47: 1 | N47: 1 | O47: 1
A48: Minh | B48: Question 22 | C48: 0 | D48: 9.6706643 | E48: 1 | F48: 1 | G48: 1 | H48: 1 | I48: 1 | J48: 1 | K48: 1 | L48: 1 | M48: 1 | N48: 1 | O48: 1
A49: Minh | B49: Question 23 | C49: 0 | D49: 5.153507 | E49: 1 | F49: 1 | G49: 1 | H49: 1 | I49: 0 | J49: 0 | K49: 1 | L49: 1 | M49: 1 | N49: 1 | O49: 1 | P49: Topic Alignment: The problem context is about school clubs (Science Club, Music Club) which are academic/educational activities, not recreation activities like sports, games, exercises, music performance, movies, dancing, painting, or fishing. Grade Alignment: This problem requires formal set notation and set operations concepts that are typically introduced at higher secondary levels or pre-university mathematics, not at Secondary O-level 3/4 where basic arithmetic and algebra are the focus.
A50: Minh | B50: Question 24 | C50: 0 | D50: 8.6996899 | E50: 1 | F50: 1 | G50: 1 | H50: 1 | I50: 1 | J50: 1 | K50: 1 | L50: 1 | M50: 1 | N50: 1 | O50: 1
A51: Minh | B51: Question 25 | C51: 0 | D51: 5.5416696 | E51: 1 | F51: 1 | G51: 1 | H51: 0 | I51: 1 | J51: 0 | K51: 1 | L51: 1 | M51: 1 | N51: 1 | O51: 1 | P51: synergy: The two parts (a) and (b) are independent calculations that do not require using the result from part (a) to solve part (b). There is no connection between the questions where one builds upon the other. grade_alignment: Finding median and mode are basic statistical concepts typically introduced in Primary 5-6 or Secondary 1 levels. This problem is too elementary for Secondary O-level 2 students, who should be working with more advanced statistical concepts like standard deviation, probability distributions, or hypothesis testing.
A52: Sarah | B52: Question 1 | C52: 0 | D52: 9.0540767 | E52: 1 | F52: 1 | G52: 1 | H52: 1 | I52: 1 | J52: 1 | K52: 1 | L52: 1 | M52: 1 | N52: 1 | O52: 1
A53: Sarah | B53: Question 2 | C53: 0 | D53: 5.1160297 | E53: 1 | F53: 1 | G53: 1 | H53: 1 | I53: 1 | J53: 0 | K53: 1 | L53: 1 | M53: 1 | N53: 1 | O53: 1 | P53: grade_alignment: The problem is designed for Secondary O-level 2 but uses very basic linear inequality concepts that are typically introduced much earlier in Primary 6 or Secondary 1. The mathematical complexity (12n + 10 <= 50) is too simple for O-level 2 students who should be handling more advanced algebraic concepts involving multiple variables, systems of inequalities, or quadratic relationships.
A54: Sarah | B54: Question 3 | C54: 0 | D54: 4.9281068 | E54: 1 | F54: 1 | G54: 1 | H54: 1 | I54: 1 | J54: 0 | K54: 1 | L54: 1 | M54: 1 | N54: 1 | O54: 1 | P54: Grade Alignment: This problem is too simple for Secondary O-level 3/4 students. It involves basic probability concepts (drawing cards and rolling dice) that are typically taught at primary or lower secondary levels. O-level 3/4 students would be expected to handle more complex probability scenarios involving conditional probability, permutations, combinations, or multi-step probability problems with more sophisticated mathematical reasoning.
A55: Sarah | B55: Question 4 | C55: 0 | D55: 11.4257 | E55: 1 | F55: 1 | G55: 1 | H55: 1 | I55: 1 | J55: 1 | K55: 0 | L55: 0 | M55: 1 | N55: 1 | O55: 1 | P55: Real-world feasibility: If friends paint together and divide 3/4 hour equally among 3 people, Sarah leaving 1/6 hour early would affect everyone's time, not create individual time allocations. Clarity: Problem is ambiguous about whether painting is collaborative or individual, and part (b) question unclear about what comparison is requested.
A56: Sarah | B56: Question 5 | C56: 0 | D56: 14.068829 | E56: 1 | F56: 1 | G56: 1 | H56: 1 | I56: 1 | J56: 0 | K56: 0 | L56: 0 | M56: 1 | N56: 1 | O56: 1 | P56: Grade alignment: Problem too simple for O-level students, involves basic percentage calculations suitable for primary level. Real-world feasibility: Piano exams typically use qualitative grades not numerical marks out of 100, scenario lacks realistic context. Clarity: Ambiguous whether 80% and 96 refer to percentage scores or absolute marks, relationship between different values unclear.
A57: Sarah | B57: Question 6 | C57: 0 | D57: 4.7569616 | E57: 1 | F57: 1 | G57: 1 | H57: 1 | I57: 1 | J57: 1 | K57: 0 | L57: 1 | M57: 1 | N57: 1 | O57: 1 | P57: Real-world feasibility: In table tennis, players do not hit the ball distances of 2+ metres as described. Table tennis is played on a table that is 2.74m long, so hitting the ball 2.35m, 2.171m, or 2.47m as consistent distances during practice does not reflect realistic table tennis gameplay where the ball travels back and forth across the net on the table surface.
A58: Sarah | B58: Question 7 | C58: 0 | D58: 5.1005027 | E58: 1 | F58: 1 | G58: 1 | H58: 1 | I58: 1 | J58: 0 | K58: 0 | L58: 1 | M58: 1 | N58: 1 | O58: 1 | P58: Grade alignment: This problem involves basic ratio concepts and decimal addition which are typically covered in primary grades (Primary 5-6), not Secondary O-level 1 which would require more advanced mathematical concepts. Real-world feasibility: Having 12.5 boys and 3.7 girls joining is unrealistic as you cannot have fractional people in real-world scenarios.
A59: Sarah | B59: Question 8 | C59: 0 | D59: 9.1456816 | E59: 1 | F59: 1 | G59: 1 | H59: 1 | I59: 1 | J59: 1 | K59: 1 | L59: 1 | M59: 1 | N59: 1 | O59: 1
A60: Sarah | B60: Question 9 | C60: 0 | D60: 5.2248659 | E60: 1 | F60: 1 | G60: 1 | H60: 1 | I60: 1 | J60: 0 | K60: 1 | L60: 1 | M60: 1 | N60: 1 | O60: 1 | P60: Grade Alignment: This problem is too easy for Secondary O-level 1 students. Calculating percentage increase (150-120)/120 * 100 = 25% and converting 25% to fraction 1/4 are concepts typically mastered in primary grades 5-6. Secondary O-level 1 students would expect more complex percentage problems involving compound calculations, multiple steps, or advanced applications.
A61: Sarah | B61: Question 10 | C61: 0 | D61: 11.993373 | E61: 1 | F61: 1 | G61: 1 | H61: 1 | I61: 1 | J61: 1 | K61: 0 | L61: 1 | M61: 1 | N61: 1 | O61: 1 | P61: Real-world plausibility issue: A student practicing 7/4 (175%) of planned time on Monday and then 5/3 of that amount on Tuesday does not reflect realistic practice scenarios. People typically practice within reasonable time limits, not exceeding planned time by such large margins.
A62: Sarah | B62: Question 11 | C62: 0 | D62: 10.626365 | E62: 1 | F62: 1 | G62: 1 | H62: 1 | I62: 1 | J62: 1 | K62: 1 | L62: 1 | M62: 1 | N62: 1 | O62: 1
A63: Sarah | B63: Question 12 | C63: 0 | D63: 5.4615138 | E63: 1 | F63: 1 | G63: 1 | H63: 1 | I63: 1 | J63: 0 | K63: 0 | L63: 1 | M63: 1 | N63: 1 | O63: 1 | P63: Grade Alignment: The problem is intended for Secondary O-level 1 but involves quadratic expressions (2x^2 + 3x + 5) which are typically introduced in later secondary grades, making it too advanced for the intended grade level. Real-World Plausibility: Mini-golf course booking costs following a quadratic function 2x^2 + 3x + 5 is unrealistic - actual hourly rates are typically linear or have fixed costs, not quadratic relationships where cost increases exponentially with time.
A64: Sarah | B64: Question 13 | C64: 0 | D64: 9.402385 | E64: 1 | F64: 1 | G64: 1 | H64: 1 | I64: 1 | J64: 1 | K64: 1 | L64: 1 | M64: 1 | N64: 1 | O64: 1
A65: Sarah | B65: Question 14 | C65: 0 | D65: 2.6679268 | E65: 1 | F65: 1 | G65: 1 | H65: 1 | I65: 1 | J65: 1 | K65: 1 | L65: 1 | M65: 1 | N65: 1 | O65: 1
A66: Sarah | B66: Question 15 | C66: 0 | D66: 4.7196543 | E66: 1 | F66: 1 | G66: 1 | H66: 1 | I66: 1 | J66: 0 | K66: 1 | L66: 1 | M66: 1 | N66: 1 | O66: 1 | P66: Grade alignment: This problem involves basic ratio concepts with simple fractions that would typically be taught at Primary 5-6 level in Singapore math curriculum, not Secondary O-level 1. The complexity level is too low for Secondary O-level students who would be expected to handle more advanced algebraic ratios and complex fraction operations.
A67: Sarah | B67: Question 16 | C67: 0 | D67: 10.272307 | E67: 1 | F67: 1 | G67: 1 | H67: 1 | I67: 1 | J67: 1 | K67: 1 | L67: 1 | M67: 1 | N67: 1 | O67: 1
A68: Sarah | B68: Question 17 | C68: 0 | D68: 6.6718972 | E68: 0 | F68: 'NA | G68: 'NA | H68: 'NA | I68: 'NA | J68: 'NA | K68: 'NA | L68: 'NA | M68: 'NA | N68: 'NA | O68: 'NA | P68: Answerability: The problem lacks critical information - we cannot determine the remainder without knowing how many complete bottles were filled. The problem states bottles are filled with 0.100 litres each from 14.250 litres total, but doesn't specify how many bottles Sarah actually has available to fill. Primary KC Alignment: The intended primary knowledge component is dividing decimals by 10, 100, 1000 and their multiples, but the actual division required is 14.250 / 0.100 = 142.5, which involves dividing by 0.100 (a decimal), not by whole number multiples of 10, 100, or 1000. Synergy: Since the primary knowledge component alignment fails, the two knowledge components cannot work in proper tandem as intended.
A69: Sarah | B69: Question 18 | C69: 0 | D69: 9.4470522 | E69: 1 | F69: 1 | G69: 1 | H69: 1 | I69: 1 | J69: 1 | K69: 1 | L69: 1 | M69: 1 | N69: 1 | O69: 1
A70: Sarah | B70: Question 19 | C70: 0 | D70: 9.3639731 | E70: 1 | F70: 1 | G70: 1 | H70: 1 | I70: 1 | J70: 1 | K70: 1 | L70: 1 | M70: 1 | N70: 1 | O70: 1
A71: Sarah | B71: Question 20 | C71: 0 | D71: 5.5125754 | E71: 1 | F71: 0 | G71: 1 | H71: 'NA | I71: 1 | J71: 'NA | K71: 1 | L71: 1 | M71: 1 | N71: 1 | O71: 1 | P71: Primary KC alignment: The problem can be solved without addition of probabilities. Students who play at least one instrument = 30 - (students who play neither) = 30 - (30 - 18 - 15 + 6) = 27. Probability = 27/30 = 9/10. No probability addition required. Synergy: Since primary KC is not needed, primary and secondary KCs are not used in tandem. The problem only requires basic probability calculation of combined events, not addition of separate probabilities.
A72: Sarah | B72: Question 21 | C72: 0 | D72: 10.799605 | E72: 1 | F72: 1 | G72: 1 | H72: 1 | I72: 1 | J72: 0 | K72: 1 | L72: 1 | M72: 1 | N72: 1 | O72: 1 | P72: Grade Alignment: The problem involves basic percentage calculation (15% of 120) and simple addition, which are typically mastered in Primary 5-6. For Secondary O-level 1 students, this content is too elementary and does not match the expected mathematical complexity for this grade level.
A73: Sarah | B73: Question 22 | C73: 0 | D73: 9.8867621 | E73: 1 | F73: 1 | G73: 1 | H73: 1 | I73: 1 | J73: 1 | K73: 1 | L73: 1 | M73: 1 | N73: 1 | O73: 1
A74: Sarah | B74: Question 23 | C74: 0 | D74: 11.688546 | E74: 1 | F74: 1 | G74: 1 | H74: 0 | I74: 1 | J74: 0 | K74: 1 | L74: 1 | M74: 1 | N74: 1 | O74: 1 | P74: Synergy: The two parts (a) and (b) are independent questions that can be solved separately without using results from one to solve the other. Grade Alignment: Finding median and range are basic statistical concepts typically taught at Primary 5-6 level, making this problem too elementary for Secondary O-level 2 students who should work with more advanced statistical analysis.
A75: Sarah | B75: Question 24 | C75: 0 | D75: 5.3393629 | E75: 1 | F75: 0 | G75: 1 | H75: 'NA | I75: 1 | J75: 'NA | K75: 1 | L75: 1 | M75: 1 | N75: 1 | O75: 1 | P75: Primary KC Alignment: The problem does not require multiplying decimals by 10, 100, 1000 or their multiples as specified. Part (b) involves 0.775 x 10 = 7.75 and part (c) involves 7.75 x 2 = 15.5, but the main computational focus is on decimal addition (0.125 + 0.25 + 0.4) rather than the intended primary knowledge component of multiplying by powers of 10.
A76: Sarah | B76: Question 25 | C76: 0 | D76: 8.6489401 | E76: 1 | F76: 1 | G76: 1 | H76: 1 | I76: 1 | J76: 1 | K76: 1 | L76: 1 | M76: 1 | N76: 1 | O76: 1
A77: Sarah | B77: Question 26 | C77: 0 | D77: 12.725411 | E77: 0 | F77: 'NA | G77: 'NA | H77: 'NA | I77: 'NA | J77: 'NA | K77: 'NA | L77: 'NA | M77: 'NA | N77: 'NA | O77: 'NA | P77: Answerability: Part (a) gives 12.450/10 = 1.245m per lap, but part (b) provides 10 different distances totaling 12.467m, creating conflicting information. Primary KC Alignment: Problem requires dividing 12.450 by 10, which is basic decimal division, not specifically dividing by multiples of 10, 100, 1000 as intended. Synergy: The logical inconsistency between parts (a) and (b) prevents the knowledge components from working together effectively.

Sheet recreation_v2_6
A1: Evaluator | B1: Question | C1: status | D1: response_time | E1: answerability | F1: primary_kc_alignment | G1: secondary_kc_alignment | H1: synergy | I1: topic_alignment | J1: grade_alignment | K1: real_world_feasibility | L1: clarity | M1: conciseness_and_relevance | N1: language_quality | O1: content_appropriateness | P1: explanation
A2: TD | B2: Question 1 | C2: 0 | D2: 10.966771 | E2: 1 | F2: 1 | G2: 1 | H2: 1 | I2: 1 | J2: 0 | K2: 1 | L2: 1 | M2: 1 | N2: 1 | O2: 1 | P2: Grade alignment: The problem uses 4-digit numbers (1562) which is typically beyond Primary 3 level. Primary 3 students usually work with 3-digit numbers, while 4-digit operations are introduced in Primary 4.
A3: TD | B3: Question 2 | C3: 0 | D3: 12.90036 | E3: 1 | F3: 0 | G3: 1 | H3: 'NA | I3: 1 | J3: 'NA | K3: 1 | L3: 1 | M3: 1 | N3: 1 | O3: 1 | P3: Primary KC alignment fails because the problem requires dividing 202.457 by 50, which is dividing a decimal by a whole number, not specifically by 10, 100, 1000 or their multiples as stated in the intended Primary Knowledge Component.
A4: TD | B4: Question 3 | C4: 0 | D4: 7.8134184 | E4: 1 | F4: 1 | G4: 1 | H4: 1 | I4: 1 | J4: 1 | K4: 0 | L4: 0 | M4: 0 | N4: 1 | O4: 1 | P4: Real-world feasibility: The scenario is unrealistic - Wei Lin swam only 2 days (Monday and Wednesday) but is asked to divide the distance among 10 days, which doesn't make practical sense for a training plan. Clarity: The problem is ambiguous about whether she should swim the average distance for 10 days total or as a daily routine, and the phrase 'that week' conflicts with the 10-day division. Conciseness: The phrase 'rounded to three decimal places' is unnecessary since 12.000/10 = 1.200 already has exactly 3 decimal places, and asking for rounding when no rounding is needed adds confusion.
A5: TD | B5: Question 4 | C5: 0 | D5: 2.885164 | E5: 1 | F5: 1 | G5: 1 | H5: 1 | I5: 1 | J5: 1 | K5: 1 | L5: 1 | M5: 1 | N5: 1 | O5: 1
A6: TD | B6: Question 5 | C6: 0 | D6: 2.7602148 | E6: 1 | F6: 1 | G6: 1 | H6: 1 | I6: 1 | J6: 1 | K6: 1 | L6: 1 | M6: 1 | N6: 1 | O6: 1
A7: TD | B7: Question 6 | C7: 0 | D7: 9.5751102 | E7: 1 | F7: 1 | G7: 1 | H7: 1 | I7: 1 | J7: 1 | K7: 1 | L7: 1 | M7: 1 | N7: 1 | O7: 1
A8: TD | B8: Question 7 | C8: 0 | D8: 7.8254948 | E8: 1 | F8: 1 | G8: 1 | H8: 1 | I8: 1 | J8: 1 | K8: 0 | L8: 1 | M8: 1 | N8: 1 | O8: 1 | P8: Real-world feasibility: The problem asks how many dance routines can be performed in 2 hours when each takes 3/4 hour. The mathematical answer is 8/3 = 2.67 routines, but in reality, you cannot perform 0.67 of a dance routine - you can only perform complete routines (2 full routines with 0.5 hours remaining). This creates a disconnect between the mathematical solution and real-world logic.
A9: TD | B9: Question 8 | C9: 0 | D9: 12.194606 | E9: 1 | F9: 1 | G9: 1 | H9: 1 | I9: 1 | J9: 0 | K9: 1 | L9: 1 | M9: 1 | N9: 1 | O9: 1 | P9: Grade Alignment: The problem uses 0.755 km which has 3 decimal places. Primary 4 students typically work with decimals up to 2 decimal places only. The subtraction 3.83 - 0.755 requires skills beyond typical Primary 4 level.
A10: TD | B10: Question 9 | C10: 0 | D10: 6.3747039 | E10: 1 | F10: 1 | G10: 1 | H10: 1 | I10: 1 | J10: 0 | K10: 0 | L10: 1 | M10: 1 | N10: 1 | O10: 1 | P10: Grade Alignment: Matrix operations including matrix multiplication are typically taught at A-level or higher education level, not at Secondary O-level 3/4 which typically covers basic algebra, geometry, and elementary statistics. Real-World Plausibility: The use of impact factor weightage matrix M with values like 0.5 and 0.8 for different sports activities is not how coaches typically analyze or plan training in reality. Coaches usually work with direct time allocations, percentages, or simple ratios rather than matrix multiplication with decimal weightage factors.
A11: TD | B11: Question 10 | C11: 0 | D11: 2.8708148 | E11: 1 | F11: 1 | G11: 1 | H11: 1 | I11: 1 | J11: 1 | K11: 1 | L11: 1 | M11: 1 | N11: 1 | O11: 1
A12: TD | B12: Question 11 | C12: 0 | D12: 9.4785137 | E12: 1 | F12: 1 | G12: 1 | H12: 1 | I12: 1 | J12: 1 | K12: 0 | L12: 1 | M12: 1 | N12: 1 | O12: 1 | P12: real_world_feasibility: Attending 5/3 sessions (approximately 1.67 sessions) is unrealistic as people typically attend complete sessions, not fractional parts of sessions.
A13: TD | B13: Question 12 | C13: 0 | D13: 4.7401688 | E13: 1 | F13: 1 | G13: 1 | H13: 1 | I13: 1 | J13: 0 | K13: 1 | L13: 1 | M13: 1 | N13: 1 | O13: 1 | P13: Grade Alignment: This problem requires algebraic expressions with variables (x, n) and algebraic manipulation which are typically introduced in Secondary 1-2, not Primary 6. Primary 6 students in Singapore typically work with basic algebra using simple letter representations but not complex algebraic expressions involving multiple variables and simplification at this level.
A14: TD | B14: Question 13 | C14: 0 | D14: 12.019702 | E14: 1 | F14: 1 | G14: 1 | H14: 1 | I14: 1 | J14: 0 | K14: 1 | L14: 1 | M14: 1 | N14: 1 | O14: 1 | P14: Grade Alignment: The division 5.30 / 4 = 1.325 produces a result with 3 decimal places, which exceeds the typical Primary 4 curriculum that works with decimals up to 2 decimal places only.
A15: TD | B15: Question 14 | C15: 0 | D15: 12.121318 | E15: 1 | F15: 1 | G15: 1 | H15: 1 | I15: 1 | J15: 0 | K15: 1 | L15: 1 | M15: 1 | N15: 1 | O15: 1 | P15: Grade Alignment: The problem difficulty is too low for Secondary O-level 1 students. Basic percentage increase (15%) and simple subtraction are typically mastered in primary grades 5-6. Secondary O-level 1 students require more complex percentage applications involving multiple steps, compound changes, or algebraic reasoning.
A16: TD | B16: Question 15 | C16: 0 | D16: 10.797413 | E16: 1 | F16: 1 | G16: 0 | H16: 'NA | I16: 1 | J16: 1 | K16: 1 | L16: 1 | M16: 1 | N16: 1 | O16: 1 | P16: The secondary KC specifies 'Finding mean deviation' but the problem only asks for calculating the mean, not the mean deviation. Mean deviation is a different statistical measure that involves finding the average of absolute deviations from the mean.
A17: TD | B17: Question 16 | C17: 0 | D17: 11.104954 | E17: 0 | F17: 'NA | G17: 'NA | H17: 'NA | I17: 'NA | J17: 'NA | K17: 'NA | L17: 'NA | M17: 'NA | N17: 'NA | O17: 'NA | P17: Answerability: There is conflicting information - if Siti earned 17.5 points and her display shows 17.5 points, then 0 points were wrongly added, contradicting the stated 2.35 wrongly added points. The display should show 17.5 + 2.35 = 19.85 if 2.35 were wrongly added. Primary KC Alignment: The problem requires multiplying 0.175 x 100, which uses 100 exactly, not a multiple of 100 as specified in the intended primary knowledge component about multiples of 10, 100, 1000.
A18: TD | B18: Question 17 | C18: 0 | D18: 10.181165 | E18: 0 | F18: 'NA | G18: 'NA | H18: 'NA | I18: 'NA | J18: 'NA | K18: 'NA | L18: 'NA | M18: 'NA | N18: 'NA | O18: 'NA | P18: Answerability: The problem cannot be solved because it lacks essential information - the number of sessions Sarah attended last month is not provided. Without knowing the baseline number of sessions, we cannot calculate 5/3 of that amount or determine the total paint used this month.
A19: TD | B19: Question 18 | C19: 0 | D19: 11.302904 | E19: 1 | F19: 1 | G19: 1 | H19: 1 | I19: 1 | J19: 1 | K19: 1 | L19: 1 | M19: 1 | N19: 1 | O19: 1
A20: TD | B20: Question 19 | C20: 0 | D20: 9.5451763 | E20: 1 | F20: 1 | G20: 1 | H20: 1 | I20: 1 | J20: 1 | K20: 1 | L20: 1 | M20: 1 | N20: 1 | O20: 1
A21: TD | B21: Question 20 | C21: 0 | D21: 12.942078 | E21: 0 | F21: 'NA | G21: 'NA | H21: 'NA | I21: 'NA | J21: 'NA | K21: 'NA | L21: 'NA | M21: 'NA | N21: 'NA | O21: 'NA | P21: Answerability: Problem requires assumption that painting completion is proportional to time spent, which is not explicitly stated. Real-world feasibility: The direct proportional relationship between time and painting completion is unrealistic as painting efficiency varies. Clarity: The relationship between time spent painting and fraction of painting completed is ambiguous.
A22: TD | B22: Question 21 | C22: 0 | D22: 2.8803875 | E22: 1 | F22: 1 | G22: 1 | H22: 1 | I22: 1 | J22: 1 | K22: 1 | L22: 1 | M22: 1 | N22: 1 | O22: 1
A23: TD | B23: Question 22 | C23: 0 | D23: 12.04306 | E23: 1 | F23: 0 | G23: 1 | H23: 'NA | I23: 1 | J23: 'NA | K23: 1 | L23: 1 | M23: 1 | N23: 1 | O23: 1 | P23: Primary KC alignment: Problem includes 3 decimal places (8.125, 8.085) but intended KC is up to 2 decimal places only. Synergy: Part (a) and (b) are independent - part (b) does not use results from part (a). Grade alignment: 3 decimal places may exceed Primary 4 level expectations in Singapore math curriculum.
A24: TD | B24: Question 23 | C24: 0 | D24: 7.68536 | E24: 0 | F24: 'NA | G24: 'NA | H24: 'NA | I24: 'NA | J24: 'NA | K24: 'NA | L24: 'NA | M24: 'NA | N24: 'NA | O24: 'NA | P24: The problem cannot be solved because critical information is missing - the number of practice days last month is not provided. To find total hours this month, we need: (7/4 hours per day) × (9/5 × days last month), but days last month is unknown. Without this information, the multiplication of fractions 7/4 × 9/5 can be performed but cannot yield the final answer requested.
A25: TD | B25: Question 24 | C25: 0 | D25: 10.481904 | E25: 1 | F25: 1 | G25: 1 | H25: 1 | I25: 1 | J25: 0 | K25: 1 | L25: 1 | M25: 1 | N25: 1 | O25: 1 | P25: Grade Alignment: Direct proportion is typically taught at Primary 6 level in Singapore math curriculum, making this problem too elementary for Secondary O-level 2 students who should be working with more advanced mathematical concepts.
A26: TD | B26: Question 25 | C26: 0 | D26: 2.8732784 | E26: 1 | F26: 1 | G26: 1 | H26: 1 | I26: 1 | J26: 1 | K26: 1 | L26: 1 | M26: 1 | N26: 1 | O26: 1
A27: Minh | B27: Question 1 | C27: 0 | D27: 12.361276 | E27: 1 | F27: 0 | G27: 1 | H27: 'NA | I27: 1 | J27: 'NA | K27: 1 | L27: 1 | M27: 1 | N27: 1 | O27: 1 | P27: Primary KC alignment: The intended primary KC specifies adding decimals up to 2 decimal places, but the problem includes 1.797 which has 3 decimal places, exceeding the specified limit. Grade alignment: Using 3-decimal place numbers like 1.797 may be beyond typical Primary 4 level where students usually work with decimals up to 2 decimal places.
A28: Minh | B28: Question 2 | C28: 0 | D28: 10.247757 | E28: 1 | F28: 1 | G28: 1 | H28: 1 | I28: 1 | J28: 1 | K28: 1 | L28: 1 | M28: 1 | N28: 1 | O28: 1
A29: Minh | B29: Question 3 | C29: 0 | D29: 10.909761 | E29: 1 | F29: 1 | G29: 1 | H29: 1 | I29: 1 | J29: 1 | K29: 0 | L29: 1 | M29: 1 | N29: 1 | O29: 1 | P29: Real-world feasibility: Dividing 0.125 hours (7.5 minutes) among 1000 students gives each student only 0.000125 hours (0.27 seconds) of practice time, which is unrealistic and impractical for actual music education.
A30: Minh | B30: Question 4 | C30: 0 | D30: 12.445494 | E30: 1 | F30: 1 | G30: 1 | H30: 1 | I30: 1 | J30: 0 | K30: 1 | L30: 1 | M30: 1 | N30: 1 | O30: 1 | P30: Grade Alignment: Matrix operations are too advanced for Primary 3/4 students who typically work with basic arithmetic on whole numbers, not matrices which are Secondary O-level concepts.
A31: Minh | B31: Question 5 | C31: 0 | D31: 9.3443689 | E31: 1 | F31: 1 | G31: 1 | H31: 1 | I31: 1 | J31: 1 | K31: 1 | L31: 1 | M31: 1 | N31: 1 | O31: 1
A32: Minh | B32: Question 6 | C32: 0 | D32: 2.8622868 | E32: 1 | F32: 1 | G32: 1 | H32: 1 | I32: 1 | J32: 1 | K32: 1 | L32: 1 | M32: 1 | N32: 1 | O32: 1
A33: Minh | B33: Question 7 | C33: 0 | D33: 11.546589 | E33: 1 | F33: 1 | G33: 1 | H33: 1 | I33: 1 | J33: 0 | K33: 1 | L33: 1 | M33: 1 | N33: 1 | O33: 1 | P33: Grade Alignment: The problem requires formal algebraic equation solving with variables, which is beyond Primary 6 level in Singapore curriculum. Primary 6 students typically solve such problems using arithmetic division (60 / 12 = 5) rather than algebraic methods with variables like n.
A34: Minh | B34: Question 8 | C34: 0 | D34: 9.621103 | E34: 1 | F34: 1 | G34: 1 | H34: 1 | I34: 1 | J34: 1 | K34: 1 | L34: 1 | M34: 1 | N34: 1 | O34: 1
A35: Minh | B35: Question 9 | C35: 0 | D35: 3.0815039 | E35: 1 | F35: 1 | G35: 1 | H35: 1 | I35: 1 | J35: 1 | K35: 1 | L35: 1 | M35: 1 | N35: 1 | O35: 1
A36: Minh | B36: Question 10 | C36: 0 | D36: 4.628762 | E36: 1 | F36: 1 | G36: 1 | H36: 1 | I36: 1 | J36: 0 | K36: 1 | L36: 1 | M36: 1 | N36: 1 | O36: 1 | P36: Grade Alignment: The problem is designed for Secondary O-level 3/4 but quartiles and interquartile range are typically introduced earlier in most Singapore math curricula, around Secondary 1-2 level. The complexity and mathematical rigor expected at O-level 3/4 would typically involve more advanced statistical concepts beyond basic quartile calculations.
A37: Minh | B37: Question 11 | C37: 0 | D37: 3.0786188 | E37: 1 | F37: 1 | G37: 1 | H37: 1 | I37: 1 | J37: 1 | K37: 1 | L37: 1 | M37: 1 | N37: 1 | O37: 1
A38: Minh | B38: Question 12 | C38: 0 | D38: 10.394073 | E38: 0 | F38: 'NA | G38: 'NA | H38: 'NA | I38: 'NA | J38: 'NA | K38: 'NA | L38: 'NA | M38: 'NA | N38: 'NA | O38: 'NA | P38: Answerability: The problem contains conflicting information. From ratio 3/4:2 with 24 dancing students gives 9 painting students, but condition 5/6 as many painting as dancing gives 20 painting students. Secondary KC: No fraction division is required - only fraction multiplication (3/4 divided by 2, then multiply by 24, and 5/6 multiply by 24). Synergy: Since secondary KC fraction division is not actually needed, primary and secondary KCs are not used in tandem. Conciseness: The two conditions (ratio and proportional relationship) provide redundant/conflicting information rather than both being necessary.
A39: Minh | B39: Question 13 | C39: 0 | D39: 6.3774529 | E39: 1 | F39: 1 | G39: 1 | H39: 0 | I39: 1 | J39: 0 | K39: 0 | L39: 1 | M39: 1 | N39: 1 | O39: 1 | P39: Synergy: The two parts (a) and (b) are independent problems that do not require results from part (a) to solve part (b). Part (a) uses inverse proportion while part (b) uses division, but they are not connected. Grade Alignment: This problem is too simple for Secondary O-level 2 students. Inverse proportion and basic division are typically covered in primary grades 5-6, not secondary level. Real-World Feasibility: Board games do not work with inverse proportion in reality. Adding more players typically increases game duration due to more turns and decisions, not decreases it proportionally as the problem suggests.
A40: Minh | B40: Question 14 | C40: 0 | D40: 12.405885 | E40: 0 | F40: 'NA | G40: 'NA | H40: 'NA | I40: 'NA | J40: 'NA | K40: 'NA | L40: 'NA | M40: 'NA | N40: 'NA | O40: 'NA | P40: Answerability: 183 / 4 = 45.75 children per group, which is impossible since you cannot have 0.75 of a child. Real-World Plausibility: Organizers would not attempt to divide children into fractional parts in real situations.
A41: Minh | B41: Question 15 | C41: 0 | D41: 6.7013543 | E41: 0 | F41: 'NA | G41: 'NA | H41: 'NA | I41: 'NA | J41: 'NA | K41: 'NA | L41: 'NA | M41: 'NA | N41: 'NA | O41: 'NA | P41: Answerability: The problem contains conflicting information. It states the total amount paid was $28, but when calculated with the given values (3 hours at $4/hour = $12, plus 5 rackets at $2/racket = $10), the total is only $22, not $28. Primary KC Alignment: The problem does not require solving linear equations in two variables. The problem can be solved using simple arithmetic (4*3 + 2*5 = 22) without needing to solve a system of equations. The equations requested are for representation only, not for solving. Synergy: There is no synergy between the primary and secondary knowledge components since the primary KC (solving linear equations in two variables) is not actually needed to solve the problem.
A42: Minh | B42: Question 16 | C42: 0 | D42: 10.38574 | E42: 1 | F42: 1 | G42: 1 | H42: 1 | I42: 1 | J42: 1 | K42: 1 | L42: 1 | M42: 1 | N42: 1 | O42: 1
A43: Minh | B43: Question 17 | C43: 0 | D43: 10.5807 | E43: 1 | F43: 1 | G43: 0 | H43: 'NA | I43: 1 | J43: 1 | K43: 1 | L43: 1 | M43: 1 | N43: 1 | O43: 1 | P43: Secondary KC alignment: Problem only requires division (168/4=42, then 42/6=7). No multiplication needed. Synergy: Since multiplication is not required, there is no synergy between division and multiplication knowledge components.
A44: Minh | B44: Question 18 | C44: 0 | D44: 4.925298 | E44: 1 | F44: 1 | G44: 1 | H44: 1 | I44: 1 | J44: 1 | K44: 0 | L44: 1 | M44: 1 | N44: 1 | O44: 1 | P44: Real-world feasibility: Playing football for 12 hours in one week and 18 hours in another week is unrealistic. 12 hours per week equals about 1.7 hours per day, and 18 hours per week equals about 2.6 hours per day. While possible, this represents an extremely high amount of football playing for a primary school student during holidays, making the scenario implausible for typical real-world behavior.
A45: Minh | B45: Question 19 | C45: 0 | D45: 2.8755863 | E45: 1 | F45: 1 | G45: 1 | H45: 1 | I45: 1 | J45: 1 | K45: 1 | L45: 1 | M45: 1 | N45: 1 | O45: 1
A46: Minh | B46: Question 20 | C46: 0 | D46: 10.307177 | E46: 1 | F46: 1 | G46: 1 | H46: 1 | I46: 1 | J46: 1 | K46: 1 | L46: 1 | M46: 1 | N46: 1 | O46: 1
A47: Minh | B47: Question 21 | C47: 0 | D47: 2.9371998 | E47: 1 | F47: 1 | G47: 1 | H47: 1 | I47: 1 | J47: 1 | K47: 1 | L47: 1 | M47: 1 | N47: 1 | O47: 1
A48: Minh | B48: Question 22 | C48: 0 | D48: 9.3467119 | E48: 1 | F48: 1 | G48: 1 | H48: 1 | I48: 1 | J48: 1 | K48: 1 | L48: 1 | M48: 1 | N48: 1 | O48: 1
A49: Minh | B49: Question 23 | C49: 0 | D49: 6.3687932 | E49: 1 | F49: 1 | G49: 1 | H49: 1 | I49: 0 | J49: 0 | K49: 1 | L49: 1 | M49: 1 | N49: 1 | O49: 1 | P49: Topic Alignment: The problem context is about school clubs (Science Club, Music Club) which are educational/academic activities, not recreation activities like sports, games, exercises, music performance, movies, dancing, painting, fishing etc. School clubs for academic subjects do not fall under recreation. Grade Alignment: This problem requires formal set notation and set theory concepts which are typically introduced at higher secondary levels (Secondary 4/5 or pre-university), not at Secondary O-level 3/4 where students are usually 15-16 years old and focus on more basic mathematical concepts.
A50: Minh | B50: Question 24 | C50: 0 | D50: 8.6307664 | E50: 1 | F50: 1 | G50: 1 | H50: 1 | I50: 1 | J50: 1 | K50: 1 | L50: 1 | M50: 1 | N50: 1 | O50: 1
A51: Minh | B51: Question 25 | C51: 0 | D51: 6.672488 | E51: 1 | F51: 1 | G51: 1 | H51: 0 | I51: 1 | J51: 0 | K51: 1 | L51: 1 | M51: 1 | N51: 1 | O51: 1 | P51: Synergy: The two parts (a) and (b) are independent questions that can be solved separately using the same dataset. There is no connection where the result of part (a) is needed to solve part (b), so they are not used in tandem. Grade_alignment: This problem involves basic statistical concepts of finding median and mode from a simple dataset, which are typically introduced at Primary 5-6 level in Singapore math curriculum. For Secondary O-level 2 students, this problem is too elementary and does not match the expected complexity level which should involve more advanced statistical concepts like quartiles, standard deviation, or probability distributions.
A52: Sarah | B52: Question 1 | C52: 0 | D52: 7.0890644 | E52: 1 | F52: 1 | G52: 1 | H52: 1 | I52: 1 | J52: 1 | K52: 1 | L52: 0 | M52: 1 | N52: 1 | O52: 1 | P52: Clarity: The phrase 'the total possible points were multiplied by 2' is ambiguous - it could mean the second game has double the points of the first game, or that Sarah's potential score is doubled. This creates confusion about whether the second game offers 120 total points or some other amount.
A53: Sarah | B53: Question 2 | C53: 0 | D53: 5.4811788 | E53: 1 | F53: 1 | G53: 1 | H53: 1 | I53: 1 | J53: 0 | K53: 1 | L53: 1 | M53: 1 | N53: 1 | O53: 1 | P53: grade_alignment: The problem is designed for Secondary O-level 2 but uses primary-level arithmetic concepts. Linear inequalities with one variable are typically introduced in Secondary 1 or lower secondary levels. The problem involves simple calculations (50 - 10 = 40, 40 / 12 = 3.33) that are too elementary for O-level 2 students who should be tackling more complex algebraic concepts.
A54: Sarah | B54: Question 3 | C54: 0 | D54: 5.3052108 | E54: 1 | F54: 1 | G54: 1 | H54: 1 | I54: 1 | J54: 0 | K54: 1 | L54: 1 | M54: 1 | N54: 1 | O54: 1 | P54: Grade Alignment: This problem is too simple for Secondary O-level 3/4 students. It involves basic probability multiplication (5/12 * 3/6 = 5/24) which is typically covered in primary grades 5-6 or lower secondary levels. O-level 3/4 students would be expected to handle more complex probability problems involving conditional probability, permutations, combinations, or more sophisticated statistical concepts.
A55: Sarah | B55: Question 4 | C55: 0 | D55: 12.94798 | E55: 1 | F55: 1 | G55: 1 | H55: 1 | I55: 1 | J55: 1 | K55: 0 | L55: 0 | M55: 1 | N55: 1 | O55: 1 | P55: Real-world feasibility: The scenario is illogical - if Sarah planned and divided the painting time equally among 3 people, the concept of her leaving early from a predetermined time allocation doesn't make practical sense. Clarity: The problem setup is confusing about how time division works when someone leaves early from their own planned activity.
A56: Sarah | B56: Question 5 | C56: 0 | D56: 8.6325767 | E56: 1 | F56: 1 | G56: 1 | H56: 1 | I56: 1 | J56: 0 | K56: 1 | L56: 1 | M56: 1 | N56: 1 | O56: 1 | P56: Grade Alignment: This problem requires advanced percentage concepts including reverse percentages and multi-step percentage calculations that are typically covered at higher secondary levels, not Secondary O-level 1. The complexity of working backwards from a percentage increase to find the original maximum mark exceeds the expected difficulty for first-year O-level students.
A57: Sarah | B57: Question 6 | C57: 0 | D57: 5.335753 | E57: 1 | F57: 1 | G57: 1 | H57: 1 | I57: 1 | J57: 1 | K57: 0 | L57: 1 | M57: 1 | N57: 1 | O57: 1 | P57: Real-world feasibility: In table tennis, players do not hit the ball to travel specific distances like 2.35 metres as a measure of performance. Table tennis is played on a standard table (2.74m x 1.525m) where the ball travels back and forth between players. The concept of measuring how far a player hits the ball as a distance measurement does not reflect realistic table tennis practice or tournament scenarios.
A58: Sarah | B58: Question 7 | C58: 0 | D58: 5.0305383 | E58: 1 | F58: 1 | G58: 1 | H58: 1 | I58: 1 | J58: 0 | K58: 0 | L58: 1 | M58: 1 | N58: 1 | O58: 1 | P58: Grade Alignment: This problem is too basic for Secondary O-level 1 students. Decimal ratios and basic decimal addition are typically covered in primary grades (P5-P6), not secondary level. Real-World Feasibility: Having 12.5 boys and 3.7 girls joining is unrealistic as you cannot have fractional people in real life scenarios.
A59: Sarah | B59: Question 8 | C59: 0 | D59: 7.6087625 | E59: 1 | F59: 1 | G59: 1 | H59: 1 | I59: 1 | J59: 1 | K59: 1 | L59: 1 | M59: 1 | N59: 1 | O59: 1
A60: Sarah | B60: Question 9 | C60: 0 | D60: 5.3601978 | E60: 1 | F60: 1 | G60: 1 | H60: 1 | I60: 1 | J60: 0 | K60: 1 | L60: 1 | M60: 1 | N60: 1 | O60: 1 | P60: Grade Alignment: This problem is too simple for Secondary O-level 1 students. The percentage calculation (150-120)/120 * 100 = 25% and converting 25% to 1/4 are concepts typically mastered in upper primary grades (Primary 5-6). Secondary O-level 1 students would be expected to handle more complex percentage problems involving compound calculations, multiple steps, or algebraic applications.
A61: Sarah | B61: Question 10 | C61: 0 | D61: 8.9240894 | E61: 1 | F61: 0 | G61: 1 | H61: 'NA | I61: 1 | J61: 'NA | K61: 1 | L61: 0 | M61: 1 | N61: 1 | O61: 1 | P61: Primary KC alignment (0): The problem context naturally leads to addition (7/4 + 5/3 = 41/12) for combined practice time, not multiplication of the two fractions as intended. The phrase 'both days combined' clearly indicates addition. Synergy (0): Since the primary KC (multiplication) is not naturally required by the problem setup, there is no proper synergy between multiplication and decimal conversion - they become disconnected operations rather than working in tandem. Clarity (0): The problem is ambiguous because the natural mathematical interpretation (addition for combined time) conflicts with the intended solution method (multiplication), creating confusion about what operation is actually required.
A62: Sarah | B62: Question 11 | C62: 0 | D62: 2.8578672 | E62: 1 | F62: 1 | G62: 1 | H62: 1 | I62: 1 | J62: 1 | K62: 1 | L62: 1 | M62: 1 | N62: 1 | O62: 1
A63: Sarah | B63: Question 12 | C63: 0 | D63: 5.8860455 | E63: 1 | F63: 1 | G63: 1 | H63: 1 | I63: 1 | J63: 0 | K63: 0 | L63: 1 | M63: 1 | N63: 1 | O63: 1 | P63: Grade Alignment: The problem is intended for Secondary O-level 1 but involves quadratic expressions (2x^2 + 3x + 5) which are typically introduced in later secondary grades, not at the beginning level. Real-World Plausibility: Mini-golf course booking costs following a quadratic function 2x^2 + 3x + 5 is unrealistic. Real-world hourly rates are typically linear (fixed rate per hour) or have step functions, not quadratic relationships where costs increase exponentially.
A64: Sarah | B64: Question 13 | C64: 0 | D64: 9.4344051 | E64: 1 | F64: 1 | G64: 1 | H64: 1 | I64: 1 | J64: 1 | K64: 1 | L64: 1 | M64: 1 | N64: 1 | O64: 1
A65: Sarah | B65: Question 14 | C65: 0 | D65: 2.8843534 | E65: 1 | F65: 1 | G65: 1 | H65: 1 | I65: 1 | J65: 1 | K65: 1 | L65: 1 | M65: 1 | N65: 1 | O65: 1
A66: Sarah | B66: Question 15 | C66: 0 | D66: 5.3161924 | E66: 1 | F66: 1 | G66: 1 | H66: 1 | I66: 1 | J66: 0 | K66: 1 | L66: 1 | M66: 1 | N66: 1 | O66: 1 | P66: Grade Alignment: This problem involves basic ratio concepts with simple fractions that would typically be covered in Primary 5-6 level, not Secondary O-level 1. The ratio 2/3:1 and multiplication of fractions 2/3 * 3/4 are fundamental concepts below Secondary O-level standard which should involve more complex algebraic manipulation or advanced ratio applications.
A67: Sarah | B67: Question 16 | C67: 0 | D67: 9.4465976 | E67: 1 | F67: 1 | G67: 1 | H67: 1 | I67: 1 | J67: 1 | K67: 1 | L67: 1 | M67: 1 | N67: 1 | O67: 1
A68: Sarah | B68: Question 17 | C68: 0 | D68: 8.3421402 | E68: 0 | F68: 'NA | G68: 'NA | H68: 'NA | I68: 'NA | J68: 'NA | K68: 'NA | L68: 'NA | M68: 'NA | N68: 'NA | O68: 'NA | P68: Answerability: The problem leads to a negative answer (-0.025 litres) which is mathematically impossible for a remaining quantity of liquid. After filling 142 bottles using 14.200 litres, only 0.050 litres remains, but Sarah drinks 0.075 litres which is more than available. Real-world feasibility: It is physically impossible to drink more liquid than what remains available, making this scenario unrealistic.
A69: Sarah | B69: Question 18 | C69: 0 | D69: 9.7663031 | E69: 1 | F69: 1 | G69: 1 | H69: 1 | I69: 1 | J69: 1 | K69: 1 | L69: 1 | M69: 1 | N69: 1 | O69: 1
A70: Sarah | B70: Question 19 | C70: 0 | D70: 2.6430235 | E70: 1 | F70: 1 | G70: 1 | H70: 1 | I70: 1 | J70: 1 | K70: 1 | L70: 1 | M70: 1 | N70: 1 | O70: 1
A71: Sarah | B71: Question 20 | C71: 0 | D71: 11.814236 | E71: 1 | F71: 0 | G71: 1 | H71: 'NA | I71: 1 | J71: 'NA | K71: 1 | L71: 1 | M71: 1 | N71: 1 | O71: 1 | P71: Primary KC alignment fails because the problem does not require addition of probabilities - it uses set theory with inclusion-exclusion principle (27/30 = 18 + 15 - 6 divided by 30). Synergy fails because the primary KC is not actually used in solving the problem, so no tandem usage occurs between intended knowledge components.
A72: Sarah | B72: Question 21 | C72: 0 | D72: 11.303416 | E72: 1 | F72: 1 | G72: 1 | H72: 1 | I72: 1 | J72: 0 | K72: 1 | L72: 1 | M72: 1 | N72: 1 | O72: 1 | P72: Grade alignment: The problem involves basic percentage increase (120 * 1.15 = 138) and simple addition (138 + 25 = 163), which are concepts typically mastered in Primary 5-6. For Secondary O-level 1 students, this problem is too elementary and does not match the expected difficulty level for that grade.
A73: Sarah | B73: Question 22 | C73: 0 | D73: 2.8833144 | E73: 1 | F73: 1 | G73: 1 | H73: 1 | I73: 1 | J73: 1 | K73: 1 | L73: 1 | M73: 1 | N73: 1 | O73: 1
A74: Sarah | B74: Question 23 | C74: 0 | D74: 5.330996 | E74: 1 | F74: 1 | G74: 1 | H74: 0 | I74: 1 | J74: 0 | K74: 1 | L74: 1 | M74: 1 | N74: 1 | O74: 1 | P74: Synergy: The two parts (a) and (b) are independent calculations that do not require using results from one part to solve the other part. Finding median and range can be done separately without connection. Grade Alignment: Finding median and range are basic statistical concepts typically introduced in Primary 5-6 or Secondary 1, which is below Secondary O-level 2 difficulty level.
A75: Sarah | B75: Question 24 | C75: 0 | D75: 6.1491265 | E75: 1 | F75: 0 | G75: 1 | H75: 'NA | I75: 1 | J75: 'NA | K75: 1 | L75: 1 | M75: 1 | N75: 1 | O75: 1 | P75: Primary KC alignment fails because the problem requires multiplying decimals by single/double digit numbers (0.125 + 0.25 + 0.4) * 10 * 2 = 15.5, but the intended primary KC is specifically about multiplying decimals by 10, 100, 1000 and their multiples. While 10 appears in the calculation, the main multiplication operations are (0.125 + 0.25 + 0.4) * 10 and then * 2, where multiplying by 2 is not a multiple of 10, 100, or 1000.
A76: Sarah | B76: Question 25 | C76: 0 | D76: 11.50606 | E76: 1 | F76: 1 | G76: 1 | H76: 1 | I76: 0 | J76: 1 | K76: 1 | L76: 1 | M76: 1 | N76: 1 | O76: 1 | P76: Topic Alignment: The problem focuses on sharing chocolate at a picnic, which relates to food sharing and social activities rather than recreation activities like sports, games, exercises, music, movies, dancing, painting, or fishing.
A77: Sarah | B77: Question 26 | C77: 0 | D77: 8.1180036 | E77: 0 | F77: 'NA | G77: 'NA | H77: 'NA | I77: 'NA | J77: 'NA | K77: 'NA | L77: 'NA | M77: 'NA | N77: 'NA | O77: 'NA | P77: Answerability: Part (a) gives 12.450 / 10 = 1.245 metres per lap, but part (b) provides 10 individual lap distances that sum to 12.457 metres, creating conflicting information. Primary KC Alignment: Part (a) requires 12.450 / 10 which is basic decimal division, not division by multiples of 10/100/1000 as specified in the intended knowledge component. Synergy: The two knowledge components are used in separate parts (a) and (b)/(c) rather than in tandem - part (a) result is not used for parts (b) and (c). Real World Feasibility: Swimming lap distances varying by millimeters (1.240 to 1.250) is unrealistic for practical measurement in competitions. Conciseness and Relevance: The calculated answer from part (a) is not used in subsequent parts, making it irrelevant information.

Sheet recreation_v2_7
A1: Evaluator | B1: Question | C1: status | D1: response_time | E1: answerability | F1: primary_kc_alignment | G1: secondary_kc_alignment | H1: synergy | I1: topic_alignment | J1: grade_alignment | K1: real_world_feasibility | L1: clarity | M1: conciseness_and_relevance | N1: language_quality | O1: content_appropriateness | P1: explanation
A2: TD | B2: Question 1 | C2: 0 | D2: 8.8292282 | E2: 1 | F2: 1 | G2: 1 | H2: 1 | I2: 1 | J2: 1 | K2: 1 | L2: 1 | M2: 1 | N2: 1 | O2: 1
A3: TD | B3: Question 2 | C3: 0 | D3: 10.586419 | E3: 1 | F3: 1 | G3: 1 | H3: 1 | I3: 1 | J3: 1 | K3: 1 | L3: 1 | M3: 1 | N3: 1 | O3: 1
A4: TD | B4: Question 3 | C4: 0 | D4: 4.7464764 | E4: 1 | F4: 0 | G4: 1 | H4: 'NA | I4: 1 | J4: 'NA | K4: 1 | L4: 1 | M4: 1 | N4: 1 | O4: 1 | P4: Primary KC alignment fails because the problem requires dividing 12.000 by 10, which is basic division by 10 (resulting in 1.200), not the intended more complex division of decimals by multiples of 10 that would demonstrate mastery of dividing decimals up to 3 decimal places by 10, 100, 1000 and their multiples.
A5: TD | B5: Question 4 | C5: 0 | D5: 2.9829743 | E5: 1 | F5: 1 | G5: 1 | H5: 1 | I5: 1 | J5: 1 | K5: 1 | L5: 1 | M5: 1 | N5: 1 | O5: 1
A6: TD | B6: Question 5 | C6: 0 | D6: 10.565943 | E6: 1 | F6: 1 | G6: 1 | H6: 1 | I6: 1 | J6: 1 | K6: 1 | L6: 1 | M6: 1 | N6: 1 | O6: 1
A7: TD | B7: Question 6 | C7: 0 | D7: 2.8882141 | E7: 1 | F7: 1 | G7: 1 | H7: 1 | I7: 1 | J7: 1 | K7: 1 | L7: 1 | M7: 1 | N7: 1 | O7: 1
A8: TD | B8: Question 7 | C8: 0 | D8: 3.1747651 | E8: 1 | F8: 1 | G8: 1 | H8: 1 | I8: 1 | J8: 1 | K8: 1 | L8: 1 | M8: 1 | N8: 1 | O8: 1
A9: TD | B9: Question 8 | C9: 0 | D9: 2.9812384 | E9: 1 | F9: 1 | G9: 1 | H9: 1 | I9: 1 | J9: 1 | K9: 1 | L9: 1 | M9: 1 | N9: 1 | O9: 1
A10: TD | B10: Question 9 | C10: 0 | D10: 5.3422201 | E10: 1 | F10: 1 | G10: 1 | H10: 1 | I10: 1 | J10: 0 | K10: 0 | L10: 1 | M10: 1 | N10: 1 | O10: 1 | P10: Grade alignment: Matrix operations are typically covered in Secondary 5/A-level or tertiary mathematics, not O-level 3/4. Real-world feasibility: The impact factor matrix M with values 1, 0.5, 0.8 and the resulting multiplication C x M producing weighted scores lacks clear real-world meaning in the sports club context. The scenario does not mirror typical sports club operations where such mathematical weightings would be applied.
A11: TD | B11: Question 10 | C11: 0 | D11: 9.1759417 | E11: 1 | F11: 1 | G11: 1 | H11: 1 | I11: 1 | J11: 1 | K11: 1 | L11: 1 | M11: 1 | N11: 1 | O11: 1
A12: TD | B12: Question 11 | C12: 0 | D12: 10.049004 | E12: 1 | F12: 1 | G12: 1 | H12: 1 | I12: 1 | J12: 1 | K12: 0 | L12: 1 | M12: 1 | N12: 1 | O12: 1 | P12: Real-world feasibility: Attending 5/3 sessions (approximately 1.67 sessions) is unrealistic as one cannot attend a partial session in practice.
A13: TD | B13: Question 12 | C13: 0 | D13: 5.1484213 | E13: 1 | F13: 1 | G13: 1 | H13: 1 | I13: 1 | J13: 0 | K13: 1 | L13: 1 | M13: 1 | N13: 1 | O13: 1 | P13: Grade Alignment: This problem requires algebraic expressions with variables (x, n) and algebraic manipulation which are typically introduced in Secondary 1-2, not Primary 6. Primary 6 students in Singapore math syllabus typically work with basic arithmetic and simple algebraic concepts but not complex variable expressions and simplification of linear expressions with multiple variables.
A14: TD | B14: Question 13 | C14: 0 | D14: 11.401763 | E14: 1 | F14: 1 | G14: 1 | H14: 1 | I14: 1 | J14: 0 | K14: 1 | L14: 1 | M14: 1 | N14: 1 | O14: 1 | P14: Grade alignment: The problem results in 1.325 m per person, which has 3 decimal places. This exceeds Primary 4 level expectations and the primary KC specification of up to 2 decimal places.
A15: TD | B15: Question 14 | C15: 0 | D15: 11.103193 | E15: 1 | F15: 1 | G15: 1 | H15: 1 | I15: 1 | J15: 0 | K15: 1 | L15: 1 | M15: 1 | N15: 1 | O15: 1 | P15: Grade Alignment: The problem is too simple for Secondary O-level 1 students. It involves basic percentage calculation (15% of 60 = 9) and simple subtraction (69 - 10 = 59), which are concepts typically mastered in primary school, not challenging enough for 15-16 year old students.
A16: TD | B16: Question 15 | C16: 0 | D16: 10.503006 | E16: 1 | F16: 1 | G16: 1 | H16: 1 | I16: 1 | J16: 1 | K16: 1 | L16: 1 | M16: 1 | N16: 1 | O16: 1
A17: TD | B17: Question 16 | C17: 0 | D17: 12.419333 | E17: 1 | F17: 0 | G17: 1 | H17: 'NA | I17: 1 | J17: 'NA | K17: 1 | L17: 1 | M17: 1 | N17: 1 | O17: 1 | P17: Primary KC alignment fails because the problem only requires basic multiplication of 0.175 * 100 = 17.5, which is straightforward decimal multiplication by 100. The intended primary KC specifically targets multiplying by multiples of 10, 100, 1000 (like 20, 300, 4000), which would be more complex and is not demonstrated in this problem.
A18: TD | B18: Question 17 | C18: 0 | D18: 8.2587128 | E18: 0 | F18: 'NA | G18: 'NA | H18: 'NA | I18: 'NA | J18: 'NA | K18: 'NA | L18: 'NA | M18: 'NA | N18: 'NA | O18: 'NA | P18: The problem is missing critical information - the number of sessions Sarah attended last month. Without this information, it is impossible to determine how many sessions she attended this month (5/3 times an unknown number) and therefore impossible to calculate the total paint used this month.
A19: TD | B19: Question 18 | C19: 0 | D19: 10.13975 | E19: 1 | F19: 1 | G19: 1 | H19: 1 | I19: 1 | J19: 1 | K19: 1 | L19: 1 | M19: 1 | N19: 1 | O19: 1
A20: TD | B20: Question 19 | C20: 0 | D20: 5.5768538 | E20: 0 | F20: 'NA | G20: 'NA | H20: 'NA | I20: 'NA | J20: 'NA | K20: 'NA | L20: 'NA | M20: 'NA | N20: 'NA | O20: 'NA | P20: Answerability: The problem contains ambiguous information about how the additional 1/8 watermelon is distributed. It states Sarah adds 1/8 to what each person already has, but it's unclear if this means 1/8 total is divided among all 5 people or if each of the 5 people gets 1/8 additional watermelon. Clarity: The distribution method for the additional 1/8 watermelon is not clearly specified, making the problem ambiguous to solve.
A21: TD | B21: Question 20 | C21: 0 | D21: 10.66585 | E21: 1 | F21: 1 | G21: 1 | H21: 1 | I21: 1 | J21: 1 | K21: 0 | L21: 1 | M21: 1 | N21: 1 | O21: 1 | P21: The problem assumes that spending 2/3 as much time painting directly results in completing 2/3 as much work. In reality, painting completion depends on factors beyond just time spent, such as painting complexity, technique, and efficiency. This creates an unrealistic direct proportional relationship between time and work output.
A22: TD | B22: Question 21 | C22: 0 | D22: 10.276766 | E22: 1 | F22: 1 | G22: 1 | H22: 0 | I22: 1 | J22: 0 | K22: 1 | L22: 1 | M22: 1 | N22: 1 | O22: 1 | P22: Synergy: The two knowledge components work independently rather than in tandem - converting 15% to decimal (0.15) is separate from finding original price from 85% = $102. Grade alignment: Reverse percentage problems are typically too advanced for Secondary O-level 1 students (ages 13-14) and usually taught at higher secondary levels.
A23: TD | B23: Question 22 | C23: 0 | D23: 11.924159 | E23: 1 | F23: 0 | G23: 1 | H23: 'NA | I23: 1 | J23: 'NA | K23: 1 | L23: 1 | M23: 1 | N23: 1 | O23: 1 | P23: Primary KC alignment: Problem uses 3 decimal places (8.125) but intended component specifies up to 2 decimal places only. Synergy: Part (b) does not use results from part (a) - the questions are independent rather than building upon each other. Grade alignment: 3 decimal place operations may exceed typical Primary 4 curriculum expectations.
A24: TD | B24: Question 23 | C24: 0 | D24: 11.008698 | E24: 0 | F24: 'NA | G24: 'NA | H24: 'NA | I24: 'NA | J24: 'NA | K24: 'NA | L24: 'NA | M24: 'NA | N24: 'NA | O24: 'NA | P24: The problem cannot be solved because it is missing critical information - the number of practice days last month is not provided. To find total hours this month, we need: (7/4 hours per day) * (9/5 * days last month) * (days last month), but the value for days last month is not given.
A25: TD | B25: Question 24 | C25: 0 | D25: 11.509672 | E25: 1 | F25: 1 | G25: 1 | H25: 1 | I25: 1 | J25: 0 | K25: 1 | L25: 1 | M25: 1 | N25: 1 | O25: 1 | P25: Grade Alignment: Direct proportion is typically taught at Primary 6 level in Singapore math curriculum, making this problem too easy for Secondary O-level 2 students who should be handling more advanced mathematical concepts.
A26: TD | B26: Question 25 | C26: 0 | D26: 9.2698736 | E26: 1 | F26: 1 | G26: 1 | H26: 1 | I26: 1 | J26: 1 | K26: 1 | L26: 1 | M26: 1 | N26: 1 | O26: 1
A27: Minh | B27: Question 1 | C27: 0 | D27: 12.207029 | E27: 1 | F27: 0 | G27: 1 | H27: 'NA | I27: 1 | J27: 'NA | K27: 1 | L27: 1 | M27: 1 | N27: 1 | O27: 1 | P27: Primary KC alignment: The distance 1.797 km has 3 decimal places, exceeding the intended 2 decimal places limit. Grade alignment: Using 3 decimal places (1.797) may be too advanced for Primary 4 students when the intended primary KC specifies up to 2 decimal places only.
A28: Minh | B28: Question 2 | C28: 0 | D28: 10.428056 | E28: 1 | F28: 1 | G28: 1 | H28: 1 | I28: 1 | J28: 1 | K28: 1 | L28: 1 | M28: 1 | N28: 1 | O28: 1
A29: Minh | B29: Question 3 | C29: 0 | D29: 11.258657 | E29: 1 | F29: 1 | G29: 1 | H29: 1 | I29: 1 | J29: 1 | K29: 0 | L29: 1 | M29: 1 | N29: 1 | O29: 1 | P29: Real-World Plausibility: Dividing 0.125 hours among 1000 students gives each student 0.0001125 hours or approximately 0.4 seconds, which is unrealistically short for piano practice.
A30: Minh | B30: Question 4 | C30: 0 | D30: 12.333076 | E30: 1 | F30: 1 | G30: 1 | H30: 1 | I30: 1 | J30: 0 | K30: 1 | L30: 1 | M30: 1 | N30: 1 | O30: 1 | P30: Grade alignment fails because matrix operations are typically taught at A-level or university level, not at Secondary O-level 3/4 where students are usually 15-16 years old and study basic algebra, geometry, and trigonometry.
A31: Minh | B31: Question 5 | C31: 0 | D31: 11.726676 | E31: 1 | F31: 1 | G31: 1 | H31: 1 | I31: 1 | J31: 1 | K31: 1 | L31: 1 | M31: 1 | N31: 1 | O31: 1
A32: Minh | B32: Question 6 | C32: 0 | D32: 11.085871 | E32: 1 | F32: 1 | G32: 1 | H32: 1 | I32: 1 | J32: 1 | K32: 1 | L32: 1 | M32: 1 | N32: 1 | O32: 1
A33: Minh | B33: Question 7 | C33: 0 | D33: 11.938291 | E33: 1 | F33: 1 | G33: 1 | H33: 1 | I33: 1 | J33: 0 | K33: 1 | L33: 1 | M33: 1 | N33: 1 | O33: 1 | P33: Grade Alignment: The problem requires formal algebraic methods with variables and equation solving that are typically taught in Secondary 1 of Singapore curriculum, not Primary 6. Primary 6 students typically solve such problems using arithmetic methods rather than algebraic equations with variables.
A34: Minh | B34: Question 8 | C34: 0 | D34: 11.074604 | E34: 1 | F34: 1 | G34: 1 | H34: 1 | I34: 1 | J34: 1 | K34: 1 | L34: 1 | M34: 1 | N34: 1 | O34: 1
A35: Minh | B35: Question 9 | C35: 0 | D35: 10.286548 | E35: 1 | F35: 1 | G35: 1 | H35: 1 | I35: 1 | J35: 1 | K35: 1 | L35: 1 | M35: 1 | N35: 1 | O35: 1
A36: Minh | B36: Question 10 | C36: 0 | D36: 4.8174362 | E36: 1 | F36: 1 | G36: 1 | H36: 1 | I36: 1 | J36: 0 | K36: 1 | L36: 1 | M36: 1 | N36: 1 | O36: 1 | P36: Grade Alignment: The problem is designed for Secondary O-level 3/4 but quartiles and interquartile range are typically introduced at Primary 6 or Secondary 1/2 level in Singapore math syllabus. This makes the problem too elementary for the intended grade level of Secondary O-level 3/4 students.
A37: Minh | B37: Question 11 | C37: 0 | D37: 2.9754205 | E37: 1 | F37: 1 | G37: 1 | H37: 1 | I37: 1 | J37: 1 | K37: 1 | L37: 1 | M37: 1 | N37: 1 | O37: 1
A38: Minh | B38: Question 12 | C38: 0 | D38: 14.602862 | E38: 0 | F38: 'NA | G38: 'NA | H38: 'NA | I38: 'NA | J38: 'NA | K38: 'NA | L38: 'NA | M38: 'NA | N38: 'NA | O38: 'NA | P38: Answerability: Problem has conflicting constraints - ratio 3/4:2 with 24 dancing students gives 9 painting students, but 5/6 * 24 = 20 painting students. Secondary KC: No fraction division is required, only fraction multiplication and ratios. Synergy: Conflicting constraints prevent knowledge components from working together. Grade alignment: Complex fraction ratios too advanced for Secondary O-level 1. Clarity: Conflicting mathematical information makes problem confusing.
A39: Minh | B39: Question 13 | C39: 0 | D39: 11.805742 | E39: 1 | F39: 1 | G39: 1 | H39: 0 | I39: 1 | J39: 0 | K39: 0 | L39: 1 | M39: 1 | N39: 1 | O39: 1 | P39: Synergy: The two parts are connected by context but do not require tandem use of both knowledge components - part (a) uses only inverse proportion, part (b) uses only division. Grade Alignment: The mathematical concepts (120/4*6 and 36/6) are too elementary for Secondary O-level 2 students who should handle advanced algebra, trigonometry, or calculus. Real-World Feasibility: Board games typically have fixed completion times regardless of player count - more players do not reduce game duration.
A40: Minh | B40: Question 14 | C40: 0 | D40: 7.7096441 | E40: 0 | F40: 'NA | G40: 'NA | H40: 'NA | I40: 'NA | J40: 'NA | K40: 'NA | L40: 'NA | M40: 'NA | N40: 'NA | O40: 'NA | P40: Answerability: The problem asks to divide 183 children equally into 4 groups, but 183 / 4 = 45 remainder 3, making equal division impossible. Real-world feasibility: An organizer would not expect to divide 183 children into exactly 4 equal groups as this is mathematically impossible, making the scenario unrealistic.
A41: Minh | B41: Question 15 | C41: 0 | D41: 7.0107756 | E41: 0 | F41: 'NA | G41: 'NA | H41: 'NA | I41: 'NA | J41: 'NA | K41: 'NA | L41: 'NA | M41: 'NA | N41: 'NA | O41: 'NA | P41: Answerability: The problem has conflicting information - it states the total paid was $28, then asks to find total spending for 3 hours and 5 rackets, which would be 4*3 + 2*5 = $22, not $28. Primary KC Alignment: The problem does not require solving linear equations in two variables as the primary skill. The second part can be solved with simple arithmetic (4*3 + 2*5 = 22) without using the system of equations. Synergy: The two parts are disconnected - the equation-writing part and the calculation part do not work together, and the conflicting totals prevent proper synergy between primary and secondary knowledge components.
A42: Minh | B42: Question 16 | C42: 0 | D42: 2.9566824 | E42: 1 | F42: 1 | G42: 1 | H42: 1 | I42: 1 | J42: 1 | K42: 1 | L42: 1 | M42: 1 | N42: 1 | O42: 1
A43: Minh | B43: Question 17 | C43: 0 | D43: 6.6009994 | E43: 1 | F43: 1 | G43: 0 | H43: 'NA | I43: 1 | J43: 1 | K43: 1 | L43: 1 | M43: 1 | N43: 1 | O43: 1 | P43: Secondary KC alignment: The problem only requires division operations (168/4=42, then 42/6=7). No multiplication is needed to solve this problem. Synergy: Since multiplication is not required, there is no synergy between the primary division KC and secondary multiplication KC.
A44: Minh | B44: Question 18 | C44: 0 | D44: 9.6290846 | E44: 1 | F44: 1 | G44: 1 | H44: 1 | I44: 1 | J44: 1 | K44: 1 | L44: 1 | M44: 1 | N44: 1 | O44: 1
A45: Minh | B45: Question 19 | C45: 0 | D45: 3.0940101 | E45: 1 | F45: 1 | G45: 1 | H45: 1 | I45: 1 | J45: 1 | K45: 1 | L45: 1 | M45: 1 | N45: 1 | O45: 1
A46: Minh | B46: Question 20 | C46: 0 | D46: 7.3245416 | E46: 1 | F46: 1 | G46: 0 | H46: 'NA | I46: 1 | J46: 1 | K46: 1 | L46: 1 | M46: 1 | N46: 1 | O46: 1 | P46: Secondary KC Alignment: The problem mentions subtraction in the narrative but the actual solution does not require subtracting decimals - it only needs division 36.84/6=6.14 and multiplication 6.14*2=12.28. Synergy: Since decimal subtraction is not actually needed to solve the problem, there is no synergy between the primary KC (decimal division) and secondary KC (decimal subtraction).
A47: Minh | B47: Question 21 | C47: 0 | D47: 2.9596739 | E47: 1 | F47: 1 | G47: 1 | H47: 1 | I47: 1 | J47: 1 | K47: 1 | L47: 1 | M47: 1 | N47: 1 | O47: 1
A48: Minh | B48: Question 22 | C48: 0 | D48: 10.262404 | E48: 1 | F48: 1 | G48: 1 | H48: 1 | I48: 1 | J48: 1 | K48: 1 | L48: 1 | M48: 1 | N48: 1 | O48: 1
A49: Minh | B49: Question 23 | C49: 0 | D49: 6.1030486 | E49: 1 | F49: 1 | G49: 1 | H49: 1 | I49: 0 | J49: 0 | K49: 1 | L49: 1 | M49: 1 | N49: 1 | O49: 1 | P49: Topic Alignment: The problem context is about school clubs (Science Club, Music Club) which relates to academic activities rather than recreation activities like sports, games, exercises, music performance, movies, dancing, painting, or fishing. School clubs are educational/academic in nature, not recreational. Grade Alignment: This problem requires formal set notation and set theory operations which are typically introduced at higher secondary levels or pre-university mathematics, not at Secondary O-level 3/4 where basic arithmetic, algebra, and geometry are the focus.
A50: Minh | B50: Question 24 | C50: 0 | D50: 9.7570517 | E50: 1 | F50: 1 | G50: 1 | H50: 1 | I50: 1 | J50: 1 | K50: 1 | L50: 1 | M50: 1 | N50: 1 | O50: 1
A51: Minh | B51: Question 25 | C51: 0 | D51: 6.0331163 | E51: 1 | F51: 1 | G51: 1 | H51: 0 | I51: 1 | J51: 0 | K51: 1 | L51: 1 | M51: 1 | N51: 1 | O51: 1 | P51: synergy: The two parts (a) and (b) are independent questions that can be solved separately using the same dataset. There is no connection where the result of part (a) is used to solve part (b) or vice versa. grade_alignment: This problem requires only basic understanding of median and mode concepts which are typically taught at primary or lower secondary levels. For Secondary O-level 2 students, this problem is too simple and does not match the expected complexity and sophistication of statistical concepts that should be covered at that grade level.
A52: Sarah | B52: Question 1 | C52: 0 | D52: 9.5507755 | E52: 1 | F52: 1 | G52: 1 | H52: 1 | I52: 1 | J52: 1 | K52: 1 | L52: 1 | M52: 1 | N52: 1 | O52: 1
A53: Sarah | B53: Question 2 | C53: 0 | D53: 5.0470014 | E53: 1 | F53: 1 | G53: 1 | H53: 1 | I53: 1 | J53: 0 | K53: 1 | L53: 1 | M53: 1 | N53: 1 | O53: 1 | P53: Grade Alignment (0): This problem is too advanced for Secondary O-level 2 students. Linear inequalities with algebraic representation using variables like n are typically introduced in higher secondary grades (O-level 3-4). Secondary 2 students typically work with basic algebraic expressions and simple equations, not inequality formulation and solving.
A54: Sarah | B54: Question 3 | C54: 0 | D54: 5.9397171 | E54: 1 | F54: 1 | G54: 1 | H54: 1 | I54: 1 | J54: 0 | K54: 1 | L54: 1 | M54: 1 | N54: 1 | O54: 1 | P54: Grade Alignment: This problem is too simple for Secondary O-level 3/4 students. The probability calculation involves basic multiplication of simple probabilities (5/12 * 3/6 = 5/24) which is typically covered in primary or lower secondary levels. O-level 3/4 students would be expected to handle more complex probability scenarios involving conditional probability, permutations, combinations, or more sophisticated statistical concepts.
A55: Sarah | B55: Question 4 | C55: 0 | D55: 13.263376 | E55: 1 | F55: 1 | G55: 1 | H55: 1 | I55: 1 | J55: 1 | K55: 0 | L55: 0 | M55: 1 | N55: 1 | O55: 1 | P55: Real-world feasibility: The scenario is unrealistic - friends painting together would not have one person dictate time division, and leaving early from pre-divided time creates logical inconsistency. Clarity: The problem setup is confusing about how Sarah can divide shared painting time and then leave early from that division, making the scenario unclear and ambiguous.
A56: Sarah | B56: Question 5 | C56: 0 | D56: 14.170376 | E56: 1 | F56: 1 | G56: 1 | H56: 1 | I56: 1 | J56: 1 | K56: 0 | L56: 0 | M56: 1 | N56: 1 | O56: 1 | P56: Real-world feasibility: The wording 'this increase represents exactly 20% more than her score last month' is unnatural and contrived - people don't typically speak this way about score improvements. Clarity: The phrase 'this increase represents exactly 20% more than her score last month' is ambiguous - it's unclear what specific increase is being referenced, making the problem confusing to interpret.
A57: Sarah | B57: Question 6 | C57: 0 | D57: 10.492911 | E57: 1 | F57: 1 | G57: 1 | H57: 1 | I57: 1 | J57: 1 | K57: 0 | L57: 1 | M57: 1 | N57: 1 | O57: 1 | P57: Real-world feasibility: Table tennis balls do not travel distances of 2+ meters in normal gameplay. The scenario of measuring how far players hit the ball does not reflect realistic table tennis activities.
A58: Sarah | B58: Question 7 | C58: 0 | D58: 5.0305305 | E58: 1 | F58: 1 | G58: 1 | H58: 1 | I58: 1 | J58: 0 | K58: 0 | L58: 1 | M58: 1 | N58: 1 | O58: 1 | P58: Grade alignment: This problem involves basic ratio concepts and decimal addition that are typically covered in primary grades (P5-P6), not secondary O-level 1 which requires more advanced mathematical concepts. Real-world feasibility: Having 12.5 boys and 3.7 girls joining is unrealistic as you cannot have fractional people in real-world scenarios.
A59: Sarah | B59: Question 8 | C59: 0 | D59: 9.4401207 | E59: 1 | F59: 1 | G59: 1 | H59: 1 | I59: 1 | J59: 1 | K59: 1 | L59: 1 | M59: 1 | N59: 1 | O59: 1
A60: Sarah | B60: Question 9 | C60: 0 | D60: 5.2350047 | E60: 1 | F60: 1 | G60: 1 | H60: 1 | I60: 1 | J60: 0 | K60: 1 | L60: 1 | M60: 1 | N60: 1 | O60: 1 | P60: Grade Alignment: This problem is too simple for Secondary O-level 1 students. The calculations involve basic percentage comparison (150-120)/120 x 100% = 25% and converting 25% to 1/4, which are concepts typically mastered in Primary 5-6. Secondary O-level 1 students would be expected to handle more complex percentage problems involving compound calculations, multiple steps, or algebraic manipulation.
A61: Sarah | B61: Question 10 | C61: 0 | D61: 14.10125 | E61: 0 | F61: 'NA | G61: 'NA | H61: 'NA | I61: 'NA | J61: 'NA | K61: 'NA | L61: 'NA | M61: 'NA | N61: 'NA | O61: 'NA | P61: Answerability: The phrase 'she managed to practise 5/3 of that time' is ambiguous - unclear if 'that time' refers to Monday's actual practice (7/4) or original planned time, leading to different solutions. Primary KC Alignment: The intended operation (multiplying improper fractions) is not clearly required due to ambiguous wording - could be interpreted as addition problem instead. Clarity: Ambiguous reference in 'that time' makes the problem unclear about which quantity Tuesday's practice should be calculated from.
A62: Sarah | B62: Question 11 | C62: 0 | D62: 2.9887788 | E62: 1 | F62: 1 | G62: 1 | H62: 1 | I62: 1 | J62: 1 | K62: 1 | L62: 1 | M62: 1 | N62: 1 | O62: 1
A63: Sarah | B63: Question 12 | C63: 0 | D63: 5.507539 | E63: 1 | F63: 1 | G63: 1 | H63: 1 | I63: 1 | J63: 0 | K63: 0 | L63: 1 | M63: 1 | N63: 1 | O63: 1 | P63: Grade Alignment: The problem is intended for Secondary O-level 1 but quadratic expressions (2x^2 + 3x + 5) are typically introduced in later secondary grades, making it too advanced for the intended grade level. Real-World Plausibility: Mini-golf booking costs following a quadratic function 2x^2 + 3x + 5 is unrealistic - real mini-golf venues typically charge flat hourly rates or have simpler linear pricing structures, not quadratic cost models.
A64: Sarah | B64: Question 13 | C64: 0 | D64: 9.8732243 | E64: 1 | F64: 1 | G64: 1 | H64: 1 | I64: 1 | J64: 1 | K64: 1 | L64: 1 | M64: 1 | N64: 1 | O64: 1
A65: Sarah | B65: Question 14 | C65: 0 | D65: 2.6745648 | E65: 1 | F65: 1 | G65: 1 | H65: 1 | I65: 1 | J65: 1 | K65: 1 | L65: 1 | M65: 1 | N65: 1 | O65: 1
A66: Sarah | B66: Question 15 | C66: 0 | D66: 5.3362052 | E66: 1 | F66: 1 | G66: 1 | H66: 1 | I66: 1 | J66: 0 | K66: 1 | L66: 1 | M66: 1 | N66: 1 | O66: 1 | P66: Grade alignment: This problem involves basic ratio concepts with simple fractions that are typically taught at Primary 5-6 level in Singapore math syllabus. Secondary O-level 1 students would find this problem too elementary as they should be working with more complex ratio problems involving algebraic expressions, simultaneous equations, or advanced proportional reasoning.
A67: Sarah | B67: Question 16 | C67: 0 | D67: 8.7432361 | E67: 1 | F67: 1 | G67: 1 | H67: 1 | I67: 1 | J67: 1 | K67: 1 | L67: 1 | M67: 1 | N67: 1 | O67: 1
A68: Sarah | B68: Question 17 | C68: 0 | D68: 12.89254 | E68: 0 | F68: 'NA | G68: 'NA | H68: 'NA | I68: 'NA | J68: 'NA | K68: 'NA | L68: 'NA | M68: 'NA | N68: 'NA | O68: 'NA | P68: Answerability: The problem contains conflicting information. After filling bottles, only 0.050 litres remain (14.250 - 14.200 = 0.050), but Sarah is said to drink 0.075 litres, which is more than what remains available. Real-World Plausibility: The scenario is unrealistic because a person cannot drink more liquid than what is actually available.
A69: Sarah | B69: Question 18 | C69: 0 | D69: 9.3951073 | E69: 1 | F69: 1 | G69: 1 | H69: 1 | I69: 1 | J69: 1 | K69: 1 | L69: 1 | M69: 1 | N69: 1 | O69: 1
A70: Sarah | B70: Question 19 | C70: 0 | D70: 2.8570006 | E70: 1 | F70: 1 | G70: 1 | H70: 1 | I70: 1 | J70: 1 | K70: 1 | L70: 1 | M70: 1 | N70: 1 | O70: 1
A71: Sarah | B71: Question 20 | C71: 0 | D71: 14.711528 | E71: 1 | F71: 0 | G71: 1 | H71: 'NA | I71: 1 | J71: 'NA | K71: 1 | L71: 1 | M71: 1 | N71: 1 | O71: 1 | P71: Primary KC alignment: Problem uses inclusion-exclusion principle from set theory, not addition of probabilities. The solution involves |P union G| = |P| + |G| - |P intersect G| = 18 + 15 - 6 = 27, then P = 27/30, which does not require adding separate probability values. Synergy: Since primary KC is not needed, no synergy exists between intended knowledge components. Grade alignment: Set theory concepts like inclusion-exclusion principle typically taught at higher academic levels than O-level 3/4.
A72: Sarah | B72: Question 21 | C72: 0 | D72: 10.87336 | E72: 1 | F72: 1 | G72: 1 | H72: 1 | I72: 1 | J72: 0 | K72: 1 | L72: 1 | M72: 1 | N72: 1 | O72: 1 | P72: Grade alignment: The problem involves basic percentage calculation (15% increase) and simple whole number addition, which are typically taught at Primary 5-6 level. For Secondary O-level 1 students, this problem would be too elementary and does not match the expected difficulty level for that grade.
A73: Sarah | B73: Question 22 | C73: 0 | D73: 2.9872069 | E73: 1 | F73: 1 | G73: 1 | H73: 1 | I73: 1 | J73: 1 | K73: 1 | L73: 1 | M73: 1 | N73: 1 | O73: 1
A74: Sarah | B74: Question 23 | C74: 0 | D74: 11.593776 | E74: 1 | F74: 1 | G74: 1 | H74: 0 | I74: 1 | J74: 1 | K74: 1 | L74: 1 | M74: 1 | N74: 1 | O74: 1 | P74: Synergy: The two questions (a) and (b) are independent calculations. Finding the median does not require the range, and finding the range does not require the median. The questions are not connected such that the result of one is used as input for the other.
A75: Sarah | B75: Question 24 | C75: 0 | D75: 6.776293 | E75: 1 | F75: 0 | G75: 1 | H75: 'NA | I75: 1 | J75: 'NA | K75: 1 | L75: 1 | M75: 1 | N75: 1 | O75: 1 | P75: Primary KC Alignment: The intended primary knowledge component is multiplying decimals by 10, 100, 1000 and their multiples. However, the problem requires multiplying decimals by 10 (part b: multiply by 10 bags) and by 20 (part c: multiply by 20 total bags). While 10 is covered, 20 is not a multiple of 10, 100, or 1000 as specified in the primary KC. The problem also requires general decimal multiplication (0.125 + 0.25 + 0.4 = 0.775, then 0.775 x 10 and 0.775 x 20) rather than focusing specifically on multiples of 10, 100, 1000.
A76: Sarah | B76: Question 25 | C76: 0 | D76: 9.8904316 | E76: 1 | F76: 1 | G76: 1 | H76: 1 | I76: 1 | J76: 1 | K76: 1 | L76: 1 | M76: 1 | N76: 1 | O76: 1
A77: Sarah | B77: Question 26 | C77: 0 | D77: 8.0015759 | E77: 0 | F77: 'NA | G77: 'NA | H77: 'NA | I77: 'NA | J77: 'NA | K77: 'NA | L77: 'NA | M77: 'NA | N77: 'NA | O77: 'NA | P77: Answerability: The problem contains conflicting information. Part (a) calculates 12.450 / 10 = 1.245 metres per lap, but the individual lap distances in part (b) sum to 12.457 metres, not 12.450 metres. Primary KC Alignment: The division in part (a) is simple decimal division by 10, not division by multiples of 10/100/1000 as specified in the primary knowledge component. The problem does not require the intended primary skill. Synergy: Parts (a) and (b) are disconnected - the calculated average from part (a) is not used in parts (b) and (c). The questions do not build upon each other as required. Real-world feasibility: Swimming laps of different distances in a competition is unrealistic - competitive swimming involves equal lap distances. Conciseness and relevance: The total distance of 12.450 metres from part (a) becomes irrelevant due to the conflicting individual lap distances, making this information unnecessary.

Sheet recreation_v2_8
A1: Evaluator | B1: Question | C1: status | D1: response_time | E1: answerability | F1: primary_kc_alignment | G1: secondary_kc_alignment | H1: synergy | I1: topic_alignment | J1: grade_alignment | K1: real_world_feasibility | L1: clarity | M1: conciseness_and_relevance | N1: language_quality | O1: content_appropriateness | P1: explanation
A2: TD | B2: Question 1 | C2: 0 | D2: 4.2545023 | E2: 1 | F2: 1 | G2: 1 | H2: 1 | I2: 1 | J2: 0 | K2: 1 | L2: 1 | M2: 1 | N2: 1 | O2: 1 | P2: Grade alignment: The problem involves 4-digit subtraction (1562 - 738) and 3-digit addition (824 + 247), which are typically taught in Primary 4, not Primary 3. Primary 3 students typically work with numbers up to 1000.
A3: TD | B3: Question 2 | C3: 0 | D3: 7.5306346 | E3: 1 | F3: 0 | G3: 1 | H3: 'NA | I3: 1 | J3: 'NA | K3: 1 | L3: 1 | M3: 1 | N3: 1 | O3: 1 | P3: Primary KC alignment fails because the problem requires dividing 202.457 by 50, but the intended primary KC is specifically about dividing decimals by 10, 100, 1000 and their multiples. The number 50 is not 10, 100, 1000 or their multiples (50 = 2 × 5 × 5, not 10^n × integer where the integer uses only factors of 10).
A4: TD | B4: Question 3 | C4: 0 | D4: 7.3835707 | E4: 1 | F4: 1 | G4: 1 | H4: 1 | I4: 1 | J4: 1 | K4: 0 | L4: 0 | M4: 0 | N4: 1 | O4: 1 | P4: Real-world feasibility: The problem states Wei Lin swam on Monday and Wednesday (2 days) but then asks to divide among 10 days for that week, which is illogical since a week has 7 days and she only swam 2 days. Clarity: The phrase 'that week' is ambiguous - it's unclear if this refers to the current week or a future training week. The connection between her actual swimming days and the 10-day division plan is confusing. Conciseness and relevance: The phrase 'rounded to three decimal places' is unnecessary since 12.000/10 = 1.200 exactly with no rounding needed, making this instruction irrelevant.
A5: TD | B5: Question 4 | C5: 0 | D5: 2.9632802 | E5: 1 | F5: 1 | G5: 1 | H5: 1 | I5: 1 | J5: 1 | K5: 1 | L5: 1 | M5: 1 | N5: 1 | O5: 1
A6: TD | B6: Question 5 | C6: 0 | D6: 9.1602857 | E6: 1 | F6: 1 | G6: 1 | H6: 1 | I6: 1 | J6: 1 | K6: 1 | L6: 1 | M6: 1 | N6: 1 | O6: 1
A7: TD | B7: Question 6 | C7: 0 | D7: 8.9367771 | E7: 1 | F7: 1 | G7: 1 | H7: 1 | I7: 1 | J7: 1 | K7: 1 | L7: 1 | M7: 1 | N7: 1 | O7: 1
A8: TD | B8: Question 7 | C8: 0 | D8: 2.9537668 | E8: 1 | F8: 1 | G8: 1 | H8: 1 | I8: 1 | J8: 1 | K8: 1 | L8: 1 | M8: 1 | N8: 1 | O8: 1
A9: TD | B9: Question 8 | C9: 0 | D9: 2.8304398 | E9: 1 | F9: 1 | G9: 1 | H9: 1 | I9: 1 | J9: 1 | K9: 1 | L9: 1 | M9: 1 | N9: 1 | O9: 1
A10: TD | B10: Question 9 | C10: 0 | D10: 5.7178175 | E10: 1 | F10: 1 | G10: 1 | H10: 1 | I10: 1 | J10: 0 | K10: 0 | L10: 1 | M10: 1 | N10: 1 | O10: 1 | P10: Grade Alignment: Matrix operations including matrix multiplication are typically covered at A-level or higher secondary mathematics, not O-level 3/4. O-level mathematics usually covers basic algebra, geometry, and statistics but not advanced matrix operations. Real-World Feasibility: The concept of multiplying a matrix of hours by impact factors to get weighted scores is not a realistic scenario in actual sports club operations. Sports clubs typically track total hours or performance metrics directly rather than applying mathematical weightage matrices to training hours.
A11: TD | B11: Question 10 | C11: 0 | D11: 9.8642569 | E11: 1 | F11: 1 | G11: 1 | H11: 1 | I11: 1 | J11: 1 | K11: 1 | L11: 1 | M11: 1 | N11: 1 | O11: 1
A12: TD | B12: Question 11 | C12: 0 | D12: 9.456778 | E12: 1 | F12: 1 | G12: 1 | H12: 1 | I12: 1 | J12: 1 | K12: 0 | L12: 1 | M12: 1 | N12: 1 | O12: 1 | P12: The scenario describes attending 5/3 sessions which equals 1.67 sessions. In reality you cannot attend a partial session - you either attend a complete session or you do not attend at all.
A13: TD | B13: Question 12 | C13: 0 | D13: 4.6168635 | E13: 1 | F13: 1 | G13: 1 | H13: 1 | I13: 1 | J13: 0 | K13: 1 | L13: 1 | M13: 1 | N13: 1 | O13: 1 | P13: Grade Alignment: This problem requires knowledge of algebraic expressions with variables (x, n) and algebraic manipulation which is typically introduced in Secondary 1-2, not Primary 6. Primary 6 students in Singapore typically work with basic arithmetic and simple pre-algebraic concepts but not formal algebraic expressions with multiple variables.
A14: TD | B14: Question 13 | C14: 0 | D14: 9.6671355 | E14: 1 | F14: 1 | G14: 1 | H14: 1 | I14: 1 | J14: 1 | K14: 1 | L14: 1 | M14: 1 | N14: 1 | O14: 1
A15: TD | B15: Question 14 | C15: 0 | D15: 11.507887 | E15: 1 | F15: 1 | G15: 1 | H15: 1 | I15: 1 | J15: 0 | K15: 1 | L15: 1 | M15: 1 | N15: 1 | O15: 1 | P15: Grade alignment issue: The problem involves basic percentage calculation (15% increase) and simple whole number subtraction, which are typically Primary 5-6 level concepts in Singapore curriculum. Secondary O-level 1 students require more advanced mathematical concepts like algebra, geometry, or trigonometry.
A16: TD | B16: Question 15 | C16: 0 | D16: 9.5587497 | E16: 1 | F16: 1 | G16: 1 | H16: 1 | I16: 1 | J16: 1 | K16: 1 | L16: 1 | M16: 1 | N16: 1 | O16: 1
A17: TD | B17: Question 16 | C17: 0 | D17: 12.023425 | E17: 0 | F17: 'NA | G17: 'NA | H17: 'NA | I17: 'NA | J17: 'NA | K17: 'NA | L17: 'NA | M17: 'NA | N17: 'NA | O17: 'NA | P17: Answerability: Logical inconsistency - if Siti earns 0.175 points per note for 100 notes, she should earn exactly 17.5 points, but the problem states 17.5 includes 2.35 wrongly added points. Primary KC: The problem requires decimal subtraction (17.5 - 2.35), not multiplying decimals by 10/100/1000. Synergy: Since primary KC is not used, there is no synergy between intended knowledge components.
A18: TD | B18: Question 17 | C18: 0 | D18: 11.198777 | E18: 0 | F18: 'NA | G18: 'NA | H18: 'NA | I18: 'NA | J18: 'NA | K18: 'NA | L18: 'NA | M18: 'NA | N18: 'NA | O18: 'NA | P18: Answerability: The problem cannot be solved because the number of sessions Sarah attended last month is not provided. Without this information, we cannot calculate how many sessions she attended this month (5/3 times an unknown number) or the total paint used. Conciseness and Relevance: The problem is missing essential information needed for solving, making it incomplete rather than concise.
A19: TD | B19: Question 18 | C19: 0 | D19: 2.7196012 | E19: 1 | F19: 1 | G19: 1 | H19: 1 | I19: 1 | J19: 1 | K19: 1 | L19: 1 | M19: 1 | N19: 1 | O19: 1
A20: TD | B20: Question 19 | C20: 0 | D20: 11.15262 | E20: 1 | F20: 1 | G20: 1 | H20: 1 | I20: 1 | J20: 1 | K20: 1 | L20: 1 | M20: 1 | N20: 1 | O20: 1
A21: TD | B21: Question 20 | C21: 0 | D21: 12.739032 | E21: 1 | F21: 1 | G21: 1 | H21: 1 | I21: 1 | J21: 1 | K21: 0 | L21: 1 | M21: 1 | N21: 1 | O21: 1 | P21: Real-world feasibility issue: The problem assumes that spending 2/3 as much time painting directly translates to completing 2/3 as much work, but this relationship is not established. In reality, painting completion depends on many factors beyond just time spent.
A22: TD | B22: Question 21 | C22: 0 | D22: 2.6960146 | E22: 1 | F22: 1 | G22: 1 | H22: 1 | I22: 1 | J22: 1 | K22: 1 | L22: 1 | M22: 1 | N22: 1 | O22: 1
A23: TD | B23: Question 22 | C23: 0 | D23: 6.2342091 | E23: 1 | F23: 0 | G23: 1 | H23: 'NA | I23: 1 | J23: 'NA | K23: 1 | L23: 1 | M23: 1 | N23: 1 | O23: 1 | P23: Primary KC alignment: The problem includes decimals with 3 decimal places (8.125, 8.085) which exceeds the intended primary KC of adding decimals up to 2 decimal places only. Synergy: Part (a) only requires decimal addition while part (b) only requires decimal comparison - the results from part (a) are not used in part (b), so the two knowledge components are not used in tandem. Grade alignment: Primary 4 students typically work with decimals up to 2 decimal places, but this problem includes 3 decimal places (8.125, 8.085) which may be beyond the grade level.
A24: TD | B24: Question 23 | C24: 0 | D24: 6.6957586 | E24: 0 | F24: 'NA | G24: 'NA | H24: 'NA | I24: 'NA | J24: 'NA | K24: 'NA | L24: 'NA | M24: 'NA | N24: 'NA | O24: 'NA | P24: Answerability: The problem is missing critical information - the number of practice days last month is not provided. Without this information, it is impossible to calculate the total hours each student practices this month. The problem states there are 9/5 times as many practice days this month compared to last month, but does not specify how many days last month had.
A25: TD | B25: Question 24 | C25: 0 | D25: 12.743428 | E25: 1 | F25: 1 | G25: 1 | H25: 1 | I25: 1 | J25: 0 | K25: 0 | L25: 1 | M25: 1 | N25: 1 | O25: 1 | P25: Grade alignment: The proportion calculation 6/8 * 30 = 22.5 mats creates fractional results that may be too complex for Secondary O-level 2 students in practical contexts. Real-world feasibility: Cannot have 22.5 physical exercise mats in reality - would need to round to whole number of mats.
A26: TD | B26: Question 25 | C26: 0 | D26: 9.8424313 | E26: 1 | F26: 1 | G26: 1 | H26: 1 | I26: 1 | J26: 1 | K26: 1 | L26: 1 | M26: 1 | N26: 1 | O26: 1
A27: Minh | B27: Question 1 | C27: 0 | D27: 9.9774241 | E27: 1 | F27: 0 | G27: 1 | H27: 'NA | I27: 1 | J27: 'NA | K27: 1 | L27: 1 | M27: 1 | N27: 1 | O27: 1 | P27: Primary KC alignment: The intended primary knowledge component specifies adding decimals up to 2 decimal places, but the problem includes 1.797 km which has 3 decimal places, exceeding the specified limit.
A28: Minh | B28: Question 2 | C28: 0 | D28: 9.9582582 | E28: 1 | F28: 1 | G28: 0 | H28: 'NA | I28: 1 | J28: 1 | K28: 1 | L28: 1 | M28: 1 | N28: 1 | O28: 1 | P28: Secondary Knowledge Component: The answer 3/4 / 3 = 1/4 is already in simplest form, so expressing a fraction in its simplest form is not actively required. Synergy: Since no simplification is needed, the primary and secondary knowledge components do not work together in solving the problem.
A29: Minh | B29: Question 3 | C29: 0 | D29: 10.278625 | E29: 1 | F29: 1 | G29: 1 | H29: 1 | I29: 1 | J29: 1 | K29: 0 | L29: 1 | M29: 1 | N29: 1 | O29: 1 | P29: Real-world feasibility: Dividing 0.125 hours among 1000 students gives each student 0.000125 hours = 0.45 seconds, which is not a realistic practice duration for music education.
A30: Minh | B30: Question 4 | C30: 0 | D30: 11.838459 | E30: 1 | F30: 1 | G30: 1 | H30: 1 | I30: 1 | J30: 0 | K30: 1 | L30: 1 | M30: 1 | N30: 1 | O30: 1 | P30: Grade Alignment: Matrix operations including scalar multiplication and matrix subtraction are typically taught at A-level or university level mathematics, not at Secondary O-level 3/4. This problem requires knowledge components that are too advanced for the intended grade level.
A31: Minh | B31: Question 5 | C31: 0 | D31: 11.456226 | E31: 1 | F31: 1 | G31: 1 | H31: 1 | I31: 1 | J31: 1 | K31: 1 | L31: 1 | M31: 1 | N31: 1 | O31: 1
A32: Minh | B32: Question 6 | C32: 0 | D32: 2.7895133 | E32: 1 | F32: 1 | G32: 1 | H32: 1 | I32: 1 | J32: 1 | K32: 1 | L32: 1 | M32: 1 | N32: 1 | O32: 1
A33: Minh | B33: Question 7 | C33: 0 | D33: 11.531544 | E33: 1 | F33: 1 | G33: 1 | H33: 1 | I33: 1 | J33: 0 | K33: 1 | L33: 1 | M33: 1 | N33: 1 | O33: 1 | P33: Grade alignment fails because algebraic equations with variables are not taught in Singapore Primary 6 curriculum. Primary 6 students typically solve problems using arithmetic methods rather than algebraic notation with variables like n.
A34: Minh | B34: Question 8 | C34: 0 | D34: 2.8079963 | E34: 1 | F34: 1 | G34: 1 | H34: 1 | I34: 1 | J34: 1 | K34: 1 | L34: 1 | M34: 1 | N34: 1 | O34: 1
A35: Minh | B35: Question 9 | C35: 0 | D35: 2.8056219 | E35: 1 | F35: 1 | G35: 1 | H35: 1 | I35: 1 | J35: 1 | K35: 1 | L35: 1 | M35: 1 | N35: 1 | O35: 1
A36: Minh | B36: Question 10 | C36: 0 | D36: 4.5168464 | E36: 1 | F36: 1 | G36: 1 | H36: 1 | I36: 1 | J36: 0 | K36: 1 | L36: 1 | M36: 1 | N36: 1 | O36: 1 | P36: Grade Alignment: The problem is designed for Secondary O-level 3/4 students but uses terminology and concepts (quartiles Q1, Q2, Q3, interquartile range) that are typically introduced in Primary 6 or Secondary 1/2 levels in Singapore math curriculum, making it too basic for the intended grade level.
A37: Minh | B37: Question 11 | C37: 0 | D37: 2.8709714 | E37: 1 | F37: 1 | G37: 1 | H37: 1 | I37: 1 | J37: 1 | K37: 1 | L37: 1 | M37: 1 | N37: 1 | O37: 1
A38: Minh | B38: Question 12 | C38: 0 | D38: 12.464845 | E38: 0 | F38: 'NA | G38: 'NA | H38: 'NA | I38: 'NA | J38: 'NA | K38: 'NA | L38: 'NA | M38: 'NA | N38: 'NA | O38: 'NA | P38: Answerability: The problem contains conflicting information. Given ratio 3/4 : 2 equals 3:8, but if dancing = 24 and painting = 5/6 * 24 = 20, then actual ratio is 20:24 = 5:6. These ratios 3:8 and 5:6 are inconsistent. Secondary KC Alignment: No fraction division operation is required to solve the problem. Synergy: Primary and secondary knowledge components do not work together since fraction division is not needed.
A39: Minh | B39: Question 13 | C39: 0 | D39: 11.00863 | E39: 1 | F39: 1 | G39: 1 | H39: 1 | I39: 1 | J39: 0 | K39: 1 | L39: 1 | M39: 1 | N39: 1 | O39: 1 | P39: Grade alignment issue: Inverse proportion problems requiring the conceptual understanding that gameplay time decreases as player count increases may be too advanced for Secondary O-level 2 students. This level of abstract proportional reasoning typically comes later in mathematical development.
A40: Minh | B40: Question 14 | C40: 0 | D40: 8.9232655 | E40: 0 | F40: 'NA | G40: 'NA | H40: 'NA | I40: 'NA | J40: 'NA | K40: 'NA | L40: 'NA | M40: 'NA | N40: 'NA | O40: 'NA | P40: ANSWERABILITY: The problem cannot be solved as stated because 183 ÷ 4 = 45.75, which is not a whole number of children. The problem asks for equal groups but this is mathematically impossible with the given numbers. GRADE_ALIGNMENT: Primary 3 students typically work with division problems that result in whole numbers. A problem requiring decimal answers (45.75) or understanding of remainders in this context exceeds Primary 3 expectations. REAL_WORLD_FEASIBILITY: In reality, workshop organizers would not create groups with fractional children (45.75 per group). They would either form unequal groups or adjust the number of groups, making the premise unrealistic.
A41: Minh | B41: Question 15 | C41: 0 | D41: 14.240126 | E41: 0 | F41: 'NA | G41: 'NA | H41: 'NA | I41: 'NA | J41: 'NA | K41: 'NA | L41: 'NA | M41: 'NA | N41: 'NA | O41: 'NA | P41: Answerability: Conflicting information - total stated as $28 but calculation gives 4*3 + 2*5 = $22. Primary KC Alignment: Problem does not require solving linear equations in two variables as specific values x=3, y=5 are given directly. Synergy: Two parts can be solved independently - second part does not use equation from first part.
A42: Minh | B42: Question 16 | C42: 0 | D42: 2.4601746 | E42: 1 | F42: 1 | G42: 1 | H42: 1 | I42: 1 | J42: 1 | K42: 1 | L42: 1 | M42: 1 | N42: 1 | O42: 1
A43: Minh | B43: Question 17 | C43: 0 | D43: 10.520123 | E43: 1 | F43: 1 | G43: 0 | H43: 'NA | I43: 1 | J43: 1 | K43: 1 | L43: 1 | M43: 1 | N43: 1 | O43: 1 | P43: Secondary KC alignment fails because solving requires 168/4=42 then 42/6=7, both division operations, but intended secondary KC is multiplication. Synergy fails because both operations are division rather than the intended primary division + secondary multiplication combination.
A44: Minh | B44: Question 18 | C44: 0 | D44: 4.0865874 | E44: 1 | F44: 1 | G44: 1 | H44: 1 | I44: 1 | J44: 1 | K44: 0 | L44: 1 | M44: 1 | N44: 1 | O44: 1 | P44: Real-world feasibility: Playing football for 12 hours in one week and 18 hours in another week is unrealistic. This amounts to 1.7-2.6 hours per day which is excessive for a typical student during holidays and does not mirror realistic recreational activity patterns.
A45: Minh | B45: Question 19 | C45: 0 | D45: 2.8675241 | E45: 1 | F45: 1 | G45: 1 | H45: 1 | I45: 1 | J45: 1 | K45: 1 | L45: 1 | M45: 1 | N45: 1 | O45: 1
A46: Minh | B46: Question 20 | C46: 0 | D46: 11.586026 | E46: 1 | F46: 1 | G46: 0 | H46: 'NA | I46: 1 | J46: 1 | K46: 1 | L46: 1 | M46: 0 | N46: 1 | O46: 1 | P46: Secondary KC alignment: Problem mentions subtraction but solution only requires 36.84/6*2=12.28, no subtraction needed. Synergy: No synergy since subtraction not required. Conciseness: Subtraction reference is misleading and irrelevant to actual solution.
A47: Minh | B47: Question 21 | C47: 0 | D47: 2.6819475 | E47: 1 | F47: 1 | G47: 1 | H47: 1 | I47: 1 | J47: 1 | K47: 1 | L47: 1 | M47: 1 | N47: 1 | O47: 1
A48: Minh | B48: Question 22 | C48: 0 | D48: 9.1961551 | E48: 1 | F48: 1 | G48: 1 | H48: 1 | I48: 1 | J48: 1 | K48: 1 | L48: 1 | M48: 1 | N48: 1 | O48: 1
A49: Minh | B49: Question 23 | C49: 0 | D49: 5.6182449 | E49: 1 | F49: 1 | G49: 1 | H49: 1 | I49: 0 | J49: 0 | K49: 1 | L49: 1 | M49: 1 | N49: 1 | O49: 1 | P49: Topic Alignment: The problem context is about school clubs (Science Club, Music Club) which is educational/academic rather than recreation activities like sports, games, exercises, music performance, movie watching, dancing, painting, fishing. Grade Alignment: This problem requires formal set notation and set operations concepts that are typically introduced at Secondary O-level 1/2 or earlier, making it below the intended Secondary O-level 3/4 grade level which should involve more advanced mathematical concepts.
A50: Minh | B50: Question 24 | C50: 0 | D50: 2.7857549 | E50: 1 | F50: 1 | G50: 1 | H50: 1 | I50: 1 | J50: 1 | K50: 1 | L50: 1 | M50: 1 | N50: 1 | O50: 1
A51: Minh | B51: Question 25 | C51: 0 | D51: 12.526394 | E51: 1 | F51: 1 | G51: 1 | H51: 0 | I51: 1 | J51: 0 | K51: 1 | L51: 1 | M51: 1 | N51: 1 | O51: 1 | P51: Synergy: The two parts calculate median and mode independently from the same dataset - part (a) result is not used to solve part (b), lacking the required connection between questions. Grade Alignment: Finding median and mode are Primary 5-6 level concepts in Singapore curriculum, too basic for Secondary O-level 2 students who should be working with advanced statistics like standard deviation or probability distributions.
A52: Sarah | B52: Question 1 | C52: 0 | D52: 10.434022 | E52: 1 | F52: 1 | G52: 1 | H52: 1 | I52: 1 | J52: 1 | K52: 1 | L52: 1 | M52: 1 | N52: 1 | O52: 1
A53: Sarah | B53: Question 2 | C53: 0 | D53: 5.5664489 | E53: 1 | F53: 1 | G53: 1 | H53: 1 | I53: 1 | J53: 0 | K53: 1 | L53: 1 | M53: 1 | N53: 1 | O53: 1 | P53: Grade Alignment: The problem is designed for Secondary O-level 2 but involves basic linear inequalities that are typically introduced in Primary 6 or Secondary 1. The mathematical concepts (12n + 10 <= 50, solving for n <= 3.33, therefore n = 3) are too elementary for O-level 2 students who should be working with more complex algebraic concepts, systems of inequalities, or quadratic inequalities.
A54: Sarah | B54: Question 3 | C54: 0 | D54: 5.0407612 | E54: 1 | F54: 1 | G54: 1 | H54: 1 | I54: 1 | J54: 0 | K54: 1 | L54: 1 | M54: 1 | N54: 1 | O54: 1 | P54: Grade Alignment: This problem is too simple for Secondary O-level 3/4 students. It involves basic probability multiplication (5/12 * 3/6 = 5/24) which is typically covered in primary or lower secondary grades. O-level 3/4 students would be expected to handle more complex probability scenarios involving conditional probability, permutations, combinations, or multi-step probability trees.
A55: Sarah | B55: Question 4 | C55: 0 | D55: 9.8067231 | E55: 1 | F55: 1 | G55: 1 | H55: 1 | I55: 1 | J55: 1 | K55: 1 | L55: 1 | M55: 1 | N55: 1 | O55: 1
A56: Sarah | B56: Question 5 | C56: 0 | D56: 7.8694994 | E56: 1 | F56: 1 | G56: 1 | H56: 1 | I56: 1 | J56: 1 | K56: 1 | L56: 0 | M56: 1 | N56: 1 | O56: 1 | P56: Clarity: The problem statement is ambiguous about what the 20% increase refers to. The phrase 'her score increased by a certain percentage' followed by 'this increase represents exactly 20% more than her score last month' creates confusion about whether 20% is the increase percentage or describes the relationship between scores.
A57: Sarah | B57: Question 6 | C57: 0 | D57: 11.793356 | E57: 1 | F57: 1 | G57: 1 | H57: 1 | I57: 1 | J57: 1 | K57: 0 | L57: 1 | M57: 1 | N57: 1 | O57: 1 | P57: Real-world feasibility issue: In table tennis, players do not hit the ball specific distances like 2.35m consistently. Table tennis involves rallies across a 2.74m table, making the scenario of measuring how far players hit the ball unrealistic for this sport.
A58: Sarah | B58: Question 7 | C58: 0 | D58: 5.1629367 | E58: 1 | F58: 1 | G58: 1 | H58: 1 | I58: 1 | J58: 0 | K58: 0 | L58: 1 | M58: 1 | N58: 1 | O58: 1 | P58: Grade alignment: This problem is too basic for Secondary O-level 1 students as it only involves simple ratio calculations with decimals and basic decimal addition, which are typically covered in primary school. Real-world feasibility: Having 12.5 boys and 3.7 girls joining is unrealistic as you cannot have fractional people in real-world scenarios.
A59: Sarah | B59: Question 8 | C59: 0 | D59: 2.8968358 | E59: 1 | F59: 1 | G59: 1 | H59: 1 | I59: 1 | J59: 1 | K59: 1 | L59: 1 | M59: 1 | N59: 1 | O59: 1
A60: Sarah | B60: Question 9 | C60: 0 | D60: 5.4091418 | E60: 1 | F60: 1 | G60: 1 | H60: 1 | I60: 1 | J60: 0 | K60: 1 | L60: 1 | M60: 1 | N60: 1 | O60: 1 | P60: Grade Alignment: This problem is too simple for Secondary O-level 1 students. Calculating percentage increase using (150-120)/120 * 100 = 25% and converting 25% to 1/4 are concepts typically mastered in Primary 5-6. Secondary O-level 1 students would expect more complex percentage problems involving compound calculations, multiple steps, or algebraic manipulation.
A61: Sarah | B61: Question 10 | C61: 0 | D61: 14.049019 | E61: 1 | F61: 1 | G61: 1 | H61: 1 | I61: 1 | J61: 0 | K61: 0 | L61: 0 | M61: 1 | N61: 1 | O61: 1 | P61: Grade alignment: Problem involves fractions greater than 1 (7/4 = 1.75, 5/3 = 1.67) representing over 100% of practice time, and results in complex decimal 3.417, which may be too advanced for Primary 5. Real-world feasibility: Completing 175% and 167% of planned practice time on consecutive days is unrealistic. Clarity: The phrase 'of that time' creates ambiguity about whether to multiply 5/3 * 7/4 or add 7/4 + 5/3.
A62: Sarah | B62: Question 11 | C62: 0 | D62: 9.8667219 | E62: 1 | F62: 1 | G62: 1 | H62: 1 | I62: 1 | J62: 1 | K62: 1 | L62: 1 | M62: 1 | N62: 1 | O62: 1
A63: Sarah | B63: Question 12 | C63: 0 | D63: 5.7623713 | E63: 1 | F63: 1 | G63: 1 | H63: 1 | I63: 1 | J63: 0 | K63: 0 | L63: 1 | M63: 1 | N63: 1 | O63: 1 | P63: Grade Alignment: The problem is designed for Secondary O-level 1 but involves quadratic expressions (2x^2 + 3x + 5) which are typically introduced in later secondary grades, not at the O-level 1 foundation level. Real-World Plausibility: Mini-golf course booking costs following a quadratic function 2x^2 + 3x + 5 is unrealistic - typical hourly rates are linear (fixed rate per hour), and the given function would result in $45 for 4 hours which is excessively expensive for mini-golf.
A64: Sarah | B64: Question 13 | C64: 0 | D64: 11.808728 | E64: 1 | F64: 1 | G64: 1 | H64: 1 | I64: 1 | J64: 1 | K64: 1 | L64: 1 | M64: 1 | N64: 1 | O64: 1
A65: Sarah | B65: Question 14 | C65: 0 | D65: 3.0104761 | E65: 1 | F65: 1 | G65: 1 | H65: 1 | I65: 1 | J65: 1 | K65: 1 | L65: 1 | M65: 1 | N65: 1 | O65: 1
A66: Sarah | B66: Question 15 | C66: 0 | D66: 4.4842284 | E66: 1 | F66: 1 | G66: 1 | H66: 1 | I66: 1 | J66: 0 | K66: 1 | L66: 1 | M66: 1 | N66: 1 | O66: 1 | P66: Grade alignment: This problem involves basic ratio concepts with fraction arithmetic that would typically be covered in upper primary or lower secondary grades, making it too simple for Secondary O-level 1 students who should be working with more advanced mathematical concepts and complex problem-solving scenarios.
A67: Sarah | B67: Question 16 | C67: 0 | D67: 8.4116828 | E67: 1 | F67: 1 | G67: 1 | H67: 1 | I67: 1 | J67: 1 | K67: 1 | L67: 1 | M67: 1 | N67: 1 | O67: 1
A68: Sarah | B68: Question 17 | C68: 0 | D68: 12.513499 | E68: 0 | F68: 'NA | G68: 'NA | H68: 'NA | I68: 'NA | J68: 'NA | K68: 'NA | L68: 'NA | M68: 'NA | N68: 'NA | O68: 'NA | P68: Answerability: The problem creates an impossible scenario where Sarah drinks 0.075 litres when only 0.050 litres remains after filling bottles (14.250 - 142*0.100 = 0.050 litres remaining, but she drinks 0.075 litres). Real-World Plausibility: It is impossible to drink more liquid than what is available, making this scenario unrealistic.
A69: Sarah | B69: Question 18 | C69: 0 | D69: 9.6323242 | E69: 1 | F69: 1 | G69: 1 | H69: 1 | I69: 1 | J69: 1 | K69: 1 | L69: 1 | M69: 1 | N69: 1 | O69: 1
A70: Sarah | B70: Question 19 | C70: 0 | D70: 2.686779 | E70: 1 | F70: 1 | G70: 1 | H70: 1 | I70: 1 | J70: 1 | K70: 1 | L70: 1 | M70: 1 | N70: 1 | O70: 1
A71: Sarah | B71: Question 20 | C71: 0 | D71: 12.789877 | E71: 1 | F71: 0 | G71: 1 | H71: 'NA | I71: 1 | J71: 'NA | K71: 1 | L71: 1 | M71: 1 | N71: 1 | O71: 1 | P71: Primary KC alignment: Problem requires inclusion-exclusion principle with counting, not addition of probabilities. Solution involves adding counts (18 + 15 - 6 = 27) then finding probability (27/30), rather than adding probabilities directly. Synergy: Cannot achieve synergy when primary KC is not properly aligned with the problem requirements.
A72: Sarah | B72: Question 21 | C72: 0 | D72: 4.7444355 | E72: 1 | F72: 1 | G72: 1 | H72: 1 | I72: 1 | J72: 0 | K72: 1 | L72: 1 | M72: 1 | N72: 1 | O72: 1 | P72: Grade Alignment: This problem involves basic percentage calculations (15% increase) and simple addition, which are typically mastered in Primary 5-6. For Secondary O-level 1 students, this problem would be too elementary and does not match the complexity expected at that grade level. Secondary O-level 1 students would typically work with more complex percentage problems involving compound interest, percentage profit/loss, or multi-step percentage calculations.
A73: Sarah | B73: Question 22 | C73: 0 | D73: 8.5699306 | E73: 1 | F73: 1 | G73: 1 | H73: 1 | I73: 1 | J73: 1 | K73: 1 | L73: 1 | M73: 1 | N73: 1 | O73: 1
A74: Sarah | B74: Question 23 | C74: 0 | D74: 5.7699316 | E74: 1 | F74: 1 | G74: 1 | H74: 0 | I74: 1 | J74: 0 | K74: 1 | L74: 1 | M74: 1 | N74: 1 | O74: 1 | P74: Synergy: The two parts (a) and (b) are independent calculations that do not require using results from one part to solve the other part. Finding median and range can be solved separately without connection. Grade Alignment: Finding median and range are basic statistical concepts typically introduced in Primary 5-6 or Secondary 1, which is below the Secondary O-level 2 standard. This grade level should involve more advanced statistical concepts like quartiles, standard deviation, or probability distributions.
A75: Sarah | B75: Question 24 | C75: 0 | D75: 10.383919 | E75: 1 | F75: 0 | G75: 1 | H75: 'NA | I75: 1 | J75: 'NA | K75: 1 | L75: 1 | M75: 1 | N75: 1 | O75: 1 | P75: Primary KC alignment fails because the problem focuses more on decimal addition than on multiplying decimals by multiples of 10/100/1000. While multiplication by 10 and 20 occurs, it is not the main difficulty or emphasis of the problem.
A76: Sarah | B76: Question 25 | C76: 0 | D76: 9.570195 | E76: 1 | F76: 1 | G76: 1 | H76: 1 | I76: 1 | J76: 1 | K76: 1 | L76: 1 | M76: 1 | N76: 1 | O76: 1
A77: Sarah | B77: Question 26 | C77: 0 | D77: 13.212274 | E77: 0 | F77: 'NA | G77: 'NA | H77: 'NA | I77: 'NA | J77: 'NA | K77: 'NA | L77: 'NA | M77: 'NA | N77: 'NA | O77: 'NA | P77: Answerability: Problem states 10 equal laps but then provides 10 different lap distances, creating conflicting information. Primary KC alignment: Problem only requires 12.450/10 = 1.245, which is basic division, not dividing by multiples of 10, 100, 1000. Synergy: Parts are disconnected due to contradictory information about equal vs different lap distances. Real-world feasibility: Swimming competitions measure time per lap, not distance per lap variations. Clarity: Contradictory statements about equal laps vs different distances create confusion. Conciseness: Total distance 12.450m becomes irrelevant after part a due to contradiction.

Sheet recreation_v2_9
A1: Evaluator | B1: Question | C1: status | D1: response_time | E1: answerability | F1: primary_kc_alignment | G1: secondary_kc_alignment | H1: synergy | I1: topic_alignment | J1: grade_alignment | K1: real_world_feasibility | L1: clarity | M1: conciseness_and_relevance | N1: language_quality | O1: content_appropriateness | P1: explanation
A2: TD | B2: Question 1 | C2: 0 | D2: 4.3597925 | E2: 1 | F2: 1 | G2: 1 | H2: 1 | I2: 1 | J2: 0 | K2: 1 | L2: 1 | M2: 1 | N2: 1 | O2: 1 | P2: Grade alignment: The problem uses 4-digit numbers (1562, 738, 247) which are typically introduced in Primary 4 or higher. Primary 3 students typically work with 3-digit numbers or smaller. The computational complexity of subtracting and adding 4-digit numbers exceeds Primary 3 level expectations.
A3: TD | B3: Question 2 | C3: 0 | D3: 10.840834 | E3: 1 | F3: 0 | G3: 1 | H3: 'NA | I3: 1 | J3: 'NA | K3: 1 | L3: 1 | M3: 1 | N3: 1 | O3: 1 | P3: Primary KC alignment fails because the required calculation 202.457 / 50 cannot be solved using the intended method of dividing decimals by 10, 100, 1000 and their multiples. While 50 = 10 x 5, this division requires general decimal division algorithms rather than the place-value shifting method specific to powers of 10.
A4: TD | B4: Question 3 | C4: 0 | D4: 7.0765119 | E4: 1 | F4: 1 | G4: 1 | H4: 1 | I4: 1 | J4: 1 | K4: 1 | L4: 0 | M4: 1 | N4: 1 | O4: 1 | P4: The problem contains ambiguous language regarding the time frame. It states Wei Lin swam on Monday and Wednesday, then asks her to divide the total distance equally among 10 days as part of a training plan. It is unclear whether the 10 days refers to the current week (which would not make sense as a week has 7 days) or a future training period. This creates confusion about the context and timeline of the division task.
A5: TD | B5: Question 4 | C5: 0 | D5: 2.7348113 | E5: 1 | F5: 1 | G5: 1 | H5: 1 | I5: 1 | J5: 1 | K5: 1 | L5: 1 | M5: 1 | N5: 1 | O5: 1
A6: TD | B6: Question 5 | C6: 0 | D6: 11.202191 | E6: 1 | F6: 1 | G6: 1 | H6: 1 | I6: 1 | J6: 0 | K6: 1 | L6: 1 | M6: 1 | N6: 1 | O6: 1 | P6: Grade alignment failed because the problem uses 3.276 minutes which has 3 decimal places. Primary 4 students typically work with decimals up to 2 decimal places only according to Singapore math curriculum. The number 3.276 requires knowledge above Primary 4 level.
A7: TD | B7: Question 6 | C7: 0 | D7: 6.7938976 | E7: 1 | F7: 1 | G7: 1 | H7: 1 | I7: 1 | J7: 1 | K7: 1 | L7: 1 | M7: 1 | N7: 1 | O7: 1
A8: TD | B8: Question 7 | C8: 0 | D8: 2.7297006 | E8: 1 | F8: 1 | G8: 1 | H8: 1 | I8: 1 | J8: 1 | K8: 1 | L8: 1 | M8: 1 | N8: 1 | O8: 1
A9: TD | B9: Question 8 | C9: 0 | D9: 2.737859 | E9: 1 | F9: 1 | G9: 1 | H9: 1 | I9: 1 | J9: 1 | K9: 1 | L9: 1 | M9: 1 | N9: 1 | O9: 1
A10: TD | B10: Question 9 | C10: 0 | D10: 5.2020807 | E10: 1 | F10: 1 | G10: 1 | H10: 1 | I10: 1 | J10: 0 | K10: 0 | L10: 1 | M10: 1 | N10: 1 | O10: 1 | P10: Grade alignment: Matrix operations are typically taught at A-level or higher education, not O-level 3/4. Real-world feasibility: The impact factor matrix M with values like 0.5 and 0.8 as weightages for sports activities lacks clear real-world meaning - it is unclear what these decimal multipliers represent in the context of sports training hours or why basketball would have impact factor 1 while badminton has 0.5.
A11: TD | B11: Question 10 | C11: 0 | D11: 2.8171892 | E11: 1 | F11: 1 | G11: 1 | H11: 1 | I11: 1 | J11: 1 | K11: 1 | L11: 1 | M11: 1 | N11: 1 | O11: 1
A12: TD | B12: Question 11 | C12: 0 | D12: 12.286176 | E12: 1 | F12: 1 | G12: 1 | H12: 1 | I12: 1 | J12: 0 | K12: 0 | L12: 0 | M12: 1 | N12: 1 | O12: 1 | P12: Grade alignment: Attending 5/3 sessions is too abstract for Primary 5 students. Real-world feasibility: Attending 1.67 sessions is unrealistic in practice. Clarity: The phrase 5/3 of such sessions is confusing for the target grade level.
A13: TD | B13: Question 12 | C13: 0 | D13: 4.7259777 | E13: 1 | F13: 1 | G13: 1 | H13: 1 | I13: 1 | J13: 0 | K13: 1 | L13: 1 | M13: 1 | N13: 1 | O13: 1 | P13: Grade Alignment: This problem requires understanding of algebraic variables (x, n), algebraic expressions with variables, and algebraic manipulation which are typically introduced in Secondary 1-2, not Primary 6. Primary 6 students in Singapore math syllabus work with basic algebraic thinking but not formal algebraic expressions with multiple variables.
A14: TD | B14: Question 13 | C14: 0 | D14: 9.4775894 | E14: 1 | F14: 1 | G14: 1 | H14: 1 | I14: 1 | J14: 1 | K14: 1 | L14: 1 | M14: 1 | N14: 1 | O14: 1
A15: TD | B15: Question 14 | C15: 0 | D15: 10.664023 | E15: 1 | F15: 1 | G15: 1 | H15: 1 | I15: 1 | J15: 0 | K15: 1 | L15: 1 | M15: 1 | N15: 1 | O15: 1 | P15: Grade alignment: The problem involves basic 15% calculation (60 * 1.15 = 69) and simple subtraction (69 - 10 = 59), which are elementary-level skills inappropriate for Secondary O-level 1 students who should handle more complex mathematical concepts.
A16: TD | B16: Question 15 | C16: 0 | D16: 9.247515 | E16: 1 | F16: 1 | G16: 1 | H16: 1 | I16: 1 | J16: 1 | K16: 1 | L16: 1 | M16: 1 | N16: 1 | O16: 1
A17: TD | B17: Question 16 | C17: 0 | D17: 13.581187 | E17: 1 | F17: 1 | G17: 1 | H17: 1 | I17: 1 | J17: 0 | K17: 1 | L17: 1 | M17: 1 | N17: 1 | O17: 1 | P17: Grade alignment issue: The problem contains a logical inconsistency. If Siti got every note correct at 0.175 points each for 100 notes, she should earn exactly 17.5 points. However, the problem states 2.35 points were wrongly added to give a displayed score of 17.5, which would mean she actually earned 17.5 - 2.35 = 15.15 points, contradicting the perfect performance setup. This inconsistency makes the problem confusing and inappropriate for Primary 5 students.
A18: TD | B18: Question 17 | C18: 0 | D18: 9.7507212 | E18: 0 | F18: 'NA | G18: 'NA | H18: 'NA | I18: 'NA | J18: 'NA | K18: 'NA | L18: 'NA | M18: 'NA | N18: 'NA | O18: 'NA | P18: The problem cannot be solved because it lacks essential information - the number of painting sessions Sarah attended last month is not provided. To find the total paint used this month, we need: (sessions last month) * (5/3) * (3/4), but the first value is missing.
A19: TD | B19: Question 18 | C19: 0 | D19: 11.10044 | E19: 1 | F19: 1 | G19: 1 | H19: 1 | I19: 1 | J19: 1 | K19: 1 | L19: 1 | M19: 1 | N19: 1 | O19: 1
A20: TD | B20: Question 19 | C20: 0 | D20: 7.6954136 | E20: 1 | F20: 1 | G20: 1 | H20: 1 | I20: 1 | J20: 1 | K20: 0 | L20: 1 | M20: 1 | N20: 1 | O20: 1 | P20: Real-world feasibility: The scenario where Sarah adds 1/8 watermelon from her lunchbox to each person individually (meaning she would need 4 * 1/8 = 1/2 watermelon total) is unrealistic. It would be more natural to add the 1/8 watermelon to the shared pool and redistribute equally among all 5 people, rather than having exactly enough additional watermelon to give each of the original 4 people the same additional amount.
A21: TD | B21: Question 20 | C21: 0 | D21: 9.0421703 | E21: 0 | F21: 'NA | G21: 'NA | H21: 'NA | I21: 'NA | J21: 'NA | K21: 'NA | L21: 'NA | M21: 'NA | N21: 'NA | O21: 'NA | P21: Answerability: The problem cannot be solved because it provides time spent (2/3 as much time) but asks for painting completed. Missing information about relationship between time and painting completion rate. Real-world feasibility: The problem assumes time spent directly equals fraction of painting completed, which is not realistic - painting speed can vary. Clarity: Ambiguous relationship between time spent painting and amount of painting completed creates confusion about what is being asked.
A22: TD | B22: Question 21 | C22: 0 | D22: 9.5771339 | E22: 1 | F22: 1 | G22: 1 | H22: 1 | I22: 1 | J22: 1 | K22: 1 | L22: 1 | M22: 1 | N22: 1 | O22: 1
A23: TD | B23: Question 22 | C23: 0 | D23: 11.486451 | E23: 1 | F23: 0 | G23: 1 | H23: 'NA | I23: 1 | J23: 'NA | K23: 1 | L23: 1 | M23: 1 | N23: 1 | O23: 1 | P23: Primary KC alignment: Problem requires adding decimals with 3 decimal places (8.125) but intended KC specifies up to 2 decimal places only. Synergy: Part (a) total score calculation is not used in part (b) comparison - the two parts are independent. Grade alignment: Adding 3-decimal place numbers exceeds typical Primary 4 curriculum expectations in Singapore math.
A24: TD | B24: Question 23 | C24: 0 | D24: 9.0407834 | E24: 0 | F24: 'NA | G24: 'NA | H24: 'NA | I24: 'NA | J24: 'NA | K24: 'NA | L24: 'NA | M24: 'NA | N24: 'NA | O24: 'NA | P24: The problem is missing essential information - the number of practice days last month is not provided. Without this information, we cannot calculate 9/5 times that number to determine this month's practice days, making the problem unsolvable.
A25: TD | B25: Question 24 | C25: 0 | D25: 6.1641569 | E25: 1 | F25: 1 | G25: 1 | H25: 1 | I25: 1 | J25: 0 | K25: 1 | L25: 1 | M25: 1 | N25: 1 | O25: 1 | P25: Grade Alignment: This problem is too simple for Secondary O-level 2 students. Direct proportion with simple whole number multiplication is typically covered in Primary 5-6 or Secondary 1 at most. O-level 2 students would be expected to handle more complex mathematical concepts like algebraic manipulation, quadratic equations, or advanced geometry. The mathematical demand does not match the cognitive level expected for this grade.
A26: TD | B26: Question 25 | C26: 0 | D26: 2.827497 | E26: 1 | F26: 1 | G26: 1 | H26: 1 | I26: 1 | J26: 1 | K26: 1 | L26: 1 | M26: 1 | N26: 1 | O26: 1
A27: Minh | B27: Question 1 | C27: 0 | D27: 10.66747 | E27: 1 | F27: 0 | G27: 1 | H27: 'NA | I27: 1 | J27: 'NA | K27: 1 | L27: 1 | M27: 1 | N27: 1 | O27: 1 | P27: Primary KC alignment fails because the problem requires adding decimals up to 3 decimal places (1.797) while the intended primary KC specifies adding decimals up to 2 decimal places only.
A28: Minh | B28: Question 2 | C28: 0 | D28: 8.6111703 | E28: 1 | F28: 1 | G28: 1 | H28: 1 | I28: 1 | J28: 1 | K28: 1 | L28: 1 | M28: 1 | N28: 1 | O28: 1
A29: Minh | B29: Question 3 | C29: 0 | D29: 7.1908157 | E29: 1 | F29: 1 | G29: 1 | H29: 1 | I29: 1 | J29: 1 | K29: 0 | L29: 1 | M29: 1 | N29: 1 | O29: 1 | P29: Real-world feasibility fails because dividing a 0.125-hour song (7.5 minutes) among 1000 students gives each student 0.000125 hours (0.45 seconds) of practice time, which is completely impractical and unrealistic for meaningful piano practice or any educational purpose.
A30: Minh | B30: Question 4 | C30: 0 | D30: 11.290826 | E30: 1 | F30: 1 | G30: 1 | H30: 1 | I30: 1 | J30: 1 | K30: 0 | L30: 1 | M30: 1 | N30: 1 | O30: 1 | P30: The scenario lacks real-world plausibility because the principal's decision to double one team's practice hours and subtract another team's hours has no realistic educational or administrative justification. This mathematical operation does not reflect how practice time management would realistically work in a school music club setting.
A31: Minh | B31: Question 5 | C31: 0 | D31: 10.489297 | E31: 1 | F31: 1 | G31: 1 | H31: 1 | I31: 1 | J31: 1 | K31: 1 | L31: 1 | M31: 1 | N31: 1 | O31: 1
A32: Minh | B32: Question 6 | C32: 0 | D32: 10.564195 | E32: 1 | F32: 1 | G32: 1 | H32: 1 | I32: 1 | J32: 1 | K32: 1 | L32: 1 | M32: 1 | N32: 1 | O32: 1
A33: Minh | B33: Question 7 | C33: 0 | D33: 13.254077 | E33: 1 | F33: 1 | G33: 1 | H33: 1 | I33: 1 | J33: 0 | K33: 1 | L33: 1 | M33: 1 | N33: 1 | O33: 1 | P33: Grade Alignment: The problem requires formal algebraic equation solving (12n = 60) and explicit translation into algebraic expressions, which typically appears in Secondary 1 curriculum rather than Primary 6 in Singapore math syllabus.
A34: Minh | B34: Question 8 | C34: 0 | D34: 2.7060719 | E34: 1 | F34: 1 | G34: 1 | H34: 1 | I34: 1 | J34: 1 | K34: 1 | L34: 1 | M34: 1 | N34: 1 | O34: 1
A35: Minh | B35: Question 9 | C35: 0 | D35: 2.6291101 | E35: 1 | F35: 1 | G35: 1 | H35: 1 | I35: 1 | J35: 1 | K35: 1 | L35: 1 | M35: 1 | N35: 1 | O35: 1
A36: Minh | B36: Question 10 | C36: 0 | D36: 4.9354153 | E36: 1 | F36: 1 | G36: 1 | H36: 1 | I36: 1 | J36: 0 | K36: 1 | L36: 1 | M36: 1 | N36: 1 | O36: 1 | P36: Grade Alignment: The problem is designed for Secondary O-level 3/4 but quartiles and interquartile range are typically introduced at Primary 6 or Secondary 1/2 level in Singapore math syllabus. This topic is below the expected difficulty for O-level 3/4 students who should be working with more advanced statistical concepts like standard deviation, probability distributions, or hypothesis testing.
A37: Minh | B37: Question 11 | C37: 0 | D37: 2.6785231 | E37: 1 | F37: 1 | G37: 1 | H37: 1 | I37: 1 | J37: 1 | K37: 1 | L37: 1 | M37: 1 | N37: 1 | O37: 1
A38: Minh | B38: Question 12 | C38: 0 | D38: 12.009394 | E38: 0 | F38: 'NA | G38: 'NA | H38: 'NA | I38: 'NA | J38: 'NA | K38: 'NA | L38: 'NA | M38: 'NA | N38: 'NA | O38: 'NA | P38: The problem contains conflicting information. From ratio 3/4 : 2 with 24 dancing students: painting = (3/4) * 12 = 9 students. But the fraction condition gives: painting = (5/6) * 24 = 20 students. Since 9 ≠ 20, the problem has no solution.
A39: Minh | B39: Question 13 | C39: 0 | D39: 6.9903669 | E39: 1 | F39: 1 | G39: 1 | H39: 0 | I39: 1 | J39: 0 | K39: 0 | L39: 1 | M39: 1 | N39: 1 | O39: 1 | P39: Synergy: The two parts (a) and (b) are independent - part (b) does not use the result from part (a). Part (a) asks for game completion time with 6 players, but part (b) uses 6 players as given information, not as a result from part (a). Grade Alignment: This problem is too simple for Secondary O-level 2 students. The inverse proportion concept (4 players x 120 minutes = 6 players x t minutes, so t = 80 minutes) and basic division (36 / 6 = 6) are concepts typically mastered in primary grades, not secondary O-level. Real-World Feasibility: The assumption that game completion time is inversely proportional to number of players is unrealistic. In reality, board games have fixed rules and turns, so adding more players typically increases game duration rather than decreases it.
A40: Minh | B40: Question 14 | C40: 0 | D40: 10.16479 | E40: 0 | F40: 'NA | G40: 'NA | H40: 'NA | I40: 'NA | J40: 'NA | K40: 'NA | L40: 'NA | M40: 'NA | N40: 'NA | O40: 'NA | P40: The problem is not answerable because 183 / 4 = 45.75, meaning you cannot divide 183 children equally into 4 groups since you cannot have 0.75 of a child in a group.
A41: Minh | B41: Question 15 | C41: 0 | D41: 6.9974699 | E41: 0 | F41: 'NA | G41: 'NA | H41: 'NA | I41: 'NA | J41: 'NA | K41: 'NA | L41: 'NA | M41: 'NA | N41: 'NA | O41: 'NA | P41: Answerability: The problem contains contradictory information. The setup asks for equations with variables x and y to represent the total cost of $28, but then asks for the total cost when x=3 and y=5, which should be calculated as 4*3 + 2*5 = $22, not $28. This creates conflicting information making the problem logically inconsistent. Primary KC Alignment: The problem does not require solving linear equations in two variables. The main task is translating the situation into equations and then performing simple substitution/calculation. No actual solving of a system of equations is needed. Synergy: There is no meaningful connection between the equation-writing task and the calculation task. The second part simply substitutes given values rather than requiring the use of both knowledge components together to solve a coherent problem.
A42: Minh | B42: Question 16 | C42: 0 | D42: 9.4465625 | E42: 1 | F42: 1 | G42: 1 | H42: 1 | I42: 1 | J42: 1 | K42: 1 | L42: 1 | M42: 1 | N42: 1 | O42: 1
A43: Minh | B43: Question 17 | C43: 0 | D43: 6.971947 | E43: 1 | F43: 1 | G43: 0 | H43: 'NA | I43: 1 | J43: 1 | K43: 1 | L43: 1 | M43: 1 | N43: 1 | O43: 1 | P43: Secondary KC alignment: The problem only requires division operations (168/4=42, then 42/6=7). No multiplication is needed to solve the problem, so the intended Secondary Knowledge Component of multiplication is not utilized. Synergy: Since multiplication is not needed in the solution, there is no synergy between the Primary KC (division) and Secondary KC (multiplication) - they are not used in tandem to solve the problem.
A44: Minh | B44: Question 18 | C44: 0 | D44: 10.685811 | E44: 1 | F44: 1 | G44: 1 | H44: 1 | I44: 1 | J44: 1 | K44: 1 | L44: 1 | M44: 1 | N44: 1 | O44: 1
A45: Minh | B45: Question 19 | C45: 0 | D45: 3.737294 | E45: 1 | F45: 1 | G45: 1 | H45: 1 | I45: 1 | J45: 1 | K45: 1 | L45: 1 | M45: 1 | N45: 1 | O45: 1
A46: Minh | B46: Question 20 | C46: 0 | D46: 11.15756 | E46: 1 | F46: 1 | G46: 0 | H46: 'NA | I46: 1 | J46: 1 | K46: 1 | L46: 1 | M46: 1 | N46: 1 | O46: 1 | P46: Secondary KC Alignment: The problem mentions subtraction but solving only requires division (36.84 / 6 = 6.14) and multiplication (6.14 * 2 = 12.28). Subtraction is not needed. Synergy: Since subtraction is not required for the solution, there is no synergy between the intended primary and secondary knowledge components.
A47: Minh | B47: Question 21 | C47: 0 | D47: 2.779304 | E47: 1 | F47: 1 | G47: 1 | H47: 1 | I47: 1 | J47: 1 | K47: 1 | L47: 1 | M47: 1 | N47: 1 | O47: 1
A48: Minh | B48: Question 22 | C48: 0 | D48: 8.9234052 | E48: 1 | F48: 1 | G48: 1 | H48: 1 | I48: 1 | J48: 1 | K48: 1 | L48: 1 | M48: 1 | N48: 1 | O48: 1
A49: Minh | B49: Question 23 | C49: 0 | D49: 5.3345861 | E49: 1 | F49: 1 | G49: 1 | H49: 1 | I49: 0 | J49: 0 | K49: 1 | L49: 1 | M49: 1 | N49: 1 | O49: 1 | P49: Topic Alignment: The problem context is about school clubs rather than recreation activities. While clubs may involve recreational elements, the focus is on academic/school organization rather than recreation activities like sports, games, exercises, music, movie, dancing, painting, fishing. Grade Alignment: This problem requires formal set notation and set theory concepts that are typically introduced at higher secondary levels or pre-university mathematics, not at O-level 3/4 where basic arithmetic and algebra are the focus.
A50: Minh | B50: Question 24 | C50: 0 | D50: 9.8924737 | E50: 1 | F50: 1 | G50: 1 | H50: 1 | I50: 1 | J50: 1 | K50: 1 | L50: 1 | M50: 1 | N50: 1 | O50: 1
A51: Minh | B51: Question 25 | C51: 0 | D51: 12.011 | E51: 1 | F51: 1 | G51: 1 | H51: 0 | I51: 1 | J51: 0 | K51: 1 | L51: 1 | M51: 1 | N51: 1 | O51: 1 | P51: Synergy: The two parts (a) and (b) are independent calculations on the same dataset - finding median does not require the mode result or vice versa, so they are not used in tandem. Grade Alignment: Finding median and mode for a simple 9-number dataset is too basic for Secondary O-level 2 students (Grade 10 equivalent) - this content is typically appropriate for Grade 6-8 level.
A52: Sarah | B52: Question 1 | C52: 0 | D52: 9.3080187 | E52: 1 | F52: 1 | G52: 1 | H52: 1 | I52: 1 | J52: 1 | K52: 1 | L52: 1 | M52: 1 | N52: 1 | O52: 1
A53: Sarah | B53: Question 2 | C53: 0 | D53: 5.3532517 | E53: 1 | F53: 1 | G53: 1 | H53: 1 | I53: 1 | J53: 0 | K53: 1 | L53: 1 | M53: 1 | N53: 1 | O53: 1 | P53: Grade Alignment: The problem is designed for Secondary O-level 2 but involves solving simple linear inequalities which is typically introduced in Primary 6 or Secondary 1 in Singapore math syllabus. The problem complexity (12n + 10 <= 50, solving for n <= 3.33, so n = 3) is too elementary for O-level 2 students who should be working with more complex algebraic concepts, simultaneous equations, or quadratic inequalities.
A54: Sarah | B54: Question 3 | C54: 0 | D54: 5.1352615 | E54: 1 | F54: 1 | G54: 1 | H54: 1 | I54: 1 | J54: 0 | K54: 1 | L54: 1 | M54: 1 | N54: 1 | O54: 1 | P54: Grade Alignment: This problem is too simple for Secondary O-level 3/4 students. It involves basic probability multiplication (5/12 * 3/6 = 5/24) which is typically taught at Primary 5-6 or lower Secondary levels. O-level 3/4 students would be expected to handle more complex probability scenarios involving conditional probability, combinations, or multi-step probability trees.
A55: Sarah | B55: Question 4 | C55: 0 | D55: 9.6598237 | E55: 1 | F55: 1 | G55: 1 | H55: 1 | I55: 1 | J55: 1 | K55: 1 | L55: 1 | M55: 1 | N55: 1 | O55: 1
A56: Sarah | B56: Question 5 | C56: 0 | D56: 12.324698 | E56: 0 | F56: 'NA | G56: 'NA | H56: 'NA | I56: 'NA | J56: 'NA | K56: 'NA | L56: 'NA | M56: 'NA | N56: 'NA | O56: 'NA | P56: Answerability: The phrase 'this increase represents exactly 20% more than her score last month' is ambiguous - unclear if 96 = 1.2 * last month score or if increase amount = 0.2 * last month score, leading to different solutions. Secondary KC Alignment: Converting 20% to fraction is only mentioned in instructions, not integral to solution method. Synergy: The two knowledge components are not used in tandem - fraction conversion is superficial add-on rather than essential part of reverse percentage calculation. Grade Alignment: Mathematical complexity and ambiguous wording too advanced for Secondary O-level 1 students (age 13-14). Clarity: Ambiguous mathematical relationship makes problem statement unclear.
A57: Sarah | B57: Question 6 | C57: 0 | D57: 4.4525838 | E57: 1 | F57: 1 | G57: 1 | H57: 1 | I57: 1 | J57: 1 | K57: 0 | L57: 1 | M57: 1 | N57: 1 | O57: 1 | P57: Real-world feasibility: In table tennis, players do not hit the ball across distances of 2+ metres as described. Table tennis involves hitting a ball back and forth across a net on a small table (2.74m x 1.525m), not hitting balls across open distances. The scenario does not reflect how table tennis is actually played in reality.
A58: Sarah | B58: Question 7 | C58: 0 | D58: 5.0736182 | E58: 1 | F58: 1 | G58: 1 | H58: 1 | I58: 1 | J58: 0 | K58: 0 | L58: 1 | M58: 1 | N58: 1 | O58: 1 | P58: Grade alignment: This problem involves basic ratio concepts with decimals and simple decimal addition, which are typically covered at Primary 5-6 level, not Secondary O-level 1 which requires more advanced mathematical concepts. Real-world feasibility: Having 12.5 boys and 3.7 girls joining is unrealistic as you cannot have fractional people in real-world scenarios.
A59: Sarah | B59: Question 8 | C59: 0 | D59: 9.2630355 | E59: 1 | F59: 1 | G59: 1 | H59: 1 | I59: 1 | J59: 1 | K59: 1 | L59: 1 | M59: 1 | N59: 1 | O59: 1
A60: Sarah | B60: Question 9 | C60: 0 | D60: 4.5235174 | E60: 1 | F60: 1 | G60: 1 | H60: 1 | I60: 1 | J60: 0 | K60: 1 | L60: 1 | M60: 1 | N60: 1 | O60: 1 | P60: Grade Alignment: This problem is too elementary for Secondary O-level 1 students. Basic percentage calculations and fraction conversions are typically mastered in primary school (around Primary 5-6). O-level students would be expected to handle more complex percentage problems involving compound calculations, percentage change over time, or integration with advanced algebraic concepts.
A61: Sarah | B61: Question 10 | C61: 0 | D61: 10.678125 | E61: 0 | F61: 'NA | G61: 'NA | H61: 'NA | I61: 'NA | J61: 'NA | K61: 'NA | L61: 'NA | M61: 'NA | N61: 'NA | O61: 'NA | P61: Answerability: The phrase 'that time' is ambiguous - unclear if it refers to planned practice time or Monday's actual practice time. Primary KC Alignment: Due to ambiguous wording, the problem could be solved with simple addition (7/4 + 5/3) rather than requiring multiplication of improper fractions. Real-world feasibility: Practicing 7/4 = 175% and 5/3 = 167% of planned time is unrealistic - people cannot typically exceed planned practice time by such large amounts. Clarity: The ambiguous reference 'that time' makes the problem unclear to solve definitively.
A62: Sarah | B62: Question 11 | C62: 0 | D62: 9.9704163 | E62: 1 | F62: 1 | G62: 1 | H62: 1 | I62: 1 | J62: 1 | K62: 1 | L62: 1 | M62: 1 | N62: 1 | O62: 1
A63: Sarah | B63: Question 12 | C63: 0 | D63: 5.2519851 | E63: 1 | F63: 1 | G63: 1 | H63: 1 | I63: 1 | J63: 0 | K63: 0 | L63: 1 | M63: 1 | N63: 1 | O63: 1 | P63: Grade Alignment: The problem specifies Secondary O-level 1 but uses quadratic expressions (2x^2 + 3x + 5) which are typically introduced in later secondary years, not O-level 1. Real-World Plausibility: Mini-golf course booking costs represented by quadratic expressions like 2x^2 + 3x + 5 is unrealistic. Actual mini-golf venues typically charge fixed hourly rates or flat fees, not costs that increase quadratically with time.
A64: Sarah | B64: Question 13 | C64: 0 | D64: 9.4419153 | E64: 1 | F64: 1 | G64: 1 | H64: 1 | I64: 1 | J64: 1 | K64: 1 | L64: 1 | M64: 1 | N64: 1 | O64: 1
A65: Sarah | B65: Question 14 | C65: 0 | D65: 2.7431545 | E65: 1 | F65: 1 | G65: 1 | H65: 1 | I65: 1 | J65: 1 | K65: 1 | L65: 1 | M65: 1 | N65: 1 | O65: 1
A66: Sarah | B66: Question 15 | C66: 0 | D66: 5.1635518 | E66: 1 | F66: 1 | G66: 1 | H66: 1 | I66: 1 | J66: 0 | K66: 1 | L66: 1 | M66: 1 | N66: 1 | O66: 1 | P66: Grade alignment: This problem involves basic ratio concepts with simple fractions that would typically be taught at Primary 5-6 level in Singapore math curriculum, not Secondary O-level 1. The operations required (converting ratio to fraction form and multiplying fractions) are too elementary for Secondary O-level 1 students who should be working with more complex algebraic ratios, simultaneous equations, or advanced fraction applications.
A67: Sarah | B67: Question 16 | C67: 0 | D67: 9.3248615 | E67: 1 | F67: 1 | G67: 1 | H67: 1 | I67: 1 | J67: 1 | K67: 1 | L67: 1 | M67: 1 | N67: 1 | O67: 1
A68: Sarah | B68: Question 17 | C68: 0 | D68: 12.93443 | E68: 0 | F68: 'NA | G68: 'NA | H68: 'NA | I68: 'NA | J68: 'NA | K68: 'NA | L68: 'NA | M68: 'NA | N68: 'NA | O68: 'NA | P68: Answerability: Problem has illogical relationship - only 0.050 litres remain but Sarah drinks 0.075 litres, resulting in impossible negative amount (-0.025 litres). Primary KC Alignment: Division is by 0.100 litres, not by 10/100/1000 or their multiples as specified in primary knowledge component. Real-World Plausibility: Scenario impossible due to negative result - cannot drink more than what remains.
A69: Sarah | B69: Question 18 | C69: 0 | D69: 10.700334 | E69: 1 | F69: 1 | G69: 1 | H69: 1 | I69: 1 | J69: 1 | K69: 1 | L69: 1 | M69: 1 | N69: 0 | O69: 1 | P69: Language Quality: Missing article - should be 'This represents 35% of the total number of students in THE school'
A70: Sarah | B70: Question 19 | C70: 0 | D70: 2.6512437 | E70: 1 | F70: 1 | G70: 1 | H70: 1 | I70: 1 | J70: 1 | K70: 1 | L70: 1 | M70: 1 | N70: 1 | O70: 1
A71: Sarah | B71: Question 20 | C71: 0 | D71: 6.2599444 | E71: 1 | F71: 0 | G71: 1 | H71: 'NA | I71: 1 | J71: 'NA | K71: 1 | L71: 1 | M71: 1 | N71: 1 | O71: 1 | P71: Primary KC alignment: The problem can be solved directly using basic probability (9/30 = 3/10) without requiring addition of probabilities as the main solving method. The primary knowledge component should be the core difficulty driver. Synergy: Since addition of probabilities is not the primary solving approach, there is insufficient synergy between the intended primary and secondary knowledge components working in tandem. Grade alignment: This problem is too basic for Secondary O-level 3/4 students. Set theory concepts with Venn diagrams and basic probability calculations are typically covered in lower secondary levels (Secondary 1/2), not O-level 3/4 which requires more advanced probability concepts.
A72: Sarah | B72: Question 21 | C72: 0 | D72: 5.3412447 | E72: 1 | F72: 1 | G72: 1 | H72: 1 | I72: 1 | J72: 0 | K72: 1 | L72: 1 | M72: 1 | N72: 1 | O72: 1 | P72: Grade Alignment: This problem involves basic percentage calculations (15% increase) and simple addition, which are typically covered in Primary 5-6 or Secondary 1 at most basic level. For Secondary O-level 1 students, this problem is too elementary and does not challenge students appropriately for their grade level. O-level students should be working with more complex percentage problems involving compound changes, multiple percentage operations, or integration with algebraic concepts.
A73: Sarah | B73: Question 22 | C73: 0 | D73: 9.3305221 | E73: 1 | F73: 1 | G73: 1 | H73: 1 | I73: 1 | J73: 1 | K73: 1 | L73: 1 | M73: 1 | N73: 1 | O73: 1
A74: Sarah | B74: Question 23 | C74: 0 | D74: 6.0656612 | E74: 1 | F74: 1 | G74: 1 | H74: 0 | I74: 1 | J74: 0 | K74: 1 | L74: 1 | M74: 1 | N74: 1 | O74: 1 | P74: Synergy: The two parts (a) and (b) are independent calculations that do not require using results from one part to solve the other part. Finding median and range are separate statistical measures that can be calculated independently from the same dataset. Grade Alignment: Finding median and range are basic statistical concepts typically introduced at Primary 5-6 or Secondary 1 level in Singapore math syllabus, which is below the Secondary O-level 2 grade level. This problem lacks the complexity and advanced statistical concepts expected for Secondary O-level 2 students.
A75: Sarah | B75: Question 24 | C75: 0 | D75: 5.8493929 | E75: 1 | F75: 0 | G75: 1 | H75: 'NA | I75: 1 | J75: 'NA | K75: 1 | L75: 1 | M75: 1 | N75: 1 | O75: 1 | P75: Primary KC Alignment: The intended primary knowledge component is multiplying decimals by 10, 100, 1000 and their multiples. However, the problem requires multiplying decimals by single-digit numbers (10 and 20), not specifically by 10, 100, 1000 as standalone multipliers. The multiplication 0.815 × 10 in part (b) aligns, but parts (a) and (c) involve multiplying by 20, which is not a direct application of the intended primary KC focus on 10, 100, 1000 and their standard multiples.
A76: Sarah | B76: Question 25 | C76: 0 | D76: 11.308775 | E76: 1 | F76: 1 | G76: 1 | H76: 1 | I76: 1 | J76: 1 | K76: 1 | L76: 1 | M76: 1 | N76: 1 | O76: 1
A77: Sarah | B77: Question 26 | C77: 0 | D77: 9.2338698 | E77: 0 | F77: 'NA | G77: 'NA | H77: 'NA | I77: 'NA | J77: 'NA | K77: 'NA | L77: 'NA | M77: 'NA | N77: 'NA | O77: 'NA | P77: Answerability: Part (a) gives 12.450 / 10 = 1.245 metres per lap, but part (b) provides 10 different individual lap distances that sum to 12.457 metres, not 12.450 metres. This creates conflicting information making the problem unsolvable as stated. Primary KC Alignment: The division required is 12.450 / 10 = 1.245, which is simple division by 10, not division by multiples of 10/100/1000 as specified in the intended knowledge component. Real-world feasibility: Swimming competitions measure lap times, not individual lap distances. Pool lanes have fixed distances, so each lap would be exactly the same distance. Measuring different distances per lap (1.240 to 1.250 metres) is unrealistic. Synergy: The two knowledge components are used in separate, disconnected parts rather than in tandem. Part (a) uses division while parts (b) and (c) use ordering, but the results don't connect meaningfully. Conciseness and relevance: The total distance of 12.450 metres from part (a) becomes irrelevant once individual lap distances are provided in part (b), creating redundant information.

Sheet Compiled Votes
A1: Evaluator | B1: Question | C1: status | D1: response_time | E1: answerability | F1: primary_kc_alignment | G1: secondary_kc_alignment | H1: synergy | I1: topic_alignment | J1: grade_alignment | K1: real_world_feasibility | L1: clarity | M1: conciseness_and_relevance | N1: language_quality | O1: content_appropriateness
A2: TD | B2: Question 1 | C2: 0 | D2: 4.3597925 | E2: =ROUND(SUM(recreation_v2_6!E2,recreation_v2_7!E2,recreation_v2_8!E2,recreation_v2_9!E2,recreation_v2_10!E2)/COUNT(recreation_v2_6!E2,recreation_v2_7!E2,recreation_v2_8!E2,recreation_v2_9!E2,recreation_v2_10!E2),0) -> 1 | F2: =IF($E2=0, "NA", ROUND(SUM(recreation_v2_6!F2,recreation_v2_7!F2,recreation_v2_8!F2,recreation_v2_9!F2,recreation_v2_10!F2)/COUNT(recreation_v2_6!F2,recreation_v2_7!F2,recreation_v2_8!F2,recreation_v2_9!F2,recreation_v2_10!F2),0)) -> 1 | G2: =IF($E2=0,"NA",ROUND(SUM(recreation_v2_6!G2,recreation_v2_7!G2,recreation_v2_8!G2,recreation_v2_9!G2,recreation_v2_10!G2)/COUNT(recreation_v2_6!G2,recreation_v2_7!G2,recreation_v2_8!G2,recreation_v2_9!G2,recreation_v2_10!G2),0)) -> 1 | H2: =IF(AND(F2=1, G2=1),ROUND(SUM(recreation_v2_6!H2,recreation_v2_7!H2,recreation_v2_8!H2,recreation_v2_9!H2,recreation_v2_10!H2)/COUNT(recreation_v2_6!H2,recreation_v2_7!H2,recreation_v2_8!H2,recreation_v2_9!H2,recreation_v2_10!H2),0),"NA") -> 1 | I2: =IF($E2=0, "NA", ROUND(SUM(recreation_v2_6!I2,recreation_v2_7!I2,recreation_v2_8!I2,recreation_v2_9!I2,recreation_v2_10!I2)/COUNT(recreation_v2_6!I2,recreation_v2_7!I2,recreation_v2_8!I2,recreation_v2_9!I2,recreation_v2_10!I2),0)) -> 1 | J2: =IF(F2=1,ROUND(SUM(recreation_v2_6!J2,recreation_v2_7!J2,recreation_v2_8!J2,recreation_v2_9!J2,recreation_v2_10!J2)/COUNT(recreation_v2_6!J2,recreation_v2_7!J2,recreation_v2_8!J2,recreation_v2_9!J2,recreation_v2_10!J2),0),"NA") -> 0 | K2: =IF($E2=0, "NA", ROUND(SUM(recreation_v2_6!K2,recreation_v2_7!K2,recreation_v2_8!K2,recreation_v2_9!K2,recreation_v2_10!K2)/COUNT(recreation_v2_6!K2,recreation_v2_7!K2,recreation_v2_8!K2,recreation_v2_9!K2,recreation_v2_10!K2),0)) -> 1 | L2: =IF($E2=0,"NA",ROUND(SUM(recreation_v2_6!L2,recreation_v2_7!L2,recreation_v2_8!L2,recreation_v2_9!L2,recreation_v2_10!L2)/COUNT(recreation_v2_6!L2,recreation_v2_7!L2,recreation_v2_8!L2,recreation_v2_9!L2,recreation_v2_10!L2),0)) -> 1 | M2: =IF($E2=0, "NA", ROUND(SUM(recreation_v2_6!M2,recreation_v2_7!M2,recreation_v2_8!M2,recreation_v2_9!M2,recreation_v2_10!M2)/COUNT(recreation_v2_6!M2,recreation_v2_7!M2,recreation_v2_8!M2,recreation_v2_9!M2,recreation_v2_10!M2),0)) -> 1 | N2: =IF($E2=0,"NA",ROUND(SUM(recreation_v2_6!N2,recreation_v2_7!N2,recreation_v2_8!N2,recreation_v2_9!N2,recreation_v2_10!N2)/COUNT(recreation_v2_6!N2,recreation_v2_7!N2,recreation_v2_8!N2,recreation_v2_9!N2,recreation_v2_10!N2),0)) -> 1 | O2: =IF($E2=0, "NA", ROUND(SUM(recreation_v2_6!O2,recreation_v2_7!O2,recreation_v2_8!O2,recreation_v2_9!O2,recreation_v2_10!O2)/COUNT(recreation_v2_6!O2,recreation_v2_7!O2,recreation_v2_8!O2,recreation_v2_9!O2,recreation_v2_10!O2),0)) -> 1
A3: TD | B3: Question 2 | C3: 0 | D3: 10.840834 | E3: =ROUND(SUM(recreation_v2_6!E3,recreation_v2_7!E3,recreation_v2_8!E3,recreation_v2_9!E3,recreation_v2_10!E3)/COUNT(recreation_v2_6!E3,recreation_v2_7!E3,recreation_v2_8!E3,recreation_v2_9!E3,recreation_v2_10!E3),0) -> 1 | F3: =IF($E3=0, "NA", ROUND(SUM(recreation_v2_6!F3,recreation_v2_7!F3,recreation_v2_8!F3,recreation_v2_9!F3,recreation_v2_10!F3)/COUNT(recreation_v2_6!F3,recreation_v2_7!F3,recreation_v2_8!F3,recreation_v2_9!F3,recreation_v2_10!F3),0)) -> 0 | G3: =IF($E3=0,"NA",ROUND(SUM(recreation_v2_6!G3,recreation_v2_7!G3,recreation_v2_8!G3,recreation_v2_9!G3,recreation_v2_10!G3)/COUNT(recreation_v2_6!G3,recreation_v2_7!G3,recreation_v2_8!G3,recreation_v2_9!G3,recreation_v2_10!G3),0)) -> 1 | H3: =IF(AND(F3=1, G3=1),ROUND(SUM(recreation_v2_6!H3,recreation_v2_7!H3,recreation_v2_8!H3,recreation_v2_9!H3,recreation_v2_10!H3)/COUNT(recreation_v2_6!H3,recreation_v2_7!H3,recreation_v2_8!H3,recreation_v2_9!H3,recreation_v2_10!H3),0),"NA") -> NA | I3: =IF($E3=0, "NA", ROUND(SUM(recreation_v2_6!I3,recreation_v2_7!I3,recreation_v2_8!I3,recreation_v2_9!I3,recreation_v2_10!I3)/COUNT(recreation_v2_6!I3,recreation_v2_7!I3,recreation_v2_8!I3,recreation_v2_9!I3,recreation_v2_10!I3),0)) -> 1 | J3: =IF(F3=1,ROUND(SUM(recreation_v2_6!J3,recreation_v2_7!J3,recreation_v2_8!J3,recreation_v2_9!J3,recreation_v2_10!J3)/COUNT(recreation_v2_6!J3,recreation_v2_7!J3,recreation_v2_8!J3,recreation_v2_9!J3,recreation_v2_10!J3),0),"NA") -> NA | K3: =IF($E3=0, "NA", ROUND(SUM(recreation_v2_6!K3,recreation_v2_7!K3,recreation_v2_8!K3,recreation_v2_9!K3,recreation_v2_10!K3)/COUNT(recreation_v2_6!K3,recreation_v2_7!K3,recreation_v2_8!K3,recreation_v2_9!K3,recreation_v2_10!K3),0)) -> 1 | L3: =IF($E3=0,"NA",ROUND(SUM(recreation_v2_6!L3,recreation_v2_7!L3,recreation_v2_8!L3,recreation_v2_9!L3,recreation_v2_10!L3)/COUNT(recreation_v2_6!L3,recreation_v2_7!L3,recreation_v2_8!L3,recreation_v2_9!L3,recreation_v2_10!L3),0)) -> 1 | M3: =IF($E3=0, "NA", ROUND(SUM(recreation_v2_6!M3,recreation_v2_7!M3,recreation_v2_8!M3,recreation_v2_9!M3,recreation_v2_10!M3)/COUNT(recreation_v2_6!M3,recreation_v2_7!M3,recreation_v2_8!M3,recreation_v2_9!M3,recreation_v2_10!M3),0)) -> 1 | N3: =IF($E3=0,"NA",ROUND(SUM(recreation_v2_6!N3,recreation_v2_7!N3,recreation_v2_8!N3,recreation_v2_9!N3,recreation_v2_10!N3)/COUNT(recreation_v2_6!N3,recreation_v2_7!N3,recreation_v2_8!N3,recreation_v2_9!N3,recreation_v2_10!N3),0)) -> 1 | O3: =IF($E3=0, "NA", ROUND(SUM(recreation_v2_6!O3,recreation_v2_7!O3,recreation_v2_8!O3,recreation_v2_9!O3,recreation_v2_10!O3)/COUNT(recreation_v2_6!O3,recreation_v2_7!O3,recreation_v2_8!O3,recreation_v2_9!O3,recreation_v2_10!O3),0)) -> 1
A4: TD | B4: Question 3 | C4: 0 | D4: 7.0765119 | E4: =ROUND(SUM(recreation_v2_6!E4,recreation_v2_7!E4,recreation_v2_8!E4,recreation_v2_9!E4,recreation_v2_10!E4)/COUNT(recreation_v2_6!E4,recreation_v2_7!E4,recreation_v2_8!E4,recreation_v2_9!E4,recreation_v2_10!E4),0) -> 1 | F4: =IF($E4=0, "NA", ROUND(SUM(recreation_v2_6!F4,recreation_v2_7!F4,recreation_v2_8!F4,recreation_v2_9!F4,recreation_v2_10!F4)/COUNT(recreation_v2_6!F4,recreation_v2_7!F4,recreation_v2_8!F4,recreation_v2_9!F4,recreation_v2_10!F4),0)) -> 1 | G4: =IF($E4=0,"NA",ROUND(SUM(recreation_v2_6!G4,recreation_v2_7!G4,recreation_v2_8!G4,recreation_v2_9!G4,recreation_v2_10!G4)/COUNT(recreation_v2_6!G4,recreation_v2_7!G4,recreation_v2_8!G4,recreation_v2_9!G4,recreation_v2_10!G4),0)) -> 1 | H4: =IF(AND(F4=1, G4=1),ROUND(SUM(recreation_v2_6!H4,recreation_v2_7!H4,recreation_v2_8!H4,recreation_v2_9!H4,recreation_v2_10!H4)/COUNT(recreation_v2_6!H4,recreation_v2_7!H4,recreation_v2_8!H4,recreation_v2_9!H4,recreation_v2_10!H4),0),"NA") -> 1 | I4: =IF($E4=0, "NA", ROUND(SUM(recreation_v2_6!I4,recreation_v2_7!I4,recreation_v2_8!I4,recreation_v2_9!I4,recreation_v2_10!I4)/COUNT(recreation_v2_6!I4,recreation_v2_7!I4,recreation_v2_8!I4,recreation_v2_9!I4,recreation_v2_10!I4),0)) -> 1 | J4: =IF(F4=1,ROUND(SUM(recreation_v2_6!J4,recreation_v2_7!J4,recreation_v2_8!J4,recreation_v2_9!J4,recreation_v2_10!J4)/COUNT(recreation_v2_6!J4,recreation_v2_7!J4,recreation_v2_8!J4,recreation_v2_9!J4,recreation_v2_10!J4),0),"NA") -> 1 | K4: =IF($E4=0, "NA", ROUND(SUM(recreation_v2_6!K4,recreation_v2_7!K4,recreation_v2_8!K4,recreation_v2_9!K4,recreation_v2_10!K4)/COUNT(recreation_v2_6!K4,recreation_v2_7!K4,recreation_v2_8!K4,recreation_v2_9!K4,recreation_v2_10!K4),0)) -> 1 | L4: =IF($E4=0,"NA",ROUND(SUM(recreation_v2_6!L4,recreation_v2_7!L4,recreation_v2_8!L4,recreation_v2_9!L4,recreation_v2_10!L4)/COUNT(recreation_v2_6!L4,recreation_v2_7!L4,recreation_v2_8!L4,recreation_v2_9!L4,recreation_v2_10!L4),0)) -> 0 | M4: =IF($E4=0, "NA", ROUND(SUM(recreation_v2_6!M4,recreation_v2_7!M4,recreation_v2_8!M4,recreation_v2_9!M4,recreation_v2_10!M4)/COUNT(recreation_v2_6!M4,recreation_v2_7!M4,recreation_v2_8!M4,recreation_v2_9!M4,recreation_v2_10!M4),0)) -> 1 | N4: =IF($E4=0,"NA",ROUND(SUM(recreation_v2_6!N4,recreation_v2_7!N4,recreation_v2_8!N4,recreation_v2_9!N4,recreation_v2_10!N4)/COUNT(recreation_v2_6!N4,recreation_v2_7!N4,recreation_v2_8!N4,recreation_v2_9!N4,recreation_v2_10!N4),0)) -> 1 | O4: =IF($E4=0, "NA", ROUND(SUM(recreation_v2_6!O4,recreation_v2_7!O4,recreation_v2_8!O4,recreation_v2_9!O4,recreation_v2_10!O4)/COUNT(recreation_v2_6!O4,recreation_v2_7!O4,recreation_v2_8!O4,recreation_v2_9!O4,recreation_v2_10!O4),0)) -> 1
A5: TD | B5: Question 4 | C5: 0 | D5: 2.7348113 | E5: =ROUND(SUM(recreation_v2_6!E5,recreation_v2_7!E5,recreation_v2_8!E5,recreation_v2_9!E5,recreation_v2_10!E5)/COUNT(recreation_v2_6!E5,recreation_v2_7!E5,recreation_v2_8!E5,recreation_v2_9!E5,recreation_v2_10!E5),0) -> 1 | F5: =IF($E5=0, "NA", ROUND(SUM(recreation_v2_6!F5,recreation_v2_7!F5,recreation_v2_8!F5,recreation_v2_9!F5,recreation_v2_10!F5)/COUNT(recreation_v2_6!F5,recreation_v2_7!F5,recreation_v2_8!F5,recreation_v2_9!F5,recreation_v2_10!F5),0)) -> 1 | G5: =IF($E5=0,"NA",ROUND(SUM(recreation_v2_6!G5,recreation_v2_7!G5,recreation_v2_8!G5,recreation_v2_9!G5,recreation_v2_10!G5)/COUNT(recreation_v2_6!G5,recreation_v2_7!G5,recreation_v2_8!G5,recreation_v2_9!G5,recreation_v2_10!G5),0)) -> 1 | H5: =IF(AND(F5=1, G5=1),ROUND(SUM(recreation_v2_6!H5,recreation_v2_7!H5,recreation_v2_8!H5,recreation_v2_9!H5,recreation_v2_10!H5)/COUNT(recreation_v2_6!H5,recreation_v2_7!H5,recreation_v2_8!H5,recreation_v2_9!H5,recreation_v2_10!H5),0),"NA") -> 1 | I5: =IF($E5=0, "NA", ROUND(SUM(recreation_v2_6!I5,recreation_v2_7!I5,recreation_v2_8!I5,recreation_v2_9!I5,recreation_v2_10!I5)/COUNT(recreation_v2_6!I5,recreation_v2_7!I5,recreation_v2_8!I5,recreation_v2_9!I5,recreation_v2_10!I5),0)) -> 1 | J5: =IF(F5=1,ROUND(SUM(recreation_v2_6!J5,recreation_v2_7!J5,recreation_v2_8!J5,recreation_v2_9!J5,recreation_v2_10!J5)/COUNT(recreation_v2_6!J5,recreation_v2_7!J5,recreation_v2_8!J5,recreation_v2_9!J5,recreation_v2_10!J5),0),"NA") -> 1 | K5: =IF($E5=0, "NA", ROUND(SUM(recreation_v2_6!K5,recreation_v2_7!K5,recreation_v2_8!K5,recreation_v2_9!K5,recreation_v2_10!K5)/COUNT(recreation_v2_6!K5,recreation_v2_7!K5,recreation_v2_8!K5,recreation_v2_9!K5,recreation_v2_10!K5),0)) -> 1 | L5: =IF($E5=0,"NA",ROUND(SUM(recreation_v2_6!L5,recreation_v2_7!L5,recreation_v2_8!L5,recreation_v2_9!L5,recreation_v2_10!L5)/COUNT(recreation_v2_6!L5,recreation_v2_7!L5,recreation_v2_8!L5,recreation_v2_9!L5,recreation_v2_10!L5),0)) -> 1 | M5: =IF($E5=0, "NA", ROUND(SUM(recreation_v2_6!M5,recreation_v2_7!M5,recreation_v2_8!M5,recreation_v2_9!M5,recreation_v2_10!M5)/COUNT(recreation_v2_6!M5,recreation_v2_7!M5,recreation_v2_8!M5,recreation_v2_9!M5,recreation_v2_10!M5),0)) -> 1 | N5: =IF($E5=0,"NA",ROUND(SUM(recreation_v2_6!N5,recreation_v2_7!N5,recreation_v2_8!N5,recreation_v2_9!N5,recreation_v2_10!N5)/COUNT(recreation_v2_6!N5,recreation_v2_7!N5,recreation_v2_8!N5,recreation_v2_9!N5,recreation_v2_10!N5),0)) -> 1 | O5: =IF($E5=0, "NA", ROUND(SUM(recreation_v2_6!O5,recreation_v2_7!O5,recreation_v2_8!O5,recreation_v2_9!O5,recreation_v2_10!O5)/COUNT(recreation_v2_6!O5,recreation_v2_7!O5,recreation_v2_8!O5,recreation_v2_9!O5,recreation_v2_10!O5),0)) -> 1
A6: TD | B6: Question 5 | C6: 0 | D6: 11.202191 | E6: =ROUND(SUM(recreation_v2_6!E6,recreation_v2_7!E6,recreation_v2_8!E6,recreation_v2_9!E6,recreation_v2_10!E6)/COUNT(recreation_v2_6!E6,recreation_v2_7!E6,recreation_v2_8!E6,recreation_v2_9!E6,recreation_v2_10!E6),0) -> 1 | F6: =IF($E6=0, "NA", ROUND(SUM(recreation_v2_6!F6,recreation_v2_7!F6,recreation_v2_8!F6,recreation_v2_9!F6,recreation_v2_10!F6)/COUNT(recreation_v2_6!F6,recreation_v2_7!F6,recreation_v2_8!F6,recreation_v2_9!F6,recreation_v2_10!F6),0)) -> 1 | G6: =IF($E6=0,"NA",ROUND(SUM(recreation_v2_6!G6,recreation_v2_7!G6,recreation_v2_8!G6,recreation_v2_9!G6,recreation_v2_10!G6)/COUNT(recreation_v2_6!G6,recreation_v2_7!G6,recreation_v2_8!G6,recreation_v2_9!G6,recreation_v2_10!G6),0)) -> 1 | H6: =IF(AND(F6=1, G6=1),ROUND(SUM(recreation_v2_6!H6,recreation_v2_7!H6,recreation_v2_8!H6,recreation_v2_9!H6,recreation_v2_10!H6)/COUNT(recreation_v2_6!H6,recreation_v2_7!H6,recreation_v2_8!H6,recreation_v2_9!H6,recreation_v2_10!H6),0),"NA") -> 1 | I6: =IF($E6=0, "NA", ROUND(SUM(recreation_v2_6!I6,recreation_v2_7!I6,recreation_v2_8!I6,recreation_v2_9!I6,recreation_v2_10!I6)/COUNT(recreation_v2_6!I6,recreation_v2_7!I6,recreation_v2_8!I6,recreation_v2_9!I6,recreation_v2_10!I6),0)) -> 1 | J6: =IF(F6=1,ROUND(SUM(recreation_v2_6!J6,recreation_v2_7!J6,recreation_v2_8!J6,recreation_v2_9!J6,recreation_v2_10!J6)/COUNT(recreation_v2_6!J6,recreation_v2_7!J6,recreation_v2_8!J6,recreation_v2_9!J6,recreation_v2_10!J6),0),"NA") -> 1 | K6: =IF($E6=0, "NA", ROUND(SUM(recreation_v2_6!K6,recreation_v2_7!K6,recreation_v2_8!K6,recreation_v2_9!K6,recreation_v2_10!K6)/COUNT(recreation_v2_6!K6,recreation_v2_7!K6,recreation_v2_8!K6,recreation_v2_9!K6,recreation_v2_10!K6),0)) -> 1 | L6: =IF($E6=0,"NA",ROUND(SUM(recreation_v2_6!L6,recreation_v2_7!L6,recreation_v2_8!L6,recreation_v2_9!L6,recreation_v2_10!L6)/COUNT(recreation_v2_6!L6,recreation_v2_7!L6,recreation_v2_8!L6,recreation_v2_9!L6,recreation_v2_10!L6),0)) -> 1 | M6: =IF($E6=0, "NA", ROUND(SUM(recreation_v2_6!M6,recreation_v2_7!M6,recreation_v2_8!M6,recreation_v2_9!M6,recreation_v2_10!M6)/COUNT(recreation_v2_6!M6,recreation_v2_7!M6,recreation_v2_8!M6,recreation_v2_9!M6,recreation_v2_10!M6),0)) -> 1 | N6: =IF($E6=0,"NA",ROUND(SUM(recreation_v2_6!N6,recreation_v2_7!N6,recreation_v2_8!N6,recreation_v2_9!N6,recreation_v2_10!N6)/COUNT(recreation_v2_6!N6,recreation_v2_7!N6,recreation_v2_8!N6,recreation_v2_9!N6,recreation_v2_10!N6),0)) -> 1 | O6: =IF($E6=0, "NA", ROUND(SUM(recreation_v2_6!O6,recreation_v2_7!O6,recreation_v2_8!O6,recreation_v2_9!O6,recreation_v2_10!O6)/COUNT(recreation_v2_6!O6,recreation_v2_7!O6,recreation_v2_8!O6,recreation_v2_9!O6,recreation_v2_10!O6),0)) -> 1
A7: TD | B7: Question 6 | C7: 0 | D7: 6.7938976 | E7: =ROUND(SUM(recreation_v2_6!E7,recreation_v2_7!E7,recreation_v2_8!E7,recreation_v2_9!E7,recreation_v2_10!E7)/COUNT(recreation_v2_6!E7,recreation_v2_7!E7,recreation_v2_8!E7,recreation_v2_9!E7,recreation_v2_10!E7),0) -> 1 | F7: =IF($E7=0, "NA", ROUND(SUM(recreation_v2_6!F7,recreation_v2_7!F7,recreation_v2_8!F7,recreation_v2_9!F7,recreation_v2_10!F7)/COUNT(recreation_v2_6!F7,recreation_v2_7!F7,recreation_v2_8!F7,recreation_v2_9!F7,recreation_v2_10!F7),0)) -> 1 | G7: =IF($E7=0,"NA",ROUND(SUM(recreation_v2_6!G7,recreation_v2_7!G7,recreation_v2_8!G7,recreation_v2_9!G7,recreation_v2_10!G7)/COUNT(recreation_v2_6!G7,recreation_v2_7!G7,recreation_v2_8!G7,recreation_v2_9!G7,recreation_v2_10!G7),0)) -> 1 | H7: =IF(AND(F7=1, G7=1),ROUND(SUM(recreation_v2_6!H7,recreation_v2_7!H7,recreation_v2_8!H7,recreation_v2_9!H7,recreation_v2_10!H7)/COUNT(recreation_v2_6!H7,recreation_v2_7!H7,recreation_v2_8!H7,recreation_v2_9!H7,recreation_v2_10!H7),0),"NA") -> 1 | I7: =IF($E7=0, "NA", ROUND(SUM(recreation_v2_6!I7,recreation_v2_7!I7,recreation_v2_8!I7,recreation_v2_9!I7,recreation_v2_10!I7)/COUNT(recreation_v2_6!I7,recreation_v2_7!I7,recreation_v2_8!I7,recreation_v2_9!I7,recreation_v2_10!I7),0)) -> 1 | J7: =IF(F7=1,ROUND(SUM(recreation_v2_6!J7,recreation_v2_7!J7,recreation_v2_8!J7,recreation_v2_9!J7,recreation_v2_10!J7)/COUNT(recreation_v2_6!J7,recreation_v2_7!J7,recreation_v2_8!J7,recreation_v2_9!J7,recreation_v2_10!J7),0),"NA") -> 1 | K7: =IF($E7=0, "NA", ROUND(SUM(recreation_v2_6!K7,recreation_v2_7!K7,recreation_v2_8!K7,recreation_v2_9!K7,recreation_v2_10!K7)/COUNT(recreation_v2_6!K7,recreation_v2_7!K7,recreation_v2_8!K7,recreation_v2_9!K7,recreation_v2_10!K7),0)) -> 1 | L7: =IF($E7=0,"NA",ROUND(SUM(recreation_v2_6!L7,recreation_v2_7!L7,recreation_v2_8!L7,recreation_v2_9!L7,recreation_v2_10!L7)/COUNT(recreation_v2_6!L7,recreation_v2_7!L7,recreation_v2_8!L7,recreation_v2_9!L7,recreation_v2_10!L7),0)) -> 1 | M7: =IF($E7=0, "NA", ROUND(SUM(recreation_v2_6!M7,recreation_v2_7!M7,recreation_v2_8!M7,recreation_v2_9!M7,recreation_v2_10!M7)/COUNT(recreation_v2_6!M7,recreation_v2_7!M7,recreation_v2_8!M7,recreation_v2_9!M7,recreation_v2_10!M7),0)) -> 1 | N7: =IF($E7=0,"NA",ROUND(SUM(recreation_v2_6!N7,recreation_v2_7!N7,recreation_v2_8!N7,recreation_v2_9!N7,recreation_v2_10!N7)/COUNT(recreation_v2_6!N7,recreation_v2_7!N7,recreation_v2_8!N7,recreation_v2_9!N7,recreation_v2_10!N7),0)) -> 1 | O7: =IF($E7=0, "NA", ROUND(SUM(recreation_v2_6!O7,recreation_v2_7!O7,recreation_v2_8!O7,recreation_v2_9!O7,recreation_v2_10!O7)/COUNT(recreation_v2_6!O7,recreation_v2_7!O7,recreation_v2_8!O7,recreation_v2_9!O7,recreation_v2_10!O7),0)) -> 1
A8: TD | B8: Question 7 | C8: 0 | D8: 2.7297006 | E8: =ROUND(SUM(recreation_v2_6!E8,recreation_v2_7!E8,recreation_v2_8!E8,recreation_v2_9!E8,recreation_v2_10!E8)/COUNT(recreation_v2_6!E8,recreation_v2_7!E8,recreation_v2_8!E8,recreation_v2_9!E8,recreation_v2_10!E8),0) -> 1 | F8: =IF($E8=0, "NA", ROUND(SUM(recreation_v2_6!F8,recreation_v2_7!F8,recreation_v2_8!F8,recreation_v2_9!F8,recreation_v2_10!F8)/COUNT(recreation_v2_6!F8,recreation_v2_7!F8,recreation_v2_8!F8,recreation_v2_9!F8,recreation_v2_10!F8),0)) -> 1 | G8: =IF($E8=0,"NA",ROUND(SUM(recreation_v2_6!G8,recreation_v2_7!G8,recreation_v2_8!G8,recreation_v2_9!G8,recreation_v2_10!G8)/COUNT(recreation_v2_6!G8,recreation_v2_7!G8,recreation_v2_8!G8,recreation_v2_9!G8,recreation_v2_10!G8),0)) -> 1 | H8: =IF(AND(F8=1, G8=1),ROUND(SUM(recreation_v2_6!H8,recreation_v2_7!H8,recreation_v2_8!H8,recreation_v2_9!H8,recreation_v2_10!H8)/COUNT(recreation_v2_6!H8,recreation_v2_7!H8,recreation_v2_8!H8,recreation_v2_9!H8,recreation_v2_10!H8),0),"NA") -> 1 | I8: =IF($E8=0, "NA", ROUND(SUM(recreation_v2_6!I8,recreation_v2_7!I8,recreation_v2_8!I8,recreation_v2_9!I8,recreation_v2_10!I8)/COUNT(recreation_v2_6!I8,recreation_v2_7!I8,recreation_v2_8!I8,recreation_v2_9!I8,recreation_v2_10!I8),0)) -> 1 | J8: =IF(F8=1,ROUND(SUM(recreation_v2_6!J8,recreation_v2_7!J8,recreation_v2_8!J8,recreation_v2_9!J8,recreation_v2_10!J8)/COUNT(recreation_v2_6!J8,recreation_v2_7!J8,recreation_v2_8!J8,recreation_v2_9!J8,recreation_v2_10!J8),0),"NA") -> 1 | K8: =IF($E8=0, "NA", ROUND(SUM(recreation_v2_6!K8,recreation_v2_7!K8,recreation_v2_8!K8,recreation_v2_9!K8,recreation_v2_10!K8)/COUNT(recreation_v2_6!K8,recreation_v2_7!K8,recreation_v2_8!K8,recreation_v2_9!K8,recreation_v2_10!K8),0)) -> 1 | L8: =IF($E8=0,"NA",ROUND(SUM(recreation_v2_6!L8,recreation_v2_7!L8,recreation_v2_8!L8,recreation_v2_9!L8,recreation_v2_10!L8)/COUNT(recreation_v2_6!L8,recreation_v2_7!L8,recreation_v2_8!L8,recreation_v2_9!L8,recreation_v2_10!L8),0)) -> 1 | M8: =IF($E8=0, "NA", ROUND(SUM(recreation_v2_6!M8,recreation_v2_7!M8,recreation_v2_8!M8,recreation_v2_9!M8,recreation_v2_10!M8)/COUNT(recreation_v2_6!M8,recreation_v2_7!M8,recreation_v2_8!M8,recreation_v2_9!M8,recreation_v2_10!M8),0)) -> 1 | N8: =IF($E8=0,"NA",ROUND(SUM(recreation_v2_6!N8,recreation_v2_7!N8,recreation_v2_8!N8,recreation_v2_9!N8,recreation_v2_10!N8)/COUNT(recreation_v2_6!N8,recreation_v2_7!N8,recreation_v2_8!N8,recreation_v2_9!N8,recreation_v2_10!N8),0)) -> 1 | O8: =IF($E8=0, "NA", ROUND(SUM(recreation_v2_6!O8,recreation_v2_7!O8,recreation_v2_8!O8,recreation_v2_9!O8,recreation_v2_10!O8)/COUNT(recreation_v2_6!O8,recreation_v2_7!O8,recreation_v2_8!O8,recreation_v2_9!O8,recreation_v2_10!O8),0)) -> 1
A9: TD | B9: Question 8 | C9: 0 | D9: 2.737859 | E9: =ROUND(SUM(recreation_v2_6!E9,recreation_v2_7!E9,recreation_v2_8!E9,recreation_v2_9!E9,recreation_v2_10!E9)/COUNT(recreation_v2_6!E9,recreation_v2_7!E9,recreation_v2_8!E9,recreation_v2_9!E9,recreation_v2_10!E9),0) -> 1 | F9: =IF($E9=0, "NA", ROUND(SUM(recreation_v2_6!F9,recreation_v2_7!F9,recreation_v2_8!F9,recreation_v2_9!F9,recreation_v2_10!F9)/COUNT(recreation_v2_6!F9,recreation_v2_7!F9,recreation_v2_8!F9,recreation_v2_9!F9,recreation_v2_10!F9),0)) -> 1 | G9: =IF($E9=0,"NA",ROUND(SUM(recreation_v2_6!G9,recreation_v2_7!G9,recreation_v2_8!G9,recreation_v2_9!G9,recreation_v2_10!G9)/COUNT(recreation_v2_6!G9,recreation_v2_7!G9,recreation_v2_8!G9,recreation_v2_9!G9,recreation_v2_10!G9),0)) -> 1 | H9: =IF(AND(F9=1, G9=1),ROUND(SUM(recreation_v2_6!H9,recreation_v2_7!H9,recreation_v2_8!H9,recreation_v2_9!H9,recreation_v2_10!H9)/COUNT(recreation_v2_6!H9,recreation_v2_7!H9,recreation_v2_8!H9,recreation_v2_9!H9,recreation_v2_10!H9),0),"NA") -> 1 | I9: =IF($E9=0, "NA", ROUND(SUM(recreation_v2_6!I9,recreation_v2_7!I9,recreation_v2_8!I9,recreation_v2_9!I9,recreation_v2_10!I9)/COUNT(recreation_v2_6!I9,recreation_v2_7!I9,recreation_v2_8!I9,recreation_v2_9!I9,recreation_v2_10!I9),0)) -> 1 | J9: =IF(F9=1,ROUND(SUM(recreation_v2_6!J9,recreation_v2_7!J9,recreation_v2_8!J9,recreation_v2_9!J9,recreation_v2_10!J9)/COUNT(recreation_v2_6!J9,recreation_v2_7!J9,recreation_v2_8!J9,recreation_v2_9!J9,recreation_v2_10!J9),0),"NA") -> 1 | K9: =IF($E9=0, "NA", ROUND(SUM(recreation_v2_6!K9,recreation_v2_7!K9,recreation_v2_8!K9,recreation_v2_9!K9,recreation_v2_10!K9)/COUNT(recreation_v2_6!K9,recreation_v2_7!K9,recreation_v2_8!K9,recreation_v2_9!K9,recreation_v2_10!K9),0)) -> 1 | L9: =IF($E9=0,"NA",ROUND(SUM(recreation_v2_6!L9,recreation_v2_7!L9,recreation_v2_8!L9,recreation_v2_9!L9,recreation_v2_10!L9)/COUNT(recreation_v2_6!L9,recreation_v2_7!L9,recreation_v2_8!L9,recreation_v2_9!L9,recreation_v2_10!L9),0)) -> 1 | M9: =IF($E9=0, "NA", ROUND(SUM(recreation_v2_6!M9,recreation_v2_7!M9,recreation_v2_8!M9,recreation_v2_9!M9,recreation_v2_10!M9)/COUNT(recreation_v2_6!M9,recreation_v2_7!M9,recreation_v2_8!M9,recreation_v2_9!M9,recreation_v2_10!M9),0)) -> 1 | N9: =IF($E9=0,"NA",ROUND(SUM(recreation_v2_6!N9,recreation_v2_7!N9,recreation_v2_8!N9,recreation_v2_9!N9,recreation_v2_10!N9)/COUNT(recreation_v2_6!N9,recreation_v2_7!N9,recreation_v2_8!N9,recreation_v2_9!N9,recreation_v2_10!N9),0)) -> 1 | O9: =IF($E9=0, "NA", ROUND(SUM(recreation_v2_6!O9,recreation_v2_7!O9,recreation_v2_8!O9,recreation_v2_9!O9,recreation_v2_10!O9)/COUNT(recreation_v2_6!O9,recreation_v2_7!O9,recreation_v2_8!O9,recreation_v2_9!O9,recreation_v2_10!O9),0)) -> 1
A10: TD | B10: Question 9 | C10: 0 | D10: 5.2020807 | E10: =ROUND(SUM(recreation_v2_6!E10,recreation_v2_7!E10,recreation_v2_8!E10,recreation_v2_9!E10,recreation_v2_10!E10)/COUNT(recreation_v2_6!E10,recreation_v2_7!E10,recreation_v2_8!E10,recreation_v2_9!E10,recreation_v2_10!E10),0) -> 1 | F10: =IF($E10=0, "NA", ROUND(SUM(recreation_v2_6!F10,recreation_v2_7!F10,recreation_v2_8!F10,recreation_v2_9!F10,recreation_v2_10!F10)/COUNT(recreation_v2_6!F10,recreation_v2_7!F10,recreation_v2_8!F10,recreation_v2_9!F10,recreation_v2_10!F10),0)) -> 1 | G10: =IF($E10=0,"NA",ROUND(SUM(recreation_v2_6!G10,recreation_v2_7!G10,recreation_v2_8!G10,recreation_v2_9!G10,recreation_v2_10!G10)/COUNT(recreation_v2_6!G10,recreation_v2_7!G10,recreation_v2_8!G10,recreation_v2_9!G10,recreation_v2_10!G10),0)) -> 1 | H10: =IF(AND(F10=1, G10=1),ROUND(SUM(recreation_v2_6!H10,recreation_v2_7!H10,recreation_v2_8!H10,recreation_v2_9!H10,recreation_v2_10!H10)/COUNT(recreation_v2_6!H10,recreation_v2_7!H10,recreation_v2_8!H10,recreation_v2_9!H10,recreation_v2_10!H10),0),"NA") -> 1 | I10: =IF($E10=0, "NA", ROUND(SUM(recreation_v2_6!I10,recreation_v2_7!I10,recreation_v2_8!I10,recreation_v2_9!I10,recreation_v2_10!I10)/COUNT(recreation_v2_6!I10,recreation_v2_7!I10,recreation_v2_8!I10,recreation_v2_9!I10,recreation_v2_10!I10),0)) -> 1 | J10: =IF(F10=1,ROUND(SUM(recreation_v2_6!J10,recreation_v2_7!J10,recreation_v2_8!J10,recreation_v2_9!J10,recreation_v2_10!J10)/COUNT(recreation_v2_6!J10,recreation_v2_7!J10,recreation_v2_8!J10,recreation_v2_9!J10,recreation_v2_10!J10),0),"NA") -> 0 | K10: =IF($E10=0, "NA", ROUND(SUM(recreation_v2_6!K10,recreation_v2_7!K10,recreation_v2_8!K10,recreation_v2_9!K10,recreation_v2_10!K10)/COUNT(recreation_v2_6!K10,recreation_v2_7!K10,recreation_v2_8!K10,recreation_v2_9!K10,recreation_v2_10!K10),0)) -> 0 | L10: =IF($E10=0,"NA",ROUND(SUM(recreation_v2_6!L10,recreation_v2_7!L10,recreation_v2_8!L10,recreation_v2_9!L10,recreation_v2_10!L10)/COUNT(recreation_v2_6!L10,recreation_v2_7!L10,recreation_v2_8!L10,recreation_v2_9!L10,recreation_v2_10!L10),0)) -> 1 | M10: =IF($E10=0, "NA", ROUND(SUM(recreation_v2_6!M10,recreation_v2_7!M10,recreation_v2_8!M10,recreation_v2_9!M10,recreation_v2_10!M10)/COUNT(recreation_v2_6!M10,recreation_v2_7!M10,recreation_v2_8!M10,recreation_v2_9!M10,recreation_v2_10!M10),0)) -> 1 | N10: =IF($E10=0,"NA",ROUND(SUM(recreation_v2_6!N10,recreation_v2_7!N10,recreation_v2_8!N10,recreation_v2_9!N10,recreation_v2_10!N10)/COUNT(recreation_v2_6!N10,recreation_v2_7!N10,recreation_v2_8!N10,recreation_v2_9!N10,recreation_v2_10!N10),0)) -> 1 | O10: =IF($E10=0, "NA", ROUND(SUM(recreation_v2_6!O10,recreation_v2_7!O10,recreation_v2_8!O10,recreation_v2_9!O10,recreation_v2_10!O10)/COUNT(recreation_v2_6!O10,recreation_v2_7!O10,recreation_v2_8!O10,recreation_v2_9!O10,recreation_v2_10!O10),0)) -> 1
A11: TD | B11: Question 10 | C11: 0 | D11: 2.8171892 | E11: =ROUND(SUM(recreation_v2_6!E11,recreation_v2_7!E11,recreation_v2_8!E11,recreation_v2_9!E11,recreation_v2_10!E11)/COUNT(recreation_v2_6!E11,recreation_v2_7!E11,recreation_v2_8!E11,recreation_v2_9!E11,recreation_v2_10!E11),0) -> 1 | F11: =IF($E11=0, "NA", ROUND(SUM(recreation_v2_6!F11,recreation_v2_7!F11,recreation_v2_8!F11,recreation_v2_9!F11,recreation_v2_10!F11)/COUNT(recreation_v2_6!F11,recreation_v2_7!F11,recreation_v2_8!F11,recreation_v2_9!F11,recreation_v2_10!F11),0)) -> 1 | G11: =IF($E11=0,"NA",ROUND(SUM(recreation_v2_6!G11,recreation_v2_7!G11,recreation_v2_8!G11,recreation_v2_9!G11,recreation_v2_10!G11)/COUNT(recreation_v2_6!G11,recreation_v2_7!G11,recreation_v2_8!G11,recreation_v2_9!G11,recreation_v2_10!G11),0)) -> 1 | H11: =IF(AND(F11=1, G11=1),ROUND(SUM(recreation_v2_6!H11,recreation_v2_7!H11,recreation_v2_8!H11,recreation_v2_9!H11,recreation_v2_10!H11)/COUNT(recreation_v2_6!H11,recreation_v2_7!H11,recreation_v2_8!H11,recreation_v2_9!H11,recreation_v2_10!H11),0),"NA") -> 1 | I11: =IF($E11=0, "NA", ROUND(SUM(recreation_v2_6!I11,recreation_v2_7!I11,recreation_v2_8!I11,recreation_v2_9!I11,recreation_v2_10!I11)/COUNT(recreation_v2_6!I11,recreation_v2_7!I11,recreation_v2_8!I11,recreation_v2_9!I11,recreation_v2_10!I11),0)) -> 1 | J11: =IF(F11=1,ROUND(SUM(recreation_v2_6!J11,recreation_v2_7!J11,recreation_v2_8!J11,recreation_v2_9!J11,recreation_v2_10!J11)/COUNT(recreation_v2_6!J11,recreation_v2_7!J11,recreation_v2_8!J11,recreation_v2_9!J11,recreation_v2_10!J11),0),"NA") -> 1 | K11: =IF($E11=0, "NA", ROUND(SUM(recreation_v2_6!K11,recreation_v2_7!K11,recreation_v2_8!K11,recreation_v2_9!K11,recreation_v2_10!K11)/COUNT(recreation_v2_6!K11,recreation_v2_7!K11,recreation_v2_8!K11,recreation_v2_9!K11,recreation_v2_10!K11),0)) -> 1 | L11: =IF($E11=0,"NA",ROUND(SUM(recreation_v2_6!L11,recreation_v2_7!L11,recreation_v2_8!L11,recreation_v2_9!L11,recreation_v2_10!L11)/COUNT(recreation_v2_6!L11,recreation_v2_7!L11,recreation_v2_8!L11,recreation_v2_9!L11,recreation_v2_10!L11),0)) -> 1 | M11: =IF($E11=0, "NA", ROUND(SUM(recreation_v2_6!M11,recreation_v2_7!M11,recreation_v2_8!M11,recreation_v2_9!M11,recreation_v2_10!M11)/COUNT(recreation_v2_6!M11,recreation_v2_7!M11,recreation_v2_8!M11,recreation_v2_9!M11,recreation_v2_10!M11),0)) -> 1 | N11: =IF($E11=0,"NA",ROUND(SUM(recreation_v2_6!N11,recreation_v2_7!N11,recreation_v2_8!N11,recreation_v2_9!N11,recreation_v2_10!N11)/COUNT(recreation_v2_6!N11,recreation_v2_7!N11,recreation_v2_8!N11,recreation_v2_9!N11,recreation_v2_10!N11),0)) -> 1 | O11: =IF($E11=0, "NA", ROUND(SUM(recreation_v2_6!O11,recreation_v2_7!O11,recreation_v2_8!O11,recreation_v2_9!O11,recreation_v2_10!O11)/COUNT(recreation_v2_6!O11,recreation_v2_7!O11,recreation_v2_8!O11,recreation_v2_9!O11,recreation_v2_10!O11),0)) -> 1
A12: TD | B12: Question 11 | C12: 0 | D12: 12.286176 | E12: =ROUND(SUM(recreation_v2_6!E12,recreation_v2_7!E12,recreation_v2_8!E12,recreation_v2_9!E12,recreation_v2_10!E12)/COUNT(recreation_v2_6!E12,recreation_v2_7!E12,recreation_v2_8!E12,recreation_v2_9!E12,recreation_v2_10!E12),0) -> 1 | F12: =IF($E12=0, "NA", ROUND(SUM(recreation_v2_6!F12,recreation_v2_7!F12,recreation_v2_8!F12,recreation_v2_9!F12,recreation_v2_10!F12)/COUNT(recreation_v2_6!F12,recreation_v2_7!F12,recreation_v2_8!F12,recreation_v2_9!F12,recreation_v2_10!F12),0)) -> 1 | G12: =IF($E12=0,"NA",ROUND(SUM(recreation_v2_6!G12,recreation_v2_7!G12,recreation_v2_8!G12,recreation_v2_9!G12,recreation_v2_10!G12)/COUNT(recreation_v2_6!G12,recreation_v2_7!G12,recreation_v2_8!G12,recreation_v2_9!G12,recreation_v2_10!G12),0)) -> 1 | H12: =IF(AND(F12=1, G12=1),ROUND(SUM(recreation_v2_6!H12,recreation_v2_7!H12,recreation_v2_8!H12,recreation_v2_9!H12,recreation_v2_10!H12)/COUNT(recreation_v2_6!H12,recreation_v2_7!H12,recreation_v2_8!H12,recreation_v2_9!H12,recreation_v2_10!H12),0),"NA") -> 1 | I12: =IF($E12=0, "NA", ROUND(SUM(recreation_v2_6!I12,recreation_v2_7!I12,recreation_v2_8!I12,recreation_v2_9!I12,recreation_v2_10!I12)/COUNT(recreation_v2_6!I12,recreation_v2_7!I12,recreation_v2_8!I12,recreation_v2_9!I12,recreation_v2_10!I12),0)) -> 1 | J12: =IF(F12=1,ROUND(SUM(recreation_v2_6!J12,recreation_v2_7!J12,recreation_v2_8!J12,recreation_v2_9!J12,recreation_v2_10!J12)/COUNT(recreation_v2_6!J12,recreation_v2_7!J12,recreation_v2_8!J12,recreation_v2_9!J12,recreation_v2_10!J12),0),"NA") -> 1 | K12: =IF($E12=0, "NA", ROUND(SUM(recreation_v2_6!K12,recreation_v2_7!K12,recreation_v2_8!K12,recreation_v2_9!K12,recreation_v2_10!K12)/COUNT(recreation_v2_6!K12,recreation_v2_7!K12,recreation_v2_8!K12,recreation_v2_9!K12,recreation_v2_10!K12),0)) -> 0 | L12: =IF($E12=0,"NA",ROUND(SUM(recreation_v2_6!L12,recreation_v2_7!L12,recreation_v2_8!L12,recreation_v2_9!L12,recreation_v2_10!L12)/COUNT(recreation_v2_6!L12,recreation_v2_7!L12,recreation_v2_8!L12,recreation_v2_9!L12,recreation_v2_10!L12),0)) -> 1 | M12: =IF($E12=0, "NA", ROUND(SUM(recreation_v2_6!M12,recreation_v2_7!M12,recreation_v2_8!M12,recreation_v2_9!M12,recreation_v2_10!M12)/COUNT(recreation_v2_6!M12,recreation_v2_7!M12,recreation_v2_8!M12,recreation_v2_9!M12,recreation_v2_10!M12),0)) -> 1 | N12: =IF($E12=0,"NA",ROUND(SUM(recreation_v2_6!N12,recreation_v2_7!N12,recreation_v2_8!N12,recreation_v2_9!N12,recreation_v2_10!N12)/COUNT(recreation_v2_6!N12,recreation_v2_7!N12,recreation_v2_8!N12,recreation_v2_9!N12,recreation_v2_10!N12),0)) -> 1 | O12: =IF($E12=0, "NA", ROUND(SUM(recreation_v2_6!O12,recreation_v2_7!O12,recreation_v2_8!O12,recreation_v2_9!O12,recreation_v2_10!O12)/COUNT(recreation_v2_6!O12,recreation_v2_7!O12,recreation_v2_8!O12,recreation_v2_9!O12,recreation_v2_10!O12),0)) -> 1
A13: TD | B13: Question 12 | C13: 0 | D13: 4.7259777 | E13: =ROUND(SUM(recreation_v2_6!E13,recreation_v2_7!E13,recreation_v2_8!E13,recreation_v2_9!E13,recreation_v2_10!E13)/COUNT(recreation_v2_6!E13,recreation_v2_7!E13,recreation_v2_8!E13,recreation_v2_9!E13,recreation_v2_10!E13),0) -> 1 | F13: =IF($E13=0, "NA", ROUND(SUM(recreation_v2_6!F13,recreation_v2_7!F13,recreation_v2_8!F13,recreation_v2_9!F13,recreation_v2_10!F13)/COUNT(recreation_v2_6!F13,recreation_v2_7!F13,recreation_v2_8!F13,recreation_v2_9!F13,recreation_v2_10!F13),0)) -> 1 | G13: =IF($E13=0,"NA",ROUND(SUM(recreation_v2_6!G13,recreation_v2_7!G13,recreation_v2_8!G13,recreation_v2_9!G13,recreation_v2_10!G13)/COUNT(recreation_v2_6!G13,recreation_v2_7!G13,recreation_v2_8!G13,recreation_v2_9!G13,recreation_v2_10!G13),0)) -> 1 | H13: =IF(AND(F13=1, G13=1),ROUND(SUM(recreation_v2_6!H13,recreation_v2_7!H13,recreation_v2_8!H13,recreation_v2_9!H13,recreation_v2_10!H13)/COUNT(recreation_v2_6!H13,recreation_v2_7!H13,recreation_v2_8!H13,recreation_v2_9!H13,recreation_v2_10!H13),0),"NA") -> 1 | I13: =IF($E13=0, "NA", ROUND(SUM(recreation_v2_6!I13,recreation_v2_7!I13,recreation_v2_8!I13,recreation_v2_9!I13,recreation_v2_10!I13)/COUNT(recreation_v2_6!I13,recreation_v2_7!I13,recreation_v2_8!I13,recreation_v2_9!I13,recreation_v2_10!I13),0)) -> 1 | J13: =IF(F13=1,ROUND(SUM(recreation_v2_6!J13,recreation_v2_7!J13,recreation_v2_8!J13,recreation_v2_9!J13,recreation_v2_10!J13)/COUNT(recreation_v2_6!J13,recreation_v2_7!J13,recreation_v2_8!J13,recreation_v2_9!J13,recreation_v2_10!J13),0),"NA") -> 0 | K13: =IF($E13=0, "NA", ROUND(SUM(recreation_v2_6!K13,recreation_v2_7!K13,recreation_v2_8!K13,recreation_v2_9!K13,recreation_v2_10!K13)/COUNT(recreation_v2_6!K13,recreation_v2_7!K13,recreation_v2_8!K13,recreation_v2_9!K13,recreation_v2_10!K13),0)) -> 1 | L13: =IF($E13=0,"NA",ROUND(SUM(recreation_v2_6!L13,recreation_v2_7!L13,recreation_v2_8!L13,recreation_v2_9!L13,recreation_v2_10!L13)/COUNT(recreation_v2_6!L13,recreation_v2_7!L13,recreation_v2_8!L13,recreation_v2_9!L13,recreation_v2_10!L13),0)) -> 1 | M13: =IF($E13=0, "NA", ROUND(SUM(recreation_v2_6!M13,recreation_v2_7!M13,recreation_v2_8!M13,recreation_v2_9!M13,recreation_v2_10!M13)/COUNT(recreation_v2_6!M13,recreation_v2_7!M13,recreation_v2_8!M13,recreation_v2_9!M13,recreation_v2_10!M13),0)) -> 1 | N13: =IF($E13=0,"NA",ROUND(SUM(recreation_v2_6!N13,recreation_v2_7!N13,recreation_v2_8!N13,recreation_v2_9!N13,recreation_v2_10!N13)/COUNT(recreation_v2_6!N13,recreation_v2_7!N13,recreation_v2_8!N13,recreation_v2_9!N13,recreation_v2_10!N13),0)) -> 1 | O13: =IF($E13=0, "NA", ROUND(SUM(recreation_v2_6!O13,recreation_v2_7!O13,recreation_v2_8!O13,recreation_v2_9!O13,recreation_v2_10!O13)/COUNT(recreation_v2_6!O13,recreation_v2_7!O13,recreation_v2_8!O13,recreation_v2_9!O13,recreation_v2_10!O13),0)) -> 1
... A77: Sarah | B77: Question 26 | C77: 0 | D77: 9.2338698 | E77: =ROUND(SUM(recreation_v2_6!E77,recreation_v2_7!E77,recreation_v2_8!E77,recreation_v2_9!E77,recreation_v2_10!E77)/COUNT(recreation_v2_6!E77,recreation_v2_7!E77,recreation_v2_8!E77,recreation_v2_9!E77,recreation_v2_10!E77),0) -> 0 | F77: =IF($E77=0, "NA", ROUND(SUM(recreation_v2_6!F77,recreation_v2_7!F77,recreation_v2_8!F77,recreation_v2_9!F77,recreation_v2_10!F77)/COUNT(recreation_v2_6!F77,recreation_v2_7!F77,recreation_v2_8!F77,recreation_v2_9!F77,recreation_v2_10!F77),0)) -> NA | G77: =IF($E77=0,"NA",ROUND(SUM(recreation_v2_6!G77,recreation_v2_7!G77,recreation_v2_8!G77,recreation_v2_9!G77,recreation_v2_10!G77)/COUNT(recreation_v2_6!G77,recreation_v2_7!G77,recreation_v2_8!G77,recreation_v2_9!G77,recreation_v2_10!G77),0)) -> NA | H77: =IF(AND(F77=1, G77=1),ROUND(SUM(recreation_v2_6!H77,recreation_v2_7!H77,recreation_v2_8!H77,recreation_v2_9!H77,recreation_v2_10!H77)/COUNT(recreation_v2_6!H77,recreation_v2_7!H77,recreation_v2_8!H77,recreation_v2_9!H77,recreation_v2_10!H77),0),"NA") -> NA | I77: =IF($E77=0, "NA", ROUND(SUM(recreation_v2_6!I77,recreation_v2_7!I77,recreation_v2_8!I77,recreation_v2_9!I77,recreation_v2_10!I77)/COUNT(recreation_v2_6!I77,recreation_v2_7!I77,recreation_v2_8!I77,recreation_v2_9!I77,recreation_v2_10!I77),0)) -> NA | J77: =IF(F77=1,ROUND(SUM(recreation_v2_6!J77,recreation_v2_7!J77,recreation_v2_8!J77,recreation_v2_9!J77,recreation_v2_10!J77)/COUNT(recreation_v2_6!J77,recreation_v2_7!J77,recreation_v2_8!J77,recreation_v2_9!J77,recreation_v2_10!J77),0),"NA") -> NA | K77: =IF($E77=0, "NA", ROUND(SUM(recreation_v2_6!K77,recreation_v2_7!K77,recreation_v2_8!K77,recreation_v2_9!K77,recreation_v2_10!K77)/COUNT(recreation_v2_6!K77,recreation_v2_7!K77,recreation_v2_8!K77,recreation_v2_9!K77,recreation_v2_10!K77),0)) -> NA | L77: =IF($E77=0,"NA",ROUND(SUM(recreation_v2_6!L77,recreation_v2_7!L77,recreation_v2_8!L77,recreation_v2_9!L77,recreation_v2_10!L77)/COUNT(recreation_v2_6!L77,recreation_v2_7!L77,recreation_v2_8!L77,recreation_v2_9!L77,recreation_v2_10!L77),0)) -> NA | M77: =IF($E77=0, "NA", ROUND(SUM(recreation_v2_6!M77,recreation_v2_7!M77,recreation_v2_8!M77,recreation_v2_9!M77,recreation_v2_10!M77)/COUNT(recreation_v2_6!M77,recreation_v2_7!M77,recreation_v2_8!M77,recreation_v2_9!M77,recreation_v2_10!M77),0)) -> NA | N77: =IF($E77=0,"NA",ROUND(SUM(recreation_v2_6!N77,recreation_v2_7!N77,recreation_v2_8!N77,recreation_v2_9!N77,recreation_v2_10!N77)/COUNT(recreation_v2_6!N77,recreation_v2_7!N77,recreation_v2_8!N77,recreation_v2_9!N77,recreation_v2_10!N77),0)) -> NA | O77: =IF($E77=0, "NA", ROUND(SUM(recreation_v2_6!O77,recreation_v2_7!O77,recreation_v2_8!O77,recreation_v2_9!O77,recreation_v2_10!O77)/COUNT(recreation_v2_6!O77,recreation_v2_7!O77,recreation_v2_8!O77,recreation_v2_9!O77,recreation_v2_10!O77),0)) -> NA
