Workbook

Sheet recreation_claude_v2_1
A1: Evaluator | B1: Question | C1: status | D1: response_time | E1: answerability | F1: primary_kc_alignment | G1: secondary_kc_alignment | H1: synergy | I1: topic_alignment | J1: grade_alignment | K1: real_world_feasibility | L1: clarity | M1: conciseness_and_relevance | N1: language_quality | O1: content_appropriateness | P1: explanation
A2: TD | B2: Question 1 | C2: 0 | D2: 11.105753 | E2: 1 | F2: 1 | G2: 1 | H2: 1 | I2: 1 | J2: 0 | K2: 1 | L2: 1 | M2: 1 | N2: 1 | O2: 1 | P2: Grade alignment issue: Problem requires 4-digit addition (1245+876, 987+1298, 1156+945) but Primary 3 students typically work with 3-digit numbers. 4-digit addition is usually taught in Primary 4.
A3: TD | B3: Question 2 | C3: 0 | D3: 9.6764731 | E3: 1 | F3: 1 | G3: 1 | H3: 1 | I3: 1 | J3: 1 | K3: 1 | L3: 1 | M3: 1 | N3: 1 | O3: 1
A4: TD | B4: Question 3 | C4: 0 | D4: 2.970257 | E4: 1 | F4: 1 | G4: 1 | H4: 1 | I4: 1 | J4: 1 | K4: 1 | L4: 1 | M4: 1 | N4: 1 | O4: 1
A5: TD | B5: Question 4 | C5: 0 | D5: 8.1421077 | E5: 1 | F5: 0 | G5: 1 | H5: 'NA | I5: 1 | J5: 'NA | K5: 1 | L5: 1 | M5: 1 | N5: 1 | O5: 1 | P5: Primary KC alignment: The problem requires multiplying 3-digit numbers (126, 148, 235) by 1-digit numbers (4, 3, 2), but the intended primary KC is specifically for multiplying whole numbers UP TO 3 digits by 1 digit, which typically means the multiplicand should be at most 3 digits. However, 126x4=504, 148x3=444, and 235x2=470 are all manageable calculations, but 235 is a 3-digit number that when multiplied results in complexity beyond typical Primary 3 expectations. Grade alignment: This problem involves 3-digit by 1-digit multiplication with numbers like 235x2, 148x3, and 126x4, which produces results in the hundreds. This level of multiplication complexity is typically introduced in Primary 4, not Primary 3 where students usually work with simpler 2-digit by 1-digit or very basic 3-digit by 1-digit multiplication.
A6: TD | B6: Question 5 | C6: 0 | D6: 3.0410473 | E6: 1 | F6: 1 | G6: 1 | H6: 1 | I6: 1 | J6: 1 | K6: 1 | L6: 1 | M6: 1 | N6: 1 | O6: 1
A7: TD | B7: Question 6 | C7: 0 | D7: 2.9441407 | E7: 1 | F7: 1 | G7: 1 | H7: 1 | I7: 1 | J7: 1 | K7: 1 | L7: 1 | M7: 1 | N7: 1 | O7: 1
A8: TD | B8: Question 7 | C8: 0 | D8: 10.786603 | E8: 1 | F8: 1 | G8: 1 | H8: 1 | I8: 1 | J8: 1 | K8: 1 | L8: 1 | M8: 1 | N8: 1 | O8: 1
A9: TD | B9: Question 8 | C9: 0 | D9: 10.350135 | E9: 1 | F9: 1 | G9: 1 | H9: 1 | I9: 1 | J9: 1 | K9: 1 | L9: 1 | M9: 1 | N9: 1 | O9: 1
A10: TD | B10: Question 9 | C10: 0 | D10: 2.9266968 | E10: 1 | F10: 1 | G10: 1 | H10: 1 | I10: 1 | J10: 1 | K10: 1 | L10: 1 | M10: 1 | N10: 1 | O10: 1
A11: TD | B11: Question 10 | C11: 0 | D11: 8.6437135 | E11: 1 | F11: 1 | G11: 1 | H11: 1 | I11: 1 | J11: 1 | K11: 1 | L11: 1 | M11: 1 | N11: 1 | O11: 1
A12: TD | B12: Question 11 | C12: 0 | D12: 11.651141 | E12: 0 | F12: 'NA | G12: 'NA | H12: 'NA | I12: 'NA | J12: 'NA | K12: 'NA | L12: 'NA | M12: 'NA | N12: 'NA | O12: 'NA | P12: Answerability: Questions (a) and (b) ask for totals but only provide single fractions - Sarah has 2/3 painting and 1/4 music, no second fractions to add. Primary KC Alignment: Problem does not require adding unlike fractions since each person has only one fraction per challenge type. Synergy: Primary and secondary knowledge components cannot work together effectively when primary component is not properly implemented.
A13: TD | B13: Question 12 | C13: 0 | D13: 2.9765003 | E13: 1 | F13: 1 | G13: 1 | H13: 1 | I13: 1 | J13: 1 | K13: 1 | L13: 1 | M13: 1 | N13: 1 | O13: 1
A14: TD | B14: Question 13 | C14: 0 | D14: 11.87017 | E14: 1 | F14: 0 | G14: 1 | H14: 'NA | I14: 1 | J14: 'NA | K14: 1 | L14: 1 | M14: 1 | N14: 1 | O14: 1 | P14: Primary KC alignment: Problem requires adding decimals up to 3 decimal places (1.142) but intended component specifies up to 2 decimal places only. Grade alignment: The use of 3 decimal places (1.142) may be too advanced for Primary 4 students who typically work with simpler decimal operations.
A15: TD | B15: Question 14 | C15: 0 | D15: 2.93716 | E15: 1 | F15: 1 | G15: 1 | H15: 1 | I15: 1 | J15: 1 | K15: 1 | L15: 1 | M15: 1 | N15: 1 | O15: 1
A16: TD | B16: Question 15 | C16: 0 | D16: 11.390833 | E16: 1 | F16: 1 | G16: 1 | H16: 1 | I16: 1 | J16: 0 | K16: 1 | L16: 1 | M16: 1 | N16: 1 | O16: 1 | P16: Grade alignment issue: The problem uses 2.486 km which has 3 decimal places (thousandths). Primary 4 students typically work with decimals up to 2 decimal places only. Working with 3 decimal places is usually introduced in Primary 5, making this problem too advanced for the intended grade level.
A17: TD | B17: Question 16 | C17: 0 | D17: 8.6064401 | E17: 1 | F17: 1 | G17: 1 | H17: 1 | I17: 1 | J17: 1 | K17: 1 | L17: 1 | M17: 1 | N17: 1 | O17: 1
A18: TD | B18: Question 17 | C18: 0 | D18: 9.417341 | E18: 1 | F18: 1 | G18: 1 | H18: 1 | I18: 1 | J18: 1 | K18: 1 | L18: 1 | M18: 1 | N18: 1 | O18: 1
A19: TD | B19: Question 18 | C19: 0 | D19: 2.9293506 | E19: 1 | F19: 1 | G19: 1 | H19: 1 | I19: 1 | J19: 1 | K19: 1 | L19: 1 | M19: 1 | N19: 1 | O19: 1
A20: TD | B20: Question 19 | C20: 0 | D20: 13.552191 | E20: 0 | F20: 'NA | G20: 'NA | H20: 'NA | I20: 'NA | J20: 'NA | K20: 'NA | L20: 'NA | M20: 'NA | N20: 'NA | O20: 'NA | P20: Answerability: The question 'total distance per lap over two days' is ambiguous and mathematically unclear. Primary KC Alignment: 5.24 / 3 = 1.7466... which exceeds 2 decimal places, violating the intended scope. Grade Alignment: Non-terminating decimals and ambiguous phrasing too complex for Primary 4. Real-world feasibility: Same pool having different lap distances on different days is unrealistic. Clarity: Final question phrasing is confusing and ambiguous.
A21: TD | B21: Question 20 | C21: 0 | D21: 8.9025273 | E21: 1 | F21: 1 | G21: 1 | H21: 1 | I21: 1 | J21: 1 | K21: 1 | L21: 1 | M21: 1 | N21: 1 | O21: 1
A22: TD | B22: Question 21 | C22: 0 | D22: 10.184599 | E22: 1 | F22: 1 | G22: 1 | H22: 1 | I22: 1 | J22: 1 | K22: 1 | L22: 1 | M22: 1 | N22: 1 | O22: 1
A23: TD | B23: Question 22 | C23: 0 | D23: 11.651554 | E23: 1 | F23: 1 | G23: 1 | H23: 1 | I23: 1 | J23: 1 | K23: 1 | L23: 1 | M23: 1 | N23: 1 | O23: 1
A24: TD | B24: Question 23 | C24: 0 | D24: 9.8399601 | E24: 1 | F24: 1 | G24: 1 | H24: 1 | I24: 1 | J24: 1 | K24: 1 | L24: 1 | M24: 1 | N24: 1 | O24: 1
A25: TD | B25: Question 24 | C25: 0 | D25: 11.518569 | E25: 1 | F25: 1 | G25: 1 | H25: 1 | I25: 1 | J25: 1 | K25: 1 | L25: 1 | M25: 1 | N25: 1 | O25: 1
A26: TD | B26: Question 25 | C26: 0 | D26: 10.433698 | E26: 1 | F26: 1 | G26: 1 | H26: 1 | I26: 1 | J26: 1 | K26: 1 | L26: 1 | M26: 1 | N26: 1 | O26: 1
A27: TD | B27: Question 26 | C27: 0 | D27: 11.149707 | E27: 1 | F27: 0 | G27: 1 | H27: 'NA | I27: 1 | J27: 'NA | K27: 1 | L27: 1 | M27: 1 | N27: 1 | O27: 1 | P27: Primary KC alignment: The problem only requires adding fractions (7/4 + 5/3, 9/5 + 8/7, and adding the sums). No multiplication of improper fractions is needed. Synergy: Cannot achieve synergy between primary and secondary KC when the primary KC (multiplying improper fractions) is not present in the problem.
A28: TD | B28: Question 27 | C28: 0 | D28: 6.3620174 | E28: 1 | F28: 0 | G28: 1 | H28: 'NA | I28: 1 | J28: 'NA | K28: 1 | L28: 1 | M28: 1 | N28: 1 | O28: 1 | P28: Primary KC alignment: The problem requires division of fractions (finding planned time when actual time is 2/3 of planned), not multiplication of two improper fractions. The main operation is (7/4 + 5/3 - 3/2) ÷ (2/3) which involves division as the primary operation. Synergy: The Primary KC (multiplication of improper fractions) and Secondary KC (subtraction of fractions) are not used in tandem. The problem primarily uses addition and subtraction of fractions, then division, but not multiplication of two improper fractions as required by the Primary KC.
A29: TD | B29: Question 28 | C29: 0 | D29: 10.531832 | E29: 1 | F29: 1 | G29: 1 | H29: 1 | I29: 1 | J29: 1 | K29: 1 | L29: 1 | M29: 1 | N29: 1 | O29: 1
A30: TD | B30: Question 29 | C30: 0 | D30: 10.047207 | E30: 1 | F30: 1 | G30: 0 | H30: 'NA | I30: 1 | J30: 1 | K30: 1 | L30: 1 | M30: 1 | N30: 1 | O30: 1 | P30: Secondary Knowledge Component misalignment: The problem requires subtracting whole numbers (22 - 19 = 3) rather than subtracting fractions as specified in the intended Secondary Knowledge Component.
A31: TD | B31: Question 30 | C31: 0 | D31: 12.467189 | E31: 1 | F31: 0 | G31: 1 | H31: 'NA | I31: 1 | J31: 'NA | K31: 1 | L31: 1 | M31: 1 | N31: 1 | O31: 1 | P31: Primary KC alignment: Problem requires 0.875 * 300 which is general decimal multiplication, not specifically multiplying by 10, 100, 1000 or their multiples as intended. Synergy: Since intended primary KC is not actually used, there is no synergistic relationship between the intended primary and secondary knowledge components.
A32: TD | B32: Question 31 | C32: 0 | D32: 6.1254821 | E32: 1 | F32: 0 | G32: 1 | H32: 'NA | I32: 1 | J32: 'NA | K32: 1 | L32: 1 | M32: 1 | N32: 1 | O32: 1 | P32: Primary KC alignment: The problem requires 0.125 * 400 which is decimal multiplication by a whole number, not specifically multiplying decimals by 10, 100, 1000 or their multiples as intended. Synergy: The two parts can be solved independently - the first part calculates distance (0.125 * 400 = 50), the second part subtracts (65.8 - 50 = 15.8). The primary and secondary knowledge components are not used in tandem as the multiplication result is not essential for the subtraction part.
A33: TD | B33: Question 32 | C33: 0 | D33: 11.520845 | E33: 1 | F33: 0 | G33: 1 | H33: 'NA | I33: 1 | J33: 'NA | K33: 1 | L33: 1 | M33: 1 | N33: 1 | O33: 1 | P33: Primary KC alignment fails because the problem requires dividing by 7, but the intended primary KC is dividing decimals by 10, 100, 1000 and their multiples. Since 7 is not a multiple of 10, 100, or 1000, this creates a fundamental misalignment with the intended knowledge component.
A34: TD | B34: Question 33 | C34: 0 | D34: 8.7761075 | E34: 0 | F34: 'NA | G34: 'NA | H34: 'NA | I34: 'NA | J34: 'NA | K34: 'NA | L34: 'NA | M34: 'NA | N34: 'NA | O34: 'NA | P34: Answerability: The problem contains illogical information - if Sarah swam 40000 meters total and the coach divides total time by 400, this does not give average time per 100 meters as stated. The calculation 40000/400=100, so dividing by 400 would give time per 100-meter segments, but the setup is mathematically inconsistent. Primary KC Alignment: The division required is by 400, not by 10, 100, 1000 or their multiples as specified in the intended knowledge component. 400 is not a multiple of 10, 100, or 1000 in the standard sense for this curriculum topic. Real-world Feasibility: Swimming 40000 meters (40 km) in 4 laps is unrealistic - this would mean each lap is 10 km, which is not feasible for a typical swimming practice session. Conciseness and Relevance: The 40000 meters information appears unnecessary and creates confusion since the actual calculation can be done by adding the times and dividing by 400 directly.
A35: TD | B35: Question 34 | C35: 0 | D35: 11.226322 | E35: 1 | F35: 1 | G35: 0 | H35: 'NA | I35: 1 | J35: 1 | K35: 1 | L35: 1 | M35: 1 | N35: 1 | O35: 1 | P35: Secondary KC alignment: Problem requires division (90/120) and multiplication by 100, not multiplication of whole numbers as intended. Synergy: No synergy exists since the intended secondary KC (whole number multiplication) is not actually needed to solve the problem.
A36: TD | B36: Question 35 | C36: 0 | D36: 6.2476168 | E36: 1 | F36: 1 | G36: 1 | H36: 1 | I36: 1 | J36: 1 | K36: 1 | L36: 1 | M36: 1 | N36: 1 | O36: 1
A37: TD | B37: Question 36 | C37: 0 | D37: 11.940733 | E37: 1 | F37: 1 | G37: 1 | H37: 1 | I37: 1 | J37: 1 | K37: 0 | L37: 1 | M37: 1 | N37: 1 | O37: 1 | P37: Real-world feasibility: 1.25 km/h is unrealistically slow for marathon training - this is slower than normal walking speed of 4-5 km/h and would not represent realistic training pace.
A38: TD | B38: Question 37 | C38: 0 | D38: 9.7374115 | E38: 1 | F38: 1 | G38: 1 | H38: 1 | I38: 1 | J38: 1 | K38: 1 | L38: 1 | M38: 1 | N38: 1 | O38: 1
A39: TD | B39: Question 38 | C39: 0 | D39: 2.8938303 | E39: 1 | F39: 1 | G39: 1 | H39: 1 | I39: 1 | J39: 1 | K39: 1 | L39: 1 | M39: 1 | N39: 1 | O39: 1
A40: TD | B40: Question 39 | C40: 0 | D40: 11.566289 | E40: 1 | F40: 1 | G40: 1 | H40: 1 | I40: 1 | J40: 1 | K40: 0 | L40: 1 | M40: 1 | N40: 1 | O40: 1 | P40: Real-world plausibility: The phrase 2/3 of the week refers to 4.67 days, which is not how people typically plan practice schedules in reality. Practice schedules are usually planned in whole days or specific days of the week.
A41: TD | B41: Question 40 | C41: 0 | D41: 12.776811 | E41: 0 | F41: 'NA | G41: 'NA | H41: 'NA | I41: 'NA | J41: 'NA | K41: 'NA | L41: 'NA | M41: 'NA | N41: 'NA | O41: 'NA | P41: The problem lacks critical information needed to solve it. We know Sarah completed 3/4 of her total practice time and each session is 2/5 hour, but we don't know her total practice time for today. Without knowing the total time (e.g., 2 hours total practice time), we cannot determine how much actual time 3/4 represents, and therefore cannot calculate how many 2/5 hour sessions fit into that time.
A42: TD | B42: Question 41 | C42: 0 | D42: 12.013047 | E42: 1 | F42: 1 | G42: 1 | H42: 0 | I42: 1 | J42: 1 | K42: 0 | L42: 1 | M42: 1 | N42: 1 | O42: 1 | P42: Synergy: The two knowledge components are used sequentially rather than in tandem - percentage calculation is completed first (72 / 0.6 = 120), then simple addition follows (120 + 45 = 165), without meaningful interdependence. Real-World Plausibility: A coach instructing a player to attempt exactly 45 more shots while maintaining precisely 60% success rate is unrealistic - success rates naturally vary and coaches do not typically give such mathematically precise instructions.
A43: TD | B43: Question 42 | C43: 0 | D43: 10.923738 | E43: 1 | F43: 1 | G43: 0 | H43: 'NA | I43: 1 | J43: 1 | K43: 1 | L43: 1 | M43: 0 | N43: 1 | O43: 1 | P43: Secondary KC alignment: The problem can be solved using only 180 and 216 without requiring division of whole numbers. Synergy: Since division is not needed, there is no synergy between primary and secondary KCs. Conciseness: The attempt numbers 300 and 360 are irrelevant to solving the percentage increase problem.
A44: TD | B44: Question 43 | C44: 0 | D44: 5.7875755 | E44: 1 | F44: 1 | G44: 0 | H44: 'NA | I44: 1 | J44: 1 | K44: 1 | L44: 1 | M44: 1 | N44: 1 | O44: 1 | P44: Secondary KC Alignment: The problem only requires finding the ratio 45:36:54 and simplifying it to 5:4:6. No addition of whole numbers is needed to solve this problem. The three point values are directly given and used as-is for the ratio calculation. Synergy: Since the secondary knowledge component (addition of whole numbers) is not required to solve the problem, there is no synergy between the primary and secondary knowledge components. The problem can be solved using only ratio concepts without any addition operations.
A45: TD | B45: Question 44 | C45: 0 | D45: 11.909623 | E45: 1 | F45: 1 | G45: 1 | H45: 1 | I45: 1 | J45: 0 | K45: 1 | L45: 1 | M45: 1 | N45: 1 | O45: 1 | P45: Grade alignment: This problem requires algebraic thinking with variables and linear equations which is too advanced for Primary 6 students. Primary 6 mathematics typically involves arithmetic word problems with concrete numbers, not abstract algebraic expressions with variables like x.
A46: TD | B46: Question 45 | C46: 0 | D46: 6.4374862 | E46: 1 | F46: 1 | G46: 1 | H46: 1 | I46: 1 | J46: 0 | K46: 1 | L46: 1 | M46: 1 | N46: 1 | O46: 1 | P46: Grade alignment: This problem requires only basic percentage calculations (25% and 15% of whole numbers) and simple subtraction, which are typically mastered in primary/lower secondary levels. For Secondary O-level 1 students, this problem would be too elementary and does not challenge students at the appropriate academic level expected for that grade.
A47: TD | B47: Question 46 | C47: 0 | D47: 10.66452 | E47: 1 | F47: 1 | G47: 1 | H47: 1 | I47: 1 | J47: 0 | K47: 1 | L47: 1 | M47: 1 | N47: 1 | O47: 1 | P47: Grade alignment fails because percentage concepts and reverse percentages are typically taught in Primary 5-6 in Singapore curriculum, making this problem too basic for Secondary O-level 1 students.
A48: TD | B48: Question 47 | C48: 0 | D48: 13.019923 | E48: 1 | F48: 1 | G48: 1 | H48: 1 | I48: 1 | J48: 0 | K48: 1 | L48: 1 | M48: 1 | N48: 1 | O48: 1 | P48: Grade Alignment: The problem difficulty level is too elementary for Secondary O-level 2 students. Ratio problems of this type are typically taught at Primary 6 level in Singapore math curriculum, making it inappropriate for O-level students who should be working with more advanced mathematical concepts.
A49: TD | B49: Question 48 | C49: 0 | D49: 11.507749 | E49: 1 | F49: 1 | G49: 1 | H49: 1 | I49: 1 | J49: 1 | K49: 1 | L49: 1 | M49: 1 | N49: 1 | O49: 1
A50: TD | B50: Question 49 | C50: 0 | D50: 4.6331789 | E50: 1 | F50: 1 | G50: 1 | H50: 1 | I50: 1 | J50: 0 | K50: 1 | L50: 1 | M50: 1 | N50: 1 | O50: 1 | P50: Grade Alignment: Standard deviation calculation is typically introduced at Secondary 4/5 or higher levels in Singapore math curriculum, not at Primary levels. The problem requires knowledge of variance, square roots, and complex statistical concepts that exceed Primary grade mathematical capabilities.
A51: Minh | B51: Question 1 | C51: 0 | D51: 10.219038 | E51: 1 | F51: 1 | G51: 1 | H51: 1 | I51: 1 | J51: 1 | K51: 1 | L51: 1 | M51: 1 | N51: 1 | O51: 1
A52: Minh | B52: Question 2 | C52: 0 | D52: 10.409481 | E52: 1 | F52: 1 | G52: 0 | H52: 'NA | I52: 1 | J52: 1 | K52: 1 | L52: 1 | M52: 1 | N52: 1 | O52: 1 | P52: Secondary KC alignment: The problem does not require adding whole numbers - the total is given as 847. Synergy: No meaningful connection between primary and secondary KCs since addition is not needed to solve the problem.
A53: Minh | B53: Question 3 | C53: 0 | D53: 9.8612285 | E53: 1 | F53: 1 | G53: 1 | H53: 1 | I53: 1 | J53: 1 | K53: 1 | L53: 1 | M53: 1 | N53: 1 | O53: 1
A54: Minh | B54: Question 4 | C54: 0 | D54: 5.9518399 | E54: 1 | F54: 1 | G54: 1 | H54: 1 | I54: 1 | J54: 1 | K54: 1 | L54: 1 | M54: 1 | N54: 1 | O54: 1
A55: Minh | B55: Question 5 | C55: 0 | D55: 9.2996967 | E55: 1 | F55: 1 | G55: 1 | H55: 1 | I55: 1 | J55: 1 | K55: 1 | L55: 1 | M55: 1 | N55: 1 | O55: 1
A56: Minh | B56: Question 6 | C56: 0 | D56: 7.0525119 | E56: 1 | F56: 1 | G56: 0 | H56: 'NA | I56: 1 | J56: 1 | K56: 1 | L56: 1 | M56: 1 | N56: 1 | O56: 1 | P56: Secondary KC Alignment: The problem requires division operations (432/6=72, then 72/4=18) but the intended secondary knowledge component is multiplication of whole numbers, which is not needed to solve either question. Synergy: Since multiplication is not actually required to solve the problem, the primary KC (division) and intended secondary KC (multiplication) are not used in tandem as required.
A57: Minh | B57: Question 7 | C57: 0 | D57: 10.734996 | E57: 1 | F57: 1 | G57: 1 | H57: 1 | I57: 1 | J57: 1 | K57: 1 | L57: 1 | M57: 1 | N57: 1 | O57: 1
A58: Minh | B58: Question 8 | C58: 0 | D58: 11.705861 | E58: 0 | F58: 'NA | G58: 'NA | H58: 'NA | I58: 'NA | J58: 'NA | K58: 'NA | L58: 'NA | M58: 'NA | N58: 'NA | O58: 'NA | P58: Answerability: The second question asks how much longer Wednesday practice was compared to Monday+Tuesday combined, but Wednesday (5/12 hour) is actually shorter than the combined time (5/8 hour), making the question illogical. Primary KC Alignment: While subtraction is present, the problem structure emphasizes addition more prominently (first question is purely addition, subtraction only appears in second question), which conflicts with subtraction being the primary knowledge component.
A59: Minh | B59: Question 9 | C59: 0 | D59: 12.039231 | E59: 1 | F59: 1 | G59: 1 | H59: 1 | I59: 1 | J59: 1 | K59: 1 | L59: 1 | M59: 0 | N59: 1 | O59: 1 | P59: The number 12 (pieces per pack) is provided but not necessary for solving the problem, as only the cost per pack and number of packs are needed for the calculation.
A60: Minh | B60: Question 10 | C60: 0 | D60: 4.852222 | E60: 1 | F60: 1 | G60: 1 | H60: 1 | I60: 1 | J60: 1 | K60: 0 | L60: 1 | M60: 1 | N60: 1 | O60: 1 | P60: Real-world feasibility: The numbers of students are unrealistic for a single school to bring to a badminton tournament. 2,856, 1,944, and 3,528 students per school would require massive venues and logistics that do not reflect typical inter-school sports events where schools usually bring much smaller groups of participants and supporters.
A61: Minh | B61: Question 11 | C61: 0 | D61: 9.138993 | E61: 1 | F61: 1 | G61: 1 | H61: 1 | I61: 1 | J61: 1 | K61: 1 | L61: 1 | M61: 1 | N61: 1 | O61: 1
A62: Minh | B62: Question 12 | C62: 0 | D62: 10.363491 | E62: 1 | F62: 1 | G62: 1 | H62: 1 | I62: 1 | J62: 1 | K62: 1 | L62: 1 | M62: 1 | N62: 1 | O62: 1
A63: Minh | B63: Question 13 | C63: 0 | D63: 2.9503808 | E63: 1 | F63: 1 | G63: 1 | H63: 1 | I63: 1 | J63: 1 | K63: 1 | L63: 1 | M63: 1 | N63: 1 | O63: 1
A64: Minh | B64: Question 14 | C64: 0 | D64: 6.5485303 | E64: 1 | F64: 1 | G64: 0 | H64: 'NA | I64: 1 | J64: 1 | K64: 1 | L64: 1 | M64: 1 | N64: 1 | O64: 1 | P64: Secondary KC alignment: The problem asks to express answer as mixed number, but the intended secondary KC is converting decimals to fractions, not mixed numbers. The calculation 2.75 + 1.8 + 3.25 = 7.8 km results in 7.8, which when converted to mixed number becomes 7 4/5, but this requires fraction conversion skills beyond the stated secondary KC. Synergy: Since the secondary KC is not properly aligned, there is no true synergy between primary and secondary KCs. The decimal addition (primary KC) can be completed independently without requiring the intended secondary KC of decimal to fraction conversion.
A65: Minh | B65: Question 15 | C65: 0 | D65: 12.013779 | E65: 1 | F65: 0 | G65: 1 | H65: 'NA | I65: 1 | J65: 'NA | K65: 1 | L65: 1 | M65: 1 | N65: 1 | O65: 1 | P65: Primary KC alignment: Problem includes 3.126 km which has 3 decimal places, exceeding the intended scope of up to 2 decimal places. Grade alignment: Using 3 decimal places is typically above Primary 4 level where students usually work with decimals up to 2 decimal places.
A66: Minh | B66: Question 16 | C66: 0 | D66: 9.7704906 | E66: 1 | F66: 1 | G66: 1 | H66: 1 | I66: 1 | J66: 1 | K66: 1 | L66: 1 | M66: 1 | N66: 1 | O66: 1
A67: Minh | B67: Question 17 | C67: 0 | D67: 9.5236752 | E67: 1 | F67: 1 | G67: 1 | H67: 1 | I67: 1 | J67: 1 | K67: 1 | L67: 1 | M67: 1 | N67: 1 | O67: 1
A68: Minh | B68: Question 18 | C68: 0 | D68: 12.989555 | E68: 1 | F68: 1 | G68: 0 | H68: 'NA | I68: 1 | J68: 1 | K68: 1 | L68: 1 | M68: 0 | N68: 1 | O68: 1 | P68: Secondary KC Alignment: The problem gives the remaining amount directly as 8.91, so decimal subtraction is not needed to solve it. Synergy: Since secondary KC is not required, the two knowledge components do not work together. Conciseness and Relevance: The purchase prices 12.48 and 2.76 are unnecessary information since the remaining amount 8.91 is provided directly.
A69: Minh | B69: Question 19 | C69: 0 | D69: 2.9065669 | E69: 1 | F69: 1 | G69: 1 | H69: 1 | I69: 1 | J69: 1 | K69: 1 | L69: 1 | M69: 1 | N69: 1 | O69: 1
A70: Minh | B70: Question 20 | C70: 0 | D70: 9.8680251 | E70: 1 | F70: 1 | G70: 1 | H70: 1 | I70: 1 | J70: 1 | K70: 1 | L70: 1 | M70: 1 | N70: 1 | O70: 1
A71: Minh | B71: Question 21 | C71: 0 | D71: 10.294959 | E71: 1 | F71: 1 | G71: 1 | H71: 1 | I71: 1 | J71: 1 | K71: 1 | L71: 1 | M71: 1 | N71: 1 | O71: 1
A72: Minh | B72: Question 22 | C72: 0 | D72: 8.9038367 | E72: 1 | F72: 1 | G72: 1 | H72: 1 | I72: 1 | J72: 1 | K72: 1 | L72: 1 | M72: 1 | N72: 1 | O72: 1
A73: Minh | B73: Question 23 | C73: 0 | D73: 2.98542 | E73: 1 | F73: 1 | G73: 1 | H73: 1 | I73: 1 | J73: 1 | K73: 1 | L73: 1 | M73: 1 | N73: 1 | O73: 1
A74: Minh | B74: Question 24 | C74: 0 | D74: 9.665309 | E74: 1 | F74: 1 | G74: 1 | H74: 1 | I74: 1 | J74: 1 | K74: 1 | L74: 1 | M74: 1 | N74: 1 | O74: 1
A75: Minh | B75: Question 25 | C75: 0 | D75: 10.305582 | E75: 1 | F75: 1 | G75: 1 | H75: 1 | I75: 1 | J75: 1 | K75: 1 | L75: 1 | M75: 1 | N75: 1 | O75: 1
A76: Minh | B76: Question 26 | C76: 0 | D76: 9.851155 | E76: 1 | F76: 1 | G76: 1 | H76: 1 | I76: 1 | J76: 1 | K76: 1 | L76: 1 | M76: 1 | N76: 1 | O76: 1
A77: Minh | B77: Question 27 | C77: 0 | D77: 4.8917942 | E77: 1 | F77: 0 | G77: 1 | H77: 'NA | I77: 1 | J77: 'NA | K77: 1 | L77: 1 | M77: 1 | N77: 1 | O77: 1 | P77: Primary KC alignment fails because the problem requires multiplying 23.456 x 30, which is multiplying a decimal by a non-multiple of 10, 100, or 1000. The intended primary KC specifically states multiplying decimals by 10, 100, 1000 and their multiples only. 30 is not a multiple of 10, 100, or 1000.
A78: Minh | B78: Question 28 | C78: 0 | D78: 5.189441 | E78: 1 | F78: 0 | G78: 1 | H78: 'NA | I78: 1 | J78: 'NA | K78: 1 | L78: 1 | M78: 1 | N78: 1 | O78: 1 | P78: Primary KC alignment fails because the problem requires dividing 142.8 by 60, but the intended primary KC is about dividing decimals by 10, 100, 1000 and their multiples. 60 is not a multiple of 10, 100, or 1000 (60 = 2^2 * 3 * 5, while multiples of powers of 10 only contain factors of 2 and 5 in specific ratios).
A79: Minh | B79: Question 29 | C79: 0 | D79: 11.260087 | E79: 1 | F79: 1 | G79: 1 | H79: 1 | I79: 1 | J79: 1 | K79: 1 | L79: 1 | M79: 1 | N79: 1 | O79: 1
A80: Minh | B80: Question 30 | C80: 0 | D80: 8.7496953 | E80: 1 | F80: 1 | G80: 1 | H80: 1 | I80: 1 | J80: 1 | K80: 1 | L80: 1 | M80: 1 | N80: 1 | O80: 1
A81: Minh | B81: Question 31 | C81: 0 | D81: 11.420748 | E81: 1 | F81: 1 | G81: 0 | H81: 'NA | I81: 1 | J81: 1 | K81: 0 | L81: 1 | M81: 1 | N81: 1 | O81: 1 | P81: Secondary KC alignment: Problem requires converting from larger unit (km) to smaller unit (m), but intended secondary KC is converting from smaller to larger unit. Real-world feasibility: Running pace of 1.25 km/min equals 75 km/h which is unrealistically fast for human marathon training.
A82: Minh | B82: Question 32 | C82: 0 | D82: 10.21146 | E82: 1 | F82: 1 | G82: 0 | H82: 'NA | I82: 1 | J82: 1 | K82: 1 | L82: 1 | M82: 1 | N82: 1 | O82: 1 | P82: Secondary Knowledge Component not addressed: The problem does not involve converting measurements from larger units in decimal form to smaller units. All values (0.8 laps/minute, 21.6 minutes, resulting laps) remain in their original units with no conversion required. Synergy absent: Since the secondary knowledge component is not present in the problem, there is no synergy between the intended primary and secondary knowledge components.
A83: Minh | B83: Question 33 | C83: 0 | D83: 3.0583427 | E83: 1 | F83: 1 | G83: 1 | H83: 1 | I83: 1 | J83: 1 | K83: 1 | L83: 1 | M83: 1 | N83: 1 | O83: 1
A84: Minh | B84: Question 34 | C84: 0 | D84: 11.868451 | E84: 1 | F84: 1 | G84: 1 | H84: 1 | I84: 1 | J84: 1 | K84: 0 | L84: 1 | M84: 1 | N84: 1 | O84: 1 | P84: Real-world feasibility: Tuesday calculation gives 8.25 sessions. Having 0.25 or quarter of a practice session is unrealistic - practice sessions cannot be fractional in real life.
A85: Minh | B85: Question 35 | C85: 0 | D85: 5.2096934 | E85: 1 | F85: 1 | G85: 0 | H85: 'NA | I85: 1 | J85: 1 | K85: 1 | L85: 1 | M85: 1 | N85: 1 | O85: 1 | P85: Secondary KC alignment: The problem requires dividing 3/4 by 1/8 which equals 6, a whole number. Since 6 is already in its simplest form, no fraction simplification is needed or demonstrated. Synergy: Since the secondary knowledge component (simplifying fractions) is not actually required to solve the problem, the two knowledge components do not work in tandem as intended.
A86: Minh | B86: Question 36 | C86: 0 | D86: 10.416767 | E86: 1 | F86: 1 | G86: 1 | H86: 1 | I86: 1 | J86: 1 | K86: 1 | L86: 1 | M86: 1 | N86: 1 | O86: 1
A87: Minh | B87: Question 37 | C87: 0 | D87: 8.1673076 | E87: 0 | F87: 'NA | G87: 'NA | H87: 'NA | I87: 'NA | J87: 'NA | K87: 'NA | L87: 'NA | M87: 'NA | N87: 'NA | O87: 'NA | P87: ANSWERABILITY: The problem asks for percentage decrease but accuracy remained constant at 70% both months (84/120 = 105/150 = 0.7). There is no decrease to calculate, making the question as stated unanswerable. PRIMARY_KC_ALIGNMENT: Since both months show 70% accuracy, there is no percentage increase or decrease occurring. The primary knowledge component of finding percentage change cannot be meaningfully applied when the values are identical. SYNERGY: With no actual percentage change occurring (0% change), the primary and secondary knowledge components do not work together as intended to solve a meaningful problem.
A88: Minh | B88: Question 38 | C88: 0 | D88: 8.0423343 | E88: 1 | F88: 1 | G88: 1 | H88: 0 | I88: 1 | J88: 1 | K88: 1 | L88: 1 | M88: 1 | N88: 1 | O88: 1 | P88: Synergy: The two questions can be solved independently. Question 1 requires multiplication (45*3, 63*3) then subtraction. Question 2 only needs the original free throw numbers (45, 63) for percentage calculation. The result from Question 1 is not needed to solve Question 2, so the knowledge components are not used in tandem.
A89: Minh | B89: Question 39 | C89: 0 | D89: 10.6338 | E89: 1 | F89: 1 | G89: 1 | H89: 1 | I89: 1 | J89: 1 | K89: 1 | L89: 1 | M89: 1 | N89: 1 | O89: 1
A90: Minh | B90: Question 40 | C90: 0 | D90: 2.8690937 | E90: 1 | F90: 1 | G90: 1 | H90: 1 | I90: 1 | J90: 1 | K90: 1 | L90: 1 | M90: 1 | N90: 1 | O90: 1
A91: Minh | B91: Question 41 | C91: 0 | D91: 2.9348586 | E91: 1 | F91: 1 | G91: 1 | H91: 1 | I91: 1 | J91: 1 | K91: 1 | L91: 1 | M91: 1 | N91: 1 | O91: 1
A92: Minh | B92: Question 42 | C92: 0 | D92: 9.4844956 | E92: 1 | F92: 1 | G92: 1 | H92: 1 | I92: 1 | J92: 1 | K92: 1 | L92: 1 | M92: 1 | N92: 1 | O92: 1
A93: Minh | B93: Question 43 | C93: 0 | D93: 4.6243322 | E93: 1 | F93: 1 | G93: 1 | H93: 1 | I93: 1 | J93: 0 | K93: 1 | L93: 1 | M93: 1 | N93: 1 | O93: 1 | P93: Grade Alignment: The problem requires algebraic expressions with variables (a, b) and substitution evaluation, which are typically introduced in Secondary 1-2 mathematics curriculum, not Primary 6. Primary 6 students work with concrete numbers and basic equations, not abstract algebraic expressions with multiple variables.
A94: Minh | B94: Question 44 | C94: 0 | D94: 11.005552 | E94: 1 | F94: 1 | G94: 1 | H94: 1 | I94: 1 | J94: 1 | K94: 1 | L94: 1 | M94: 1 | N94: 1 | O94: 1
A95: Minh | B95: Question 45 | C95: 0 | D95: 11.997175 | E95: 1 | F95: 1 | G95: 1 | H95: 1 | I95: 1 | J95: 0 | K95: 1 | L95: 1 | M95: 1 | N95: 1 | O95: 1 | P95: Grade Alignment: The problem requires complex fraction subtraction (3/4 - 1/6 and 5/6 - 1/4) and ratio concepts involving fractions, which are too advanced for Secondary O-level 1 students. These topics are typically covered in higher grade levels.
A96: Minh | B96: Question 46 | C96: 0 | D96: 6.2708519 | E96: 1 | F96: 1 | G96: 1 | H96: 1 | I96: 1 | J96: 0 | K96: 1 | L96: 1 | M96: 1 | N96: 1 | O96: 1 | P96: Grade alignment fails because this problem is too elementary for Secondary O-level 1 students. The fraction operations (3/4 * 7, 1/2 * 7, simple ratio 21/4 : 7/2, and dividing 21/4 by 3) are concepts typically mastered in primary grades 4-6. Secondary O-level 1 students would be expected to handle more complex ratio problems involving algebraic manipulation, proportion solving, or multi-step applications rather than basic fraction arithmetic.
A97: Minh | B97: Question 47 | C97: 0 | D97: 12.125996 | E97: 1 | F97: 0 | G97: 1 | H97: 'NA | I97: 1 | J97: 'NA | K97: 1 | L97: 1 | M97: 1 | N97: 1 | O97: 1 | P97: Primary KC: Problem focuses more on complex GCD calculation (97, 66, 129) than decimal ratio concepts. Grade Alignment: Finding GCD of 97, 66, 129 requires advanced factorization beyond Secondary O-level 1.
A98: Minh | B98: Question 48 | C98: 0 | D98: 11.102888 | E98: 1 | F98: 1 | G98: 1 | H98: 1 | I98: 1 | J98: 0 | K98: 1 | L98: 1 | M98: 1 | N98: 1 | O98: 1 | P98: Grade alignment: The problem involves basic percentage calculations (24/40 = 60%, 18/30 = 60%) and simple decimal conversion (60% = 0.6) which are too elementary for Secondary O-level 1 students who should be working with more advanced mathematical concepts.
A99: Minh | B99: Question 49 | C99: 0 | D99: 12.488479 | E99: 1 | F99: 1 | G99: 1 | H99: 1 | I99: 1 | J99: 0 | K99: 1 | L99: 1 | M99: 1 | N99: 1 | O99: 1 | P99: Grade alignment: The problem only requires basic arithmetic operations (480/12, 25% calculation, multiplication) that are typically mastered in upper primary grades (P5-P6). For Secondary O-level 1 students, this problem would be too elementary and does not match the expected difficulty level for that grade.
A100: Minh | B100: Question 50 | C100: 0 | D100: 10.694754 | E100: 0 | F100: 'NA | G100: 'NA | H100: 'NA | I100: 'NA | J100: 'NA | K100: 'NA | L100: 'NA | M100: 'NA | N100: 'NA | O100: 'NA | P100: Answerability: Problem contains contradictory information - Sarah swims at constant speed d/36 per minute based on given data, but needs speed d/30 per minute to finish in 30 minutes, making problem unsolvable. Primary KC Alignment: Problem does not require solving fractional equations reducible to linear equations - solution involves direct proportion calculations, not equation solving. Synergy: Since primary KC is not needed, primary and secondary KCs cannot work in tandem. Grade Alignment: Problem complexity with proportional reasoning and fraction manipulation is below Secondary O-level 1 standard. Real-World Feasibility: Scenario is illogical - swimmer cannot maintain constant speed while also adjusting pace to meet different time target.
...

Sheet recreation_claude_v2_2
A1: Evaluator | B1: Question | C1: status | D1: response_time | E1: answerability | F1: primary_kc_alignment | G1: secondary_kc_alignment | H1: synergy | I1: topic_alignment | J1: grade_alignment | K1: real_world_feasibility | L1: clarity | M1: conciseness_and_relevance | N1: language_quality | O1: content_appropriateness | P1: explanation
A2: TD | B2: Question 1 | C2: 0 | D2: 4.6345649 | E2: 1 | F2: 1 | G2: 1 | H2: 1 | I2: 1 | J2: 0 | K2: 1 | L2: 1 | M2: 1 | N2: 1 | O2: 1 | P2: Grade alignment: Primary 3 students typically work with 3-digit numbers, but this problem uses 4-digit numbers (1245, 1298, 1156) which is typically introduced in Primary 4. The addition of 4-digit numbers exceeds the expected mathematical complexity for Primary 3 students.
A3: TD | B3: Question 2 | C3: 0 | D3: 9.7286408 | E3: 1 | F3: 1 | G3: 1 | H3: 1 | I3: 1 | J3: 1 | K3: 1 | L3: 1 | M3: 1 | N3: 1 | O3: 1
A4: TD | B4: Question 3 | C4: 0 | D4: 10.642204 | E4: 1 | F4: 1 | G4: 1 | H4: 1 | I4: 1 | J4: 1 | K4: 1 | L4: 1 | M4: 1 | N4: 1 | O4: 1
A5: TD | B5: Question 4 | C5: 0 | D5: 5.6356914 | E5: 1 | F5: 0 | G5: 1 | H5: 'NA | I5: 1 | J5: 'NA | K5: 1 | L5: 1 | M5: 1 | N5: 1 | O5: 1 | P5: Primary KC alignment: Problem requires multiplying 3-digit numbers by 1-digit numbers (126x4, 148x3, 235x2), but Primary 3 students typically learn multiplication of 2-digit by 1-digit numbers. Grade alignment: The multiplication operations involve 3-digit by 1-digit multiplication which exceeds typical Primary 3 curriculum expectations where students usually work with simpler multiplication facts and 2-digit by 1-digit operations.
A6: TD | B6: Question 5 | C6: 0 | D6: 2.9623332 | E6: 1 | F6: 1 | G6: 1 | H6: 1 | I6: 1 | J6: 1 | K6: 1 | L6: 1 | M6: 1 | N6: 1 | O6: 1
A7: TD | B7: Question 6 | C7: 0 | D7: 3.0652823 | E7: 1 | F7: 1 | G7: 1 | H7: 1 | I7: 1 | J7: 1 | K7: 1 | L7: 1 | M7: 1 | N7: 1 | O7: 1
A8: TD | B8: Question 7 | C8: 0 | D8: 11.272932 | E8: 1 | F8: 1 | G8: 1 | H8: 1 | I8: 1 | J8: 1 | K8: 1 | L8: 1 | M8: 1 | N8: 1 | O8: 1
A9: TD | B9: Question 8 | C9: 0 | D9: 8.3822763 | E9: 1 | F9: 1 | G9: 1 | H9: 1 | I9: 1 | J9: 1 | K9: 1 | L9: 1 | M9: 1 | N9: 1 | O9: 1
A10: TD | B10: Question 9 | C10: 0 | D10: 2.8803325 | E10: 1 | F10: 1 | G10: 1 | H10: 1 | I10: 1 | J10: 1 | K10: 1 | L10: 1 | M10: 1 | N10: 1 | O10: 1
A11: TD | B11: Question 10 | C11: 0 | D11: 7.7712424 | E11: 1 | F11: 1 | G11: 1 | H11: 1 | I11: 1 | J11: 1 | K11: 1 | L11: 0 | M11: 1 | N11: 1 | O11: 1 | P11: Clarity: The problem contains the phrase 'clarity' appears twice in the JSON structure which creates ambiguity in the evaluation framework. Additionally, while the problem context is clear, the transition between the two mathematical operations could be more explicitly connected in the problem statement.
A12: TD | B12: Question 11 | C12: 0 | D12: 13.712001 | E12: 0 | F12: 'NA | G12: 'NA | H12: 'NA | I12: 'NA | J12: 'NA | K12: 'NA | L12: 'NA | M12: 'NA | N12: 'NA | O12: 'NA | P12: Answerability: Questions (a) and (b) ask for totals when only single fractions are given per person per challenge, making them unanswerable as intended. Primary KC Alignment: Questions (a) and (b) do not require adding fractions - they only restate given information. The primary knowledge component is not properly targeted. Synergy: Primary and secondary knowledge components are not used together - questions (a) and (b) need no addition, and question (c) can be solved independently. Clarity: Questions (a) and (b) are ambiguous since they ask what fraction Sarah completed in total when only one fraction per challenge type is provided.
A13: TD | B13: Question 12 | C13: 0 | D13: 2.9679828 | E13: 1 | F13: 1 | G13: 1 | H13: 1 | I13: 1 | J13: 1 | K13: 1 | L13: 1 | M13: 1 | N13: 1 | O13: 1
A14: TD | B14: Question 13 | C14: 0 | D14: 11.611817 | E14: 1 | F14: 0 | G14: 1 | H14: 'NA | I14: 1 | J14: 'NA | K14: 1 | L14: 1 | M14: 1 | N14: 1 | O14: 1 | P14: Primary KC alignment: The intended primary component specifies adding decimals up to 2 decimal places, but the problem includes 1.142 which has 3 decimal places, exceeding the intended scope.
A15: TD | B15: Question 14 | C15: 0 | D15: 10.927273 | E15: 1 | F15: 0 | G15: 1 | H15: 'NA | I15: 1 | J15: 'NA | K15: 1 | L15: 1 | M15: 1 | N15: 1 | O15: 1 | P15: Primary KC alignment fails because the problem directly states Wednesday practice was 0.25 hours less than Monday, so no decimal subtraction calculation is needed - students just need to recognize 0.25 as the answer. Synergy fails because the primary KC (decimal subtraction) is not actually required to solve the problem, so the two knowledge components do not work together as intended.
A16: TD | B16: Question 15 | C16: 0 | D16: 10.436213 | E16: 1 | F16: 1 | G16: 1 | H16: 1 | I16: 1 | J16: 1 | K16: 1 | L16: 1 | M16: 1 | N16: 1 | O16: 1
A17: TD | B17: Question 16 | C17: 0 | D17: 12.342287 | E17: 1 | F17: 1 | G17: 1 | H17: 1 | I17: 1 | J17: 0 | K17: 1 | L17: 1 | M17: 1 | N17: 1 | O17: 1 | P17: Grade Alignment: The problem requires converting 2.45 to fraction form 245/100, then simplifying to 49/20, and final answer 147/20. Working with complex fractions like 49/20 and 147/20 exceeds typical Primary 4 mathematical abilities.
A18: TD | B18: Question 17 | C18: 0 | D18: 3.0017624 | E18: 1 | F18: 1 | G18: 1 | H18: 1 | I18: 1 | J18: 1 | K18: 1 | L18: 1 | M18: 1 | N18: 1 | O18: 1
A19: TD | B19: Question 18 | C19: 0 | D19: 7.3627777 | E19: 1 | F19: 1 | G19: 1 | H19: 1 | I19: 1 | J19: 1 | K19: 1 | L19: 1 | M19: 1 | N19: 1 | O19: 1
A20: TD | B20: Question 19 | C20: 0 | D20: 11.361562 | E20: 0 | F20: 'NA | G20: 'NA | H20: 'NA | I20: 'NA | J20: 'NA | K20: 'NA | L20: 'NA | M20: 'NA | N20: 'NA | O20: 'NA | P20: Answerability: The question what is the total distance Sarah swam per lap over the two days is ambiguous and unclear what specific calculation is required. Secondary KC alignment: Adding decimals is not clearly required since the question does not definitively ask for combining the per-lap distances. Synergy: The two knowledge components are not used in tandem as the addition step is not clearly necessary. Real-world feasibility: Swimming laps of 1.56-1.75 km each around a pool is unrealistic as typical pool laps are much shorter distances. Clarity: The final question is ambiguous about what calculation is actually wanted.
A21: TD | B21: Question 20 | C21: 0 | D21: 9.224318 | E21: 1 | F21: 1 | G21: 1 | H21: 1 | I21: 1 | J21: 1 | K21: 1 | L21: 1 | M21: 1 | N21: 1 | O21: 1
A22: TD | B22: Question 21 | C22: 0 | D22: 10.124666 | E22: 1 | F22: 1 | G22: 1 | H22: 1 | I22: 1 | J22: 1 | K22: 1 | L22: 1 | M22: 1 | N22: 1 | O22: 1
A23: TD | B23: Question 22 | C23: 0 | D23: 10.531391 | E23: 1 | F23: 1 | G23: 1 | H23: 1 | I23: 1 | J23: 1 | K23: 1 | L23: 1 | M23: 1 | N23: 1 | O23: 1
A24: TD | B24: Question 23 | C24: 0 | D24: 9.2260921 | E24: 1 | F24: 1 | G24: 1 | H24: 1 | I24: 1 | J24: 1 | K24: 1 | L24: 1 | M24: 1 | N24: 1 | O24: 1
A25: TD | B25: Question 24 | C25: 0 | D25: 2.8937142 | E25: 1 | F25: 1 | G25: 1 | H25: 1 | I25: 1 | J25: 1 | K25: 1 | L25: 1 | M25: 1 | N25: 1 | O25: 1
A26: TD | B26: Question 25 | C26: 0 | D26: 10.699326 | E26: 1 | F26: 1 | G26: 1 | H26: 1 | I26: 1 | J26: 1 | K26: 1 | L26: 1 | M26: 1 | N26: 1 | O26: 1
A27: TD | B27: Question 26 | C27: 0 | D27: 5.4365289 | E27: 1 | F27: 0 | G27: 1 | H27: 'NA | I27: 1 | J27: 'NA | K27: 1 | L27: 1 | M27: 1 | N27: 1 | O27: 1 | P27: Primary KC Alignment: The problem only requires adding fractions (7/4 + 5/3, 9/5 + 8/7, and summing the results). No multiplication of improper fractions is needed to solve any part of the problem. Synergy: The primary KC (multiplying improper fractions) is not used at all in the solution, so there is no synergy between the primary and secondary knowledge components.
A28: TD | B28: Question 27 | C28: 0 | D28: 14.998528 | E28: 1 | F28: 0 | G28: 1 | H28: 'NA | I28: 1 | J28: 'NA | K28: 1 | L28: 1 | M28: 1 | N28: 1 | O28: 1 | P28: Primary KC alignment: The problem does not focus on multiplying improper fractions as the main concept. The multiplication 23/12 * 3/2 occurs as part of division by reciprocal, not as the primary skill being tested. The main operations are fraction addition, subtraction, and division. Synergy: Since the primary KC is not properly aligned, the intended synergy between multiplying improper fractions and subtracting fractions is not achieved in the problem structure.
A29: TD | B29: Question 28 | C29: 0 | D29: 10.22271 | E29: 1 | F29: 1 | G29: 1 | H29: 1 | I29: 1 | J29: 1 | K29: 1 | L29: 1 | M29: 1 | N29: 1 | O29: 1
A30: TD | B30: Question 29 | C30: 0 | D30: 10.951265 | E30: 1 | F30: 1 | G30: 0 | H30: 'NA | I30: 1 | J30: 1 | K30: 1 | L30: 1 | M30: 1 | N30: 1 | O30: 1 | P30: Secondary KC alignment fails because the subtraction step involves whole numbers (22 - 19 = 3) rather than fractions as specified in the intended Secondary Knowledge Component of subtracting fractions.
A31: TD | B31: Question 30 | C31: 0 | D31: 6.4785011 | E31: 1 | F31: 0 | G31: 1 | H31: 'NA | I31: 1 | J31: 'NA | K31: 1 | L31: 1 | M31: 1 | N31: 1 | O31: 1 | P31: Primary KC alignment fails because the problem requires multiplying 0.875 x 300, which is multiplying a decimal by a whole number that is not 10, 100, 1000 or their multiples. The intended primary KC specifically targets multiplication by 10, 100, 1000 and their multiples only. Synergy fails because the primary KC (decimal multiplication by powers of 10) is not actually needed to solve this problem - students would directly multiply 0.875 x 300 without using the specific skill of multiplying by 10, 100, 1000, then convert the result to mixed number form using only the secondary KC.
A32: TD | B32: Question 31 | C32: 0 | D32: 6.3718319 | E32: 1 | F32: 0 | G32: 1 | H32: 'NA | I32: 1 | J32: 'NA | K32: 1 | L32: 1 | M32: 1 | N32: 1 | O32: 1 | P32: Primary KC alignment: The problem requires multiplying 0.125 x 400, which is multiplying a decimal by a whole number, not specifically multiplying decimals by 10, 100, 1000 or their multiples as intended. Synergy: The two parts of the problem are independent - the first part calculates distance (0.125 x 400 = 50), the second part subtracts (65.8 - 50 = 15.8). The primary KC (decimal multiplication by powers of 10) and secondary KC (decimal subtraction) are not used in tandem as the multiplication does not involve powers of 10.
A33: TD | B33: Question 32 | C33: 0 | D33: 9.3042269 | E33: 1 | F33: 0 | G33: 1 | H33: 'NA | I33: 1 | J33: 'NA | K33: 1 | L33: 1 | M33: 1 | N33: 1 | O33: 1 | P33: Primary KC requires dividing decimals by 10, 100, 1000 and their multiples, but the problem divides 127.850 by 7, which is general decimal division not the specific targeted skill.
A34: TD | B34: Question 33 | C34: 0 | D34: 11.838382 | E34: 1 | F34: 1 | G34: 1 | H34: 1 | I34: 1 | J34: 1 | K34: 0 | L34: 1 | M34: 1 | N34: 1 | O34: 1 | P34: Real-world feasibility fails because swimming 40000 meters in 4 laps of approximately 10 minutes total would require each lap to be 10000 meters and swimming speed of about 60 km/h which is impossible for humans.
A35: TD | B35: Question 34 | C35: 0 | D35: 10.259708 | E35: 1 | F35: 1 | G35: 1 | H35: 1 | I35: 1 | J35: 1 | K35: 1 | L35: 1 | M35: 1 | N35: 1 | O35: 1
A36: TD | B36: Question 35 | C36: 0 | D36: 8.6072161 | E36: 1 | F36: 1 | G36: 1 | H36: 1 | I36: 1 | J36: 1 | K36: 0 | L36: 1 | M36: 1 | N36: 1 | O36: 1 | P36: Real-world feasibility: In basketball tournaments, teams typically have 5 starting players + 7-12 substitutes = 12-17 total players per team. Having 30 players per team with 15 eliminated per team is unrealistic for standard basketball tournament structure.
A37: TD | B37: Question 36 | C37: 0 | D37: 7.4785573 | E37: 1 | F37: 1 | G37: 1 | H37: 1 | I37: 1 | J37: 1 | K37: 0 | L37: 1 | M37: 1 | N37: 1 | O37: 1 | P37: Real-world feasibility fails because 1.25 km/h is an unrealistically slow running pace - this is slower than normal walking speed (4-5 km/h). Marathon runners typically run at 10-20 km/h during training. This speed would be more appropriate for a very slow walk rather than running training.
A38: TD | B38: Question 37 | C38: 0 | D38: 9.6309726 | E38: 1 | F38: 1 | G38: 1 | H38: 1 | I38: 1 | J38: 1 | K38: 1 | L38: 1 | M38: 1 | N38: 1 | O38: 1
A39: TD | B39: Question 38 | C39: 0 | D39: 3.0311999 | E39: 1 | F39: 1 | G39: 1 | H39: 1 | I39: 1 | J39: 1 | K39: 1 | L39: 1 | M39: 1 | N39: 1 | O39: 1
A40: TD | B40: Question 39 | C40: 0 | D40: 11.142194 | E40: 1 | F40: 1 | G40: 1 | H40: 1 | I40: 1 | J40: 1 | K40: 0 | L40: 1 | M40: 1 | N40: 1 | O40: 1 | P40: Real-world plausibility: The concept of dividing practice time over 2/3 of a week is unrealistic. People do not typically plan activities for fractional portions of a week in real life scenarios.
A41: TD | B41: Question 40 | C41: 0 | D41: 9.0538862 | E41: 0 | F41: 'NA | G41: 'NA | H41: 'NA | I41: 'NA | J41: 'NA | K41: 'NA | L41: 'NA | M41: 'NA | N41: 'NA | O41: 'NA | P41: Answerability: Missing critical information - Sarah's total practice time for today is not given, making the problem unsolvable. To find number of sessions = (3/4 * total time) / (2/5 hour per session), we need the total time. Clarity: The problem setup is ambiguous about what information is available versus what needs to be found, leading to confusion about the solution approach.
A42: TD | B42: Question 41 | C42: 0 | D42: 10.538192 | E42: 1 | F42: 1 | G42: 1 | H42: 1 | I42: 1 | J42: 1 | K42: 1 | L42: 1 | M42: 1 | N42: 1 | O42: 1
A43: TD | B43: Question 42 | C43: 0 | D43: 7.7775462 | E43: 1 | F43: 1 | G43: 0 | H43: 'NA | I43: 1 | J43: 1 | K43: 1 | L43: 1 | M43: 0 | N43: 1 | O43: 1 | P43: Secondary KC alignment: The problem requires division (36/180) but this involves dividing whole numbers where 36/180 = 1/5, which is more about fractions/decimals than pure whole number division. Synergy: Since the secondary KC is not properly aligned, true synergy between primary and secondary KCs cannot be achieved. Conciseness: The shooting accuracy data (180/300 and 216/360) is irrelevant to solving the percentage increase question, as only the successful shot counts (180 and 216) are needed.
A44: TD | B44: Question 43 | C44: 0 | D44: 5.0243139 | E44: 1 | F44: 1 | G44: 0 | H44: 'NA | I44: 1 | J44: 1 | K44: 1 | L44: 1 | M44: 1 | N44: 1 | O44: 1 | P44: Secondary KC Alignment: The problem does not require addition of whole numbers to solve. The solution only needs finding the ratio 45:36:54 and simplifying it to 5:4:6 by dividing by GCD of 9. No addition is needed. Synergy: Since the secondary knowledge component (addition) is not required for solving the problem, there is no synergy between the primary and secondary knowledge components.
A45: TD | B45: Question 44 | C45: 0 | D45: 11.355181 | E45: 1 | F45: 1 | G45: 1 | H45: 1 | I45: 1 | J45: 0 | K45: 1 | L45: 1 | M45: 1 | N45: 1 | O45: 1 | P45: Grade alignment fails because Primary 6 students in Singapore have not typically learned algebraic variables and linear equations. This content involving variable x and algebraic expression manipulation is usually introduced in Secondary 1-2, making it too advanced for the intended grade level.
A46: TD | B46: Question 45 | C46: 0 | D46: 5.358536 | E46: 1 | F46: 1 | G46: 1 | H46: 1 | I46: 1 | J46: 0 | K46: 1 | L46: 1 | M46: 1 | N46: 1 | O46: 1 | P46: Grade Alignment: This problem is too simple for Secondary O-level 1 students. The percentage calculations (25% and 15%) and whole number operations involved are more appropriate for upper primary levels (Primary 5-6). Secondary O-level 1 students would typically handle more complex percentage problems involving compound percentages, fractional percentages, or multi-step percentage applications that are more mathematically challenging.
A47: TD | B47: Question 46 | C47: 0 | D47: 12.037617 | E47: 1 | F47: 1 | G47: 1 | H47: 1 | I47: 1 | J47: 0 | K47: 1 | L47: 1 | M47: 1 | N47: 1 | O47: 1 | P47: Grade alignment issue: The problem involves basic reverse percentage calculation (36 / 0.72 = 50) which is typically taught at Primary 5-6 level in Singapore curriculum, but it is assigned to Secondary O-level 1 students who would be learning much more advanced mathematical concepts. This makes the problem inappropriately easy for the intended grade level.
A48: TD | B48: Question 47 | C48: 0 | D48: 12.445556 | E48: 1 | F48: 1 | G48: 1 | H48: 0 | I48: 1 | J48: 0 | K48: 1 | L48: 1 | M48: 1 | N48: 1 | O48: 1 | P48: Synergy: The multiplication component (x4) is too simple and does not meaningfully integrate with the ratio component - it serves as basic arithmetic rather than a substantial secondary knowledge component that adds complexity. Grade Alignment: The problem involves basic ratio concepts and simple multiplication suitable for Primary 5-6 level, making it too elementary for Secondary O-level 2 students who should be challenged with more advanced mathematical concepts.
A49: TD | B49: Question 48 | C49: 0 | D49: 8.8264439 | E49: 1 | F49: 1 | G49: 1 | H49: 1 | I49: 1 | J49: 1 | K49: 1 | L49: 1 | M49: 1 | N49: 1 | O49: 1
A50: TD | B50: Question 49 | C50: 0 | D50: 5.0662704 | E50: 1 | F50: 1 | G50: 1 | H50: 1 | I50: 1 | J50: 0 | K50: 1 | L50: 1 | M50: 1 | N50: 1 | O50: 1 | P50: Grade Alignment: Standard deviation calculation is typically introduced at upper secondary levels (O-level 4/5 or A-levels), not at Secondary O-level 3/4. At O-level 3/4, students typically work with basic statistics like mean, median, mode, and range, but standard deviation is more advanced mathematical concept that requires understanding of variance and square roots of sums of squared deviations.
A51: Minh | B51: Question 1 | C51: 0 | D51: 11.931627 | E51: 1 | F51: 1 | G51: 1 | H51: 1 | I51: 1 | J51: 0 | K51: 1 | L51: 1 | M51: 1 | N51: 1 | O51: 1 | P51: Grade Alignment: The problem uses 4-digit numbers (8524, 6789, 7356) which are typically introduced in Primary 4, not Primary 3. Primary 3 students in Singapore math curriculum typically work with numbers up to 1000.
A52: Minh | B52: Question 2 | C52: 0 | D52: 10.021155 | E52: 1 | F52: 1 | G52: 0 | H52: 'NA | I52: 1 | J52: 1 | K52: 1 | L52: 1 | M52: 1 | N52: 1 | O52: 1 | P52: Secondary KC alignment: The third question asks for total students participating, which is just the given number 847, requiring no addition operation. Synergy: The questions do not build on each other - the third question does not use results from the first two questions to create meaningful connection.
A53: Minh | B53: Question 3 | C53: 0 | D53: 7.5161824 | E53: 1 | F53: 1 | G53: 1 | H53: 1 | I53: 1 | J53: 0 | K53: 0 | L53: 1 | M53: 1 | N53: 1 | O53: 1 | P53: Grade alignment: Primary 3 students typically work with 2-digit multiplication, but this problem requires 43 x 7 = 301, which is challenging 2-digit x 1-digit multiplication that may exceed typical Primary 3 expectations. Real-world feasibility: The scenario of giving 7 sheets of paper per paintbrush (301 sheets per group, 2408 total sheets) is unrealistic for a typical art club painting activity - this creates an impractical paper-to-paintbrush ratio.
A54: Minh | B54: Question 4 | C54: 0 | D54: 2.9210894 | E54: 1 | F54: 1 | G54: 1 | H54: 1 | I54: 1 | J54: 1 | K54: 1 | L54: 1 | M54: 1 | N54: 1 | O54: 1
A55: Minh | B55: Question 5 | C55: 0 | D55: 10.830088 | E55: 1 | F55: 1 | G55: 1 | H55: 1 | I55: 1 | J55: 0 | K55: 1 | L55: 1 | M55: 1 | N55: 1 | O55: 1 | P55: Grade alignment issue: The problem requires 816 / 6 which is 3-digit by 1-digit division typically taught in Primary 4, not Primary 3 where students usually learn 2-digit by 1-digit division.
A56: Minh | B56: Question 6 | C56: 0 | D56: 6.614145 | E56: 1 | F56: 1 | G56: 0 | H56: 'NA | I56: 1 | J56: 1 | K56: 1 | L56: 1 | M56: 1 | N56: 1 | O56: 1 | P56: Secondary KC alignment fails because the problem requires only division operations (432/6=72, then 72/4=18) but the intended secondary KC is multiplication. The problem does not require multiplying whole numbers at any step. Synergy fails because both questions use division only, not the intended combination of division and multiplication working together.
A57: Minh | B57: Question 7 | C57: 0 | D57: 9.2682793 | E57: 1 | F57: 1 | G57: 1 | H57: 1 | I57: 1 | J57: 1 | K57: 1 | L57: 1 | M57: 1 | N57: 1 | O57: 1
A58: Minh | B58: Question 8 | C58: 0 | D58: 14.442602 | E58: 1 | F58: 1 | G58: 1 | H58: 1 | I58: 1 | J58: 0 | K58: 1 | L58: 1 | M58: 1 | N58: 1 | O58: 1 | P58: Grade Alignment: The problem requires finding common denominators for fractions with denominators 8 and 12 (LCM = 24), working with three different fractions simultaneously, and interpreting negative results. These concepts typically exceed Primary 3 level and are more appropriate for Primary 4-5.
A59: Minh | B59: Question 9 | C59: 0 | D59: 9.4025464 | E59: 1 | F59: 1 | G59: 1 | H59: 1 | I59: 1 | J59: 1 | K59: 1 | L59: 1 | M59: 1 | N59: 1 | O59: 1
A60: Minh | B60: Question 10 | C60: 0 | D60: 4.9054663 | E60: 1 | F60: 1 | G60: 1 | H60: 1 | I60: 1 | J60: 1 | K60: 0 | L60: 1 | M60: 1 | N60: 1 | O60: 1 | P60: Real-world feasibility: The numbers of students attending from each school (2856, 1944, 3528) are unrealistically large for primary schools attending a badminton tournament. Typical primary schools have 300-800 total students, and bringing nearly 3000 students to a single sporting event is logistically implausible and does not mirror realistic school operations.
A61: Minh | B61: Question 11 | C61: 0 | D61: 7.8476911 | E61: 1 | F61: 1 | G61: 1 | H61: 1 | I61: 1 | J61: 1 | K61: 1 | L61: 1 | M61: 1 | N61: 1 | O61: 1
A62: Minh | B62: Question 12 | C62: 0 | D62: 3.0901854 | E62: 1 | F62: 1 | G62: 1 | H62: 1 | I62: 1 | J62: 1 | K62: 1 | L62: 1 | M62: 1 | N62: 1 | O62: 1
A63: Minh | B63: Question 13 | C63: 0 | D63: 2.9296267 | E63: 1 | F63: 1 | G63: 1 | H63: 1 | I63: 1 | J63: 1 | K63: 1 | L63: 1 | M63: 1 | N63: 1 | O63: 1
A64: Minh | B64: Question 14 | C64: 0 | D64: 9.4290636 | E64: 1 | F64: 1 | G64: 1 | H64: 1 | I64: 1 | J64: 1 | K64: 1 | L64: 1 | M64: 1 | N64: 1 | O64: 1
A65: Minh | B65: Question 15 | C65: 0 | D65: 7.4076402 | E65: 1 | F65: 0 | G65: 1 | H65: 'NA | I65: 1 | J65: 'NA | K65: 1 | L65: 1 | M65: 1 | N65: 1 | O65: 1 | P65: Primary KC alignment fails because the intended Primary KC is adding decimals up to 2 decimal places, but the problem requires adding 3.126 which has 3 decimal places, exceeding the specified scope of the Primary KC.
A66: Minh | B66: Question 16 | C66: 0 | D66: 10.041718 | E66: 1 | F66: 1 | G66: 1 | H66: 1 | I66: 1 | J66: 1 | K66: 1 | L66: 1 | M66: 1 | N66: 1 | O66: 1
A67: Minh | B67: Question 17 | C67: 0 | D67: 2.9412725 | E67: 1 | F67: 1 | G67: 1 | H67: 1 | I67: 1 | J67: 1 | K67: 1 | L67: 1 | M67: 1 | N67: 1 | O67: 1
A68: Minh | B68: Question 18 | C68: 0 | D68: 12.64755 | E68: 1 | F68: 1 | G68: 0 | H68: 'NA | I68: 1 | J68: 1 | K68: 1 | L68: 1 | M68: 0 | N68: 1 | O68: 1 | P68: Secondary KC alignment: The problem can be solved using only 8.91 / 3 = 2.97, decimal subtraction is not required. Synergy: Since decimal subtraction is not needed, the two knowledge components do not work together. Conciseness: The purchase amounts 12.48 and 2.76 are irrelevant since 8.91 remaining is already given.
A69: Minh | B69: Question 19 | C69: 0 | D69: 11.425162 | E69: 1 | F69: 1 | G69: 0 | H69: 'NA | I69: 1 | J69: 1 | K69: 1 | L69: 1 | M69: 1 | N69: 1 | O69: 1 | P69: Secondary KC alignment fails because 2 3/8 + 1 5/8 = 4 and 3 1/4 + 2 3/4 = 6, giving total = 10, which is already in simplest form - no simplification needed. Synergy fails because the secondary knowledge component is not actually used, so primary and secondary components do not work together.
A70: Minh | B70: Question 20 | C70: 0 | D70: 8.4926324 | E70: 1 | F70: 1 | G70: 1 | H70: 1 | I70: 1 | J70: 1 | K70: 1 | L70: 1 | M70: 1 | N70: 1 | O70: 1
A71: Minh | B71: Question 21 | C71: 0 | D71: 11.245759 | E71: 1 | F71: 1 | G71: 1 | H71: 1 | I71: 1 | J71: 1 | K71: 1 | L71: 1 | M71: 1 | N71: 1 | O71: 1
A72: Minh | B72: Question 22 | C72: 0 | D72: 10.28169 | E72: 1 | F72: 1 | G72: 1 | H72: 1 | I72: 1 | J72: 1 | K72: 1 | L72: 1 | M72: 1 | N72: 1 | O72: 1
A73: Minh | B73: Question 23 | C73: 0 | D73: 2.8853719 | E73: 1 | F73: 1 | G73: 1 | H73: 1 | I73: 1 | J73: 1 | K73: 1 | L73: 1 | M73: 1 | N73: 1 | O73: 1
A74: Minh | B74: Question 24 | C74: 0 | D74: 11.217943 | E74: 1 | F74: 1 | G74: 1 | H74: 1 | I74: 1 | J74: 1 | K74: 1 | L74: 1 | M74: 1 | N74: 1 | O74: 1
A75: Minh | B75: Question 25 | C75: 0 | D75: 9.8390038 | E75: 1 | F75: 1 | G75: 1 | H75: 1 | I75: 1 | J75: 1 | K75: 1 | L75: 1 | M75: 1 | N75: 1 | O75: 1
A76: Minh | B76: Question 26 | C76: 0 | D76: 8.0661654 | E76: 1 | F76: 1 | G76: 1 | H76: 1 | I76: 1 | J76: 1 | K76: 1 | L76: 1 | M76: 1 | N76: 1 | O76: 1
A77: Minh | B77: Question 27 | C77: 0 | D77: 4.8132257 | E77: 1 | F77: 0 | G77: 1 | H77: 'NA | I77: 1 | J77: 'NA | K77: 1 | L77: 1 | M77: 1 | N77: 1 | O77: 1 | P77: Primary KC alignment fails because the problem requires multiplying 23.456 x 30, which is multiplication of a decimal by a 2-digit number, not multiplication by 10, 100, 1000 or their multiples as specified in the intended Primary Knowledge Component.
A78: Minh | B78: Question 28 | C78: 0 | D78: 5.0024016 | E78: 1 | F78: 0 | G78: 1 | H78: 'NA | I78: 1 | J78: 'NA | K78: 1 | L78: 1 | M78: 1 | N78: 1 | O78: 1 | P78: Primary KC alignment: The problem requires dividing 142.8 by 60, which involves dividing a decimal by a non-multiple of 10/100/1000. The intended primary KC specifies division by 10, 100, 1000 and their multiples only, but 60 is not a multiple of these numbers (60 = 2^2 * 3 * 5).
A79: Minh | B79: Question 29 | C79: 0 | D79: 6.9890454 | E79: 1 | F79: 1 | G79: 1 | H79: 1 | I79: 1 | J79: 1 | K79: 1 | L79: 1 | M79: 1 | N79: 1 | O79: 1
A80: Minh | B80: Question 30 | C80: 0 | D80: 9.1687217 | E80: 1 | F80: 1 | G80: 1 | H80: 1 | I80: 1 | J80: 1 | K80: 1 | L80: 1 | M80: 1 | N80: 1 | O80: 1
A81: Minh | B81: Question 31 | C81: 0 | D81: 11.41047 | E81: 1 | F81: 1 | G81: 0 | H81: 'NA | I81: 1 | J81: 1 | K81: 0 | L81: 1 | M81: 1 | N81: 1 | O81: 1 | P81: Secondary KC alignment fails: problem converts from larger unit km to smaller unit meters, not smaller to larger as intended. Real-world feasibility fails: 1.25 km/min equals 75 km/hour which is unrealistic for human running speed.
A82: Minh | B82: Question 32 | C82: 0 | D82: 6.7229023 | E82: 1 | F82: 1 | G82: 0 | H82: 'NA | I82: 1 | J82: 1 | K82: 1 | L82: 1 | M82: 1 | N82: 1 | O82: 1 | P82: Secondary KC Alignment: The problem does not involve converting measurements from larger units in decimal form to smaller units. All values (0.8 laps/minute, 21.6 minutes) remain in their original units throughout the solution. No unit conversion occurs. Synergy: Since the secondary knowledge component is not present in the problem, there is no synergy between primary and secondary knowledge components. The problem only requires rate calculations with decimal multiplication.
A83: Minh | B83: Question 33 | C83: 0 | D83: 8.1109457 | E83: 1 | F83: 1 | G83: 1 | H83: 1 | I83: 1 | J83: 1 | K83: 1 | L83: 1 | M83: 1 | N83: 1 | O83: 1
A84: Minh | B84: Question 34 | C84: 0 | D84: 7.2218845 | E84: 0 | F84: 'NA | G84: 'NA | H84: 'NA | I84: 'NA | J84: 'NA | K84: 'NA | L84: 'NA | M84: 'NA | N84: 'NA | O84: 'NA | P84: Answerability: Tuesday calculation gives 11/6 divided by 2/9 = 33/4 = 8.25 sessions. Cannot have fractional practice sessions in real world context. Real-World Plausibility: Same issue - 8.25 sessions is not realistic for actual practice sessions which must be whole numbers.
A85: Minh | B85: Question 35 | C85: 0 | D85: 9.5925035 | E85: 1 | F85: 1 | G85: 1 | H85: 1 | I85: 1 | J85: 1 | K85: 1 | L85: 1 | M85: 1 | N85: 1 | O85: 1
A86: Minh | B86: Question 36 | C86: 0 | D86: 12.05483 | E86: 1 | F86: 1 | G86: 1 | H86: 1 | I86: 1 | J86: 1 | K86: 1 | L86: 1 | M86: 1 | N86: 1 | O86: 1
A87: Minh | B87: Question 37 | C87: 0 | D87: 2.9784312 | E87: 1 | F87: 1 | G87: 1 | H87: 1 | I87: 1 | J87: 1 | K87: 1 | L87: 1 | M87: 1 | N87: 1 | O87: 1
A88: Minh | B88: Question 38 | C88: 0 | D88: 13.83016 | E88: 1 | F88: 1 | G88: 1 | H88: 0 | I88: 1 | J88: 1 | K88: 1 | L88: 1 | M88: 1 | N88: 1 | O88: 1 | P88: Synergy: The two questions are independent - the point calculation (45*3=135, 63*3=189, 189-135=54) is not needed for the percentage calculation ((63-45)/45*100=40%). The questions should be connected where the result of the first question is used in the second question.
A89: Minh | B89: Question 39 | C89: 0 | D89: 9.5830622 | E89: 1 | F89: 1 | G89: 1 | H89: 1 | I89: 1 | J89: 1 | K89: 1 | L89: 1 | M89: 1 | N89: 1 | O89: 1
A90: Minh | B90: Question 40 | C90: 0 | D90: 10.133409 | E90: 1 | F90: 1 | G90: 1 | H90: 1 | I90: 1 | J90: 1 | K90: 1 | L90: 1 | M90: 1 | N90: 1 | O90: 1
A91: Minh | B91: Question 41 | C91: 0 | D91: 11.079493 | E91: 1 | F91: 1 | G91: 1 | H91: 1 | I91: 1 | J91: 1 | K91: 1 | L91: 1 | M91: 1 | N91: 1 | O91: 1
A92: Minh | B92: Question 42 | C92: 0 | D92: 8.0458412 | E92: 1 | F92: 1 | G92: 1 | H92: 1 | I92: 1 | J92: 1 | K92: 1 | L92: 1 | M92: 1 | N92: 1 | O92: 1
A93: Minh | B93: Question 43 | C93: 0 | D93: 4.444521 | E93: 1 | F93: 1 | G93: 1 | H93: 1 | I93: 1 | J93: 0 | K93: 1 | L93: 1 | M93: 1 | N93: 1 | O93: 1 | P93: Grade Alignment: This problem requires algebraic expressions with variables (a, b) and substitution, which are typically introduced in Secondary 1-2 mathematics curriculum, not Primary 6. Primary 6 students typically work with basic arithmetic and simple word problems without algebraic variables.
A94: Minh | B94: Question 44 | C94: 0 | D94: 10.498931 | E94: 1 | F94: 1 | G94: 1 | H94: 1 | I94: 1 | J94: 1 | K94: 1 | L94: 1 | M94: 1 | N94: 1 | O94: 1
A95: Minh | B95: Question 45 | C95: 0 | D95: 13.469226 | E95: 1 | F95: 1 | G95: 1 | H95: 1 | I95: 1 | J95: 0 | K95: 1 | L95: 1 | M95: 1 | N95: 1 | O95: 1 | P95: Grade Alignment: The problem involves basic fraction subtraction (3/4 - 1/6, 5/6 - 1/4) and simple ratio calculation, which are typically Primary 5-6 level concepts in Singapore math curriculum. This is too elementary for Secondary O-level 1 students who should be working with more advanced algebraic concepts and complex ratios.
A96: Minh | B96: Question 46 | C96: 0 | D96: 5.6138499 | E96: 1 | F96: 1 | G96: 1 | H96: 1 | I96: 1 | J96: 0 | K96: 1 | L96: 1 | M96: 1 | N96: 1 | O96: 1 | P96: Grade alignment: This problem involves basic fraction operations (multiplication by 7, finding ratios with simple fractions like 3/4 and 1/2, and division by 3) which are typically mastered in Primary 5-6. Secondary O-level 1 students would find this problem too elementary as they should be working with more complex algebraic concepts, advanced fraction operations, or multi-step ratio problems involving variables.
A97: Minh | B97: Question 47 | C97: 0 | D97: 11.891526 | E97: 1 | F97: 1 | G97: 1 | H97: 1 | I97: 1 | J97: 0 | K97: 1 | L97: 1 | M97: 1 | N97: 1 | O97: 1 | P97: Grade Alignment: The problem involves basic decimal subtraction (24.8 - 5.4, 18.6 - 5.4, 31.2 - 5.4) and simple ratio work, which is too elementary for Secondary O-level 1 students. This level of mathematical content would be more appropriate for Primary 5-6 grade levels.
A98: Minh | B98: Question 48 | C98: 0 | D98: 6.7512319 | E98: 1 | F98: 1 | G98: 1 | H98: 1 | I98: 1 | J98: 0 | K98: 1 | L98: 1 | M98: 1 | N98: 1 | O98: 1 | P98: Grade Alignment: This problem involves basic percentage calculations (24/40 = 60%, 18/30 = 60%) and simple decimal conversion (60% = 0.60) that students typically learn in Primary 5-6. Secondary O-level 1 students would find this too elementary as they should be working with more complex percentage applications like compound interest, percentage error, or multi-step percentage problems.
A99: Minh | B99: Question 49 | C99: 0 | D99: 5.2088816 | E99: 1 | F99: 1 | G99: 1 | H99: 1 | I99: 1 | J99: 0 | K99: 1 | L99: 1 | M99: 1 | N99: 1 | O99: 1 | P99: Grade alignment: This problem involves basic percentage calculations (25% increase) and simple division (480/12), which are concepts typically mastered in upper primary grades (Primary 5-6). For Secondary O-level 1 students, this problem would be too elementary and does not challenge students at the appropriate grade level with more complex mathematical concepts expected at that stage.
A100: Minh | B100: Question 50 | C100: 0 | D100: 11.662914 | E100: 0 | F100: 'NA | G100: 'NA | H100: 'NA | I100: 'NA | J100: 'NA | K100: 'NA | L100: 'NA | M100: 'NA | N100: 'NA | O100: 'NA | P100: Answerability: The connection between wanting to finish in 30 minutes and needing to know progress at 12 minutes is unclear and illogical. Primary KC: Problem can be solved with simple proportions, not fractional equations. Secondary KC: No equation setup required, just direct calculation. Synergy: Knowledge components not used together as problem doesn't require algebraic approach. Clarity: The phrase 'to stay on track' and relevance of 12 minutes is ambiguous. Conciseness: The 30-minute target information is irrelevant to solving the actual question asked.
...

Sheet recreation_claude_v2_3
A1: Evaluator | B1: Question | C1: status | D1: response_time | E1: answerability | F1: primary_kc_alignment | G1: secondary_kc_alignment | H1: synergy | I1: topic_alignment | J1: grade_alignment | K1: real_world_feasibility | L1: clarity | M1: conciseness_and_relevance | N1: language_quality | O1: content_appropriateness | P1: explanation
A2: TD | B2: Question 1 | C2: 0 | D2: 9.9057977 | E2: 1 | F2: 1 | G2: 1 | H2: 1 | I2: 1 | J2: 1 | K2: 1 | L2: 1 | M2: 1 | N2: 1 | O2: 1
A3: TD | B3: Question 2 | C3: 0 | D3: 2.9739623 | E3: 1 | F3: 1 | G3: 1 | H3: 1 | I3: 1 | J3: 1 | K3: 1 | L3: 1 | M3: 1 | N3: 1 | O3: 1
A4: TD | B4: Question 3 | C4: 0 | D4: 7.9791753 | E4: 1 | F4: 1 | G4: 1 | H4: 1 | I4: 1 | J4: 1 | K4: 1 | L4: 1 | M4: 1 | N4: 1 | O4: 1
A5: TD | B5: Question 4 | C5: 0 | D5: 6.3302639 | E5: 1 | F5: 0 | G5: 1 | H5: 'NA | I5: 1 | J5: 'NA | K5: 1 | L5: 1 | M5: 1 | N5: 1 | O5: 1 | P5: Primary KC alignment: The problem requires multiplying 3-digit numbers (126, 148, 235) by 1-digit numbers (4, 3, 2), but the intended primary KC is multiplying whole numbers UP TO 3 digits by 1 digit, which typically means the multiplicand should be at most 3 digits but the complexity suggests this exceeds Primary 3 level expectations. Grade alignment: Multiplying 3-digit by 1-digit numbers like 126×4=504, 148×3=444, 235×2=470 requires advanced multiplication skills typically taught in Primary 4 or higher, not Primary 3.
A6: TD | B6: Question 5 | C6: 0 | D6: 2.9503314 | E6: 1 | F6: 1 | G6: 1 | H6: 1 | I6: 1 | J6: 1 | K6: 1 | L6: 1 | M6: 1 | N6: 1 | O6: 1
A7: TD | B7: Question 6 | C7: 0 | D7: 3.0048316 | E7: 1 | F7: 1 | G7: 1 | H7: 1 | I7: 1 | J7: 1 | K7: 1 | L7: 1 | M7: 1 | N7: 1 | O7: 1
A8: TD | B8: Question 7 | C8: 0 | D8: 10.941786 | E8: 1 | F8: 1 | G8: 1 | H8: 1 | I8: 1 | J8: 1 | K8: 1 | L8: 1 | M8: 1 | N8: 1 | O8: 1
A9: TD | B9: Question 8 | C9: 0 | D9: 8.5720222 | E9: 1 | F9: 1 | G9: 1 | H9: 1 | I9: 1 | J9: 1 | K9: 1 | L9: 1 | M9: 1 | N9: 1 | O9: 1
A10: TD | B10: Question 9 | C10: 0 | D10: 7.4044814 | E10: 1 | F10: 1 | G10: 1 | H10: 1 | I10: 1 | J10: 1 | K10: 1 | L10: 1 | M10: 1 | N10: 1 | O10: 1
A11: TD | B11: Question 10 | C11: 0 | D11: 10.857038 | E11: 1 | F11: 1 | G11: 1 | H11: 1 | I11: 1 | J11: 1 | K11: 1 | L11: 1 | M11: 1 | N11: 1 | O11: 1
A12: TD | B12: Question 11 | C12: 0 | D12: 13.191507 | E12: 0 | F12: 'NA | G12: 'NA | H12: 'NA | I12: 'NA | J12: 'NA | K12: 'NA | L12: 'NA | M12: 'NA | N12: 'NA | O12: 'NA | P12: Answerability: Questions (a) and (b) ask for totals but only provide single fractions per person per activity - Sarah has 2/3 painting and 1/4 music, Emma has 1/2 painting and 3/8 music. No addition possible. Primary KC Alignment: Primary component requires adding unlike fractions but questions (a) and (b) involve single fractions only, no addition needed. Synergy: Addition and comparison components cannot work together since addition component is not properly utilized. Clarity: Asking for total fractions when only single values exist per category creates confusion.
A13: TD | B13: Question 12 | C13: 0 | D13: 2.8128757 | E13: 1 | F13: 1 | G13: 1 | H13: 1 | I13: 1 | J13: 1 | K13: 1 | L13: 1 | M13: 1 | N13: 1 | O13: 1
A14: TD | B14: Question 13 | C14: 0 | D14: 11.63449 | E14: 1 | F14: 0 | G14: 1 | H14: 'NA | I14: 1 | J14: 'NA | K14: 1 | L14: 1 | M14: 1 | N14: 1 | O14: 1 | P14: Primary KC alignment: The problem requires adding decimals including 1.142 which has 3 decimal places, exceeding the intended scope of up to 2 decimal places for addition.
A15: TD | B15: Question 14 | C15: 0 | D15: 3.0382113 | E15: 1 | F15: 1 | G15: 1 | H15: 1 | I15: 1 | J15: 1 | K15: 1 | L15: 1 | M15: 1 | N15: 1 | O15: 1
A16: TD | B16: Question 15 | C16: 0 | D16: 9.9127398 | E16: 1 | F16: 1 | G16: 1 | H16: 1 | I16: 1 | J16: 1 | K16: 1 | L16: 1 | M16: 1 | N16: 1 | O16: 1
A17: TD | B17: Question 16 | C17: 0 | D17: 11.510377 | E17: 1 | F17: 1 | G17: 1 | H17: 1 | I17: 1 | J17: 0 | K17: 1 | L17: 1 | M17: 1 | N17: 1 | O17: 1 | P17: Grade Alignment: Converting decimals to fractions and fraction simplification are typically taught in Primary 5-6, making this problem too advanced for Primary 4 students.
A18: TD | B18: Question 17 | C18: 0 | D18: 2.9226916 | E18: 1 | F18: 1 | G18: 1 | H18: 1 | I18: 1 | J18: 1 | K18: 1 | L18: 1 | M18: 1 | N18: 1 | O18: 1
A19: TD | B19: Question 18 | C19: 0 | D19: 2.9136155 | E19: 1 | F19: 1 | G19: 1 | H19: 1 | I19: 1 | J19: 1 | K19: 1 | L19: 1 | M19: 1 | N19: 1 | O19: 1
A20: TD | B20: Question 19 | C20: 0 | D20: 11.08664 | E20: 1 | F20: 1 | G20: 1 | H20: 1 | I20: 1 | J20: 1 | K20: 1 | L20: 1 | M20: 1 | N20: 1 | O20: 1
A21: TD | B21: Question 20 | C21: 0 | D21: 10.205905 | E21: 1 | F21: 1 | G21: 1 | H21: 1 | I21: 1 | J21: 1 | K21: 1 | L21: 1 | M21: 1 | N21: 1 | O21: 1
A22: TD | B22: Question 21 | C22: 0 | D22: 9.5037072 | E22: 1 | F22: 1 | G22: 1 | H22: 1 | I22: 1 | J22: 1 | K22: 1 | L22: 1 | M22: 1 | N22: 1 | O22: 1
A23: TD | B23: Question 22 | C23: 0 | D23: 11.98301 | E23: 1 | F23: 1 | G23: 0 | H23: 'NA | I23: 1 | J23: 1 | K23: 1 | L23: 1 | M23: 1 | N23: 1 | O23: 1 | P23: Secondary KC Alignment: The comparison is between decimals 13.5 and 12.8, not fractions, so fraction comparison skills are not needed. Synergy: Since fraction comparison is not required, the primary and secondary knowledge components do not work together as intended.
A24: TD | B24: Question 23 | C24: 0 | D24: 8.1547527 | E24: 1 | F24: 1 | G24: 1 | H24: 1 | I24: 1 | J24: 1 | K24: 1 | L24: 1 | M24: 1 | N24: 1 | O24: 1
A25: TD | B25: Question 24 | C25: 0 | D25: 10.094259 | E25: 1 | F25: 1 | G25: 1 | H25: 1 | I25: 1 | J25: 1 | K25: 1 | L25: 1 | M25: 1 | N25: 1 | O25: 1
A26: TD | B26: Question 25 | C26: 0 | D26: 9.6442754 | E26: 1 | F26: 1 | G26: 1 | H26: 1 | I26: 1 | J26: 1 | K26: 1 | L26: 1 | M26: 1 | N26: 1 | O26: 1
A27: TD | B27: Question 26 | C27: 0 | D27: 8.2266335 | E27: 1 | F27: 0 | G27: 1 | H27: 'NA | I27: 1 | J27: 'NA | K27: 1 | L27: 1 | M27: 1 | N27: 1 | O27: 1 | P27: Primary KC Alignment: The problem only requires adding fractions (7/4 + 5/3, 9/5 + 8/7, then summing results). No multiplication of improper fractions is needed despite this being the intended primary KC. Synergy: Since the primary KC (multiplying improper fractions) is not actually used in the solution, there is no synergy between primary and secondary KCs - only the secondary KC (adding fractions) is utilized.
A28: TD | B28: Question 27 | C28: 0 | D28: 11.883206 | E28: 1 | F28: 0 | G28: 1 | H28: 'NA | I28: 1 | J28: 'NA | K28: 1 | L28: 1 | M28: 1 | N28: 1 | O28: 1 | P28: Primary KC Alignment: The problem primarily requires division of fractions (23/12 divided by 2/3), not multiplication of two improper fractions as intended. Synergy: The intended primary KC (multiplying improper fractions) and secondary KC (subtracting fractions) are not used in tandem - division is the main operation needed, not multiplication.
A29: TD | B29: Question 28 | C29: 0 | D29: 10.120775 | E29: 1 | F29: 1 | G29: 1 | H29: 1 | I29: 1 | J29: 1 | K29: 1 | L29: 1 | M29: 1 | N29: 1 | O29: 1
A30: TD | B30: Question 29 | C30: 0 | D30: 4.7794852 | E30: 1 | F30: 1 | G30: 1 | H30: 1 | I30: 1 | J30: 1 | K30: 0 | L30: 1 | M30: 1 | N30: 1 | O30: 1 | P30: Real-world feasibility: Swimming 2 3/4 laps per minute (165 laps per hour) and 3 1/6 laps per minute (190 laps per hour) are unrealistically fast rates for human swimming training. Typical competitive swimmers complete 1-2 laps per minute at most.
A31: TD | B31: Question 30 | C31: 0 | D31: 10.879211 | E31: 1 | F31: 0 | G31: 0 | H31: 'NA | I31: 1 | J31: 'NA | K31: 1 | L31: 1 | M31: 1 | N31: 1 | O31: 1 | P31: Primary KC: Problem requires 0.875 x 300 but 300 is not a multiple of 10, 100, or 1000 as specified. Secondary KC: Problem requires converting decimal to mixed number, not expressing decimal as fraction.
A32: TD | B32: Question 31 | C32: 0 | D32: 10.549736 | E32: 1 | F32: 0 | G32: 1 | H32: 'NA | I32: 1 | J32: 'NA | K32: 1 | L32: 1 | M32: 1 | N32: 1 | O32: 1 | P32: Primary KC misalignment: Problem requires 0.125 * 400 which is general decimal multiplication, not specifically multiplication by 10, 100, 1000 or their multiples as intended.
A33: TD | B33: Question 32 | C33: 0 | D33: 11.158752 | E33: 1 | F33: 0 | G33: 1 | H33: 'NA | I33: 1 | J33: 'NA | K33: 1 | L33: 1 | M33: 1 | N33: 1 | O33: 1 | P33: Primary KC alignment fails because the problem requires dividing by 7, but the intended primary KC specifically targets dividing by 10, 100, 1000 and their multiples. 7 is not a multiple of 10, 100, or 1000.
A34: TD | B34: Question 33 | C34: 0 | D34: 7.7823808 | E34: 1 | F34: 1 | G34: 1 | H34: 1 | I34: 1 | J34: 1 | K34: 0 | L34: 1 | M34: 1 | N34: 1 | O34: 1 | P34: Real-world feasibility issue: Swimming 40000 meters in 4 laps means each lap is 10000 meters (10 km), which is unrealistic for typical swimming practice. Standard pool laps are 25m, 50m, or at most a few hundred meters.
A35: TD | B35: Question 34 | C35: 0 | D35: 10.239755 | E35: 1 | F35: 1 | G35: 1 | H35: 1 | I35: 1 | J35: 1 | K35: 1 | L35: 1 | M35: 1 | N35: 1 | O35: 1
A36: TD | B36: Question 35 | C36: 0 | D36: 8.17382 | E36: 1 | F36: 1 | G36: 1 | H36: 1 | I36: 1 | J36: 1 | K36: 0 | L36: 1 | M36: 1 | N36: 1 | O36: 1 | P36: Real-world feasibility: Basketball teams typically have 5 players on court with limited substitutes (usually 7-12 total players per team). Having 30 players per team and eliminating 15 players in one round does not reflect realistic basketball tournament structure.
A37: TD | B37: Question 36 | C37: 0 | D37: 11.613573 | E37: 1 | F37: 1 | G37: 1 | H37: 1 | I37: 1 | J37: 1 | K37: 0 | L37: 1 | M37: 1 | N37: 1 | O37: 1 | P37: Real-world feasibility: 1.25 km/h is unrealistically slow for marathon training - this is slower than normal walking speed of 4-5 km/h. Marathon runners typically train at speeds of 8-15 km/h.
A38: TD | B38: Question 37 | C38: 0 | D38: 11.331115 | E38: 1 | F38: 1 | G38: 1 | H38: 1 | I38: 1 | J38: 1 | K38: 1 | L38: 1 | M38: 1 | N38: 1 | O38: 1
A39: TD | B39: Question 38 | C39: 0 | D39: 3.0335958 | E39: 1 | F39: 1 | G39: 1 | H39: 1 | I39: 1 | J39: 1 | K39: 1 | L39: 1 | M39: 1 | N39: 1 | O39: 1
A40: TD | B40: Question 39 | C40: 0 | D40: 13.636707 | E40: 1 | F40: 1 | G40: 1 | H40: 1 | I40: 1 | J40: 1 | K40: 0 | L40: 1 | M40: 1 | N40: 1 | O40: 1 | P40: Real-world plausibility fails because 2/3 of a week equals 4 + 2/3 days, but practicing for 2/3 of a day is unrealistic in normal daily scheduling. The mathematical result of 3/4 hours per day does not align with how people would typically plan practice sessions.
A41: TD | B41: Question 40 | C41: 0 | D41: 10.003046 | E41: 0 | F41: 'NA | G41: 'NA | H41: 'NA | I41: 'NA | J41: 'NA | K41: 'NA | L41: 'NA | M41: 'NA | N41: 'NA | O41: 'NA | P41: Answerability: Missing critical information - total practice time not given, making problem unsolvable. Primary KC alignment: Cannot perform intended division operation due to missing information. Secondary KC alignment: Cannot convert result to decimal since no unique answer exists. Synergy: Primary and secondary components cannot work together due to missing information preventing solution.
A42: TD | B42: Question 41 | C42: 0 | D42: 9.9413979 | E42: 1 | F42: 1 | G42: 1 | H42: 1 | I42: 1 | J42: 1 | K42: 1 | L42: 1 | M42: 1 | N42: 1 | O42: 1
A43: TD | B43: Question 42 | C43: 0 | D43: 9.8289547 | E43: 1 | F43: 1 | G43: 1 | H43: 1 | I43: 1 | J43: 1 | K43: 1 | L43: 1 | M43: 1 | N43: 1 | O43: 1
A44: TD | B44: Question 43 | C44: 0 | D44: 10.738045 | E44: 1 | F44: 1 | G44: 0 | H44: 'NA | I44: 1 | J44: 1 | K44: 1 | L44: 1 | M44: 1 | N44: 1 | O44: 1 | P44: Secondary Knowledge Component Alignment: The problem does not require adding whole numbers. The three point values (45, 36, 54) are given directly and no addition operation is needed to solve for the ratio. Synergy: Since addition is not required in the solution, there is no synergy between finding ratios and adding whole numbers.
A45: TD | B45: Question 44 | C45: 0 | D45: 11.7954 | E45: 1 | F45: 1 | G45: 1 | H45: 1 | I45: 1 | J45: 0 | K45: 1 | L45: 1 | M45: 1 | N45: 1 | O45: 1 | P45: Grade alignment issue: This algebraic problem with variables is too advanced for Primary 6 students who typically work with concrete arithmetic problems. Algebraic thinking with variables is usually introduced in Primary 7/Secondary 1 in Singapore math curriculum.
A46: TD | B46: Question 45 | C46: 0 | D46: 9.3292933 | E46: 1 | F46: 1 | G46: 1 | H46: 1 | I46: 1 | J46: 1 | K46: 1 | L46: 1 | M46: 1 | N46: 1 | O46: 1
A47: TD | B47: Question 46 | C47: 0 | D47: 12.255929 | E47: 1 | F47: 1 | G47: 0 | H47: 'NA | I47: 1 | J47: 1 | K47: 1 | L47: 1 | M47: 1 | N47: 1 | O47: 1 | P47: Secondary KC alignment: The problem can be solved using reverse percentages (36 / 0.72 = 50) but does not explicitly require or emphasize converting percentage to decimal form. Synergy: Since the secondary knowledge component is not clearly integrated into the problem structure, there is no meaningful synergy between the primary and secondary knowledge components.
A48: TD | B48: Question 47 | C48: 0 | D48: 15.777393 | E48: 1 | F48: 1 | G48: 1 | H48: 1 | I48: 1 | J48: 0 | K48: 1 | L48: 1 | M48: 1 | N48: 1 | O48: 1 | P48: Grade Alignment: The problem involves basic ratio concepts (3:5 ratio, direct proportion) and simple whole number multiplication (x4) which are typically covered in Primary 5-6 or lower secondary levels. For Secondary O-level 2 students, this problem would be too elementary and does not match the expected mathematical sophistication and complexity required for that grade level.
A49: TD | B49: Question 48 | C49: 0 | D49: 12.882825 | E49: 1 | F49: 1 | G49: 1 | H49: 1 | I49: 1 | J49: 0 | K49: 0 | L49: 1 | M49: 1 | N49: 1 | O49: 1 | P49: Grade alignment: Matrix operations are too advanced for O-level Secondary 3/4 students. Real-world feasibility: The multiplication of team base scores by individual member multipliers creates illogical mixing of team-level and individual-level data that does not reflect realistic gaming score calculation.
A50: TD | B50: Question 49 | C50: 0 | D50: 5.1226912 | E50: 1 | F50: 1 | G50: 1 | H50: 1 | I50: 1 | J50: 0 | K50: 1 | L50: 1 | M50: 1 | N50: 1 | O50: 1 | P50: Grade Alignment: Standard deviation calculation is typically introduced at higher secondary levels (O-level 4/5 or A-levels) rather than Secondary O-level 3/4. At O-level 3/4, students typically work with simpler statistical measures like mean, median, mode, and range. Standard deviation requires understanding of variance, squared deviations, and square roots of statistical measures which are more advanced concepts.
A51: Minh | B51: Question 1 | C51: 0 | D51: 4.9543865 | E51: 1 | F51: 1 | G51: 1 | H51: 1 | I51: 1 | J51: 0 | K51: 1 | L51: 1 | M51: 1 | N51: 1 | O51: 1 | P51: Grade Alignment: 4-digit numbers and operations with 4-digit numbers are typically introduced in Primary 4, not Primary 3. Primary 3 students typically work with numbers up to 1000 or at most 3-digit numbers. The numbers 8524, 6789, and 7356 exceed the typical Primary 3 curriculum scope.
A52: Minh | B52: Question 2 | C52: 0 | D52: 11.03752 | E52: 1 | F52: 1 | G52: 0 | H52: 'NA | I52: 1 | J52: 1 | K52: 1 | L52: 1 | M52: 1 | N52: 1 | O52: 1 | P52: Secondary KC alignment: The third question asks for total students participating, which equals the original 847 students given, requiring no additional calculation beyond restating the given information. Synergy: The questions do not build upon each other - the third question does not use results from questions 1 and 2, instead it simply restates the original number 847.
A53: Minh | B53: Question 3 | C53: 0 | D53: 7.8989961 | E53: 1 | F53: 1 | G53: 1 | H53: 1 | I53: 1 | J53: 1 | K53: 1 | L53: 0 | M53: 1 | N53: 1 | O53: 1 | P53: Clarity: The problem contains 2 questions in the first sentence asking about paintbrushes per group and remainder, then 1 question in the second sentence about paper sheets. This creates ambiguity about whether there are 2 or 3 total questions to answer, making the problem structure unclear.
A54: Minh | B54: Question 4 | C54: 0 | D54: 2.905658 | E54: 1 | F54: 1 | G54: 1 | H54: 1 | I54: 1 | J54: 1 | K54: 1 | L54: 1 | M54: 1 | N54: 1 | O54: 1
A55: Minh | B55: Question 5 | C55: 0 | D55: 9.6623547 | E55: 1 | F55: 1 | G55: 1 | H55: 1 | I55: 1 | J55: 1 | K55: 1 | L55: 1 | M55: 1 | N55: 1 | O55: 1
A56: Minh | B56: Question 6 | C56: 0 | D56: 11.177444 | E56: 1 | F56: 1 | G56: 0 | H56: 'NA | I56: 1 | J56: 1 | K56: 1 | L56: 1 | M56: 1 | N56: 1 | O56: 1 | P56: Secondary KC Alignment: Problem does not require multiplication - both questions use division only (432/6=72, then 72/4=18). Synergy: No synergy between primary and secondary KC since multiplication is not used in the solution.
A57: Minh | B57: Question 7 | C57: 0 | D57: 2.8316157 | E57: 1 | F57: 1 | G57: 1 | H57: 1 | I57: 1 | J57: 1 | K57: 1 | L57: 1 | M57: 1 | N57: 1 | O57: 1
A58: Minh | B58: Question 8 | C58: 0 | D58: 12.123996 | E58: 1 | F58: 1 | G58: 1 | H58: 1 | I58: 1 | J58: 0 | K58: 1 | L58: 1 | M58: 1 | N58: 1 | O58: 1 | P58: Grade Alignment: The problem involves complex fractions (3/8, 5/12, 13/24) and requires finding LCM of 24, which exceeds typical Primary 3 curriculum that focuses on simpler unit fractions and basic denominators.
A59: Minh | B59: Question 9 | C59: 0 | D59: 11.329368 | E59: 1 | F59: 1 | G59: 1 | H59: 1 | I59: 1 | J59: 1 | K59: 1 | L59: 1 | M59: 1 | N59: 1 | O59: 1
A60: Minh | B60: Question 10 | C60: 0 | D60: 5.9065905 | E60: 0 | F60: 'NA | G60: 'NA | H60: 'NA | I60: 'NA | J60: 'NA | K60: 'NA | L60: 'NA | M60: 'NA | N60: 'NA | O60: 'NA | P60: Answerability: The division calculations contain errors - 2856/8=357, 1944/8=243, 3528/8=441, but these do not divide evenly as implied by the problem context of dividing students equally into groups. Real-world feasibility: The numbers of students attending a badminton tournament are unrealistic - 2856, 1944, and 3528 students per school for a single sporting event is implausibly large for primary schools.
A61: Minh | B61: Question 11 | C61: 0 | D61: 11.071687 | E61: 1 | F61: 1 | G61: 1 | H61: 1 | I61: 1 | J61: 1 | K61: 1 | L61: 1 | M61: 1 | N61: 1 | O61: 1
A62: Minh | B62: Question 12 | C62: 0 | D62: 2.974786 | E62: 1 | F62: 1 | G62: 1 | H62: 1 | I62: 1 | J62: 1 | K62: 1 | L62: 1 | M62: 1 | N62: 1 | O62: 1
A63: Minh | B63: Question 13 | C63: 0 | D63: 2.8389494 | E63: 1 | F63: 1 | G63: 1 | H63: 1 | I63: 1 | J63: 1 | K63: 1 | L63: 1 | M63: 1 | N63: 1 | O63: 1
A64: Minh | B64: Question 14 | C64: 0 | D64: 6.6982429 | E64: 1 | F64: 1 | G64: 0 | H64: 'NA | I64: 1 | J64: 1 | K64: 1 | L64: 1 | M64: 1 | N64: 1 | O64: 1 | P64: Secondary KC Alignment: The problem asks to express the answer as a mixed number, but the intended secondary KC is converting decimals to fractions, not mixed numbers. The calculation 2.75 + 1.8 + 3.25 = 7.8 results in 7.8, which when converted to a fraction becomes 7 4/5 (mixed number), but this requires fraction conversion knowledge beyond what is specified. Synergy: Since the secondary KC is not properly aligned, there is no effective synergy between primary and secondary knowledge components. The decimal addition (primary KC) can be completed independently without requiring decimal-to-fraction conversion as specified in the secondary KC.
A65: Minh | B65: Question 15 | C65: 0 | D65: 5.3200893 | E65: 1 | F65: 0 | G65: 1 | H65: 'NA | I65: 1 | J65: 'NA | K65: 1 | L65: 1 | M65: 1 | N65: 1 | O65: 1 | P65: Primary KC Alignment: The problem requires adding 3.126 km which has 3 decimal places, exceeding the intended primary KC of adding decimals up to 2 decimal places only. Grade Alignment: Adding decimals with 3 decimal places (3.126) is typically beyond Primary 4 level in Singapore math syllabus, which focuses on decimals up to 2 decimal places at this grade.
A66: Minh | B66: Question 16 | C66: 0 | D66: 9.0069945 | E66: 1 | F66: 1 | G66: 1 | H66: 1 | I66: 1 | J66: 1 | K66: 1 | L66: 1 | M66: 1 | N66: 1 | O66: 1
A67: Minh | B67: Question 17 | C67: 0 | D67: 9.7138567 | E67: 1 | F67: 1 | G67: 1 | H67: 1 | I67: 1 | J67: 1 | K67: 1 | L67: 1 | M67: 1 | N67: 1 | O67: 1
A68: Minh | B68: Question 18 | C68: 0 | D68: 12.053574 | E68: 1 | F68: 1 | G68: 0 | H68: 'NA | I68: 1 | J68: 1 | K68: 1 | L68: 1 | M68: 0 | N68: 1 | O68: 1 | P68: Secondary KC alignment fails because decimal subtraction is not required - the remaining amount 8.91 is directly given. Synergy fails because the two knowledge components do not work together since subtraction is not needed. Conciseness fails because the purchase amounts 12.48 and 2.76 are irrelevant information not needed for solving the problem.
A69: Minh | B69: Question 19 | C69: 0 | D69: 10.400389 | E69: 1 | F69: 1 | G69: 1 | H69: 1 | I69: 1 | J69: 1 | K69: 1 | L69: 1 | M69: 1 | N69: 1 | O69: 1
A70: Minh | B70: Question 20 | C70: 0 | D70: 9.085089 | E70: 1 | F70: 1 | G70: 1 | H70: 1 | I70: 1 | J70: 1 | K70: 1 | L70: 1 | M70: 1 | N70: 1 | O70: 1
A71: Minh | B71: Question 21 | C71: 0 | D71: 10.556652 | E71: 1 | F71: 1 | G71: 1 | H71: 1 | I71: 1 | J71: 1 | K71: 1 | L71: 1 | M71: 1 | N71: 1 | O71: 1
A72: Minh | B72: Question 22 | C72: 0 | D72: 10.701731 | E72: 1 | F72: 1 | G72: 1 | H72: 1 | I72: 1 | J72: 1 | K72: 1 | L72: 1 | M72: 1 | N72: 1 | O72: 1
A73: Minh | B73: Question 23 | C73: 0 | D73: 10.953443 | E73: 1 | F73: 1 | G73: 1 | H73: 1 | I73: 1 | J73: 1 | K73: 1 | L73: 1 | M73: 1 | N73: 1 | O73: 1
A74: Minh | B74: Question 24 | C74: 0 | D74: 2.8537571 | E74: 1 | F74: 1 | G74: 1 | H74: 1 | I74: 1 | J74: 1 | K74: 1 | L74: 1 | M74: 1 | N74: 1 | O74: 1
A75: Minh | B75: Question 25 | C75: 0 | D75: 11.971837 | E75: 1 | F75: 1 | G75: 0 | H75: 'NA | I75: 1 | J75: 1 | K75: 1 | L75: 1 | M75: 1 | N75: 1 | O75: 1 | P75: Secondary KC Alignment: The answer 2 1/4 * 6 = 13 1/2 is already in simplest form, so no fraction simplification is actually required. Synergy: Since no real simplification work is needed, the primary and secondary knowledge components do not work together meaningfully to solve the problem.
A76: Minh | B76: Question 26 | C76: 0 | D76: 10.335236 | E76: 1 | F76: 1 | G76: 1 | H76: 1 | I76: 1 | J76: 1 | K76: 1 | L76: 1 | M76: 1 | N76: 1 | O76: 1
A77: Minh | B77: Question 27 | C77: 0 | D77: 4.7701924 | E77: 1 | F77: 0 | G77: 1 | H77: 'NA | I77: 1 | J77: 'NA | K77: 1 | L77: 1 | M77: 1 | N77: 1 | O77: 1 | P77: Primary KC alignment fails because the problem requires multiplying 23.456 x 30, which is multiplying a decimal by a non-multiple of 10/100/1000. The intended primary KC is specifically about multiplying decimals by 10, 100, 1000 and their multiples, but 30 is not a multiple of these numbers.
A78: Minh | B78: Question 28 | C78: 0 | D78: 4.3326931 | E78: 1 | F78: 0 | G78: 1 | H78: 'NA | I78: 1 | J78: 'NA | K78: 1 | L78: 1 | M78: 1 | N78: 1 | O78: 1 | P78: Primary KC alignment fails because the problem requires dividing 142.8 by 60, but the intended Primary KC is about dividing decimals by 10, 100, 1000 and their multiples. 60 is not a multiple of 10, 100, or 1000.
A79: Minh | B79: Question 29 | C79: 0 | D79: 9.8836656 | E79: 1 | F79: 1 | G79: 1 | H79: 1 | I79: 1 | J79: 1 | K79: 1 | L79: 1 | M79: 1 | N79: 1 | O79: 1
A80: Minh | B80: Question 30 | C80: 0 | D80: 10.330837 | E80: 1 | F80: 1 | G80: 1 | H80: 1 | I80: 1 | J80: 1 | K80: 1 | L80: 1 | M80: 1 | N80: 1 | O80: 1
A81: Minh | B81: Question 31 | C81: 0 | D81: 12.004747 | E81: 1 | F81: 1 | G81: 0 | H81: 'NA | I81: 1 | J81: 1 | K81: 0 | L81: 1 | M81: 1 | N81: 1 | O81: 1 | P81: Secondary KC requires conversion from smaller to larger units but problem converts km to m (larger to smaller). Synergy fails due to secondary KC misalignment. Running pace of 1.25 km/min = 75 km/h is unrealistic for humans.
A82: Minh | B82: Question 32 | C82: 0 | D82: 11.355969 | E82: 1 | F82: 1 | G82: 0 | H82: 'NA | I82: 1 | J82: 1 | K82: 1 | L82: 1 | M82: 1 | N82: 1 | O82: 1 | P82: Secondary KC Alignment: Problem involves decimal multiplication 0.8 * 21.6 but does not involve converting measurements from larger units to smaller units. No unit conversion occurs. Synergy: Since secondary KC is not present, primary and secondary KCs cannot work in tandem.
A83: Minh | B83: Question 33 | C83: 0 | D83: 8.9900048 | E83: 1 | F83: 1 | G83: 1 | H83: 1 | I83: 1 | J83: 1 | K83: 1 | L83: 1 | M83: 1 | N83: 1 | O83: 1
A84: Minh | B84: Question 34 | C84: 0 | D84: 7.5514057 | E84: 0 | F84: 'NA | G84: 'NA | H84: 'NA | I84: 'NA | J84: 'NA | K84: 'NA | L84: 'NA | M84: 'NA | N84: 'NA | O84: 'NA | P84: Answerability: Tuesday calculation gives 11/6 ÷ 2/9 = 33/4 = 8.25 sessions. Cannot have 8.25 practice sessions in reality - sessions must be whole numbers. Real-world feasibility: Same issue - the mathematical result of 8.25 sessions is not realistic as you cannot have a fraction of a practice session.
A85: Minh | B85: Question 35 | C85: 0 | D85: 11.763001 | E85: 1 | F85: 1 | G85: 0 | H85: 'NA | I85: 1 | J85: 1 | K85: 1 | L85: 1 | M85: 1 | N85: 1 | O85: 1 | P85: Secondary KC alignment: The answer (3/4) / (1/8) = 6 is a whole number, so fraction simplification is not needed despite the instruction asking for simplest form. Synergy: Since secondary KC is not actually required, there is no meaningful connection between primary and secondary knowledge components.
A86: Minh | B86: Question 36 | C86: 0 | D86: 10.468932 | E86: 1 | F86: 1 | G86: 1 | H86: 1 | I86: 1 | J86: 1 | K86: 1 | L86: 1 | M86: 1 | N86: 1 | O86: 1
A87: Minh | B87: Question 37 | C87: 0 | D87: 7.7699115 | E87: 0 | F87: 'NA | G87: 'NA | H87: 'NA | I87: 'NA | J87: 'NA | K87: 'NA | L87: 'NA | M87: 'NA | N87: 'NA | O87: 'NA | P87: ANSWERABILITY: The problem asks for percentage decrease but accuracy remained constant at 70% both months (84/120 = 105/150 = 0.7). There is no decrease to calculate, making the question fundamentally flawed. PRIMARY_KC_ALIGNMENT: Since both months have identical 70% accuracy, there is no percentage increase or decrease occurring. The primary knowledge component cannot be meaningfully applied. SYNERGY: With no actual percentage change to calculate, the primary and secondary knowledge components cannot work together as intended - whole number subtraction becomes irrelevant when the final result is 0% change.
A88: Minh | B88: Question 38 | C88: 0 | D88: 11.253231 | E88: 1 | F88: 1 | G88: 1 | H88: 0 | I88: 1 | J88: 1 | K88: 1 | L88: 1 | M88: 1 | N88: 1 | O88: 1 | P88: The two questions are somewhat independent - the percentage increase question uses the original throw counts (45 and 63) while the points question uses multiplication. The questions do not build upon each other where one result feeds into the next calculation.
A89: Minh | B89: Question 39 | C89: 0 | D89: 10.240556 | E89: 1 | F89: 1 | G89: 1 | H89: 1 | I89: 1 | J89: 1 | K89: 1 | L89: 1 | M89: 1 | N89: 1 | O89: 1
A90: Minh | B90: Question 40 | C90: 0 | D90: 3.0367889 | E90: 1 | F90: 1 | G90: 1 | H90: 1 | I90: 1 | J90: 1 | K90: 1 | L90: 1 | M90: 1 | N90: 1 | O90: 1
A91: Minh | B91: Question 41 | C91: 0 | D91: 10.820862 | E91: 1 | F91: 1 | G91: 1 | H91: 1 | I91: 1 | J91: 1 | K91: 1 | L91: 1 | M91: 1 | N91: 1 | O91: 1
A92: Minh | B92: Question 42 | C92: 0 | D92: 2.9577286 | E92: 1 | F92: 1 | G92: 1 | H92: 1 | I92: 1 | J92: 1 | K92: 1 | L92: 1 | M92: 1 | N92: 1 | O92: 1
A93: Minh | B93: Question 43 | C93: 0 | D93: 4.8294637 | E93: 1 | F93: 1 | G93: 1 | H93: 1 | I93: 1 | J93: 0 | K93: 1 | L93: 1 | M93: 1 | N93: 1 | O93: 1 | P93: Grade Alignment: The problem requires understanding of algebraic variables (a, b), creating complex algebraic expressions with multiple variables, and substitution methods. These concepts are typically introduced in Secondary 1-2 mathematics curriculum, not Primary 6. Primary 6 students typically work with simple algebraic expressions with one variable and basic substitution only.
A94: Minh | B94: Question 44 | C94: 0 | D94: 10.895059 | E94: 1 | F94: 1 | G94: 1 | H94: 1 | I94: 1 | J94: 1 | K94: 1 | L94: 1 | M94: 1 | N94: 1 | O94: 1
A95: Minh | B95: Question 45 | C95: 0 | D95: 13.457232 | E95: 1 | F95: 1 | G95: 1 | H95: 1 | I95: 1 | J95: 0 | K95: 1 | L95: 1 | M95: 1 | N95: 1 | O95: 1 | P95: Grade alignment: The problem involves fraction subtraction and ratios with fractions which are typically taught at Primary 5-6 level, making it too simple for Secondary O-level 1 students who should be working with more advanced mathematical concepts.
A96: Minh | B96: Question 46 | C96: 0 | D96: 5.3853102 | E96: 1 | F96: 1 | G96: 1 | H96: 1 | I96: 1 | J96: 0 | K96: 1 | L96: 1 | M96: 1 | N96: 1 | O96: 1 | P96: Grade alignment: This problem involves basic fraction operations (multiplication by 7, finding ratios with simple fractions like 3/4 and 1/2, and dividing fractions by whole numbers) which are typically covered in Primary 5-6 levels, not Secondary O-level 1. Secondary O-level 1 students would be expected to handle more complex fraction operations and algebraic concepts.
A97: Minh | B97: Question 47 | C97: 0 | D97: 12.318403 | E97: 1 | F97: 1 | G97: 1 | H97: 1 | I97: 1 | J97: 0 | K97: 1 | L97: 1 | M97: 1 | N97: 1 | O97: 1 | P97: Grade Alignment: The problem is too simple for Secondary O-level 1 students. It only requires basic decimal subtraction (24.8 - 5.4) and simple ratio concepts typically taught in elementary/middle school grades, not advanced secondary level mathematics.
A98: Minh | B98: Question 48 | C98: 0 | D98: 12.474492 | E98: 1 | F98: 1 | G98: 1 | H98: 1 | I98: 1 | J98: 0 | K98: 1 | L98: 1 | M98: 1 | N98: 1 | O98: 1 | P98: Grade Alignment: The problem involves basic percentage calculations (24/40 = 60%, 18/30 = 60%) and simple decimal conversions (60% = 0.6) which are typically taught at Primary 5-6 level in Singapore curriculum. This is significantly below the expected complexity and knowledge components for Secondary O-level 1 students.
A99: Minh | B99: Question 49 | C99: 0 | D99: 5.3146496 | E99: 1 | F99: 1 | G99: 1 | H99: 1 | I99: 1 | J99: 0 | K99: 1 | L99: 1 | M99: 1 | N99: 1 | O99: 1 | P99: Grade alignment: This problem is too simple for Secondary O-level 1 students. It only requires basic division (480/12=40) and percentage calculation (40*1.25=50, then 50*8=400), which are concepts typically mastered in primary school. Secondary O-level 1 students would be expected to handle more complex mathematical concepts and multi-step problems with higher cognitive demands.
A100: Minh | B100: Question 50 | C100: 0 | D100: 12.989003 | E100: 1 | F100: 0 | G100: 0 | H100: 'NA | I100: 1 | J100: 'NA | K100: 1 | L100: 1 | M100: 1 | N100: 1 | O100: 1 | P100: Primary KC: Problem solves using rates and proportions, not fractional equations. Secondary KC: Solution uses direct calculation, no algebraic equation translation needed. Synergy: Neither intended KC required so cannot work together. Grade: Problem difficulty suits lower secondary level, not O-level 1 algebraic complexity.
...

Sheet recreation_claude_v2_4
A1: Evaluator | B1: Question | C1: status | D1: response_time | E1: answerability | F1: primary_kc_alignment | G1: secondary_kc_alignment | H1: synergy | I1: topic_alignment | J1: grade_alignment | K1: real_world_feasibility | L1: clarity | M1: conciseness_and_relevance | N1: language_quality | O1: content_appropriateness | P1: explanation
A2: TD | B2: Question 1 | C2: 0 | D2: 9.1908042 | E2: 1 | F2: 1 | G2: 1 | H2: 1 | I2: 1 | J2: 1 | K2: 1 | L2: 1 | M2: 1 | N2: 1 | O2: 1
A3: TD | B3: Question 2 | C3: 0 | D3: 9.6037319 | E3: 1 | F3: 1 | G3: 1 | H3: 1 | I3: 1 | J3: 1 | K3: 1 | L3: 1 | M3: 1 | N3: 1 | O3: 1
A4: TD | B4: Question 3 | C4: 0 | D4: 11.292465 | E4: 1 | F4: 1 | G4: 1 | H4: 1 | I4: 1 | J4: 1 | K4: 1 | L4: 1 | M4: 1 | N4: 1 | O4: 1
A5: TD | B5: Question 4 | C5: 0 | D5: 6.7262769 | E5: 1 | F5: 0 | G5: 1 | H5: 'NA | I5: 1 | J5: 'NA | K5: 1 | L5: 1 | M5: 1 | N5: 1 | O5: 1 | P5: Primary KC Alignment: The problem requires multiplying 3-digit numbers (126, 148, 235) by 1-digit numbers (4, 3, 2), but the intended primary KC is multiplying whole numbers UP TO 3 digits by 1 digit, which typically means the multiplicand should be at most 99 for Primary 3 level. The numbers 126, 148, and 235 exceed this expectation. Grade Alignment: The calculations required (4x126=504, 3x148=444, 2x235=470) involve 3-digit by 1-digit multiplication that produces results in the hundreds, which may be too advanced for Primary 3 students who typically work with smaller numbers in multiplication.
A6: TD | B6: Question 5 | C6: 0 | D6: 3.033381 | E6: 1 | F6: 1 | G6: 1 | H6: 1 | I6: 1 | J6: 1 | K6: 1 | L6: 1 | M6: 1 | N6: 1 | O6: 1
A7: TD | B7: Question 6 | C7: 0 | D7: 2.8941858 | E7: 1 | F7: 1 | G7: 1 | H7: 1 | I7: 1 | J7: 1 | K7: 1 | L7: 1 | M7: 1 | N7: 1 | O7: 1
A8: TD | B8: Question 7 | C8: 0 | D8: 9.8123996 | E8: 1 | F8: 1 | G8: 1 | H8: 1 | I8: 1 | J8: 1 | K8: 1 | L8: 1 | M8: 1 | N8: 1 | O8: 1
A9: TD | B9: Question 8 | C9: 0 | D9: 9.6471558 | E9: 1 | F9: 1 | G9: 1 | H9: 1 | I9: 1 | J9: 1 | K9: 1 | L9: 1 | M9: 1 | N9: 1 | O9: 1
A10: TD | B10: Question 9 | C10: 0 | D10: 2.9008126 | E10: 1 | F10: 1 | G10: 1 | H10: 1 | I10: 1 | J10: 1 | K10: 1 | L10: 1 | M10: 1 | N10: 1 | O10: 1
A11: TD | B11: Question 10 | C11: 0 | D11: 10.316988 | E11: 1 | F11: 1 | G11: 1 | H11: 1 | I11: 1 | J11: 1 | K11: 1 | L11: 1 | M11: 1 | N11: 1 | O11: 1
A12: TD | B12: Question 11 | C12: 0 | D12: 12.80777 | E12: 0 | F12: 'NA | G12: 'NA | H12: 'NA | I12: 'NA | J12: 'NA | K12: 'NA | L12: 'NA | M12: 'NA | N12: 'NA | O12: 'NA | P12: Answerability: Questions (a) and (b) ask for totals when only single values are given per person - Sarah completed 2/3 painting and 1/4 music, so asking for her total in each category is unclear. Primary KC Alignment: Questions (a) and (b) do not require adding unlike fractions since only one fraction per person per challenge is provided - no addition needed. Synergy: Questions (a) and (b) results are not needed to solve question (c) which requires independent fraction addition and comparison. Clarity: Questions (a) and (b) are ambiguous about what total means when only single fractions are provided for each person per challenge.
A13: TD | B13: Question 12 | C13: 0 | D13: 11.209576 | E13: 1 | F13: 1 | G13: 1 | H13: 1 | I13: 1 | J13: 1 | K13: 1 | L13: 1 | M13: 1 | N13: 1 | O13: 1
A14: TD | B14: Question 13 | C14: 0 | D14: 13.171897 | E14: 1 | F14: 0 | G14: 1 | H14: 'NA | I14: 1 | J14: 'NA | K14: 1 | L14: 1 | M14: 1 | N14: 1 | O14: 1 | P14: Primary KC alignment: Problem requires adding decimals up to 3 decimal places (1.142) but intended KC specifies up to 2 decimal places only. Synergy: The two knowledge components work independently rather than in tandem - addition and comparison are separate tasks not building on each other. Grade alignment: Primary 4 students typically work with decimals up to 2 decimal places but this problem includes 3 decimal places which may be too advanced.
A15: TD | B15: Question 14 | C15: 0 | D15: 8.6759117 | E15: 1 | F15: 1 | G15: 1 | H15: 1 | I15: 1 | J15: 1 | K15: 1 | L15: 1 | M15: 1 | N15: 1 | O15: 1
A16: TD | B16: Question 15 | C16: 0 | D16: 2.8752611 | E16: 1 | F16: 1 | G16: 1 | H16: 1 | I16: 1 | J16: 1 | K16: 1 | L16: 1 | M16: 1 | N16: 1 | O16: 1
A17: TD | B17: Question 16 | C17: 0 | D17: 10.242868 | E17: 1 | F17: 1 | G17: 1 | H17: 1 | I17: 1 | J17: 1 | K17: 1 | L17: 1 | M17: 1 | N17: 1 | O17: 1
A18: TD | B18: Question 17 | C18: 0 | D18: 2.9498243 | E18: 1 | F18: 1 | G18: 1 | H18: 1 | I18: 1 | J18: 1 | K18: 1 | L18: 1 | M18: 1 | N18: 1 | O18: 1
A19: TD | B19: Question 18 | C19: 0 | D19: 2.9697349 | E19: 1 | F19: 1 | G19: 1 | H19: 1 | I19: 1 | J19: 1 | K19: 1 | L19: 1 | M19: 1 | N19: 1 | O19: 1
A20: TD | B20: Question 19 | C20: 0 | D20: 9.019249 | E20: 0 | F20: 'NA | G20: 'NA | H20: 'NA | I20: 'NA | J20: 'NA | K20: 'NA | L20: 'NA | M20: 'NA | N20: 'NA | O20: 'NA | P20: Answerability: The question 'What is the total distance Sarah swam per lap over the two days?' is ambiguous - unclear if asking for sum of distances per lap or separate calculations. Grade_alignment: Tuesday calculation 5.24 / 3 = 1.748 km results in 3 decimal places, exceeding Primary 4 expectation of 2 decimal places. Real_world_feasibility: Pool laps of different lengths (1.56 km vs 1.748 km) on consecutive days is unrealistic - pools have fixed perimeters. Clarity: Ambiguous phrasing makes the intended calculation unclear.
A21: TD | B21: Question 20 | C21: 0 | D21: 9.5956309 | E21: 1 | F21: 1 | G21: 1 | H21: 1 | I21: 1 | J21: 1 | K21: 1 | L21: 1 | M21: 1 | N21: 1 | O21: 1
A22: TD | B22: Question 21 | C22: 0 | D22: 8.8142426 | E22: 1 | F22: 1 | G22: 1 | H22: 1 | I22: 1 | J22: 1 | K22: 1 | L22: 1 | M22: 1 | N22: 1 | O22: 1
A23: TD | B23: Question 22 | C23: 0 | D23: 10.144593 | E23: 1 | F23: 1 | G23: 1 | H23: 1 | I23: 1 | J23: 1 | K23: 1 | L23: 1 | M23: 1 | N23: 1 | O23: 1
A24: TD | B24: Question 23 | C24: 0 | D24: 9.1206853 | E24: 1 | F24: 1 | G24: 1 | H24: 1 | I24: 1 | J24: 1 | K24: 1 | L24: 1 | M24: 1 | N24: 1 | O24: 1
A25: TD | B25: Question 24 | C25: 0 | D25: 10.171844 | E25: 1 | F25: 1 | G25: 1 | H25: 1 | I25: 1 | J25: 1 | K25: 1 | L25: 1 | M25: 1 | N25: 1 | O25: 1
A26: TD | B26: Question 25 | C26: 0 | D26: 10.005701 | E26: 1 | F26: 1 | G26: 1 | H26: 1 | I26: 1 | J26: 1 | K26: 1 | L26: 1 | M26: 1 | N26: 1 | O26: 1
A27: TD | B27: Question 26 | C27: 0 | D27: 7.9541109 | E27: 1 | F27: 0 | G27: 1 | H27: 'NA | I27: 1 | J27: 'NA | K27: 1 | L27: 1 | M27: 1 | N27: 1 | O27: 1 | P27: Primary KC Alignment: The problem requires only fraction addition, not multiplication of improper fractions as intended. No multiplication operations are needed to solve any part. Synergy: Since the primary KC (fraction multiplication) is not actually required, there is no synergy between the intended primary and secondary knowledge components. The problem only uses fraction addition throughout.
A28: TD | B28: Question 27 | C28: 0 | D28: 10.737911 | E28: 1 | F28: 1 | G28: 1 | H28: 1 | I28: 1 | J28: 1 | K28: 1 | L28: 1 | M28: 1 | N28: 1 | O28: 1
A29: TD | B29: Question 28 | C29: 0 | D29: 9.4137452 | E29: 1 | F29: 1 | G29: 1 | H29: 1 | I29: 1 | J29: 1 | K29: 1 | L29: 1 | M29: 1 | N29: 1 | O29: 1
A30: TD | B30: Question 29 | C30: 0 | D30: 9.1940057 | E30: 1 | F30: 1 | G30: 1 | H30: 1 | I30: 1 | J30: 1 | K30: 1 | L30: 1 | M30: 1 | N30: 1 | O30: 1
A31: TD | B31: Question 30 | C31: 0 | D31: 12.147567 | E31: 1 | F31: 0 | G31: 1 | H31: 'NA | I31: 1 | J31: 'NA | K31: 1 | L31: 1 | M31: 1 | N31: 1 | O31: 1 | P31: Primary KC alignment: Problem requires general decimal multiplication (0.875 * 300), not specifically multiplying decimals by 10, 100, 1000 or their multiples. Synergy: Since primary KC is not actually used, there is no synergy between intended primary and secondary knowledge components.
A32: TD | B32: Question 31 | C32: 0 | D32: 6.0864937 | E32: 1 | F32: 0 | G32: 1 | H32: 'NA | I32: 1 | J32: 'NA | K32: 1 | L32: 1 | M32: 1 | N32: 1 | O32: 1 | P32: Primary KC alignment: The problem requires 0.125 * 400 which is standard decimal multiplication, not specifically multiplying by 10, 100, 1000 or their multiples as intended. Synergy: The two parts can be solved independently - the second question uses 65.8 and 50 (result from first part) but does not require the primary KC of multiplying by multiples of 10/100/1000, only basic decimal subtraction.
A33: TD | B33: Question 32 | C33: 0 | D33: 8.9372134 | E33: 1 | F33: 0 | G33: 1 | H33: 'NA | I33: 1 | J33: 'NA | K33: 1 | L33: 1 | M33: 1 | N33: 1 | O33: 1 | P33: Primary KC alignment: The problem requires dividing 127.850 by 7, but the intended primary KC is dividing by 10, 100, 1000 and their multiples. 7 is not a multiple of these numbers. Synergy: Since the primary KC does not align with the actual division needed (127.850 / 7), the primary and secondary KCs cannot work together as intended in this problem.
A34: TD | B34: Question 33 | C34: 0 | D34: 14.500815 | E34: 0 | F34: 'NA | G34: 'NA | H34: 'NA | I34: 'NA | J34: 'NA | K34: 'NA | L34: 'NA | M34: 'NA | N34: 'NA | O34: 'NA | P34: Answerability: The mathematical relationship between dividing total time by 400 to get average time per 100m is logically flawed. Real-world feasibility: The calculation method described does not produce a meaningful real-world result. Clarity: The explanation of why dividing by 400 gives time per 100m is mathematically incorrect and confusing. Conciseness: The 40000 meters information is irrelevant to solving the problem and creates unnecessary confusion.
A35: TD | B35: Question 34 | C35: 0 | D35: 10.549078 | E35: 1 | F35: 1 | G35: 1 | H35: 1 | I35: 1 | J35: 1 | K35: 1 | L35: 1 | M35: 1 | N35: 1 | O35: 1
A36: TD | B36: Question 35 | C36: 0 | D36: 6.339045 | E36: 1 | F36: 1 | G36: 1 | H36: 1 | I36: 1 | J36: 1 | K36: 0 | L36: 1 | M36: 1 | N36: 1 | O36: 1 | P36: Real-world feasibility: In basketball tournaments, players are typically not eliminated from teams during matches - teams as units advance or are eliminated. Individual players being removed from multiple teams simultaneously (15 from each of 8 teams) does not reflect realistic basketball tournament operations.
A37: TD | B37: Question 36 | C37: 0 | D37: 11.857007 | E37: 1 | F37: 1 | G37: 1 | H37: 1 | I37: 1 | J37: 1 | K37: 0 | L37: 1 | M37: 1 | N37: 1 | O37: 1 | P37: Real-world feasibility: 1.25 km/hour is unrealistically slow for marathon training - this is walking speed not running speed. Marathon runners typically train at 8-15 km/hour.
A38: TD | B38: Question 37 | C38: 0 | D38: 12.424082 | E38: 1 | F38: 1 | G38: 1 | H38: 1 | I38: 1 | J38: 1 | K38: 1 | L38: 1 | M38: 1 | N38: 1 | O38: 1
A39: TD | B39: Question 38 | C39: 0 | D39: 7.8060708 | E39: 1 | F39: 1 | G39: 1 | H39: 1 | I39: 1 | J39: 1 | K39: 1 | L39: 1 | M39: 1 | N39: 1 | O39: 1
A40: TD | B40: Question 39 | C40: 0 | D40: 12.143643 | E40: 1 | F40: 1 | G40: 1 | H40: 1 | I40: 1 | J40: 1 | K40: 0 | L40: 1 | M40: 1 | N40: 1 | O40: 1 | P40: Real-world feasibility: The phrase 2/3 of the week is unrealistic. People do not typically plan activities using fractional portions of weeks. A more realistic scenario would specify a concrete number of days like the next 3 days or next 5 days.
A41: TD | B41: Question 40 | C41: 0 | D41: 9.2926035 | E41: 0 | F41: 'NA | G41: 'NA | H41: 'NA | I41: 'NA | J41: 'NA | K41: 'NA | L41: 'NA | M41: 'NA | N41: 'NA | O41: 'NA | P41: ANSWERABILITY: The problem has missing critical information - Sarah's total practice time is not given, making it impossible to determine actual session count. REAL_WORLD_FEASIBILITY: The scenario is unrealistic because practice sessions have fixed durations but the problem treats them as variable fractions of total time, which contradicts how piano practice actually works. CLARITY: The problem is ambiguous about whether 3/4 refers to total planned time or actual time practiced, and the relationship between session length and total time is unclear. CONCISENESS_AND_RELEVANCE: The fraction 3/4 appears irrelevant to the solution since without knowing total practice time, this information cannot be meaningfully used to find number of sessions.
A42: TD | B42: Question 41 | C42: 0 | D42: 11.062967 | E42: 1 | F42: 1 | G42: 1 | H42: 1 | I42: 1 | J42: 1 | K42: 1 | L42: 1 | M42: 1 | N42: 1 | O42: 1
A43: TD | B43: Question 42 | C43: 0 | D43: 6.6338072 | E43: 1 | F43: 1 | G43: 0 | H43: 'NA | I43: 1 | J43: 1 | K43: 1 | L43: 1 | M43: 0 | N43: 1 | O43: 1 | P43: Secondary Knowledge Component (whole number division) is not required - the calculation 36/180 involves dividing by 180 which yields 0.2, not whole number division. Synergy fails because the secondary KC is not needed. Conciseness fails because the denominators 300 and 360 are provided but not needed for solving the problem - only the numerators 180 and 216 are required.
A44: TD | B44: Question 43 | C44: 0 | D44: 7.2194262 | E44: 1 | F44: 1 | G44: 0 | H44: 'NA | I44: 1 | J44: 1 | K44: 1 | L44: 1 | M44: 1 | N44: 1 | O44: 1 | P44: Secondary KC alignment fails because the problem does not require adding whole numbers - the three point values are given directly and students only need to find their ratio in simplest form. The solution process involves ratio formation and simplification using GCD, not addition. Synergy fails because since addition is not needed, the primary and secondary knowledge components are not used together to solve the problem.
A45: TD | B45: Question 44 | C45: 0 | D45: 13.152567 | E45: 1 | F45: 1 | G45: 1 | H45: 1 | I45: 1 | J45: 0 | K45: 1 | L45: 1 | M45: 1 | N45: 1 | O45: 1 | P45: Grade Alignment: The problem requires solving linear equations with algebraic variables (x), which is typically introduced in Secondary 1, not Primary 6. Primary 6 students have not yet learned to work with algebraic unknowns in equations.
A46: TD | B46: Question 45 | C46: 0 | D46: 6.7058651 | E46: 1 | F46: 1 | G46: 1 | H46: 1 | I46: 1 | J46: 0 | K46: 1 | L46: 1 | M46: 1 | N46: 1 | O46: 1 | P46: Grade alignment fails because Secondary O-level 1 students should be working with more advanced mathematical concepts like algebra, quadratic equations, or advanced geometry. This problem only requires basic percentage calculations and subtraction that are typically mastered in primary school (grades 5-6). The mathematical complexity is below the expected level for Secondary O-level 1.
A47: TD | B47: Question 46 | C47: 0 | D47: 9.0618212 | E47: 1 | F47: 1 | G47: 1 | H47: 1 | I47: 1 | J47: 1 | K47: 1 | L47: 1 | M47: 1 | N47: 1 | O47: 1
A48: TD | B48: Question 47 | C48: 0 | D48: 8.894474 | E48: 1 | F48: 1 | G48: 1 | H48: 1 | I48: 1 | J48: 0 | K48: 1 | L48: 1 | M48: 1 | N48: 1 | O48: 1 | P48: Grade Alignment: This problem requires setting up algebraic equations with variables (3x + 5x = 8x, then 4 * 8x = 192) and solving linear equations systematically. These algebraic manipulation skills and formal variable-based problem solving approaches are typically taught at Secondary 3-4 level, not Secondary 2 (O-level 2). Secondary 2 students would typically handle simpler ratio problems with direct arithmetic methods rather than algebraic equation solving.
A49: TD | B49: Question 48 | C49: 0 | D49: 15.057038 | E49: 0 | F49: 'NA | G49: 'NA | H49: 'NA | I49: 'NA | J49: 'NA | K49: 'NA | L49: 'NA | M49: 'NA | N49: 'NA | O49: 'NA | P49: Matrix B is described as multiplier bonuses per team member but the mathematical operation AB multiplies team base scores by these individual bonuses which creates an illogical relationship. The narrative suggests B should represent team-level multipliers not individual member bonuses to make the multiplication meaningful.
A50: TD | B50: Question 49 | C50: 0 | D50: 5.0395968 | E50: 1 | F50: 1 | G50: 1 | H50: 1 | I50: 1 | J50: 0 | K50: 1 | L50: 1 | M50: 1 | N50: 1 | O50: 1 | P50: Grade Alignment: The problem requires calculation of standard deviation which is typically taught at Secondary 4/5 or higher levels, not Secondary 3. Standard deviation involves complex mathematical concepts including square roots of variance calculations that exceed the typical Secondary O-level 3 curriculum which usually covers basic statistics like mean, median, mode but not standard deviation.
A51: Minh | B51: Question 1 | C51: 0 | D51: 10.403069 | E51: 1 | F51: 1 | G51: 1 | H51: 1 | I51: 1 | J51: 1 | K51: 1 | L51: 1 | M51: 1 | N51: 1 | O51: 1
A52: Minh | B52: Question 2 | C52: 0 | D52: 10.599266 | E52: 1 | F52: 1 | G52: 0 | H52: 'NA | I52: 1 | J52: 1 | K52: 1 | L52: 1 | M52: 1 | N52: 1 | O52: 1 | P52: Secondary KC alignment: The third question asks for total students participating, which is 847 (given number), requiring no addition calculation. Synergy: The division results (141 groups, 1 remaining) are not used in the addition question, and the addition question does not add meaningful complexity as it simply restates given information.
A53: Minh | B53: Question 3 | C53: 0 | D53: 3.0027425 | E53: 1 | F53: 1 | G53: 1 | H53: 1 | I53: 1 | J53: 1 | K53: 1 | L53: 1 | M53: 1 | N53: 1 | O53: 1
A54: Minh | B54: Question 4 | C54: 0 | D54: 2.969362 | E54: 1 | F54: 1 | G54: 1 | H54: 1 | I54: 1 | J54: 1 | K54: 1 | L54: 1 | M54: 1 | N54: 1 | O54: 1
A55: Minh | B55: Question 5 | C55: 0 | D55: 9.7634461 | E55: 1 | F55: 1 | G55: 1 | H55: 1 | I55: 1 | J55: 1 | K55: 1 | L55: 1 | M55: 1 | N55: 1 | O55: 1
A56: Minh | B56: Question 6 | C56: 0 | D56: 7.2171612 | E56: 1 | F56: 1 | G56: 0 | H56: 'NA | I56: 1 | J56: 1 | K56: 1 | L56: 1 | M56: 1 | N56: 1 | O56: 1 | P56: Secondary KC Alignment: The intended secondary knowledge component is multiplication of whole numbers, but the problem only requires division operations (432/6=72, then 72/4=18). No multiplication is needed to solve either question. Synergy: Since the secondary knowledge component (multiplication) is not actually used in the problem, there is no synergy between the primary KC (division) and secondary KC (multiplication). Both questions only require division skills.
A57: Minh | B57: Question 7 | C57: 0 | D57: 10.434143 | E57: 1 | F57: 1 | G57: 1 | H57: 1 | I57: 1 | J57: 1 | K57: 1 | L57: 1 | M57: 1 | N57: 1 | O57: 1
A58: Minh | B58: Question 8 | C58: 0 | D58: 12.389018 | E58: 0 | F58: 'NA | G58: 'NA | H58: 'NA | I58: 'NA | J58: 'NA | K58: 'NA | L58: 'NA | M58: 'NA | N58: 'NA | O58: 'NA | P58: Answerability: The second question asks how much longer Wednesday was compared to Monday+Tuesday, but 5/12 < 7/12, so Wednesday was actually shorter, making the question illogical. Primary KC Alignment: The subtraction 5/12 - 7/12 = -1/6 creates a negative result which contradicts the question asking how much longer. Grade Alignment: Fraction operations with unlike denominators are typically taught in Primary 4-5, not Primary 3 in Singapore math curriculum.
A59: Minh | B59: Question 9 | C59: 0 | D59: 2.8656161 | E59: 1 | F59: 1 | G59: 1 | H59: 1 | I59: 1 | J59: 1 | K59: 1 | L59: 1 | M59: 1 | N59: 1 | O59: 1
A60: Minh | B60: Question 10 | C60: 0 | D60: 4.6850567 | E60: 1 | F60: 1 | G60: 1 | H60: 1 | I60: 1 | J60: 1 | K60: 0 | L60: 1 | M60: 1 | N60: 1 | O60: 1 | P60: Real-world feasibility: The numbers of students are unrealistic for inter-school badminton tournaments. Primary schools typically have 300-1500 total students, so bringing 2856, 1944, and 3528 students to a single tournament is implausible. This would represent multiple entire schools worth of students for just cheering activities.
A61: Minh | B61: Question 11 | C61: 0 | D61: 8.6969039 | E61: 1 | F61: 1 | G61: 1 | H61: 1 | I61: 1 | J61: 1 | K61: 1 | L61: 1 | M61: 1 | N61: 1 | O61: 1
A62: Minh | B62: Question 12 | C62: 0 | D62: 9.6030312 | E62: 1 | F62: 1 | G62: 1 | H62: 1 | I62: 1 | J62: 1 | K62: 1 | L62: 1 | M62: 1 | N62: 1 | O62: 1
A63: Minh | B63: Question 13 | C63: 0 | D63: 11.486143 | E63: 1 | F63: 1 | G63: 1 | H63: 1 | I63: 1 | J63: 1 | K63: 1 | L63: 1 | M63: 1 | N63: 1 | O63: 1
A64: Minh | B64: Question 14 | C64: 0 | D64: 6.0283599 | E64: 1 | F64: 1 | G64: 0 | H64: 'NA | I64: 1 | J64: 1 | K64: 1 | L64: 1 | M64: 1 | N64: 1 | O64: 1 | P64: Secondary KC Alignment: The problem asks to express the answer as a mixed number, but the intended secondary KC is about converting decimals to fractions, not mixed numbers. The total is 7.8 km which would be expressed as 7 4/5 as a mixed number, but this requires fraction conversion skills beyond the stated secondary KC. Synergy: Since the secondary KC alignment fails, there is no proper synergy between primary and secondary KCs. The problem primarily focuses on decimal addition with mixed number conversion rather than decimal to fraction conversion.
A65: Minh | B65: Question 15 | C65: 0 | D65: 9.8335447 | E65: 1 | F65: 0 | G65: 1 | H65: 'NA | I65: 1 | J65: 'NA | K65: 1 | L65: 1 | M65: 1 | N65: 1 | O65: 1 | P65: Primary KC specifies adding decimals up to 2 decimal places, but the problem includes 3.126 which has 3 decimal places, exceeding the intended specification.
A66: Minh | B66: Question 16 | C66: 0 | D66: 9.3282745 | E66: 1 | F66: 1 | G66: 1 | H66: 1 | I66: 1 | J66: 1 | K66: 1 | L66: 1 | M66: 1 | N66: 1 | O66: 1
A67: Minh | B67: Question 17 | C67: 0 | D67: 7.5928476 | E67: 1 | F67: 1 | G67: 1 | H67: 1 | I67: 1 | J67: 1 | K67: 1 | L67: 1 | M67: 1 | N67: 1 | O67: 1
A68: Minh | B68: Question 18 | C68: 0 | D68: 7.2211137 | E68: 1 | F68: 1 | G68: 0 | H68: 'NA | I68: 1 | J68: 1 | K68: 1 | L68: 1 | M68: 1 | N68: 1 | O68: 1 | P68: Secondary Knowledge Component Alignment: The problem states Sarah had $8.91 left, making decimal subtraction unnecessary since the remaining amount is directly given. The solution only requires decimal division: $8.91 / 3 = $2.97. Synergy: Since decimal subtraction is not needed to solve the problem, the primary and secondary knowledge components are not used in tandem. The secondary component adds no complexity to the problem-solving process.
A69: Minh | B69: Question 19 | C69: 0 | D69: 9.098927 | E69: 1 | F69: 1 | G69: 1 | H69: 1 | I69: 1 | J69: 1 | K69: 1 | L69: 1 | M69: 1 | N69: 1 | O69: 1
A70: Minh | B70: Question 20 | C70: 0 | D70: 10.230838 | E70: 1 | F70: 1 | G70: 1 | H70: 1 | I70: 1 | J70: 1 | K70: 1 | L70: 1 | M70: 1 | N70: 1 | O70: 1
A71: Minh | B71: Question 21 | C71: 0 | D71: 10.506489 | E71: 1 | F71: 1 | G71: 1 | H71: 1 | I71: 1 | J71: 1 | K71: 1 | L71: 1 | M71: 1 | N71: 1 | O71: 1
A72: Minh | B72: Question 22 | C72: 0 | D72: 7.7063594 | E72: 1 | F72: 1 | G72: 1 | H72: 1 | I72: 1 | J72: 1 | K72: 1 | L72: 1 | M72: 1 | N72: 1 | O72: 1
A73: Minh | B73: Question 23 | C73: 0 | D73: 9.5089548 | E73: 1 | F73: 1 | G73: 1 | H73: 1 | I73: 1 | J73: 1 | K73: 1 | L73: 1 | M73: 1 | N73: 1 | O73: 1
A74: Minh | B74: Question 24 | C74: 0 | D74: 8.643034 | E74: 0 | F74: 'NA | G74: 'NA | H74: 'NA | I74: 'NA | J74: 'NA | K74: 'NA | L74: 'NA | M74: 'NA | N74: 'NA | O74: 'NA | P74: Answerability: The problem has a logical flaw - both students practiced exactly 22 hours total (Sarah: 2.75 × 8 = 22, Emma: 1.833... × 12 = 22), making the question 'who practiced more and by how much' unanswerable as intended since they practiced the same amount. Secondary KC Alignment: While the problem requires calculating two different mixed number products, it does not require comparing/ordering fractions as knowledge components - students only need to compare the final whole number results (22 vs 22). The fraction comparison skill is not actually needed. Synergy: Since the secondary KC (fraction comparison) is not genuinely required, there is no true synergy between multiplying mixed numbers and comparing fractions.
A75: Minh | B75: Question 25 | C75: 0 | D75: 11.613724 | E75: 1 | F75: 1 | G75: 0 | H75: 'NA | I75: 1 | J75: 1 | K75: 1 | L75: 1 | M75: 1 | N75: 1 | O75: 1 | P75: Secondary KC alignment fails because 2 1/4 * 6 = 54/4 = 13 1/2 is already in simplest form, so no actual simplifying work is required. Synergy fails because the secondary KC is not genuinely needed to solve the problem.
A76: Minh | B76: Question 26 | C76: 0 | D76: 8.910187 | E76: 1 | F76: 1 | G76: 1 | H76: 1 | I76: 1 | J76: 1 | K76: 1 | L76: 1 | M76: 1 | N76: 1 | O76: 1
A77: Minh | B77: Question 27 | C77: 0 | D77: 4.5856297 | E77: 1 | F77: 0 | G77: 1 | H77: 'NA | I77: 1 | J77: 'NA | K77: 1 | L77: 1 | M77: 1 | N77: 1 | O77: 1 | P77: Primary KC alignment fails because the problem requires multiplying 23.456 x 30, which involves multiplying a decimal by a 2-digit number rather than specifically by 10, 100, 1000 or their multiples as stated in the intended Primary Knowledge Component.
A78: Minh | B78: Question 28 | C78: 0 | D78: 4.491775 | E78: 1 | F78: 0 | G78: 1 | H78: 'NA | I78: 1 | J78: 'NA | K78: 1 | L78: 1 | M78: 1 | N78: 1 | O78: 1 | P78: Primary KC alignment: The problem requires dividing 142.8 by 60, but the intended primary KC is dividing decimals by 10, 100, 1000 and their multiples. Since 60 is not a multiple of 10, 100, or 1000, this does not align with the intended primary knowledge component.
A79: Minh | B79: Question 29 | C79: 0 | D79: 12.173971 | E79: 1 | F79: 1 | G79: 1 | H79: 1 | I79: 1 | J79: 1 | K79: 0 | L79: 1 | M79: 1 | N79: 1 | O79: 1 | P79: Real-world feasibility: 2400/48 = 50 meters per lap is unusually long for typical swimming pools which are commonly 25m or maximum 50m for Olympic pools, making this scenario unrealistic.
A80: Minh | B80: Question 30 | C80: 0 | D80: 9.127522 | E80: 1 | F80: 1 | G80: 1 | H80: 1 | I80: 1 | J80: 1 | K80: 1 | L80: 1 | M80: 1 | N80: 1 | O80: 1
A81: Minh | B81: Question 31 | C81: 0 | D81: 11.459584 | E81: 1 | F81: 1 | G81: 0 | H81: 'NA | I81: 1 | J81: 1 | K81: 0 | L81: 1 | M81: 1 | N81: 1 | O81: 1 | P81: Secondary KC alignment: Problem converts from larger unit (km) to smaller unit (m), but intended KC is converting smaller to larger units. Synergy: Secondary KC not properly implemented so components don't work in tandem. Real-world feasibility: Running pace of 1.25 km/min equals 75 km/hour which is unrealistic for human marathon training.
A82: Minh | B82: Question 32 | C82: 0 | D82: 10.737748 | E82: 1 | F82: 1 | G82: 0 | H82: 'NA | I82: 1 | J82: 1 | K82: 1 | L82: 1 | M82: 1 | N82: 1 | O82: 1 | P82: Secondary KC alignment: Problem does not involve converting measurements from larger units in decimal form to smaller units - no unit conversion occurs. Synergy: Since secondary KC is not properly integrated, there is no synergy between primary and secondary knowledge components.
A83: Minh | B83: Question 33 | C83: 0 | D83: 11.159025 | E83: 1 | F83: 1 | G83: 1 | H83: 1 | I83: 1 | J83: 1 | K83: 1 | L83: 1 | M83: 1 | N83: 1 | O83: 1
A84: Minh | B84: Question 34 | C84: 0 | D84: 2.9809685 | E84: 1 | F84: 1 | G84: 1 | H84: 1 | I84: 1 | J84: 1 | K84: 1 | L84: 1 | M84: 1 | N84: 1 | O84: 1
A85: Minh | B85: Question 35 | C85: 0 | D85: 7.4460101 | E85: 1 | F85: 1 | G85: 0 | H85: 'NA | I85: 1 | J85: 1 | K85: 1 | L85: 1 | M85: 1 | N85: 1 | O85: 1 | P85: Secondary KC Alignment: The problem asks to express answer in simplest form if it is a fraction, but the answer 3/4 ÷ 1/8 = 6 is a whole number, so no fraction simplification is actually needed or demonstrated. Synergy: Since the secondary knowledge component (fraction simplification) is not actually required to solve the problem, the two knowledge components do not work in tandem as intended.
A86: Minh | B86: Question 36 | C86: 0 | D86: 9.4809606 | E86: 1 | F86: 1 | G86: 1 | H86: 1 | I86: 1 | J86: 1 | K86: 1 | L86: 1 | M86: 1 | N86: 1 | O86: 1
A87: Minh | B87: Question 37 | C87: 0 | D87: 12.43105 | E87: 1 | F87: 0 | G87: 1 | H87: 'NA | I87: 1 | J87: 'NA | K87: 1 | L87: 1 | M87: 1 | N87: 1 | O87: 1 | P87: Primary KC alignment: Problem asks for percentage decrease but accuracy remains constant at 70% both months (84/120 = 105/150 = 0.7), so no decrease exists to calculate. Synergy: Since no actual percentage decrease occurs, primary and secondary knowledge components cannot work together meaningfully.
A88: Minh | B88: Question 38 | C88: 0 | D88: 9.6828141 | E88: 1 | F88: 1 | G88: 1 | H88: 1 | I88: 1 | J88: 1 | K88: 1 | L88: 1 | M88: 1 | N88: 1 | O88: 1
A89: Minh | B89: Question 39 | C89: 0 | D89: 11.15478 | E89: 1 | F89: 1 | G89: 1 | H89: 1 | I89: 1 | J89: 1 | K89: 1 | L89: 1 | M89: 1 | N89: 1 | O89: 1
A90: Minh | B90: Question 40 | C90: 0 | D90: 11.460375 | E90: 1 | F90: 1 | G90: 1 | H90: 1 | I90: 1 | J90: 1 | K90: 1 | L90: 1 | M90: 1 | N90: 1 | O90: 1
A91: Minh | B91: Question 41 | C91: 0 | D91: 10.400881 | E91: 1 | F91: 1 | G91: 1 | H91: 1 | I91: 1 | J91: 1 | K91: 1 | L91: 1 | M91: 1 | N91: 1 | O91: 1
A92: Minh | B92: Question 42 | C92: 0 | D92: 11.178828 | E92: 1 | F92: 1 | G92: 1 | H92: 1 | I92: 1 | J92: 1 | K92: 0 | L92: 1 | M92: 1 | N92: 1 | O92: 1 | P92: Real-world feasibility: The problem states Team A will win all 4 additional games, which changes their win:loss ratio from 3:5 to 22:30. In reality, maintaining or guaranteeing a specific win rate in future games is not realistic.
A93: Minh | B93: Question 43 | C93: 0 | D93: 5.6463094 | E93: 1 | F93: 1 | G93: 1 | H93: 1 | I93: 1 | J93: 0 | K93: 1 | L93: 1 | M93: 1 | N93: 1 | O93: 1 | P93: Grade Alignment: The problem requires advanced algebraic manipulation with variables (a, b) and creating complex algebraic expressions like (a + 2a + 3a) + (b + (b+5) + b) = 6a + 3b + 5, which is beyond Primary 6 level in Singapore math syllabus. Primary 6 students typically work with simple algebraic concepts and basic substitution, not multi-variable expressions of this complexity.
A94: Minh | B94: Question 44 | C94: 0 | D94: 10.621564 | E94: 1 | F94: 1 | G94: 1 | H94: 1 | I94: 1 | J94: 1 | K94: 1 | L94: 1 | M94: 1 | N94: 1 | O94: 1
A95: Minh | B95: Question 45 | C95: 0 | D95: 13.485785 | E95: 1 | F95: 1 | G95: 1 | H95: 1 | I95: 1 | J95: 0 | K95: 1 | L95: 1 | M95: 1 | N95: 1 | O95: 1 | P95: Grade Alignment: The problem involves basic fraction operations (3/4 - 1/6, 5/6 - 1/4) and simple ratio concepts that are typically taught in Primary 5-6. For Secondary O-level 1 students, this content is too elementary and below their expected mathematical level.
A96: Minh | B96: Question 46 | C96: 0 | D96: 5.930495 | E96: 1 | F96: 1 | G96: 1 | H96: 1 | I96: 1 | J96: 0 | K96: 1 | L96: 1 | M96: 1 | N96: 1 | O96: 1 | P96: Grade Alignment: This problem is too elementary for Secondary O-level 1 students. The operations required are basic fraction multiplication (3/4 * 7 and 1/2 * 7), simple ratio representation (21/4 : 7/2), and basic fraction division (21/4 ÷ 3). These skills are typically mastered in upper primary grades (Primary 5-6), not secondary level. Secondary O-level 1 students would be expected to handle more complex mathematical concepts and multi-step problems involving advanced algebraic thinking.
A97: Minh | B97: Question 47 | C97: 0 | D97: 7.6775496 | E97: 1 | F97: 1 | G97: 1 | H97: 1 | I97: 1 | J97: 0 | K97: 1 | L97: 1 | M97: 1 | N97: 1 | O97: 1 | P97: Grade Alignment: This problem requires knowledge of ratios involving decimals and expressing ratios in simplest form by finding GCD of decimal-derived integers. These concepts are typically taught at Secondary 2-3 level in Singapore math curriculum, not Secondary O-level 1. The complexity of finding GCD of larger numbers (97, 66, 129) and working with 3-term ratios involving decimals exceeds Secondary O-level 1 expectations.
A98: Minh | B98: Question 48 | C98: 0 | D98: 4.7633865 | E98: 1 | F98: 1 | G98: 1 | H98: 1 | I98: 1 | J98: 0 | K98: 1 | L98: 1 | M98: 1 | N98: 1 | O98: 1 | P98: Grade Alignment: This problem is too simple for Secondary O-level 1 students. Converting percentages to decimals and basic percentage calculations are typically mastered in Primary 5-6. Secondary O-level 1 students would be expected to handle more complex percentage problems involving compound interest, profit/loss, or multi-step percentage calculations.
A99: Minh | B99: Question 49 | C99: 0 | D99: 4.7245972 | E99: 1 | F99: 1 | G99: 1 | H99: 1 | I99: 1 | J99: 0 | K99: 1 | L99: 1 | M99: 1 | N99: 1 | O99: 1 | P99: Grade alignment: This problem involves basic percentage calculations (25% increase) and simple division (480/12) which are typically mastered in primary grades 5-6. For Secondary O-level 1 students, this problem would be too elementary and does not match the expected complexity level for that grade.
A100: Minh | B100: Question 50 | C100: 0 | D100: 12.593563 | E100: 1 | F100: 0 | G100: 0 | H100: 'NA | I100: 1 | J100: 'NA | K100: 1 | L100: 1 | M100: 1 | N100: 1 | O100: 1 | P100: Primary KC: Problem solved through proportional reasoning and fraction arithmetic, not by solving fractional equations. Secondary KC: No algebraic equations need to be formed from the real-world scenario. Synergy: Neither intended knowledge component is used. Grade: Problem difficulty is too basic for Secondary O-level 1, requiring only upper primary level fraction and proportion skills rather than algebraic equation solving.
...

Sheet recreation_claude_v2_5
A1: Evaluator | B1: Question | C1: status | D1: response_time | E1: answerability | F1: primary_kc_alignment | G1: secondary_kc_alignment | H1: synergy | I1: topic_alignment | J1: grade_alignment | K1: real_world_feasibility | L1: clarity | M1: conciseness_and_relevance | N1: language_quality | O1: content_appropriateness | P1: explanation
A2: TD | B2: Question 1 | C2: 0 | D2: 11.617415 | E2: 1 | F2: 1 | G2: 1 | H2: 1 | I2: 1 | J2: 0 | K2: 1 | L2: 1 | M2: 1 | N2: 1 | O2: 1 | P2: Grade alignment: 4-digit addition (1245+876, 987+1298, 1156+945) may be too advanced for Primary 3 students who typically work with 3-digit whole number operations in Singapore math curriculum.
A3: TD | B3: Question 2 | C3: 0 | D3: 9.4811239 | E3: 1 | F3: 1 | G3: 1 | H3: 1 | I3: 1 | J3: 1 | K3: 1 | L3: 1 | M3: 1 | N3: 1 | O3: 1
A4: TD | B4: Question 3 | C4: 0 | D4: 10.818715 | E4: 1 | F4: 1 | G4: 1 | H4: 1 | I4: 1 | J4: 1 | K4: 1 | L4: 1 | M4: 1 | N4: 1 | O4: 1
A5: TD | B5: Question 4 | C5: 0 | D5: 7.6704519 | E5: 1 | F5: 0 | G5: 1 | H5: 'NA | I5: 1 | J5: 'NA | K5: 1 | L5: 1 | M5: 1 | N5: 1 | O5: 1 | P5: Primary KC alignment: The problem requires multiplying 3-digit numbers (126, 148, 235) by 1-digit numbers (4, 3, 2), but the intended primary KC is multiplying whole numbers UP TO 3 digits by 1 digit, which typically means the multiplicand should be at most 3 digits. However, 126x4=504, 148x3=444, and 235x2=470 are all reasonable calculations, but 235 is a 3-digit number being multiplied, which pushes the boundary. More critically, this level of multiplication may be too advanced for the stated Primary KC scope. Grade alignment: For Primary 3 students, multiplying 3-digit numbers like 126x4, 148x3, and 235x2 is typically too advanced. Primary 3 students usually work with simpler multiplication problems involving smaller numbers.
A6: TD | B6: Question 5 | C6: 0 | D6: 2.8635883 | E6: 1 | F6: 1 | G6: 1 | H6: 1 | I6: 1 | J6: 1 | K6: 1 | L6: 1 | M6: 1 | N6: 1 | O6: 1
A7: TD | B7: Question 6 | C7: 0 | D7: 3.2042382 | E7: 1 | F7: 1 | G7: 1 | H7: 1 | I7: 1 | J7: 1 | K7: 1 | L7: 1 | M7: 1 | N7: 1 | O7: 1
A8: TD | B8: Question 7 | C8: 0 | D8: 10.661453 | E8: 1 | F8: 1 | G8: 1 | H8: 1 | I8: 1 | J8: 1 | K8: 1 | L8: 1 | M8: 1 | N8: 1 | O8: 1
A9: TD | B9: Question 8 | C9: 0 | D9: 8.7032056 | E9: 1 | F9: 1 | G9: 1 | H9: 1 | I9: 1 | J9: 1 | K9: 1 | L9: 1 | M9: 1 | N9: 1 | O9: 1
A10: TD | B10: Question 9 | C10: 0 | D10: 2.9548335 | E10: 1 | F10: 1 | G10: 1 | H10: 1 | I10: 1 | J10: 1 | K10: 1 | L10: 1 | M10: 1 | N10: 1 | O10: 1
A11: TD | B11: Question 10 | C11: 0 | D11: 9.9386742 | E11: 1 | F11: 1 | G11: 1 | H11: 1 | I11: 1 | J11: 1 | K11: 1 | L11: 1 | M11: 1 | N11: 1 | O11: 1
A12: TD | B12: Question 11 | C12: 0 | D12: 11.667341 | E12: 0 | F12: 'NA | G12: 'NA | H12: 'NA | I12: 'NA | J12: 'NA | K12: 'NA | L12: 'NA | M12: 'NA | N12: 'NA | O12: 'NA | P12: Questions (a) and (b) ask for totals when only single fractions are given for each activity - Sarah completed 2/3 of painting and 1/4 of music, but questions ask for totals implying addition is needed when none exists. Primary KC requires adding unlike fractions but the problem structure does not necessitate fraction addition since each person has single values per activity type. The primary and secondary knowledge components cannot work in tandem as intended because the fraction addition component is not properly integrated into the problem structure.
A13: TD | B13: Question 12 | C13: 0 | D13: 10.78279 | E13: 1 | F13: 1 | G13: 1 | H13: 1 | I13: 1 | J13: 1 | K13: 1 | L13: 1 | M13: 1 | N13: 1 | O13: 1
A14: TD | B14: Question 13 | C14: 0 | D14: 11.96278 | E14: 1 | F14: 0 | G14: 1 | H14: 'NA | I14: 1 | J14: 'NA | K14: 1 | L14: 1 | M14: 1 | N14: 1 | O14: 1 | P14: Primary KC alignment: Problem involves adding decimals with 3 decimal places (1.142) which exceeds the intended scope of up to 2 decimal places. Synergy: The two tasks (addition and comparison) are somewhat independent rather than truly integrated. Grade alignment: Using 3 decimal places (1.142) may be beyond Primary 4 level which typically focuses on 1-2 decimal places.
A15: TD | B15: Question 14 | C15: 0 | D15: 9.8080211 | E15: 1 | F15: 1 | G15: 1 | H15: 1 | I15: 1 | J15: 1 | K15: 1 | L15: 1 | M15: 0 | N15: 1 | O15: 1 | P15: The Tuesday practice time of 1.50 hours is mentioned but not needed for solving the problem, violating the requirement that all given numbers must be necessary.
A16: TD | B16: Question 15 | C16: 0 | D16: 9.8104343 | E16: 1 | F16: 1 | G16: 1 | H16: 1 | I16: 1 | J16: 1 | K16: 1 | L16: 1 | M16: 1 | N16: 1 | O16: 1
A17: TD | B17: Question 16 | C17: 0 | D17: 10.247204 | E17: 1 | F17: 1 | G17: 1 | H17: 1 | I17: 1 | J17: 1 | K17: 1 | L17: 1 | M17: 1 | N17: 1 | O17: 1
A18: TD | B18: Question 17 | C18: 0 | D18: 8.6891675 | E18: 1 | F18: 1 | G18: 1 | H18: 1 | I18: 1 | J18: 1 | K18: 1 | L18: 1 | M18: 1 | N18: 1 | O18: 1
A19: TD | B19: Question 18 | C19: 0 | D19: 3.0835211 | E19: 1 | F19: 1 | G19: 1 | H19: 1 | I19: 1 | J19: 1 | K19: 1 | L19: 1 | M19: 1 | N19: 1 | O19: 1
A20: TD | B20: Question 19 | C20: 0 | D20: 6.4564734 | E20: 0 | F20: 'NA | G20: 'NA | H20: 'NA | I20: 'NA | J20: 'NA | K20: 'NA | L20: 'NA | M20: 'NA | N20: 'NA | O20: 'NA | P20: answerability: The problem asks for 'total distance Sarah swam per lap over the two days' which is ambiguous. It could mean (1) distance per lap on each day then sum them, or (2) total distance over both days divided by total number of laps. The wording creates confusion about whether the answer should be 1.56 + 1.75 = 3.31 km or (4.68 + 5.24) / 6 = 1.65 km. clarity: The question 'What is the total distance Sarah swam per lap over the two days?' is unclear and can be interpreted in multiple ways, making it difficult for students to understand what exactly is being asked.
A21: TD | B21: Question 20 | C21: 0 | D21: 9.80902 | E21: 1 | F21: 1 | G21: 1 | H21: 1 | I21: 1 | J21: 1 | K21: 1 | L21: 1 | M21: 1 | N21: 1 | O21: 1
A22: TD | B22: Question 21 | C22: 0 | D22: 9.5236602 | E22: 1 | F22: 1 | G22: 1 | H22: 1 | I22: 1 | J22: 1 | K22: 1 | L22: 1 | M22: 1 | N22: 1 | O22: 1
A23: TD | B23: Question 22 | C23: 0 | D23: 9.412307 | E23: 1 | F23: 1 | G23: 1 | H23: 1 | I23: 1 | J23: 1 | K23: 1 | L23: 1 | M23: 1 | N23: 1 | O23: 1
A24: TD | B24: Question 23 | C24: 0 | D24: 9.0084975 | E24: 1 | F24: 1 | G24: 1 | H24: 1 | I24: 1 | J24: 1 | K24: 1 | L24: 1 | M24: 1 | N24: 1 | O24: 1
A25: TD | B25: Question 24 | C25: 0 | D25: 3.0714173 | E25: 1 | F25: 1 | G25: 1 | H25: 1 | I25: 1 | J25: 1 | K25: 1 | L25: 1 | M25: 1 | N25: 1 | O25: 1
A26: TD | B26: Question 25 | C26: 0 | D26: 8.3874447 | E26: 1 | F26: 1 | G26: 1 | H26: 1 | I26: 1 | J26: 1 | K26: 1 | L26: 1 | M26: 1 | N26: 1 | O26: 1
A27: TD | B27: Question 26 | C27: 0 | D27: 7.6903317 | E27: 1 | F27: 0 | G27: 1 | H27: 'NA | I27: 1 | J27: 'NA | K27: 1 | L27: 1 | M27: 1 | N27: 1 | O27: 1 | P27: Primary KC alignment fails because the problem only requires adding fractions (7/4 + 5/3, 9/5 + 8/7, then adding results) but the intended Primary KC is multiplying two improper fractions, which is not needed at all. Synergy fails because without the Primary KC being used, there is no synergy between Primary and Secondary KCs - only the Secondary KC (fraction addition) is used throughout the problem.
A28: TD | B28: Question 27 | C28: 0 | D28: 14.286865 | E28: 1 | F28: 0 | G28: 1 | H28: 'NA | I28: 1 | J28: 'NA | K28: 1 | L28: 1 | M28: 1 | N28: 1 | O28: 1 | P28: Primary KC alignment: The problem's main difficulty involves fraction addition/subtraction rather than multiplication of improper fractions. While multiplication occurs in the solution (23/12 * 3/2), it is not the primary focus. Synergy: Since the primary KC is not properly aligned, the intended synergy between multiplication and subtraction of fractions is not achieved as designed.
A29: TD | B29: Question 28 | C29: 0 | D29: 9.6711001 | E29: 1 | F29: 1 | G29: 1 | H29: 1 | I29: 1 | J29: 1 | K29: 1 | L29: 1 | M29: 1 | N29: 1 | O29: 1
A30: TD | B30: Question 29 | C30: 0 | D30: 7.8149142 | E30: 1 | F30: 1 | G30: 0 | H30: 'NA | I30: 1 | J30: 1 | K30: 1 | L30: 1 | M30: 1 | N30: 1 | O30: 1 | P30: Secondary KC Alignment: The problem requires subtracting whole numbers (22 - 19 = 3), not subtracting fractions as specified in the intended Secondary Knowledge Component. Synergy: Since the secondary KC (subtracting fractions) is not actually needed, the primary and secondary KCs are not used in tandem as required.
A31: TD | B31: Question 30 | C31: 0 | D31: 11.536116 | E31: 1 | F31: 0 | G31: 1 | H31: 'NA | I31: 1 | J31: 'NA | K31: 1 | L31: 1 | M31: 1 | N31: 1 | O31: 1 | P31: Primary KC alignment fails because the problem requires general decimal multiplication (0.875 × 300) rather than the intended specific skill of multiplying decimals by 10, 100, 1000 and their multiples. Synergy fails because the two knowledge components are used sequentially rather than in integrated tandem - first multiply decimals, then convert to fraction, without the components enhancing each other's application.
A32: TD | B32: Question 31 | C32: 0 | D32: 11.136322 | E32: 1 | F32: 0 | G32: 1 | H32: 'NA | I32: 1 | J32: 'NA | K32: 1 | L32: 1 | M32: 1 | N32: 1 | O32: 1 | P32: Primary KC requires multiplying decimals by 10, 100, 1000 and their multiples, but the problem uses 0.125 * 400 which is general decimal multiplication, not specifically by powers of 10 or their multiples.
A33: TD | B33: Question 32 | C33: 0 | D33: 11.403902 | E33: 1 | F33: 0 | G33: 1 | H33: 'NA | I33: 1 | J33: 'NA | K33: 1 | L33: 1 | M33: 1 | N33: 1 | O33: 1 | P33: Primary KC alignment fails because the problem requires dividing by 7, which is not a multiple of 10, 100, or 1000 as specified in the intended primary knowledge component. Synergy fails because the primary KC is not properly aligned, preventing the intended tandem use of both knowledge components.
A34: TD | B34: Question 33 | C34: 0 | D34: 14.810105 | E34: 0 | F34: 'NA | G34: 'NA | H34: 'NA | I34: 'NA | J34: 'NA | K34: 'NA | L34: 'NA | M34: 'NA | N34: 'NA | O34: 'NA | P34: Answerability: Swimming 40000 meters in practice is unrealistic and creates conflicting scenario. Real-world feasibility: 40 kilometers swimming in single practice session is completely implausible. Clarity: Relationship between 4 laps and 40000 total meters with division by 400 is confusing.
A35: TD | B35: Question 34 | C35: 0 | D35: 10.964511 | E35: 1 | F35: 1 | G35: 1 | H35: 1 | I35: 1 | J35: 1 | K35: 1 | L35: 1 | M35: 1 | N35: 1 | O35: 1
A36: TD | B36: Question 35 | C36: 0 | D36: 2.8423097 | E36: 1 | F36: 1 | G36: 1 | H36: 1 | I36: 1 | J36: 1 | K36: 1 | L36: 1 | M36: 1 | N36: 1 | O36: 1
A37: TD | B37: Question 36 | C37: 0 | D37: 6.9412949 | E37: 1 | F37: 1 | G37: 1 | H37: 1 | I37: 1 | J37: 1 | K37: 0 | L37: 1 | M37: 1 | N37: 1 | O37: 1 | P37: Real-world feasibility: Sarah's running speed of 1.25 km/hr is unrealistic for marathon training. Average walking speed is 5 km/hr and marathon runners train at 10-15 km/hr. A speed of 1.25 km/hr would be extremely slow walking pace, not suitable for marathon preparation.
A38: TD | B38: Question 37 | C38: 0 | D38: 10.952121 | E38: 1 | F38: 1 | G38: 1 | H38: 1 | I38: 1 | J38: 1 | K38: 1 | L38: 1 | M38: 1 | N38: 1 | O38: 1
A39: TD | B39: Question 38 | C39: 0 | D39: 2.9735079 | E39: 1 | F39: 1 | G39: 1 | H39: 1 | I39: 1 | J39: 1 | K39: 1 | L39: 1 | M39: 1 | N39: 1 | O39: 1
A40: TD | B40: Question 39 | C40: 0 | D40: 11.256452 | E40: 1 | F40: 1 | G40: 1 | H40: 1 | I40: 1 | J40: 1 | K40: 0 | L40: 1 | M40: 1 | N40: 1 | O40: 1 | P40: Real-world feasibility fails because dividing practice time over 2/3 of a week (4.67 days) is unrealistic - people typically plan practice schedules over whole days, not fractional portions of days.
A41: TD | B41: Question 40 | C41: 0 | D41: 10.744537 | E41: 0 | F41: 'NA | G41: 'NA | H41: 'NA | I41: 'NA | J41: 'NA | K41: 'NA | L41: 'NA | M41: 'NA | N41: 'NA | O41: 'NA | P41: The problem is missing critical information - Sarah's total practice time for today. Without knowing the total practice time, it is impossible to calculate how many complete sessions she has finished. The problem states she completed 3/4 of her total practice time and each session is 2/5 hour, but the total practice time value is needed to solve (3/4 * total time) / (2/5 hour per session).
A42: TD | B42: Question 41 | C42: 0 | D42: 8.4913306 | E42: 1 | F42: 1 | G42: 1 | H42: 1 | I42: 1 | J42: 1 | K42: 1 | L42: 1 | M42: 1 | N42: 1 | O42: 1
A43: TD | B43: Question 42 | C43: 0 | D43: 9.7348709 | E43: 1 | F43: 1 | G43: 1 | H43: 1 | I43: 1 | J43: 1 | K43: 1 | L43: 1 | M43: 1 | N43: 1 | O43: 1
A44: TD | B44: Question 43 | C44: 0 | D44: 11.264399 | E44: 1 | F44: 1 | G44: 0 | H44: 'NA | I44: 1 | J44: 1 | K44: 1 | L44: 1 | M44: 1 | N44: 1 | O44: 1 | P44: Secondary KC alignment: The problem does not require addition of whole numbers as the point totals are given directly (45, 36, 54). No addition operations are needed to solve for the ratio. Synergy: Since addition is not required, there is no synergy between finding ratios and adding whole numbers.
A45: TD | B45: Question 44 | C45: 0 | D45: 11.964055 | E45: 1 | F45: 1 | G45: 1 | H45: 1 | I45: 1 | J45: 0 | K45: 1 | L45: 1 | M45: 1 | N45: 1 | O45: 1 | P45: Grade alignment fails because solving linear equations with variables like 4x + 5 = 89 is typically taught in Secondary 1, not Primary 6. Primary 6 students work with simpler algebraic concepts without formal equation solving.
A46: TD | B46: Question 45 | C46: 0 | D46: 6.5599129 | E46: 1 | F46: 1 | G46: 1 | H46: 1 | I46: 1 | J46: 0 | K46: 1 | L46: 1 | M46: 1 | N46: 1 | O46: 1 | P46: Grade alignment issue: This problem involves basic percentage calculations (25%, 15%) and simple whole number operations that are typically mastered in Primary 5-6. For Secondary O-level 1 students, this represents content significantly below their expected mathematical level, making it inappropriately easy for the intended grade.
A47: TD | B47: Question 46 | C47: 0 | D47: 11.754531 | E47: 1 | F47: 1 | G47: 1 | H47: 1 | I47: 1 | J47: 0 | K47: 1 | L47: 1 | M47: 1 | N47: 1 | O47: 1 | P47: Grade Alignment: The problem involves reverse percentages and percentage-to-decimal conversion, which are typically taught in Primary 5-6 levels. Secondary O-level 1 students would be expected to work on more advanced mathematical concepts appropriate for their grade level.
A48: TD | B48: Question 47 | C48: 0 | D48: 12.029417 | E48: 1 | F48: 1 | G48: 1 | H48: 1 | I48: 1 | J48: 0 | K48: 1 | L48: 1 | M48: 1 | N48: 1 | O48: 1 | P48: Grade alignment: Problem involves basic ratio 3:5 and simple multiplication by 4, concepts typically mastered in Primary 5-6. Secondary O-level 2 students need more complex algebraic reasoning, simultaneous equations, or advanced proportional problems.
A49: TD | B49: Question 48 | C49: 0 | D49: 9.4713063 | E49: 1 | F49: 1 | G49: 1 | H49: 1 | I49: 1 | J49: 1 | K49: 1 | L49: 1 | M49: 1 | N49: 1 | O49: 1
A50: TD | B50: Question 49 | C50: 0 | D50: 5.228617 | E50: 1 | F50: 1 | G50: 1 | H50: 1 | I50: 1 | J50: 0 | K50: 1 | L50: 1 | M50: 1 | N50: 1 | O50: 1 | P50: Grade Alignment: Standard deviation calculation is typically taught at upper secondary or pre-university level (Secondary 4/5 or A-levels), not at Secondary O-level 3/4. This mathematical concept requires understanding of variance, square roots of sums of squared deviations, and statistical analysis that exceeds the typical curriculum for O-level 3/4 students.
A51: Minh | B51: Question 1 | C51: 0 | D51: 10.656481 | E51: 1 | F51: 1 | G51: 1 | H51: 1 | I51: 1 | J51: 1 | K51: 1 | L51: 1 | M51: 1 | N51: 1 | O51: 1
A52: Minh | B52: Question 2 | C52: 0 | D52: 10.20438 | E52: 1 | F52: 1 | G52: 0 | H52: 'NA | I52: 1 | J52: 1 | K52: 1 | L52: 1 | M52: 1 | N52: 1 | O52: 1 | P52: Secondary KC alignment fails because the third question asks for total students participating which is given as 847 - no addition calculation needed. Synergy fails because addition is not required so primary and secondary KCs do not work together.
A53: Minh | B53: Question 3 | C53: 0 | D53: 2.8809469 | E53: 1 | F53: 1 | G53: 1 | H53: 1 | I53: 1 | J53: 1 | K53: 1 | L53: 1 | M53: 1 | N53: 1 | O53: 1
A54: Minh | B54: Question 4 | C54: 0 | D54: 3.0364149 | E54: 1 | F54: 1 | G54: 1 | H54: 1 | I54: 1 | J54: 1 | K54: 1 | L54: 1 | M54: 1 | N54: 1 | O54: 1
A55: Minh | B55: Question 5 | C55: 0 | D55: 7.2716005 | E55: 1 | F55: 0 | G55: 1 | H55: 'NA | I55: 1 | J55: 'NA | K55: 1 | L55: 1 | M55: 1 | N55: 1 | O55: 1 | P55: Primary KC alignment fails because the division required is 816 / 6 which involves dividing a 3-digit number by 1-digit, but 816 exceeds typical 3-digit scope for Primary 3. Grade alignment fails because Primary 3 students typically work with smaller numbers - dividing 816 by 6 requiring knowledge of 6x136=816 is too advanced for Primary 3 level.
A56: Minh | B56: Question 6 | C56: 0 | D56: 7.3693457 | E56: 1 | F56: 1 | G56: 0 | H56: 'NA | I56: 1 | J56: 1 | K56: 1 | L56: 1 | M56: 1 | N56: 1 | O56: 1 | P56: Secondary KC Alignment: The intended secondary knowledge component is multiplication of whole numbers, but the problem only requires division operations (432/6=72, then 72/4=18). No multiplication is needed to solve either question. Synergy: Since multiplication is not actually required, there is no synergy between the intended primary KC (division) and secondary KC (multiplication). Both questions only use division, so the knowledge components are not used in tandem as intended.
A57: Minh | B57: Question 7 | C57: 0 | D57: 2.9733546 | E57: 1 | F57: 1 | G57: 1 | H57: 1 | I57: 1 | J57: 1 | K57: 1 | L57: 1 | M57: 1 | N57: 1 | O57: 1
A58: Minh | B58: Question 8 | C58: 0 | D58: 4.5747297 | E58: 1 | F58: 1 | G58: 1 | H58: 1 | I58: 1 | J58: 0 | K58: 1 | L58: 1 | M58: 1 | N58: 1 | O58: 1 | P58: Grade Alignment: The problem requires operations with fractions having denominators 8, 4, and 12, requiring finding common denominators (LCD of 24) and complex fraction arithmetic that exceeds Primary 3 level capabilities. Primary 3 students typically work with simpler fractions like halves, quarters, and basic unit fractions.
A59: Minh | B59: Question 9 | C59: 0 | D59: 10.268669 | E59: 1 | F59: 1 | G59: 1 | H59: 1 | I59: 1 | J59: 1 | K59: 1 | L59: 1 | M59: 1 | N59: 1 | O59: 1
A60: Minh | B60: Question 10 | C60: 0 | D60: 4.1870804 | E60: 1 | F60: 1 | G60: 1 | H60: 1 | I60: 1 | J60: 1 | K60: 0 | L60: 1 | M60: 1 | N60: 1 | O60: 1 | P60: Real-world feasibility fails because bringing 2856, 1944, and 3528 students from individual primary schools to a badminton tournament is unrealistic. Primary schools typically have 200-800 total students, and bringing thousands of students to watch a tournament would be logistically impossible and unsafe.
A61: Minh | B61: Question 11 | C61: 0 | D61: 10.514935 | E61: 1 | F61: 1 | G61: 1 | H61: 1 | I61: 1 | J61: 1 | K61: 1 | L61: 1 | M61: 1 | N61: 1 | O61: 1
A62: Minh | B62: Question 12 | C62: 0 | D62: 10.422291 | E62: 1 | F62: 1 | G62: 1 | H62: 1 | I62: 1 | J62: 1 | K62: 1 | L62: 1 | M62: 1 | N62: 1 | O62: 1
A63: Minh | B63: Question 13 | C63: 0 | D63: 2.9143412 | E63: 1 | F63: 1 | G63: 1 | H63: 1 | I63: 1 | J63: 1 | K63: 1 | L63: 1 | M63: 1 | N63: 1 | O63: 1
A64: Minh | B64: Question 14 | C64: 0 | D64: 6.4166687 | E64: 1 | F64: 1 | G64: 0 | H64: 'NA | I64: 1 | J64: 1 | K64: 1 | L64: 1 | M64: 1 | N64: 1 | O64: 1 | P64: Secondary KC alignment: The problem asks to express answer as mixed number, but the intended secondary KC is converting decimals to fractions, not mixed numbers. The solution involves adding decimals (2.75 + 1.8 + 3.25 = 7.8) then converting 7.8 to mixed number 7 4/5, but this requires fraction conversion skills beyond the stated secondary KC. Synergy: Since secondary KC alignment fails, primary and secondary KCs cannot work in tandem as intended. The problem becomes primarily about decimal addition with mixed number conversion rather than decimal to fraction conversion.
A65: Minh | B65: Question 15 | C65: 0 | D65: 5.3955798 | E65: 1 | F65: 0 | G65: 1 | H65: 'NA | I65: 1 | J65: 'NA | K65: 1 | L65: 1 | M65: 1 | N65: 1 | O65: 1 | P65: Primary KC alignment: The problem requires adding 3.126 km which has 3 decimal places, but the intended primary KC is limited to adding decimals up to 2 decimal places only. Grade alignment: Primary 4 students typically work with decimals up to 2 decimal places, but this problem includes 3.126 km which has 3 decimal places, making it too advanced for the intended grade level.
A66: Minh | B66: Question 16 | C66: 0 | D66: 2.8345768 | E66: 1 | F66: 1 | G66: 1 | H66: 1 | I66: 1 | J66: 1 | K66: 1 | L66: 1 | M66: 1 | N66: 1 | O66: 1
A67: Minh | B67: Question 17 | C67: 0 | D67: 2.9753349 | E67: 1 | F67: 1 | G67: 1 | H67: 1 | I67: 1 | J67: 1 | K67: 1 | L67: 1 | M67: 1 | N67: 1 | O67: 1
A68: Minh | B68: Question 18 | C68: 0 | D68: 12.385565 | E68: 1 | F68: 1 | G68: 0 | H68: 'NA | I68: 1 | J68: 1 | K68: 1 | L68: 1 | M68: 1 | N68: 1 | O68: 1 | P68: Secondary KC alignment fails because the problem directly states Sarah had 8.91 left rather than requiring subtraction calculation (12.48 + 2.76 from original allowance). Synergy fails because the secondary KC (subtracting decimals) is not actually needed to solve the problem, so the two knowledge components are not used in tandem.
A69: Minh | B69: Question 19 | C69: 0 | D69: 10.220716 | E69: 1 | F69: 1 | G69: 1 | H69: 1 | I69: 1 | J69: 1 | K69: 1 | L69: 1 | M69: 1 | N69: 1 | O69: 1
A70: Minh | B70: Question 20 | C70: 0 | D70: 8.6004028 | E70: 1 | F70: 1 | G70: 1 | H70: 1 | I70: 1 | J70: 1 | K70: 1 | L70: 1 | M70: 1 | N70: 1 | O70: 1
A71: Minh | B71: Question 21 | C71: 0 | D71: 10.320682 | E71: 1 | F71: 1 | G71: 1 | H71: 1 | I71: 1 | J71: 1 | K71: 1 | L71: 1 | M71: 1 | N71: 1 | O71: 1
A72: Minh | B72: Question 22 | C72: 0 | D72: 10.026516 | E72: 1 | F72: 1 | G72: 1 | H72: 1 | I72: 1 | J72: 1 | K72: 1 | L72: 1 | M72: 1 | N72: 1 | O72: 1
A73: Minh | B73: Question 23 | C73: 0 | D73: 10.042344 | E73: 1 | F73: 1 | G73: 1 | H73: 1 | I73: 1 | J73: 1 | K73: 1 | L73: 1 | M73: 1 | N73: 1 | O73: 1
A74: Minh | B74: Question 24 | C74: 0 | D74: 8.4212837 | E74: 0 | F74: 'NA | G74: 'NA | H74: 'NA | I74: 'NA | J74: 'NA | K74: 'NA | L74: 'NA | M74: 'NA | N74: 'NA | O74: 'NA | P74: Answerability: The problem has a logical flaw - both Sarah (2 3/4 × 8 = 22) and Emma (1 5/6 × 12 = 22) practiced exactly the same total hours, making the question 'who practiced more and by how much' unanswerable as neither practiced more. Secondary KC Alignment: While the problem requires multiplication of mixed numbers and whole numbers (primary KC), it does not require comparing/ordering fractions (secondary KC) since students only need to compare the final whole number results (22 vs 22), not fractional values. Synergy: Since the secondary KC (fraction comparison) is not actually needed, the two knowledge components do not work in tandem to solve the problem.
A75: Minh | B75: Question 25 | C75: 0 | D75: 10.591741 | E75: 1 | F75: 1 | G75: 0 | H75: 'NA | I75: 1 | J75: 1 | K75: 1 | L75: 1 | M75: 1 | N75: 1 | O75: 1 | P75: Secondary KC alignment: The calculation 2+1/4 * 6 = 54/4 = 13+1/2 results in 13+1/2 which is already in simplest form, so no actual simplification is needed. Synergy: Since the secondary knowledge component of simplifying fractions is not actually required to solve the problem, the two knowledge components do not work in tandem.
A76: Minh | B76: Question 26 | C76: 0 | D76: 10.024194 | E76: 1 | F76: 1 | G76: 1 | H76: 1 | I76: 1 | J76: 1 | K76: 1 | L76: 1 | M76: 1 | N76: 1 | O76: 1
A77: Minh | B77: Question 27 | C77: 0 | D77: 4.7047439 | E77: 1 | F77: 0 | G77: 1 | H77: 'NA | I77: 1 | J77: 'NA | K77: 1 | L77: 1 | M77: 1 | N77: 1 | O77: 1 | P77: Primary KC alignment fails because the problem requires multiplying 23.456 x 30, which is multiplying a decimal by a whole number that is not 10, 100, 1000 or their multiples. The intended Primary KC specifically targets multiplying decimals by 10, 100, 1000 and their multiples only.
A78: Minh | B78: Question 28 | C78: 0 | D78: 4.565273 | E78: 1 | F78: 0 | G78: 1 | H78: 'NA | I78: 1 | J78: 'NA | K78: 1 | L78: 1 | M78: 1 | N78: 1 | O78: 1 | P78: Primary KC alignment fails because the problem requires dividing 142.8 by 60, but the intended primary KC is about dividing decimals by 10, 100, 1000 and their multiples. 60 is not a multiple of 10, 100, or 1000.
A79: Minh | B79: Question 29 | C79: 0 | D79: 7.3940613 | E79: 1 | F79: 1 | G79: 1 | H79: 1 | I79: 1 | J79: 1 | K79: 0 | L79: 1 | M79: 1 | N79: 1 | O79: 1 | P79: Real-world feasibility issue: The calculated rate is 50 meters per lap, which means each lap of the pool is 50 meters long. This is unusually long for a typical swimming pool - standard pools are 25m or 50m in total length, not per lap. A lap typically refers to swimming from one end to the other and back (or just one way), so 50m per lap suggests a 100m pool or 25m one-way laps, both of which are unrealistic for typical training scenarios.
A80: Minh | B80: Question 30 | C80: 0 | D80: 10.126662 | E80: 1 | F80: 1 | G80: 1 | H80: 1 | I80: 1 | J80: 1 | K80: 1 | L80: 1 | M80: 1 | N80: 1 | O80: 1
A81: Minh | B81: Question 31 | C81: 0 | D81: 14.312466 | E81: 1 | F81: 0 | G81: 0 | H81: 'NA | I81: 1 | J81: 'NA | K81: 0 | L81: 1 | M81: 1 | N81: 1 | O81: 1 | P81: Primary KC: Decimal multiplication 1.25 * 48 too advanced for Primary 5. Secondary KC: Problem converts km to m (larger to smaller unit) but intended KC is smaller to larger unit conversion. Grade alignment: 1.25 * 48 calculation exceeds Primary 5 level. Real-world: 1.25 km/min = 75 km/h unrealistic for human running speed.
A82: Minh | B82: Question 32 | C82: 0 | D82: 10.863117 | E82: 1 | F82: 1 | G82: 0 | H82: 'NA | I82: 1 | J82: 1 | K82: 1 | L82: 1 | M82: 1 | N82: 1 | O82: 1 | P82: Secondary KC alignment: The problem does not require converting measurements from larger to smaller units - both rate and time use minutes as the unit. Synergy: Since the secondary KC is not present in the problem, there is no synergy between primary and secondary knowledge components.
A83: Minh | B83: Question 33 | C83: 0 | D83: 9.6226172 | E83: 1 | F83: 1 | G83: 1 | H83: 1 | I83: 1 | J83: 1 | K83: 1 | L83: 1 | M83: 1 | N83: 1 | O83: 1
A84: Minh | B84: Question 34 | C84: 0 | D84: 7.5394487 | E84: 0 | F84: 'NA | G84: 'NA | H84: 'NA | I84: 'NA | J84: 'NA | K84: 'NA | L84: 'NA | M84: 'NA | N84: 'NA | O84: 'NA | P84: Answerability: Tuesday calculation gives 11/6 divided by 2/9 equals 33/4 = 8.25 sessions, which is not a whole number. Cannot have fractional practice sessions. Real-world feasibility: Same issue - the mathematical result of 8.25 sessions does not represent a realistic scenario since practice sessions must be complete units.
A85: Minh | B85: Question 35 | C85: 0 | D85: 11.274426 | E85: 1 | F85: 1 | G85: 0 | H85: 'NA | I85: 1 | J85: 1 | K85: 1 | L85: 1 | M85: 1 | N85: 1 | O85: 1 | P85: Secondary KC alignment: The answer is 6, a whole number, so simplifying fractions is not needed. Synergy: Since secondary KC is not required, there is no synergy between primary and secondary components.
A86: Minh | B86: Question 36 | C86: 0 | D86: 7.8736556 | E86: 1 | F86: 1 | G86: 1 | H86: 1 | I86: 1 | J86: 1 | K86: 0 | L86: 0 | M86: 1 | N86: 1 | O86: 1 | P86: Real-world feasibility: The problem states opponents scored 47 points in second half only, but typical basketball games have 15-20 minute halves where scoring 47 points in one half is unrealistically high for most levels of play. Clarity: The problem is ambiguous - it asks for second half score but the given information (23 fewer than total) relates to total game score, creating confusion about whether opponents scored 47 total or 47 in second half only.
A87: Minh | B87: Question 37 | C87: 0 | D87: 6.434576 | E87: 0 | F87: 'NA | G87: 'NA | H87: 'NA | I87: 'NA | J87: 'NA | K87: 'NA | L87: 'NA | M87: 'NA | N87: 'NA | O87: 'NA | P87: ANSWERABILITY: The problem asks to find percentage decrease but the actual answer is 0% change (70% to 70% accuracy). This creates a logical contradiction as there is no decrease to find. CLARITY: The problem is misleading by asking students to find a decrease when no decrease exists, causing confusion about what answer is expected.
A88: Minh | B88: Question 38 | C88: 0 | D88: 8.0960717 | E88: 1 | F88: 1 | G88: 1 | H88: 0 | I88: 1 | J88: 1 | K88: 1 | L88: 1 | M88: 0 | N88: 1 | O88: 1 | P88: SYNERGY: The two questions can be solved independently. Question 1 uses multiplication (63-45) * 3 = 54, Question 2 uses percentage increase ((63-45)/45) * 100 = 40%. Neither question requires the result from the other question. CONCISENESS_AND_RELEVANCE: The points information (3 points per free throw) is only needed for question 1 but not for question 2. The free throw data (45 and 63) is only needed for question 2 but the points calculation in question 1 could be solved with just the difference. Some given information is not necessary for all parts of the problem.
A89: Minh | B89: Question 39 | C89: 0 | D89: 9.9114048 | E89: 1 | F89: 1 | G89: 1 | H89: 1 | I89: 1 | J89: 1 | K89: 1 | L89: 1 | M89: 1 | N89: 1 | O89: 1
A90: Minh | B90: Question 40 | C90: 0 | D90: 2.8670089 | E90: 1 | F90: 1 | G90: 1 | H90: 1 | I90: 1 | J90: 1 | K90: 1 | L90: 1 | M90: 1 | N90: 1 | O90: 1
A91: Minh | B91: Question 41 | C91: 0 | D91: 2.969018 | E91: 1 | F91: 1 | G91: 1 | H91: 1 | I91: 1 | J91: 1 | K91: 1 | L91: 1 | M91: 1 | N91: 1 | O91: 1
A92: Minh | B92: Question 42 | C92: 0 | D92: 9.946465 | E92: 1 | F92: 1 | G92: 1 | H92: 1 | I92: 1 | J92: 1 | K92: 1 | L92: 1 | M92: 1 | N92: 1 | O92: 1
A93: Minh | B93: Question 43 | C93: 0 | D93: 2.8073866 | E93: 1 | F93: 1 | G93: 1 | H93: 1 | I93: 1 | J93: 1 | K93: 1 | L93: 1 | M93: 1 | N93: 1 | O93: 1
A94: Minh | B94: Question 44 | C94: 0 | D94: 11.144025 | E94: 1 | F94: 1 | G94: 1 | H94: 1 | I94: 1 | J94: 1 | K94: 1 | L94: 1 | M94: 1 | N94: 1 | O94: 1
A95: Minh | B95: Question 45 | C95: 0 | D95: 13.603111 | E95: 1 | F95: 1 | G95: 1 | H95: 1 | I95: 1 | J95: 0 | K95: 1 | L95: 1 | M95: 1 | N95: 1 | O95: 1 | P95: Grade Alignment: The problem difficulty level (involving basic fraction subtraction like 3/4 - 1/6 and simple ratios) is more suitable for Primary 5-6 students in Singapore math curriculum, not Secondary O-level 1 students who should handle more advanced mathematical concepts.
A96: Minh | B96: Question 46 | C96: 0 | D96: 7.892669 | E96: 1 | F96: 1 | G96: 1 | H96: 1 | I96: 1 | J96: 0 | K96: 1 | L96: 1 | M96: 1 | N96: 1 | O96: 1 | P96: Grade alignment fails because this problem is too simple for Secondary O-level 1 students. The intended grade typically handles advanced algebra, trigonometry, and complex mathematical concepts, while this problem only requires basic fraction operations and ratios suitable for upper primary or lower secondary levels. The mathematical complexity (multiplying fractions by whole numbers, simple division, basic ratios) does not match the expected difficulty for O-level students.
A97: Minh | B97: Question 47 | C97: 0 | D97: 12.164172 | E97: 1 | F97: 1 | G97: 1 | H97: 1 | I97: 1 | J97: 0 | K97: 1 | L97: 1 | M97: 1 | N97: 1 | O97: 1 | P97: Grade Alignment: The problem requires converting decimal ratios 19.4:13.2:25.8 to simplest integer form 97:66:129, which involves complex ratio simplification beyond typical Secondary O-level 1 curriculum. This level of ratio manipulation is too advanced for the intended grade.
A98: Minh | B98: Question 48 | C98: 0 | D98: 10.456962 | E98: 1 | F98: 1 | G98: 1 | H98: 1 | I98: 1 | J98: 0 | K98: 1 | L98: 1 | M98: 1 | N98: 1 | O98: 1 | P98: Grade Alignment: The problem involves basic percentage calculations (24/40, 18/30) and simple decimal conversions which are elementary level concepts, not appropriate for Secondary O-level 1 students who should be working with more advanced mathematical concepts.
A99: Minh | B99: Question 49 | C99: 0 | D99: 4.8831336 | E99: 1 | F99: 1 | G99: 1 | H99: 1 | I99: 1 | J99: 0 | K99: 1 | L99: 1 | M99: 1 | N99: 1 | O99: 1 | P99: Grade alignment issue: This problem involves basic percentage calculations (25% increase) and simple division (480/12) which are typically covered in Primary 5-6 grades, not Secondary O-level 1. Secondary O-level 1 students would be expected to handle more complex mathematical concepts beyond basic percentage increases and whole number division.
A100: Minh | B100: Question 50 | C100: 0 | D100: 8.2547367 | E100: 1 | F100: 0 | G100: 0 | H100: 'NA | I100: 1 | J100: 'NA | K100: 1 | L100: 1 | M100: 1 | N100: 1 | O100: 1 | P100: Primary KC alignment: The problem can be solved using simple proportional reasoning without requiring fractional equations or algebraic solving. If 2/3 distance takes 24 minutes, then full distance takes 36 minutes at constant speed. To complete in 30 minutes requires speed increase of 36/30 = 6/5. In first 12 minutes at new speed, distance = (1/5) * (6/5) * full distance = 2/5 of planned distance. No fractional equations needed. Secondary KC alignment: Problem does not require translation to equations - can be solved through direct proportional relationships and arithmetic without algebraic representation. Synergy: Since neither primary nor secondary KC are properly addressed, they are not used in tandem as intended. Grade alignment: This proportional reasoning problem is more suitable for upper primary or lower secondary levels, not O-level 1 which should involve more complex algebraic concepts including fractional equations.
...

Sheet Compiled Votes
A1: Evaluator | B1: Question | C1: status | D1: response_time | E1: answerability | F1: primary_kc_alignment | G1: secondary_kc_alignment | H1: topic_alignment | I1: grade_alignment | J1: real_world_feasibility | K1: synergy | L1: clarity | M1: conciseness_and_relevance | N1: language_quality | O1: content_appropriateness
A2: TD | B2: Question 1 | C2: 0 | D2: 11.617415 | E2: =ROUND(SUM(recreation_claude_v2_5!E2,recreation_claude_v2_4!E2,recreation_claude_v2_3!E2,recreation_claude_v2_2!E2,recreation_claude_v2_1!E2)/COUNT(recreation_claude_v2_5!E2,recreation_claude_v2_4!E2,recreation_claude_v2_3!E2,recreation_claude_v2_2!E2,recreation_claude_v2_1!E2),0) -> 1 | F2: =IF($E2 = 1,ROUND(SUM(recreation_claude_v2_5!F2,recreation_claude_v2_4!F2,recreation_claude_v2_3!F2,recreation_claude_v2_2!F2,recreation_claude_v2_1!F2)/COUNT(recreation_claude_v2_5!F2,recreation_claude_v2_4!F2,recreation_claude_v2_3!F2,recreation_claude_v2_2!F2,recreation_claude_v2_1!F2),0),"NA") -> 1 | G2: =IF($E2 = 1,ROUND(SUM(recreation_claude_v2_5!G2,recreation_claude_v2_4!G2,recreation_claude_v2_3!G2,recreation_claude_v2_2!G2,recreation_claude_v2_1!G2)/COUNT(recreation_claude_v2_5!G2,recreation_claude_v2_4!G2,recreation_claude_v2_3!G2,recreation_claude_v2_2!G2,recreation_claude_v2_1!G2),0),"NA") -> 1 | H2: =IF($E2 = 1,ROUND(SUM(recreation_claude_v2_5!I2,recreation_claude_v2_4!I2,recreation_claude_v2_3!I2,recreation_claude_v2_2!I2,recreation_claude_v2_1!I2)/COUNT(recreation_claude_v2_5!I2,recreation_claude_v2_4!I2,recreation_claude_v2_3!I2,recreation_claude_v2_2!I2,recreation_claude_v2_1!I2),0),"NA") -> 1 | I2: =IF($F2 = 1,ROUND(SUM(recreation_claude_v2_5!J2,recreation_claude_v2_4!J2,recreation_claude_v2_3!J2,recreation_claude_v2_2!J2,recreation_claude_v2_1!J2)/COUNT(recreation_claude_v2_5!J2,recreation_claude_v2_4!J2,recreation_claude_v2_3!J2,recreation_claude_v2_2!J2,recreation_claude_v2_1!J2),0),"NA") -> 0 | J2: =IF($E2 = 1,ROUND(SUM(recreation_claude_v2_5!K2,recreation_claude_v2_4!K2,recreation_claude_v2_3!K2,recreation_claude_v2_2!K2,recreation_claude_v2_1!K2)/COUNT(recreation_claude_v2_5!K2,recreation_claude_v2_4!K2,recreation_claude_v2_3!K2,recreation_claude_v2_2!K2,recreation_claude_v2_1!K2),0),"NA") -> 1 | K2: =IF(AND($F2 = 1, $G2 = 1),ROUND(SUM(recreation_claude_v2_5!$H2,recreation_claude_v2_4!$H2,recreation_claude_v2_3!$H2,recreation_claude_v2_2!$H2,recreation_claude_v2_1!$H2)/COUNT(recreation_claude_v2_5!$H2,recreation_claude_v2_4!$H2,recreation_claude_v2_3!$H2,recreation_claude_v2_2!$H2,recreation_claude_v2_1!$H2),0)) -> 1 | L2: =IF($E2 = 1,ROUND(SUM(recreation_claude_v2_5!L2,recreation_claude_v2_4!L2,recreation_claude_v2_3!L2,recreation_claude_v2_2!L2,recreation_claude_v2_1!L2)/COUNT(recreation_claude_v2_5!L2,recreation_claude_v2_4!L2,recreation_claude_v2_3!L2,recreation_claude_v2_2!L2,recreation_claude_v2_1!L2),0),"NA") -> 1 | M2: =IF($E2 = 1,ROUND(SUM(recreation_claude_v2_5!M2,recreation_claude_v2_4!M2,recreation_claude_v2_3!M2,recreation_claude_v2_2!M2,recreation_claude_v2_1!M2)/COUNT(recreation_claude_v2_5!M2,recreation_claude_v2_4!M2,recreation_claude_v2_3!M2,recreation_claude_v2_2!M2,recreation_claude_v2_1!M2),0),"NA") -> 1 | N2: =IF($E2 = 1,ROUND(SUM(recreation_claude_v2_5!N2,recreation_claude_v2_4!N2,recreation_claude_v2_3!N2,recreation_claude_v2_2!N2,recreation_claude_v2_1!N2)/COUNT(recreation_claude_v2_5!N2,recreation_claude_v2_4!N2,recreation_claude_v2_3!N2,recreation_claude_v2_2!N2,recreation_claude_v2_1!N2),0),"NA") -> 1 | O2: =IF($E2 = 1,ROUND(SUM(recreation_claude_v2_5!O2,recreation_claude_v2_4!O2,recreation_claude_v2_3!O2,recreation_claude_v2_2!O2,recreation_claude_v2_1!O2)/COUNT(recreation_claude_v2_5!O2,recreation_claude_v2_4!O2,recreation_claude_v2_3!O2,recreation_claude_v2_2!O2,recreation_claude_v2_1!O2),0),"NA") -> 1
A3: TD | B3: Question 2 | C3: 0 | D3: 9.4811239 | E3: =ROUND(SUM(recreation_claude_v2_5!E3,recreation_claude_v2_4!E3,recreation_claude_v2_3!E3,recreation_claude_v2_2!E3,recreation_claude_v2_1!E3)/COUNT(recreation_claude_v2_5!E3,recreation_claude_v2_4!E3,recreation_claude_v2_3!E3,recreation_claude_v2_2!E3,recreation_claude_v2_1!E3),0) -> 1 | F3: =IF($E3 = 1,ROUND(SUM(recreation_claude_v2_5!F3,recreation_claude_v2_4!F3,recreation_claude_v2_3!F3,recreation_claude_v2_2!F3,recreation_claude_v2_1!F3)/COUNT(recreation_claude_v2_5!F3,recreation_claude_v2_4!F3,recreation_claude_v2_3!F3,recreation_claude_v2_2!F3,recreation_claude_v2_1!F3),0),"NA") -> 1 | G3: =IF($E3 = 1,ROUND(SUM(recreation_claude_v2_5!G3,recreation_claude_v2_4!G3,recreation_claude_v2_3!G3,recreation_claude_v2_2!G3,recreation_claude_v2_1!G3)/COUNT(recreation_claude_v2_5!G3,recreation_claude_v2_4!G3,recreation_claude_v2_3!G3,recreation_claude_v2_2!G3,recreation_claude_v2_1!G3),0),"NA") -> 1 | H3: =IF($E3 = 1,ROUND(SUM(recreation_claude_v2_5!I3,recreation_claude_v2_4!I3,recreation_claude_v2_3!I3,recreation_claude_v2_2!I3,recreation_claude_v2_1!I3)/COUNT(recreation_claude_v2_5!I3,recreation_claude_v2_4!I3,recreation_claude_v2_3!I3,recreation_claude_v2_2!I3,recreation_claude_v2_1!I3),0),"NA") -> 1 | I3: =IF($F3 = 1,ROUND(SUM(recreation_claude_v2_5!J3,recreation_claude_v2_4!J3,recreation_claude_v2_3!J3,recreation_claude_v2_2!J3,recreation_claude_v2_1!J3)/COUNT(recreation_claude_v2_5!J3,recreation_claude_v2_4!J3,recreation_claude_v2_3!J3,recreation_claude_v2_2!J3,recreation_claude_v2_1!J3),0),"NA") -> 1 | J3: =IF($E3 = 1,ROUND(SUM(recreation_claude_v2_5!K3,recreation_claude_v2_4!K3,recreation_claude_v2_3!K3,recreation_claude_v2_2!K3,recreation_claude_v2_1!K3)/COUNT(recreation_claude_v2_5!K3,recreation_claude_v2_4!K3,recreation_claude_v2_3!K3,recreation_claude_v2_2!K3,recreation_claude_v2_1!K3),0),"NA") -> 1 | K3: =IF(AND($F3 = 1, $G3 = 1),ROUND(SUM(recreation_claude_v2_5!L3,recreation_claude_v2_4!L3,recreation_claude_v2_3!L3,recreation_claude_v2_2!L3,recreation_claude_v2_1!L3)/COUNT(recreation_claude_v2_5!L3,recreation_claude_v2_4!L3,recreation_claude_v2_3!L3,recreation_claude_v2_2!L3,recreation_claude_v2_1!L3),0),"NA") -> 1 | L3: =IF($E3 = 1,ROUND(SUM(recreation_claude_v2_5!L3,recreation_claude_v2_4!L3,recreation_claude_v2_3!L3,recreation_claude_v2_2!L3,recreation_claude_v2_1!L3)/COUNT(recreation_claude_v2_5!L3,recreation_claude_v2_4!L3,recreation_claude_v2_3!L3,recreation_claude_v2_2!L3,recreation_claude_v2_1!L3),0),"NA") -> 1 | M3: =IF($E3 = 1,ROUND(SUM(recreation_claude_v2_5!M3,recreation_claude_v2_4!M3,recreation_claude_v2_3!M3,recreation_claude_v2_2!M3,recreation_claude_v2_1!M3)/COUNT(recreation_claude_v2_5!M3,recreation_claude_v2_4!M3,recreation_claude_v2_3!M3,recreation_claude_v2_2!M3,recreation_claude_v2_1!M3),0),"NA") -> 1 | N3: =IF($E3 = 1,ROUND(SUM(recreation_claude_v2_5!N3,recreation_claude_v2_4!N3,recreation_claude_v2_3!N3,recreation_claude_v2_2!N3,recreation_claude_v2_1!N3)/COUNT(recreation_claude_v2_5!N3,recreation_claude_v2_4!N3,recreation_claude_v2_3!N3,recreation_claude_v2_2!N3,recreation_claude_v2_1!N3),0),"NA") -> 1 | O3: =IF($E3 = 1,ROUND(SUM(recreation_claude_v2_5!O3,recreation_claude_v2_4!O3,recreation_claude_v2_3!O3,recreation_claude_v2_2!O3,recreation_claude_v2_1!O3)/COUNT(recreation_claude_v2_5!O3,recreation_claude_v2_4!O3,recreation_claude_v2_3!O3,recreation_claude_v2_2!O3,recreation_claude_v2_1!O3),0),"NA") -> 1
A4: TD | B4: Question 3 | C4: 0 | D4: 10.818715 | E4: =ROUND(SUM(recreation_claude_v2_5!E4,recreation_claude_v2_4!E4,recreation_claude_v2_3!E4,recreation_claude_v2_2!E4,recreation_claude_v2_1!E4)/COUNT(recreation_claude_v2_5!E4,recreation_claude_v2_4!E4,recreation_claude_v2_3!E4,recreation_claude_v2_2!E4,recreation_claude_v2_1!E4),0) -> 1 | F4: =IF($E4 = 1,ROUND(SUM(recreation_claude_v2_5!F4,recreation_claude_v2_4!F4,recreation_claude_v2_3!F4,recreation_claude_v2_2!F4,recreation_claude_v2_1!F4)/COUNT(recreation_claude_v2_5!F4,recreation_claude_v2_4!F4,recreation_claude_v2_3!F4,recreation_claude_v2_2!F4,recreation_claude_v2_1!F4),0),"NA") -> 1 | G4: =IF($E4 = 1,ROUND(SUM(recreation_claude_v2_5!G4,recreation_claude_v2_4!G4,recreation_claude_v2_3!G4,recreation_claude_v2_2!G4,recreation_claude_v2_1!G4)/COUNT(recreation_claude_v2_5!G4,recreation_claude_v2_4!G4,recreation_claude_v2_3!G4,recreation_claude_v2_2!G4,recreation_claude_v2_1!G4),0),"NA") -> 1 | H4: =IF($E4 = 1,ROUND(SUM(recreation_claude_v2_5!I4,recreation_claude_v2_4!I4,recreation_claude_v2_3!I4,recreation_claude_v2_2!I4,recreation_claude_v2_1!I4)/COUNT(recreation_claude_v2_5!I4,recreation_claude_v2_4!I4,recreation_claude_v2_3!I4,recreation_claude_v2_2!I4,recreation_claude_v2_1!I4),0),"NA") -> 1 | I4: =IF($F4 = 1,ROUND(SUM(recreation_claude_v2_5!J4,recreation_claude_v2_4!J4,recreation_claude_v2_3!J4,recreation_claude_v2_2!J4,recreation_claude_v2_1!J4)/COUNT(recreation_claude_v2_5!J4,recreation_claude_v2_4!J4,recreation_claude_v2_3!J4,recreation_claude_v2_2!J4,recreation_claude_v2_1!J4),0),"NA") -> 1 | J4: =IF($E4 = 1,ROUND(SUM(recreation_claude_v2_5!K4,recreation_claude_v2_4!K4,recreation_claude_v2_3!K4,recreation_claude_v2_2!K4,recreation_claude_v2_1!K4)/COUNT(recreation_claude_v2_5!K4,recreation_claude_v2_4!K4,recreation_claude_v2_3!K4,recreation_claude_v2_2!K4,recreation_claude_v2_1!K4),0),"NA") -> 1 | K4: =IF(AND($F4 = 1, $G4 = 1),ROUND(SUM(recreation_claude_v2_5!L4,recreation_claude_v2_4!L4,recreation_claude_v2_3!L4,recreation_claude_v2_2!L4,recreation_claude_v2_1!L4)/COUNT(recreation_claude_v2_5!L4,recreation_claude_v2_4!L4,recreation_claude_v2_3!L4,recreation_claude_v2_2!L4,recreation_claude_v2_1!L4),0),"NA") -> 1 | L4: =IF($E4 = 1,ROUND(SUM(recreation_claude_v2_5!L4,recreation_claude_v2_4!L4,recreation_claude_v2_3!L4,recreation_claude_v2_2!L4,recreation_claude_v2_1!L4)/COUNT(recreation_claude_v2_5!L4,recreation_claude_v2_4!L4,recreation_claude_v2_3!L4,recreation_claude_v2_2!L4,recreation_claude_v2_1!L4),0),"NA") -> 1 | M4: =IF($E4 = 1,ROUND(SUM(recreation_claude_v2_5!M4,recreation_claude_v2_4!M4,recreation_claude_v2_3!M4,recreation_claude_v2_2!M4,recreation_claude_v2_1!M4)/COUNT(recreation_claude_v2_5!M4,recreation_claude_v2_4!M4,recreation_claude_v2_3!M4,recreation_claude_v2_2!M4,recreation_claude_v2_1!M4),0),"NA") -> 1 | N4: =IF($E4 = 1,ROUND(SUM(recreation_claude_v2_5!N4,recreation_claude_v2_4!N4,recreation_claude_v2_3!N4,recreation_claude_v2_2!N4,recreation_claude_v2_1!N4)/COUNT(recreation_claude_v2_5!N4,recreation_claude_v2_4!N4,recreation_claude_v2_3!N4,recreation_claude_v2_2!N4,recreation_claude_v2_1!N4),0),"NA") -> 1 | O4: =IF($E4 = 1,ROUND(SUM(recreation_claude_v2_5!O4,recreation_claude_v2_4!O4,recreation_claude_v2_3!O4,recreation_claude_v2_2!O4,recreation_claude_v2_1!O4)/COUNT(recreation_claude_v2_5!O4,recreation_claude_v2_4!O4,recreation_claude_v2_3!O4,recreation_claude_v2_2!O4,recreation_claude_v2_1!O4),0),"NA") -> 1
A5: TD | B5: Question 4 | C5: 0 | D5: 7.6704519 | E5: =ROUND(SUM(recreation_claude_v2_5!E5,recreation_claude_v2_4!E5,recreation_claude_v2_3!E5,recreation_claude_v2_2!E5,recreation_claude_v2_1!E5)/COUNT(recreation_claude_v2_5!E5,recreation_claude_v2_4!E5,recreation_claude_v2_3!E5,recreation_claude_v2_2!E5,recreation_claude_v2_1!E5),0) -> 1 | F5: =IF($E5 = 1,ROUND(SUM(recreation_claude_v2_5!F5,recreation_claude_v2_4!F5,recreation_claude_v2_3!F5,recreation_claude_v2_2!F5,recreation_claude_v2_1!F5)/COUNT(recreation_claude_v2_5!F5,recreation_claude_v2_4!F5,recreation_claude_v2_3!F5,recreation_claude_v2_2!F5,recreation_claude_v2_1!F5),0),"NA") -> 0 | G5: =IF($E5 = 1,ROUND(SUM(recreation_claude_v2_5!G5,recreation_claude_v2_4!G5,recreation_claude_v2_3!G5,recreation_claude_v2_2!G5,recreation_claude_v2_1!G5)/COUNT(recreation_claude_v2_5!G5,recreation_claude_v2_4!G5,recreation_claude_v2_3!G5,recreation_claude_v2_2!G5,recreation_claude_v2_1!G5),0),"NA") -> 1 | H5: =IF($E5 = 1,ROUND(SUM(recreation_claude_v2_5!I5,recreation_claude_v2_4!I5,recreation_claude_v2_3!I5,recreation_claude_v2_2!I5,recreation_claude_v2_1!I5)/COUNT(recreation_claude_v2_5!I5,recreation_claude_v2_4!I5,recreation_claude_v2_3!I5,recreation_claude_v2_2!I5,recreation_claude_v2_1!I5),0),"NA") -> 1 | I5: =IF($F5 = 1,ROUND(SUM(recreation_claude_v2_5!J5,recreation_claude_v2_4!J5,recreation_claude_v2_3!J5,recreation_claude_v2_2!J5,recreation_claude_v2_1!J5)/COUNT(recreation_claude_v2_5!J5,recreation_claude_v2_4!J5,recreation_claude_v2_3!J5,recreation_claude_v2_2!J5,recreation_claude_v2_1!J5),0),"NA") -> NA | J5: =IF($E5 = 1,ROUND(SUM(recreation_claude_v2_5!K5,recreation_claude_v2_4!K5,recreation_claude_v2_3!K5,recreation_claude_v2_2!K5,recreation_claude_v2_1!K5)/COUNT(recreation_claude_v2_5!K5,recreation_claude_v2_4!K5,recreation_claude_v2_3!K5,recreation_claude_v2_2!K5,recreation_claude_v2_1!K5),0),"NA") -> 1 | K5: =IF(AND($F5 = 1, $G5 = 1),ROUND(SUM(recreation_claude_v2_5!L5,recreation_claude_v2_4!L5,recreation_claude_v2_3!L5,recreation_claude_v2_2!L5,recreation_claude_v2_1!L5)/COUNT(recreation_claude_v2_5!L5,recreation_claude_v2_4!L5,recreation_claude_v2_3!L5,recreation_claude_v2_2!L5,recreation_claude_v2_1!L5),0),"NA") -> NA | L5: =IF($E5 = 1,ROUND(SUM(recreation_claude_v2_5!L5,recreation_claude_v2_4!L5,recreation_claude_v2_3!L5,recreation_claude_v2_2!L5,recreation_claude_v2_1!L5)/COUNT(recreation_claude_v2_5!L5,recreation_claude_v2_4!L5,recreation_claude_v2_3!L5,recreation_claude_v2_2!L5,recreation_claude_v2_1!L5),0),"NA") -> 1 | M5: =IF($E5 = 1,ROUND(SUM(recreation_claude_v2_5!M5,recreation_claude_v2_4!M5,recreation_claude_v2_3!M5,recreation_claude_v2_2!M5,recreation_claude_v2_1!M5)/COUNT(recreation_claude_v2_5!M5,recreation_claude_v2_4!M5,recreation_claude_v2_3!M5,recreation_claude_v2_2!M5,recreation_claude_v2_1!M5),0),"NA") -> 1 | N5: =IF($E5 = 1,ROUND(SUM(recreation_claude_v2_5!N5,recreation_claude_v2_4!N5,recreation_claude_v2_3!N5,recreation_claude_v2_2!N5,recreation_claude_v2_1!N5)/COUNT(recreation_claude_v2_5!N5,recreation_claude_v2_4!N5,recreation_claude_v2_3!N5,recreation_claude_v2_2!N5,recreation_claude_v2_1!N5),0),"NA") -> 1 | O5: =IF($E5 = 1,ROUND(SUM(recreation_claude_v2_5!O5,recreation_claude_v2_4!O5,recreation_claude_v2_3!O5,recreation_claude_v2_2!O5,recreation_claude_v2_1!O5)/COUNT(recreation_claude_v2_5!O5,recreation_claude_v2_4!O5,recreation_claude_v2_3!O5,recreation_claude_v2_2!O5,recreation_claude_v2_1!O5),0),"NA") -> 1
A6: TD | B6: Question 5 | C6: 0 | D6: 2.8635883 | E6: =ROUND(SUM(recreation_claude_v2_5!E6,recreation_claude_v2_4!E6,recreation_claude_v2_3!E6,recreation_claude_v2_2!E6,recreation_claude_v2_1!E6)/COUNT(recreation_claude_v2_5!E6,recreation_claude_v2_4!E6,recreation_claude_v2_3!E6,recreation_claude_v2_2!E6,recreation_claude_v2_1!E6),0) -> 1 | F6: =IF($E6 = 1,ROUND(SUM(recreation_claude_v2_5!F6,recreation_claude_v2_4!F6,recreation_claude_v2_3!F6,recreation_claude_v2_2!F6,recreation_claude_v2_1!F6)/COUNT(recreation_claude_v2_5!F6,recreation_claude_v2_4!F6,recreation_claude_v2_3!F6,recreation_claude_v2_2!F6,recreation_claude_v2_1!F6),0),"NA") -> 1 | G6: =IF($E6 = 1,ROUND(SUM(recreation_claude_v2_5!G6,recreation_claude_v2_4!G6,recreation_claude_v2_3!G6,recreation_claude_v2_2!G6,recreation_claude_v2_1!G6)/COUNT(recreation_claude_v2_5!G6,recreation_claude_v2_4!G6,recreation_claude_v2_3!G6,recreation_claude_v2_2!G6,recreation_claude_v2_1!G6),0),"NA") -> 1 | H6: =IF($E6 = 1,ROUND(SUM(recreation_claude_v2_5!I6,recreation_claude_v2_4!I6,recreation_claude_v2_3!I6,recreation_claude_v2_2!I6,recreation_claude_v2_1!I6)/COUNT(recreation_claude_v2_5!I6,recreation_claude_v2_4!I6,recreation_claude_v2_3!I6,recreation_claude_v2_2!I6,recreation_claude_v2_1!I6),0),"NA") -> 1 | I6: =IF($F6 = 1,ROUND(SUM(recreation_claude_v2_5!J6,recreation_claude_v2_4!J6,recreation_claude_v2_3!J6,recreation_claude_v2_2!J6,recreation_claude_v2_1!J6)/COUNT(recreation_claude_v2_5!J6,recreation_claude_v2_4!J6,recreation_claude_v2_3!J6,recreation_claude_v2_2!J6,recreation_claude_v2_1!J6),0),"NA") -> 1 | J6: =IF($E6 = 1,ROUND(SUM(recreation_claude_v2_5!K6,recreation_claude_v2_4!K6,recreation_claude_v2_3!K6,recreation_claude_v2_2!K6,recreation_claude_v2_1!K6)/COUNT(recreation_claude_v2_5!K6,recreation_claude_v2_4!K6,recreation_claude_v2_3!K6,recreation_claude_v2_2!K6,recreation_claude_v2_1!K6),0),"NA") -> 1 | K6: =IF(AND($F6 = 1, $G6 = 1),ROUND(SUM(recreation_claude_v2_5!L6,recreation_claude_v2_4!L6,recreation_claude_v2_3!L6,recreation_claude_v2_2!L6,recreation_claude_v2_1!L6)/COUNT(recreation_claude_v2_5!L6,recreation_claude_v2_4!L6,recreation_claude_v2_3!L6,recreation_claude_v2_2!L6,recreation_claude_v2_1!L6),0),"NA") -> 1 | L6: =IF($E6 = 1,ROUND(SUM(recreation_claude_v2_5!L6,recreation_claude_v2_4!L6,recreation_claude_v2_3!L6,recreation_claude_v2_2!L6,recreation_claude_v2_1!L6)/COUNT(recreation_claude_v2_5!L6,recreation_claude_v2_4!L6,recreation_claude_v2_3!L6,recreation_claude_v2_2!L6,recreation_claude_v2_1!L6),0),"NA") -> 1 | M6: =IF($E6 = 1,ROUND(SUM(recreation_claude_v2_5!M6,recreation_claude_v2_4!M6,recreation_claude_v2_3!M6,recreation_claude_v2_2!M6,recreation_claude_v2_1!M6)/COUNT(recreation_claude_v2_5!M6,recreation_claude_v2_4!M6,recreation_claude_v2_3!M6,recreation_claude_v2_2!M6,recreation_claude_v2_1!M6),0),"NA") -> 1 | N6: =IF($E6 = 1,ROUND(SUM(recreation_claude_v2_5!N6,recreation_claude_v2_4!N6,recreation_claude_v2_3!N6,recreation_claude_v2_2!N6,recreation_claude_v2_1!N6)/COUNT(recreation_claude_v2_5!N6,recreation_claude_v2_4!N6,recreation_claude_v2_3!N6,recreation_claude_v2_2!N6,recreation_claude_v2_1!N6),0),"NA") -> 1 | O6: =IF($E6 = 1,ROUND(SUM(recreation_claude_v2_5!O6,recreation_claude_v2_4!O6,recreation_claude_v2_3!O6,recreation_claude_v2_2!O6,recreation_claude_v2_1!O6)/COUNT(recreation_claude_v2_5!O6,recreation_claude_v2_4!O6,recreation_claude_v2_3!O6,recreation_claude_v2_2!O6,recreation_claude_v2_1!O6),0),"NA") -> 1
A7: TD | B7: Question 6 | C7: 0 | D7: 3.2042382 | E7: =ROUND(SUM(recreation_claude_v2_5!E7,recreation_claude_v2_4!E7,recreation_claude_v2_3!E7,recreation_claude_v2_2!E7,recreation_claude_v2_1!E7)/COUNT(recreation_claude_v2_5!E7,recreation_claude_v2_4!E7,recreation_claude_v2_3!E7,recreation_claude_v2_2!E7,recreation_claude_v2_1!E7),0) -> 1 | F7: =IF($E7 = 1,ROUND(SUM(recreation_claude_v2_5!F7,recreation_claude_v2_4!F7,recreation_claude_v2_3!F7,recreation_claude_v2_2!F7,recreation_claude_v2_1!F7)/COUNT(recreation_claude_v2_5!F7,recreation_claude_v2_4!F7,recreation_claude_v2_3!F7,recreation_claude_v2_2!F7,recreation_claude_v2_1!F7),0),"NA") -> 1 | G7: =IF($E7 = 1,ROUND(SUM(recreation_claude_v2_5!G7,recreation_claude_v2_4!G7,recreation_claude_v2_3!G7,recreation_claude_v2_2!G7,recreation_claude_v2_1!G7)/COUNT(recreation_claude_v2_5!G7,recreation_claude_v2_4!G7,recreation_claude_v2_3!G7,recreation_claude_v2_2!G7,recreation_claude_v2_1!G7),0),"NA") -> 1 | H7: =IF($E7 = 1,ROUND(SUM(recreation_claude_v2_5!I7,recreation_claude_v2_4!I7,recreation_claude_v2_3!I7,recreation_claude_v2_2!I7,recreation_claude_v2_1!I7)/COUNT(recreation_claude_v2_5!I7,recreation_claude_v2_4!I7,recreation_claude_v2_3!I7,recreation_claude_v2_2!I7,recreation_claude_v2_1!I7),0),"NA") -> 1 | I7: =IF($F7 = 1,ROUND(SUM(recreation_claude_v2_5!J7,recreation_claude_v2_4!J7,recreation_claude_v2_3!J7,recreation_claude_v2_2!J7,recreation_claude_v2_1!J7)/COUNT(recreation_claude_v2_5!J7,recreation_claude_v2_4!J7,recreation_claude_v2_3!J7,recreation_claude_v2_2!J7,recreation_claude_v2_1!J7),0),"NA") -> 1 | J7: =IF($E7 = 1,ROUND(SUM(recreation_claude_v2_5!K7,recreation_claude_v2_4!K7,recreation_claude_v2_3!K7,recreation_claude_v2_2!K7,recreation_claude_v2_1!K7)/COUNT(recreation_claude_v2_5!K7,recreation_claude_v2_4!K7,recreation_claude_v2_3!K7,recreation_claude_v2_2!K7,recreation_claude_v2_1!K7),0),"NA") -> 1 | K7: =IF(AND($F7 = 1, $G7 = 1),ROUND(SUM(recreation_claude_v2_5!L7,recreation_claude_v2_4!L7,recreation_claude_v2_3!L7,recreation_claude_v2_2!L7,recreation_claude_v2_1!L7)/COUNT(recreation_claude_v2_5!L7,recreation_claude_v2_4!L7,recreation_claude_v2_3!L7,recreation_claude_v2_2!L7,recreation_claude_v2_1!L7),0),"NA") -> 1 | L7: =IF($E7 = 1,ROUND(SUM(recreation_claude_v2_5!L7,recreation_claude_v2_4!L7,recreation_claude_v2_3!L7,recreation_claude_v2_2!L7,recreation_claude_v2_1!L7)/COUNT(recreation_claude_v2_5!L7,recreation_claude_v2_4!L7,recreation_claude_v2_3!L7,recreation_claude_v2_2!L7,recreation_claude_v2_1!L7),0),"NA") -> 1 | M7: =IF($E7 = 1,ROUND(SUM(recreation_claude_v2_5!M7,recreation_claude_v2_4!M7,recreation_claude_v2_3!M7,recreation_claude_v2_2!M7,recreation_claude_v2_1!M7)/COUNT(recreation_claude_v2_5!M7,recreation_claude_v2_4!M7,recreation_claude_v2_3!M7,recreation_claude_v2_2!M7,recreation_claude_v2_1!M7),0),"NA") -> 1 | N7: =IF($E7 = 1,ROUND(SUM(recreation_claude_v2_5!N7,recreation_claude_v2_4!N7,recreation_claude_v2_3!N7,recreation_claude_v2_2!N7,recreation_claude_v2_1!N7)/COUNT(recreation_claude_v2_5!N7,recreation_claude_v2_4!N7,recreation_claude_v2_3!N7,recreation_claude_v2_2!N7,recreation_claude_v2_1!N7),0),"NA") -> 1 | O7: =IF($E7 = 1,ROUND(SUM(recreation_claude_v2_5!O7,recreation_claude_v2_4!O7,recreation_claude_v2_3!O7,recreation_claude_v2_2!O7,recreation_claude_v2_1!O7)/COUNT(recreation_claude_v2_5!O7,recreation_claude_v2_4!O7,recreation_claude_v2_3!O7,recreation_claude_v2_2!O7,recreation_claude_v2_1!O7),0),"NA") -> 1
A8: TD | B8: Question 7 | C8: 0 | D8: 10.661453 | E8: =ROUND(SUM(recreation_claude_v2_5!E8,recreation_claude_v2_4!E8,recreation_claude_v2_3!E8,recreation_claude_v2_2!E8,recreation_claude_v2_1!E8)/COUNT(recreation_claude_v2_5!E8,recreation_claude_v2_4!E8,recreation_claude_v2_3!E8,recreation_claude_v2_2!E8,recreation_claude_v2_1!E8),0) -> 1 | F8: =IF($E8 = 1,ROUND(SUM(recreation_claude_v2_5!F8,recreation_claude_v2_4!F8,recreation_claude_v2_3!F8,recreation_claude_v2_2!F8,recreation_claude_v2_1!F8)/COUNT(recreation_claude_v2_5!F8,recreation_claude_v2_4!F8,recreation_claude_v2_3!F8,recreation_claude_v2_2!F8,recreation_claude_v2_1!F8),0),"NA") -> 1 | G8: =IF($E8 = 1,ROUND(SUM(recreation_claude_v2_5!G8,recreation_claude_v2_4!G8,recreation_claude_v2_3!G8,recreation_claude_v2_2!G8,recreation_claude_v2_1!G8)/COUNT(recreation_claude_v2_5!G8,recreation_claude_v2_4!G8,recreation_claude_v2_3!G8,recreation_claude_v2_2!G8,recreation_claude_v2_1!G8),0),"NA") -> 1 | H8: =IF($E8 = 1,ROUND(SUM(recreation_claude_v2_5!I8,recreation_claude_v2_4!I8,recreation_claude_v2_3!I8,recreation_claude_v2_2!I8,recreation_claude_v2_1!I8)/COUNT(recreation_claude_v2_5!I8,recreation_claude_v2_4!I8,recreation_claude_v2_3!I8,recreation_claude_v2_2!I8,recreation_claude_v2_1!I8),0),"NA") -> 1 | I8: =IF($F8 = 1,ROUND(SUM(recreation_claude_v2_5!J8,recreation_claude_v2_4!J8,recreation_claude_v2_3!J8,recreation_claude_v2_2!J8,recreation_claude_v2_1!J8)/COUNT(recreation_claude_v2_5!J8,recreation_claude_v2_4!J8,recreation_claude_v2_3!J8,recreation_claude_v2_2!J8,recreation_claude_v2_1!J8),0),"NA") -> 1 | J8: =IF($E8 = 1,ROUND(SUM(recreation_claude_v2_5!K8,recreation_claude_v2_4!K8,recreation_claude_v2_3!K8,recreation_claude_v2_2!K8,recreation_claude_v2_1!K8)/COUNT(recreation_claude_v2_5!K8,recreation_claude_v2_4!K8,recreation_claude_v2_3!K8,recreation_claude_v2_2!K8,recreation_claude_v2_1!K8),0),"NA") -> 1 | K8: =IF(AND($F8 = 1, $G8 = 1),ROUND(SUM(recreation_claude_v2_5!L8,recreation_claude_v2_4!L8,recreation_claude_v2_3!L8,recreation_claude_v2_2!L8,recreation_claude_v2_1!L8)/COUNT(recreation_claude_v2_5!L8,recreation_claude_v2_4!L8,recreation_claude_v2_3!L8,recreation_claude_v2_2!L8,recreation_claude_v2_1!L8),0),"NA") -> 1 | L8: =IF($E8 = 1,ROUND(SUM(recreation_claude_v2_5!L8,recreation_claude_v2_4!L8,recreation_claude_v2_3!L8,recreation_claude_v2_2!L8,recreation_claude_v2_1!L8)/COUNT(recreation_claude_v2_5!L8,recreation_claude_v2_4!L8,recreation_claude_v2_3!L8,recreation_claude_v2_2!L8,recreation_claude_v2_1!L8),0),"NA") -> 1 | M8: =IF($E8 = 1,ROUND(SUM(recreation_claude_v2_5!M8,recreation_claude_v2_4!M8,recreation_claude_v2_3!M8,recreation_claude_v2_2!M8,recreation_claude_v2_1!M8)/COUNT(recreation_claude_v2_5!M8,recreation_claude_v2_4!M8,recreation_claude_v2_3!M8,recreation_claude_v2_2!M8,recreation_claude_v2_1!M8),0),"NA") -> 1 | N8: =IF($E8 = 1,ROUND(SUM(recreation_claude_v2_5!N8,recreation_claude_v2_4!N8,recreation_claude_v2_3!N8,recreation_claude_v2_2!N8,recreation_claude_v2_1!N8)/COUNT(recreation_claude_v2_5!N8,recreation_claude_v2_4!N8,recreation_claude_v2_3!N8,recreation_claude_v2_2!N8,recreation_claude_v2_1!N8),0),"NA") -> 1 | O8: =IF($E8 = 1,ROUND(SUM(recreation_claude_v2_5!O8,recreation_claude_v2_4!O8,recreation_claude_v2_3!O8,recreation_claude_v2_2!O8,recreation_claude_v2_1!O8)/COUNT(recreation_claude_v2_5!O8,recreation_claude_v2_4!O8,recreation_claude_v2_3!O8,recreation_claude_v2_2!O8,recreation_claude_v2_1!O8),0),"NA") -> 1
A9: TD | B9: Question 8 | C9: 0 | D9: 8.7032056 | E9: =ROUND(SUM(recreation_claude_v2_5!E9,recreation_claude_v2_4!E9,recreation_claude_v2_3!E9,recreation_claude_v2_2!E9,recreation_claude_v2_1!E9)/COUNT(recreation_claude_v2_5!E9,recreation_claude_v2_4!E9,recreation_claude_v2_3!E9,recreation_claude_v2_2!E9,recreation_claude_v2_1!E9),0) -> 1 | F9: =IF($E9 = 1,ROUND(SUM(recreation_claude_v2_5!F9,recreation_claude_v2_4!F9,recreation_claude_v2_3!F9,recreation_claude_v2_2!F9,recreation_claude_v2_1!F9)/COUNT(recreation_claude_v2_5!F9,recreation_claude_v2_4!F9,recreation_claude_v2_3!F9,recreation_claude_v2_2!F9,recreation_claude_v2_1!F9),0),"NA") -> 1 | G9: =IF($E9 = 1,ROUND(SUM(recreation_claude_v2_5!G9,recreation_claude_v2_4!G9,recreation_claude_v2_3!G9,recreation_claude_v2_2!G9,recreation_claude_v2_1!G9)/COUNT(recreation_claude_v2_5!G9,recreation_claude_v2_4!G9,recreation_claude_v2_3!G9,recreation_claude_v2_2!G9,recreation_claude_v2_1!G9),0),"NA") -> 1 | H9: =IF($E9 = 1,ROUND(SUM(recreation_claude_v2_5!I9,recreation_claude_v2_4!I9,recreation_claude_v2_3!I9,recreation_claude_v2_2!I9,recreation_claude_v2_1!I9)/COUNT(recreation_claude_v2_5!I9,recreation_claude_v2_4!I9,recreation_claude_v2_3!I9,recreation_claude_v2_2!I9,recreation_claude_v2_1!I9),0),"NA") -> 1 | I9: =IF($F9 = 1,ROUND(SUM(recreation_claude_v2_5!J9,recreation_claude_v2_4!J9,recreation_claude_v2_3!J9,recreation_claude_v2_2!J9,recreation_claude_v2_1!J9)/COUNT(recreation_claude_v2_5!J9,recreation_claude_v2_4!J9,recreation_claude_v2_3!J9,recreation_claude_v2_2!J9,recreation_claude_v2_1!J9),0),"NA") -> 1 | J9: =IF($E9 = 1,ROUND(SUM(recreation_claude_v2_5!K9,recreation_claude_v2_4!K9,recreation_claude_v2_3!K9,recreation_claude_v2_2!K9,recreation_claude_v2_1!K9)/COUNT(recreation_claude_v2_5!K9,recreation_claude_v2_4!K9,recreation_claude_v2_3!K9,recreation_claude_v2_2!K9,recreation_claude_v2_1!K9),0),"NA") -> 1 | K9: =IF(AND($F9 = 1, $G9 = 1),ROUND(SUM(recreation_claude_v2_5!L9,recreation_claude_v2_4!L9,recreation_claude_v2_3!L9,recreation_claude_v2_2!L9,recreation_claude_v2_1!L9)/COUNT(recreation_claude_v2_5!L9,recreation_claude_v2_4!L9,recreation_claude_v2_3!L9,recreation_claude_v2_2!L9,recreation_claude_v2_1!L9),0),"NA") -> 1 | L9: =IF($E9 = 1,ROUND(SUM(recreation_claude_v2_5!L9,recreation_claude_v2_4!L9,recreation_claude_v2_3!L9,recreation_claude_v2_2!L9,recreation_claude_v2_1!L9)/COUNT(recreation_claude_v2_5!L9,recreation_claude_v2_4!L9,recreation_claude_v2_3!L9,recreation_claude_v2_2!L9,recreation_claude_v2_1!L9),0),"NA") -> 1 | M9: =IF($E9 = 1,ROUND(SUM(recreation_claude_v2_5!M9,recreation_claude_v2_4!M9,recreation_claude_v2_3!M9,recreation_claude_v2_2!M9,recreation_claude_v2_1!M9)/COUNT(recreation_claude_v2_5!M9,recreation_claude_v2_4!M9,recreation_claude_v2_3!M9,recreation_claude_v2_2!M9,recreation_claude_v2_1!M9),0),"NA") -> 1 | N9: =IF($E9 = 1,ROUND(SUM(recreation_claude_v2_5!N9,recreation_claude_v2_4!N9,recreation_claude_v2_3!N9,recreation_claude_v2_2!N9,recreation_claude_v2_1!N9)/COUNT(recreation_claude_v2_5!N9,recreation_claude_v2_4!N9,recreation_claude_v2_3!N9,recreation_claude_v2_2!N9,recreation_claude_v2_1!N9),0),"NA") -> 1 | O9: =IF($E9 = 1,ROUND(SUM(recreation_claude_v2_5!O9,recreation_claude_v2_4!O9,recreation_claude_v2_3!O9,recreation_claude_v2_2!O9,recreation_claude_v2_1!O9)/COUNT(recreation_claude_v2_5!O9,recreation_claude_v2_4!O9,recreation_claude_v2_3!O9,recreation_claude_v2_2!O9,recreation_claude_v2_1!O9),0),"NA") -> 1
A10: TD | B10: Question 9 | C10: 0 | D10: 2.9548335 | E10: =ROUND(SUM(recreation_claude_v2_5!E10,recreation_claude_v2_4!E10,recreation_claude_v2_3!E10,recreation_claude_v2_2!E10,recreation_claude_v2_1!E10)/COUNT(recreation_claude_v2_5!E10,recreation_claude_v2_4!E10,recreation_claude_v2_3!E10,recreation_claude_v2_2!E10,recreation_claude_v2_1!E10),0) -> 1 | F10: =IF($E10 = 1,ROUND(SUM(recreation_claude_v2_5!F10,recreation_claude_v2_4!F10,recreation_claude_v2_3!F10,recreation_claude_v2_2!F10,recreation_claude_v2_1!F10)/COUNT(recreation_claude_v2_5!F10,recreation_claude_v2_4!F10,recreation_claude_v2_3!F10,recreation_claude_v2_2!F10,recreation_claude_v2_1!F10),0),"NA") -> 1 | G10: =IF($E10 = 1,ROUND(SUM(recreation_claude_v2_5!G10,recreation_claude_v2_4!G10,recreation_claude_v2_3!G10,recreation_claude_v2_2!G10,recreation_claude_v2_1!G10)/COUNT(recreation_claude_v2_5!G10,recreation_claude_v2_4!G10,recreation_claude_v2_3!G10,recreation_claude_v2_2!G10,recreation_claude_v2_1!G10),0),"NA") -> 1 | H10: =IF($E10 = 1,ROUND(SUM(recreation_claude_v2_5!I10,recreation_claude_v2_4!I10,recreation_claude_v2_3!I10,recreation_claude_v2_2!I10,recreation_claude_v2_1!I10)/COUNT(recreation_claude_v2_5!I10,recreation_claude_v2_4!I10,recreation_claude_v2_3!I10,recreation_claude_v2_2!I10,recreation_claude_v2_1!I10),0),"NA") -> 1 | I10: =IF($F10 = 1,ROUND(SUM(recreation_claude_v2_5!J10,recreation_claude_v2_4!J10,recreation_claude_v2_3!J10,recreation_claude_v2_2!J10,recreation_claude_v2_1!J10)/COUNT(recreation_claude_v2_5!J10,recreation_claude_v2_4!J10,recreation_claude_v2_3!J10,recreation_claude_v2_2!J10,recreation_claude_v2_1!J10),0),"NA") -> 1 | J10: =IF($E10 = 1,ROUND(SUM(recreation_claude_v2_5!K10,recreation_claude_v2_4!K10,recreation_claude_v2_3!K10,recreation_claude_v2_2!K10,recreation_claude_v2_1!K10)/COUNT(recreation_claude_v2_5!K10,recreation_claude_v2_4!K10,recreation_claude_v2_3!K10,recreation_claude_v2_2!K10,recreation_claude_v2_1!K10),0),"NA") -> 1 | K10: =IF(AND($F10 = 1, $G10 = 1),ROUND(SUM(recreation_claude_v2_5!L10,recreation_claude_v2_4!L10,recreation_claude_v2_3!L10,recreation_claude_v2_2!L10,recreation_claude_v2_1!L10)/COUNT(recreation_claude_v2_5!L10,recreation_claude_v2_4!L10,recreation_claude_v2_3!L10,recreation_claude_v2_2!L10,recreation_claude_v2_1!L10),0),"NA") -> 1 | L10: =IF($E10 = 1,ROUND(SUM(recreation_claude_v2_5!L10,recreation_claude_v2_4!L10,recreation_claude_v2_3!L10,recreation_claude_v2_2!L10,recreation_claude_v2_1!L10)/COUNT(recreation_claude_v2_5!L10,recreation_claude_v2_4!L10,recreation_claude_v2_3!L10,recreation_claude_v2_2!L10,recreation_claude_v2_1!L10),0),"NA") -> 1 | M10: =IF($E10 = 1,ROUND(SUM(recreation_claude_v2_5!M10,recreation_claude_v2_4!M10,recreation_claude_v2_3!M10,recreation_claude_v2_2!M10,recreation_claude_v2_1!M10)/COUNT(recreation_claude_v2_5!M10,recreation_claude_v2_4!M10,recreation_claude_v2_3!M10,recreation_claude_v2_2!M10,recreation_claude_v2_1!M10),0),"NA") -> 1 | N10: =IF($E10 = 1,ROUND(SUM(recreation_claude_v2_5!N10,recreation_claude_v2_4!N10,recreation_claude_v2_3!N10,recreation_claude_v2_2!N10,recreation_claude_v2_1!N10)/COUNT(recreation_claude_v2_5!N10,recreation_claude_v2_4!N10,recreation_claude_v2_3!N10,recreation_claude_v2_2!N10,recreation_claude_v2_1!N10),0),"NA") -> 1 | O10: =IF($E10 = 1,ROUND(SUM(recreation_claude_v2_5!O10,recreation_claude_v2_4!O10,recreation_claude_v2_3!O10,recreation_claude_v2_2!O10,recreation_claude_v2_1!O10)/COUNT(recreation_claude_v2_5!O10,recreation_claude_v2_4!O10,recreation_claude_v2_3!O10,recreation_claude_v2_2!O10,recreation_claude_v2_1!O10),0),"NA") -> 1
A11: TD | B11: Question 10 | C11: 0 | D11: 9.9386742 | E11: =ROUND(SUM(recreation_claude_v2_5!E11,recreation_claude_v2_4!E11,recreation_claude_v2_3!E11,recreation_claude_v2_2!E11,recreation_claude_v2_1!E11)/COUNT(recreation_claude_v2_5!E11,recreation_claude_v2_4!E11,recreation_claude_v2_3!E11,recreation_claude_v2_2!E11,recreation_claude_v2_1!E11),0) -> 1 | F11: =IF($E11 = 1,ROUND(SUM(recreation_claude_v2_5!F11,recreation_claude_v2_4!F11,recreation_claude_v2_3!F11,recreation_claude_v2_2!F11,recreation_claude_v2_1!F11)/COUNT(recreation_claude_v2_5!F11,recreation_claude_v2_4!F11,recreation_claude_v2_3!F11,recreation_claude_v2_2!F11,recreation_claude_v2_1!F11),0),"NA") -> 1 | G11: =IF($E11 = 1,ROUND(SUM(recreation_claude_v2_5!G11,recreation_claude_v2_4!G11,recreation_claude_v2_3!G11,recreation_claude_v2_2!G11,recreation_claude_v2_1!G11)/COUNT(recreation_claude_v2_5!G11,recreation_claude_v2_4!G11,recreation_claude_v2_3!G11,recreation_claude_v2_2!G11,recreation_claude_v2_1!G11),0),"NA") -> 1 | H11: =IF($E11 = 1,ROUND(SUM(recreation_claude_v2_5!I11,recreation_claude_v2_4!I11,recreation_claude_v2_3!I11,recreation_claude_v2_2!I11,recreation_claude_v2_1!I11)/COUNT(recreation_claude_v2_5!I11,recreation_claude_v2_4!I11,recreation_claude_v2_3!I11,recreation_claude_v2_2!I11,recreation_claude_v2_1!I11),0),"NA") -> 1 | I11: =IF($F11 = 1,ROUND(SUM(recreation_claude_v2_5!J11,recreation_claude_v2_4!J11,recreation_claude_v2_3!J11,recreation_claude_v2_2!J11,recreation_claude_v2_1!J11)/COUNT(recreation_claude_v2_5!J11,recreation_claude_v2_4!J11,recreation_claude_v2_3!J11,recreation_claude_v2_2!J11,recreation_claude_v2_1!J11),0),"NA") -> 1 | J11: =IF($E11 = 1,ROUND(SUM(recreation_claude_v2_5!K11,recreation_claude_v2_4!K11,recreation_claude_v2_3!K11,recreation_claude_v2_2!K11,recreation_claude_v2_1!K11)/COUNT(recreation_claude_v2_5!K11,recreation_claude_v2_4!K11,recreation_claude_v2_3!K11,recreation_claude_v2_2!K11,recreation_claude_v2_1!K11),0),"NA") -> 1 | K11: =IF(AND($F11 = 1, $G11 = 1),ROUND(SUM(recreation_claude_v2_5!L11,recreation_claude_v2_4!L11,recreation_claude_v2_3!L11,recreation_claude_v2_2!L11,recreation_claude_v2_1!L11)/COUNT(recreation_claude_v2_5!L11,recreation_claude_v2_4!L11,recreation_claude_v2_3!L11,recreation_claude_v2_2!L11,recreation_claude_v2_1!L11),0),"NA") -> 1 | L11: =IF($E11 = 1,ROUND(SUM(recreation_claude_v2_5!L11,recreation_claude_v2_4!L11,recreation_claude_v2_3!L11,recreation_claude_v2_2!L11,recreation_claude_v2_1!L11)/COUNT(recreation_claude_v2_5!L11,recreation_claude_v2_4!L11,recreation_claude_v2_3!L11,recreation_claude_v2_2!L11,recreation_claude_v2_1!L11),0),"NA") -> 1 | M11: =IF($E11 = 1,ROUND(SUM(recreation_claude_v2_5!M11,recreation_claude_v2_4!M11,recreation_claude_v2_3!M11,recreation_claude_v2_2!M11,recreation_claude_v2_1!M11)/COUNT(recreation_claude_v2_5!M11,recreation_claude_v2_4!M11,recreation_claude_v2_3!M11,recreation_claude_v2_2!M11,recreation_claude_v2_1!M11),0),"NA") -> 1 | N11: =IF($E11 = 1,ROUND(SUM(recreation_claude_v2_5!N11,recreation_claude_v2_4!N11,recreation_claude_v2_3!N11,recreation_claude_v2_2!N11,recreation_claude_v2_1!N11)/COUNT(recreation_claude_v2_5!N11,recreation_claude_v2_4!N11,recreation_claude_v2_3!N11,recreation_claude_v2_2!N11,recreation_claude_v2_1!N11),0),"NA") -> 1 | O11: =IF($E11 = 1,ROUND(SUM(recreation_claude_v2_5!O11,recreation_claude_v2_4!O11,recreation_claude_v2_3!O11,recreation_claude_v2_2!O11,recreation_claude_v2_1!O11)/COUNT(recreation_claude_v2_5!O11,recreation_claude_v2_4!O11,recreation_claude_v2_3!O11,recreation_claude_v2_2!O11,recreation_claude_v2_1!O11),0),"NA") -> 1
