Workbook

Sheet services_v8_v1_split_1
A1: Evaluator | B1: Question | C1: status | D1: answerability | E1: primary_kc_alignment | F1: secondary_kc_alignment | G1: topic_alignment | H1: grade_alignment | I1: real_world_feasibility | J1: synergy | K1: clarity | L1: conciseness_and_relevance | M1: language_quality | N1: content_appropriateness | O1: explanation | P1: response_time | Q1: language_quality1
A2: TD | B2: Question 1 | C2: 0 | D2: 1 | E2: 1 | F2: 1 | G2: 1 | H2: 1 | I2: 1 | J2: 1 | K2: 1 | L2: 1 | M2: 1 | N2: 1 | P2: 1.7294452
A3: TD | B3: Question 2 | C3: 0 | D3: 1 | E3: 1 | F3: 1 | G3: 1 | H3: 1 | I3: 1 | J3: 1 | K3: 1 | L3: 1 | M3: 1 | N3: 1 | P3: 1.1833944
A4: TD | B4: Question 3 | C4: 0 | D4: 1 | E4: 1 | F4: 1 | G4: 1 | H4: 1 | I4: 1 | J4: 1 | K4: 1 | L4: 1 | M4: 1 | N4: 1 | P4: 1.6417899
A5: TD | B5: Question 4 | C5: 0 | D5: 1 | E5: 1 | F5: 1 | G5: 1 | H5: 1 | I5: 1 | J5: 1 | K5: 1 | L5: 1 | M5: 1 | N5: 1 | P5: 1.3574936
A6: TD | B6: Question 5 | C6: 0 | D6: 1 | E6: 1 | F6: 1 | G6: 1 | H6: 1 | I6: 1 | J6: 1 | K6: 1 | L6: 1 | M6: 1 | N6: 1 | P6: 1.5421603
A7: TD | B7: Question 6 | C7: 0 | D7: 1 | E7: 1 | F7: 1 | G7: 1 | H7: 1 | I7: 1 | J7: 1 | K7: 1 | L7: 1 | M7: 1 | N7: 1 | P7: 1.0707474
A8: TD | B8: Question 7 | C8: 0 | D8: 1 | E8: 1 | F8: 1 | G8: 1 | H8: 1 | I8: 1 | J8: 1 | K8: 1 | L8: 1 | M8: 1 | N8: 1 | P8: 1.1521637
A9: TD | B9: Question 8 | C9: 0 | D9: 1 | E9: 1 | F9: 1 | G9: 1 | H9: 1 | I9: 1 | J9: 1 | K9: 1 | L9: 1 | M9: 1 | N9: 1 | P9: 1.2082791
A10: TD | B10: Question 9 | C10: 0 | D10: 1 | E10: 1 | F10: 1 | G10: 1 | H10: 1 | I10: 1 | J10: 1 | K10: 1 | L10: 1 | M10: 1 | N10: 1 | P10: 1.5106106
A11: TD | B11: Question 10 | C11: 0 | D11: 1 | E11: 1 | F11: 1 | G11: 1 | H11: 1 | I11: 1 | J11: 1 | K11: 1 | L11: 1 | M11: 1 | N11: 1 | P11: 1.0836513
A12: TD | B12: Question 11 | C12: 0 | D12: 1 | E12: 1 | F12: 1 | G12: 1 | H12: 1 | I12: 1 | J12: 1 | K12: 1 | L12: 1 | M12: 1 | N12: 1 | P12: 1.161694
A13: TD | B13: Question 12 | C13: 0 | D13: 1 | E13: 0 | F13: 1 | G13: 1 | H13: 'NA | I13: 1 | J13: 'NA | K13: 1 | L13: 1 | M13: 1 | N13: 1 | O13: primary_kc_alignment: The problem asks for a comparison (ratio/fraction) between two amounts, not for subtracting unlike fractions as required by the primary KC. synergy: Solving the problem does not require both subtracting unlike fractions and simplifying a fraction; only simplification is necessary. | P13: 15.936013
A14: TD | B14: Question 13 | C14: 0 | D14: 1 | E14: 1 | F14: 1 | G14: 1 | H14: 1 | I14: 1 | J14: 1 | K14: 1 | L14: 1 | M14: 1 | N14: 1 | P14: 1.2003603
A15: TD | B15: Question 14 | C15: 0 | D15: 1 | E15: 1 | F15: 1 | G15: 1 | H15: 1 | I15: 1 | J15: 1 | K15: 1 | L15: 1 | M15: 1 | N15: 1 | P15: 1.106673
A16: TD | B16: Question 15 | C16: 0 | D16: 1 | E16: 1 | F16: 1 | G16: 1 | H16: 1 | I16: 1 | J16: 1 | K16: 1 | L16: 1 | M16: 1 | N16: 1 | P16: 1.5923073
A17: TD | B17: Question 16 | C17: 0 | D17: 1 | E17: 1 | F17: 1 | G17: 1 | H17: 1 | I17: 1 | J17: 1 | K17: 1 | L17: 1 | M17: 1 | N17: 1 | P17: 1.1827509
A18: TD | B18: Question 17 | C18: 0 | D18: 1 | E18: 1 | F18: 1 | G18: 1 | H18: 1 | I18: 1 | J18: 1 | K18: 1 | L18: 1 | M18: 1 | N18: 1 | P18: 1.7943628
A19: TD | B19: Question 18 | C19: 0 | D19: 1 | E19: 0 | F19: 1 | G19: 1 | H19: 'NA | I19: 1 | J19: 'NA | K19: 1 | L19: 1 | M19: 1 | N19: 1 | O19: Primary KC: The question requires dividing $38.75 by 5 for (a), but the quotient is $7.75, which involves dividing a decimal with two decimal places by a 1-digit number. However, part (b) compares a 3-decimal place number ($9.725) with a 2-decimal place number ($7.75), and while comparison/alignment works, using $9.725 as a price per room is unrealistic for Singapore currency and exceeds the P4 syllabus, which only expects students to work with decimals up to 2 decimal places. Grade Alignment: The use of $9.725 is outside the Primary 4 MOE curriculum, which restricts decimal work to 2 d.p. for both calculation and comparison, making it unsuitable for P4 students. | P19: 4.4835992
A20: TD | B20: Question 19 | C20: 0 | D20: 1 | E20: 1 | F20: 1 | G20: 1 | H20: 1 | I20: 1 | J20: 1 | K20: 1 | L20: 1 | M20: 1 | N20: 1 | P20: 1.556649
A21: TD | B21: Question 20 | C21: 0 | D21: 1 | E21: 1 | F21: 1 | G21: 1 | H21: 1 | I21: 1 | J21: 1 | K21: 1 | L21: 1 | M21: 1 | N21: 1 | P21: 1.3002613
A22: TD | B22: Question 21 | C22: 0 | D22: 1 | E22: 1 | F22: 1 | G22: 1 | H22: 1 | I22: 1 | J22: 0 | K22: 1 | L22: 1 | M22: 1 | N22: 1 | O22: 7. The two parts of the word problem ((a) subtraction, (b) comparison/ordering) are independent and do not require results to be used across parts. Each part can be solved separately, so there is no synergy between the knowledge components. | P22: 3.5205433
A23: TD | B23: Question 22 | C23: 0 | D23: 1 | E23: 1 | F23: 0 | G23: 1 | H23: 1 | I23: 1 | J23: 'NA | K23: 1 | L23: 1 | M23: 1 | N23: 1 | O23: 3. The secondary KC specified is 'FRACTIONS | Comparison and ordering | comparing and ordering fractions', but the comparison in part (b) is between a whole number and a fraction of that whole number, not between two fractions or ordering of multiple fractions. 7. The two parts of the question do not require the combined use of both Primary and Secondary KCs to solve. Part (a) is just multiplying a fraction by a whole, and part (b) simply repeats the calculation and subtracts absolute numbers, not using comparison/ordering of fractions. | P23: 2.4759388
A24: TD | B24: Question 23 | C24: 0 | D24: 1 | E24: 1 | F24: 1 | G24: 1 | H24: 1 | I24: 1 | J24: 1 | K24: 1 | L24: 1 | M24: 1 | N24: 1 | P24: 1.366713
A25: TD | B25: Question 24 | C25: 0 | D25: 1 | E25: 1 | F25: 1 | G25: 1 | H25: 1 | I25: 1 | J25: 1 | K25: 1 | L25: 1 | M25: 1 | N25: 1 | P25: 1.2464883
A26: TD | B26: Question 25 | C26: 0 | D26: 1 | E26: 1 | F26: 1 | G26: 1 | H26: 1 | I26: 1 | J26: 1 | K26: 1 | L26: 1 | M26: 1 | N26: 1 | P26: 1.8140666
A27: TD | B27: Question 26 | C27: 0 | D27: 1 | E27: 0 | F27: 1 | G27: 1 | H27: 'NA | I27: 1 | J27: 'NA | K27: 1 | L27: 1 | M27: 1 | N27: 1 | O27: Primary KC Alignment (0): The word problem requires multiplying an improper fraction ($[FORMULA]$) by a whole number (3), which does not involve multiplying two improper fractions as specified by the intended primary knowledge component. It only requires the multiplication of a fraction by a whole number, which is a different—and simpler—skill. | P27: 3.2918026
A28: TD | B28: Question 27 | C28: 0 | D28: 1 | E28: 1 | F28: 1 | G28: 1 | H28: 1 | I28: 1 | J28: 1 | K28: 1 | L28: 1 | M28: 1 | N28: 1 | P28: 1.4767232
A29: TD | B29: Question 28 | C29: 0 | D29: 1 | E29: 1 | F29: 1 | G29: 1 | H29: 1 | I29: 1 | J29: 1 | K29: 1 | L29: 1 | M29: 1 | N29: 1 | P29: 1.3438215
A30: TD | B30: Question 29 | C30: 0 | D30: 1 | E30: 1 | F30: 1 | G30: 1 | H30: 1 | I30: 1 | J30: 1 | K30: 1 | L30: 1 | M30: 1 | N30: 1 | P30: 1.795882
A31: TD | B31: Question 30 | C31: 0 | D31: 1 | E31: 0 | F31: 1 | G31: 1 | H31: 'NA | I31: 1 | J31: 'NA | K31: 1 | L31: 1 | M31: 1 | N31: 1 | O31: Primary KC Alignment: The calculation required is $3.75 [FORMULA] 12$ (multiplying a decimal by a whole number), not multiplying a decimal by 10, 100, 1000 or their multiples as specified in the intended Primary Knowledge Component. Therefore, the main calculation does not require this specific KC, so it does not fully satisfy Primary KC Alignment. | P31: 2.5092857
A32: TD | B32: Question 31 | C32: 0 | D32: 1 | E32: 0 | F32: 1 | G32: 1 | H32: 'NA | I32: 1 | J32: 'NA | K32: 1 | L32: 1 | M32: 1 | N32: 1 | O32: B2: The intended primary KC specifies 'multiplying decimals (up to 3 decimal places) by 10, 100, 1000 and their multiples'. However, the multiplication needed is 3.850 [FORMULA] 140 and 3.850 [FORMULA] 1.4, which is not using 10, 100, 1000 or their multiples directly but multiplying by arbitrary numbers (140 and 1.4). This does not strictly target the intended KC. | P32: 2.2778325
A33: TD | B33: Question 32 | C33: 0 | D33: 1 | E33: 1 | F33: 1 | G33: 1 | H33: 1 | I33: 1 | J33: 1 | K33: 1 | L33: 1 | M33: 1 | N33: 1 | P33: 1.8629761
A34: TD | B34: Question 33 | C34: 0 | D34: 1 | E34: 0 | F34: 1 | G34: 1 | H34: 'NA | I34: 1 | J34: 'NA | K34: 1 | L34: 1 | M34: 1 | N34: 1 | O34: primary_kc_alignment: The division in the problem involves $12.500 [FORMULA] 1000$ (where $12.500$ appears to be a formatting error for $12,500$, but for decimals, $12.500$ should mean $12.50$ or $12.500$, which is typically Primary 6 material; Primary 5 typically does not use values beyond 2 decimal places. Additionally, dividing by 1000, while valid, is not the central focus here as the cost per square metre is not presented in a way that emphasizes the learning objective (dividing decimals up to 3 decimal places by 10, 100, or 1000). grade_alignment: The inclusion of a three-decimal place value ($12.500$) is uncommon for Primary 5, and cost division across such a value is not grade-appropriate as expected in Singapore's syllabus at this level. | P34: 4.6130879
A35: TD | B35: Question 34 | C35: 0 | D35: 1 | E35: 1 | F35: 1 | G35: 1 | H35: 1 | I35: 1 | J35: 1 | K35: 1 | L35: 1 | M35: 1 | N35: 1 | P35: 1.3212917
A36: TD | B36: Question 35 | C36: 0 | D36: 1 | E36: 1 | F36: 1 | G36: 1 | H36: 1 | I36: 1 | J36: 1 | K36: 1 | L36: 1 | M36: 1 | N36: 1 | P36: 1.4192681
A37: TD | B37: Question 36 | C37: 0 | D37: 1 | E37: 1 | F37: 1 | G37: 1 | H37: 1 | I37: 1 | J37: 1 | K37: 1 | L37: 1 | M37: 1 | N37: 1 | P37: 1.2292421
A38: TD | B38: Question 37 | C38: 0 | D38: 1 | E38: 0 | F38: 0 | G38: 1 | H38: 'NA | I38: 1 | J38: 'NA | K38: 1 | L38: 1 | M38: 1 | N38: 1 | O38: Primary KC Alignment: The main calculation in (a) requires dividing a fraction by a fraction (3/4 ÷ 1/8), not dividing a fraction by a whole number as required by the Primary KC. Secondary KC Alignment: The solution to (b) asks for summing the number of loads (i.e., whole numbers), not adding fractions. Thus, the intended secondary KC of adding fractions is not aligned. | P38: 2.6250014
A39: TD | B39: Question 38 | C39: 0 | D39: 1 | E39: 1 | F39: 1 | G39: 1 | H39: 1 | I39: 1 | J39: 1 | K39: 1 | L39: 1 | M39: 1 | N39: 1 | P39: 1.8294985
A40: TD | B40: Question 39 | C40: 0 | D40: 1 | E40: 1 | F40: 1 | G40: 1 | H40: 1 | I40: 1 | J40: 1 | K40: 1 | L40: 1 | M40: 1 | N40: 1 | P40: 1.2209606
A41: TD | B41: Question 40 | C41: 0 | D41: 1 | E41: 1 | F41: 1 | G41: 1 | H41: 1 | I41: 1 | J41: 1 | K41: 1 | L41: 1 | M41: 1 | N41: 1 | P41: 1.5240302
A42: TD | B42: Question 41 | C42: 0 | D42: 1 | E42: 1 | F42: 1 | G42: 1 | H42: 1 | I42: 1 | J42: 1 | K42: 1 | L42: 1 | M42: 1 | N42: 1 | P42: 1.3015156
A43: TD | B43: Question 42 | C43: 0 | D43: 1 | E43: 1 | F43: 1 | G43: 1 | H43: 1 | I43: 1 | J43: 1 | K43: 1 | L43: 1 | M43: 1 | N43: 1 | P43: 1.3656454
A44: TD | B44: Question 43 | C44: 0 | D44: 1 | E44: 1 | F44: 1 | G44: 1 | H44: 1 | I44: 1 | J44: 1 | K44: 1 | L44: 1 | M44: 1 | N44: 1 | P44: 1.1503699
A45: TD | B45: Question 44 | C45: 0 | D45: 1 | E45: 1 | F45: 1 | G45: 1 | H45: 1 | I45: 1 | J45: 1 | K45: 1 | L45: 1 | M45: 1 | N45: 1 | P45: 1.9352546
A46: TD | B46: Question 45 | C46: 0 | D46: 1 | E46: 1 | F46: 1 | G46: 1 | H46: 1 | I46: 1 | J46: 1 | K46: 1 | L46: 1 | M46: 1 | N46: 1 | P46: 1.2670608
A47: TD | B47: Question 46 | C47: 0 | D47: 1 | E47: 1 | F47: 1 | G47: 1 | H47: 1 | I47: 1 | J47: 1 | K47: 1 | L47: 1 | M47: 1 | N47: 1 | P47: 1.2021649
A48: TD | B48: Question 47 | C48: 0 | D48: 1 | E48: 1 | F48: 1 | G48: 1 | H48: 1 | I48: 1 | J48: 1 | K48: 1 | L48: 1 | M48: 1 | N48: 1 | P48: 1.4014904
A49: TD | B49: Question 48 | C49: 0 | D49: 1 | E49: 1 | F49: 1 | G49: 1 | H49: 1 | I49: 1 | J49: 1 | K49: 1 | L49: 1 | M49: 1 | N49: 1 | P49: 1.1347525
A50: TD | B50: Question 49 | C50: 0 | D50: 1 | E50: 1 | F50: 1 | G50: 1 | H50: 1 | I50: 1 | J50: 1 | K50: 1 | L50: 1 | M50: 1 | N50: 1 | P50: 1.2131555
A51: Minh | B51: Question 1 | C51: 0 | D51: 1 | E51: 1 | F51: 1 | G51: 1 | H51: 1 | I51: 1 | J51: 0 | K51: 1 | L51: 1 | M51: 1 | N51: 1 | O51: Synergy: *A* and *B* are independent; answer from (a) is not needed to complete (b), and vice versa, so the KC are not used in tandem. | P51: 1.6956291
A52: Minh | B52: Question 2 | C52: 0 | D52: 1 | E52: 1 | F52: 1 | G52: 1 | H52: 1 | I52: 1 | J52: 1 | K52: 1 | L52: 1 | M52: 1 | N52: 1 | P52: 1.248771
A53: Minh | B53: Question 3 | C53: 0 | D53: 1 | E53: 1 | F53: 1 | G53: 1 | H53: 1 | I53: 1 | J53: 1 | K53: 1 | L53: 1 | M53: 1 | N53: 1 | P53: 1.3042893
A54: Minh | B54: Question 4 | C54: 0 | D54: 1 | E54: 1 | F54: 1 | G54: 1 | H54: 1 | I54: 1 | J54: 1 | K54: 1 | L54: 1 | M54: 1 | N54: 1 | P54: 1.5885611
A55: Minh | B55: Question 5 | C55: 0 | D55: 1 | E55: 1 | F55: 1 | G55: 1 | H55: 1 | I55: 1 | J55: 1 | K55: 1 | L55: 1 | M55: 1 | N55: 1 | P55: 1.4791534
A56: Minh | B56: Question 6 | C56: 0 | D56: 1 | E56: 1 | F56: 1 | G56: 1 | H56: 1 | I56: 1 | J56: 1 | K56: 1 | L56: 1 | M56: 1 | N56: 1 | P56: 1.238673
A57: Minh | B57: Question 7 | C57: 0 | D57: 1 | E57: 1 | F57: 1 | G57: 1 | H57: 1 | I57: 1 | J57: 1 | K57: 1 | L57: 1 | M57: 1 | N57: 1 | P57: 2.1170702
A58: Minh | B58: Question 8 | C58: 0 | D58: 1 | E58: 1 | F58: 1 | G58: 1 | H58: 1 | I58: 1 | J58: 1 | K58: 1 | L58: 1 | M58: 1 | N58: 1 | P58: 1.8182385
A59: Minh | B59: Question 9 | C59: 0 | D59: 1 | E59: 1 | F59: 1 | G59: 1 | H59: 1 | I59: 1 | J59: 1 | K59: 1 | L59: 1 | M59: 1 | N59: 1 | P59: 3.4685011
A60: Minh | B60: Question 10 | C60: 0 | D60: 1 | E60: 1 | F60: 1 | G60: 1 | H60: 1 | I60: 1 | J60: 1 | K60: 1 | L60: 1 | M60: 1 | N60: 1 | P60: 1.2663445
A61: Minh | B61: Question 11 | C61: 0 | D61: 1 | E61: 1 | F61: 1 | G61: 1 | H61: 1 | I61: 1 | J61: 1 | K61: 1 | L61: 1 | M61: 1 | N61: 1 | P61: 1.1531017
A62: Minh | B62: Question 12 | C62: 0 | D62: 1 | E62: 1 | F62: 1 | G62: 1 | H62: 1 | I62: 1 | J62: 1 | K62: 1 | L62: 1 | M62: 1 | N62: 1 | P62: 1.2800925
A63: Minh | B63: Question 13 | C63: 0 | D63: 1 | E63: 1 | F63: 1 | G63: 1 | H63: 1 | I63: 1 | J63: 1 | K63: 1 | L63: 1 | M63: 1 | N63: 1 | P63: 1.2042754
A64: Minh | B64: Question 14 | C64: 0 | D64: 1 | E64: 1 | F64: 1 | G64: 1 | H64: 1 | I64: 1 | J64: 1 | K64: 1 | L64: 1 | M64: 1 | N64: 1 | P64: 1.2174551
A65: Minh | B65: Question 15 | C65: 0 | D65: 1 | E65: 0 | F65: 1 | G65: 1 | H65: 'NA | I65: 1 | J65: 'NA | K65: 1 | L65: 1 | M65: 1 | N65: 1 | O65: Primary KC Alignment: The intended KC is adding decimals up to 2 decimal places, but the problem requires adding 8.95 and 13.299 (where one number has 3 decimal places), which is not aligned with the intended constraint of up to 2 decimal places. Grade Alignment: The word problem involves a decimal value with 3 decimal places (13.299), which exceeds the Primary 4 expected standard of up to 2 decimal places. | P65: 2.3972981
A66: Minh | B66: Question 16 | C66: 0 | D66: 1 | E66: 1 | F66: 1 | G66: 1 | H66: 1 | I66: 1 | J66: 1 | K66: 1 | L66: 1 | M66: 1 | N66: 1 | P66: 1.370193
A67: Minh | B67: Question 17 | C67: 0 | D67: 1 | E67: 0 | F67: 1 | G67: 1 | H67: 'NA | I67: 1 | J67: 'NA | K67: 1 | L67: 1 | M67: 1 | N67: 1 | O67: B2+ The division required is $24[FORMULA]3.75$, which involves dividing a whole number by a decimal, not 'dividing decimals (up to 2 decimal places) by a 1-digit whole number' as required by the intended primary knowledge component. | P67: 1.901998
A68: Minh | B68: Question 18 | C68: 0 | D68: 1 | E68: 1 | F68: 1 | G68: 1 | H68: 1 | I68: 1 | J68: 1 | K68: 1 | L68: 1 | M68: 1 | N68: 1 | P68: 1.2643127
A69: Minh | B69: Question 19 | C69: 0 | D69: 1 | E69: 1 | F69: 1 | G69: 1 | H69: 1 | I69: 1 | J69: 1 | K69: 1 | L69: 1 | M69: 1 | N69: 1 | P69: 1.132674
A70: Minh | B70: Question 20 | C70: 0 | D70: 1 | E70: 1 | F70: 1 | G70: 1 | H70: 1 | I70: 1 | J70: 1 | K70: 1 | L70: 1 | M70: 1 | N70: 1 | P70: 1.3040767
A71: Minh | B71: Question 21 | C71: 0 | D71: 1 | E71: 1 | F71: 1 | G71: 1 | H71: 1 | I71: 1 | J71: 1 | K71: 1 | L71: 1 | M71: 1 | N71: 1 | P71: 4.3275931
A72: Minh | B72: Question 22 | C72: 0 | D72: 1 | E72: 1 | F72: 1 | G72: 1 | H72: 1 | I72: 1 | J72: 1 | K72: 1 | L72: 1 | M72: 1 | N72: 1 | P72: 1.6086574
A73: Minh | B73: Question 23 | C73: 0 | D73: 1 | E73: 1 | F73: 1 | G73: 1 | H73: 1 | I73: 1 | J73: 1 | K73: 1 | L73: 1 | M73: 1 | N73: 1 | P73: 1.7943006
A74: Minh | B74: Question 24 | C74: 0 | D74: 1 | E74: 1 | F74: 1 | G74: 1 | H74: 1 | I74: 1 | J74: 1 | K74: 1 | L74: 1 | M74: 1 | N74: 1 | P74: 1.3154747
A75: Minh | B75: Question 25 | C75: 0 | D75: 1 | E75: 1 | F75: 1 | G75: 1 | H75: 1 | I75: 1 | J75: 1 | K75: 1 | L75: 1 | M75: 1 | N75: 1 | P75: 1.3612368
A76: Minh | B76: Question 26 | C76: 0 | D76: 1 | E76: 1 | F76: 1 | G76: 1 | H76: 1 | I76: 1 | J76: 1 | K76: 1 | L76: 1 | M76: 1 | N76: 1 | P76: 1.296792
A77: Minh | B77: Question 27 | C77: 0 | D77: 1 | E77: 0 | F77: 1 | G77: 1 | H77: 'NA | I77: 1 | J77: 'NA | K77: 1 | L77: 1 | M77: 1 | N77: 1 | O77: Primary KC Alignment: The question asks for multiplication of a decimal by 100 (a whole number multiple of 10), which is a partial match. However, Primary 5 Singapore curriculum expects the focus to be on explicit multiplicands like 10, 100, or 1000, not arbitrary numbers (e.g. 100 months may not highlight the intended skill as clearly as 'multiply $6.125 by 100, 200 or 300'). The operation is mainly two-step: multiply (step 1) then rounding (step 2), blending both KCs well in synergy. | P77: 2.6874712
A78: Minh | B78: Question 28 | C78: 0 | D78: 1 | E78: 1 | F78: 1 | G78: 1 | H78: 1 | I78: 1 | J78: 1 | K78: 1 | L78: 1 | M78: 1 | N78: 1 | P78: 1.9485164
A79: Minh | B79: Question 29 | C79: 0 | D79: 1 | E79: 1 | F79: 1 | G79: 1 | H79: 1 | I79: 1 | J79: 1 | K79: 1 | L79: 1 | M79: 1 | N79: 1 | P79: 1.2144167
A80: Minh | B80: Question 30 | C80: 0 | D80: 1 | E80: 1 | F80: 0 | G80: 1 | H80: 1 | I80: 1 | J80: 'NA | K80: 1 | L80: 1 | M80: 1 | N80: 1 | O80: secondary_kc_alignment: The problem does not require conversion from a larger unit to a smaller unit in decimal form; all calculations remain in hours and money, and no unit conversion is required. synergy: The solution only involves finding the rate (Primary KC) and does not require the use of the Secondary KC to solve it; thus, the two KCs are not used in tandem. | P80: 2.0516076
A81: Minh | B81: Question 31 | C81: 0 | D81: 1 | E81: 1 | F81: 1 | G81: 1 | H81: 1 | I81: 1 | J81: 1 | K81: 1 | L81: 1 | M81: 1 | N81: 1 | P81: 3.8588395
A82: Minh | B82: Question 32 | C82: 0 | D82: 1 | E82: 1 | F82: 1 | G82: 1 | H82: 1 | I82: 1 | J82: 1 | K82: 1 | L82: 1 | M82: 1 | N82: 1 | P82: 1.4548097
A83: Minh | B83: Question 33 | C83: 0 | D83: 1 | E83: 1 | F83: 1 | G83: 1 | H83: 1 | I83: 1 | J83: 1 | K83: 1 | L83: 1 | M83: 1 | N83: 1 | P83: 1.6713903
A84: Minh | B84: Question 34 | C84: 0 | D84: 1 | E84: 1 | F84: 1 | G84: 1 | H84: 1 | I84: 1 | J84: 1 | K84: 1 | L84: 1 | M84: 1 | N84: 1 | P84: 1.3906002
A85: Minh | B85: Question 35 | C85: 0 | D85: 1 | E85: 1 | F85: 1 | G85: 1 | H85: 1 | I85: 1 | J85: 1 | K85: 1 | L85: 1 | M85: 1 | N85: 1 | P85: 1.2361083
A86: Minh | B86: Question 36 | C86: 0 | D86: 1 | E86: 1 | F86: 0 | G86: 1 | H86: 1 | I86: 1 | J86: 'NA | K86: 1 | L86: 1 | M86: 1 | N86: 1 | O86: Secondary KC Alignment: The problem does not require explicit use of subtraction of whole numbers; it requires division by a percentage, not subtraction. Synergy: The solution relies solely on percentage reasoning (finding the whole given the part and percent), not a meaningful combination with whole number subtraction. | P86: 2.6523767
A87: Minh | B87: Question 37 | C87: 0 | D87: 1 | E87: 1 | F87: 1 | G87: 1 | H87: 1 | I87: 1 | J87: 1 | K87: 1 | L87: 1 | M87: 1 | N87: 1 | P87: 1.8744199
A88: Minh | B88: Question 38 | C88: 0 | D88: 1 | E88: 1 | F88: 1 | G88: 1 | H88: 1 | I88: 1 | J88: 1 | K88: 1 | L88: 1 | M88: 1 | N88: 1 | P88: 1.6919494
A89: Minh | B89: Question 39 | C89: 0 | D89: 1 | E89: 1 | F89: 1 | G89: 1 | H89: 1 | I89: 1 | J89: 1 | K89: 1 | L89: 1 | M89: 1 | N89: 1 | P89: 1.1705232
A90: Minh | B90: Question 40 | C90: 0 | D90: 1 | E90: 1 | F90: 1 | G90: 1 | H90: 1 | I90: 1 | J90: 1 | K90: 1 | L90: 1 | M90: 1 | N90: 1 | P90: 1.1834614
A91: Minh | B91: Question 41 | C91: 0 | D91: 1 | E91: 1 | F91: 1 | G91: 1 | H91: 1 | I91: 1 | J91: 1 | K91: 1 | L91: 1 | M91: 1 | N91: 1 | P91: 2.0539579
A92: Minh | B92: Question 42 | C92: 0 | D92: 1 | E92: 1 | F92: 1 | G92: 1 | H92: 1 | I92: 1 | J92: 1 | K92: 1 | L92: 1 | M92: 1 | N92: 1 | P92: 1.1390607
A93: Minh | B93: Question 43 | C93: 0 | D93: 1 | E93: 1 | F93: 1 | G93: 1 | H93: 1 | I93: 1 | J93: 1 | K93: 1 | L93: 1 | M93: 1 | N93: 1 | P93: 1.1929603
A94: Minh | B94: Question 44 | C94: 0 | D94: 1 | E94: 1 | F94: 1 | G94: 1 | H94: 1 | I94: 1 | J94: 1 | K94: 1 | L94: 1 | M94: 1 | N94: 1 | P94: 1.137269
A95: Minh | B95: Question 45 | C95: 0 | D95: 1 | E95: 1 | F95: 1 | G95: 1 | H95: 1 | I95: 1 | J95: 1 | K95: 1 | L95: 1 | M95: 1 | N95: 1 | P95: 1.3832161
A96: Minh | B96: Question 46 | C96: 0 | D96: 1 | E96: 1 | F96: 1 | G96: 1 | H96: 1 | I96: 1 | J96: 1 | K96: 1 | L96: 1 | M96: 1 | N96: 1 | P96: 1.7924252
A97: Minh | B97: Question 47 | C97: 0 | D97: 1 | E97: 1 | F97: 1 | G97: 1 | H97: 1 | I97: 1 | J97: 1 | K97: 1 | L97: 1 | M97: 1 | N97: 1 | P97: 1.5820029
A98: Minh | B98: Question 48 | C98: 0 | D98: 1 | E98: 1 | F98: 1 | G98: 1 | H98: 1 | I98: 1 | J98: 1 | K98: 1 | L98: 1 | M98: 1 | N98: 1 | P98: 4.084806
... A102: Minh | B102: Question 52 | C102: 0 | D102: 1 | E102: 1 | F102: 1 | G102: 1 | H102: 1 | I102: 1 | J102: 1 | K102: 1 | L102: 1 | M102: 1 | N102: 1 | P102: 1.6344929
A103: Minh | B103: Question 53 | C103: 0 | D103: 1 | E103: 0 | F103: 1 | G103: 1 | H103: 'NA | I103: 1 | J103: 'NA | K103: 1 | L103: 1 | M103: 1 | N103: 1 | O103: Primary KC Alignment is 0 because the problem only results in a linear equation in ONE variable (x), not in two variables as specified. Solving for the number of hours at which both costs are equal does not produce a system of TWO equations in TWO variables; it results in a single-variable equation: 50 + 20x = 30 + 25x. | P103: 1.9589584
...

Sheet services_v8_v1_split_2
A1: Evaluator | B1: Question | C1: status | D1: answerability | E1: primary_kc_alignment | F1: secondary_kc_alignment | G1: topic_alignment | H1: grade_alignment | I1: real_world_feasibility | J1: synergy | K1: clarity | L1: conciseness_and_relevance | M1: language_quality | N1: content_appropriateness | O1: explanation | P1: response_time | Q1: language_quality1
A2: TD | B2: Question 1 | C2: 0 | D2: 1 | E2: 1 | F2: 1 | G2: 1 | H2: 1 | I2: 1 | J2: 1 | K2: 1 | L2: 1 | M2: 1 | N2: 1 | P2: 1.6861002
A3: TD | B3: Question 2 | C3: 0 | D3: 1 | E3: 1 | F3: 1 | G3: 1 | H3: 1 | I3: 1 | J3: 1 | K3: 1 | L3: 1 | M3: 1 | N3: 1 | P3: 1.2542369
A4: TD | B4: Question 3 | C4: 0 | D4: 1 | E4: 1 | F4: 1 | G4: 1 | H4: 1 | I4: 1 | J4: 1 | K4: 1 | L4: 1 | M4: 1 | N4: 1 | P4: 1.2422731
A5: TD | B5: Question 4 | C5: 0 | D5: 1 | E5: 1 | F5: 1 | G5: 1 | H5: 1 | I5: 1 | J5: 1 | K5: 1 | L5: 1 | M5: 1 | N5: 1 | P5: 1.3139629
A6: TD | B6: Question 5 | C6: 0 | D6: 1 | E6: 1 | F6: 1 | G6: 1 | H6: 1 | I6: 1 | J6: 1 | K6: 1 | L6: 1 | M6: 1 | N6: 1 | P6: 1.2585614
A7: TD | B7: Question 6 | C7: 0 | D7: 1 | E7: 1 | F7: 1 | G7: 1 | H7: 1 | I7: 1 | J7: 1 | K7: 1 | L7: 1 | M7: 1 | N7: 1 | P7: 2.8658195
A8: TD | B8: Question 7 | C8: 0 | D8: 1 | E8: 1 | F8: 1 | G8: 1 | H8: 1 | I8: 1 | J8: 1 | K8: 1 | L8: 1 | M8: 1 | N8: 1 | P8: 1.501395
A9: TD | B9: Question 8 | C9: 0 | D9: 1 | E9: 1 | F9: 1 | G9: 1 | H9: 1 | I9: 1 | J9: 1 | K9: 1 | L9: 1 | M9: 1 | N9: 1 | P9: 1.7782958
A10: TD | B10: Question 9 | C10: 0 | D10: 1 | E10: 1 | F10: 1 | G10: 1 | H10: 1 | I10: 1 | J10: 1 | K10: 1 | L10: 1 | M10: 1 | N10: 1 | P10: 2.6582363
A11: TD | B11: Question 10 | C11: 0 | D11: 1 | E11: 1 | F11: 1 | G11: 1 | H11: 1 | I11: 1 | J11: 1 | K11: 1 | L11: 1 | M11: 1 | N11: 1 | P11: 1.8057995
A12: TD | B12: Question 11 | C12: 0 | D12: 1 | E12: 1 | F12: 1 | G12: 1 | H12: 1 | I12: 1 | J12: 1 | K12: 1 | L12: 1 | M12: 1 | N12: 1 | P12: 1.3955023
A13: TD | B13: Question 12 | C13: 0 | D13: 1 | E13: 0 | F13: 1 | G13: 1 | H13: 'NA | I13: 1 | J13: 'NA | K13: 1 | L13: 1 | M13: 1 | N13: 1 | O13: Primary KC Alignment: The problem asks for a comparison (as a fraction) of streaming service to cleaning supplies, which mathematically means forming the ratio (division) of the two fractions, not subtraction. Thus, it does not require subtracting unlike fractions, so intended Primary KC is not met. Synergy: The components needed to solve the question are division and then simplification, but since subtraction is not necessary, the intended synergy between subtraction and simplification is missing. | P13: 3.240299
A14: TD | B14: Question 13 | C14: 0 | D14: 1 | E14: 1 | F14: 1 | G14: 1 | H14: 1 | I14: 1 | J14: 1 | K14: 1 | L14: 1 | M14: 1 | N14: 1 | P14: 2.4666107
A15: TD | B15: Question 14 | C15: 0 | D15: 1 | E15: 1 | F15: 1 | G15: 1 | H15: 1 | I15: 1 | J15: 1 | K15: 1 | L15: 1 | M15: 1 | N15: 1 | P15: 1.2102401
A16: TD | B16: Question 15 | C16: 0 | D16: 1 | E16: 1 | F16: 1 | G16: 1 | H16: 1 | I16: 1 | J16: 1 | K16: 1 | L16: 1 | M16: 1 | N16: 1 | P16: 1.3226342
A17: TD | B17: Question 16 | C17: 0 | D17: 1 | E17: 1 | F17: 1 | G17: 1 | H17: 1 | I17: 1 | J17: 1 | K17: 1 | L17: 1 | M17: 1 | N17: 1 | P17: 1.5769408
A18: TD | B18: Question 17 | C18: 0 | D18: 1 | E18: 1 | F18: 1 | G18: 1 | H18: 1 | I18: 1 | J18: 1 | K18: 1 | L18: 1 | M18: 1 | N18: 1 | P18: 1.7207723
A19: TD | B19: Question 18 | C19: 0 | D19: 1 | E19: 0 | F19: 1 | G19: 1 | H19: 'NA | I19: 1 | J19: 'NA | K19: 1 | L19: 1 | M19: 1 | N19: 1 | O19: Primary KC Alignment: The intended division should be 'dividing decimals (up to 2 decimal places) by a 1-digit whole number', but $38.75 [FORMULA] 5$ involves a decimal with 2 decimal places by a 1-digit whole number, which fits; however, in part (b), comparison involves 3 decimal places ($9.725$), not 2, which means Primary KC is not the sole focus. Grade Alignment: Primary 4 students in Singapore typically are not expected to work with or compare decimals up to 3 decimal places ($9.725$) at this level. This is likely expected at a higher grade. | P19: 2.7095566
A20: TD | B20: Question 19 | C20: 0 | D20: 1 | E20: 1 | F20: 1 | G20: 1 | H20: 1 | I20: 1 | J20: 1 | K20: 1 | L20: 1 | M20: 1 | N20: 1 | P20: 1.5042558
A21: TD | B21: Question 20 | C21: 0 | D21: 1 | E21: 1 | F21: 1 | G21: 1 | H21: 1 | I21: 1 | J21: 1 | K21: 1 | L21: 1 | M21: 1 | N21: 1 | P21: 1.1493943
A22: TD | B22: Question 21 | C22: 0 | D22: 1 | E22: 1 | F22: 1 | G22: 1 | H22: 1 | I22: 1 | J22: 1 | K22: 1 | L22: 1 | M22: 1 | N22: 1 | P22: 1.7887921
A23: TD | B23: Question 22 | C23: 0 | D23: 1 | E23: 1 | F23: 1 | G23: 1 | H23: 1 | I23: 1 | J23: 1 | K23: 1 | L23: 1 | M23: 1 | N23: 1 | P23: 1.812434
A24: TD | B24: Question 23 | C24: 0 | D24: 1 | E24: 1 | F24: 1 | G24: 1 | H24: 1 | I24: 1 | J24: 1 | K24: 1 | L24: 1 | M24: 1 | N24: 1 | P24: 2.46455
A25: TD | B25: Question 24 | C25: 0 | D25: 1 | E25: 1 | F25: 1 | G25: 1 | H25: 1 | I25: 1 | J25: 1 | K25: 1 | L25: 1 | M25: 1 | N25: 1 | P25: 1.4776635
A26: TD | B26: Question 25 | C26: 0 | D26: 1 | E26: 1 | F26: 1 | G26: 1 | H26: 1 | I26: 1 | J26: 1 | K26: 1 | L26: 1 | M26: 1 | N26: 1 | P26: 1.2422709
A27: TD | B27: Question 26 | C27: 0 | D27: 1 | E27: 0 | F27: 1 | G27: 1 | H27: 'NA | I27: 1 | J27: 'NA | K27: 1 | L27: 1 | M27: 1 | N27: 1 | O27: Primary KC Alignment: The intended primary KC is 'multiplying two improper fractions', but the word problem only requires multiplying an improper fraction by a whole number (3), not another improper fraction. The scenario never asks the student to multiply two improper fractions as required by the primary KC. | P27: 2.8525422
A28: TD | B28: Question 27 | C28: 0 | D28: 1 | E28: 1 | F28: 0 | G28: 1 | H28: 1 | I28: 1 | J28: 'NA | K28: 1 | L28: 1 | M28: 1 | N28: 1 | O28: Secondary KC Alignment: The question asks 'How many loads are not sent for ironing?' This requires subtracting the number of loads sent for ironing from the total. However, since $[FORMULA]$ of the total are sent for ironing, the remaining not sent is simply $1-[FORMULA]=[FORMULA]$ of the total. This is multiplicative rather than a distinct subtraction of fractions step. Thus, the secondary KC (subtracting fractions) is not strictly necessary as the subtraction is trivial and embedded in the context. Synergy: The steps do not require the results of one component to be used directly in the second in a way that demonstrates true synergy; instead, the procedure is a sequence of two independent calculations. | P28: 3.8100648
A29: TD | B29: Question 28 | C29: 0 | D29: 1 | E29: 1 | F29: 1 | G29: 1 | H29: 1 | I29: 1 | J29: 1 | K29: 1 | L29: 1 | M29: 1 | N29: 1 | P29: 2.1237674
A30: TD | B30: Question 29 | C30: 0 | D30: 1 | E30: 1 | F30: 1 | G30: 1 | H30: 1 | I30: 1 | J30: 1 | K30: 1 | L30: 1 | M30: 1 | N30: 1 | P30: 1.2770839
A31: TD | B31: Question 30 | C31: 0 | D31: 1 | E31: 0 | F31: 1 | G31: 1 | H31: 'NA | I31: 1 | J31: 'NA | K31: 1 | L31: 1 | M31: 1 | N31: 1 | O31: Primary KC Alignment: The multiplication required in part (a) is $3.75 [FORMULA] 12$, which is multiplying a decimal by a whole number. However, the Intended Primary Knowledge Component specifies multiplying decimals by 10, 100, 1000 and their multiples, not by a general whole number. Thus, this problem does not strictly require the targeted multiplication type. | P31: 2.2203612
A32: TD | B32: Question 31 | C32: 0 | D32: 1 | E32: 0 | F32: 1 | G32: 1 | H32: 'NA | I32: 1 | J32: 'NA | K32: 1 | L32: 1 | M32: 1 | N32: 1 | O32: Primary KC Alignment: The question requires multiplication of decimals up to 3 decimal places (3.850 × area), but the context does NOT require multiplying by 10, 100, 1000 or their multiples as explicitly stated in the intended KC. The multiplication here is by 140 and 138.6 (whole numbers/decimals), not multiples of 10/100/1000. | P32: 2.864079
A33: TD | B33: Question 32 | C33: 0 | D33: 1 | E33: 1 | F33: 1 | G33: 1 | H33: 1 | I33: 1 | J33: 1 | K33: 1 | L33: 1 | M33: 1 | N33: 1 | P33: 1.7734344
A34: TD | B34: Question 33 | C34: 0 | D34: 1 | E34: 0 | F34: 1 | G34: 1 | H34: 'NA | I34: 1 | J34: 'NA | K34: 1 | L34: 1 | M34: 0 | N34: 1 | O34: Primary KC Alignment: The division required here is $12.500 ÷ 1000$, which does not require handling decimals up to 3 decimal places, as the dividend is a whole number with three decimal places and the divisor is 1000. This is more about understanding place value with dividing by 10/100/1000 rather than practical division with non-trivial decimals in both numbers. Thus, the problem does not strongly require dividing decimals as intended.Language Quality: The amount [FORMULA]12.500 uses a decimal format uncommon in Singapore context—should be $12.50$ for $12 and 50 cents, not $12.500$ (which suggests three decimal places for currency, which is not standard). Also, 'service charges are divided equally among all square metres cleaned' sounds redundant after the first rate is established, and the final part (c) is repetitive with (b). | P34: 3.7795115
A35: TD | B35: Question 34 | C35: 0 | D35: 1 | E35: 1 | F35: 1 | G35: 1 | H35: 1 | I35: 1 | J35: 1 | K35: 1 | L35: 1 | M35: 1 | N35: 1 | P35: 1.1932802
A36: TD | B36: Question 35 | C36: 0 | D36: 1 | E36: 1 | F36: 1 | G36: 1 | H36: 1 | I36: 1 | J36: 1 | K36: 1 | L36: 1 | M36: 1 | N36: 1 | P36: 1.0953043
A37: TD | B37: Question 36 | C37: 0 | D37: 1 | E37: 1 | F37: 1 | G37: 1 | H37: 1 | I37: 1 | J37: 1 | K37: 1 | L37: 1 | M37: 1 | N37: 1 | P37: 1.2998397
A38: TD | B38: Question 37 | C38: 0 | D38: 1 | E38: 0 | F38: 0 | G38: 1 | H38: 'NA | I38: 1 | J38: 'NA | K38: 1 | L38: 1 | M38: 1 | N38: 1 | O38: Primary KC Alignment=0: The problem requires dividing a fraction by a fraction, not by a whole number as specified by the intended primary knowledge component (dividing a proper fraction by a whole number). / Secondary KC Alignment=0: The addition involved is of whole numbers (number of loads for two items), not the addition of fractions itself as in the intended secondary knowledge component. / Synergy=0: The two sub-questions are independent and do not require the use of the answer from (a) as input for (b); the loads for curtains and cushion covers are calculated separately and then simply tallied up. | P38: 6.6966822
A39: TD | B39: Question 38 | C39: 0 | D39: 1 | E39: 1 | F39: 1 | G39: 1 | H39: 1 | I39: 1 | J39: 1 | K39: 1 | L39: 1 | M39: 1 | N39: 1 | P39: 1.1935899
A40: TD | B40: Question 39 | C40: 0 | D40: 1 | E40: 1 | F40: 1 | G40: 1 | H40: 1 | I40: 1 | J40: 1 | K40: 1 | L40: 1 | M40: 1 | N40: 1 | P40: 2.2261558
A41: TD | B41: Question 40 | C41: 0 | D41: 0 | E41: 'NA | F41: 'NA | G41: 'NA | H41: 'NA | I41: 'NA | J41: 'NA | K41: 'NA | L41: 'NA | M41: 1 | N41: 'NA | O41: A: 01. The cost of 'each cleaning session' is given as (3/4) of the 'amount she has' ($60). This means the cost is a percentage (relative figure), not a fixed amount, so after 1 session, Maya's remaining money changes, causing an ambiguity and making it impossible to answer how many sessions ($60/(3/4 of $60) = $60/$45 = 1.333...) – fractional sessions are not realistic for service bookings.B: 02. The calculation required is $60/(3/4 x $60) = $60/$45, which is just 1 1/3, so dividing by a proper fraction is not required (as dividing a whole number by a proper fraction would be $60 ÷ 3/4). The main computation is not division by a proper fraction.F: 06. No service would charge someone a different amount depending on how much they have. In reality, a cleaning service has a fixed price per session, not a price relative to the customer's total funds. | P41: 4.1321685 | Q41: 'NA
A42: TD | B42: Question 41 | C42: 0 | D42: 1 | E42: 1 | F42: 1 | G42: 1 | H42: 1 | I42: 1 | J42: 1 | K42: 1 | L42: 1 | M42: 1 | N42: 1 | P42: 1.2116642
A43: TD | B43: Question 42 | C43: 0 | D43: 1 | E43: 1 | F43: 1 | G43: 1 | H43: 1 | I43: 1 | J43: 1 | K43: 1 | L43: 1 | M43: 1 | N43: 1 | P43: 1.8741791
A44: TD | B44: Question 43 | C44: 0 | D44: 1 | E44: 1 | F44: 1 | G44: 1 | H44: 1 | I44: 1 | J44: 1 | K44: 1 | L44: 1 | M44: 1 | N44: 1 | P44: 1.1626747
A45: TD | B45: Question 44 | C45: 0 | D45: 1 | E45: 1 | F45: 1 | G45: 1 | H45: 1 | I45: 1 | J45: 1 | K45: 1 | L45: 1 | M45: 1 | N45: 1 | P45: 1.6023324
A46: TD | B46: Question 45 | C46: 0 | D46: 1 | E46: 1 | F46: 1 | G46: 1 | H46: 1 | I46: 1 | J46: 1 | K46: 1 | L46: 1 | M46: 1 | N46: 1 | P46: 1.2384565
A47: TD | B47: Question 46 | C47: 0 | D47: 1 | E47: 1 | F47: 1 | G47: 1 | H47: 1 | I47: 1 | J47: 1 | K47: 1 | L47: 1 | M47: 1 | N47: 1 | P47: 1.9258578
A48: TD | B48: Question 47 | C48: 0 | D48: 1 | E48: 1 | F48: 1 | G48: 1 | H48: 1 | I48: 1 | J48: 1 | K48: 1 | L48: 1 | M48: 1 | N48: 1 | P48: 1.2622883
A49: TD | B49: Question 48 | C49: 0 | D49: 1 | E49: 1 | F49: 1 | G49: 1 | H49: 1 | I49: 1 | J49: 1 | K49: 1 | L49: 1 | M49: 1 | N49: 1 | P49: 1.2732906
A50: TD | B50: Question 49 | C50: 0 | D50: 1 | E50: 1 | F50: 1 | G50: 1 | H50: 1 | I50: 1 | J50: 1 | K50: 1 | L50: 1 | M50: 1 | N50: 1 | P50: 1.1735754
A51: Minh | B51: Question 1 | C51: 0 | D51: 1 | E51: 1 | F51: 1 | G51: 1 | H51: 1 | I51: 1 | J51: 0 | K51: 1 | L51: 1 | M51: 1 | N51: 1 | O51: Synergy=0: The two sub-questions are independent; the answer to (a) is not required to answer (b), and vice versa. The Primary and Secondary Knowledge Components are used separately rather than in tandem. | P51: 1.689363
A52: Minh | B52: Question 2 | C52: 0 | D52: 1 | E52: 1 | F52: 1 | G52: 1 | H52: 1 | I52: 1 | J52: 1 | K52: 1 | L52: 1 | M52: 1 | N52: 1 | P52: 1.4991
A53: Minh | B53: Question 3 | C53: 0 | D53: 1 | E53: 1 | F53: 1 | G53: 1 | H53: 1 | I53: 1 | J53: 0 | K53: 1 | L53: 1 | M53: 1 | N53: 1 | O53: Synergy: 7 - The two questions are not clearly connected by dependency. The outcome from (a) (i.e., the number of filled baskets possible) should affect the reasoning or correctness of answer for (b). However, (b) does not specifically indicate whether the total number of baskets filled in (a) is to be used as a cap or if 5 washing machines can be filled regardless of (a). For strict synergy, the baskets determined from (a) should directly limit the number of baskets considered in (b) and the question should clarify this link. | P53: 2.3387985
A54: Minh | B54: Question 4 | C54: 0 | D54: 1 | E54: 1 | F54: 1 | G54: 1 | H54: 1 | I54: 1 | J54: 1 | K54: 1 | L54: 1 | M54: 1 | N54: 1 | P54: 1.680526
A55: Minh | B55: Question 5 | C55: 0 | D55: 1 | E55: 1 | F55: 1 | G55: 1 | H55: 1 | I55: 1 | J55: 1 | K55: 1 | L55: 1 | M55: 1 | N55: 1 | P55: 1.1608515
A56: Minh | B56: Question 6 | C56: 0 | D56: 1 | E56: 1 | F56: 1 | G56: 1 | H56: 1 | I56: 1 | J56: 1 | K56: 1 | L56: 1 | M56: 1 | N56: 1 | P56: 1.1642158
A57: Minh | B57: Question 7 | C57: 0 | D57: 1 | E57: 1 | F57: 1 | G57: 1 | H57: 1 | I57: 1 | J57: 1 | K57: 1 | L57: 1 | M57: 1 | N57: 1 | P57: 1.2927158
A58: Minh | B58: Question 8 | C58: 0 | D58: 1 | E58: 1 | F58: 1 | G58: 1 | H58: 1 | I58: 1 | J58: 1 | K58: 1 | L58: 1 | M58: 1 | N58: 1 | P58: 1.5896852
A59: Minh | B59: Question 9 | C59: 0 | D59: 1 | E59: 1 | F59: 1 | G59: 1 | H59: 1 | I59: 1 | J59: 1 | K59: 1 | L59: 1 | M59: 1 | N59: 1 | P59: 1.2014868
A60: Minh | B60: Question 10 | C60: 0 | D60: 1 | E60: 1 | F60: 1 | G60: 1 | H60: 1 | I60: 1 | J60: 1 | K60: 1 | L60: 1 | M60: 1 | N60: 1 | P60: 1.1576486
A61: Minh | B61: Question 11 | C61: 0 | D61: 1 | E61: 1 | F61: 1 | G61: 1 | H61: 1 | I61: 1 | J61: 1 | K61: 1 | L61: 1 | M61: 1 | N61: 1 | P61: 1.3507133
A62: Minh | B62: Question 12 | C62: 0 | D62: 1 | E62: 1 | F62: 1 | G62: 1 | H62: 1 | I62: 1 | J62: 1 | K62: 1 | L62: 1 | M62: 1 | N62: 1 | P62: 1.3618004
A63: Minh | B63: Question 13 | C63: 0 | D63: 1 | E63: 1 | F63: 1 | G63: 1 | H63: 1 | I63: 1 | J63: 1 | K63: 1 | L63: 1 | M63: 1 | N63: 1 | P63: 1.2240825
A64: Minh | B64: Question 14 | C64: 0 | D64: 1 | E64: 1 | F64: 1 | G64: 1 | H64: 1 | I64: 1 | J64: 1 | K64: 1 | L64: 1 | M64: 1 | N64: 1 | P64: 1.2301881
A65: Minh | B65: Question 15 | C65: 0 | D65: 1 | E65: 0 | F65: 1 | G65: 1 | H65: 'NA | I65: 0 | J65: 'NA | K65: 1 | L65: 1 | M65: 1 | N65: 1 | O65: Primary KC Alignment: The second value, $13.299, has three decimal places which exceeds 'adding decimals up to 2 decimal places' as per the intended primary knowledge component. Grade Alignment: Values requiring handling of 3 decimal places and rounding to 3 decimal places are not appropriate for Primary 4 (should cap at 2 decimal places). Real-World Feasibility: Prices for streaming services are not typically quoted in $13.299 format (usually up to 2 decimals, e.g., $13.29, $13.30). | P65: 2.7468433
A66: Minh | B66: Question 16 | C66: 0 | D66: 1 | E66: 1 | F66: 1 | G66: 1 | H66: 1 | I66: 1 | J66: 1 | K66: 1 | L66: 1 | M66: 1 | N66: 1 | P66: 1.145633
A67: Minh | B67: Question 17 | C67: 0 | D67: 1 | E67: 0 | F67: 1 | G67: 1 | H67: 'NA | I67: 1 | J67: 'NA | K67: 1 | L67: 1 | M67: 1 | N67: 1 | O67: Primary KC Alignment: The problem requires dividing $24 by $3.75, which involves dividing a whole number by a decimal (not a decimal by a 1-digit whole number as stated in the KC). The intended Primary KC specifies dividing decimals by a 1-digit whole number, so this does not match. | P67: 2.05793
A68: Minh | B68: Question 18 | C68: 0 | D68: 1 | E68: 1 | F68: 1 | G68: 1 | H68: 1 | I68: 1 | J68: 1 | K68: 1 | L68: 1 | M68: 1 | N68: 1 | P68: 1.1779373
A69: Minh | B69: Question 19 | C69: 0 | D69: 1 | E69: 1 | F69: 1 | G69: 1 | H69: 1 | I69: 1 | J69: 1 | K69: 1 | L69: 1 | M69: 1 | N69: 1 | P69: 1.0958424
A70: Minh | B70: Question 20 | C70: 0 | D70: 1 | E70: 1 | F70: 1 | G70: 1 | H70: 1 | I70: 1 | J70: 1 | K70: 1 | L70: 1 | M70: 1 | N70: 1 | P70: 1.827518
A71: Minh | B71: Question 21 | C71: 0 | D71: 1 | E71: 1 | F71: 1 | G71: 1 | H71: 1 | I71: 1 | J71: 1 | K71: 1 | L71: 1 | M71: 1 | N71: 1 | P71: 1.571825
A72: Minh | B72: Question 22 | C72: 0 | D72: 1 | E72: 1 | F72: 1 | G72: 1 | H72: 1 | I72: 1 | J72: 1 | K72: 1 | L72: 1 | M72: 1 | N72: 1 | P72: 1.529439
A73: Minh | B73: Question 23 | C73: 0 | D73: 1 | E73: 1 | F73: 1 | G73: 1 | H73: 1 | I73: 1 | J73: 1 | K73: 1 | L73: 1 | M73: 1 | N73: 1 | P73: 1.4497268
A74: Minh | B74: Question 24 | C74: 0 | D74: 1 | E74: 1 | F74: 1 | G74: 1 | H74: 1 | I74: 1 | J74: 1 | K74: 1 | L74: 1 | M74: 1 | N74: 1 | P74: 1.1888082
A75: Minh | B75: Question 25 | C75: 0 | D75: 1 | E75: 1 | F75: 1 | G75: 1 | H75: 1 | I75: 1 | J75: 1 | K75: 1 | L75: 1 | M75: 1 | N75: 1 | P75: 1.5247676
A76: Minh | B76: Question 26 | C76: 0 | D76: 1 | E76: 1 | F76: 1 | G76: 1 | H76: 1 | I76: 1 | J76: 1 | K76: 1 | L76: 1 | M76: 1 | N76: 1 | P76: 1.1246595
A77: Minh | B77: Question 27 | C77: 0 | D77: 1 | E77: 0 | F77: 1 | G77: 1 | H77: 'NA | I77: 1 | J77: 'NA | K77: 1 | L77: 1 | M77: 1 | N77: 1 | O77: Primary KC Alignment: The multiplication is 6.125 × 100. While 100 is a multiple of 10, the intention was to test multiplication of decimals by 10, 100, 1000 directly. However, multiplying by 100 is essentially multiplying a decimal by 100 and therefore technically satisfies the requirement, but the decimal's place-value movement is very straightforward (just shift decimal two places), with no further conceptual complexity. In Singapore Primary 5, students are expected to handle more nuanced decimal multiplication (e.g., multiplying 6.125 × 125 or similar). Hence, the knowledge component is only marginally tested. | P77: 3.346235
A78: Minh | B78: Question 28 | C78: 0 | D78: 1 | E78: 1 | F78: 1 | G78: 1 | H78: 1 | I78: 1 | J78: 1 | K78: 1 | L78: 1 | M78: 1 | N78: 1 | P78: 1.4079239
A79: Minh | B79: Question 29 | C79: 0 | D79: 1 | E79: 1 | F79: 1 | G79: 1 | H79: 1 | I79: 1 | J79: 1 | K79: 1 | L79: 1 | M79: 1 | N79: 1 | P79: 1.5368011
A80: Minh | B80: Question 30 | C80: 0 | D80: 1 | E80: 1 | F80: 0 | G80: 1 | H80: 1 | I80: 1 | J80: 'NA | K80: 1 | L80: 1 | M80: 1 | N80: 1 | O80: Secondary KC Alignment (0): The problem does not require conversion from a larger unit to a smaller unit in decimals, since the hours are already given in decimal form (1.5 hours) and no conversion is needed to solve the problem. Synergy (0): The secondary knowledge component is not actually needed to solve the main question, and the solution does not depend on both components working together. | P80: 3.630609
A81: Minh | B81: Question 31 | C81: 0 | D81: 1 | E81: 1 | F81: 1 | G81: 1 | H81: 1 | I81: 1 | J81: 1 | K81: 1 | L81: 1 | M81: 1 | N81: 1 | P81: 1.5560374
A82: Minh | B82: Question 32 | C82: 0 | D82: 1 | E82: 1 | F82: 1 | G82: 1 | H82: 1 | I82: 1 | J82: 1 | K82: 1 | L82: 1 | M82: 1 | N82: 1 | P82: 1.1859083
A83: Minh | B83: Question 33 | C83: 0 | D83: 1 | E83: 1 | F83: 1 | G83: 1 | H83: 1 | I83: 1 | J83: 1 | K83: 1 | L83: 1 | M83: 1 | N83: 1 | P83: 1.2080045
A84: Minh | B84: Question 34 | C84: 0 | D84: 1 | E84: 1 | F84: 1 | G84: 1 | H84: 1 | I84: 1 | J84: 1 | K84: 1 | L84: 1 | M84: 1 | N84: 1 | P84: 1.4545698
A85: Minh | B85: Question 35 | C85: 0 | D85: 1 | E85: 1 | F85: 1 | G85: 1 | H85: 1 | I85: 1 | J85: 1 | K85: 1 | L85: 1 | M85: 1 | N85: 1 | P85: 1.1717987
A86: Minh | B86: Question 36 | C86: 0 | D86: 1 | E86: 1 | F86: 0 | G86: 1 | H86: 1 | I86: 1 | J86: 'NA | K86: 1 | L86: 1 | M86: 1 | N86: 1 | O86: Secondary KC Alignment (0): Subtraction of whole numbers is not required to solve the problem; only percentage calculation is necessary. Synergy (0): The word problem does not require both the intended KCs together—solving relies solely on percentage calculation. | P86: 7.2229197
A87: Minh | B87: Question 37 | C87: 0 | D87: 1 | E87: 1 | F87: 1 | G87: 1 | H87: 1 | I87: 1 | J87: 1 | K87: 1 | L87: 1 | M87: 1 | N87: 1 | P87: 2.8804786
A88: Minh | B88: Question 38 | C88: 0 | D88: 1 | E88: 1 | F88: 1 | G88: 1 | H88: 1 | I88: 1 | J88: 1 | K88: 1 | L88: 1 | M88: 1 | N88: 1 | P88: 1.1121588
A89: Minh | B89: Question 39 | C89: 0 | D89: 1 | E89: 1 | F89: 1 | G89: 1 | H89: 1 | I89: 1 | J89: 1 | K89: 1 | L89: 1 | M89: 1 | N89: 1 | P89: 1.1847618
A90: Minh | B90: Question 40 | C90: 0 | D90: 1 | E90: 1 | F90: 1 | G90: 1 | H90: 1 | I90: 1 | J90: 1 | K90: 1 | L90: 1 | M90: 1 | N90: 1 | P90: 1.2028201
A91: Minh | B91: Question 41 | C91: 0 | D91: 1 | E91: 1 | F91: 1 | G91: 1 | H91: 1 | I91: 1 | J91: 1 | K91: 1 | L91: 1 | M91: 1 | N91: 1 | P91: 2.0763202
A92: Minh | B92: Question 42 | C92: 0 | D92: 1 | E92: 1 | F92: 1 | G92: 1 | H92: 1 | I92: 1 | J92: 1 | K92: 1 | L92: 1 | M92: 1 | N92: 1 | P92: 1.7127223
A93: Minh | B93: Question 43 | C93: 0 | D93: 1 | E93: 1 | F93: 1 | G93: 1 | H93: 1 | I93: 1 | J93: 1 | K93: 1 | L93: 1 | M93: 1 | N93: 1 | P93: 1.6288664
A94: Minh | B94: Question 44 | C94: 0 | D94: 1 | E94: 1 | F94: 1 | G94: 1 | H94: 1 | I94: 1 | J94: 1 | K94: 1 | L94: 1 | M94: 1 | N94: 1 | P94: 1.1805375
A95: Minh | B95: Question 45 | C95: 0 | D95: 1 | E95: 1 | F95: 1 | G95: 1 | H95: 1 | I95: 1 | J95: 1 | K95: 1 | L95: 1 | M95: 1 | N95: 1 | P95: 2.5372751
A96: Minh | B96: Question 46 | C96: 0 | D96: 1 | E96: 1 | F96: 1 | G96: 1 | H96: 1 | I96: 1 | J96: 1 | K96: 1 | L96: 1 | M96: 1 | N96: 1 | P96: 2.2444966
A97: Minh | B97: Question 47 | C97: 0 | D97: 1 | E97: 1 | F97: 1 | G97: 1 | H97: 1 | I97: 1 | J97: 1 | K97: 1 | L97: 1 | M97: 1 | N97: 1 | P97: 1.9684715
A98: Minh | B98: Question 48 | C98: 0 | D98: 1 | E98: 1 | F98: 1 | G98: 1 | H98: 1 | I98: 1 | J98: 1 | K98: 1 | L98: 1 | M98: 1 | N98: 1 | P98: 1.212631
... A117: Sarah | B117: Question 4 | C117: 0 | D117: 1 | E117: 1 | F117: 1 | G117: 1 | H117: 1 | I117: 1 | J117: 1 | K117: 1 | L117: 1 | M117: 1 | N117: 1 | P117: 1.5492227
A118: Sarah | B118: Question 5 | C118: 0 | D118: 0 | E118: 'NA | F118: 'NA | G118: 'NA | H118: 'NA | I118: 'NA | J118: 'NA | K118: 'NA | L118: 'NA | M118: 1 | N118: 'NA | O118: answerability: 0 - The phrasing in part (a) is confusing and mathematically ambiguous: 'What fraction of her watchlist movies did she watch last month than this month?' is not clear. It should clarify that it wants the difference (last month minus this month). primary_kc_alignment: 0 - Because of the unclear phrasing in (a), the intended subtraction could be missed or misunderstood by students, so the main KC is not solidly targeted. grade_alignment: 0 - Fractions with different, non-unit numerators and denominators above 10, along with the language ambiguity, are above the direct-application level expected for Primary 3. synergy: 0 - The simplification part (b) does not clearly depend on the correct computation in (a) due to potential confusion; the parts are not tightly linked for strong synergy. clarity: 0 - The question in (a) is missing a word ('more') or should be rephrased as: 'By what fraction did Erin watch more watchlist movies last month than this month?'. | P118: 3.4180653 | Q118: 'NA
...

Sheet services_v8_v1_split_3
A1: Evaluator | B1: Question | C1: status | D1: answerability | E1: primary_kc_alignment | F1: secondary_kc_alignment | G1: topic_alignment | H1: grade_alignment | I1: real_world_feasibility | J1: synergy | K1: clarity | L1: conciseness_and_relevance | M1: language_quality | N1: content_appropriateness | O1: explanation | P1: response_time | Q1: language_quality1
A2: TD | B2: Question 1 | C2: 0 | D2: 1 | E2: 1 | F2: 1 | G2: 1 | H2: 1 | I2: 1 | J2: 1 | K2: 1 | L2: 1 | M2: 1 | N2: 1 | P2: 1.4358344
A3: TD | B3: Question 2 | C3: 0 | D3: 1 | E3: 1 | F3: 1 | G3: 1 | H3: 1 | I3: 1 | J3: 1 | K3: 1 | L3: 1 | M3: 1 | N3: 1 | P3: 1.2256327
A4: TD | B4: Question 3 | C4: 0 | D4: 1 | E4: 1 | F4: 1 | G4: 1 | H4: 1 | I4: 1 | J4: 1 | K4: 1 | L4: 1 | M4: 1 | N4: 1 | P4: 3.7735586
A5: TD | B5: Question 4 | C5: 0 | D5: 1 | E5: 1 | F5: 1 | G5: 1 | H5: 1 | I5: 1 | J5: 1 | K5: 1 | L5: 1 | M5: 1 | N5: 1 | P5: 1.3616157
A6: TD | B6: Question 5 | C6: 0 | D6: 1 | E6: 1 | F6: 1 | G6: 1 | H6: 1 | I6: 1 | J6: 1 | K6: 1 | L6: 1 | M6: 1 | N6: 1 | P6: 1.5372276
A7: TD | B7: Question 6 | C7: 0 | D7: 1 | E7: 1 | F7: 1 | G7: 1 | H7: 1 | I7: 1 | J7: 1 | K7: 1 | L7: 1 | M7: 1 | N7: 1 | P7: 1.2145395
A8: TD | B8: Question 7 | C8: 0 | D8: 1 | E8: 1 | F8: 1 | G8: 1 | H8: 1 | I8: 1 | J8: 1 | K8: 1 | L8: 1 | M8: 1 | N8: 1 | P8: 1.2895463
A9: TD | B9: Question 8 | C9: 0 | D9: 1 | E9: 1 | F9: 1 | G9: 1 | H9: 1 | I9: 1 | J9: 1 | K9: 1 | L9: 1 | M9: 1 | N9: 1 | P9: 1.1941273
A10: TD | B10: Question 9 | C10: 0 | D10: 1 | E10: 1 | F10: 1 | G10: 1 | H10: 1 | I10: 1 | J10: 1 | K10: 1 | L10: 1 | M10: 1 | N10: 1 | P10: 1.2945511
A11: TD | B11: Question 10 | C11: 0 | D11: 1 | E11: 1 | F11: 1 | G11: 1 | H11: 1 | I11: 1 | J11: 1 | K11: 1 | L11: 1 | M11: 1 | N11: 1 | P11: 2.9018707
A12: TD | B12: Question 11 | C12: 0 | D12: 1 | E12: 1 | F12: 1 | G12: 1 | H12: 1 | I12: 1 | J12: 0 | K12: 1 | L12: 1 | M12: 1 | N12: 1 | O12: 7: The two parts (addition and ordering of fractions) are independent in this word problem. The answer to (1) is not necessary for (2), nor vice versa. The problems do not build on each other, so synergy is lacking. | P12: 1.813031
A13: TD | B13: Question 12 | C13: 0 | D13: 1 | E13: 0 | F13: 1 | G13: 1 | H13: 'NA | I13: 1 | J13: 'NA | K13: 1 | L13: 1 | M13: 1 | N13: 1 | O13: B1- The question asks for the fraction of the allowance spent on streaming compared to cleaning supplies, which requires division (finding the ratio), not subtraction of fractions as stipulated in the intended Primary Knowledge Component. B7- The word problem does not require synergy between subtraction and simplification: only comparing via division is needed and then simplifying, not using subtraction and simplification together. | P13: 2.4905815
A14: TD | B14: Question 13 | C14: 0 | D14: 1 | E14: 1 | F14: 1 | G14: 1 | H14: 0 | I14: 0 | J14: 1 | K14: 1 | L14: 1 | M14: 1 | N14: 1 | O14: 5: The word problem requires students to compare and order decimal values with three decimal places (e.g., $36.450$), but Primary 4 students in Singapore are only expected to work with decimals up to two decimal places. This exceeds the grade level expectation. 6: Receipt totals including three decimal places (even though the service sums only need two) are not realistic in Singapore, as services almost always round to two decimal places due to the currency system—that is, cents. Receipts to the thousandth of a dollar aren't used. | P14: 8.0114985
A15: TD | B15: Question 14 | C15: 0 | D15: 1 | E15: 1 | F15: 1 | G15: 1 | H15: 1 | I15: 1 | J15: 1 | K15: 1 | L15: 1 | M15: 1 | N15: 1 | P15: 2.0466049
A16: TD | B16: Question 15 | C16: 0 | D16: 1 | E16: 1 | F16: 1 | G16: 1 | H16: 1 | I16: 1 | J16: 1 | K16: 1 | L16: 1 | M16: 1 | N16: 1 | P16: 1.3831022
A17: TD | B17: Question 16 | C17: 0 | D17: 1 | E17: 1 | F17: 1 | G17: 1 | H17: 1 | I17: 1 | J17: 0 | K17: 1 | L17: 1 | M17: 1 | N17: 1 | O17: 7- The two parts (a) and (b) are independent of each other and do not demonstrate synergy; solving one does not require the result of the other. | P17: 2.1098597
A18: TD | B18: Question 17 | C18: 0 | D18: 1 | E18: 1 | F18: 1 | G18: 1 | H18: 1 | I18: 1 | J18: 1 | K18: 1 | L18: 1 | M18: 1 | N18: 1 | P18: 1.6059194
A19: TD | B19: Question 18 | C19: 0 | D19: 1 | E19: 0 | F19: 1 | G19: 1 | H19: 'NA | I19: 1 | J19: 'NA | K19: 1 | L19: 1 | M19: 1 | N19: 1 | O19: Primary KC Alignment: - The division required in (a) is $38.75 [FORMULA] 5 = 7.75$, which only involves dividing a number with at most 2 decimal places by a single-digit whole number, satisfying the intended KC. However, in part (b), the comparison involves a number ($9.725$) with 3 decimal places in the context of Singapore Primary 4, students typically only work with up to 2 decimal places in routine division situations. Grade Alignment: - Part (b) requires students to compare $7.75$ and $9.725$, where $9.725$ is written with 3 decimal places, which is beyond the typical Primary 4 decimal comparison syllabus in Singapore, as this level usually restricts questions to decimals with up to 2 decimal places. | P19: 3.2708125
A20: TD | B20: Question 19 | C20: 0 | D20: 1 | E20: 1 | F20: 1 | G20: 1 | H20: 1 | I20: 1 | J20: 1 | K20: 1 | L20: 1 | M20: 1 | N20: 1 | P20: 1.1546955
A21: TD | B21: Question 20 | C21: 0 | D21: 1 | E21: 1 | F21: 1 | G21: 1 | H21: 1 | I21: 1 | J21: 1 | K21: 1 | L21: 1 | M21: 1 | N21: 1 | P21: 1.1216848
A22: TD | B22: Question 21 | C22: 0 | D22: 1 | E22: 1 | F22: 1 | G22: 1 | H22: 1 | I22: 1 | J22: 1 | K22: 1 | L22: 1 | M22: 1 | N22: 1 | P22: 1.2392769
A23: TD | B23: Question 22 | C23: 0 | D23: 1 | E23: 1 | F23: 0 | G23: 1 | H23: 1 | I23: 1 | J23: 'NA | K23: 1 | L23: 1 | M23: 1 | N23: 1 | O23: secondary_kc_alignment: The secondary knowledge component (comparison and ordering of fractions) is not directly required—the comparison in (b) can be done by comparing two whole numbers, not fractions, as both Mrs Lim's and her friend's values will be turned into whole numbers for comparison. synergy: The result from (a) is used in (b), but the intended secondary KC is not needed, so strong synergy between the two intended KCs is absent. | P23: 2.7512496
A24: TD | B24: Question 23 | C24: 0 | D24: 1 | E24: 1 | F24: 1 | G24: 1 | H24: 1 | I24: 1 | J24: 1 | K24: 1 | L24: 1 | M24: 1 | N24: 1 | P24: 1.8896658
A25: TD | B25: Question 24 | C25: 0 | D25: 1 | E25: 1 | F25: 1 | G25: 1 | H25: 1 | I25: 1 | J25: 1 | K25: 1 | L25: 1 | M25: 1 | N25: 1 | P25: 1.1975698
A26: TD | B26: Question 25 | C26: 0 | D26: 1 | E26: 1 | F26: 1 | G26: 1 | H26: 1 | I26: 1 | J26: 1 | K26: 1 | L26: 1 | M26: 1 | N26: 1 | P26: 1.5837059
A27: TD | B27: Question 26 | C27: 0 | D27: 1 | E27: 0 | F27: 1 | G27: 1 | H27: 'NA | I27: 1 | J27: 'NA | K27: 1 | L27: 1 | M27: 1 | N27: 1 | O27: primary_kc_alignment: The problem requires multiplying the improper fraction \([FORMULA]\) by the integer 3, not multiplying two improper fractions as specified in the intended primary KC. Multiplication is with a whole number, not an improper fraction. | P27: 1.837652
A28: TD | B28: Question 27 | C28: 0 | D28: 1 | E28: 1 | F28: 1 | G28: 1 | H28: 1 | I28: 1 | J28: 1 | K28: 1 | L28: 1 | M28: 1 | N28: 1 | P28: 1.1256123
A29: TD | B29: Question 28 | C29: 0 | D29: 1 | E29: 1 | F29: 1 | G29: 1 | H29: 1 | I29: 0 | J29: 1 | K29: 1 | L29: 1 | M29: 1 | N29: 1 | O29: Real World Feasibility: - In real situations, it is highly unlikely to clean a non-whole-number of rooms (8/5 = 1.6 rooms) in a session, especially for a cleaning company that counts by discrete rooms, not fractions of a room. This makes the scenario unrealistic for the intended grade and context. | P29: 3.0800958
A30: TD | B30: Question 29 | C30: 0 | D30: 1 | E30: 1 | F30: 1 | G30: 1 | H30: 1 | I30: 1 | J30: 1 | K30: 1 | L30: 1 | M30: 1 | N30: 1 | P30: 1.4802535
A31: TD | B31: Question 30 | C31: 0 | D31: 1 | E31: 0 | F31: 1 | G31: 1 | H31: 'NA | I31: 1 | J31: 'NA | K31: 1 | L31: 1 | M31: 1 | N31: 1 | O31: Primary KC Alignment: The word problem does require multiplication involving decimals (3.75 x 12), but it does not require multiplying by 10, 100, 1000 or their multiples, as specified in the intended Primary Knowledge Component. Instead, it is simply multiplying two numbers with decimals, which is a different skill focus. | P31: 1.9709678
A32: TD | B32: Question 31 | C32: 0 | D32: 1 | E32: 1 | F32: 1 | G32: 1 | H32: 1 | I32: 1 | J32: 1 | K32: 1 | L32: 1 | M32: 1 | N32: 1 | P32: 1.2840397
A33: TD | B33: Question 32 | C33: 0 | D33: 1 | E33: 1 | F33: 1 | G33: 1 | H33: 1 | I33: 1 | J33: 1 | K33: 1 | L33: 1 | M33: 1 | N33: 1 | P33: 1.1874092
A34: TD | B34: Question 33 | C34: 0 | D34: 1 | E34: 0 | F34: 1 | G34: 1 | H34: 'NA | I34: 1 | J34: 'NA | K34: 1 | L34: 1 | M34: 0 | N34: 1 | O34: primary_kc_alignment: The main knowledge component requires dividing decimals by 10, 100, 1000 or their multiples. The value 12.500 looks like a formatting or decimal point error (should be $12,500 or $12.50). If it's $12.50, dividing by 1000 gives the unit cost, but the presence of three decimal places is not evident in the calculation. The KC doesn't emphasize dividing by 10, 100, 1000 specifically.language_quality: There's a formatting error in the currency value: '[FORMULA]12.500' is not standard for dollars and cents. This may cause confusion for students and should be corrected. | P34: 2.8934646
A35: TD | B35: Question 34 | C35: 0 | D35: 1 | E35: 1 | F35: 1 | G35: 1 | H35: 1 | I35: 1 | J35: 1 | K35: 1 | L35: 1 | M35: 1 | N35: 1 | P35: 2.5798905
A36: TD | B36: Question 35 | C36: 0 | D36: 1 | E36: 1 | F36: 1 | G36: 1 | H36: 1 | I36: 1 | J36: 1 | K36: 1 | L36: 1 | M36: 1 | N36: 1 | P36: 1.6847355
A37: TD | B37: Question 36 | C37: 0 | D37: 1 | E37: 1 | F37: 1 | G37: 1 | H37: 1 | I37: 1 | J37: 1 | K37: 1 | L37: 1 | M37: 1 | N37: 1 | P37: 1.4750748
A38: TD | B38: Question 37 | C38: 0 | D38: 1 | E38: 0 | F38: 0 | G38: 1 | H38: 'NA | I38: 1 | J38: 'NA | K38: 1 | L38: 1 | M38: 1 | N38: 1 | O38: Primary KC Alignment: The problem asks students to compute how many loads by dividing a fraction by a fraction (3/4 ÷ 1/8), not by a whole number as specified in the intended KC. Secondary KC Alignment: Students are not required to add fractions; rather, the total is found by summing two whole numbers of loads, which doesn't require the operation of adding fractions. Synergy: The two sub-questions (a) and (b) can be answered independently; they are connected by context but not by their mathematical operations or results (the answer for (a) is not needed to answer (b)). | P38: 3.4917967
A39: TD | B39: Question 38 | C39: 0 | D39: 1 | E39: 1 | F39: 1 | G39: 1 | H39: 1 | I39: 1 | J39: 1 | K39: 1 | L39: 1 | M39: 1 | N39: 1 | P39: 1.3485582
A40: TD | B40: Question 39 | C40: 0 | D40: 1 | E40: 1 | F40: 1 | G40: 1 | H40: 1 | I40: 1 | J40: 1 | K40: 1 | L40: 1 | M40: 1 | N40: 1 | P40: 1.1097412
A41: TD | B41: Question 40 | C41: 0 | D41: 1 | E41: 0 | F41: 1 | G41: 1 | H41: 'NA | I41: 0 | J41: 'NA | K41: 1 | L41: 1 | M41: 1 | N41: 1 | O41: Primary KC Alignment: The problem does not require dividing a whole number or fraction by another fraction. Instead, it involves multiplying $60 by the reciprocal of $45 (finding how many times $45 fits into $60 is $60 / $45, not $60 / (3/4)). The question should have been: 'Each session costs $3/4 of a dollar,' not '$3/4 of the amount she has.' Real-World Feasibility: It is unrealistic for each session to cost 3/4 of the total amount Maya initially has, since after one session, the remaining amount would also change. Synergy: Both parts can be solved independently; part (b) is simply expressing the answer from (a) as a decimal—there is no necessary dependency or tandem use of the KCs for their solution. | P41: 3.1533217
A42: TD | B42: Question 41 | C42: 0 | D42: 1 | E42: 1 | F42: 1 | G42: 1 | H42: 1 | I42: 1 | J42: 1 | K42: 1 | L42: 1 | M42: 1 | N42: 1 | P42: 1.9199865
A43: TD | B43: Question 42 | C43: 0 | D43: 1 | E43: 1 | F43: 1 | G43: 1 | H43: 1 | I43: 1 | J43: 1 | K43: 1 | L43: 1 | M43: 1 | N43: 1 | P43: 1.4087288
A44: TD | B44: Question 43 | C44: 0 | D44: 1 | E44: 1 | F44: 1 | G44: 1 | H44: 1 | I44: 1 | J44: 1 | K44: 1 | L44: 1 | M44: 1 | N44: 1 | P44: 1.1872821
A45: TD | B45: Question 44 | C45: 0 | D45: 1 | E45: 1 | F45: 1 | G45: 1 | H45: 1 | I45: 1 | J45: 1 | K45: 1 | L45: 1 | M45: 1 | N45: 1 | P45: 1.1633725
A46: TD | B46: Question 45 | C46: 0 | D46: 1 | E46: 1 | F46: 1 | G46: 1 | H46: 1 | I46: 1 | J46: 1 | K46: 1 | L46: 1 | M46: 1 | N46: 1 | P46: 1.5568473
A47: TD | B47: Question 46 | C47: 0 | D47: 1 | E47: 1 | F47: 1 | G47: 1 | H47: 1 | I47: 1 | J47: 1 | K47: 1 | L47: 1 | M47: 1 | N47: 1 | P47: 1.114888
A48: TD | B48: Question 47 | C48: 0 | D48: 1 | E48: 1 | F48: 1 | G48: 1 | H48: 1 | I48: 1 | J48: 1 | K48: 1 | L48: 1 | M48: 1 | N48: 1 | P48: 1.4509926
A49: TD | B49: Question 48 | C49: 0 | D49: 1 | E49: 1 | F49: 1 | G49: 1 | H49: 1 | I49: 1 | J49: 1 | K49: 1 | L49: 1 | M49: 1 | N49: 1 | P49: 1.1227045
A50: TD | B50: Question 49 | C50: 0 | D50: 1 | E50: 1 | F50: 1 | G50: 1 | H50: 1 | I50: 1 | J50: 1 | K50: 1 | L50: 1 | M50: 1 | N50: 1 | P50: 1.1446157
A51: Minh | B51: Question 1 | C51: 0 | D51: 1 | E51: 1 | F51: 1 | G51: 1 | H51: 1 | I51: 1 | J51: 0 | K51: 1 | L51: 1 | M51: 1 | N51: 1 | O51: synergy: The two sub-questions (a) and (b) are independent. The result from (a) is not needed to solve (b), and vice versa. | P51: 1.6847453
A52: Minh | B52: Question 2 | C52: 0 | D52: 1 | E52: 1 | F52: 1 | G52: 1 | H52: 1 | I52: 1 | J52: 1 | K52: 1 | L52: 1 | M52: 1 | N52: 1 | P52: 1.1242442
A53: Minh | B53: Question 3 | C53: 0 | D53: 1 | E53: 1 | F53: 1 | G53: 1 | H53: 1 | I53: 1 | J53: 1 | K53: 1 | L53: 1 | M53: 1 | N53: 1 | P53: 1.5821147
A54: Minh | B54: Question 4 | C54: 0 | D54: 1 | E54: 1 | F54: 1 | G54: 1 | H54: 1 | I54: 1 | J54: 1 | K54: 1 | L54: 1 | M54: 1 | N54: 1 | P54: 1.1589198
A55: Minh | B55: Question 5 | C55: 0 | D55: 1 | E55: 1 | F55: 1 | G55: 1 | H55: 1 | I55: 1 | J55: 1 | K55: 1 | L55: 1 | M55: 1 | N55: 1 | P55: 1.8773561
A56: Minh | B56: Question 6 | C56: 0 | D56: 1 | E56: 1 | F56: 1 | G56: 1 | H56: 1 | I56: 1 | J56: 1 | K56: 1 | L56: 1 | M56: 1 | N56: 1 | P56: 1.1255395
A57: Minh | B57: Question 7 | C57: 0 | D57: 1 | E57: 1 | F57: 1 | G57: 1 | H57: 1 | I57: 1 | J57: 1 | K57: 1 | L57: 1 | M57: 1 | N57: 1 | P57: 1.5988708
A58: Minh | B58: Question 8 | C58: 0 | D58: 1 | E58: 1 | F58: 1 | G58: 1 | H58: 1 | I58: 1 | J58: 1 | K58: 1 | L58: 1 | M58: 1 | N58: 1 | P58: 1.3342781
A59: Minh | B59: Question 9 | C59: 0 | D59: 1 | E59: 1 | F59: 1 | G59: 1 | H59: 1 | I59: 1 | J59: 1 | K59: 1 | L59: 1 | M59: 1 | N59: 1 | P59: 2.1148422
A60: Minh | B60: Question 10 | C60: 0 | D60: 1 | E60: 1 | F60: 1 | G60: 1 | H60: 1 | I60: 1 | J60: 1 | K60: 1 | L60: 1 | M60: 1 | N60: 1 | P60: 1.1843503
A61: Minh | B61: Question 11 | C61: 0 | D61: 1 | E61: 1 | F61: 1 | G61: 1 | H61: 1 | I61: 1 | J61: 1 | K61: 1 | L61: 1 | M61: 1 | N61: 1 | P61: 1.6986396
A62: Minh | B62: Question 12 | C62: 0 | D62: 1 | E62: 1 | F62: 1 | G62: 1 | H62: 1 | I62: 1 | J62: 1 | K62: 1 | L62: 1 | M62: 1 | N62: 1 | P62: 1.2093041
A63: Minh | B63: Question 13 | C63: 0 | D63: 1 | E63: 1 | F63: 1 | G63: 1 | H63: 1 | I63: 1 | J63: 1 | K63: 1 | L63: 1 | M63: 1 | N63: 1 | P63: 1.8001285
A64: Minh | B64: Question 14 | C64: 0 | D64: 1 | E64: 1 | F64: 1 | G64: 1 | H64: 1 | I64: 1 | J64: 1 | K64: 1 | L64: 1 | M64: 1 | N64: 1 | P64: 1.1670923
A65: Minh | B65: Question 15 | C65: 0 | D65: 1 | E65: 0 | F65: 1 | G65: 1 | H65: 'NA | I65: 1 | J65: 'NA | K65: 1 | L65: 1 | M65: 1 | N65: 1 | O65: Primary KC Alignment (0): The word problem requires adding $8.95$ and $13.299$, but $13.299$ is NOT up to 2 decimal places, which exceeds Primary 4 expectations per Singapore syllabus and violates the intended primary KC (adding decimals up to 2 decimal places). Grade Alignment (0): The presence of $13.299$ (3 decimal places) is not age-appropriate for Primary 4 in Singapore, where students typically only deal with decimals up to 2 decimal places. | P65: 2.8037229
A66: Minh | B66: Question 16 | C66: 0 | D66: 1 | E66: 1 | F66: 1 | G66: 1 | H66: 1 | I66: 1 | J66: 1 | K66: 1 | L66: 1 | M66: 1 | N66: 1 | P66: 1.8635695
A67: Minh | B67: Question 17 | C67: 0 | D67: 1 | E67: 0 | F67: 1 | G67: 1 | H67: 'NA | I67: 1 | J67: 'NA | K67: 1 | L67: 1 | M67: 1 | N67: 1 | O67: Primary KC Alignment: The question requires dividing 24 by 3.75, which involves dividing a whole number by a decimal (not dividing a decimal by a whole number as specified in the Primary KC). For the intended KC, the structure should be like 'divide a number with up to 2 decimal places by a 1-digit whole number', e.g., 7.50 ÷ 3. This problem does not fulfil this requirement, as the divisor is a decimal. | P67: 2.1900854
A68: Minh | B68: Question 18 | C68: 0 | D68: 1 | E68: 1 | F68: 1 | G68: 1 | H68: 1 | I68: 1 | J68: 1 | K68: 1 | L68: 1 | M68: 1 | N68: 1 | P68: 1.254118
A69: Minh | B69: Question 19 | C69: 0 | D69: 1 | E69: 1 | F69: 1 | G69: 1 | H69: 1 | I69: 1 | J69: 1 | K69: 1 | L69: 1 | M69: 1 | N69: 1 | P69: 1.6828496
A70: Minh | B70: Question 20 | C70: 0 | D70: 1 | E70: 1 | F70: 1 | G70: 1 | H70: 1 | I70: 1 | J70: 1 | K70: 1 | L70: 1 | M70: 1 | N70: 1 | P70: 1.1137567
A71: Minh | B71: Question 21 | C71: 0 | D71: 1 | E71: 1 | F71: 1 | G71: 1 | H71: 1 | I71: 1 | J71: 1 | K71: 1 | L71: 1 | M71: 1 | N71: 1 | P71: 1.1505103
A72: Minh | B72: Question 22 | C72: 0 | D72: 1 | E72: 1 | F72: 1 | G72: 1 | H72: 1 | I72: 1 | J72: 1 | K72: 1 | L72: 1 | M72: 1 | N72: 1 | P72: 1.7034051
A73: Minh | B73: Question 23 | C73: 0 | D73: 1 | E73: 1 | F73: 1 | G73: 1 | H73: 1 | I73: 1 | J73: 1 | K73: 1 | L73: 1 | M73: 1 | N73: 1 | P73: 1.2280293
A74: Minh | B74: Question 24 | C74: 0 | D74: 1 | E74: 1 | F74: 1 | G74: 1 | H74: 1 | I74: 1 | J74: 1 | K74: 1 | L74: 1 | M74: 1 | N74: 1 | P74: 1.8510249
A75: Minh | B75: Question 25 | C75: 0 | D75: 1 | E75: 1 | F75: 1 | G75: 1 | H75: 1 | I75: 1 | J75: 1 | K75: 1 | L75: 1 | M75: 1 | N75: 1 | P75: 1.4062531
A76: Minh | B76: Question 26 | C76: 0 | D76: 1 | E76: 1 | F76: 1 | G76: 1 | H76: 1 | I76: 1 | J76: 1 | K76: 1 | L76: 1 | M76: 1 | N76: 1 | P76: 2.3184242
A77: Minh | B77: Question 27 | C77: 0 | D77: 1 | E77: 1 | F77: 1 | G77: 1 | H77: 1 | I77: 1 | J77: 1 | K77: 1 | L77: 1 | M77: 1 | N77: 1 | P77: 1.1434767
A78: Minh | B78: Question 28 | C78: 0 | D78: 1 | E78: 1 | F78: 1 | G78: 1 | H78: 1 | I78: 1 | J78: 1 | K78: 1 | L78: 1 | M78: 1 | N78: 1 | P78: 2.0323608
A79: Minh | B79: Question 29 | C79: 0 | D79: 1 | E79: 1 | F79: 1 | G79: 1 | H79: 1 | I79: 1 | J79: 1 | K79: 1 | L79: 1 | M79: 1 | N79: 1 | P79: 1.3065679
A80: Minh | B80: Question 30 | C80: 0 | D80: 1 | E80: 1 | F80: 0 | G80: 1 | H80: 1 | I80: 1 | J80: 'NA | K80: 1 | L80: 1 | M80: 1 | N80: 1 | O80: Secondary KC Alignment (0): The question does not require converting a measurement from a larger unit in decimal form to a smaller unit. The provided values are already in consistent units (dollars, hours). Synergy (0): The use of rate is the only knowledge component required; there is no need to perform a conversion between decimal measures forming a necessary synergy between the target knowledge components. | P80: 2.1807535
A81: Minh | B81: Question 31 | C81: 0 | D81: 1 | E81: 1 | F81: 1 | G81: 1 | H81: 1 | I81: 1 | J81: 1 | K81: 1 | L81: 1 | M81: 1 | N81: 1 | P81: 1.2955387
A82: Minh | B82: Question 32 | C82: 0 | D82: 1 | E82: 1 | F82: 1 | G82: 1 | H82: 1 | I82: 1 | J82: 1 | K82: 1 | L82: 1 | M82: 1 | N82: 1 | P82: 1.6204362
A83: Minh | B83: Question 33 | C83: 0 | D83: 1 | E83: 1 | F83: 1 | G83: 1 | H83: 1 | I83: 1 | J83: 1 | K83: 1 | L83: 1 | M83: 1 | N83: 1 | P83: 1.4191687
A84: Minh | B84: Question 34 | C84: 0 | D84: 1 | E84: 1 | F84: 1 | G84: 1 | H84: 1 | I84: 1 | J84: 1 | K84: 1 | L84: 1 | M84: 1 | N84: 1 | P84: 1.2800114
A85: Minh | B85: Question 35 | C85: 0 | D85: 1 | E85: 1 | F85: 1 | G85: 1 | H85: 1 | I85: 1 | J85: 1 | K85: 1 | L85: 1 | M85: 1 | N85: 1 | P85: 2.0075519
A86: Minh | B86: Question 36 | C86: 0 | D86: 1 | E86: 1 | F86: 0 | G86: 1 | H86: 1 | I86: 1 | J86: 'NA | K86: 1 | L86: 1 | M86: 1 | N86: 1 | O86: C: The secondary KC is 'subtracting whole numbers', but the question does not require explicit subtraction—students only need to find the original amount given a percentage decrease (using division and multiplication), not direct subtraction. G: Since there is only one question and no sequence, synergy between primary and secondary KCs cannot be established as required. | P86: 4.703717
A87: Minh | B87: Question 37 | C87: 0 | D87: 1 | E87: 1 | F87: 1 | G87: 1 | H87: 1 | I87: 1 | J87: 1 | K87: 1 | L87: 1 | M87: 1 | N87: 1 | P87: 1.8153539
A88: Minh | B88: Question 38 | C88: 0 | D88: 1 | E88: 1 | F88: 1 | G88: 1 | H88: 1 | I88: 1 | J88: 1 | K88: 1 | L88: 1 | M88: 1 | N88: 1 | P88: 1.1171873
A89: Minh | B89: Question 39 | C89: 0 | D89: 1 | E89: 1 | F89: 1 | G89: 1 | H89: 1 | I89: 1 | J89: 1 | K89: 1 | L89: 1 | M89: 1 | N89: 1 | P89: 1.2480345
A90: Minh | B90: Question 40 | C90: 0 | D90: 1 | E90: 1 | F90: 1 | G90: 1 | H90: 1 | I90: 1 | J90: 1 | K90: 1 | L90: 1 | M90: 1 | N90: 1 | P90: 2.0168538
A91: Minh | B91: Question 41 | C91: 0 | D91: 1 | E91: 1 | F91: 1 | G91: 1 | H91: 1 | I91: 1 | J91: 1 | K91: 1 | L91: 1 | M91: 1 | N91: 1 | P91: 1.512949
A92: Minh | B92: Question 42 | C92: 0 | D92: 1 | E92: 1 | F92: 1 | G92: 1 | H92: 1 | I92: 1 | J92: 1 | K92: 1 | L92: 1 | M92: 1 | N92: 1 | P92: 1.219676
A93: Minh | B93: Question 43 | C93: 0 | D93: 1 | E93: 1 | F93: 1 | G93: 1 | H93: 1 | I93: 1 | J93: 1 | K93: 1 | L93: 1 | M93: 1 | N93: 1 | P93: 1.0737445
A94: Minh | B94: Question 44 | C94: 0 | D94: 1 | E94: 1 | F94: 1 | G94: 1 | H94: 1 | I94: 1 | J94: 1 | K94: 1 | L94: 1 | M94: 1 | N94: 1 | P94: 3.8536854
A95: Minh | B95: Question 45 | C95: 0 | D95: 1 | E95: 1 | F95: 1 | G95: 1 | H95: 1 | I95: 1 | J95: 1 | K95: 1 | L95: 1 | M95: 1 | N95: 1 | P95: 1.5800509
A96: Minh | B96: Question 46 | C96: 0 | D96: 1 | E96: 1 | F96: 1 | G96: 1 | H96: 1 | I96: 1 | J96: 1 | K96: 1 | L96: 1 | M96: 1 | N96: 1 | P96: 1.6086719
A97: Minh | B97: Question 47 | C97: 0 | D97: 1 | E97: 1 | F97: 1 | G97: 1 | H97: 1 | I97: 1 | J97: 1 | K97: 1 | L97: 1 | M97: 1 | N97: 1 | P97: 1.1566715
A98: Minh | B98: Question 48 | C98: 0 | D98: 1 | E98: 1 | F98: 1 | G98: 1 | H98: 1 | I98: 1 | J98: 1 | K98: 1 | L98: 1 | M98: 1 | N98: 1 | P98: 1.1048715
... A103: Minh | B103: Question 53 | C103: 0 | D103: 1 | E103: 1 | F103: 1 | G103: 1 | H103: 1 | I103: 1 | J103: 1 | K103: 1 | L103: 1 | M103: 1 | N103: 1 | P103: 1.8238266
A104: Minh | B104: Question 54 | C104: 0 | D104: 1 | E104: 1 | F104: 1 | G104: 1 | H104: 1 | I104: 1 | J104: 0 | K104: 1 | L104: 1 | M104: 1 | N104: 1 | O104: Synergy = 0: The two parts (median and mode) are separate and independent; calculation of (a) does not require the result of (b) or vice versa. | P104: 1.5303931
...

Sheet services_v8_v1_split_4
A1: Evaluator | B1: Question | C1: status | D1: answerability | E1: primary_kc_alignment | F1: secondary_kc_alignment | G1: topic_alignment | H1: grade_alignment | I1: real_world_feasibility | J1: synergy | K1: clarity | L1: conciseness_and_relevance | M1: language_quality | N1: content_appropriateness | O1: explanation | P1: response_time | Q1: language_quality1
A2: TD | B2: Question 1 | C2: 0 | D2: 1 | E2: 1 | F2: 1 | G2: 1 | H2: 1 | I2: 1 | J2: 1 | K2: 1 | L2: 1 | M2: 1 | N2: 1 | P2: 2.3237884
A3: TD | B3: Question 2 | C3: 0 | D3: 1 | E3: 1 | F3: 1 | G3: 1 | H3: 1 | I3: 1 | J3: 1 | K3: 1 | L3: 1 | M3: 1 | N3: 1 | P3: 1.6036172
A4: TD | B4: Question 3 | C4: 0 | D4: 1 | E4: 1 | F4: 1 | G4: 1 | H4: 1 | I4: 1 | J4: 1 | K4: 1 | L4: 1 | M4: 1 | N4: 1 | P4: 1.1431363
A5: TD | B5: Question 4 | C5: 0 | D5: 1 | E5: 0 | F5: 1 | G5: 1 | H5: 'NA | I5: 1 | J5: 'NA | K5: 1 | L5: 1 | M5: 1 | N5: 1 | O5: Primary KC Alignment: The problem requires 7 × 128 and 5 × 153 multiplications (3 digits × 1 digit and 3 digits × 1 digit), but Primary 3 Singapore syllabus only covers multiplication of up to 3 digits by 1 digit for WHOLE NUMBERS. Multiplying by 128 and 153 both require a 3-digit × 1-digit, but this could be challenging at Primary 3 because students are not expected to directly multiply 3-digit by 1-digit through mental methods, but rather with possible scaffolding steps. However, the question may be slightly advanced as it expects handling of multiples beyond the lower 100s, so partial credit could be argued—but strictly, it would be more appropriate if numbers were capped at lower 3-digit values for Primary 3. | P5: 3.2959087
A6: TD | B6: Question 5 | C6: 0 | D6: 1 | E6: 1 | F6: 1 | G6: 1 | H6: 1 | I6: 1 | J6: 1 | K6: 1 | L6: 1 | M6: 1 | N6: 1 | P6: 1.1317205
A7: TD | B7: Question 6 | C7: 0 | D7: 1 | E7: 1 | F7: 1 | G7: 1 | H7: 1 | I7: 1 | J7: 1 | K7: 1 | L7: 1 | M7: 1 | N7: 1 | P7: 2.1605623
A8: TD | B8: Question 7 | C8: 0 | D8: 1 | E8: 1 | F8: 1 | G8: 1 | H8: 1 | I8: 1 | J8: 1 | K8: 1 | L8: 1 | M8: 1 | N8: 1 | P8: 1.2190931
A9: TD | B9: Question 8 | C9: 0 | D9: 1 | E9: 1 | F9: 1 | G9: 1 | H9: 1 | I9: 1 | J9: 1 | K9: 1 | L9: 1 | M9: 1 | N9: 1 | P9: 1.6791534
A10: TD | B10: Question 9 | C10: 0 | D10: 1 | E10: 1 | F10: 1 | G10: 1 | H10: 1 | I10: 1 | J10: 1 | K10: 1 | L10: 1 | M10: 1 | N10: 1 | P10: 2.318548
A11: TD | B11: Question 10 | C11: 0 | D11: 1 | E11: 1 | F11: 1 | G11: 1 | H11: 1 | I11: 1 | J11: 1 | K11: 1 | L11: 1 | M11: 1 | N11: 1 | P11: 2.1317003
A12: TD | B12: Question 11 | C12: 0 | D12: 1 | E12: 1 | F12: 1 | G12: 1 | H12: 1 | I12: 1 | J12: 1 | K12: 1 | L12: 1 | M12: 1 | N12: 1 | P12: 13.478088
A13: TD | B13: Question 12 | C13: 0 | D13: 1 | E13: 0 | F13: 1 | G13: 1 | H13: 'NA | I13: 1 | J13: 'NA | K13: 1 | L13: 1 | M13: 1 | N13: 1 | O13: Primary KC Alignment and Synergy: The question asks for a COMPARISON between the spending on streaming and cleaning supplies, which leads to forming a ratio or a fraction ([FORMULA] compared to [FORMULA]) rather than the subtraction of the two fractions. Therefore, subtracting unlike fractions is not necessary or used in the solution, so the primary KC is not aligned and there is no synergy present between the primary and secondary KCs. | P13: 2.190896
A14: TD | B14: Question 13 | C14: 0 | D14: 1 | E14: 1 | F14: 1 | G14: 1 | H14: 1 | I14: 1 | J14: 1 | K14: 1 | L14: 1 | M14: 1 | N14: 1 | P14: 1.2049429
A15: TD | B15: Question 14 | C15: 0 | D15: 1 | E15: 1 | F15: 1 | G15: 1 | H15: 1 | I15: 1 | J15: 1 | K15: 1 | L15: 1 | M15: 1 | N15: 1 | P15: 2.1968625
A16: TD | B16: Question 15 | C16: 0 | D16: 1 | E16: 1 | F16: 1 | G16: 1 | H16: 1 | I16: 1 | J16: 1 | K16: 1 | L16: 1 | M16: 1 | N16: 1 | P16: 1.8490651
A17: TD | B17: Question 16 | C17: 0 | D17: 1 | E17: 1 | F17: 1 | G17: 1 | H17: 1 | I17: 1 | J17: 1 | K17: 1 | L17: 1 | M17: 1 | N17: 1 | P17: 1.2850058
A18: TD | B18: Question 17 | C18: 0 | D18: 1 | E18: 1 | F18: 1 | G18: 1 | H18: 1 | I18: 1 | J18: 1 | K18: 1 | L18: 1 | M18: 1 | N18: 1 | P18: 1.5740914
A19: TD | B19: Question 18 | C19: 0 | D19: 1 | E19: 0 | F19: 1 | G19: 1 | H19: 'NA | I19: 1 | J19: 'NA | K19: 1 | L19: 1 | M19: 1 | N19: 1 | O19: Primary KC Alignment: The division required to solve part (a) involves dividing $38.75 by 5, which can result in a value with up to 3 decimal places (7.75), but the context reasonably limits it to 2 decimal places; however, part (b) asks to compare $9.725 per room (3 decimal places), which is not in line with Primary 4 knowledge, as official Singapore syllabus up to Primary 4 only expects working with decimals to 2 decimal places for division. Grade Alignment: Based on the official Singapore Math syllabus, comparing and ordering decimals up to 3 decimal places is not expected at Primary 4, which is appropriate for comparing and ordering decimals up to only 2 decimal places. | P19: 8.2338071
A20: TD | B20: Question 19 | C20: 0 | D20: 1 | E20: 1 | F20: 1 | G20: 1 | H20: 1 | I20: 1 | J20: 1 | K20: 1 | L20: 1 | M20: 1 | N20: 1 | P20: 1.2660003
A21: TD | B21: Question 20 | C21: 0 | D21: 1 | E21: 1 | F21: 1 | G21: 1 | H21: 1 | I21: 1 | J21: 1 | K21: 1 | L21: 1 | M21: 1 | N21: 1 | P21: 1.3131759
A22: TD | B22: Question 21 | C22: 0 | D22: 1 | E22: 1 | F22: 1 | G22: 1 | H22: 1 | I22: 1 | J22: 1 | K22: 1 | L22: 1 | M22: 1 | N22: 1 | P22: 1.3503015
A23: TD | B23: Question 22 | C23: 0 | D23: 1 | E23: 1 | F23: 0 | G23: 1 | H23: 1 | I23: 1 | J23: 'NA | K23: 1 | L23: 1 | M23: 1 | N23: 1 | O23: Secondary KC Alignment (0): The problem only requires multiplying fractions and a whole number, and finding a simple difference. It does not actually require comparing and ordering two fractions directly for its solution. Synergy (0): The first part's result is simply used as a value in a difference calculation, but no comparison of fractions (secondary KC) is used, so there is no meaningful synergy between primary and secondary. | P23: 2.0593617
A24: TD | B24: Question 23 | C24: 0 | D24: 1 | E24: 1 | F24: 1 | G24: 1 | H24: 1 | I24: 1 | J24: 1 | K24: 1 | L24: 1 | M24: 1 | N24: 1 | P24: 1.2655065
A25: TD | B25: Question 24 | C25: 0 | D25: 1 | E25: 1 | F25: 1 | G25: 1 | H25: 1 | I25: 1 | J25: 1 | K25: 1 | L25: 1 | M25: 1 | N25: 1 | P25: 1.1676579
A26: TD | B26: Question 25 | C26: 0 | D26: 1 | E26: 1 | F26: 1 | G26: 1 | H26: 1 | I26: 1 | J26: 1 | K26: 1 | L26: 1 | M26: 1 | N26: 1 | P26: 1.2662535
A27: TD | B27: Question 26 | C27: 0 | D27: 1 | E27: 0 | F27: 1 | G27: 1 | H27: 'NA | I27: 1 | J27: 'NA | K27: 1 | L27: 1 | M27: 1 | N27: 1 | O27: Primary KC Alignment: The multiplication in part (a) requires multiplying an improper fraction by a whole number (not by another improper fraction as intended by the metadata: 'multiplying two improper fractions'). | P27: 2.3791063
A28: TD | B28: Question 27 | C28: 0 | D28: 1 | E28: 1 | F28: 1 | G28: 1 | H28: 1 | I28: 1 | J28: 1 | K28: 1 | L28: 1 | M28: 1 | N28: 1 | P28: 1.5917971
A29: TD | B29: Question 28 | C29: 0 | D29: 1 | E29: 1 | F29: 1 | G29: 1 | H29: 1 | I29: 1 | J29: 1 | K29: 1 | L29: 1 | M29: 1 | N29: 1 | P29: 1.1366558
A30: TD | B30: Question 29 | C30: 0 | D30: 1 | E30: 1 | F30: 1 | G30: 1 | H30: 1 | I30: 1 | J30: 1 | K30: 1 | L30: 1 | M30: 1 | N30: 1 | P30: 1.282769
A31: TD | B31: Question 30 | C31: 0 | D31: 1 | E31: 0 | F31: 1 | G31: 1 | H31: 'NA | I31: 1 | J31: 'NA | K31: 1 | L31: 1 | M31: 1 | N31: 1 | O31: Primary KC Alignment: The main calculation in (a) is $3.75 [FORMULA] 12$, which does not involve multiplying by 10, 100, 1000 or their multiples, so the specific intended skill is not required. Synergy: The two parts (a) and (b) are not interdependent; the answer from (a) is not needed for (b), thus there is no synergy between the KC's. | P31: 4.1398644
A32: TD | B32: Question 31 | C32: 0 | D32: 1 | E32: 0 | F32: 1 | G32: 1 | H32: 'NA | I32: 1 | J32: 'NA | K32: 1 | L32: 1 | M32: 1 | N32: 1 | O32: Primary KC Alignment: The focus is on multiplication of decimals by whole numbers (3.850 x 140), but the intent was 'multiplying decimals (up to 3 decimal places) by 10, 100, 1000 and their multiples.' In this problem, students do not multiply specifically by 10/100/1000 or their multiples; instead, they multiply by 140 and by 1.4. The multiplication by 140 is not strictly aligning with the target KC of applying scalar multiples of 10/100/1000. The question, therefore, does not require the intended KC as necessitated. | P32: 3.2442324
A33: TD | B33: Question 32 | C33: 0 | D33: 1 | E33: 1 | F33: 1 | G33: 1 | H33: 1 | I33: 1 | J33: 1 | K33: 1 | L33: 1 | M33: 1 | N33: 1 | P33: 1.7444165
A34: TD | B34: Question 33 | C34: 0 | D34: 1 | E34: 0 | F34: 1 | G34: 1 | H34: 'NA | I34: 1 | J34: 'NA | K34: 1 | L34: 1 | M34: 1 | N34: 1 | O34: Primary KC Alignment: The division $12.500 [FORMULA] 1000$ for (a) does not align with the intended KC, as Primary 5 curriculum focuses on numbers with up to 2 decimal places and does not use notation like $[FORMULA]12.500$. This result also requires handling currency values beyond expected decimals for this level. Grade Alignment: Same issue as above. Handling $12.500$ is not typical or expected for Primary 5, as the decimal notation is non-standard in Singapore primary curriculum. A more suitable figure would be $12.50$. | P34: 3.0748825
A35: TD | B35: Question 34 | C35: 0 | D35: 1 | E35: 1 | F35: 1 | G35: 1 | H35: 1 | I35: 1 | J35: 1 | K35: 1 | L35: 1 | M35: 1 | N35: 1 | P35: 1.6374686
A36: TD | B36: Question 35 | C36: 0 | D36: 1 | E36: 1 | F36: 1 | G36: 1 | H36: 1 | I36: 1 | J36: 1 | K36: 1 | L36: 1 | M36: 1 | N36: 1 | P36: 1.1745088
A37: TD | B37: Question 36 | C37: 0 | D37: 1 | E37: 1 | F37: 1 | G37: 1 | H37: 1 | I37: 1 | J37: 1 | K37: 1 | L37: 1 | M37: 1 | N37: 1 | P37: 1.1860778
A38: TD | B38: Question 37 | C38: 0 | D38: 1 | E38: 0 | F38: 0 | G38: 1 | H38: 'NA | I38: 1 | J38: 'NA | K38: 1 | L38: 1 | M38: 1 | N38: 1 | O38: Primary KC Alignment: The problem involves dividing a fraction by a fraction ($[FORMULA] [FORMULA] [FORMULA]$), not dividing a proper fraction by a whole number as intended. Secondary KC Alignment: The problem requires addition of whole numbers (loads), not addition of fractions. | P38: 1.7388387
A39: TD | B39: Question 38 | C39: 0 | D39: 1 | E39: 1 | F39: 1 | G39: 1 | H39: 1 | I39: 1 | J39: 1 | K39: 1 | L39: 1 | M39: 1 | N39: 1 | P39: 1.654583
A40: TD | B40: Question 39 | C40: 0 | D40: 1 | E40: 1 | F40: 1 | G40: 1 | H40: 1 | I40: 1 | J40: 1 | K40: 1 | L40: 1 | M40: 1 | N40: 1 | P40: 1.7214978
A41: TD | B41: Question 40 | C41: 0 | D41: 0 | E41: 'NA | F41: 'NA | G41: 'NA | H41: 'NA | I41: 'NA | J41: 'NA | K41: 'NA | L41: 'NA | M41: 1 | N41: 'NA | O41: answerability: - The information is incomplete/illogical: If 'each cleaning session costs \( [FORMULA] \) of the amount she has', then the cost of one session depends on Maya's total money, which is not fixed for each session she attends. After one session, the amount she has left changes, so the cost of the next session changes, forming a recursive scenario, not a straightforward division problem as intended, making the problem unanswerable as a straightforward P6 division.[FORMULA]_kc_alignment: - The division of $60 by a fraction as a cost per session is not mathematically valid for the scenario as worded; the price of each session is not a fixed dollar amount, and division of 60 by 3/4 does not represent the correct solution as the cost is always relative, not constant.[FORMULA]_world_feasibility: - In real contexts, services have a fixed cost per unit/session; pricing a session as a fraction of one's remaining money is illogical and does not occur in real home cleaning service scenarios. | P41: 8.3567057 | Q41: 'NA
A42: TD | B42: Question 41 | C42: 0 | D42: 1 | E42: 1 | F42: 1 | G42: 1 | H42: 1 | I42: 1 | J42: 1 | K42: 1 | L42: 1 | M42: 1 | N42: 1 | P42: 1.1299961
A43: TD | B43: Question 42 | C43: 0 | D43: 1 | E43: 1 | F43: 1 | G43: 1 | H43: 1 | I43: 1 | J43: 1 | K43: 1 | L43: 1 | M43: 1 | N43: 1 | P43: 1.1838911
A44: TD | B44: Question 43 | C44: 0 | D44: 1 | E44: 1 | F44: 1 | G44: 1 | H44: 1 | I44: 1 | J44: 1 | K44: 1 | L44: 1 | M44: 1 | N44: 1 | P44: 1.3413615
A45: TD | B45: Question 44 | C45: 0 | D45: 1 | E45: 1 | F45: 1 | G45: 1 | H45: 1 | I45: 1 | J45: 1 | K45: 1 | L45: 1 | M45: 1 | N45: 1 | P45: 1.4588068
A46: TD | B46: Question 45 | C46: 0 | D46: 1 | E46: 1 | F46: 1 | G46: 1 | H46: 1 | I46: 1 | J46: 1 | K46: 1 | L46: 1 | M46: 1 | N46: 1 | P46: 1.1669731
A47: TD | B47: Question 46 | C47: 0 | D47: 1 | E47: 1 | F47: 1 | G47: 1 | H47: 1 | I47: 1 | J47: 1 | K47: 1 | L47: 1 | M47: 1 | N47: 1 | P47: 1.1124532
A48: TD | B48: Question 47 | C48: 0 | D48: 1 | E48: 1 | F48: 1 | G48: 1 | H48: 1 | I48: 1 | J48: 1 | K48: 1 | L48: 1 | M48: 1 | N48: 1 | P48: 1.4712
A49: TD | B49: Question 48 | C49: 0 | D49: 1 | E49: 1 | F49: 1 | G49: 1 | H49: 1 | I49: 1 | J49: 1 | K49: 1 | L49: 1 | M49: 1 | N49: 1 | P49: 1.6125691
A50: TD | B50: Question 49 | C50: 0 | D50: 1 | E50: 1 | F50: 1 | G50: 1 | H50: 1 | I50: 1 | J50: 1 | K50: 1 | L50: 1 | M50: 1 | N50: 1 | P50: 1.1622667
A51: Minh | B51: Question 1 | C51: 0 | D51: 1 | E51: 1 | F51: 1 | G51: 1 | H51: 1 | I51: 1 | J51: 0 | K51: 1 | L51: 1 | M51: 1 | N51: 1 | O51: synergy: The two questions (a) and (b) are unrelated in that the answer to (a) is not needed for (b), nor does (b) depend on the result of (a). They are both about the same scenario but do not exhibit the required input-output dependence for full synergy. | P51: 2.2552636
A52: Minh | B52: Question 2 | C52: 0 | D52: 1 | E52: 1 | F52: 1 | G52: 1 | H52: 1 | I52: 1 | J52: 1 | K52: 1 | L52: 1 | M52: 1 | N52: 1 | P52: 1.9394455
A53: Minh | B53: Question 3 | C53: 0 | D53: 1 | E53: 1 | F53: 1 | G53: 1 | H53: 1 | I53: 1 | J53: 1 | K53: 1 | L53: 1 | M53: 1 | N53: 1 | P53: 1.2115867
A54: Minh | B54: Question 4 | C54: 0 | D54: 1 | E54: 1 | F54: 1 | G54: 1 | H54: 1 | I54: 1 | J54: 1 | K54: 1 | L54: 1 | M54: 1 | N54: 1 | P54: 1.2529261
A55: Minh | B55: Question 5 | C55: 0 | D55: 1 | E55: 1 | F55: 1 | G55: 1 | H55: 1 | I55: 1 | J55: 1 | K55: 1 | L55: 1 | M55: 1 | N55: 1 | P55: 1.9368379
A56: Minh | B56: Question 6 | C56: 0 | D56: 1 | E56: 1 | F56: 1 | G56: 1 | H56: 1 | I56: 1 | J56: 1 | K56: 1 | L56: 1 | M56: 1 | N56: 1 | P56: 1.1472199
A57: Minh | B57: Question 7 | C57: 0 | D57: 1 | E57: 1 | F57: 1 | G57: 1 | H57: 1 | I57: 1 | J57: 1 | K57: 1 | L57: 1 | M57: 1 | N57: 1 | P57: 1.8944166
A58: Minh | B58: Question 8 | C58: 0 | D58: 1 | E58: 1 | F58: 1 | G58: 1 | H58: 1 | I58: 1 | J58: 1 | K58: 1 | L58: 1 | M58: 1 | N58: 1 | P58: 1.4758406
A59: Minh | B59: Question 9 | C59: 0 | D59: 1 | E59: 1 | F59: 1 | G59: 1 | H59: 1 | I59: 1 | J59: 1 | K59: 1 | L59: 1 | M59: 1 | N59: 1 | P59: 1.5211737
A60: Minh | B60: Question 10 | C60: 0 | D60: 1 | E60: 1 | F60: 1 | G60: 1 | H60: 1 | I60: 1 | J60: 1 | K60: 1 | L60: 1 | M60: 1 | N60: 1 | P60: 1.6720762
A61: Minh | B61: Question 11 | C61: 0 | D61: 1 | E61: 1 | F61: 1 | G61: 1 | H61: 1 | I61: 1 | J61: 1 | K61: 1 | L61: 1 | M61: 1 | N61: 1 | P61: 1.7284682
A62: Minh | B62: Question 12 | C62: 0 | D62: 1 | E62: 1 | F62: 1 | G62: 1 | H62: 1 | I62: 1 | J62: 1 | K62: 1 | L62: 1 | M62: 1 | N62: 1 | P62: 1.1885071
A63: Minh | B63: Question 13 | C63: 0 | D63: 1 | E63: 1 | F63: 1 | G63: 1 | H63: 1 | I63: 1 | J63: 1 | K63: 1 | L63: 1 | M63: 1 | N63: 1 | P63: 1.7229571
A64: Minh | B64: Question 14 | C64: 0 | D64: 1 | E64: 1 | F64: 1 | G64: 1 | H64: 1 | I64: 1 | J64: 1 | K64: 1 | L64: 1 | M64: 1 | N64: 1 | P64: 1.1373374
A65: Minh | B65: Question 15 | C65: 0 | D65: 1 | E65: 0 | F65: 1 | G65: 1 | H65: 'NA | I65: 0 | J65: 'NA | K65: 1 | L65: 1 | M65: 1 | N65: 1 | O65: Primary KC Alignment: The premium movie streaming subscription is $13.299 per month, which involves adding a 3-decimal-place number to a 2-decimal-place number. The intended KC specifies adding decimals up to 2 decimal places only. Grade Alignment: Primary 4 students in Singapore are typically expected to add decimals up to 2 decimal places only, not 3. Real-World Feasibility: Service prices are rarely, if ever, listed as $13.299 per month; in real scenarios, subscription prices are typically rounded to 2 decimal places (e.g., $13.29 or $13.30), making this unlikely in a real-world context. | P65: 7.9630566
A66: Minh | B66: Question 16 | C66: 0 | D66: 1 | E66: 1 | F66: 1 | G66: 1 | H66: 1 | I66: 1 | J66: 1 | K66: 1 | L66: 1 | M66: 1 | N66: 1 | P66: 1.2570672
A67: Minh | B67: Question 17 | C67: 0 | D67: 1 | E67: 0 | F67: 1 | G67: 1 | H67: 'NA | I67: 1 | J67: 'NA | K67: 1 | L67: 1 | M67: 1 | N67: 1 | O67: Primary KC: - Division is not dividing a decimal by a 1-digit whole number as specified (it is $24 [FORMULA] 3.75$, a whole number divided by a decimal), which does not match the intended knowledge component. The question should require dividing a decimal (up to 2 d.p.) by a 1-digit whole number, e.g., $3.75 [FORMULA] 3$. | P67: 2.9327958
A68: Minh | B68: Question 18 | C68: 0 | D68: 1 | E68: 1 | F68: 1 | G68: 1 | H68: 1 | I68: 1 | J68: 1 | K68: 1 | L68: 1 | M68: 1 | N68: 1 | P68: 1.1409655
A69: Minh | B69: Question 19 | C69: 0 | D69: 1 | E69: 1 | F69: 1 | G69: 1 | H69: 1 | I69: 1 | J69: 1 | K69: 1 | L69: 1 | M69: 1 | N69: 1 | P69: 1.2139571
A70: Minh | B70: Question 20 | C70: 0 | D70: 1 | E70: 1 | F70: 1 | G70: 1 | H70: 1 | I70: 1 | J70: 1 | K70: 1 | L70: 1 | M70: 1 | N70: 1 | P70: 1.8982878
A71: Minh | B71: Question 21 | C71: 0 | D71: 1 | E71: 1 | F71: 1 | G71: 1 | H71: 1 | I71: 1 | J71: 1 | K71: 1 | L71: 1 | M71: 1 | N71: 1 | P71: 1.1568811
A72: Minh | B72: Question 22 | C72: 0 | D72: 1 | E72: 1 | F72: 1 | G72: 1 | H72: 1 | I72: 1 | J72: 1 | K72: 1 | L72: 1 | M72: 1 | N72: 1 | P72: 1.601285
A73: Minh | B73: Question 23 | C73: 0 | D73: 1 | E73: 1 | F73: 1 | G73: 1 | H73: 1 | I73: 1 | J73: 1 | K73: 1 | L73: 1 | M73: 1 | N73: 1 | P73: 1.3017964
A74: Minh | B74: Question 24 | C74: 0 | D74: 1 | E74: 1 | F74: 1 | G74: 1 | H74: 1 | I74: 1 | J74: 1 | K74: 1 | L74: 1 | M74: 1 | N74: 1 | P74: 1.2660422
A75: Minh | B75: Question 25 | C75: 0 | D75: 1 | E75: 1 | F75: 1 | G75: 1 | H75: 1 | I75: 1 | J75: 1 | K75: 1 | L75: 1 | M75: 1 | N75: 1 | P75: 1.3166392
A76: Minh | B76: Question 26 | C76: 0 | D76: 1 | E76: 1 | F76: 1 | G76: 1 | H76: 1 | I76: 1 | J76: 1 | K76: 1 | L76: 1 | M76: 1 | N76: 1 | P76: 1.73984
A77: Minh | B77: Question 27 | C77: 0 | D77: 1 | E77: 0 | F77: 1 | G77: 1 | H77: 'NA | I77: 1 | J77: 'NA | K77: 1 | L77: 1 | M77: 1 | N77: 1 | O77: Primary KC Alignment: The intended primary knowledge component is multiplying decimals (up to 3 decimal places) by 10, 100, 1000 and their multiples. However, the problem asks students to multiply $6.125 by 100 (which fits the KC), but the usual intent with 'multiples of 10, 100, 1000' in the Singapore syllabus is to focus on patterns such as moving the decimal point, not just general multiplication by any number that is a multiple of these values. Since the question simply has '100 months' and does not test students' understanding of the pattern of shifting the decimal, but rather just wants them to multiply by 100, this is borderline. However, if strictly aligned with the KS—the word problem only happens to use 100 but not in a context that elucidates or requires the understanding of multiplying by 10, 100, or 1000 (for process, pattern, or place value shifts), so I am scoring this as 0. | P77: 5.3828211
A78: Minh | B78: Question 28 | C78: 0 | D78: 1 | E78: 1 | F78: 1 | G78: 1 | H78: 1 | I78: 1 | J78: 1 | K78: 1 | L78: 1 | M78: 1 | N78: 1 | P78: 1.6858323
A79: Minh | B79: Question 29 | C79: 0 | D79: 1 | E79: 1 | F79: 1 | G79: 1 | H79: 1 | I79: 1 | J79: 1 | K79: 1 | L79: 1 | M79: 1 | N79: 1 | P79: 1.1246591
A80: Minh | B80: Question 30 | C80: 0 | D80: 1 | E80: 1 | F80: 0 | G80: 1 | H80: 1 | I80: 1 | J80: 'NA | K80: 1 | L80: 1 | M80: 1 | N80: 1 | O80: Secondary KC Alignment: The problem does not require converting a measurement from a larger unit in decimal form to a smaller unit (e.g., hours to minutes), as all calculations can be completed using decimal hours. Synergy: The secondary knowledge component (unit conversion) is not needed in tandem with the primary (finding rate), so there is no synergy between the two. | P80: 2.1144314
A81: Minh | B81: Question 31 | C81: 0 | D81: 1 | E81: 1 | F81: 1 | G81: 1 | H81: 1 | I81: 1 | J81: 1 | K81: 1 | L81: 1 | M81: 1 | N81: 1 | P81: 1.5026548
A82: Minh | B82: Question 32 | C82: 0 | D82: 1 | E82: 1 | F82: 1 | G82: 1 | H82: 1 | I82: 1 | J82: 1 | K82: 1 | L82: 1 | M82: 1 | N82: 1 | P82: 1.1044924
A83: Minh | B83: Question 33 | C83: 0 | D83: 1 | E83: 1 | F83: 1 | G83: 1 | H83: 1 | I83: 1 | J83: 1 | K83: 1 | L83: 1 | M83: 1 | N83: 1 | P83: 1.0982618
A84: Minh | B84: Question 34 | C84: 0 | D84: 1 | E84: 1 | F84: 1 | G84: 1 | H84: 1 | I84: 1 | J84: 1 | K84: 1 | L84: 1 | M84: 1 | N84: 1 | P84: 1.1739316
A85: Minh | B85: Question 35 | C85: 0 | D85: 1 | E85: 1 | F85: 1 | G85: 1 | H85: 1 | I85: 1 | J85: 1 | K85: 1 | L85: 1 | M85: 1 | N85: 1 | P85: 1.6230347
A86: Minh | B86: Question 36 | C86: 0 | D86: 1 | E86: 1 | F86: 0 | G86: 1 | H86: 1 | I86: 1 | J86: 'NA | K86: 1 | L86: 1 | M86: 1 | N86: 1 | O86: 3: The problem does not require the use of subtraction with whole numbers. The main computation involves finding the original price given the discounted price and the percentage decrease, which is pure percentage calculation. 7: Because the Secondary Knowledge Component is not actually required, synergy cannot be established between the KC components. | P86: 3.4595983
A87: Minh | B87: Question 37 | C87: 0 | D87: 1 | E87: 1 | F87: 1 | G87: 1 | H87: 1 | I87: 1 | J87: 1 | K87: 1 | L87: 1 | M87: 1 | N87: 1 | P87: 1.1441932
A88: Minh | B88: Question 38 | C88: 0 | D88: 1 | E88: 1 | F88: 1 | G88: 1 | H88: 1 | I88: 1 | J88: 1 | K88: 1 | L88: 1 | M88: 1 | N88: 1 | P88: 1.1525061
A89: Minh | B89: Question 39 | C89: 0 | D89: 1 | E89: 1 | F89: 1 | G89: 1 | H89: 1 | I89: 1 | J89: 1 | K89: 1 | L89: 1 | M89: 1 | N89: 1 | P89: 1.2703421
A90: Minh | B90: Question 40 | C90: 0 | D90: 1 | E90: 1 | F90: 1 | G90: 1 | H90: 1 | I90: 1 | J90: 1 | K90: 1 | L90: 1 | M90: 1 | N90: 1 | P90: 1.146023
A91: Minh | B91: Question 41 | C91: 0 | D91: 1 | E91: 1 | F91: 1 | G91: 1 | H91: 1 | I91: 1 | J91: 1 | K91: 1 | L91: 1 | M91: 1 | N91: 1 | P91: 2.0397906
A92: Minh | B92: Question 42 | C92: 0 | D92: 1 | E92: 1 | F92: 1 | G92: 1 | H92: 1 | I92: 1 | J92: 1 | K92: 1 | L92: 1 | M92: 1 | N92: 1 | P92: 1.6616676
A93: Minh | B93: Question 43 | C93: 0 | D93: 1 | E93: 1 | F93: 1 | G93: 1 | H93: 1 | I93: 1 | J93: 1 | K93: 1 | L93: 1 | M93: 1 | N93: 1 | P93: 1.1490407
A94: Minh | B94: Question 44 | C94: 0 | D94: 1 | E94: 1 | F94: 1 | G94: 1 | H94: 1 | I94: 1 | J94: 1 | K94: 1 | L94: 1 | M94: 1 | N94: 1 | P94: 1.1688175
A95: Minh | B95: Question 45 | C95: 0 | D95: 1 | E95: 1 | F95: 1 | G95: 1 | H95: 1 | I95: 1 | J95: 1 | K95: 1 | L95: 1 | M95: 1 | N95: 1 | P95: 1.5153906
A96: Minh | B96: Question 46 | C96: 0 | D96: 1 | E96: 1 | F96: 1 | G96: 1 | H96: 1 | I96: 1 | J96: 1 | K96: 1 | L96: 1 | M96: 1 | N96: 1 | P96: 1.376847
A97: Minh | B97: Question 47 | C97: 0 | D97: 1 | E97: 1 | F97: 1 | G97: 1 | H97: 1 | I97: 1 | J97: 1 | K97: 1 | L97: 1 | M97: 1 | N97: 1 | P97: 1.2523761
A98: Minh | B98: Question 48 | C98: 0 | D98: 1 | E98: 1 | F98: 1 | G98: 1 | H98: 1 | I98: 1 | J98: 1 | K98: 1 | L98: 1 | M98: 1 | N98: 1 | P98: 1.1240492
... A103: Minh | B103: Question 53 | C103: 0 | D103: 1 | E103: 1 | F103: 1 | G103: 1 | H103: 1 | I103: 1 | J103: 1 | K103: 1 | L103: 1 | M103: 1 | N103: 1 | P103: 1.2354002
A104: Minh | B104: Question 54 | C104: 0 | D104: 1 | E104: 1 | F104: 1 | G104: 1 | H104: 1 | I104: 1 | J104: 0 | K104: 1 | L104: 1 | M104: 1 | N104: 1 | O104: 7: The two parts (a) and (b) do not require results from each other to solve. The median and mode are each calculated independently from the same data set, so there is no synergy between the primary and secondary knowledge components. | P104: 5.3184662
...

Sheet services_v8_v1_split_5
A1: Evaluator | B1: Question | C1: status | D1: answerability | E1: primary_kc_alignment | F1: secondary_kc_alignment | G1: topic_alignment | H1: grade_alignment | I1: real_world_feasibility | J1: synergy | K1: clarity | L1: conciseness_and_relevance | M1: language_quality | N1: content_appropriateness | O1: explanation | P1: response_time | Q1: language_quality1
A2: TD | B2: Question 1 | C2: 0 | D2: 1 | E2: 1 | F2: 1 | G2: 1 | H2: 1 | I2: 1 | J2: 1 | K2: 1 | L2: 1 | M2: 1 | N2: 1 | P2: 2.892709
A3: TD | B3: Question 2 | C3: 0 | D3: 1 | E3: 1 | F3: 1 | G3: 1 | H3: 1 | I3: 1 | J3: 1 | K3: 1 | L3: 1 | M3: 1 | N3: 1 | P3: 1.5651164
A4: TD | B4: Question 3 | C4: 0 | D4: 1 | E4: 1 | F4: 1 | G4: 1 | H4: 1 | I4: 1 | J4: 1 | K4: 1 | L4: 1 | M4: 1 | N4: 1 | P4: 1.1845906
A5: TD | B5: Question 4 | C5: 0 | D5: 1 | E5: 1 | F5: 1 | G5: 1 | H5: 1 | I5: 1 | J5: 1 | K5: 1 | L5: 1 | M5: 1 | N5: 1 | P5: 1.3986135
A6: TD | B6: Question 5 | C6: 0 | D6: 1 | E6: 1 | F6: 1 | G6: 1 | H6: 1 | I6: 1 | J6: 1 | K6: 1 | L6: 1 | M6: 1 | N6: 1 | P6: 2.2525892
A7: TD | B7: Question 6 | C7: 0 | D7: 1 | E7: 1 | F7: 1 | G7: 1 | H7: 1 | I7: 1 | J7: 1 | K7: 1 | L7: 1 | M7: 1 | N7: 1 | P7: 1.3041592
A8: TD | B8: Question 7 | C8: 0 | D8: 1 | E8: 1 | F8: 1 | G8: 1 | H8: 1 | I8: 1 | J8: 1 | K8: 1 | L8: 1 | M8: 1 | N8: 1 | P8: 2.1331723
A9: TD | B9: Question 8 | C9: 0 | D9: 1 | E9: 1 | F9: 1 | G9: 1 | H9: 1 | I9: 1 | J9: 1 | K9: 1 | L9: 1 | M9: 1 | N9: 1 | P9: 1.1178393
A10: TD | B10: Question 9 | C10: 0 | D10: 1 | E10: 1 | F10: 1 | G10: 1 | H10: 1 | I10: 1 | J10: 1 | K10: 1 | L10: 1 | M10: 1 | N10: 1 | P10: 1.2017143
A11: TD | B11: Question 10 | C11: 0 | D11: 1 | E11: 1 | F11: 1 | G11: 1 | H11: 1 | I11: 1 | J11: 1 | K11: 1 | L11: 1 | M11: 1 | N11: 1 | P11: 1.3063612
A12: TD | B12: Question 11 | C12: 0 | D12: 1 | E12: 1 | F12: 1 | G12: 1 | H12: 1 | I12: 1 | J12: 0 | K12: 1 | L12: 1 | M12: 1 | N12: 1 | O12: 7: The two sub-questions are independent; solving Q1 (addition) is not required to answer Q2 (comparison and ordering), and vice versa, so Primary KC and Secondary KC are not used in tandem. | P12: 2.1675339
A13: TD | B13: Question 12 | C13: 0 | D13: 1 | E13: 0 | F13: 1 | G13: 1 | H13: 'NA | I13: 1 | J13: 'NA | K13: 1 | L13: 1 | M13: 1 | N13: 1 | O13: Primary KC Alignment: The problem asks for 'What fraction of her allowance did Aisha spend on the streaming service compared to the cleaning supplies?' This leads students to find the ratio (i.e., division) of the two fractions, not the difference (subtraction), which is the intended primary knowledge component.Synergy: The intended synergy was that students would need to subtract the fractions and then simplify, but since the problem only asks for the ratio and then to simplify, only the secondary KC is necessary. | P13: 4.1346498
A14: TD | B14: Question 13 | C14: 0 | D14: 1 | E14: 1 | F14: 1 | G14: 1 | H14: 0 | I14: 0 | J14: 1 | K14: 1 | L14: 1 | M14: 1 | N14: 1 | O14: E: The receipts display totals with 3 decimal places (e.g., $36.450$), but the sums of actual service charges (money) should always be shown up to only 2 decimal places. Singapore Primary 4 students are only expected to work with money in 2 decimal places. This makes the question too advanced for this grade. F: In real life, payment receipts for money are never written as $36.450$; monetary values are recorded with 2 decimal places (i.e., $36.45$). Having 3 decimal places for dollars and cents is not a typical real-world scenario for receipts. | P14: 4.0231805
A15: TD | B15: Question 14 | C15: 0 | D15: 1 | E15: 1 | F15: 1 | G15: 1 | H15: 1 | I15: 1 | J15: 1 | K15: 1 | L15: 1 | M15: 1 | N15: 1 | P15: 1.2098517
A16: TD | B16: Question 15 | C16: 0 | D16: 1 | E16: 1 | F16: 1 | G16: 1 | H16: 1 | I16: 1 | J16: 1 | K16: 1 | L16: 1 | M16: 1 | N16: 1 | P16: 2.3098817
A17: TD | B17: Question 16 | C17: 0 | D17: 1 | E17: 1 | F17: 1 | G17: 1 | H17: 1 | I17: 1 | J17: 1 | K17: 1 | L17: 1 | M17: 1 | N17: 1 | P17: 1.9737151
A18: TD | B18: Question 17 | C18: 0 | D18: 1 | E18: 1 | F18: 1 | G18: 1 | H18: 1 | I18: 1 | J18: 1 | K18: 1 | L18: 1 | M18: 1 | N18: 1 | P18: 1.2898533
A19: TD | B19: Question 18 | C19: 0 | D19: 1 | E19: 0 | F19: 1 | G19: 1 | H19: 'NA | I19: 1 | J19: 'NA | K19: 1 | L19: 1 | M19: 1 | N19: 1 | O19: Primary KC Alignment: The expected division involves dividing $38.75 by 5. However, the quotient is $7.75, not a decimal with up to 2 decimal places divided by a 1-digit whole number, so it fits at first glance. BUT, part (b) introduces comparison of 3 decimal places ($9.725), which exceeds Primary 4 expectations for dividing decimals up to 2 decimal places. Grade Alignment: The presence of $9.725 (requiring understanding of decimals to 3 decimal places), and comparison/ordering at that precision, is beyond typical Primary 4 standards in Singapore. Students are only expected to work with decimals up to 2 decimal places in both calculations and comparisons at this level. | P19: 2.6584413
A20: TD | B20: Question 19 | C20: 0 | D20: 1 | E20: 1 | F20: 1 | G20: 1 | H20: 1 | I20: 1 | J20: 1 | K20: 1 | L20: 1 | M20: 1 | N20: 1 | P20: 1.1681368
A21: TD | B21: Question 20 | C21: 0 | D21: 1 | E21: 1 | F21: 1 | G21: 1 | H21: 1 | I21: 1 | J21: 1 | K21: 1 | L21: 1 | M21: 1 | N21: 1 | P21: 1.8566313
A22: TD | B22: Question 21 | C22: 0 | D22: 1 | E22: 1 | F22: 1 | G22: 1 | H22: 1 | I22: 1 | J22: 0 | K22: 1 | L22: 1 | M22: 1 | N22: 1 | O22: Synergy = 0: The questions (a) subtraction and (b) ordering are independent and do not require results from each other; solving (a) is not needed for (b), and vice versa. | P22: 3.3182828
A23: TD | B23: Question 22 | C23: 0 | D23: 1 | E23: 1 | F23: 0 | G23: 1 | H23: 1 | I23: 1 | J23: 'NA | K23: 1 | L23: 1 | M23: 1 | N23: 1 | O23: C3: The Secondary KC requires explicit need for comparing and ordering fractions. In this word problem, part (b) involves finding out how many uniforms Mrs Lim's friend laundered (which is less), but students only subtract the smaller (friend) from the larger (Mrs Lim) to answer 'who laundered more and by how many'. This does not require any actual comparison or ordering of fractions, as it is clear from context that Mrs Lim's friend laundered less (since [FORMULA] < 1). There is no question or situation requiring explicit comparison of two fractions. | P23: 3.0460413
A24: TD | B24: Question 23 | C24: 0 | D24: 1 | E24: 1 | F24: 1 | G24: 1 | H24: 1 | I24: 1 | J24: 1 | K24: 1 | L24: 1 | M24: 1 | N24: 1 | P24: 2.0433326
A25: TD | B25: Question 24 | C25: 0 | D25: 1 | E25: 1 | F25: 1 | G25: 1 | H25: 1 | I25: 1 | J25: 1 | K25: 1 | L25: 1 | M25: 1 | N25: 1 | P25: 1.8533928
A26: TD | B26: Question 25 | C26: 0 | D26: 1 | E26: 1 | F26: 1 | G26: 1 | H26: 1 | I26: 1 | J26: 1 | K26: 1 | L26: 1 | M26: 1 | N26: 1 | P26: 1.1325202
A27: TD | B27: Question 26 | C27: 0 | D27: 1 | E27: 0 | F27: 1 | G27: 1 | H27: 'NA | I27: 1 | J27: 'NA | K27: 1 | L27: 1 | M27: 1 | N27: 1 | O27: Primary KC Alignment: The problem requires multiplying a fraction by a whole number ([FORMULA] [FORMULA] 3), not multiplying two improper fractions as intended. Therefore, the main intent of practicing multiplication of two improper fractions is not met. | P27: 2.5853088
A28: TD | B28: Question 27 | C28: 0 | D28: 1 | E28: 1 | F28: 1 | G28: 1 | H28: 1 | I28: 1 | J28: 1 | K28: 1 | L28: 1 | M28: 1 | N28: 1 | P28: 1.1307583
A29: TD | B29: Question 28 | C29: 0 | D29: 1 | E29: 1 | F29: 1 | G29: 1 | H29: 1 | I29: 1 | J29: 1 | K29: 1 | L29: 1 | M29: 1 | N29: 1 | P29: 1.8251584
A30: TD | B30: Question 29 | C30: 0 | D30: 1 | E30: 1 | F30: 1 | G30: 1 | H30: 1 | I30: 1 | J30: 1 | K30: 1 | L30: 1 | M30: 1 | N30: 1 | P30: 1.8888743
A31: TD | B31: Question 30 | C31: 0 | D31: 1 | E31: 0 | F31: 1 | G31: 1 | H31: 'NA | I31: 1 | J31: 'NA | K31: 1 | L31: 1 | M31: 1 | N31: 1 | O31: Primary KC Alignment: The multiplication required is 3.75 × 12. While multiplying decimals by a whole number is involved, it does not require multiplying by 10, 100, 1000, or their multiples as intended by the Primary KC. Synergy: The two parts (a) and (b) are independent; the conversion from decimal to fraction does not depend on the cost calculation in (a), nor does (a) require the fraction form from (b). | P31: 3.200918
A32: TD | B32: Question 31 | C32: 0 | D32: 1 | E32: 0 | F32: 1 | G32: 1 | H32: 'NA | I32: 1 | J32: 'NA | K32: 1 | L32: 1 | M32: 1 | N32: 1 | O32: Primary KC Alignment=0: The word problem asks for multiplication of a decimal (3.850) by a whole number (140), which is not specifically targeting multiplying decimals by 10, 100, 1000 or their multiples as intended in the primary KC. Instead, the multiplication is by 140, which is not a straightforward application of multiplying by 10, 100, 1000 and their multiples. | P32: 3.9469965
A33: TD | B33: Question 32 | C33: 0 | D33: 1 | E33: 1 | F33: 1 | G33: 1 | H33: 1 | I33: 1 | J33: 1 | K33: 1 | L33: 1 | M33: 1 | N33: 1 | P33: 1.5335612
A34: TD | B34: Question 33 | C34: 0 | D34: 1 | E34: 0 | F34: 1 | G34: 1 | H34: 'NA | I34: 1 | J34: 'NA | K34: 1 | L34: 1 | M34: 1 | N34: 1 | O34: Primary KC Alignment: The intended primary KC is dividing decimals (up to 3 decimal places) by 10, 100, 1000 and their multiples. In the problem, students are required to divide 12.500 by 1000 and then later by 1250 (1000 + 250) to find per square metre costs, but neither divisor (1250) is 10, 100, 1000 or their multiples. The problem does not require the specific use of dividing decimals by the given types of divisors; therefore, it does not fully satisfy the intended primary knowledge component. | P34: 6.160677
A35: TD | B35: Question 34 | C35: 0 | D35: 1 | E35: 1 | F35: 1 | G35: 1 | H35: 1 | I35: 1 | J35: 1 | K35: 1 | L35: 1 | M35: 1 | N35: 1 | P35: 1.7336931
A36: TD | B36: Question 35 | C36: 0 | D36: 1 | E36: 1 | F36: 1 | G36: 1 | H36: 1 | I36: 1 | J36: 1 | K36: 1 | L36: 1 | M36: 1 | N36: 1 | P36: 1.3040788
A37: TD | B37: Question 36 | C37: 0 | D37: 1 | E37: 1 | F37: 1 | G37: 1 | H37: 1 | I37: 1 | J37: 1 | K37: 1 | L37: 1 | M37: 1 | N37: 1 | P37: 1.5145795
A38: TD | B38: Question 37 | C38: 0 | D38: 1 | E38: 0 | F38: 0 | G38: 1 | H38: 'NA | I38: 1 | J38: 'NA | K38: 1 | L38: 1 | M38: 1 | N38: 1 | O38: Primary KC Alignment (0): The intended primary KC is dividing a proper fraction by a whole number, but the problem requires dividing a proper fraction (e.g., 3/4) by another proper fraction (1/8), not a whole number. Secondary KC Alignment (0): The intended secondary KC is adding fractions, but the problem requires adding numbers of loads (whole numbers) from each part, not fractions themselves. | P38: 1.9133818
A39: TD | B39: Question 38 | C39: 0 | D39: 1 | E39: 1 | F39: 1 | G39: 1 | H39: 1 | I39: 1 | J39: 1 | K39: 1 | L39: 1 | M39: 1 | N39: 1 | P39: 1.1394653
A40: TD | B40: Question 39 | C40: 0 | D40: 1 | E40: 1 | F40: 1 | G40: 1 | H40: 1 | I40: 1 | J40: 1 | K40: 1 | L40: 1 | M40: 1 | N40: 1 | P40: 1.2322116
A41: TD | B41: Question 40 | C41: 0 | D41: 0 | E41: 'NA | F41: 'NA | G41: 'NA | H41: 'NA | I41: 'NA | J41: 'NA | K41: 'NA | L41: 'NA | M41: 1 | N41: 'NA | O41: answerability: The word problem cannot be answered logically, because it states each session costs 3/4 of the total amount ($60). This means every session is $45, so she can only pay for 1 session, but the context implies buying multiple sessions.primary_kc_alignment: The main calculation is $60 [FORMULA] $45, a whole number divided by a whole number, NOT a fraction by a fraction, so does not target the intended primary KC.real_world_feasibility: It's unlikely for a service to charge a customer '3/4 of all the money you have' for each session; prices are fixed per session, not based on the buyer's entire amount.synergy: The conversion to decimal (secondary KC) does not depend on the outcome or method of the primary KC, because the primary KC is division of two whole numbers (not fraction by fraction), so the steps are not functionally synergistic. | P41: 3.2541349 | Q41: 'NA
A42: TD | B42: Question 41 | C42: 0 | D42: 1 | E42: 1 | F42: 1 | G42: 1 | H42: 1 | I42: 1 | J42: 1 | K42: 1 | L42: 1 | M42: 1 | N42: 1 | P42: 1.2319939
A43: TD | B43: Question 42 | C43: 0 | D43: 1 | E43: 1 | F43: 1 | G43: 1 | H43: 1 | I43: 1 | J43: 1 | K43: 1 | L43: 1 | M43: 1 | N43: 1 | P43: 1.846683
A44: TD | B44: Question 43 | C44: 0 | D44: 1 | E44: 1 | F44: 1 | G44: 1 | H44: 1 | I44: 1 | J44: 1 | K44: 1 | L44: 1 | M44: 1 | N44: 1 | P44: 1.2119095
A45: TD | B45: Question 44 | C45: 0 | D45: 1 | E45: 1 | F45: 1 | G45: 1 | H45: 1 | I45: 1 | J45: 1 | K45: 1 | L45: 1 | M45: 1 | N45: 1 | P45: 1.8852866
A46: TD | B46: Question 45 | C46: 0 | D46: 1 | E46: 1 | F46: 1 | G46: 1 | H46: 1 | I46: 1 | J46: 1 | K46: 1 | L46: 1 | M46: 1 | N46: 1 | P46: 1.1833582
A47: TD | B47: Question 46 | C47: 0 | D47: 1 | E47: 1 | F47: 1 | G47: 1 | H47: 1 | I47: 1 | J47: 1 | K47: 1 | L47: 1 | M47: 1 | N47: 1 | P47: 1.1479435
A48: TD | B48: Question 47 | C48: 0 | D48: 1 | E48: 1 | F48: 1 | G48: 1 | H48: 1 | I48: 1 | J48: 1 | K48: 1 | L48: 1 | M48: 1 | N48: 1 | P48: 1.5750618
A49: TD | B49: Question 48 | C49: 0 | D49: 1 | E49: 1 | F49: 1 | G49: 1 | H49: 1 | I49: 1 | J49: 1 | K49: 1 | L49: 1 | M49: 1 | N49: 1 | P49: 1.7821221
A50: TD | B50: Question 49 | C50: 0 | D50: 1 | E50: 1 | F50: 1 | G50: 1 | H50: 1 | I50: 1 | J50: 1 | K50: 1 | L50: 1 | M50: 1 | N50: 1 | P50: 1.1708722
A51: Minh | B51: Question 1 | C51: 0 | D51: 1 | E51: 1 | F51: 1 | G51: 1 | H51: 1 | I51: 1 | J51: 0 | K51: 1 | L51: 1 | M51: 1 | N51: 1 | O51: 7: (synergy) The two sub-questions (a) and (b) are independent. The answer to (a) is not required for (b), and vice versa. To fully satisfy synergy, the sub-questions should be connected, such as needing the answer from (a) to solve (b). | P51: 2.4017658
A52: Minh | B52: Question 2 | C52: 0 | D52: 1 | E52: 1 | F52: 1 | G52: 1 | H52: 1 | I52: 1 | J52: 1 | K52: 1 | L52: 1 | M52: 1 | N52: 1 | P52: 1.1666486
A53: Minh | B53: Question 3 | C53: 0 | D53: 1 | E53: 1 | F53: 1 | G53: 1 | H53: 1 | I53: 1 | J53: 1 | K53: 1 | L53: 1 | M53: 1 | N53: 1 | P53: 1.767509
A54: Minh | B54: Question 4 | C54: 0 | D54: 1 | E54: 1 | F54: 1 | G54: 1 | H54: 1 | I54: 1 | J54: 1 | K54: 1 | L54: 1 | M54: 1 | N54: 1 | P54: 1.104079
A55: Minh | B55: Question 5 | C55: 0 | D55: 1 | E55: 1 | F55: 1 | G55: 1 | H55: 1 | I55: 1 | J55: 1 | K55: 1 | L55: 1 | M55: 1 | N55: 1 | P55: 1.0964816
A56: Minh | B56: Question 6 | C56: 0 | D56: 1 | E56: 1 | F56: 1 | G56: 1 | H56: 1 | I56: 1 | J56: 1 | K56: 1 | L56: 1 | M56: 1 | N56: 1 | P56: 1.5399017
A57: Minh | B57: Question 7 | C57: 0 | D57: 1 | E57: 1 | F57: 1 | G57: 1 | H57: 1 | I57: 1 | J57: 1 | K57: 1 | L57: 1 | M57: 1 | N57: 1 | P57: 1.3517251
A58: Minh | B58: Question 8 | C58: 0 | D58: 1 | E58: 1 | F58: 1 | G58: 1 | H58: 1 | I58: 1 | J58: 1 | K58: 1 | L58: 1 | M58: 1 | N58: 1 | P58: 2.1694531
A59: Minh | B59: Question 9 | C59: 0 | D59: 1 | E59: 1 | F59: 1 | G59: 1 | H59: 1 | I59: 1 | J59: 1 | K59: 1 | L59: 1 | M59: 1 | N59: 1 | P59: 1.1554058
A60: Minh | B60: Question 10 | C60: 0 | D60: 1 | E60: 1 | F60: 1 | G60: 1 | H60: 1 | I60: 1 | J60: 1 | K60: 1 | L60: 1 | M60: 1 | N60: 1 | P60: 1.1677308
A61: Minh | B61: Question 11 | C61: 0 | D61: 1 | E61: 1 | F61: 1 | G61: 1 | H61: 1 | I61: 1 | J61: 1 | K61: 1 | L61: 1 | M61: 1 | N61: 1 | P61: 2.0002565
A62: Minh | B62: Question 12 | C62: 0 | D62: 1 | E62: 1 | F62: 1 | G62: 1 | H62: 1 | I62: 1 | J62: 1 | K62: 1 | L62: 1 | M62: 1 | N62: 1 | P62: 1.7646654
A63: Minh | B63: Question 13 | C63: 0 | D63: 1 | E63: 1 | F63: 1 | G63: 1 | H63: 1 | I63: 1 | J63: 1 | K63: 1 | L63: 1 | M63: 1 | N63: 1 | P63: 1.5872569
A64: Minh | B64: Question 14 | C64: 0 | D64: 1 | E64: 1 | F64: 1 | G64: 1 | H64: 1 | I64: 1 | J64: 1 | K64: 1 | L64: 1 | M64: 1 | N64: 1 | P64: 1.2016563
A65: Minh | B65: Question 15 | C65: 0 | D65: 1 | E65: 0 | F65: 1 | G65: 1 | H65: 'NA | I65: 0 | J65: 'NA | K65: 1 | L65: 1 | M65: 1 | N65: 1 | O65: Primary KC Alignment: The second price has three decimal places (13.299), which forces students to add decimals beyond two decimal places. This is above the intended difficulty (up to 2 decimal places). Grade Alignment: The problem uses numbers with three decimal places (13.299), which is not appropriate for Primary 4 as per Singapore MOE standards—students are only expected to work with up to two decimal places. Real-World Feasibility: Monthly streaming subscription fees almost never involve three decimal places. The value $13.299 is not a realistically-priced service. | P65: 3.3393314
A66: Minh | B66: Question 16 | C66: 0 | D66: 1 | E66: 1 | F66: 1 | G66: 1 | H66: 1 | I66: 1 | J66: 1 | K66: 1 | L66: 1 | M66: 1 | N66: 1 | P66: 1.8568547
A67: Minh | B67: Question 17 | C67: 0 | D67: 1 | E67: 0 | F67: 1 | G67: 1 | H67: 'NA | I67: 1 | J67: 'NA | K67: 1 | L67: 1 | M67: 1 | N67: 1 | O67: Primary KC Alignment: The intended primary knowledge component is dividing decimals (up to 2 decimal places) by a 1-digit whole number. In this problem, the student must divide 24 by 3.75 to find the number of shirts, which is dividing a whole number by a decimal (not the other way around), and 3.75 has two decimal places but is NOT divided by a 1-digit whole number (3.75 is not a 1-digit, it's a decimal). Thus, the core operation does not match the intended primary knowledge component. | P67: 2.4807646
A68: Minh | B68: Question 18 | C68: 0 | D68: 1 | E68: 1 | F68: 1 | G68: 1 | H68: 1 | I68: 1 | J68: 1 | K68: 1 | L68: 1 | M68: 1 | N68: 1 | P68: 2.6216047
A69: Minh | B69: Question 19 | C69: 0 | D69: 1 | E69: 1 | F69: 1 | G69: 1 | H69: 1 | I69: 1 | J69: 1 | K69: 1 | L69: 1 | M69: 1 | N69: 1 | P69: 1.332284
A70: Minh | B70: Question 20 | C70: 0 | D70: 1 | E70: 1 | F70: 1 | G70: 1 | H70: 1 | I70: 1 | J70: 1 | K70: 1 | L70: 1 | M70: 1 | N70: 1 | P70: 1.166692
A71: Minh | B71: Question 21 | C71: 0 | D71: 1 | E71: 1 | F71: 1 | G71: 1 | H71: 1 | I71: 1 | J71: 1 | K71: 1 | L71: 1 | M71: 1 | N71: 1 | P71: 1.5692127
A72: Minh | B72: Question 22 | C72: 0 | D72: 1 | E72: 1 | F72: 1 | G72: 1 | H72: 1 | I72: 1 | J72: 1 | K72: 1 | L72: 1 | M72: 1 | N72: 1 | P72: 1.6203358
A73: Minh | B73: Question 23 | C73: 0 | D73: 1 | E73: 1 | F73: 1 | G73: 1 | H73: 1 | I73: 1 | J73: 1 | K73: 1 | L73: 1 | M73: 1 | N73: 1 | P73: 1.1671364
A74: Minh | B74: Question 24 | C74: 0 | D74: 1 | E74: 1 | F74: 1 | G74: 1 | H74: 1 | I74: 1 | J74: 1 | K74: 1 | L74: 1 | M74: 1 | N74: 1 | P74: 1.6962836
A75: Minh | B75: Question 25 | C75: 0 | D75: 1 | E75: 1 | F75: 1 | G75: 1 | H75: 1 | I75: 1 | J75: 1 | K75: 1 | L75: 1 | M75: 1 | N75: 1 | P75: 1.3065214
A76: Minh | B76: Question 26 | C76: 0 | D76: 1 | E76: 1 | F76: 1 | G76: 1 | H76: 1 | I76: 1 | J76: 1 | K76: 1 | L76: 1 | M76: 1 | N76: 1 | P76: 1.6539993
A77: Minh | B77: Question 27 | C77: 0 | D77: 1 | E77: 0 | F77: 1 | G77: 1 | H77: 'NA | I77: 1 | J77: 'NA | K77: 1 | L77: 1 | M77: 1 | N77: 1 | O77: B2: The primary KC requires multiplying decimals (up to 3 decimal places) by 10, 100, 1000 AND THEIR MULTIPLES. The question uses 6.125×100, which is a straightforward multiplication by 100, but this is not sufficiently complex or representative of the spirit of the intended KC, which often expects tasks like multiplying decimals by non-round multiples of 10 (e.g., 20, 300), not just 100 which is straightforward place shifting. For Primary 5 in Singapore context, this would not embrace the complexity sufficient for proper assessment of the targeted KC. | P77: 2.4359014
A78: Minh | B78: Question 28 | C78: 0 | D78: 1 | E78: 1 | F78: 1 | G78: 1 | H78: 1 | I78: 1 | J78: 1 | K78: 1 | L78: 1 | M78: 1 | N78: 1 | P78: 1.4131002
A79: Minh | B79: Question 29 | C79: 0 | D79: 1 | E79: 1 | F79: 1 | G79: 1 | H79: 1 | I79: 1 | J79: 1 | K79: 1 | L79: 1 | M79: 1 | N79: 1 | P79: 1.2671809
A80: Minh | B80: Question 30 | C80: 0 | D80: 1 | E80: 1 | F80: 0 | G80: 1 | H80: 1 | I80: 1 | J80: 'NA | K80: 1 | L80: 1 | M80: 1 | N80: 1 | O80: Secondary KC (DECIMALS | Conversion to smaller units) is not targeted: The problem does not require any conversion between larger and smaller decimal units (such as hours to minutes or dollars to cents); only division of totals is required. Synergy is missing: The problem can be solved with only the primary KC (rate calculation) and does not require both KCs together. | P80: 3.6465242
A81: Minh | B81: Question 31 | C81: 0 | D81: 1 | E81: 1 | F81: 1 | G81: 1 | H81: 1 | I81: 1 | J81: 1 | K81: 1 | L81: 1 | M81: 1 | N81: 1 | P81: 1.4640846
A82: Minh | B82: Question 32 | C82: 0 | D82: 1 | E82: 1 | F82: 1 | G82: 1 | H82: 1 | I82: 1 | J82: 1 | K82: 1 | L82: 1 | M82: 1 | N82: 1 | P82: 1.1609731
A83: Minh | B83: Question 33 | C83: 0 | D83: 1 | E83: 1 | F83: 1 | G83: 1 | H83: 1 | I83: 1 | J83: 1 | K83: 1 | L83: 1 | M83: 1 | N83: 1 | P83: 1.5841756
A84: Minh | B84: Question 34 | C84: 0 | D84: 1 | E84: 1 | F84: 1 | G84: 1 | H84: 1 | I84: 1 | J84: 1 | K84: 1 | L84: 1 | M84: 1 | N84: 1 | P84: 1.2521284
A85: Minh | B85: Question 35 | C85: 0 | D85: 1 | E85: 1 | F85: 1 | G85: 1 | H85: 1 | I85: 1 | J85: 1 | K85: 1 | L85: 1 | M85: 1 | N85: 1 | P85: 1.2568305
A86: Minh | B86: Question 36 | C86: 0 | D86: 1 | E86: 1 | F86: 0 | G86: 1 | H86: 1 | I86: 1 | J86: 'NA | K86: 1 | L86: 1 | M86: 1 | N86: 1 | O86: Secondary KC Alignment = 0: The solution to the problem only requires reversing a percentage decrease to find the original price; subtraction is not directly required in solving the question. Synergy = 0: The secondary KC (subtraction) is not needed to solve the word problem or synergised with the primary KC. | P86: 2.7571476
A87: Minh | B87: Question 37 | C87: 0 | D87: 1 | E87: 1 | F87: 1 | G87: 1 | H87: 1 | I87: 1 | J87: 1 | K87: 1 | L87: 1 | M87: 1 | N87: 1 | P87: 1.5126853
A88: Minh | B88: Question 38 | C88: 0 | D88: 1 | E88: 1 | F88: 1 | G88: 1 | H88: 1 | I88: 1 | J88: 1 | K88: 1 | L88: 1 | M88: 1 | N88: 1 | P88: 1.4026787
A89: Minh | B89: Question 39 | C89: 0 | D89: 1 | E89: 1 | F89: 1 | G89: 1 | H89: 1 | I89: 1 | J89: 1 | K89: 1 | L89: 1 | M89: 1 | N89: 1 | P89: 1.6927207
A90: Minh | B90: Question 40 | C90: 0 | D90: 1 | E90: 1 | F90: 1 | G90: 1 | H90: 1 | I90: 1 | J90: 1 | K90: 1 | L90: 1 | M90: 1 | N90: 1 | P90: 1.2692344
A91: Minh | B91: Question 41 | C91: 0 | D91: 1 | E91: 1 | F91: 1 | G91: 1 | H91: 1 | I91: 1 | J91: 1 | K91: 1 | L91: 1 | M91: 1 | N91: 1 | P91: 1.2427289
A92: Minh | B92: Question 42 | C92: 0 | D92: 1 | E92: 1 | F92: 1 | G92: 1 | H92: 1 | I92: 1 | J92: 1 | K92: 1 | L92: 1 | M92: 1 | N92: 1 | P92: 1.1188657
A93: Minh | B93: Question 43 | C93: 0 | D93: 1 | E93: 1 | F93: 1 | G93: 1 | H93: 1 | I93: 1 | J93: 1 | K93: 1 | L93: 1 | M93: 1 | N93: 1 | P93: 1.2825387
A94: Minh | B94: Question 44 | C94: 0 | D94: 1 | E94: 1 | F94: 1 | G94: 1 | H94: 1 | I94: 1 | J94: 1 | K94: 1 | L94: 1 | M94: 1 | N94: 1 | P94: 1.6503956
A95: Minh | B95: Question 45 | C95: 0 | D95: 1 | E95: 1 | F95: 1 | G95: 1 | H95: 1 | I95: 1 | J95: 1 | K95: 1 | L95: 1 | M95: 1 | N95: 1 | P95: 1.1411505
A96: Minh | B96: Question 46 | C96: 0 | D96: 1 | E96: 1 | F96: 1 | G96: 1 | H96: 1 | I96: 1 | J96: 1 | K96: 1 | L96: 1 | M96: 1 | N96: 1 | P96: 1.2477305
A97: Minh | B97: Question 47 | C97: 0 | D97: 1 | E97: 1 | F97: 1 | G97: 1 | H97: 1 | I97: 1 | J97: 1 | K97: 1 | L97: 1 | M97: 1 | N97: 1 | P97: 1.1370494
A98: Minh | B98: Question 48 | C98: 0 | D98: 1 | E98: 1 | F98: 1 | G98: 1 | H98: 1 | I98: 1 | J98: 1 | K98: 1 | L98: 1 | M98: 1 | N98: 1 | P98: 1.1037049
... A102: Minh | B102: Question 52 | C102: 0 | D102: 1 | E102: 1 | F102: 1 | G102: 1 | H102: 1 | I102: 1 | J102: 1 | K102: 1 | L102: 1 | M102: 1 | N102: 1 | P102: 1.1762424
A103: Minh | B103: Question 53 | C103: 0 | D103: 1 | E103: 0 | F103: 1 | G103: 1 | H103: 'NA | I103: 1 | J103: 'NA | K103: 1 | L103: 1 | M103: 1 | N103: 1 | O103: Primary KC Alignment (0): The problem only requires forming and solving a linear equation in one variable (set the two expressions equal and solve for x). It does not involve linear equations in two variables, as intended. Synergy (0): The secondary KC (translation to equations) is tested, but the 'solving linear equations in two variables' is not required in tandem, since it's just a single variable to solve for. | P103: 2.9477043
...

Sheet Compiled Votes
A1: Evaluator | B1: Question | C1: status | D1: answerability | E1: primary_kc_alignment | F1: secondary_kc_alignment | G1: topic_alignment | H1: grade_alignment | I1: real_world_feasibility | J1: synergy | K1: clarity | L1: conciseness_and_relevance | M1: language_quality | N1: content_appropriateness | O1: response_time | P1: language_quality1
A2: TD | B2: Question 1 | C2: 0 | D2: =ROUND(SUM(services_v8_v1_split_5!D2,services_v8_v1_split_4!D2,services_v8_v1_split_3!D2,services_v8_v1_split_2!D2,services_v8_v1_split_1!D2)/COUNT(services_v8_v1_split_5!D2,services_v8_v1_split_4!D2,services_v8_v1_split_3!D2,services_v8_v1_split_2!D2,services_v8_v1_split_1!D2),0) -> 1 | E2: =IF($D2 = 1,ROUND(SUM(services_v8_v1_split_5!E2,services_v8_v1_split_4!E2,services_v8_v1_split_3!E2,services_v8_v1_split_2!E2,services_v8_v1_split_1!E2)/COUNT(services_v8_v1_split_5!E2,services_v8_v1_split_4!E2,services_v8_v1_split_3!E2,services_v8_v1_split_2!E2,services_v8_v1_split_1!E2),0),"NA") -> 1 | F2: =IF($D2 = 1,ROUND(SUM(services_v8_v1_split_5!F2,services_v8_v1_split_4!F2,services_v8_v1_split_3!F2,services_v8_v1_split_2!F2,services_v8_v1_split_1!F2)/COUNT(services_v8_v1_split_5!F2,services_v8_v1_split_4!F2,services_v8_v1_split_3!F2,services_v8_v1_split_2!F2,services_v8_v1_split_1!F2),0),"NA") -> 1 | G2: =IF($D2 = 1,ROUND(SUM(services_v8_v1_split_5!G2,services_v8_v1_split_4!G2,services_v8_v1_split_3!G2,services_v8_v1_split_2!G2,services_v8_v1_split_1!G2)/COUNT(services_v8_v1_split_5!G2,services_v8_v1_split_4!G2,services_v8_v1_split_3!G2,services_v8_v1_split_2!G2,services_v8_v1_split_1!G2),0),"NA") -> 1 | H2: =IF($E2 = 1,ROUND(SUM(services_v8_v1_split_5!H2,services_v8_v1_split_4!H2,services_v8_v1_split_3!H2,services_v8_v1_split_2!H2,services_v8_v1_split_1!H2)/COUNT(services_v8_v1_split_5!H2,services_v8_v1_split_4!H2,services_v8_v1_split_3!H2,services_v8_v1_split_2!H2,services_v8_v1_split_1!H2),0),"NA") -> 1 | I2: =IF($D2 = 1,ROUND(SUM(services_v8_v1_split_5!I2,services_v8_v1_split_4!I2,services_v8_v1_split_3!I2,services_v8_v1_split_2!I2,services_v8_v1_split_1!I2)/COUNT(services_v8_v1_split_5!I2,services_v8_v1_split_4!I2,services_v8_v1_split_3!I2,services_v8_v1_split_2!I2,services_v8_v1_split_1!I2),0),"NA") -> 1 | J2: =IF(AND(E2 = 1,F2=1),ROUND(SUM(services_v8_v1_split_5!J2,services_v8_v1_split_4!J2,services_v8_v1_split_3!J2,services_v8_v1_split_2!J2,services_v8_v1_split_1!J2)/COUNT(services_v8_v1_split_5!J2,services_v8_v1_split_4!J2,services_v8_v1_split_3!J2,services_v8_v1_split_2!J2,services_v8_v1_split_1!J2),0),"NA") -> 1 | K2: =IF($D2 = 1,ROUND(SUM(services_v8_v1_split_5!K2,services_v8_v1_split_4!K2,services_v8_v1_split_3!K2,services_v8_v1_split_2!K2,services_v8_v1_split_1!K2)/COUNT(services_v8_v1_split_5!K2,services_v8_v1_split_4!K2,services_v8_v1_split_3!K2,services_v8_v1_split_2!K2,services_v8_v1_split_1!K2),0),"NA") -> 1 | L2: =IF($D2 = 1,ROUND(SUM(services_v8_v1_split_5!L2,services_v8_v1_split_4!L2,services_v8_v1_split_3!L2,services_v8_v1_split_2!L2,services_v8_v1_split_1!L2)/COUNT(services_v8_v1_split_5!L2,services_v8_v1_split_4!L2,services_v8_v1_split_3!L2,services_v8_v1_split_2!L2,services_v8_v1_split_1!L2),0),"NA") -> 1 | M2: =IF($D2 = 1,ROUND(SUM(services_v8_v1_split_5!M2,services_v8_v1_split_4!M2,services_v8_v1_split_3!M2,services_v8_v1_split_2!M2,services_v8_v1_split_1!M2)/COUNT(services_v8_v1_split_5!M2,services_v8_v1_split_4!M2,services_v8_v1_split_3!M2,services_v8_v1_split_2!M2,services_v8_v1_split_1!M2),0),"NA") -> 1 | N2: =IF($D2 = 1,ROUND(SUM(services_v8_v1_split_5!N2,services_v8_v1_split_4!N2,services_v8_v1_split_3!N2,services_v8_v1_split_2!N2,services_v8_v1_split_1!N2)/COUNT(services_v8_v1_split_5!N2,services_v8_v1_split_4!N2,services_v8_v1_split_3!N2,services_v8_v1_split_2!N2,services_v8_v1_split_1!N2),0),"NA") -> 1 | O2: 2.892709
A3: TD | B3: Question 2 | C3: 0 | D3: =ROUND(SUM(services_v8_v1_split_5!D3,services_v8_v1_split_4!D3,services_v8_v1_split_3!D3,services_v8_v1_split_2!D3,services_v8_v1_split_1!D3)/COUNT(services_v8_v1_split_5!D3,services_v8_v1_split_4!D3,services_v8_v1_split_3!D3,services_v8_v1_split_2!D3,services_v8_v1_split_1!D3),0) -> 1 | E3: =IF($D3 = 1,ROUND(SUM(services_v8_v1_split_5!E3,services_v8_v1_split_4!E3,services_v8_v1_split_3!E3,services_v8_v1_split_2!E3,services_v8_v1_split_1!E3)/COUNT(services_v8_v1_split_5!E3,services_v8_v1_split_4!E3,services_v8_v1_split_3!E3,services_v8_v1_split_2!E3,services_v8_v1_split_1!E3),0),"NA") -> 1 | F3: =IF($D3 = 1,ROUND(SUM(services_v8_v1_split_5!F3,services_v8_v1_split_4!F3,services_v8_v1_split_3!F3,services_v8_v1_split_2!F3,services_v8_v1_split_1!F3)/COUNT(services_v8_v1_split_5!F3,services_v8_v1_split_4!F3,services_v8_v1_split_3!F3,services_v8_v1_split_2!F3,services_v8_v1_split_1!F3),0),"NA") -> 1 | G3: =IF($D3 = 1,ROUND(SUM(services_v8_v1_split_5!G3,services_v8_v1_split_4!G3,services_v8_v1_split_3!G3,services_v8_v1_split_2!G3,services_v8_v1_split_1!G3)/COUNT(services_v8_v1_split_5!G3,services_v8_v1_split_4!G3,services_v8_v1_split_3!G3,services_v8_v1_split_2!G3,services_v8_v1_split_1!G3),0),"NA") -> 1 | H3: =IF($E3 = 1,ROUND(SUM(services_v8_v1_split_5!H3,services_v8_v1_split_4!H3,services_v8_v1_split_3!H3,services_v8_v1_split_2!H3,services_v8_v1_split_1!H3)/COUNT(services_v8_v1_split_5!H3,services_v8_v1_split_4!H3,services_v8_v1_split_3!H3,services_v8_v1_split_2!H3,services_v8_v1_split_1!H3),0),"NA") -> 1 | I3: =IF($D3 = 1,ROUND(SUM(services_v8_v1_split_5!I3,services_v8_v1_split_4!I3,services_v8_v1_split_3!I3,services_v8_v1_split_2!I3,services_v8_v1_split_1!I3)/COUNT(services_v8_v1_split_5!I3,services_v8_v1_split_4!I3,services_v8_v1_split_3!I3,services_v8_v1_split_2!I3,services_v8_v1_split_1!I3),0),"NA") -> 1 | J3: =IF(AND(E3 = 1,F3=1),ROUND(SUM(services_v8_v1_split_5!J3,services_v8_v1_split_4!J3,services_v8_v1_split_3!J3,services_v8_v1_split_2!J3,services_v8_v1_split_1!J3)/COUNT(services_v8_v1_split_5!J3,services_v8_v1_split_4!J3,services_v8_v1_split_3!J3,services_v8_v1_split_2!J3,services_v8_v1_split_1!J3),0),"NA") -> 1 | K3: =IF($D3 = 1,ROUND(SUM(services_v8_v1_split_5!K3,services_v8_v1_split_4!K3,services_v8_v1_split_3!K3,services_v8_v1_split_2!K3,services_v8_v1_split_1!K3)/COUNT(services_v8_v1_split_5!K3,services_v8_v1_split_4!K3,services_v8_v1_split_3!K3,services_v8_v1_split_2!K3,services_v8_v1_split_1!K3),0),"NA") -> 1 | L3: =IF($D3 = 1,ROUND(SUM(services_v8_v1_split_5!L3,services_v8_v1_split_4!L3,services_v8_v1_split_3!L3,services_v8_v1_split_2!L3,services_v8_v1_split_1!L3)/COUNT(services_v8_v1_split_5!L3,services_v8_v1_split_4!L3,services_v8_v1_split_3!L3,services_v8_v1_split_2!L3,services_v8_v1_split_1!L3),0),"NA") -> 1 | M3: =IF($D3 = 1,ROUND(SUM(services_v8_v1_split_5!M3,services_v8_v1_split_4!M3,services_v8_v1_split_3!M3,services_v8_v1_split_2!M3,services_v8_v1_split_1!M3)/COUNT(services_v8_v1_split_5!M3,services_v8_v1_split_4!M3,services_v8_v1_split_3!M3,services_v8_v1_split_2!M3,services_v8_v1_split_1!M3),0),"NA") -> 1 | N3: =IF($D3 = 1,ROUND(SUM(services_v8_v1_split_5!N3,services_v8_v1_split_4!N3,services_v8_v1_split_3!N3,services_v8_v1_split_2!N3,services_v8_v1_split_1!N3)/COUNT(services_v8_v1_split_5!N3,services_v8_v1_split_4!N3,services_v8_v1_split_3!N3,services_v8_v1_split_2!N3,services_v8_v1_split_1!N3),0),"NA") -> 1 | O3: 1.5651164
A4: TD | B4: Question 3 | C4: 0 | D4: =ROUND(SUM(services_v8_v1_split_5!D4,services_v8_v1_split_4!D4,services_v8_v1_split_3!D4,services_v8_v1_split_2!D4,services_v8_v1_split_1!D4)/COUNT(services_v8_v1_split_5!D4,services_v8_v1_split_4!D4,services_v8_v1_split_3!D4,services_v8_v1_split_2!D4,services_v8_v1_split_1!D4),0) -> 1 | E4: =IF($D4 = 1,ROUND(SUM(services_v8_v1_split_5!E4,services_v8_v1_split_4!E4,services_v8_v1_split_3!E4,services_v8_v1_split_2!E4,services_v8_v1_split_1!E4)/COUNT(services_v8_v1_split_5!E4,services_v8_v1_split_4!E4,services_v8_v1_split_3!E4,services_v8_v1_split_2!E4,services_v8_v1_split_1!E4),0),"NA") -> 1 | F4: =IF($D4 = 1,ROUND(SUM(services_v8_v1_split_5!F4,services_v8_v1_split_4!F4,services_v8_v1_split_3!F4,services_v8_v1_split_2!F4,services_v8_v1_split_1!F4)/COUNT(services_v8_v1_split_5!F4,services_v8_v1_split_4!F4,services_v8_v1_split_3!F4,services_v8_v1_split_2!F4,services_v8_v1_split_1!F4),0),"NA") -> 1 | G4: =IF($D4 = 1,ROUND(SUM(services_v8_v1_split_5!G4,services_v8_v1_split_4!G4,services_v8_v1_split_3!G4,services_v8_v1_split_2!G4,services_v8_v1_split_1!G4)/COUNT(services_v8_v1_split_5!G4,services_v8_v1_split_4!G4,services_v8_v1_split_3!G4,services_v8_v1_split_2!G4,services_v8_v1_split_1!G4),0),"NA") -> 1 | H4: =IF($E4 = 1,ROUND(SUM(services_v8_v1_split_5!H4,services_v8_v1_split_4!H4,services_v8_v1_split_3!H4,services_v8_v1_split_2!H4,services_v8_v1_split_1!H4)/COUNT(services_v8_v1_split_5!H4,services_v8_v1_split_4!H4,services_v8_v1_split_3!H4,services_v8_v1_split_2!H4,services_v8_v1_split_1!H4),0),"NA") -> 1 | I4: =IF($D4 = 1,ROUND(SUM(services_v8_v1_split_5!I4,services_v8_v1_split_4!I4,services_v8_v1_split_3!I4,services_v8_v1_split_2!I4,services_v8_v1_split_1!I4)/COUNT(services_v8_v1_split_5!I4,services_v8_v1_split_4!I4,services_v8_v1_split_3!I4,services_v8_v1_split_2!I4,services_v8_v1_split_1!I4),0),"NA") -> 1 | J4: =IF(AND(E4 = 1,F4=1),ROUND(SUM(services_v8_v1_split_5!J4,services_v8_v1_split_4!J4,services_v8_v1_split_3!J4,services_v8_v1_split_2!J4,services_v8_v1_split_1!J4)/COUNT(services_v8_v1_split_5!J4,services_v8_v1_split_4!J4,services_v8_v1_split_3!J4,services_v8_v1_split_2!J4,services_v8_v1_split_1!J4),0),"NA") -> 1 | K4: =IF($D4 = 1,ROUND(SUM(services_v8_v1_split_5!K4,services_v8_v1_split_4!K4,services_v8_v1_split_3!K4,services_v8_v1_split_2!K4,services_v8_v1_split_1!K4)/COUNT(services_v8_v1_split_5!K4,services_v8_v1_split_4!K4,services_v8_v1_split_3!K4,services_v8_v1_split_2!K4,services_v8_v1_split_1!K4),0),"NA") -> 1 | L4: =IF($D4 = 1,ROUND(SUM(services_v8_v1_split_5!L4,services_v8_v1_split_4!L4,services_v8_v1_split_3!L4,services_v8_v1_split_2!L4,services_v8_v1_split_1!L4)/COUNT(services_v8_v1_split_5!L4,services_v8_v1_split_4!L4,services_v8_v1_split_3!L4,services_v8_v1_split_2!L4,services_v8_v1_split_1!L4),0),"NA") -> 1 | M4: =IF($D4 = 1,ROUND(SUM(services_v8_v1_split_5!M4,services_v8_v1_split_4!M4,services_v8_v1_split_3!M4,services_v8_v1_split_2!M4,services_v8_v1_split_1!M4)/COUNT(services_v8_v1_split_5!M4,services_v8_v1_split_4!M4,services_v8_v1_split_3!M4,services_v8_v1_split_2!M4,services_v8_v1_split_1!M4),0),"NA") -> 1 | N4: =IF($D4 = 1,ROUND(SUM(services_v8_v1_split_5!N4,services_v8_v1_split_4!N4,services_v8_v1_split_3!N4,services_v8_v1_split_2!N4,services_v8_v1_split_1!N4)/COUNT(services_v8_v1_split_5!N4,services_v8_v1_split_4!N4,services_v8_v1_split_3!N4,services_v8_v1_split_2!N4,services_v8_v1_split_1!N4),0),"NA") -> 1 | O4: 1.1845906
A5: TD | B5: Question 4 | C5: 0 | D5: =ROUND(SUM(services_v8_v1_split_5!D5,services_v8_v1_split_4!D5,services_v8_v1_split_3!D5,services_v8_v1_split_2!D5,services_v8_v1_split_1!D5)/COUNT(services_v8_v1_split_5!D5,services_v8_v1_split_4!D5,services_v8_v1_split_3!D5,services_v8_v1_split_2!D5,services_v8_v1_split_1!D5),0) -> 1 | E5: =IF($D5 = 1,ROUND(SUM(services_v8_v1_split_5!E5,services_v8_v1_split_4!E5,services_v8_v1_split_3!E5,services_v8_v1_split_2!E5,services_v8_v1_split_1!E5)/COUNT(services_v8_v1_split_5!E5,services_v8_v1_split_4!E5,services_v8_v1_split_3!E5,services_v8_v1_split_2!E5,services_v8_v1_split_1!E5),0),"NA") -> 1 | F5: =IF($D5 = 1,ROUND(SUM(services_v8_v1_split_5!F5,services_v8_v1_split_4!F5,services_v8_v1_split_3!F5,services_v8_v1_split_2!F5,services_v8_v1_split_1!F5)/COUNT(services_v8_v1_split_5!F5,services_v8_v1_split_4!F5,services_v8_v1_split_3!F5,services_v8_v1_split_2!F5,services_v8_v1_split_1!F5),0),"NA") -> 1 | G5: =IF($D5 = 1,ROUND(SUM(services_v8_v1_split_5!G5,services_v8_v1_split_4!G5,services_v8_v1_split_3!G5,services_v8_v1_split_2!G5,services_v8_v1_split_1!G5)/COUNT(services_v8_v1_split_5!G5,services_v8_v1_split_4!G5,services_v8_v1_split_3!G5,services_v8_v1_split_2!G5,services_v8_v1_split_1!G5),0),"NA") -> 1 | H5: =IF($E5 = 1,ROUND(SUM(services_v8_v1_split_5!H5,services_v8_v1_split_4!H5,services_v8_v1_split_3!H5,services_v8_v1_split_2!H5,services_v8_v1_split_1!H5)/COUNT(services_v8_v1_split_5!H5,services_v8_v1_split_4!H5,services_v8_v1_split_3!H5,services_v8_v1_split_2!H5,services_v8_v1_split_1!H5),0),"NA") -> 1 | I5: =IF($D5 = 1,ROUND(SUM(services_v8_v1_split_5!I5,services_v8_v1_split_4!I5,services_v8_v1_split_3!I5,services_v8_v1_split_2!I5,services_v8_v1_split_1!I5)/COUNT(services_v8_v1_split_5!I5,services_v8_v1_split_4!I5,services_v8_v1_split_3!I5,services_v8_v1_split_2!I5,services_v8_v1_split_1!I5),0),"NA") -> 1 | J5: =IF(AND(E5 = 1,F5=1),ROUND(SUM(services_v8_v1_split_5!J5,services_v8_v1_split_4!J5,services_v8_v1_split_3!J5,services_v8_v1_split_2!J5,services_v8_v1_split_1!J5)/COUNT(services_v8_v1_split_5!J5,services_v8_v1_split_4!J5,services_v8_v1_split_3!J5,services_v8_v1_split_2!J5,services_v8_v1_split_1!J5),0),"NA") -> 1 | K5: =IF($D5 = 1,ROUND(SUM(services_v8_v1_split_5!K5,services_v8_v1_split_4!K5,services_v8_v1_split_3!K5,services_v8_v1_split_2!K5,services_v8_v1_split_1!K5)/COUNT(services_v8_v1_split_5!K5,services_v8_v1_split_4!K5,services_v8_v1_split_3!K5,services_v8_v1_split_2!K5,services_v8_v1_split_1!K5),0),"NA") -> 1 | L5: =IF($D5 = 1,ROUND(SUM(services_v8_v1_split_5!L5,services_v8_v1_split_4!L5,services_v8_v1_split_3!L5,services_v8_v1_split_2!L5,services_v8_v1_split_1!L5)/COUNT(services_v8_v1_split_5!L5,services_v8_v1_split_4!L5,services_v8_v1_split_3!L5,services_v8_v1_split_2!L5,services_v8_v1_split_1!L5),0),"NA") -> 1 | M5: =IF($D5 = 1,ROUND(SUM(services_v8_v1_split_5!M5,services_v8_v1_split_4!M5,services_v8_v1_split_3!M5,services_v8_v1_split_2!M5,services_v8_v1_split_1!M5)/COUNT(services_v8_v1_split_5!M5,services_v8_v1_split_4!M5,services_v8_v1_split_3!M5,services_v8_v1_split_2!M5,services_v8_v1_split_1!M5),0),"NA") -> 1 | N5: =IF($D5 = 1,ROUND(SUM(services_v8_v1_split_5!N5,services_v8_v1_split_4!N5,services_v8_v1_split_3!N5,services_v8_v1_split_2!N5,services_v8_v1_split_1!N5)/COUNT(services_v8_v1_split_5!N5,services_v8_v1_split_4!N5,services_v8_v1_split_3!N5,services_v8_v1_split_2!N5,services_v8_v1_split_1!N5),0),"NA") -> 1 | O5: 1.3986135
A6: TD | B6: Question 5 | C6: 0 | D6: =ROUND(SUM(services_v8_v1_split_5!D6,services_v8_v1_split_4!D6,services_v8_v1_split_3!D6,services_v8_v1_split_2!D6,services_v8_v1_split_1!D6)/COUNT(services_v8_v1_split_5!D6,services_v8_v1_split_4!D6,services_v8_v1_split_3!D6,services_v8_v1_split_2!D6,services_v8_v1_split_1!D6),0) -> 1 | E6: =IF($D6 = 1,ROUND(SUM(services_v8_v1_split_5!E6,services_v8_v1_split_4!E6,services_v8_v1_split_3!E6,services_v8_v1_split_2!E6,services_v8_v1_split_1!E6)/COUNT(services_v8_v1_split_5!E6,services_v8_v1_split_4!E6,services_v8_v1_split_3!E6,services_v8_v1_split_2!E6,services_v8_v1_split_1!E6),0),"NA") -> 1 | F6: =IF($D6 = 1,ROUND(SUM(services_v8_v1_split_5!F6,services_v8_v1_split_4!F6,services_v8_v1_split_3!F6,services_v8_v1_split_2!F6,services_v8_v1_split_1!F6)/COUNT(services_v8_v1_split_5!F6,services_v8_v1_split_4!F6,services_v8_v1_split_3!F6,services_v8_v1_split_2!F6,services_v8_v1_split_1!F6),0),"NA") -> 1 | G6: =IF($D6 = 1,ROUND(SUM(services_v8_v1_split_5!G6,services_v8_v1_split_4!G6,services_v8_v1_split_3!G6,services_v8_v1_split_2!G6,services_v8_v1_split_1!G6)/COUNT(services_v8_v1_split_5!G6,services_v8_v1_split_4!G6,services_v8_v1_split_3!G6,services_v8_v1_split_2!G6,services_v8_v1_split_1!G6),0),"NA") -> 1 | H6: =IF($E6 = 1,ROUND(SUM(services_v8_v1_split_5!H6,services_v8_v1_split_4!H6,services_v8_v1_split_3!H6,services_v8_v1_split_2!H6,services_v8_v1_split_1!H6)/COUNT(services_v8_v1_split_5!H6,services_v8_v1_split_4!H6,services_v8_v1_split_3!H6,services_v8_v1_split_2!H6,services_v8_v1_split_1!H6),0),"NA") -> 1 | I6: =IF($D6 = 1,ROUND(SUM(services_v8_v1_split_5!I6,services_v8_v1_split_4!I6,services_v8_v1_split_3!I6,services_v8_v1_split_2!I6,services_v8_v1_split_1!I6)/COUNT(services_v8_v1_split_5!I6,services_v8_v1_split_4!I6,services_v8_v1_split_3!I6,services_v8_v1_split_2!I6,services_v8_v1_split_1!I6),0),"NA") -> 1 | J6: =IF(AND(E6 = 1,F6=1),ROUND(SUM(services_v8_v1_split_5!J6,services_v8_v1_split_4!J6,services_v8_v1_split_3!J6,services_v8_v1_split_2!J6,services_v8_v1_split_1!J6)/COUNT(services_v8_v1_split_5!J6,services_v8_v1_split_4!J6,services_v8_v1_split_3!J6,services_v8_v1_split_2!J6,services_v8_v1_split_1!J6),0),"NA") -> 1 | K6: =IF($D6 = 1,ROUND(SUM(services_v8_v1_split_5!K6,services_v8_v1_split_4!K6,services_v8_v1_split_3!K6,services_v8_v1_split_2!K6,services_v8_v1_split_1!K6)/COUNT(services_v8_v1_split_5!K6,services_v8_v1_split_4!K6,services_v8_v1_split_3!K6,services_v8_v1_split_2!K6,services_v8_v1_split_1!K6),0),"NA") -> 1 | L6: =IF($D6 = 1,ROUND(SUM(services_v8_v1_split_5!L6,services_v8_v1_split_4!L6,services_v8_v1_split_3!L6,services_v8_v1_split_2!L6,services_v8_v1_split_1!L6)/COUNT(services_v8_v1_split_5!L6,services_v8_v1_split_4!L6,services_v8_v1_split_3!L6,services_v8_v1_split_2!L6,services_v8_v1_split_1!L6),0),"NA") -> 1 | M6: =IF($D6 = 1,ROUND(SUM(services_v8_v1_split_5!M6,services_v8_v1_split_4!M6,services_v8_v1_split_3!M6,services_v8_v1_split_2!M6,services_v8_v1_split_1!M6)/COUNT(services_v8_v1_split_5!M6,services_v8_v1_split_4!M6,services_v8_v1_split_3!M6,services_v8_v1_split_2!M6,services_v8_v1_split_1!M6),0),"NA") -> 1 | N6: =IF($D6 = 1,ROUND(SUM(services_v8_v1_split_5!N6,services_v8_v1_split_4!N6,services_v8_v1_split_3!N6,services_v8_v1_split_2!N6,services_v8_v1_split_1!N6)/COUNT(services_v8_v1_split_5!N6,services_v8_v1_split_4!N6,services_v8_v1_split_3!N6,services_v8_v1_split_2!N6,services_v8_v1_split_1!N6),0),"NA") -> 1 | O6: 2.2525892
A7: TD | B7: Question 6 | C7: 0 | D7: =ROUND(SUM(services_v8_v1_split_5!D7,services_v8_v1_split_4!D7,services_v8_v1_split_3!D7,services_v8_v1_split_2!D7,services_v8_v1_split_1!D7)/COUNT(services_v8_v1_split_5!D7,services_v8_v1_split_4!D7,services_v8_v1_split_3!D7,services_v8_v1_split_2!D7,services_v8_v1_split_1!D7),0) -> 1 | E7: =IF($D7 = 1,ROUND(SUM(services_v8_v1_split_5!E7,services_v8_v1_split_4!E7,services_v8_v1_split_3!E7,services_v8_v1_split_2!E7,services_v8_v1_split_1!E7)/COUNT(services_v8_v1_split_5!E7,services_v8_v1_split_4!E7,services_v8_v1_split_3!E7,services_v8_v1_split_2!E7,services_v8_v1_split_1!E7),0),"NA") -> 1 | F7: =IF($D7 = 1,ROUND(SUM(services_v8_v1_split_5!F7,services_v8_v1_split_4!F7,services_v8_v1_split_3!F7,services_v8_v1_split_2!F7,services_v8_v1_split_1!F7)/COUNT(services_v8_v1_split_5!F7,services_v8_v1_split_4!F7,services_v8_v1_split_3!F7,services_v8_v1_split_2!F7,services_v8_v1_split_1!F7),0),"NA") -> 1 | G7: =IF($D7 = 1,ROUND(SUM(services_v8_v1_split_5!G7,services_v8_v1_split_4!G7,services_v8_v1_split_3!G7,services_v8_v1_split_2!G7,services_v8_v1_split_1!G7)/COUNT(services_v8_v1_split_5!G7,services_v8_v1_split_4!G7,services_v8_v1_split_3!G7,services_v8_v1_split_2!G7,services_v8_v1_split_1!G7),0),"NA") -> 1 | H7: =IF($E7 = 1,ROUND(SUM(services_v8_v1_split_5!H7,services_v8_v1_split_4!H7,services_v8_v1_split_3!H7,services_v8_v1_split_2!H7,services_v8_v1_split_1!H7)/COUNT(services_v8_v1_split_5!H7,services_v8_v1_split_4!H7,services_v8_v1_split_3!H7,services_v8_v1_split_2!H7,services_v8_v1_split_1!H7),0),"NA") -> 1 | I7: =IF($D7 = 1,ROUND(SUM(services_v8_v1_split_5!I7,services_v8_v1_split_4!I7,services_v8_v1_split_3!I7,services_v8_v1_split_2!I7,services_v8_v1_split_1!I7)/COUNT(services_v8_v1_split_5!I7,services_v8_v1_split_4!I7,services_v8_v1_split_3!I7,services_v8_v1_split_2!I7,services_v8_v1_split_1!I7),0),"NA") -> 1 | J7: =IF(AND(E7 = 1,F7=1),ROUND(SUM(services_v8_v1_split_5!J7,services_v8_v1_split_4!J7,services_v8_v1_split_3!J7,services_v8_v1_split_2!J7,services_v8_v1_split_1!J7)/COUNT(services_v8_v1_split_5!J7,services_v8_v1_split_4!J7,services_v8_v1_split_3!J7,services_v8_v1_split_2!J7,services_v8_v1_split_1!J7),0),"NA") -> 1 | K7: =IF($D7 = 1,ROUND(SUM(services_v8_v1_split_5!K7,services_v8_v1_split_4!K7,services_v8_v1_split_3!K7,services_v8_v1_split_2!K7,services_v8_v1_split_1!K7)/COUNT(services_v8_v1_split_5!K7,services_v8_v1_split_4!K7,services_v8_v1_split_3!K7,services_v8_v1_split_2!K7,services_v8_v1_split_1!K7),0),"NA") -> 1 | L7: =IF($D7 = 1,ROUND(SUM(services_v8_v1_split_5!L7,services_v8_v1_split_4!L7,services_v8_v1_split_3!L7,services_v8_v1_split_2!L7,services_v8_v1_split_1!L7)/COUNT(services_v8_v1_split_5!L7,services_v8_v1_split_4!L7,services_v8_v1_split_3!L7,services_v8_v1_split_2!L7,services_v8_v1_split_1!L7),0),"NA") -> 1 | M7: =IF($D7 = 1,ROUND(SUM(services_v8_v1_split_5!M7,services_v8_v1_split_4!M7,services_v8_v1_split_3!M7,services_v8_v1_split_2!M7,services_v8_v1_split_1!M7)/COUNT(services_v8_v1_split_5!M7,services_v8_v1_split_4!M7,services_v8_v1_split_3!M7,services_v8_v1_split_2!M7,services_v8_v1_split_1!M7),0),"NA") -> 1 | N7: =IF($D7 = 1,ROUND(SUM(services_v8_v1_split_5!N7,services_v8_v1_split_4!N7,services_v8_v1_split_3!N7,services_v8_v1_split_2!N7,services_v8_v1_split_1!N7)/COUNT(services_v8_v1_split_5!N7,services_v8_v1_split_4!N7,services_v8_v1_split_3!N7,services_v8_v1_split_2!N7,services_v8_v1_split_1!N7),0),"NA") -> 1 | O7: 1.3041592
A8: TD | B8: Question 7 | C8: 0 | D8: =ROUND(SUM(services_v8_v1_split_5!D8,services_v8_v1_split_4!D8,services_v8_v1_split_3!D8,services_v8_v1_split_2!D8,services_v8_v1_split_1!D8)/COUNT(services_v8_v1_split_5!D8,services_v8_v1_split_4!D8,services_v8_v1_split_3!D8,services_v8_v1_split_2!D8,services_v8_v1_split_1!D8),0) -> 1 | E8: =IF($D8 = 1,ROUND(SUM(services_v8_v1_split_5!E8,services_v8_v1_split_4!E8,services_v8_v1_split_3!E8,services_v8_v1_split_2!E8,services_v8_v1_split_1!E8)/COUNT(services_v8_v1_split_5!E8,services_v8_v1_split_4!E8,services_v8_v1_split_3!E8,services_v8_v1_split_2!E8,services_v8_v1_split_1!E8),0),"NA") -> 1 | F8: =IF($D8 = 1,ROUND(SUM(services_v8_v1_split_5!F8,services_v8_v1_split_4!F8,services_v8_v1_split_3!F8,services_v8_v1_split_2!F8,services_v8_v1_split_1!F8)/COUNT(services_v8_v1_split_5!F8,services_v8_v1_split_4!F8,services_v8_v1_split_3!F8,services_v8_v1_split_2!F8,services_v8_v1_split_1!F8),0),"NA") -> 1 | G8: =IF($D8 = 1,ROUND(SUM(services_v8_v1_split_5!G8,services_v8_v1_split_4!G8,services_v8_v1_split_3!G8,services_v8_v1_split_2!G8,services_v8_v1_split_1!G8)/COUNT(services_v8_v1_split_5!G8,services_v8_v1_split_4!G8,services_v8_v1_split_3!G8,services_v8_v1_split_2!G8,services_v8_v1_split_1!G8),0),"NA") -> 1 | H8: =IF($E8 = 1,ROUND(SUM(services_v8_v1_split_5!H8,services_v8_v1_split_4!H8,services_v8_v1_split_3!H8,services_v8_v1_split_2!H8,services_v8_v1_split_1!H8)/COUNT(services_v8_v1_split_5!H8,services_v8_v1_split_4!H8,services_v8_v1_split_3!H8,services_v8_v1_split_2!H8,services_v8_v1_split_1!H8),0),"NA") -> 1 | I8: =IF($D8 = 1,ROUND(SUM(services_v8_v1_split_5!I8,services_v8_v1_split_4!I8,services_v8_v1_split_3!I8,services_v8_v1_split_2!I8,services_v8_v1_split_1!I8)/COUNT(services_v8_v1_split_5!I8,services_v8_v1_split_4!I8,services_v8_v1_split_3!I8,services_v8_v1_split_2!I8,services_v8_v1_split_1!I8),0),"NA") -> 1 | J8: =IF(AND(E8 = 1,F8=1),ROUND(SUM(services_v8_v1_split_5!J8,services_v8_v1_split_4!J8,services_v8_v1_split_3!J8,services_v8_v1_split_2!J8,services_v8_v1_split_1!J8)/COUNT(services_v8_v1_split_5!J8,services_v8_v1_split_4!J8,services_v8_v1_split_3!J8,services_v8_v1_split_2!J8,services_v8_v1_split_1!J8),0),"NA") -> 1 | K8: =IF($D8 = 1,ROUND(SUM(services_v8_v1_split_5!K8,services_v8_v1_split_4!K8,services_v8_v1_split_3!K8,services_v8_v1_split_2!K8,services_v8_v1_split_1!K8)/COUNT(services_v8_v1_split_5!K8,services_v8_v1_split_4!K8,services_v8_v1_split_3!K8,services_v8_v1_split_2!K8,services_v8_v1_split_1!K8),0),"NA") -> 1 | L8: =IF($D8 = 1,ROUND(SUM(services_v8_v1_split_5!L8,services_v8_v1_split_4!L8,services_v8_v1_split_3!L8,services_v8_v1_split_2!L8,services_v8_v1_split_1!L8)/COUNT(services_v8_v1_split_5!L8,services_v8_v1_split_4!L8,services_v8_v1_split_3!L8,services_v8_v1_split_2!L8,services_v8_v1_split_1!L8),0),"NA") -> 1 | M8: =IF($D8 = 1,ROUND(SUM(services_v8_v1_split_5!M8,services_v8_v1_split_4!M8,services_v8_v1_split_3!M8,services_v8_v1_split_2!M8,services_v8_v1_split_1!M8)/COUNT(services_v8_v1_split_5!M8,services_v8_v1_split_4!M8,services_v8_v1_split_3!M8,services_v8_v1_split_2!M8,services_v8_v1_split_1!M8),0),"NA") -> 1 | N8: =IF($D8 = 1,ROUND(SUM(services_v8_v1_split_5!N8,services_v8_v1_split_4!N8,services_v8_v1_split_3!N8,services_v8_v1_split_2!N8,services_v8_v1_split_1!N8)/COUNT(services_v8_v1_split_5!N8,services_v8_v1_split_4!N8,services_v8_v1_split_3!N8,services_v8_v1_split_2!N8,services_v8_v1_split_1!N8),0),"NA") -> 1 | O8: 2.1331723
A9: TD | B9: Question 8 | C9: 0 | D9: =ROUND(SUM(services_v8_v1_split_5!D9,services_v8_v1_split_4!D9,services_v8_v1_split_3!D9,services_v8_v1_split_2!D9,services_v8_v1_split_1!D9)/COUNT(services_v8_v1_split_5!D9,services_v8_v1_split_4!D9,services_v8_v1_split_3!D9,services_v8_v1_split_2!D9,services_v8_v1_split_1!D9),0) -> 1 | E9: =IF($D9 = 1,ROUND(SUM(services_v8_v1_split_5!E9,services_v8_v1_split_4!E9,services_v8_v1_split_3!E9,services_v8_v1_split_2!E9,services_v8_v1_split_1!E9)/COUNT(services_v8_v1_split_5!E9,services_v8_v1_split_4!E9,services_v8_v1_split_3!E9,services_v8_v1_split_2!E9,services_v8_v1_split_1!E9),0),"NA") -> 1 | F9: =IF($D9 = 1,ROUND(SUM(services_v8_v1_split_5!F9,services_v8_v1_split_4!F9,services_v8_v1_split_3!F9,services_v8_v1_split_2!F9,services_v8_v1_split_1!F9)/COUNT(services_v8_v1_split_5!F9,services_v8_v1_split_4!F9,services_v8_v1_split_3!F9,services_v8_v1_split_2!F9,services_v8_v1_split_1!F9),0),"NA") -> 1 | G9: =IF($D9 = 1,ROUND(SUM(services_v8_v1_split_5!G9,services_v8_v1_split_4!G9,services_v8_v1_split_3!G9,services_v8_v1_split_2!G9,services_v8_v1_split_1!G9)/COUNT(services_v8_v1_split_5!G9,services_v8_v1_split_4!G9,services_v8_v1_split_3!G9,services_v8_v1_split_2!G9,services_v8_v1_split_1!G9),0),"NA") -> 1 | H9: =IF($E9 = 1,ROUND(SUM(services_v8_v1_split_5!H9,services_v8_v1_split_4!H9,services_v8_v1_split_3!H9,services_v8_v1_split_2!H9,services_v8_v1_split_1!H9)/COUNT(services_v8_v1_split_5!H9,services_v8_v1_split_4!H9,services_v8_v1_split_3!H9,services_v8_v1_split_2!H9,services_v8_v1_split_1!H9),0),"NA") -> 1 | I9: =IF($D9 = 1,ROUND(SUM(services_v8_v1_split_5!I9,services_v8_v1_split_4!I9,services_v8_v1_split_3!I9,services_v8_v1_split_2!I9,services_v8_v1_split_1!I9)/COUNT(services_v8_v1_split_5!I9,services_v8_v1_split_4!I9,services_v8_v1_split_3!I9,services_v8_v1_split_2!I9,services_v8_v1_split_1!I9),0),"NA") -> 1 | J9: =IF(AND(E9 = 1,F9=1),ROUND(SUM(services_v8_v1_split_5!J9,services_v8_v1_split_4!J9,services_v8_v1_split_3!J9,services_v8_v1_split_2!J9,services_v8_v1_split_1!J9)/COUNT(services_v8_v1_split_5!J9,services_v8_v1_split_4!J9,services_v8_v1_split_3!J9,services_v8_v1_split_2!J9,services_v8_v1_split_1!J9),0),"NA") -> 1 | K9: =IF($D9 = 1,ROUND(SUM(services_v8_v1_split_5!K9,services_v8_v1_split_4!K9,services_v8_v1_split_3!K9,services_v8_v1_split_2!K9,services_v8_v1_split_1!K9)/COUNT(services_v8_v1_split_5!K9,services_v8_v1_split_4!K9,services_v8_v1_split_3!K9,services_v8_v1_split_2!K9,services_v8_v1_split_1!K9),0),"NA") -> 1 | L9: =IF($D9 = 1,ROUND(SUM(services_v8_v1_split_5!L9,services_v8_v1_split_4!L9,services_v8_v1_split_3!L9,services_v8_v1_split_2!L9,services_v8_v1_split_1!L9)/COUNT(services_v8_v1_split_5!L9,services_v8_v1_split_4!L9,services_v8_v1_split_3!L9,services_v8_v1_split_2!L9,services_v8_v1_split_1!L9),0),"NA") -> 1 | M9: =IF($D9 = 1,ROUND(SUM(services_v8_v1_split_5!M9,services_v8_v1_split_4!M9,services_v8_v1_split_3!M9,services_v8_v1_split_2!M9,services_v8_v1_split_1!M9)/COUNT(services_v8_v1_split_5!M9,services_v8_v1_split_4!M9,services_v8_v1_split_3!M9,services_v8_v1_split_2!M9,services_v8_v1_split_1!M9),0),"NA") -> 1 | N9: =IF($D9 = 1,ROUND(SUM(services_v8_v1_split_5!N9,services_v8_v1_split_4!N9,services_v8_v1_split_3!N9,services_v8_v1_split_2!N9,services_v8_v1_split_1!N9)/COUNT(services_v8_v1_split_5!N9,services_v8_v1_split_4!N9,services_v8_v1_split_3!N9,services_v8_v1_split_2!N9,services_v8_v1_split_1!N9),0),"NA") -> 1 | O9: 1.1178393
A10: TD | B10: Question 9 | C10: 0 | D10: =ROUND(SUM(services_v8_v1_split_5!D10,services_v8_v1_split_4!D10,services_v8_v1_split_3!D10,services_v8_v1_split_2!D10,services_v8_v1_split_1!D10)/COUNT(services_v8_v1_split_5!D10,services_v8_v1_split_4!D10,services_v8_v1_split_3!D10,services_v8_v1_split_2!D10,services_v8_v1_split_1!D10),0) -> 1 | E10: =IF($D10 = 1,ROUND(SUM(services_v8_v1_split_5!E10,services_v8_v1_split_4!E10,services_v8_v1_split_3!E10,services_v8_v1_split_2!E10,services_v8_v1_split_1!E10)/COUNT(services_v8_v1_split_5!E10,services_v8_v1_split_4!E10,services_v8_v1_split_3!E10,services_v8_v1_split_2!E10,services_v8_v1_split_1!E10),0),"NA") -> 1 | F10: =IF($D10 = 1,ROUND(SUM(services_v8_v1_split_5!F10,services_v8_v1_split_4!F10,services_v8_v1_split_3!F10,services_v8_v1_split_2!F10,services_v8_v1_split_1!F10)/COUNT(services_v8_v1_split_5!F10,services_v8_v1_split_4!F10,services_v8_v1_split_3!F10,services_v8_v1_split_2!F10,services_v8_v1_split_1!F10),0),"NA") -> 1 | G10: =IF($D10 = 1,ROUND(SUM(services_v8_v1_split_5!G10,services_v8_v1_split_4!G10,services_v8_v1_split_3!G10,services_v8_v1_split_2!G10,services_v8_v1_split_1!G10)/COUNT(services_v8_v1_split_5!G10,services_v8_v1_split_4!G10,services_v8_v1_split_3!G10,services_v8_v1_split_2!G10,services_v8_v1_split_1!G10),0),"NA") -> 1 | H10: =IF($E10 = 1,ROUND(SUM(services_v8_v1_split_5!H10,services_v8_v1_split_4!H10,services_v8_v1_split_3!H10,services_v8_v1_split_2!H10,services_v8_v1_split_1!H10)/COUNT(services_v8_v1_split_5!H10,services_v8_v1_split_4!H10,services_v8_v1_split_3!H10,services_v8_v1_split_2!H10,services_v8_v1_split_1!H10),0),"NA") -> 1 | I10: =IF($D10 = 1,ROUND(SUM(services_v8_v1_split_5!I10,services_v8_v1_split_4!I10,services_v8_v1_split_3!I10,services_v8_v1_split_2!I10,services_v8_v1_split_1!I10)/COUNT(services_v8_v1_split_5!I10,services_v8_v1_split_4!I10,services_v8_v1_split_3!I10,services_v8_v1_split_2!I10,services_v8_v1_split_1!I10),0),"NA") -> 1 | J10: =IF(AND(E10 = 1,F10=1),ROUND(SUM(services_v8_v1_split_5!J10,services_v8_v1_split_4!J10,services_v8_v1_split_3!J10,services_v8_v1_split_2!J10,services_v8_v1_split_1!J10)/COUNT(services_v8_v1_split_5!J10,services_v8_v1_split_4!J10,services_v8_v1_split_3!J10,services_v8_v1_split_2!J10,services_v8_v1_split_1!J10),0),"NA") -> 1 | K10: =IF($D10 = 1,ROUND(SUM(services_v8_v1_split_5!K10,services_v8_v1_split_4!K10,services_v8_v1_split_3!K10,services_v8_v1_split_2!K10,services_v8_v1_split_1!K10)/COUNT(services_v8_v1_split_5!K10,services_v8_v1_split_4!K10,services_v8_v1_split_3!K10,services_v8_v1_split_2!K10,services_v8_v1_split_1!K10),0),"NA") -> 1 | L10: =IF($D10 = 1,ROUND(SUM(services_v8_v1_split_5!L10,services_v8_v1_split_4!L10,services_v8_v1_split_3!L10,services_v8_v1_split_2!L10,services_v8_v1_split_1!L10)/COUNT(services_v8_v1_split_5!L10,services_v8_v1_split_4!L10,services_v8_v1_split_3!L10,services_v8_v1_split_2!L10,services_v8_v1_split_1!L10),0),"NA") -> 1 | M10: =IF($D10 = 1,ROUND(SUM(services_v8_v1_split_5!M10,services_v8_v1_split_4!M10,services_v8_v1_split_3!M10,services_v8_v1_split_2!M10,services_v8_v1_split_1!M10)/COUNT(services_v8_v1_split_5!M10,services_v8_v1_split_4!M10,services_v8_v1_split_3!M10,services_v8_v1_split_2!M10,services_v8_v1_split_1!M10),0),"NA") -> 1 | N10: =IF($D10 = 1,ROUND(SUM(services_v8_v1_split_5!N10,services_v8_v1_split_4!N10,services_v8_v1_split_3!N10,services_v8_v1_split_2!N10,services_v8_v1_split_1!N10)/COUNT(services_v8_v1_split_5!N10,services_v8_v1_split_4!N10,services_v8_v1_split_3!N10,services_v8_v1_split_2!N10,services_v8_v1_split_1!N10),0),"NA") -> 1 | O10: 1.2017143
A11: TD | B11: Question 10 | C11: 0 | D11: =ROUND(SUM(services_v8_v1_split_5!D11,services_v8_v1_split_4!D11,services_v8_v1_split_3!D11,services_v8_v1_split_2!D11,services_v8_v1_split_1!D11)/COUNT(services_v8_v1_split_5!D11,services_v8_v1_split_4!D11,services_v8_v1_split_3!D11,services_v8_v1_split_2!D11,services_v8_v1_split_1!D11),0) -> 1 | E11: =IF($D11 = 1,ROUND(SUM(services_v8_v1_split_5!E11,services_v8_v1_split_4!E11,services_v8_v1_split_3!E11,services_v8_v1_split_2!E11,services_v8_v1_split_1!E11)/COUNT(services_v8_v1_split_5!E11,services_v8_v1_split_4!E11,services_v8_v1_split_3!E11,services_v8_v1_split_2!E11,services_v8_v1_split_1!E11),0),"NA") -> 1 | F11: =IF($D11 = 1,ROUND(SUM(services_v8_v1_split_5!F11,services_v8_v1_split_4!F11,services_v8_v1_split_3!F11,services_v8_v1_split_2!F11,services_v8_v1_split_1!F11)/COUNT(services_v8_v1_split_5!F11,services_v8_v1_split_4!F11,services_v8_v1_split_3!F11,services_v8_v1_split_2!F11,services_v8_v1_split_1!F11),0),"NA") -> 1 | G11: =IF($D11 = 1,ROUND(SUM(services_v8_v1_split_5!G11,services_v8_v1_split_4!G11,services_v8_v1_split_3!G11,services_v8_v1_split_2!G11,services_v8_v1_split_1!G11)/COUNT(services_v8_v1_split_5!G11,services_v8_v1_split_4!G11,services_v8_v1_split_3!G11,services_v8_v1_split_2!G11,services_v8_v1_split_1!G11),0),"NA") -> 1 | H11: =IF($E11 = 1,ROUND(SUM(services_v8_v1_split_5!H11,services_v8_v1_split_4!H11,services_v8_v1_split_3!H11,services_v8_v1_split_2!H11,services_v8_v1_split_1!H11)/COUNT(services_v8_v1_split_5!H11,services_v8_v1_split_4!H11,services_v8_v1_split_3!H11,services_v8_v1_split_2!H11,services_v8_v1_split_1!H11),0),"NA") -> 1 | I11: =IF($D11 = 1,ROUND(SUM(services_v8_v1_split_5!I11,services_v8_v1_split_4!I11,services_v8_v1_split_3!I11,services_v8_v1_split_2!I11,services_v8_v1_split_1!I11)/COUNT(services_v8_v1_split_5!I11,services_v8_v1_split_4!I11,services_v8_v1_split_3!I11,services_v8_v1_split_2!I11,services_v8_v1_split_1!I11),0),"NA") -> 1 | J11: =IF(AND(E11 = 1,F11=1),ROUND(SUM(services_v8_v1_split_5!J11,services_v8_v1_split_4!J11,services_v8_v1_split_3!J11,services_v8_v1_split_2!J11,services_v8_v1_split_1!J11)/COUNT(services_v8_v1_split_5!J11,services_v8_v1_split_4!J11,services_v8_v1_split_3!J11,services_v8_v1_split_2!J11,services_v8_v1_split_1!J11),0),"NA") -> 1 | K11: =IF($D11 = 1,ROUND(SUM(services_v8_v1_split_5!K11,services_v8_v1_split_4!K11,services_v8_v1_split_3!K11,services_v8_v1_split_2!K11,services_v8_v1_split_1!K11)/COUNT(services_v8_v1_split_5!K11,services_v8_v1_split_4!K11,services_v8_v1_split_3!K11,services_v8_v1_split_2!K11,services_v8_v1_split_1!K11),0),"NA") -> 1 | L11: =IF($D11 = 1,ROUND(SUM(services_v8_v1_split_5!L11,services_v8_v1_split_4!L11,services_v8_v1_split_3!L11,services_v8_v1_split_2!L11,services_v8_v1_split_1!L11)/COUNT(services_v8_v1_split_5!L11,services_v8_v1_split_4!L11,services_v8_v1_split_3!L11,services_v8_v1_split_2!L11,services_v8_v1_split_1!L11),0),"NA") -> 1 | M11: =IF($D11 = 1,ROUND(SUM(services_v8_v1_split_5!M11,services_v8_v1_split_4!M11,services_v8_v1_split_3!M11,services_v8_v1_split_2!M11,services_v8_v1_split_1!M11)/COUNT(services_v8_v1_split_5!M11,services_v8_v1_split_4!M11,services_v8_v1_split_3!M11,services_v8_v1_split_2!M11,services_v8_v1_split_1!M11),0),"NA") -> 1 | N11: =IF($D11 = 1,ROUND(SUM(services_v8_v1_split_5!N11,services_v8_v1_split_4!N11,services_v8_v1_split_3!N11,services_v8_v1_split_2!N11,services_v8_v1_split_1!N11)/COUNT(services_v8_v1_split_5!N11,services_v8_v1_split_4!N11,services_v8_v1_split_3!N11,services_v8_v1_split_2!N11,services_v8_v1_split_1!N11),0),"NA") -> 1 | O11: 1.3063612
A12: TD | B12: Question 11 | C12: 0 | D12: =ROUND(SUM(services_v8_v1_split_5!D12,services_v8_v1_split_4!D12,services_v8_v1_split_3!D12,services_v8_v1_split_2!D12,services_v8_v1_split_1!D12)/COUNT(services_v8_v1_split_5!D12,services_v8_v1_split_4!D12,services_v8_v1_split_3!D12,services_v8_v1_split_2!D12,services_v8_v1_split_1!D12),0) -> 1 | E12: =IF($D12 = 1,ROUND(SUM(services_v8_v1_split_5!E12,services_v8_v1_split_4!E12,services_v8_v1_split_3!E12,services_v8_v1_split_2!E12,services_v8_v1_split_1!E12)/COUNT(services_v8_v1_split_5!E12,services_v8_v1_split_4!E12,services_v8_v1_split_3!E12,services_v8_v1_split_2!E12,services_v8_v1_split_1!E12),0),"NA") -> 1 | F12: =IF($D12 = 1,ROUND(SUM(services_v8_v1_split_5!F12,services_v8_v1_split_4!F12,services_v8_v1_split_3!F12,services_v8_v1_split_2!F12,services_v8_v1_split_1!F12)/COUNT(services_v8_v1_split_5!F12,services_v8_v1_split_4!F12,services_v8_v1_split_3!F12,services_v8_v1_split_2!F12,services_v8_v1_split_1!F12),0),"NA") -> 1 | G12: =IF($D12 = 1,ROUND(SUM(services_v8_v1_split_5!G12,services_v8_v1_split_4!G12,services_v8_v1_split_3!G12,services_v8_v1_split_2!G12,services_v8_v1_split_1!G12)/COUNT(services_v8_v1_split_5!G12,services_v8_v1_split_4!G12,services_v8_v1_split_3!G12,services_v8_v1_split_2!G12,services_v8_v1_split_1!G12),0),"NA") -> 1 | H12: =IF($E12 = 1,ROUND(SUM(services_v8_v1_split_5!H12,services_v8_v1_split_4!H12,services_v8_v1_split_3!H12,services_v8_v1_split_2!H12,services_v8_v1_split_1!H12)/COUNT(services_v8_v1_split_5!H12,services_v8_v1_split_4!H12,services_v8_v1_split_3!H12,services_v8_v1_split_2!H12,services_v8_v1_split_1!H12),0),"NA") -> 1 | I12: =IF($D12 = 1,ROUND(SUM(services_v8_v1_split_5!I12,services_v8_v1_split_4!I12,services_v8_v1_split_3!I12,services_v8_v1_split_2!I12,services_v8_v1_split_1!I12)/COUNT(services_v8_v1_split_5!I12,services_v8_v1_split_4!I12,services_v8_v1_split_3!I12,services_v8_v1_split_2!I12,services_v8_v1_split_1!I12),0),"NA") -> 1 | J12: =IF(AND(E12 = 1,F12=1),ROUND(SUM(services_v8_v1_split_5!J12,services_v8_v1_split_4!J12,services_v8_v1_split_3!J12,services_v8_v1_split_2!J12,services_v8_v1_split_1!J12)/COUNT(services_v8_v1_split_5!J12,services_v8_v1_split_4!J12,services_v8_v1_split_3!J12,services_v8_v1_split_2!J12,services_v8_v1_split_1!J12),0),"NA") -> 1 | K12: =IF($D12 = 1,ROUND(SUM(services_v8_v1_split_5!K12,services_v8_v1_split_4!K12,services_v8_v1_split_3!K12,services_v8_v1_split_2!K12,services_v8_v1_split_1!K12)/COUNT(services_v8_v1_split_5!K12,services_v8_v1_split_4!K12,services_v8_v1_split_3!K12,services_v8_v1_split_2!K12,services_v8_v1_split_1!K12),0),"NA") -> 1 | L12: =IF($D12 = 1,ROUND(SUM(services_v8_v1_split_5!L12,services_v8_v1_split_4!L12,services_v8_v1_split_3!L12,services_v8_v1_split_2!L12,services_v8_v1_split_1!L12)/COUNT(services_v8_v1_split_5!L12,services_v8_v1_split_4!L12,services_v8_v1_split_3!L12,services_v8_v1_split_2!L12,services_v8_v1_split_1!L12),0),"NA") -> 1 | M12: =IF($D12 = 1,ROUND(SUM(services_v8_v1_split_5!M12,services_v8_v1_split_4!M12,services_v8_v1_split_3!M12,services_v8_v1_split_2!M12,services_v8_v1_split_1!M12)/COUNT(services_v8_v1_split_5!M12,services_v8_v1_split_4!M12,services_v8_v1_split_3!M12,services_v8_v1_split_2!M12,services_v8_v1_split_1!M12),0),"NA") -> 1 | N12: =IF($D12 = 1,ROUND(SUM(services_v8_v1_split_5!N12,services_v8_v1_split_4!N12,services_v8_v1_split_3!N12,services_v8_v1_split_2!N12,services_v8_v1_split_1!N12)/COUNT(services_v8_v1_split_5!N12,services_v8_v1_split_4!N12,services_v8_v1_split_3!N12,services_v8_v1_split_2!N12,services_v8_v1_split_1!N12),0),"NA") -> 1 | O12: 2.1675339
A13: TD | B13: Question 12 | C13: 0 | D13: =ROUND(SUM(services_v8_v1_split_5!D13,services_v8_v1_split_4!D13,services_v8_v1_split_3!D13,services_v8_v1_split_2!D13,services_v8_v1_split_1!D13)/COUNT(services_v8_v1_split_5!D13,services_v8_v1_split_4!D13,services_v8_v1_split_3!D13,services_v8_v1_split_2!D13,services_v8_v1_split_1!D13),0) -> 1 | E13: =IF($D13 = 1,ROUND(SUM(services_v8_v1_split_5!E13,services_v8_v1_split_4!E13,services_v8_v1_split_3!E13,services_v8_v1_split_2!E13,services_v8_v1_split_1!E13)/COUNT(services_v8_v1_split_5!E13,services_v8_v1_split_4!E13,services_v8_v1_split_3!E13,services_v8_v1_split_2!E13,services_v8_v1_split_1!E13),0),"NA") -> 0 | F13: =IF($D13 = 1,ROUND(SUM(services_v8_v1_split_5!F13,services_v8_v1_split_4!F13,services_v8_v1_split_3!F13,services_v8_v1_split_2!F13,services_v8_v1_split_1!F13)/COUNT(services_v8_v1_split_5!F13,services_v8_v1_split_4!F13,services_v8_v1_split_3!F13,services_v8_v1_split_2!F13,services_v8_v1_split_1!F13),0),"NA") -> 1 | G13: =IF($D13 = 1,ROUND(SUM(services_v8_v1_split_5!G13,services_v8_v1_split_4!G13,services_v8_v1_split_3!G13,services_v8_v1_split_2!G13,services_v8_v1_split_1!G13)/COUNT(services_v8_v1_split_5!G13,services_v8_v1_split_4!G13,services_v8_v1_split_3!G13,services_v8_v1_split_2!G13,services_v8_v1_split_1!G13),0),"NA") -> 1 | H13: =IF($E13 = 1,ROUND(SUM(services_v8_v1_split_5!H13,services_v8_v1_split_4!H13,services_v8_v1_split_3!H13,services_v8_v1_split_2!H13,services_v8_v1_split_1!H13)/COUNT(services_v8_v1_split_5!H13,services_v8_v1_split_4!H13,services_v8_v1_split_3!H13,services_v8_v1_split_2!H13,services_v8_v1_split_1!H13),0),"NA") -> NA | I13: =IF($D13 = 1,ROUND(SUM(services_v8_v1_split_5!I13,services_v8_v1_split_4!I13,services_v8_v1_split_3!I13,services_v8_v1_split_2!I13,services_v8_v1_split_1!I13)/COUNT(services_v8_v1_split_5!I13,services_v8_v1_split_4!I13,services_v8_v1_split_3!I13,services_v8_v1_split_2!I13,services_v8_v1_split_1!I13),0),"NA") -> 1 | J13: =IF(AND(E13 = 1,F13=1),ROUND(SUM(services_v8_v1_split_5!J13,services_v8_v1_split_4!J13,services_v8_v1_split_3!J13,services_v8_v1_split_2!J13,services_v8_v1_split_1!J13)/COUNT(services_v8_v1_split_5!J13,services_v8_v1_split_4!J13,services_v8_v1_split_3!J13,services_v8_v1_split_2!J13,services_v8_v1_split_1!J13),0),"NA") -> NA | K13: =IF($D13 = 1,ROUND(SUM(services_v8_v1_split_5!K13,services_v8_v1_split_4!K13,services_v8_v1_split_3!K13,services_v8_v1_split_2!K13,services_v8_v1_split_1!K13)/COUNT(services_v8_v1_split_5!K13,services_v8_v1_split_4!K13,services_v8_v1_split_3!K13,services_v8_v1_split_2!K13,services_v8_v1_split_1!K13),0),"NA") -> 1 | L13: =IF($D13 = 1,ROUND(SUM(services_v8_v1_split_5!L13,services_v8_v1_split_4!L13,services_v8_v1_split_3!L13,services_v8_v1_split_2!L13,services_v8_v1_split_1!L13)/COUNT(services_v8_v1_split_5!L13,services_v8_v1_split_4!L13,services_v8_v1_split_3!L13,services_v8_v1_split_2!L13,services_v8_v1_split_1!L13),0),"NA") -> 1 | M13: =IF($D13 = 1,ROUND(SUM(services_v8_v1_split_5!M13,services_v8_v1_split_4!M13,services_v8_v1_split_3!M13,services_v8_v1_split_2!M13,services_v8_v1_split_1!M13)/COUNT(services_v8_v1_split_5!M13,services_v8_v1_split_4!M13,services_v8_v1_split_3!M13,services_v8_v1_split_2!M13,services_v8_v1_split_1!M13),0),"NA") -> 1 | N13: =IF($D13 = 1,ROUND(SUM(services_v8_v1_split_5!N13,services_v8_v1_split_4!N13,services_v8_v1_split_3!N13,services_v8_v1_split_2!N13,services_v8_v1_split_1!N13)/COUNT(services_v8_v1_split_5!N13,services_v8_v1_split_4!N13,services_v8_v1_split_3!N13,services_v8_v1_split_2!N13,services_v8_v1_split_1!N13),0),"NA") -> 1 | O13: 4.1346498
... A40: TD | B40: Question 39 | C40: 0 | D40: =ROUND(SUM(services_v8_v1_split_5!D40,services_v8_v1_split_4!D40,services_v8_v1_split_3!D40,services_v8_v1_split_2!D40,services_v8_v1_split_1!D40)/COUNT(services_v8_v1_split_5!D40,services_v8_v1_split_4!D40,services_v8_v1_split_3!D40,services_v8_v1_split_2!D40,services_v8_v1_split_1!D40),0) -> 1 | E40: =IF($D40 = 1,ROUND(SUM(services_v8_v1_split_5!E40,services_v8_v1_split_4!E40,services_v8_v1_split_3!E40,services_v8_v1_split_2!E40,services_v8_v1_split_1!E40)/COUNT(services_v8_v1_split_5!E40,services_v8_v1_split_4!E40,services_v8_v1_split_3!E40,services_v8_v1_split_2!E40,services_v8_v1_split_1!E40),0),"NA") -> 1 | F40: =IF($D40 = 1,ROUND(SUM(services_v8_v1_split_5!F40,services_v8_v1_split_4!F40,services_v8_v1_split_3!F40,services_v8_v1_split_2!F40,services_v8_v1_split_1!F40)/COUNT(services_v8_v1_split_5!F40,services_v8_v1_split_4!F40,services_v8_v1_split_3!F40,services_v8_v1_split_2!F40,services_v8_v1_split_1!F40),0),"NA") -> 1 | G40: =IF($D40 = 1,ROUND(SUM(services_v8_v1_split_5!G40,services_v8_v1_split_4!G40,services_v8_v1_split_3!G40,services_v8_v1_split_2!G40,services_v8_v1_split_1!G40)/COUNT(services_v8_v1_split_5!G40,services_v8_v1_split_4!G40,services_v8_v1_split_3!G40,services_v8_v1_split_2!G40,services_v8_v1_split_1!G40),0),"NA") -> 1 | H40: =IF($E40 = 1,ROUND(SUM(services_v8_v1_split_5!H40,services_v8_v1_split_4!H40,services_v8_v1_split_3!H40,services_v8_v1_split_2!H40,services_v8_v1_split_1!H40)/COUNT(services_v8_v1_split_5!H40,services_v8_v1_split_4!H40,services_v8_v1_split_3!H40,services_v8_v1_split_2!H40,services_v8_v1_split_1!H40),0),"NA") -> 1 | I40: =IF($D40 = 1,ROUND(SUM(services_v8_v1_split_5!I40,services_v8_v1_split_4!I40,services_v8_v1_split_3!I40,services_v8_v1_split_2!I40,services_v8_v1_split_1!I40)/COUNT(services_v8_v1_split_5!I40,services_v8_v1_split_4!I40,services_v8_v1_split_3!I40,services_v8_v1_split_2!I40,services_v8_v1_split_1!I40),0),"NA") -> 1 | J40: =IF(AND(E40 = 1,F40=1),ROUND(SUM(services_v8_v1_split_5!J40,services_v8_v1_split_4!J40,services_v8_v1_split_3!J40,services_v8_v1_split_2!J40,services_v8_v1_split_1!J40)/COUNT(services_v8_v1_split_5!J40,services_v8_v1_split_4!J40,services_v8_v1_split_3!J40,services_v8_v1_split_2!J40,services_v8_v1_split_1!J40),0),"NA") -> 1 | K40: =IF($D40 = 1,ROUND(SUM(services_v8_v1_split_5!K40,services_v8_v1_split_4!K40,services_v8_v1_split_3!K40,services_v8_v1_split_2!K40,services_v8_v1_split_1!K40)/COUNT(services_v8_v1_split_5!K40,services_v8_v1_split_4!K40,services_v8_v1_split_3!K40,services_v8_v1_split_2!K40,services_v8_v1_split_1!K40),0),"NA") -> 1 | L40: =IF($D40 = 1,ROUND(SUM(services_v8_v1_split_5!L40,services_v8_v1_split_4!L40,services_v8_v1_split_3!L40,services_v8_v1_split_2!L40,services_v8_v1_split_1!L40)/COUNT(services_v8_v1_split_5!L40,services_v8_v1_split_4!L40,services_v8_v1_split_3!L40,services_v8_v1_split_2!L40,services_v8_v1_split_1!L40),0),"NA") -> 1 | M40: =IF($D40 = 1,ROUND(SUM(services_v8_v1_split_5!M40,services_v8_v1_split_4!M40,services_v8_v1_split_3!M40,services_v8_v1_split_2!M40,services_v8_v1_split_1!M40)/COUNT(services_v8_v1_split_5!M40,services_v8_v1_split_4!M40,services_v8_v1_split_3!M40,services_v8_v1_split_2!M40,services_v8_v1_split_1!M40),0),"NA") -> 1 | N40: =IF($D40 = 1,ROUND(SUM(services_v8_v1_split_5!N40,services_v8_v1_split_4!N40,services_v8_v1_split_3!N40,services_v8_v1_split_2!N40,services_v8_v1_split_1!N40)/COUNT(services_v8_v1_split_5!N40,services_v8_v1_split_4!N40,services_v8_v1_split_3!N40,services_v8_v1_split_2!N40,services_v8_v1_split_1!N40),0),"NA") -> 1 | O40: 1.2322116
A41: TD | B41: Question 40 | C41: 0 | D41: =ROUND(SUM(services_v8_v1_split_5!D41,services_v8_v1_split_4!D41,services_v8_v1_split_3!D41,services_v8_v1_split_2!D41,services_v8_v1_split_1!D41)/COUNT(services_v8_v1_split_5!D41,services_v8_v1_split_4!D41,services_v8_v1_split_3!D41,services_v8_v1_split_2!D41,services_v8_v1_split_1!D41),0) -> 0 | E41: =IF($D41 = 1,ROUND(SUM(services_v8_v1_split_5!E41,services_v8_v1_split_4!E41,services_v8_v1_split_3!E41,services_v8_v1_split_2!E41,services_v8_v1_split_1!E41)/COUNT(services_v8_v1_split_5!E41,services_v8_v1_split_4!E41,services_v8_v1_split_3!E41,services_v8_v1_split_2!E41,services_v8_v1_split_1!E41),0),"NA") -> NA | F41: =IF($D41 = 1,ROUND(SUM(services_v8_v1_split_5!F41,services_v8_v1_split_4!F41,services_v8_v1_split_3!F41,services_v8_v1_split_2!F41,services_v8_v1_split_1!F41)/COUNT(services_v8_v1_split_5!F41,services_v8_v1_split_4!F41,services_v8_v1_split_3!F41,services_v8_v1_split_2!F41,services_v8_v1_split_1!F41),0),"NA") -> NA | G41: =IF($D41 = 1,ROUND(SUM(services_v8_v1_split_5!G41,services_v8_v1_split_4!G41,services_v8_v1_split_3!G41,services_v8_v1_split_2!G41,services_v8_v1_split_1!G41)/COUNT(services_v8_v1_split_5!G41,services_v8_v1_split_4!G41,services_v8_v1_split_3!G41,services_v8_v1_split_2!G41,services_v8_v1_split_1!G41),0),"NA") -> NA | H41: =IF($E41 = 1,ROUND(SUM(services_v8_v1_split_5!H41,services_v8_v1_split_4!H41,services_v8_v1_split_3!H41,services_v8_v1_split_2!H41,services_v8_v1_split_1!H41)/COUNT(services_v8_v1_split_5!H41,services_v8_v1_split_4!H41,services_v8_v1_split_3!H41,services_v8_v1_split_2!H41,services_v8_v1_split_1!H41),0),"NA") -> NA | I41: =IF($D41 = 1,ROUND(SUM(services_v8_v1_split_5!I41,services_v8_v1_split_4!I41,services_v8_v1_split_3!I41,services_v8_v1_split_2!I41,services_v8_v1_split_1!I41)/COUNT(services_v8_v1_split_5!I41,services_v8_v1_split_4!I41,services_v8_v1_split_3!I41,services_v8_v1_split_2!I41,services_v8_v1_split_1!I41),0),"NA") -> NA | J41: =IF(AND(E41 = 1,F41=1),ROUND(SUM(services_v8_v1_split_5!J41,services_v8_v1_split_4!J41,services_v8_v1_split_3!J41,services_v8_v1_split_2!J41,services_v8_v1_split_1!J41)/COUNT(services_v8_v1_split_5!J41,services_v8_v1_split_4!J41,services_v8_v1_split_3!J41,services_v8_v1_split_2!J41,services_v8_v1_split_1!J41),0),"NA") -> NA | K41: =IF($D41 = 1,ROUND(SUM(services_v8_v1_split_5!K41,services_v8_v1_split_4!K41,services_v8_v1_split_3!K41,services_v8_v1_split_2!K41,services_v8_v1_split_1!K41)/COUNT(services_v8_v1_split_5!K41,services_v8_v1_split_4!K41,services_v8_v1_split_3!K41,services_v8_v1_split_2!K41,services_v8_v1_split_1!K41),0),"NA") -> NA | L41: =IF($D41 = 1,ROUND(SUM(services_v8_v1_split_5!L41,services_v8_v1_split_4!L41,services_v8_v1_split_3!L41,services_v8_v1_split_2!L41,services_v8_v1_split_1!L41)/COUNT(services_v8_v1_split_5!L41,services_v8_v1_split_4!L41,services_v8_v1_split_3!L41,services_v8_v1_split_2!L41,services_v8_v1_split_1!L41),0),"NA") -> NA | M41: =IF($D41 = 1,ROUND(SUM(services_v8_v1_split_5!M41,services_v8_v1_split_4!M41,services_v8_v1_split_3!M41,services_v8_v1_split_2!M41,services_v8_v1_split_1!M41)/COUNT(services_v8_v1_split_5!M41,services_v8_v1_split_4!M41,services_v8_v1_split_3!M41,services_v8_v1_split_2!M41,services_v8_v1_split_1!M41),0),"NA") -> NA | N41: =IF($D41 = 1,ROUND(SUM(services_v8_v1_split_5!N41,services_v8_v1_split_4!N41,services_v8_v1_split_3!N41,services_v8_v1_split_2!N41,services_v8_v1_split_1!N41)/COUNT(services_v8_v1_split_5!N41,services_v8_v1_split_4!N41,services_v8_v1_split_3!N41,services_v8_v1_split_2!N41,services_v8_v1_split_1!N41),0),"NA") -> NA | O41: 3.2541349 | P41: 'NA
A42: TD | B42: Question 41 | C42: 0 | D42: =ROUND(SUM(services_v8_v1_split_5!D42,services_v8_v1_split_4!D42,services_v8_v1_split_3!D42,services_v8_v1_split_2!D42,services_v8_v1_split_1!D42)/COUNT(services_v8_v1_split_5!D42,services_v8_v1_split_4!D42,services_v8_v1_split_3!D42,services_v8_v1_split_2!D42,services_v8_v1_split_1!D42),0) -> 1 | E42: =IF($D42 = 1,ROUND(SUM(services_v8_v1_split_5!E42,services_v8_v1_split_4!E42,services_v8_v1_split_3!E42,services_v8_v1_split_2!E42,services_v8_v1_split_1!E42)/COUNT(services_v8_v1_split_5!E42,services_v8_v1_split_4!E42,services_v8_v1_split_3!E42,services_v8_v1_split_2!E42,services_v8_v1_split_1!E42),0),"NA") -> 1 | F42: =IF($D42 = 1,ROUND(SUM(services_v8_v1_split_5!F42,services_v8_v1_split_4!F42,services_v8_v1_split_3!F42,services_v8_v1_split_2!F42,services_v8_v1_split_1!F42)/COUNT(services_v8_v1_split_5!F42,services_v8_v1_split_4!F42,services_v8_v1_split_3!F42,services_v8_v1_split_2!F42,services_v8_v1_split_1!F42),0),"NA") -> 1 | G42: =IF($D42 = 1,ROUND(SUM(services_v8_v1_split_5!G42,services_v8_v1_split_4!G42,services_v8_v1_split_3!G42,services_v8_v1_split_2!G42,services_v8_v1_split_1!G42)/COUNT(services_v8_v1_split_5!G42,services_v8_v1_split_4!G42,services_v8_v1_split_3!G42,services_v8_v1_split_2!G42,services_v8_v1_split_1!G42),0),"NA") -> 1 | H42: =IF($E42 = 1,ROUND(SUM(services_v8_v1_split_5!H42,services_v8_v1_split_4!H42,services_v8_v1_split_3!H42,services_v8_v1_split_2!H42,services_v8_v1_split_1!H42)/COUNT(services_v8_v1_split_5!H42,services_v8_v1_split_4!H42,services_v8_v1_split_3!H42,services_v8_v1_split_2!H42,services_v8_v1_split_1!H42),0),"NA") -> 1 | I42: =IF($D42 = 1,ROUND(SUM(services_v8_v1_split_5!I42,services_v8_v1_split_4!I42,services_v8_v1_split_3!I42,services_v8_v1_split_2!I42,services_v8_v1_split_1!I42)/COUNT(services_v8_v1_split_5!I42,services_v8_v1_split_4!I42,services_v8_v1_split_3!I42,services_v8_v1_split_2!I42,services_v8_v1_split_1!I42),0),"NA") -> 1 | J42: =IF(AND(E42 = 1,F42=1),ROUND(SUM(services_v8_v1_split_5!J42,services_v8_v1_split_4!J42,services_v8_v1_split_3!J42,services_v8_v1_split_2!J42,services_v8_v1_split_1!J42)/COUNT(services_v8_v1_split_5!J42,services_v8_v1_split_4!J42,services_v8_v1_split_3!J42,services_v8_v1_split_2!J42,services_v8_v1_split_1!J42),0),"NA") -> 1 | K42: =IF($D42 = 1,ROUND(SUM(services_v8_v1_split_5!K42,services_v8_v1_split_4!K42,services_v8_v1_split_3!K42,services_v8_v1_split_2!K42,services_v8_v1_split_1!K42)/COUNT(services_v8_v1_split_5!K42,services_v8_v1_split_4!K42,services_v8_v1_split_3!K42,services_v8_v1_split_2!K42,services_v8_v1_split_1!K42),0),"NA") -> 1 | L42: =IF($D42 = 1,ROUND(SUM(services_v8_v1_split_5!L42,services_v8_v1_split_4!L42,services_v8_v1_split_3!L42,services_v8_v1_split_2!L42,services_v8_v1_split_1!L42)/COUNT(services_v8_v1_split_5!L42,services_v8_v1_split_4!L42,services_v8_v1_split_3!L42,services_v8_v1_split_2!L42,services_v8_v1_split_1!L42),0),"NA") -> 1 | M42: =IF($D42 = 1,ROUND(SUM(services_v8_v1_split_5!M42,services_v8_v1_split_4!M42,services_v8_v1_split_3!M42,services_v8_v1_split_2!M42,services_v8_v1_split_1!M42)/COUNT(services_v8_v1_split_5!M42,services_v8_v1_split_4!M42,services_v8_v1_split_3!M42,services_v8_v1_split_2!M42,services_v8_v1_split_1!M42),0),"NA") -> 1 | N42: =IF($D42 = 1,ROUND(SUM(services_v8_v1_split_5!N42,services_v8_v1_split_4!N42,services_v8_v1_split_3!N42,services_v8_v1_split_2!N42,services_v8_v1_split_1!N42)/COUNT(services_v8_v1_split_5!N42,services_v8_v1_split_4!N42,services_v8_v1_split_3!N42,services_v8_v1_split_2!N42,services_v8_v1_split_1!N42),0),"NA") -> 1 | O42: 1.2319939
A43: TD | B43: Question 42 | C43: 0 | D43: =ROUND(SUM(services_v8_v1_split_5!D43,services_v8_v1_split_4!D43,services_v8_v1_split_3!D43,services_v8_v1_split_2!D43,services_v8_v1_split_1!D43)/COUNT(services_v8_v1_split_5!D43,services_v8_v1_split_4!D43,services_v8_v1_split_3!D43,services_v8_v1_split_2!D43,services_v8_v1_split_1!D43),0) -> 1 | E43: =IF($D43 = 1,ROUND(SUM(services_v8_v1_split_5!E43,services_v8_v1_split_4!E43,services_v8_v1_split_3!E43,services_v8_v1_split_2!E43,services_v8_v1_split_1!E43)/COUNT(services_v8_v1_split_5!E43,services_v8_v1_split_4!E43,services_v8_v1_split_3!E43,services_v8_v1_split_2!E43,services_v8_v1_split_1!E43),0),"NA") -> 1 | F43: =IF($D43 = 1,ROUND(SUM(services_v8_v1_split_5!F43,services_v8_v1_split_4!F43,services_v8_v1_split_3!F43,services_v8_v1_split_2!F43,services_v8_v1_split_1!F43)/COUNT(services_v8_v1_split_5!F43,services_v8_v1_split_4!F43,services_v8_v1_split_3!F43,services_v8_v1_split_2!F43,services_v8_v1_split_1!F43),0),"NA") -> 1 | G43: =IF($D43 = 1,ROUND(SUM(services_v8_v1_split_5!G43,services_v8_v1_split_4!G43,services_v8_v1_split_3!G43,services_v8_v1_split_2!G43,services_v8_v1_split_1!G43)/COUNT(services_v8_v1_split_5!G43,services_v8_v1_split_4!G43,services_v8_v1_split_3!G43,services_v8_v1_split_2!G43,services_v8_v1_split_1!G43),0),"NA") -> 1 | H43: =IF($E43 = 1,ROUND(SUM(services_v8_v1_split_5!H43,services_v8_v1_split_4!H43,services_v8_v1_split_3!H43,services_v8_v1_split_2!H43,services_v8_v1_split_1!H43)/COUNT(services_v8_v1_split_5!H43,services_v8_v1_split_4!H43,services_v8_v1_split_3!H43,services_v8_v1_split_2!H43,services_v8_v1_split_1!H43),0),"NA") -> 1 | I43: =IF($D43 = 1,ROUND(SUM(services_v8_v1_split_5!I43,services_v8_v1_split_4!I43,services_v8_v1_split_3!I43,services_v8_v1_split_2!I43,services_v8_v1_split_1!I43)/COUNT(services_v8_v1_split_5!I43,services_v8_v1_split_4!I43,services_v8_v1_split_3!I43,services_v8_v1_split_2!I43,services_v8_v1_split_1!I43),0),"NA") -> 1 | J43: =IF(AND(E43 = 1,F43=1),ROUND(SUM(services_v8_v1_split_5!J43,services_v8_v1_split_4!J43,services_v8_v1_split_3!J43,services_v8_v1_split_2!J43,services_v8_v1_split_1!J43)/COUNT(services_v8_v1_split_5!J43,services_v8_v1_split_4!J43,services_v8_v1_split_3!J43,services_v8_v1_split_2!J43,services_v8_v1_split_1!J43),0),"NA") -> 1 | K43: =IF($D43 = 1,ROUND(SUM(services_v8_v1_split_5!K43,services_v8_v1_split_4!K43,services_v8_v1_split_3!K43,services_v8_v1_split_2!K43,services_v8_v1_split_1!K43)/COUNT(services_v8_v1_split_5!K43,services_v8_v1_split_4!K43,services_v8_v1_split_3!K43,services_v8_v1_split_2!K43,services_v8_v1_split_1!K43),0),"NA") -> 1 | L43: =IF($D43 = 1,ROUND(SUM(services_v8_v1_split_5!L43,services_v8_v1_split_4!L43,services_v8_v1_split_3!L43,services_v8_v1_split_2!L43,services_v8_v1_split_1!L43)/COUNT(services_v8_v1_split_5!L43,services_v8_v1_split_4!L43,services_v8_v1_split_3!L43,services_v8_v1_split_2!L43,services_v8_v1_split_1!L43),0),"NA") -> 1 | M43: =IF($D43 = 1,ROUND(SUM(services_v8_v1_split_5!M43,services_v8_v1_split_4!M43,services_v8_v1_split_3!M43,services_v8_v1_split_2!M43,services_v8_v1_split_1!M43)/COUNT(services_v8_v1_split_5!M43,services_v8_v1_split_4!M43,services_v8_v1_split_3!M43,services_v8_v1_split_2!M43,services_v8_v1_split_1!M43),0),"NA") -> 1 | N43: =IF($D43 = 1,ROUND(SUM(services_v8_v1_split_5!N43,services_v8_v1_split_4!N43,services_v8_v1_split_3!N43,services_v8_v1_split_2!N43,services_v8_v1_split_1!N43)/COUNT(services_v8_v1_split_5!N43,services_v8_v1_split_4!N43,services_v8_v1_split_3!N43,services_v8_v1_split_2!N43,services_v8_v1_split_1!N43),0),"NA") -> 1 | O43: 1.846683
A44: TD | B44: Question 43 | C44: 0 | D44: =ROUND(SUM(services_v8_v1_split_5!D44,services_v8_v1_split_4!D44,services_v8_v1_split_3!D44,services_v8_v1_split_2!D44,services_v8_v1_split_1!D44)/COUNT(services_v8_v1_split_5!D44,services_v8_v1_split_4!D44,services_v8_v1_split_3!D44,services_v8_v1_split_2!D44,services_v8_v1_split_1!D44),0) -> 1 | E44: =IF($D44 = 1,ROUND(SUM(services_v8_v1_split_5!E44,services_v8_v1_split_4!E44,services_v8_v1_split_3!E44,services_v8_v1_split_2!E44,services_v8_v1_split_1!E44)/COUNT(services_v8_v1_split_5!E44,services_v8_v1_split_4!E44,services_v8_v1_split_3!E44,services_v8_v1_split_2!E44,services_v8_v1_split_1!E44),0),"NA") -> 1 | F44: =IF($D44 = 1,ROUND(SUM(services_v8_v1_split_5!F44,services_v8_v1_split_4!F44,services_v8_v1_split_3!F44,services_v8_v1_split_2!F44,services_v8_v1_split_1!F44)/COUNT(services_v8_v1_split_5!F44,services_v8_v1_split_4!F44,services_v8_v1_split_3!F44,services_v8_v1_split_2!F44,services_v8_v1_split_1!F44),0),"NA") -> 1 | G44: =IF($D44 = 1,ROUND(SUM(services_v8_v1_split_5!G44,services_v8_v1_split_4!G44,services_v8_v1_split_3!G44,services_v8_v1_split_2!G44,services_v8_v1_split_1!G44)/COUNT(services_v8_v1_split_5!G44,services_v8_v1_split_4!G44,services_v8_v1_split_3!G44,services_v8_v1_split_2!G44,services_v8_v1_split_1!G44),0),"NA") -> 1 | H44: =IF($E44 = 1,ROUND(SUM(services_v8_v1_split_5!H44,services_v8_v1_split_4!H44,services_v8_v1_split_3!H44,services_v8_v1_split_2!H44,services_v8_v1_split_1!H44)/COUNT(services_v8_v1_split_5!H44,services_v8_v1_split_4!H44,services_v8_v1_split_3!H44,services_v8_v1_split_2!H44,services_v8_v1_split_1!H44),0),"NA") -> 1 | I44: =IF($D44 = 1,ROUND(SUM(services_v8_v1_split_5!I44,services_v8_v1_split_4!I44,services_v8_v1_split_3!I44,services_v8_v1_split_2!I44,services_v8_v1_split_1!I44)/COUNT(services_v8_v1_split_5!I44,services_v8_v1_split_4!I44,services_v8_v1_split_3!I44,services_v8_v1_split_2!I44,services_v8_v1_split_1!I44),0),"NA") -> 1 | J44: =IF(AND(E44 = 1,F44=1),ROUND(SUM(services_v8_v1_split_5!J44,services_v8_v1_split_4!J44,services_v8_v1_split_3!J44,services_v8_v1_split_2!J44,services_v8_v1_split_1!J44)/COUNT(services_v8_v1_split_5!J44,services_v8_v1_split_4!J44,services_v8_v1_split_3!J44,services_v8_v1_split_2!J44,services_v8_v1_split_1!J44),0),"NA") -> 1 | K44: =IF($D44 = 1,ROUND(SUM(services_v8_v1_split_5!K44,services_v8_v1_split_4!K44,services_v8_v1_split_3!K44,services_v8_v1_split_2!K44,services_v8_v1_split_1!K44)/COUNT(services_v8_v1_split_5!K44,services_v8_v1_split_4!K44,services_v8_v1_split_3!K44,services_v8_v1_split_2!K44,services_v8_v1_split_1!K44),0),"NA") -> 1 | L44: =IF($D44 = 1,ROUND(SUM(services_v8_v1_split_5!L44,services_v8_v1_split_4!L44,services_v8_v1_split_3!L44,services_v8_v1_split_2!L44,services_v8_v1_split_1!L44)/COUNT(services_v8_v1_split_5!L44,services_v8_v1_split_4!L44,services_v8_v1_split_3!L44,services_v8_v1_split_2!L44,services_v8_v1_split_1!L44),0),"NA") -> 1 | M44: =IF($D44 = 1,ROUND(SUM(services_v8_v1_split_5!M44,services_v8_v1_split_4!M44,services_v8_v1_split_3!M44,services_v8_v1_split_2!M44,services_v8_v1_split_1!M44)/COUNT(services_v8_v1_split_5!M44,services_v8_v1_split_4!M44,services_v8_v1_split_3!M44,services_v8_v1_split_2!M44,services_v8_v1_split_1!M44),0),"NA") -> 1 | N44: =IF($D44 = 1,ROUND(SUM(services_v8_v1_split_5!N44,services_v8_v1_split_4!N44,services_v8_v1_split_3!N44,services_v8_v1_split_2!N44,services_v8_v1_split_1!N44)/COUNT(services_v8_v1_split_5!N44,services_v8_v1_split_4!N44,services_v8_v1_split_3!N44,services_v8_v1_split_2!N44,services_v8_v1_split_1!N44),0),"NA") -> 1 | O44: 1.2119095
A45: TD | B45: Question 44 | C45: 0 | D45: =ROUND(SUM(services_v8_v1_split_5!D45,services_v8_v1_split_4!D45,services_v8_v1_split_3!D45,services_v8_v1_split_2!D45,services_v8_v1_split_1!D45)/COUNT(services_v8_v1_split_5!D45,services_v8_v1_split_4!D45,services_v8_v1_split_3!D45,services_v8_v1_split_2!D45,services_v8_v1_split_1!D45),0) -> 1 | E45: =IF($D45 = 1,ROUND(SUM(services_v8_v1_split_5!E45,services_v8_v1_split_4!E45,services_v8_v1_split_3!E45,services_v8_v1_split_2!E45,services_v8_v1_split_1!E45)/COUNT(services_v8_v1_split_5!E45,services_v8_v1_split_4!E45,services_v8_v1_split_3!E45,services_v8_v1_split_2!E45,services_v8_v1_split_1!E45),0),"NA") -> 1 | F45: =IF($D45 = 1,ROUND(SUM(services_v8_v1_split_5!F45,services_v8_v1_split_4!F45,services_v8_v1_split_3!F45,services_v8_v1_split_2!F45,services_v8_v1_split_1!F45)/COUNT(services_v8_v1_split_5!F45,services_v8_v1_split_4!F45,services_v8_v1_split_3!F45,services_v8_v1_split_2!F45,services_v8_v1_split_1!F45),0),"NA") -> 1 | G45: =IF($D45 = 1,ROUND(SUM(services_v8_v1_split_5!G45,services_v8_v1_split_4!G45,services_v8_v1_split_3!G45,services_v8_v1_split_2!G45,services_v8_v1_split_1!G45)/COUNT(services_v8_v1_split_5!G45,services_v8_v1_split_4!G45,services_v8_v1_split_3!G45,services_v8_v1_split_2!G45,services_v8_v1_split_1!G45),0),"NA") -> 1 | H45: =IF($E45 = 1,ROUND(SUM(services_v8_v1_split_5!H45,services_v8_v1_split_4!H45,services_v8_v1_split_3!H45,services_v8_v1_split_2!H45,services_v8_v1_split_1!H45)/COUNT(services_v8_v1_split_5!H45,services_v8_v1_split_4!H45,services_v8_v1_split_3!H45,services_v8_v1_split_2!H45,services_v8_v1_split_1!H45),0),"NA") -> 1 | I45: =IF($D45 = 1,ROUND(SUM(services_v8_v1_split_5!I45,services_v8_v1_split_4!I45,services_v8_v1_split_3!I45,services_v8_v1_split_2!I45,services_v8_v1_split_1!I45)/COUNT(services_v8_v1_split_5!I45,services_v8_v1_split_4!I45,services_v8_v1_split_3!I45,services_v8_v1_split_2!I45,services_v8_v1_split_1!I45),0),"NA") -> 1 | J45: =IF(AND(E45 = 1,F45=1),ROUND(SUM(services_v8_v1_split_5!J45,services_v8_v1_split_4!J45,services_v8_v1_split_3!J45,services_v8_v1_split_2!J45,services_v8_v1_split_1!J45)/COUNT(services_v8_v1_split_5!J45,services_v8_v1_split_4!J45,services_v8_v1_split_3!J45,services_v8_v1_split_2!J45,services_v8_v1_split_1!J45),0),"NA") -> 1 | K45: =IF($D45 = 1,ROUND(SUM(services_v8_v1_split_5!K45,services_v8_v1_split_4!K45,services_v8_v1_split_3!K45,services_v8_v1_split_2!K45,services_v8_v1_split_1!K45)/COUNT(services_v8_v1_split_5!K45,services_v8_v1_split_4!K45,services_v8_v1_split_3!K45,services_v8_v1_split_2!K45,services_v8_v1_split_1!K45),0),"NA") -> 1 | L45: =IF($D45 = 1,ROUND(SUM(services_v8_v1_split_5!L45,services_v8_v1_split_4!L45,services_v8_v1_split_3!L45,services_v8_v1_split_2!L45,services_v8_v1_split_1!L45)/COUNT(services_v8_v1_split_5!L45,services_v8_v1_split_4!L45,services_v8_v1_split_3!L45,services_v8_v1_split_2!L45,services_v8_v1_split_1!L45),0),"NA") -> 1 | M45: =IF($D45 = 1,ROUND(SUM(services_v8_v1_split_5!M45,services_v8_v1_split_4!M45,services_v8_v1_split_3!M45,services_v8_v1_split_2!M45,services_v8_v1_split_1!M45)/COUNT(services_v8_v1_split_5!M45,services_v8_v1_split_4!M45,services_v8_v1_split_3!M45,services_v8_v1_split_2!M45,services_v8_v1_split_1!M45),0),"NA") -> 1 | N45: =IF($D45 = 1,ROUND(SUM(services_v8_v1_split_5!N45,services_v8_v1_split_4!N45,services_v8_v1_split_3!N45,services_v8_v1_split_2!N45,services_v8_v1_split_1!N45)/COUNT(services_v8_v1_split_5!N45,services_v8_v1_split_4!N45,services_v8_v1_split_3!N45,services_v8_v1_split_2!N45,services_v8_v1_split_1!N45),0),"NA") -> 1 | O45: 1.8852866
A46: TD | B46: Question 45 | C46: 0 | D46: =ROUND(SUM(services_v8_v1_split_5!D46,services_v8_v1_split_4!D46,services_v8_v1_split_3!D46,services_v8_v1_split_2!D46,services_v8_v1_split_1!D46)/COUNT(services_v8_v1_split_5!D46,services_v8_v1_split_4!D46,services_v8_v1_split_3!D46,services_v8_v1_split_2!D46,services_v8_v1_split_1!D46),0) -> 1 | E46: =IF($D46 = 1,ROUND(SUM(services_v8_v1_split_5!E46,services_v8_v1_split_4!E46,services_v8_v1_split_3!E46,services_v8_v1_split_2!E46,services_v8_v1_split_1!E46)/COUNT(services_v8_v1_split_5!E46,services_v8_v1_split_4!E46,services_v8_v1_split_3!E46,services_v8_v1_split_2!E46,services_v8_v1_split_1!E46),0),"NA") -> 1 | F46: =IF($D46 = 1,ROUND(SUM(services_v8_v1_split_5!F46,services_v8_v1_split_4!F46,services_v8_v1_split_3!F46,services_v8_v1_split_2!F46,services_v8_v1_split_1!F46)/COUNT(services_v8_v1_split_5!F46,services_v8_v1_split_4!F46,services_v8_v1_split_3!F46,services_v8_v1_split_2!F46,services_v8_v1_split_1!F46),0),"NA") -> 1 | G46: =IF($D46 = 1,ROUND(SUM(services_v8_v1_split_5!G46,services_v8_v1_split_4!G46,services_v8_v1_split_3!G46,services_v8_v1_split_2!G46,services_v8_v1_split_1!G46)/COUNT(services_v8_v1_split_5!G46,services_v8_v1_split_4!G46,services_v8_v1_split_3!G46,services_v8_v1_split_2!G46,services_v8_v1_split_1!G46),0),"NA") -> 1 | H46: =IF($E46 = 1,ROUND(SUM(services_v8_v1_split_5!H46,services_v8_v1_split_4!H46,services_v8_v1_split_3!H46,services_v8_v1_split_2!H46,services_v8_v1_split_1!H46)/COUNT(services_v8_v1_split_5!H46,services_v8_v1_split_4!H46,services_v8_v1_split_3!H46,services_v8_v1_split_2!H46,services_v8_v1_split_1!H46),0),"NA") -> 1 | I46: =IF($D46 = 1,ROUND(SUM(services_v8_v1_split_5!I46,services_v8_v1_split_4!I46,services_v8_v1_split_3!I46,services_v8_v1_split_2!I46,services_v8_v1_split_1!I46)/COUNT(services_v8_v1_split_5!I46,services_v8_v1_split_4!I46,services_v8_v1_split_3!I46,services_v8_v1_split_2!I46,services_v8_v1_split_1!I46),0),"NA") -> 1 | J46: =IF(AND(E46 = 1,F46=1),ROUND(SUM(services_v8_v1_split_5!J46,services_v8_v1_split_4!J46,services_v8_v1_split_3!J46,services_v8_v1_split_2!J46,services_v8_v1_split_1!J46)/COUNT(services_v8_v1_split_5!J46,services_v8_v1_split_4!J46,services_v8_v1_split_3!J46,services_v8_v1_split_2!J46,services_v8_v1_split_1!J46),0),"NA") -> 1 | K46: =IF($D46 = 1,ROUND(SUM(services_v8_v1_split_5!K46,services_v8_v1_split_4!K46,services_v8_v1_split_3!K46,services_v8_v1_split_2!K46,services_v8_v1_split_1!K46)/COUNT(services_v8_v1_split_5!K46,services_v8_v1_split_4!K46,services_v8_v1_split_3!K46,services_v8_v1_split_2!K46,services_v8_v1_split_1!K46),0),"NA") -> 1 | L46: =IF($D46 = 1,ROUND(SUM(services_v8_v1_split_5!L46,services_v8_v1_split_4!L46,services_v8_v1_split_3!L46,services_v8_v1_split_2!L46,services_v8_v1_split_1!L46)/COUNT(services_v8_v1_split_5!L46,services_v8_v1_split_4!L46,services_v8_v1_split_3!L46,services_v8_v1_split_2!L46,services_v8_v1_split_1!L46),0),"NA") -> 1 | M46: =IF($D46 = 1,ROUND(SUM(services_v8_v1_split_5!M46,services_v8_v1_split_4!M46,services_v8_v1_split_3!M46,services_v8_v1_split_2!M46,services_v8_v1_split_1!M46)/COUNT(services_v8_v1_split_5!M46,services_v8_v1_split_4!M46,services_v8_v1_split_3!M46,services_v8_v1_split_2!M46,services_v8_v1_split_1!M46),0),"NA") -> 1 | N46: =IF($D46 = 1,ROUND(SUM(services_v8_v1_split_5!N46,services_v8_v1_split_4!N46,services_v8_v1_split_3!N46,services_v8_v1_split_2!N46,services_v8_v1_split_1!N46)/COUNT(services_v8_v1_split_5!N46,services_v8_v1_split_4!N46,services_v8_v1_split_3!N46,services_v8_v1_split_2!N46,services_v8_v1_split_1!N46),0),"NA") -> 1 | O46: 1.1833582
A47: TD | B47: Question 46 | C47: 0 | D47: =ROUND(SUM(services_v8_v1_split_5!D47,services_v8_v1_split_4!D47,services_v8_v1_split_3!D47,services_v8_v1_split_2!D47,services_v8_v1_split_1!D47)/COUNT(services_v8_v1_split_5!D47,services_v8_v1_split_4!D47,services_v8_v1_split_3!D47,services_v8_v1_split_2!D47,services_v8_v1_split_1!D47),0) -> 1 | E47: =IF($D47 = 1,ROUND(SUM(services_v8_v1_split_5!E47,services_v8_v1_split_4!E47,services_v8_v1_split_3!E47,services_v8_v1_split_2!E47,services_v8_v1_split_1!E47)/COUNT(services_v8_v1_split_5!E47,services_v8_v1_split_4!E47,services_v8_v1_split_3!E47,services_v8_v1_split_2!E47,services_v8_v1_split_1!E47),0),"NA") -> 1 | F47: =IF($D47 = 1,ROUND(SUM(services_v8_v1_split_5!F47,services_v8_v1_split_4!F47,services_v8_v1_split_3!F47,services_v8_v1_split_2!F47,services_v8_v1_split_1!F47)/COUNT(services_v8_v1_split_5!F47,services_v8_v1_split_4!F47,services_v8_v1_split_3!F47,services_v8_v1_split_2!F47,services_v8_v1_split_1!F47),0),"NA") -> 1 | G47: =IF($D47 = 1,ROUND(SUM(services_v8_v1_split_5!G47,services_v8_v1_split_4!G47,services_v8_v1_split_3!G47,services_v8_v1_split_2!G47,services_v8_v1_split_1!G47)/COUNT(services_v8_v1_split_5!G47,services_v8_v1_split_4!G47,services_v8_v1_split_3!G47,services_v8_v1_split_2!G47,services_v8_v1_split_1!G47),0),"NA") -> 1 | H47: =IF($E47 = 1,ROUND(SUM(services_v8_v1_split_5!H47,services_v8_v1_split_4!H47,services_v8_v1_split_3!H47,services_v8_v1_split_2!H47,services_v8_v1_split_1!H47)/COUNT(services_v8_v1_split_5!H47,services_v8_v1_split_4!H47,services_v8_v1_split_3!H47,services_v8_v1_split_2!H47,services_v8_v1_split_1!H47),0),"NA") -> 1 | I47: =IF($D47 = 1,ROUND(SUM(services_v8_v1_split_5!I47,services_v8_v1_split_4!I47,services_v8_v1_split_3!I47,services_v8_v1_split_2!I47,services_v8_v1_split_1!I47)/COUNT(services_v8_v1_split_5!I47,services_v8_v1_split_4!I47,services_v8_v1_split_3!I47,services_v8_v1_split_2!I47,services_v8_v1_split_1!I47),0),"NA") -> 1 | J47: =IF(AND(E47 = 1,F47=1),ROUND(SUM(services_v8_v1_split_5!J47,services_v8_v1_split_4!J47,services_v8_v1_split_3!J47,services_v8_v1_split_2!J47,services_v8_v1_split_1!J47)/COUNT(services_v8_v1_split_5!J47,services_v8_v1_split_4!J47,services_v8_v1_split_3!J47,services_v8_v1_split_2!J47,services_v8_v1_split_1!J47),0),"NA") -> 1 | K47: =IF($D47 = 1,ROUND(SUM(services_v8_v1_split_5!K47,services_v8_v1_split_4!K47,services_v8_v1_split_3!K47,services_v8_v1_split_2!K47,services_v8_v1_split_1!K47)/COUNT(services_v8_v1_split_5!K47,services_v8_v1_split_4!K47,services_v8_v1_split_3!K47,services_v8_v1_split_2!K47,services_v8_v1_split_1!K47),0),"NA") -> 1 | L47: =IF($D47 = 1,ROUND(SUM(services_v8_v1_split_5!L47,services_v8_v1_split_4!L47,services_v8_v1_split_3!L47,services_v8_v1_split_2!L47,services_v8_v1_split_1!L47)/COUNT(services_v8_v1_split_5!L47,services_v8_v1_split_4!L47,services_v8_v1_split_3!L47,services_v8_v1_split_2!L47,services_v8_v1_split_1!L47),0),"NA") -> 1 | M47: =IF($D47 = 1,ROUND(SUM(services_v8_v1_split_5!M47,services_v8_v1_split_4!M47,services_v8_v1_split_3!M47,services_v8_v1_split_2!M47,services_v8_v1_split_1!M47)/COUNT(services_v8_v1_split_5!M47,services_v8_v1_split_4!M47,services_v8_v1_split_3!M47,services_v8_v1_split_2!M47,services_v8_v1_split_1!M47),0),"NA") -> 1 | N47: =IF($D47 = 1,ROUND(SUM(services_v8_v1_split_5!N47,services_v8_v1_split_4!N47,services_v8_v1_split_3!N47,services_v8_v1_split_2!N47,services_v8_v1_split_1!N47)/COUNT(services_v8_v1_split_5!N47,services_v8_v1_split_4!N47,services_v8_v1_split_3!N47,services_v8_v1_split_2!N47,services_v8_v1_split_1!N47),0),"NA") -> 1 | O47: 1.1479435
A48: TD | B48: Question 47 | C48: 0 | D48: =ROUND(SUM(services_v8_v1_split_5!D48,services_v8_v1_split_4!D48,services_v8_v1_split_3!D48,services_v8_v1_split_2!D48,services_v8_v1_split_1!D48)/COUNT(services_v8_v1_split_5!D48,services_v8_v1_split_4!D48,services_v8_v1_split_3!D48,services_v8_v1_split_2!D48,services_v8_v1_split_1!D48),0) -> 1 | E48: =IF($D48 = 1,ROUND(SUM(services_v8_v1_split_5!E48,services_v8_v1_split_4!E48,services_v8_v1_split_3!E48,services_v8_v1_split_2!E48,services_v8_v1_split_1!E48)/COUNT(services_v8_v1_split_5!E48,services_v8_v1_split_4!E48,services_v8_v1_split_3!E48,services_v8_v1_split_2!E48,services_v8_v1_split_1!E48),0),"NA") -> 1 | F48: =IF($D48 = 1,ROUND(SUM(services_v8_v1_split_5!F48,services_v8_v1_split_4!F48,services_v8_v1_split_3!F48,services_v8_v1_split_2!F48,services_v8_v1_split_1!F48)/COUNT(services_v8_v1_split_5!F48,services_v8_v1_split_4!F48,services_v8_v1_split_3!F48,services_v8_v1_split_2!F48,services_v8_v1_split_1!F48),0),"NA") -> 1 | G48: =IF($D48 = 1,ROUND(SUM(services_v8_v1_split_5!G48,services_v8_v1_split_4!G48,services_v8_v1_split_3!G48,services_v8_v1_split_2!G48,services_v8_v1_split_1!G48)/COUNT(services_v8_v1_split_5!G48,services_v8_v1_split_4!G48,services_v8_v1_split_3!G48,services_v8_v1_split_2!G48,services_v8_v1_split_1!G48),0),"NA") -> 1 | H48: =IF($E48 = 1,ROUND(SUM(services_v8_v1_split_5!H48,services_v8_v1_split_4!H48,services_v8_v1_split_3!H48,services_v8_v1_split_2!H48,services_v8_v1_split_1!H48)/COUNT(services_v8_v1_split_5!H48,services_v8_v1_split_4!H48,services_v8_v1_split_3!H48,services_v8_v1_split_2!H48,services_v8_v1_split_1!H48),0),"NA") -> 1 | I48: =IF($D48 = 1,ROUND(SUM(services_v8_v1_split_5!I48,services_v8_v1_split_4!I48,services_v8_v1_split_3!I48,services_v8_v1_split_2!I48,services_v8_v1_split_1!I48)/COUNT(services_v8_v1_split_5!I48,services_v8_v1_split_4!I48,services_v8_v1_split_3!I48,services_v8_v1_split_2!I48,services_v8_v1_split_1!I48),0),"NA") -> 1 | J48: =IF(AND(E48 = 1,F48=1),ROUND(SUM(services_v8_v1_split_5!J48,services_v8_v1_split_4!J48,services_v8_v1_split_3!J48,services_v8_v1_split_2!J48,services_v8_v1_split_1!J48)/COUNT(services_v8_v1_split_5!J48,services_v8_v1_split_4!J48,services_v8_v1_split_3!J48,services_v8_v1_split_2!J48,services_v8_v1_split_1!J48),0),"NA") -> 1 | K48: =IF($D48 = 1,ROUND(SUM(services_v8_v1_split_5!K48,services_v8_v1_split_4!K48,services_v8_v1_split_3!K48,services_v8_v1_split_2!K48,services_v8_v1_split_1!K48)/COUNT(services_v8_v1_split_5!K48,services_v8_v1_split_4!K48,services_v8_v1_split_3!K48,services_v8_v1_split_2!K48,services_v8_v1_split_1!K48),0),"NA") -> 1 | L48: =IF($D48 = 1,ROUND(SUM(services_v8_v1_split_5!L48,services_v8_v1_split_4!L48,services_v8_v1_split_3!L48,services_v8_v1_split_2!L48,services_v8_v1_split_1!L48)/COUNT(services_v8_v1_split_5!L48,services_v8_v1_split_4!L48,services_v8_v1_split_3!L48,services_v8_v1_split_2!L48,services_v8_v1_split_1!L48),0),"NA") -> 1 | M48: =IF($D48 = 1,ROUND(SUM(services_v8_v1_split_5!M48,services_v8_v1_split_4!M48,services_v8_v1_split_3!M48,services_v8_v1_split_2!M48,services_v8_v1_split_1!M48)/COUNT(services_v8_v1_split_5!M48,services_v8_v1_split_4!M48,services_v8_v1_split_3!M48,services_v8_v1_split_2!M48,services_v8_v1_split_1!M48),0),"NA") -> 1 | N48: =IF($D48 = 1,ROUND(SUM(services_v8_v1_split_5!N48,services_v8_v1_split_4!N48,services_v8_v1_split_3!N48,services_v8_v1_split_2!N48,services_v8_v1_split_1!N48)/COUNT(services_v8_v1_split_5!N48,services_v8_v1_split_4!N48,services_v8_v1_split_3!N48,services_v8_v1_split_2!N48,services_v8_v1_split_1!N48),0),"NA") -> 1 | O48: 1.5750618
A49: TD | B49: Question 48 | C49: 0 | D49: =ROUND(SUM(services_v8_v1_split_5!D49,services_v8_v1_split_4!D49,services_v8_v1_split_3!D49,services_v8_v1_split_2!D49,services_v8_v1_split_1!D49)/COUNT(services_v8_v1_split_5!D49,services_v8_v1_split_4!D49,services_v8_v1_split_3!D49,services_v8_v1_split_2!D49,services_v8_v1_split_1!D49),0) -> 1 | E49: =IF($D49 = 1,ROUND(SUM(services_v8_v1_split_5!E49,services_v8_v1_split_4!E49,services_v8_v1_split_3!E49,services_v8_v1_split_2!E49,services_v8_v1_split_1!E49)/COUNT(services_v8_v1_split_5!E49,services_v8_v1_split_4!E49,services_v8_v1_split_3!E49,services_v8_v1_split_2!E49,services_v8_v1_split_1!E49),0),"NA") -> 1 | F49: =IF($D49 = 1,ROUND(SUM(services_v8_v1_split_5!F49,services_v8_v1_split_4!F49,services_v8_v1_split_3!F49,services_v8_v1_split_2!F49,services_v8_v1_split_1!F49)/COUNT(services_v8_v1_split_5!F49,services_v8_v1_split_4!F49,services_v8_v1_split_3!F49,services_v8_v1_split_2!F49,services_v8_v1_split_1!F49),0),"NA") -> 1 | G49: =IF($D49 = 1,ROUND(SUM(services_v8_v1_split_5!G49,services_v8_v1_split_4!G49,services_v8_v1_split_3!G49,services_v8_v1_split_2!G49,services_v8_v1_split_1!G49)/COUNT(services_v8_v1_split_5!G49,services_v8_v1_split_4!G49,services_v8_v1_split_3!G49,services_v8_v1_split_2!G49,services_v8_v1_split_1!G49),0),"NA") -> 1 | H49: =IF($E49 = 1,ROUND(SUM(services_v8_v1_split_5!H49,services_v8_v1_split_4!H49,services_v8_v1_split_3!H49,services_v8_v1_split_2!H49,services_v8_v1_split_1!H49)/COUNT(services_v8_v1_split_5!H49,services_v8_v1_split_4!H49,services_v8_v1_split_3!H49,services_v8_v1_split_2!H49,services_v8_v1_split_1!H49),0),"NA") -> 1 | I49: =IF($D49 = 1,ROUND(SUM(services_v8_v1_split_5!I49,services_v8_v1_split_4!I49,services_v8_v1_split_3!I49,services_v8_v1_split_2!I49,services_v8_v1_split_1!I49)/COUNT(services_v8_v1_split_5!I49,services_v8_v1_split_4!I49,services_v8_v1_split_3!I49,services_v8_v1_split_2!I49,services_v8_v1_split_1!I49),0),"NA") -> 1 | J49: =IF(AND(E49 = 1,F49=1),ROUND(SUM(services_v8_v1_split_5!J49,services_v8_v1_split_4!J49,services_v8_v1_split_3!J49,services_v8_v1_split_2!J49,services_v8_v1_split_1!J49)/COUNT(services_v8_v1_split_5!J49,services_v8_v1_split_4!J49,services_v8_v1_split_3!J49,services_v8_v1_split_2!J49,services_v8_v1_split_1!J49),0),"NA") -> 1 | K49: =IF($D49 = 1,ROUND(SUM(services_v8_v1_split_5!K49,services_v8_v1_split_4!K49,services_v8_v1_split_3!K49,services_v8_v1_split_2!K49,services_v8_v1_split_1!K49)/COUNT(services_v8_v1_split_5!K49,services_v8_v1_split_4!K49,services_v8_v1_split_3!K49,services_v8_v1_split_2!K49,services_v8_v1_split_1!K49),0),"NA") -> 1 | L49: =IF($D49 = 1,ROUND(SUM(services_v8_v1_split_5!L49,services_v8_v1_split_4!L49,services_v8_v1_split_3!L49,services_v8_v1_split_2!L49,services_v8_v1_split_1!L49)/COUNT(services_v8_v1_split_5!L49,services_v8_v1_split_4!L49,services_v8_v1_split_3!L49,services_v8_v1_split_2!L49,services_v8_v1_split_1!L49),0),"NA") -> 1 | M49: =IF($D49 = 1,ROUND(SUM(services_v8_v1_split_5!M49,services_v8_v1_split_4!M49,services_v8_v1_split_3!M49,services_v8_v1_split_2!M49,services_v8_v1_split_1!M49)/COUNT(services_v8_v1_split_5!M49,services_v8_v1_split_4!M49,services_v8_v1_split_3!M49,services_v8_v1_split_2!M49,services_v8_v1_split_1!M49),0),"NA") -> 1 | N49: =IF($D49 = 1,ROUND(SUM(services_v8_v1_split_5!N49,services_v8_v1_split_4!N49,services_v8_v1_split_3!N49,services_v8_v1_split_2!N49,services_v8_v1_split_1!N49)/COUNT(services_v8_v1_split_5!N49,services_v8_v1_split_4!N49,services_v8_v1_split_3!N49,services_v8_v1_split_2!N49,services_v8_v1_split_1!N49),0),"NA") -> 1 | O49: 1.7821221
A50: TD | B50: Question 49 | C50: 0 | D50: =ROUND(SUM(services_v8_v1_split_5!D50,services_v8_v1_split_4!D50,services_v8_v1_split_3!D50,services_v8_v1_split_2!D50,services_v8_v1_split_1!D50)/COUNT(services_v8_v1_split_5!D50,services_v8_v1_split_4!D50,services_v8_v1_split_3!D50,services_v8_v1_split_2!D50,services_v8_v1_split_1!D50),0) -> 1 | E50: =IF($D50 = 1,ROUND(SUM(services_v8_v1_split_5!E50,services_v8_v1_split_4!E50,services_v8_v1_split_3!E50,services_v8_v1_split_2!E50,services_v8_v1_split_1!E50)/COUNT(services_v8_v1_split_5!E50,services_v8_v1_split_4!E50,services_v8_v1_split_3!E50,services_v8_v1_split_2!E50,services_v8_v1_split_1!E50),0),"NA") -> 1 | F50: =IF($D50 = 1,ROUND(SUM(services_v8_v1_split_5!F50,services_v8_v1_split_4!F50,services_v8_v1_split_3!F50,services_v8_v1_split_2!F50,services_v8_v1_split_1!F50)/COUNT(services_v8_v1_split_5!F50,services_v8_v1_split_4!F50,services_v8_v1_split_3!F50,services_v8_v1_split_2!F50,services_v8_v1_split_1!F50),0),"NA") -> 1 | G50: =IF($D50 = 1,ROUND(SUM(services_v8_v1_split_5!G50,services_v8_v1_split_4!G50,services_v8_v1_split_3!G50,services_v8_v1_split_2!G50,services_v8_v1_split_1!G50)/COUNT(services_v8_v1_split_5!G50,services_v8_v1_split_4!G50,services_v8_v1_split_3!G50,services_v8_v1_split_2!G50,services_v8_v1_split_1!G50),0),"NA") -> 1 | H50: =IF($E50 = 1,ROUND(SUM(services_v8_v1_split_5!H50,services_v8_v1_split_4!H50,services_v8_v1_split_3!H50,services_v8_v1_split_2!H50,services_v8_v1_split_1!H50)/COUNT(services_v8_v1_split_5!H50,services_v8_v1_split_4!H50,services_v8_v1_split_3!H50,services_v8_v1_split_2!H50,services_v8_v1_split_1!H50),0),"NA") -> 1 | I50: =IF($D50 = 1,ROUND(SUM(services_v8_v1_split_5!I50,services_v8_v1_split_4!I50,services_v8_v1_split_3!I50,services_v8_v1_split_2!I50,services_v8_v1_split_1!I50)/COUNT(services_v8_v1_split_5!I50,services_v8_v1_split_4!I50,services_v8_v1_split_3!I50,services_v8_v1_split_2!I50,services_v8_v1_split_1!I50),0),"NA") -> 1 | J50: =IF(AND(E50 = 1,F50=1),ROUND(SUM(services_v8_v1_split_5!J50,services_v8_v1_split_4!J50,services_v8_v1_split_3!J50,services_v8_v1_split_2!J50,services_v8_v1_split_1!J50)/COUNT(services_v8_v1_split_5!J50,services_v8_v1_split_4!J50,services_v8_v1_split_3!J50,services_v8_v1_split_2!J50,services_v8_v1_split_1!J50),0),"NA") -> 1 | K50: =IF($D50 = 1,ROUND(SUM(services_v8_v1_split_5!K50,services_v8_v1_split_4!K50,services_v8_v1_split_3!K50,services_v8_v1_split_2!K50,services_v8_v1_split_1!K50)/COUNT(services_v8_v1_split_5!K50,services_v8_v1_split_4!K50,services_v8_v1_split_3!K50,services_v8_v1_split_2!K50,services_v8_v1_split_1!K50),0),"NA") -> 1 | L50: =IF($D50 = 1,ROUND(SUM(services_v8_v1_split_5!L50,services_v8_v1_split_4!L50,services_v8_v1_split_3!L50,services_v8_v1_split_2!L50,services_v8_v1_split_1!L50)/COUNT(services_v8_v1_split_5!L50,services_v8_v1_split_4!L50,services_v8_v1_split_3!L50,services_v8_v1_split_2!L50,services_v8_v1_split_1!L50),0),"NA") -> 1 | M50: =IF($D50 = 1,ROUND(SUM(services_v8_v1_split_5!M50,services_v8_v1_split_4!M50,services_v8_v1_split_3!M50,services_v8_v1_split_2!M50,services_v8_v1_split_1!M50)/COUNT(services_v8_v1_split_5!M50,services_v8_v1_split_4!M50,services_v8_v1_split_3!M50,services_v8_v1_split_2!M50,services_v8_v1_split_1!M50),0),"NA") -> 1 | N50: =IF($D50 = 1,ROUND(SUM(services_v8_v1_split_5!N50,services_v8_v1_split_4!N50,services_v8_v1_split_3!N50,services_v8_v1_split_2!N50,services_v8_v1_split_1!N50)/COUNT(services_v8_v1_split_5!N50,services_v8_v1_split_4!N50,services_v8_v1_split_3!N50,services_v8_v1_split_2!N50,services_v8_v1_split_1!N50),0),"NA") -> 1 | O50: 1.1708722
