Workbook

Sheet householdfinance_v4_1
A1: Evaluator | B1: Question | C1: status | D1: answerability | E1: primary_kc_alignment | F1: secondary_kc_alignment | G1: topic_alignment | H1: grade_alignment | I1: real_world_feasibility | J1: synergy | K1: clarity | L1: conciseness_and_relevance | M1: language_quality | N1: content_appropriateness | O1: explanation | P1: response_time | Q1: language_quality1
A2: TD | B2: Question 1 | C2: 0 | D2: 1 | E2: 1 | F2: 1 | G2: 1 | H2: 1 | I2: 1 | J2: 1 | K2: 1 | L2: 1 | M2: 1 | N2: 1 | P2: 2.7986028
A3: TD | B3: Question 2 | C3: 0 | D3: 1 | E3: 1 | F3: 0 | G3: 1 | H3: 1 | I3: 1 | J3: 'NA | K3: 1 | L3: 1 | M3: 1 | N3: 1 | O3: secondary_kc_alignment: The problem only requires subtraction (450 - 215) to find out how much Sarah spent before her father gave extra money. The extra $80 from her father is not needed to solve the problem, so addition is not necessary. synergy: Addition and subtraction are not used together to solve for the answer; only subtraction is needed. | P3: 2.7419116
A4: TD | B4: Question 3 | C4: 0 | D4: 1 | E4: 1 | F4: 1 | G4: 0 | H4: 1 | I4: 1 | J4: 1 | K4: 1 | L4: 1 | M4: 1 | N4: 1 | O4: D4*: The context describes sharing candies among children, which does not explicitly connect to the intended topic of 'Household finance such as income, utility bills, money, interest, savings, instalment, mortgage, financial planning etc.' The math situation is more about fair sharing/division with remainders, not a financial scenario. | P4: 2.2084112
A5: TD | B5: Question 4 | C5: 0 | D5: 1 | E5: 1 | F5: 1 | G5: 1 | H5: 1 | I5: 1 | J5: 1 | K5: 1 | L5: 1 | M5: 1 | N5: 1 | P5: 1.2284405
A6: TD | B6: Question 5 | C6: 0 | D6: 1 | E6: 1 | F6: 1 | G6: 1 | H6: 1 | I6: 1 | J6: 1 | K6: 1 | L6: 1 | M6: 1 | N6: 1 | P6: 1.4809985
A7: TD | B7: Question 6 | C7: 0 | D7: 1 | E7: 1 | F7: 1 | G7: 1 | H7: 1 | I7: 1 | J7: 1 | K7: 1 | L7: 1 | M7: 1 | N7: 1 | P7: 1.590306
A8: TD | B8: Question 7 | C8: 0 | D8: 1 | E8: 1 | F8: 1 | G8: 0 | H8: 1 | I8: 1 | J8: 1 | K8: 1 | L8: 1 | M8: 1 | N8: 1 | O8: D4: The scenario is about purchasing light bulbs for a house, which is only loosely related to household finance. The context does not directly address financial elements such as cost, budgeting, expenses, or savings, which are core to the intended topic of household finance. | P8: 1.7504017
A9: TD | B9: Question 8 | C9: 0 | D9: 1 | E9: 1 | F9: 1 | G9: 1 | H9: 1 | I9: 1 | J9: 1 | K9: 1 | L9: 1 | M9: 1 | N9: 1 | P9: 1.2563605
A10: TD | B10: Question 9 | C10: 0 | D10: 1 | E10: 1 | F10: 0 | G10: 1 | H10: 1 | I10: 1 | J10: 'NA | K10: 1 | L10: 1 | M10: 1 | N10: 1 | O10: Secondary KC Alignment: The problem does not require subtraction — only division is needed to answer the question. Synergy: Only division is required to solve for the amount each child receives; no combination of division and subtraction is needed. | P10: 1.7207451
A11: TD | B11: Question 10 | C11: 0 | D11: 1 | E11: 1 | F11: 1 | G11: 1 | H11: 1 | I11: 1 | J11: 1 | K11: 1 | L11: 1 | M11: 1 | N11: 1 | P11: 1.4076006
A12: TD | B12: Question 11 | C12: 0 | D12: 1 | E12: 1 | F12: 1 | G12: 1 | H12: 1 | I12: 1 | J12: 1 | K12: 1 | L12: 1 | M12: 1 | N12: 1 | P12: 1.5367053
A13: TD | B13: Question 12 | C13: 0 | D13: 1 | E13: 1 | F13: 1 | G13: 1 | H13: 1 | I13: 1 | J13: 1 | K13: 1 | L13: 1 | M13: 1 | N13: 1 | P13: 1.5695918
A14: TD | B14: Question 13 | C14: 0 | D14: 1 | E14: 0 | F14: 1 | G14: 1 | H14: 'NA | I14: 0 | J14: 'NA | K14: 1 | L14: 1 | M14: 1 | N14: 1 | O14: Primary KC alignment: 0 - Q(b) does not require students to add decimals to 2 decimal places; Q(a) is suitable but only requires standard addition, not more complex beyond 2DP. Grade alignment: 0 - The electricity bill in part (b) uses 3 decimal places ($45.605), which is beyond Primary 4 (which typically handles up to 2 decimal places). Real-world feasibility: 0 - Utility bills in Singapore (and nearly all real-world money contexts) do not use 3 decimal places, so a bill of $45.605 is not realistic. | P14: 6.1486974
A15: TD | B15: Question 14 | C15: 0 | D15: 1 | E15: 1 | F15: 1 | G15: 1 | H15: 1 | I15: 1 | J15: 1 | K15: 1 | L15: 1 | M15: 1 | N15: 1 | P15: 1.2660744
A16: TD | B16: Question 15 | C16: 0 | D16: 1 | E16: 1 | F16: 1 | G16: 1 | H16: 1 | I16: 1 | J16: 1 | K16: 1 | L16: 1 | M16: 1 | N16: 1 | P16: 1.7776628
A17: TD | B17: Question 16 | C17: 0 | D17: 1 | E17: 1 | F17: 1 | G17: 1 | H17: 1 | I17: 1 | J17: 1 | K17: 1 | L17: 1 | M17: 1 | N17: 1 | P17: 3.2931232
A18: TD | B18: Question 17 | C18: 0 | D18: 1 | E18: 1 | F18: 1 | G18: 1 | H18: 1 | I18: 1 | J18: 1 | K18: 1 | L18: 1 | M18: 1 | N18: 1 | P18: 1.2436643
A19: TD | B19: Question 18 | C19: 0 | D19: 1 | E19: 1 | F19: 1 | G19: 1 | H19: 1 | I19: 1 | J19: 1 | K19: 1 | L19: 1 | M19: 1 | N19: 1 | P19: 3.2166991
A20: TD | B20: Question 19 | C20: 0 | D20: 1 | E20: 1 | F20: 1 | G20: 1 | H20: 1 | I20: 1 | J20: 1 | K20: 1 | L20: 1 | M20: 1 | N20: 1 | P20: 1.2960212
A21: TD | B21: Question 20 | C21: 0 | D21: 1 | E21: 1 | F21: 1 | G21: 1 | H21: 1 | I21: 1 | J21: 1 | K21: 1 | L21: 1 | M21: 1 | N21: 1 | P21: 1.4096179
A22: TD | B22: Question 21 | C22: 0 | D22: 1 | E22: 1 | F22: 1 | G22: 1 | H22: 1 | I22: 1 | J22: 1 | K22: 1 | L22: 1 | M22: 1 | N22: 1 | P22: 1.304297
A23: TD | B23: Question 22 | C23: 0 | D23: 1 | E23: 1 | F23: 0 | G23: 1 | H23: 1 | I23: 1 | J23: 'NA | K23: 1 | L23: 1 | M23: 1 | N23: 1 | O23: Secondary KC Alignment: 0 - The intended secondary KC is comparing and ordering fractions, but the problem only compares a whole number ($90) with the computed fractional amount (which is a whole number after calculation). The question does not require comparing two fractions. Synergy: 0 - The solution requires the use of the primary KC (fraction multiplication), but does not require the secondary KC (comparing fractions), so the components are not used in tandem. | P23: 3.6889248
A24: TD | B24: Question 23 | C24: 0 | D24: 1 | E24: 1 | F24: 1 | G24: 1 | H24: 1 | I24: 1 | J24: 1 | K24: 1 | L24: 1 | M24: 1 | N24: 1 | P24: 3.231071
A25: TD | B25: Question 24 | C25: 0 | D25: 1 | E25: 1 | F25: 0 | G25: 1 | H25: 1 | I25: 1 | J25: 'NA | K25: 1 | L25: 1 | M25: 1 | N25: 1 | O25: Secondary KC Alignment: The problem only requires the use of multiplication of fractions sequentially. There is no requirement to add any fractions together in order to solve the problem, so Addition of Fractions is not targeted. Synergy: Only the Primary KC (Multiplication of Fractions) is needed for every operation in the sequence, so the word problem does not require both the Primary and Secondary KCs to work together. | P25: 2.0974202
A26: TD | B26: Question 25 | C26: 0 | D26: 1 | E26: 1 | F26: 1 | G26: 1 | H26: 1 | I26: 1 | J26: 1 | K26: 1 | L26: 1 | M26: 1 | N26: 1 | P26: 1.7663052
A27: TD | B27: Question 26 | C27: 0 | D27: 1 | E27: 1 | F27: 0 | G27: 0 | H27: 1 | I27: 1 | J27: 'NA | K27: 1 | L27: 1 | M27: 1 | N27: 1 | O27: 3-The secondary knowledge component is addition of fractions, but all calculations needed are multiplication and subtraction of fractions; at no point is adding of fractions required. 4-The context is about buying fruit juice for a gathering, which falls under food and daily life, not under household finance topic such as income, utility bills, or savings. | P27: 3.0723376
A28: TD | B28: Question 27 | C28: 0 | D28: 0 | E28: 'NA | F28: 'NA | G28: 'NA | H28: 'NA | I28: 'NA | J28: 'NA | K28: 'NA | L28: 'NA | M28: 1 | N28: 'NA | O28: answerability: The fractions '7/4' and '5/3' of the savings exceed 1 (whole), which is illogical since you cannot use more than 100% of the savings for each expense, thus the problem is not answerable.primary_kc_alignment: Multiplying the total by improper fractions greater than 1 is not a standard operation for allocation problems at Primary 5 and doesn't teach the intended KC properly, also the intended KC is multiplying two improper fractions, but the word problem only requires multiplying a whole by a fraction.secondary_kc_alignment: The subtraction is just simple whole number subtraction, not fraction subtraction between two fractional amounts.grade_alignment: The arithmetic involving improper fractions of a whole for allocations is beyond the typical level for Primary 5 and may confuse students.real_world_feasibility: No real-world scenario would have expenses that are more than the whole of one's savings for each category.synergy: The two KCs do not work in tandem, the student only applies fraction multiplication (using improper fractions unrealistically) and then does a subtraction with whole numbers, not with fractions. | P28: 3.8039804 | Q28: 'NA
A29: TD | B29: Question 28 | C29: 0 | D29: 1 | E29: 1 | F29: 1 | G29: 1 | H29: 1 | I29: 1 | J29: 1 | K29: 1 | L29: 1 | M29: 1 | N29: 1 | P29: 1.2004128
A30: TD | B30: Question 29 | C30: 0 | D30: 1 | E30: 1 | F30: 1 | G30: 0 | H30: 1 | I30: 1 | J30: 1 | K30: 1 | L30: 1 | M30: 1 | N30: 1 | O30: D-4: While the problem involves baking and the use of ingredients, it does NOT actually involve any of the specified household finance topics such as income, utility bills, money, interest, savings, instalment, mortgage, or financial planning. It stays in food preparation/consumption domain, not finance. | P30: 1.9118454
A31: TD | B31: Question 30 | C31: 0 | D31: 1 | E31: 0 | F31: 1 | G31: 1 | H31: 'NA | I31: 1 | J31: 'NA | K31: 1 | L31: 1 | M31: 1 | N31: 1 | O31: primary_kc_alignment: The main multiplication required is $3.75 [FORMULA] 100$ to get daily usage over 100 days (which equals 375), and then multiply by 0.174 (cost per kWh), so $375 [FORMULA] 0.174$. However, this does not require specifically multiplying decimals by 10, 100, 1000 and their multiples safely; it's normal decimal multiplication, but the focus is not explicitly on multiplying decimals by 10, 100, or 1000, as intended.[FORMULA]: The two parts (a) and (b) are independent; the answer from (a) is not required for (b), nor do they build on each other. | P31: 3.2674489
A32: TD | B32: Question 31 | C32: 0 | D32: 1 | E32: 0 | F32: 1 | G32: 1 | H32: 'NA | I32: 1 | J32: 'NA | K32: 1 | L32: 1 | M32: 1 | N32: 1 | O32: Primary KC Alignment: The problem describes decimal multiplication (73.245 × 0.15), but this involves multiplying decimals not specifically by 10, 100, 1000, or their multiples, which is what the intended KC targets. The product requires multiplying decimals generally, not scaling by powers of 10. Synergy: Subtraction should be applied after multiplication, but the scenario describes subtracting the service fee from the electricity cost, which is not actually correct since the fee should be added, not subtracted—this makes the synergy between multiplication and subtraction not logically coherent as per the premise. | P32: 2.662971
A33: TD | B33: Question 32 | C33: 0 | D33: 1 | E33: 1 | F33: 1 | G33: 1 | H33: 1 | I33: 1 | J33: 1 | K33: 1 | L33: 1 | M33: 1 | N33: 1 | P33: 2.6296833
A34: TD | B34: Question 33 | C34: 0 | D34: 1 | E34: 1 | F34: 1 | G34: 1 | H34: 1 | I34: 1 | J34: 1 | K34: 1 | L34: 1 | M34: 0 | N34: 1 | O34: language_quality: The use of '[FORMULA]' and decimal formatting ('$27.650') is not standard for financial notation—the correct format should be '$27.65'. This can confuse students and is considered a language/notation issue. | P34: 1.8400176
A35: TD | B35: Question 34 | C35: 0 | D35: 1 | E35: 1 | F35: 1 | G35: 1 | H35: 1 | I35: 1 | J35: 1 | K35: 1 | L35: 1 | M35: 1 | N35: 1 | P35: 1.5757596
A36: TD | B36: Question 35 | C36: 0 | D36: 1 | E36: 1 | F36: 1 | G36: 1 | H36: 1 | I36: 1 | J36: 1 | K36: 1 | L36: 1 | M36: 1 | N36: 1 | P36: 1.2426701
A37: TD | B37: Question 36 | C37: 0 | D37: 1 | E37: 1 | F37: 1 | G37: 1 | H37: 1 | I37: 1 | J37: 1 | K37: 1 | L37: 1 | M37: 1 | N37: 1 | P37: 1.2363698
A38: TD | B38: Question 37 | C38: 0 | D38: 1 | E38: 1 | F38: 1 | G38: 1 | H38: 1 | I38: 1 | J38: 1 | K38: 1 | L38: 1 | M38: 1 | N38: 1 | P38: 1.2000263
A39: TD | B39: Question 38 | C39: 0 | D39: 1 | E39: 0 | F39: 1 | G39: 0 | H39: 'NA | I39: 1 | J39: 'NA | K39: 1 | L39: 1 | M39: 1 | N39: 1 | O39: Primary KC Alignment: The intended primary KC is dividing a proper fraction by a whole number, but 2[FORMULA] (an improper/mixed fraction) divided by 5 is tested here, which is different in complexity from dividing a proper fraction. Topic Alignment: The scenario is about a school fundraiser and splitting cookies, which does not fit the intended topic of household finance (income, utility bills, money, etc.). | P39: 2.0618622
A40: TD | B40: Question 39 | C40: 0 | D40: 1 | E40: 0 | F40: 0 | G40: 1 | H40: 'NA | I40: 1 | J40: 'NA | K40: 1 | L40: 1 | M40: 1 | N40: 1 | O40: PRIMARY KC: The main operation needed is dividing $120$ by $3/4 [FORMULA] 120$ to find how many months the bills can be paid, but this results in dividing by a whole number (not a fraction by a fraction). The calculation required is $120 [FORMULA] 90$. SEC KC: No explicit need to subtract fractions; the subtraction is '120 - (2 [FORMULA] (3/4 [FORMULA] 120))', which is not subtraction of a fraction from a fraction or whole, so does not directly target the intended secondary KC. SYNERGY: The primary and secondary KCs are not necessary in tandem; the operations stand largely on their own and do not build off each other. | P40: 3.5045531
A41: TD | B41: Question 40 | C41: 0 | D41: 1 | E41: 0 | F41: 1 | G41: 1 | H41: 'NA | I41: 1 | J41: 'NA | K41: 1 | L41: 1 | M41: 1 | N41: 1 | O41: Primary KC Alignment: The main calculation required by the problem is to find $rac{3}{4}$ of a value (i.e., multiplying by a fraction), NOT dividing a whole number or proper fraction by a proper fraction, as the primary knowledge component specifies. The division required is division by 3 to share the amount equally, but not dividing by a fraction itself. (b) even asks about dividing 'by $[FORMULA]$' but the intention and logic is about multiplication. Synergy: The application of the Primary and Secondary KCs is not dependent—fraction division is not necessary; the only connection is fractional multiplication and then conversion to decimal. The sub-parts (a), (b), and (c) do not build on each other using outputs as direct inputs, except for the initial finding in (a). | P41: 3.4090862
A42: TD | B42: Question 41 | C42: 0 | D42: 1 | E42: 1 | F42: 0 | G42: 1 | H42: 1 | I42: 1 | J42: 'NA | K42: 1 | L42: 1 | M42: 1 | N42: 1 | O42: Secondary KC Alignment (0): The addition of grocery and transport expenses is given within the question, but the problem only asks for the total household expenses, which is to be found from the electricity expense and percentage. The secondary KC (addition) is not required to solve the problem, as the information relating to groceries and transport is irrelevant and not used. Synergy (0): The information provided on groceries and transport is not required for solving the main question, and there is no step in the solution where results from one part are needed for another. | P42: 2.4999948
A43: TD | B43: Question 42 | C43: 0 | D43: 1 | E43: 1 | F43: 1 | G43: 1 | H43: 1 | I43: 1 | J43: 1 | K43: 1 | L43: 1 | M43: 1 | N43: 1 | P43: 1.4830544
A44: TD | B44: Question 43 | C44: 0 | D44: 1 | E44: 1 | F44: 1 | G44: 1 | H44: 1 | I44: 1 | J44: 1 | K44: 1 | L44: 1 | M44: 1 | N44: 1 | P44: 1.1481886
A45: TD | B45: Question 44 | C45: 0 | D45: 1 | E45: 1 | F45: 1 | G45: 1 | H45: 1 | I45: 1 | J45: 1 | K45: 1 | L45: 1 | M45: 1 | N45: 1 | P45: 1.4787581
A46: TD | B46: Question 45 | C46: 0 | D46: 1 | E46: 1 | F46: 1 | G46: 1 | H46: 1 | I46: 1 | J46: 1 | K46: 1 | L46: 1 | M46: 1 | N46: 1 | P46: 1.8457277
A47: TD | B47: Question 46 | C47: 0 | D47: 1 | E47: 1 | F47: 1 | G47: 1 | H47: 1 | I47: 1 | J47: 1 | K47: 1 | L47: 1 | M47: 1 | N47: 1 | P47: 1.4440107
A48: TD | B48: Question 47 | C48: 0 | D48: 1 | E48: 1 | F48: 1 | G48: 1 | H48: 1 | I48: 1 | J48: 1 | K48: 1 | L48: 1 | M48: 1 | N48: 1 | P48: 1.4755998
A49: TD | B49: Question 48 | C49: 0 | D49: 1 | E49: 0 | F49: 1 | G49: 1 | H49: 'NA | I49: 1 | J49: 'NA | K49: 1 | L49: 1 | M49: 1 | N49: 1 | O49: Primary KC (matrix multiplication) is not satisfied because the question requires an element-wise (Hadamard) product, not a standard matrix multiplication, which is the expected KC for O-level matrix multiplication. The Hadamard product is not formally part of the standard curriculum at this level and does not meet the intended KC. | P49: 2.0184548
A50: TD | B50: Question 49 | C50: 0 | D50: 1 | E50: 1 | F50: 1 | G50: 1 | H50: 1 | I50: 1 | J50: 1 | K50: 1 | L50: 1 | M50: 1 | N50: 1 | P50: 1.2186029
A51: Minh | B51: Question 1 | C51: 0 | D51: 1 | E51: 1 | F51: 1 | G51: 1 | H51: 1 | I51: 1 | J51: 1 | K51: 1 | L51: 1 | M51: 1 | N51: 1 | P51: 1.1205363
A52: Minh | B52: Question 2 | C52: 0 | D52: 1 | E52: 1 | F52: 1 | G52: 1 | H52: 1 | I52: 1 | J52: 1 | K52: 1 | L52: 1 | M52: 1 | N52: 1 | P52: 1.3059199
A53: Minh | B53: Question 3 | C53: 0 | D53: 1 | E53: 1 | F53: 1 | G53: 1 | H53: 1 | I53: 1 | J53: 1 | K53: 1 | L53: 1 | M53: 1 | N53: 1 | P53: 1.130276
A54: Minh | B54: Question 4 | C54: 0 | D54: 1 | E54: 1 | F54: 1 | G54: 1 | H54: 1 | I54: 1 | J54: 1 | K54: 1 | L54: 1 | M54: 1 | N54: 1 | P54: 1.5797961
A55: Minh | B55: Question 5 | C55: 0 | D55: 1 | E55: 1 | F55: 1 | G55: 1 | H55: 1 | I55: 1 | J55: 1 | K55: 1 | L55: 1 | M55: 1 | N55: 1 | P55: 1.8469517
A56: Minh | B56: Question 6 | C56: 0 | D56: 1 | E56: 0 | F56: 1 | G56: 1 | H56: 'NA | I56: 1 | J56: 'NA | K56: 1 | L56: 1 | M56: 1 | N56: 1 | O56: Primary KC Alignment: The problem requires dividing 624 (a 3-digit number) by 8, which is a 1-digit divisor. However, the answer for 624 [FORMULA] 8 is 78, which is not up to 3 digits (since 78 is only 2 digits), so it does not fully require division of a 3-digit number by a 1-digit number in the expected context of difficulty (likely targets Primary 3, but the division gives a 2-digit answer). | P56: 4.3113143
A57: Minh | B57: Question 7 | C57: 0 | D57: 1 | E57: 1 | F57: 1 | G57: 1 | H57: 1 | I57: 1 | J57: 1 | K57: 1 | L57: 1 | M57: 1 | N57: 1 | P57: 1.1910369
A58: Minh | B58: Question 8 | C58: 0 | D58: 1 | E58: 1 | F58: 1 | G58: 0 | H58: 1 | I58: 1 | J58: 1 | K58: 1 | L58: 1 | M58: 1 | N58: 1 | O58: D-0 The topic is 'household finance such as income, utility bills, money, interest, savings, instalment, mortgage, financial planning etc.' but the problem is about personal spending of pocket money, which is not typically classified as household finance. Household finance refers more to issues concerning the management of money by a household or family, not individual personal expenditures of pocket money. | P58: 3.1404457
A59: Minh | B59: Question 9 | C59: 0 | D59: 1 | E59: 1 | F59: 1 | G59: 0 | H59: 1 | I59: 1 | J59: 1 | K59: 1 | L59: 1 | M59: 1 | N59: 1 | O59: 4: The context of the problem does not relate to 'household finance' as specified. It is about the total number of soap bars, not tracking spending, budgeting, income, or any financial aspect. The problem is about quantities, not financial calculations. | P59: 2.5940049
A60: Minh | B60: Question 10 | C60: 0 | D60: 1 | E60: 1 | F60: 1 | G60: 1 | H60: 1 | I60: 1 | J60: 1 | K60: 1 | L60: 1 | M60: 1 | N60: 1 | P60: 1.9688079
A61: Minh | B61: Question 11 | C61: 0 | D61: 1 | E61: 1 | F61: 1 | G61: 1 | H61: 1 | I61: 1 | J61: 1 | K61: 1 | L61: 1 | M61: 1 | N61: 1 | P61: 1.3689551
A62: Minh | B62: Question 12 | C62: 0 | D62: 1 | E62: 1 | F62: 1 | G62: 1 | H62: 1 | I62: 1 | J62: 1 | K62: 1 | L62: 1 | M62: 1 | N62: 1 | P62: 2.5433903
A63: Minh | B63: Question 13 | C63: 0 | D63: 1 | E63: 1 | F63: 1 | G63: 1 | H63: 1 | I63: 1 | J63: 1 | K63: 1 | L63: 1 | M63: 1 | N63: 1 | P63: 1.976619
A64: Minh | B64: Question 14 | C64: 0 | D64: 1 | E64: 1 | F64: 1 | G64: 1 | H64: 1 | I64: 1 | J64: 1 | K64: 1 | L64: 1 | M64: 1 | N64: 1 | P64: 1.2369099
A65: Minh | B65: Question 15 | C65: 0 | D65: 1 | E65: 1 | F65: 1 | G65: 1 | H65: 1 | I65: 1 | J65: 1 | K65: 1 | L65: 1 | M65: 1 | N65: 1 | P65: 1.0843596
A66: Minh | B66: Question 16 | C66: 0 | D66: 1 | E66: 1 | F66: 1 | G66: 1 | H66: 1 | I66: 1 | J66: 1 | K66: 1 | L66: 1 | M66: 1 | N66: 1 | P66: 1.2823005
A67: Minh | B67: Question 17 | C67: 0 | D67: 1 | E67: 1 | F67: 1 | G67: 1 | H67: 1 | I67: 1 | J67: 1 | K67: 1 | L67: 1 | M67: 1 | N67: 1 | P67: 1.1751907
A68: Minh | B68: Question 18 | C68: 0 | D68: 1 | E68: 1 | F68: 1 | G68: 1 | H68: 1 | I68: 1 | J68: 1 | K68: 1 | L68: 1 | M68: 1 | N68: 1 | P68: 1.75173
A69: Minh | B69: Question 19 | C69: 0 | D69: 1 | E69: 1 | F69: 1 | G69: 1 | H69: 1 | I69: 1 | J69: 1 | K69: 1 | L69: 1 | M69: 1 | N69: 1 | P69: 1.1277177
A70: Minh | B70: Question 20 | C70: 0 | D70: 1 | E70: 1 | F70: 1 | G70: 1 | H70: 1 | I70: 1 | J70: 1 | K70: 1 | L70: 1 | M70: 1 | N70: 1 | P70: 1.7189689
A71: Minh | B71: Question 21 | C71: 0 | D71: 1 | E71: 1 | F71: 0 | G71: 1 | H71: 1 | I71: 1 | J71: 'NA | K71: 1 | L71: 1 | M71: 1 | N71: 1 | O71: Secondary KC Alignment: The solution does not require subtracting fractions, only multiplication of fractions and subtraction of whole numbers, so the requirement of explicitly subtracting fractions is missing. Synergy: The problem does not require an interconnected use of the primary (fraction multiplication) and secondary (fraction subtraction) KCs—the subtraction step does not involve fractions as required by the secondary KC. | P71: 2.5765018
A72: Minh | B72: Question 22 | C72: 0 | D72: 1 | E72: 1 | F72: 1 | G72: 1 | H72: 1 | I72: 1 | J72: 1 | K72: 1 | L72: 1 | M72: 1 | N72: 1 | P72: 1.2376344
A73: Minh | B73: Question 23 | C73: 0 | D73: 1 | E73: 1 | F73: 1 | G73: 1 | H73: 1 | I73: 1 | J73: 1 | K73: 1 | L73: 1 | M73: 1 | N73: 1 | P73: 1.6657987
A74: Minh | B74: Question 24 | C74: 0 | D74: 1 | E74: 0 | F74: 0 | G74: 1 | H74: 'NA | I74: 1 | J74: 'NA | K74: 1 | L74: 1 | M74: 1 | N74: 1 | O74: Primary KC Alignment: For the amount ($12 [FORMULA] 2[FORMULA]$), it's multiplying a whole number (12) by a mixed number, but it's more directly about money calculation and does not require the specific skill of multiplying two fractions or a fraction and a whole number as intended. The multiplication here is not between two fractions but between a whole number and a mixed number (which is correct context but not maximally challenging for Primary 5 level on KC). Secondary KC Alignment: There are only whole numbers in both options for part (b). The comparison needed is between $30$ and the actual price (likely $30$ as well), with no fractions actually compared or ordered as per secondary KC. Synergy: The secondary KC is not used in the solution process—the information from part (a) and the maths required does not demand comparison or ordering of fractions, only comparison between two whole number amounts. | P74: 3.9924257
A75: Minh | B75: Question 25 | C75: 0 | D75: 1 | E75: 1 | F75: 1 | G75: 1 | H75: 1 | I75: 1 | J75: 1 | K75: 1 | L75: 1 | M75: 1 | N75: 1 | P75: 1.6688972
A76: Minh | B76: Question 26 | C76: 0 | D76: 1 | E76: 1 | F76: 1 | G76: 0 | H76: 1 | I76: 1 | J76: 1 | K76: 1 | L76: 1 | M76: 1 | N76: 1 | O76: 4: The context of the word problem (buying rice and its weight) does not align with 'household finance' topics such as money transactions, utility bills, savings, or financial planning. Instead, it fits more into everyday life or shopping rather than financial literacy. | P76: 2.0363793
A77: Minh | B77: Question 27 | C77: 0 | D77: 1 | E77: 0 | F77: 1 | G77: 1 | H77: 'NA | I77: 1 | J77: 'NA | K77: 1 | L77: 1 | M77: 1 | N77: 1 | O77: Primary KC alignment is 0: The main calculation is multiplying two decimals (132.768 × 0.183), but this does not involve multiplying a decimal by 10, 100, 1000 or their multiples as the intent states. It is simply multiplying two decimals. Thus, the problem does not require the specific KC of 'multiplying decimals (up to 3 decimal places) by 10, 100, 1000 and their multiples.' | P77: 1.9452624
A78: Minh | B78: Question 28 | C78: 0 | D78: 1 | E78: 1 | F78: 1 | G78: 1 | H78: 1 | I78: 0 | J78: 1 | K78: 1 | L78: 1 | M78: 0 | N78: 1 | O78: 6. Real-World Feasibility: Amount $187.250 is not feasible as Singapore currency uses only 2 decimal places. Realistic money values would use $187.25 or $187.20 instead. 10. Language Quality: Use of '$187.250' is a formatting/notation error; standard money amounts do not contain 3 decimal places (in Singapore). | P78: 2.0860803
A79: Minh | B79: Question 29 | C79: 0 | D79: 1 | E79: 1 | F79: 1 | G79: 1 | H79: 1 | I79: 1 | J79: 1 | K79: 1 | L79: 1 | M79: 1 | N79: 1 | P79: 1.6815796
A80: Minh | B80: Question 30 | C80: 0 | D80: 1 | E80: 1 | F80: 1 | G80: 1 | H80: 1 | I80: 1 | J80: 1 | K80: 1 | L80: 1 | M80: 1 | N80: 1 | P80: 1.1946733
A81: Minh | B81: Question 31 | C81: 0 | D81: 1 | E81: 1 | F81: 1 | G81: 1 | H81: 1 | I81: 1 | J81: 1 | K81: 1 | L81: 1 | M81: 1 | N81: 1 | P81: 1.2610281
A82: Minh | B82: Question 32 | C82: 0 | D82: 1 | E82: 1 | F82: 1 | G82: 1 | H82: 1 | I82: 1 | J82: 1 | K82: 1 | L82: 1 | M82: 1 | N82: 1 | P82: 1.2933328
A83: Minh | B83: Question 33 | C83: 0 | D83: 1 | E83: 1 | F83: 1 | G83: 0 | H83: 1 | I83: 1 | J83: 1 | K83: 1 | L83: 1 | M83: 1 | N83: 1 | O83: 4: The word problem is centred around sharing cake after a family gathering, which is not related to the intended topic of household finance such as income, utility bills, money, interest, savings, instalment, mortgage, or financial planning. | P83: 1.5497334
A84: Minh | B84: Question 34 | C84: 0 | D84: 1 | E84: 1 | F84: 1 | G84: 1 | H84: 1 | I84: 1 | J84: 1 | K84: 1 | L84: 1 | M84: 1 | N84: 1 | P84: 1.2566729
A85: Minh | B85: Question 35 | C85: 0 | D85: 1 | E85: 1 | F85: 1 | G85: 0 | H85: 1 | I85: 1 | J85: 1 | K85: 1 | L85: 1 | M85: 1 | N85: 1 | O85: D- The context is not aligned with the intended topic 'Household finance such as income, utility bills, money, interest, savings, instalment, mortgage, financial planning etc.' even though it is related to household chores; repacking detergent is not directly a finance context as required. The word problem is about volume measurement and fractions, not about a financial matter. | P85: 1.9810894
A86: Minh | B86: Question 36 | C86: 0 | D86: 1 | E86: 1 | F86: 0 | G86: 1 | H86: 1 | I86: 1 | J86: 'NA | K86: 1 | L86: 1 | M86: 1 | N86: 1 | O86: Secondary KC Alignment (0): Subtraction is not needed in this question. The problem only requires finding the 'whole' given a part and a percentage. Synergy (0): Only percentage calculation is required; subtraction is not integrated at any point in the solution. | P86: 3.5413761
A87: Minh | B87: Question 37 | C87: 0 | D87: 1 | E87: 1 | F87: 1 | G87: 1 | H87: 1 | I87: 1 | J87: 1 | K87: 1 | L87: 1 | M87: 1 | N87: 1 | P87: 1.6027436
A88: Minh | B88: Question 38 | C88: 0 | D88: 1 | E88: 1 | F88: 1 | G88: 1 | H88: 1 | I88: 1 | J88: 1 | K88: 1 | L88: 1 | M88: 1 | N88: 1 | P88: 1.4863675
A89: Minh | B89: Question 39 | C89: 0 | D89: 1 | E89: 1 | F89: 1 | G89: 1 | H89: 1 | I89: 1 | J89: 1 | K89: 1 | L89: 1 | M89: 1 | N89: 1 | P89: 2.5318041
A90: Minh | B90: Question 40 | C90: 0 | D90: 1 | E90: 1 | F90: 1 | G90: 1 | H90: 1 | I90: 1 | J90: 1 | K90: 1 | L90: 1 | M90: 1 | N90: 1 | P90: 1.6583936
A91: Minh | B91: Question 41 | C91: 0 | D91: 1 | E91: 1 | F91: 1 | G91: 1 | H91: 1 | I91: 1 | J91: 1 | K91: 1 | L91: 1 | M91: 1 | N91: 1 | P91: 1.2424407
A92: Minh | B92: Question 42 | C92: 0 | D92: 1 | E92: 1 | F92: 1 | G92: 1 | H92: 1 | I92: 1 | J92: 1 | K92: 1 | L92: 1 | M92: 1 | N92: 1 | P92: 1.7367117
A93: Minh | B93: Question 43 | C93: 0 | D93: 1 | E93: 1 | F93: 1 | G93: 1 | H93: 1 | I93: 1 | J93: 1 | K93: 1 | L93: 1 | M93: 1 | N93: 1 | P93: 1.685225
A94: Minh | B94: Question 44 | C94: 0 | D94: 1 | E94: 1 | F94: 1 | G94: 1 | H94: 1 | I94: 1 | J94: 1 | K94: 1 | L94: 1 | M94: 1 | N94: 1 | P94: 1.7600179
A95: Minh | B95: Question 45 | C95: 0 | D95: 1 | E95: 1 | F95: 1 | G95: 1 | H95: 1 | I95: 1 | J95: 1 | K95: 1 | L95: 1 | M95: 1 | N95: 1 | P95: 1.4176497
A96: Minh | B96: Question 46 | C96: 0 | D96: 1 | E96: 1 | F96: 1 | G96: 1 | H96: 1 | I96: 1 | J96: 1 | K96: 1 | L96: 1 | M96: 1 | N96: 1 | P96: 1.242502
A97: Minh | B97: Question 47 | C97: 0 | D97: 1 | E97: 1 | F97: 1 | G97: 1 | H97: 1 | I97: 1 | J97: 1 | K97: 1 | L97: 1 | M97: 1 | N97: 1 | P97: 1.2041645
A98: Minh | B98: Question 48 | C98: 0 | D98: 1 | E98: 1 | F98: 1 | G98: 1 | H98: 1 | I98: 1 | J98: 1 | K98: 1 | L98: 1 | M98: 1 | N98: 1 | P98: 1.1524215
... A103: Minh | B103: Question 53 | C103: 0 | D103: 1 | E103: 1 | F103: 1 | G103: 1 | H103: 1 | I103: 1 | J103: 1 | K103: 1 | L103: 1 | M103: 1 | N103: 1 | P103: 1.5761907
A104: Minh | B104: Question 54 | C104: 0 | D104: 1 | E104: 1 | F104: 1 | G104: 1 | H104: 1 | I104: 1 | J104: 0 | K104: 1 | L104: 1 | M104: 1 | N104: 1 | O104: Synergy: The two parts (a) and (b) are independent; the result of (a) is not required to solve (b) and vice versa. There is no interdependence between the sub-questions as required by the synergy criterion. | P104: 3.2782609
...

Sheet householdfinance_v4_2
A1: Evaluator | B1: Question | C1: status | D1: answerability | E1: primary_kc_alignment | F1: secondary_kc_alignment | G1: topic_alignment | H1: grade_alignment | I1: real_world_feasibility | J1: synergy | K1: clarity | L1: conciseness_and_relevance | M1: language_quality | N1: content_appropriateness | O1: explanation | P1: response_time | Q1: language_quality1
A2: TD | B2: Question 1 | C2: 0 | D2: 1 | E2: 1 | F2: 1 | G2: 1 | H2: 1 | I2: 1 | J2: 1 | K2: 1 | L2: 1 | M2: 1 | N2: 1 | P2: 1.7458415
A3: TD | B3: Question 2 | C3: 0 | D3: 1 | E3: 1 | F3: 0 | G3: 1 | H3: 1 | I3: 1 | J3: 'NA | K3: 1 | L3: 1 | M3: 1 | N3: 1 | O3: Secondary KC Alignment=0: The problem requires only subtraction to find out how much Sarah spent before her father gave her extra money; addition is not necessary to solve the problem. Synergy=0: There is no need to use both addition and subtraction together for this problem to be solved—the extra money from the father is not used in the calculation. | P3: 1.8329563
A4: TD | B4: Question 3 | C4: 0 | D4: 1 | E4: 1 | F4: 1 | G4: 0 | H4: 1 | I4: 1 | J4: 1 | K4: 1 | L4: 1 | M4: 1 | N4: 1 | O4: 4. Topic Alignment = 0: The problem is about sharing candies and not related to household finance topics like income, bills, money management, or financial planning as specified. | P4: 1.506896
A5: TD | B5: Question 4 | C5: 0 | D5: 1 | E5: 1 | F5: 1 | G5: 1 | H5: 1 | I5: 1 | J5: 1 | K5: 1 | L5: 1 | M5: 1 | N5: 1 | P5: 1.5906646
A6: TD | B6: Question 5 | C6: 0 | D6: 1 | E6: 1 | F6: 1 | G6: 1 | H6: 1 | I6: 1 | J6: 1 | K6: 1 | L6: 1 | M6: 1 | N6: 1 | P6: 1.2036586
A7: TD | B7: Question 6 | C7: 0 | D7: 1 | E7: 1 | F7: 1 | G7: 1 | H7: 1 | I7: 1 | J7: 1 | K7: 1 | L7: 1 | M7: 1 | N7: 1 | P7: 1.2201073
A8: TD | B8: Question 7 | C8: 0 | D8: 1 | E8: 1 | F8: 1 | G8: 0 | H8: 1 | I8: 1 | J8: 1 | K8: 1 | L8: 1 | M8: 1 | N8: 1 | O8: 4- Topic is household finance, but the question is about counting light bulbs, not related to finance topics like savings, bills, money, or planning. | P8: 3.1718147
A9: TD | B9: Question 8 | C9: 0 | D9: 1 | E9: 1 | F9: 1 | G9: 1 | H9: 1 | I9: 1 | J9: 1 | K9: 1 | L9: 1 | M9: 1 | N9: 1 | P9: 1.1983654
A10: TD | B10: Question 9 | C10: 0 | D10: 1 | E10: 1 | F10: 0 | G10: 1 | H10: 1 | I10: 1 | J10: 'NA | K10: 1 | L10: 1 | M10: 1 | N10: 1 | O10: 3,7: The secondary KC of subtraction is not necessary to solve for the amount each child receives—the problem can be solved solely with division. Synergy fails because knowledge of subtraction is not required, and no connected multi-step question involving subtraction is present. | P10: 3.1221344
A11: TD | B11: Question 10 | C11: 0 | D11: 1 | E11: 1 | F11: 1 | G11: 1 | H11: 1 | I11: 1 | J11: 1 | K11: 1 | L11: 1 | M11: 1 | N11: 1 | P11: 1.3676319
A12: TD | B12: Question 11 | C12: 0 | D12: 1 | E12: 1 | F12: 1 | G12: 1 | H12: 1 | I12: 1 | J12: 1 | K12: 1 | L12: 1 | M12: 1 | N12: 1 | P12: 1.4330013
A13: TD | B13: Question 12 | C13: 0 | D13: 1 | E13: 1 | F13: 1 | G13: 1 | H13: 1 | I13: 1 | J13: 1 | K13: 1 | L13: 1 | M13: 1 | N13: 1 | P13: 1.2430379
A14: TD | B14: Question 13 | C14: 0 | D14: 1 | E14: 0 | F14: 0 | G14: 1 | H14: 'NA | I14: 0 | J14: 'NA | K14: 1 | L14: 1 | M14: 1 | N14: 1 | O14: Primary KC: The electricity bill for July uses a value with 3 decimal places ($45.605$), but the intended difficulty is for adding decimals up to 2 decimal places only, which is violated. Secondary KC: The comparison requires comparison of $45.60$ and $45.605$ (2 vs 3 decimal places), but at the P4 level, students may not have been taught to compare decimals beyond 2 decimal places, especially when extra digits do not realistically occur in Singaporean utility billing.Grade alignment: Use of $45.605$ is not appropriate for P4 standard practice, which expects decimals up to 2 decimal places for money calculations.Real-world feasibility: In real-world utility bills, especially in Singapore, currency is not denominated to 3 decimal places; bills are always rounded to 2 decimal places. Thus, $45.605$ is not plausible. | P14: 2.9998636
A15: TD | B15: Question 14 | C15: 0 | D15: 1 | E15: 1 | F15: 1 | G15: 1 | H15: 1 | I15: 1 | J15: 1 | K15: 1 | L15: 1 | M15: 1 | N15: 1 | P15: 2.328481
A16: TD | B16: Question 15 | C16: 0 | D16: 1 | E16: 1 | F16: 1 | G16: 1 | H16: 1 | I16: 1 | J16: 1 | K16: 1 | L16: 1 | M16: 1 | N16: 1 | P16: 2.457175
A17: TD | B17: Question 16 | C17: 0 | D17: 1 | E17: 1 | F17: 1 | G17: 1 | H17: 1 | I17: 1 | J17: 0 | K17: 1 | L17: 1 | M17: 1 | N17: 1 | O17: G: The two parts (a) and (b) are independent; the answer to (a) does not need (b) and vice versa. The fraction in part (b) is not required for solving part (a), so synergy between primary/secondary KCs is not achieved. | P17: 1.6984537
A18: TD | B18: Question 17 | C18: 0 | D18: 1 | E18: 1 | F18: 1 | G18: 1 | H18: 1 | I18: 1 | J18: 1 | K18: 1 | L18: 1 | M18: 1 | N18: 1 | P18: 1.6143937
A19: TD | B19: Question 18 | C19: 0 | D19: 1 | E19: 1 | F19: 1 | G19: 1 | H19: 1 | I19: 1 | J19: 1 | K19: 1 | L19: 1 | M19: 1 | N19: 1 | P19: 1.8342416
A20: TD | B20: Question 19 | C20: 0 | D20: 1 | E20: 1 | F20: 1 | G20: 1 | H20: 1 | I20: 1 | J20: 1 | K20: 1 | L20: 1 | M20: 1 | N20: 1 | P20: 2.4994836
A21: TD | B21: Question 20 | C21: 0 | D21: 0 | E21: 'NA | F21: 'NA | G21: 'NA | H21: 'NA | I21: 'NA | J21: 'NA | K21: 'NA | L21: 'NA | M21: 1 | N21: 'NA | O21: answerability: Value '$1[FORMULA]$ of her budget' and '$2[FORMULA]$ of her budget' result in sums greater than 1 whole budget, which is illogical for expenses unless explained (exceeds 100% of the budget); unit phrasing is ambiguous (should be fractions of her budget or actual values). primary_kc_alignment: Since the fractions are of the same quantity and both are over 1 (more than the entire budget), the addition lacks real relevance and context, and the phrasing makes it unclear—also, you are not actually adding mixed numbers that make sense in this context. secondary_kc_alignment: Since the fractions are not directly compared as fractions but as labels for amounts (with the same denominator 'of her budget'), the comparison is less meaningful or even misleading, especially since both are greater than 1. synergy: The answer to (a) does not help answer (b); the two sub-questions work independently. real_world_feasibility: No one spends more than their total budget on individual items and certainly not 1 and 2 times the entire budget in a single month; the scenario is unrealistic. | P21: 4.0242484 | Q21: 'NA
A22: TD | B22: Question 21 | C22: 0 | D22: 1 | E22: 1 | F22: 1 | G22: 1 | H22: 1 | I22: 1 | J22: 1 | K22: 1 | L22: 1 | M22: 1 | N22: 1 | P22: 1.2892666
A23: TD | B23: Question 22 | C23: 0 | D23: 1 | E23: 1 | F23: 0 | G23: 1 | H23: 1 | I23: 1 | J23: 'NA | K23: 1 | L23: 1 | M23: 1 | N23: 1 | O23: C3: The comparison required is between a whole number (90) and the amount saved, which would be a whole number after multiplying the fraction by $120. This does not require use of comparing and ordering fractions, so the intended secondary KC is not targeted. C7: The use of comparison is not dependent on the understanding or outcome of the multiplication step; once the product is known, the comparison is trivial and does not require knowledge of fractions comparison/order. | P23: 2.7969849
A24: TD | B24: Question 23 | C24: 0 | D24: 1 | E24: 1 | F24: 1 | G24: 1 | H24: 1 | I24: 1 | J24: 1 | K24: 1 | L24: 1 | M24: 1 | N24: 1 | P24: 2.0710509
A25: TD | B25: Question 24 | C25: 0 | D25: 1 | E25: 1 | F25: 0 | G25: 1 | H25: 1 | I25: 1 | J25: 'NA | K25: 1 | L25: 1 | M25: 1 | N25: 1 | O25: Secondary KC Alignment: No addition of fractions is required to solve the problem—only sequential multiplication and subtraction. Synergy: Since the Secondary KC (Addition of Fractions) is not involved, the two components do not work together in the word problem. | P25: 1.9946694
A26: TD | B26: Question 25 | C26: 0 | D26: 1 | E26: 1 | F26: 1 | G26: 1 | H26: 1 | I26: 1 | J26: 1 | K26: 1 | L26: 1 | M26: 1 | N26: 1 | P26: 1.6299584
A27: TD | B27: Question 26 | C27: 0 | D27: 1 | E27: 0 | F27: 0 | G27: 0 | H27: 'NA | I27: 1 | J27: 'NA | K27: 1 | L27: 1 | M27: 1 | N27: 1 | O27: Primary KC Alignment(0): To multiply two improper fractions, you need two fractional numbers as factors. Here, the multiplication required is a whole number (3) times an improper fraction ($[FORMULA]$), NOT two improper fractions.[FORMULA] KC Alignment(0): Addition of fractions is not required to solve any step in this word problem; only multiplication and subtraction of fractions are needed.[FORMULA] Alignment(0): The context is about buying fruit juice for a gathering, which fits a real-world context but is NOT connected to household finance topics such as income, bills, savings, etc. | P27: 5.4544685
A28: TD | B28: Question 27 | C28: 0 | D28: 0 | E28: 'NA | F28: 'NA | G28: 'NA | H28: 'NA | I28: 'NA | J28: 'NA | K28: 'NA | L28: 'NA | M28: 1 | N28: 'NA | O28: A.1: The word problem is not answerable because the fractions 7/4 and 5/3 both exceed 1, and sum to more than her total savings, which is impossible (she cannot spend more than she has). A.2: The main calculation involves multiplying by improper fractions greater than 1, which is not suitable for the context and is mathematically incoherent for the scenario. A.3: Instead of requiring subtraction of fractions, the solution would only require subtraction of resulting dollar values, not a meaningful use of fraction subtraction. A.5: This type of mistake with improper fractions and financial context is not suitable for Primary 5. A.6: The situation is unrealistic as someone cannot spend more than their total savings. A.7: There is no authentic synergy as the fraction subtraction does not meaningfully contribute to solving the problem. A.8: The description is confusing due to the misuse of fractions (improper, sum over 1, not logical in context). | P28: 5.3324885 | Q28: 'NA
A29: TD | B29: Question 28 | C29: 0 | D29: 1 | E29: 1 | F29: 1 | G29: 1 | H29: 1 | I29: 1 | J29: 1 | K29: 1 | L29: 1 | M29: 1 | N29: 1 | P29: 1.8802369
A30: TD | B30: Question 29 | C30: 0 | D30: 1 | E30: 1 | F30: 1 | G30: 0 | H30: 1 | I30: 1 | J30: 1 | K30: 1 | L30: 1 | M30: 1 | N30: 1 | O30: 4- The context is about baking and using chocolate, which does not explicitly relate to household finance (topic intended: income, utility bills, money, interest, savings, instalment, mortgage, financial planning etc). It is more about baking and ingredient usage, not financial matters. | P30: 3.0508986
A31: TD | B31: Question 30 | C31: 0 | D31: 1 | E31: 0 | F31: 1 | G31: 1 | H31: 'NA | I31: 1 | J31: 'NA | K31: 1 | L31: 1 | M31: 1 | N31: 1 | O31: Primary KC alignment = 0 because the question does not explicitly require multiplying a decimal by 10, 100, 1000 or their multiples. Part (a) asks to multiply two decimals ($3.75 [FORMULA] 100 [FORMULA] 0.174$), but the direct multiplication by 10, 100, or 1000 is not the necessary step, merely multiplying decimals and whole numbers. If the intention was to focus practice on multiplying decimals by 10, 100, or 1000, the question should highlight such operation. | P31: 2.4173615
A32: TD | B32: Question 31 | C32: 0 | D32: 1 | E32: 0 | F32: 1 | G32: 1 | H32: 'NA | I32: 1 | J32: 'NA | K32: 1 | L32: 1 | M32: 1 | N32: 1 | O32: Primary KC Alignment: The question requires multiplying 73.245 by 0.15, but this is not multiplication by 10, 100, 1000, or their multiples, as specified in the intended primary KC. It is just multiplying decimals, not with base-10 numbers. Synergy: There is no actual need to subtract the service fee from the initial calculated cost since the description says the fee should be included but Mr Lim subtracts it in his calculation, which is illogical. The problems do not require using both multiplication by multiples of 10 and subtraction in tandem for the solution. | P32: 2.7731516
A33: TD | B33: Question 32 | C33: 0 | D33: 1 | E33: 1 | F33: 1 | G33: 1 | H33: 1 | I33: 1 | J33: 1 | K33: 1 | L33: 1 | M33: 1 | N33: 1 | P33: 1.1990125
A34: TD | B34: Question 33 | C34: 0 | D34: 1 | E34: 1 | F34: 1 | G34: 1 | H34: 1 | I34: 1 | J34: 1 | K34: 1 | L34: 1 | M34: 1 | N34: 1 | P34: 1.2195737
A35: TD | B35: Question 34 | C35: 0 | D35: 1 | E35: 1 | F35: 1 | G35: 1 | H35: 1 | I35: 1 | J35: 1 | K35: 1 | L35: 1 | M35: 1 | N35: 1 | P35: 1.6749773
A36: TD | B36: Question 35 | C36: 0 | D36: 1 | E36: 1 | F36: 1 | G36: 1 | H36: 1 | I36: 1 | J36: 1 | K36: 1 | L36: 1 | M36: 1 | N36: 1 | P36: 1.542454
A37: TD | B37: Question 36 | C37: 0 | D37: 1 | E37: 1 | F37: 1 | G37: 1 | H37: 1 | I37: 1 | J37: 1 | K37: 1 | L37: 1 | M37: 1 | N37: 1 | P37: 1.6807382
A38: TD | B38: Question 37 | C38: 0 | D38: 1 | E38: 1 | F38: 1 | G38: 1 | H38: 1 | I38: 1 | J38: 1 | K38: 1 | L38: 1 | M38: 1 | N38: 1 | P38: 1.9444273
A39: TD | B39: Question 38 | C39: 0 | D39: 1 | E39: 0 | F39: 1 | G39: 0 | H39: 'NA | I39: 1 | J39: 'NA | K39: 1 | L39: 1 | M39: 1 | N39: 1 | O39: Primary KC Alignment: The problem deals with dividing a mixed number (improper fraction) by a whole number, not a proper fraction as specified by the intended KC. Topic Alignment: The context is school fundraising, baking, and donation, which is not related to household finance as intended (i.e., not about money, bills, income, etc.). | P39: 2.6583643
A40: TD | B40: Question 39 | C40: 0 | D40: 1 | E40: 0 | F40: 0 | G40: 1 | H40: 'NA | I40: 1 | J40: 'NA | K40: 1 | L40: 1 | M40: 1 | N40: 1 | O40: Primary KC Alignment (0): The question requires dividing $120 by [FORMULA] [FORMULA] 120$, which is a whole number divided by a whole number, not a proper fraction. Division of a whole number by a proper fraction (intended KC) does not occur. | Secondary KC Alignment (0): The subtraction required is whole number minus whole number, not involving fraction subtraction (i.e. not subtracting fractions). | Synergy (0): The two questions are sequential but do not require using both KC (division and fraction subtraction) together – only basic arithmetic with some fractions. | P40: 3.4104009
A41: TD | B41: Question 40 | C41: 0 | D41: 0 | E41: 'NA | F41: 'NA | G41: 'NA | H41: 'NA | I41: 'NA | J41: 'NA | K41: 'NA | L41: 'NA | M41: 0 | N41: 'NA | O41: answerability: (b) is ill-posed: 'divided by 3/4' asks for $40 [FORMULA] 3/4 = 53.333$ which is not what was described in the scenario; contextually, each child is supposed to get 3/4 of their planned amount, not more. The question asks for an operation not supported by the context, leading to conflicting requirements. primary_kc_alignment: The problem does not require dividing a whole number or fraction by a fraction in a natural scenario (it actually requires multiplying by 3/4 to find the new amount given), so the target KC is not necessary. synergy: The secondary KC (conversion to decimals) appears only in part (b), but does not connect meaningfully with part (a) because the operation is not the right one for the context (division by 3/4 is divorced from the actual problem posed). clarity: The wording of (b) is misleading and mathematically incorrect with respect to the scenario. conciseness_and_relevance: The question (b) introduces irrelevant and confusing calculations that are not needed for the scenario, reducing relevance. language_quality: Q (b) has grammatical and conceptual flaws ("divided by 3/4" does not fit the context, confusing students). | P41: 5.0141423 | Q41: 'NA
A42: TD | B42: Question 41 | C42: 0 | D42: 1 | E42: 1 | F42: 0 | G42: 1 | H42: 1 | I42: 1 | J42: 'NA | K42: 1 | L42: 1 | M42: 1 | N42: 1 | O42: 3. Although three expense values are mentioned, only the electricity bill (with its percentage) is necessary to solve for total monthly household expenses; addition of groceries and transport spending is not required for the solution as currently written. 7. The solution does not need to use addition (secondary KC) in tandem with the percentage calculation (primary KC); groceries and transport spending are extraneous for finding the required total. | P42: 2.5082912
A43: TD | B43: Question 42 | C43: 0 | D43: 1 | E43: 1 | F43: 1 | G43: 1 | H43: 1 | I43: 1 | J43: 1 | K43: 1 | L43: 1 | M43: 1 | N43: 1 | P43: 1.4398353
A44: TD | B44: Question 43 | C44: 0 | D44: 1 | E44: 1 | F44: 1 | G44: 1 | H44: 1 | I44: 1 | J44: 1 | K44: 1 | L44: 1 | M44: 1 | N44: 1 | P44: 1.1766958
A45: TD | B45: Question 44 | C45: 0 | D45: 1 | E45: 1 | F45: 1 | G45: 1 | H45: 1 | I45: 1 | J45: 1 | K45: 1 | L45: 1 | M45: 1 | N45: 1 | P45: 1.4553313
A46: TD | B46: Question 45 | C46: 0 | D46: 1 | E46: 1 | F46: 1 | G46: 1 | H46: 1 | I46: 1 | J46: 1 | K46: 1 | L46: 1 | M46: 1 | N46: 1 | P46: 2.0107951
A47: TD | B47: Question 46 | C47: 0 | D47: 1 | E47: 1 | F47: 1 | G47: 1 | H47: 1 | I47: 1 | J47: 1 | K47: 1 | L47: 1 | M47: 1 | N47: 1 | P47: 2.2038741
A48: TD | B48: Question 47 | C48: 0 | D48: 1 | E48: 1 | F48: 1 | G48: 1 | H48: 1 | I48: 1 | J48: 1 | K48: 1 | L48: 1 | M48: 1 | N48: 1 | P48: 1.3724818
A49: TD | B49: Question 48 | C49: 0 | D49: 1 | E49: 0 | F49: 1 | G49: 1 | H49: 'NA | I49: 1 | J49: 'NA | K49: 1 | L49: 1 | M49: 1 | N49: 1 | O49: 2. The intended primary knowledge component is multiplication of matrices (matrix multiplication in the linear algebra sense, i.e., the dot product of rows and columns using the standard definition), but the problem uses element-wise (Hadamard) multiplication instead, which is a different operation. Element-wise multiplication is not the standard 'multiplication of matrices.' This misalignment is not suitable at O-level if the intention is to test matrix multiplication as per curriculum. | P49: 2.7417316
A50: TD | B50: Question 49 | C50: 0 | D50: 1 | E50: 1 | F50: 1 | G50: 1 | H50: 1 | I50: 1 | J50: 1 | K50: 1 | L50: 1 | M50: 1 | N50: 1 | P50: 1.7090809
A51: Minh | B51: Question 1 | C51: 0 | D51: 1 | E51: 1 | F51: 1 | G51: 1 | H51: 1 | I51: 1 | J51: 1 | K51: 1 | L51: 1 | M51: 1 | N51: 1 | P51: 1.6973925
A52: Minh | B52: Question 2 | C52: 0 | D52: 1 | E52: 1 | F52: 1 | G52: 1 | H52: 1 | I52: 1 | J52: 1 | K52: 1 | L52: 1 | M52: 1 | N52: 1 | P52: 1.7417185
A53: Minh | B53: Question 3 | C53: 0 | D53: 1 | E53: 1 | F53: 1 | G53: 1 | H53: 1 | I53: 1 | J53: 1 | K53: 1 | L53: 1 | M53: 1 | N53: 1 | P53: 1.7379415
A54: Minh | B54: Question 4 | C54: 0 | D54: 1 | E54: 1 | F54: 1 | G54: 1 | H54: 1 | I54: 1 | J54: 1 | K54: 1 | L54: 1 | M54: 1 | N54: 1 | P54: 1.2097776
A55: Minh | B55: Question 5 | C55: 0 | D55: 1 | E55: 1 | F55: 1 | G55: 1 | H55: 1 | I55: 1 | J55: 1 | K55: 1 | L55: 1 | M55: 1 | N55: 1 | P55: 1.6531372
A56: Minh | B56: Question 6 | C56: 0 | D56: 1 | E56: 0 | F56: 1 | G56: 1 | H56: 'NA | I56: 1 | J56: 'NA | K56: 1 | L56: 1 | M56: 1 | N56: 1 | O56: primary_kc_alignment: The problem requires dividing 624 (3 digits) by 8 (1 digit) to find the price of one chair, which aligns with Primary KC. However, the intent is for division up to 3 digits by 1 digit, but 624 divided by 8 gives 78, which is a 2-digit number. The wording 'dividing whole numbers up to 3 digits by 1 digit' focuses on the size of the dividend, but for Primary 3, division of 3-digit numbers like 624 is typically introduced in Primary 4 in Singapore. Therefore, this may not be fully suitable for Primary 3. grade_alignment: Division of 3-digit numbers (624 by 8) may not be appropriately aligned with the Primary 3 syllabus in Singapore, where 2-digit by 1-digit division is standard. synergy: Primary KC (division) and Secondary KC (multiplication) are not tightly coupled; you can solve the price for 6 more chairs with only multiplication once the price of one is found, but the two concepts don't require tandem or interdependent use. | P56: 5.4851463
A57: Minh | B57: Question 7 | C57: 0 | D57: 1 | E57: 1 | F57: 1 | G57: 1 | H57: 1 | I57: 1 | J57: 1 | K57: 1 | L57: 1 | M57: 1 | N57: 1 | P57: 1.6500237
A58: Minh | B58: Question 8 | C58: 0 | D58: 1 | E58: 1 | F58: 1 | G58: 0 | H58: 1 | I58: 1 | J58: 1 | K58: 1 | L58: 1 | M58: 1 | N58: 1 | O58: D* The context is about spending pocket money on snacks and a storybook, which is more of a consumer spending scenario rather than explicitly about household finance (e.g., income, bills, savings, or financial planning). The context does not closely align with the household finance topic specified. | P58: 2.1353433
A59: Minh | B59: Question 9 | C59: 0 | D59: 1 | E59: 1 | F59: 1 | G59: 0 | H59: 1 | I59: 1 | J59: 1 | K59: 1 | L59: 1 | M59: 1 | N59: 1 | O59: 4: The context is about counting soap bars purchased in different packages, not household finance. No mention of money, spending, or financial planning is present. It is only arithmetic with daily items, not explicitly household finance. | P59: 1.5969188
A60: Minh | B60: Question 10 | C60: 0 | D60: 1 | E60: 1 | F60: 1 | G60: 1 | H60: 1 | I60: 1 | J60: 1 | K60: 1 | L60: 1 | M60: 1 | N60: 1 | P60: 1.1719229
A61: Minh | B61: Question 11 | C61: 0 | D61: 1 | E61: 1 | F61: 1 | G61: 1 | H61: 1 | I61: 1 | J61: 1 | K61: 1 | L61: 1 | M61: 1 | N61: 1 | P61: 1.3336134
A62: Minh | B62: Question 12 | C62: 0 | D62: 1 | E62: 1 | F62: 1 | G62: 1 | H62: 1 | I62: 1 | J62: 1 | K62: 1 | L62: 1 | M62: 1 | N62: 1 | P62: 1.3265622
A63: Minh | B63: Question 13 | C63: 0 | D63: 1 | E63: 1 | F63: 1 | G63: 1 | H63: 1 | I63: 1 | J63: 1 | K63: 1 | L63: 1 | M63: 1 | N63: 1 | P63: 1.2554767
A64: Minh | B64: Question 14 | C64: 0 | D64: 1 | E64: 1 | F64: 1 | G64: 1 | H64: 1 | I64: 1 | J64: 0 | K64: 1 | L64: 1 | M64: 1 | N64: 1 | O64: G. The two parts (a) and (b) are independent. The answer to (a) is not required to solve (b), nor vice versa. There is no synergy in requiring both the Primary and Secondary KCs together for a single, integrated solution. | P64: 1.7223904
A65: Minh | B65: Question 15 | C65: 0 | D65: 1 | E65: 1 | F65: 1 | G65: 1 | H65: 1 | I65: 1 | J65: 1 | K65: 1 | L65: 1 | M65: 1 | N65: 1 | P65: 1.2056572
A66: Minh | B66: Question 16 | C66: 0 | D66: 1 | E66: 1 | F66: 1 | G66: 1 | H66: 1 | I66: 1 | J66: 1 | K66: 1 | L66: 1 | M66: 1 | N66: 1 | P66: 1.221251
A67: Minh | B67: Question 17 | C67: 0 | D67: 1 | E67: 1 | F67: 1 | G67: 1 | H67: 1 | I67: 1 | J67: 1 | K67: 1 | L67: 1 | M67: 1 | N67: 1 | P67: 1.3058708
A68: Minh | B68: Question 18 | C68: 0 | D68: 1 | E68: 1 | F68: 1 | G68: 1 | H68: 1 | I68: 1 | J68: 1 | K68: 1 | L68: 1 | M68: 1 | N68: 1 | P68: 1.9254355
A69: Minh | B69: Question 19 | C69: 0 | D69: 1 | E69: 1 | F69: 1 | G69: 1 | H69: 1 | I69: 1 | J69: 1 | K69: 1 | L69: 1 | M69: 1 | N69: 1 | P69: 1.1428044
A70: Minh | B70: Question 20 | C70: 0 | D70: 1 | E70: 1 | F70: 1 | G70: 1 | H70: 1 | I70: 1 | J70: 1 | K70: 1 | L70: 1 | M70: 1 | N70: 1 | P70: 1.6700435
A71: Minh | B71: Question 21 | C71: 0 | D71: 1 | E71: 1 | F71: 1 | G71: 1 | H71: 1 | I71: 1 | J71: 1 | K71: 1 | L71: 1 | M71: 1 | N71: 1 | P71: 1.1373408
A72: Minh | B72: Question 22 | C72: 0 | D72: 1 | E72: 1 | F72: 1 | G72: 1 | H72: 1 | I72: 1 | J72: 1 | K72: 1 | L72: 1 | M72: 1 | N72: 1 | P72: 1.8770068
A73: Minh | B73: Question 23 | C73: 0 | D73: 1 | E73: 1 | F73: 1 | G73: 1 | H73: 1 | I73: 1 | J73: 1 | K73: 1 | L73: 1 | M73: 1 | N73: 1 | P73: 1.2261252
A74: Minh | B74: Question 24 | C74: 0 | D74: 1 | E74: 0 | F74: 0 | G74: 1 | H74: 'NA | I74: 1 | J74: 'NA | K74: 1 | L74: 1 | M74: 1 | N74: 1 | O74: 2: The calculation in (a) only requires multiplying a whole number by a mixed number ($12 [FORMULA] 2[FORMULA]$), but the intent was for the student to multiply a mixed number by a whole number, that is, $2[FORMULA] [FORMULA] 12$. This subtlety fails strict alignment to the primary intended KC. 3: The comparison in (b) is between whole numbers ($30 vs $12x2.5=$30). There are no fractions to compare or order, so the secondary KC is not necessary to solve this problem. 7: There is no synergy between primary and secondary KC because secondary KC is not required to solve or inform the answer in either part; both options are easily compared as whole numbers. | P74: 14.389709
A75: Minh | B75: Question 25 | C75: 0 | D75: 1 | E75: 1 | F75: 1 | G75: 1 | H75: 1 | I75: 1 | J75: 1 | K75: 1 | L75: 1 | M75: 1 | N75: 1 | P75: 1.4085684
A76: Minh | B76: Question 26 | C76: 0 | D76: 1 | E76: 1 | F76: 1 | G76: 0 | H76: 1 | I76: 1 | J76: 1 | K76: 1 | L76: 1 | M76: 1 | N76: 1 | O76: D-4: The word problem describes buying rice, which relates to household consumption but does not clearly fit the explicit household finance topics (income, utility bills, money, interest, savings, instalment, mortgage, financial planning, etc) as specified. It focuses on quantity/weight, not money or explicit financial planning. | P76: 2.6959844
A77: Minh | B77: Question 27 | C77: 0 | D77: 1 | E77: 0 | F77: 1 | G77: 1 | H77: 'NA | I77: 1 | J77: 'NA | K77: 1 | L77: 1 | M77: 1 | N77: 1 | O77: 2: The multiplication is multiplying 132.768 by 0.183, which is not multiplying decimals by 10, 100, 1000 or their multiples, as specifically required by the intended Primary KC. | P77: 1.8302889
A78: Minh | B78: Question 28 | C78: 0 | D78: 1 | E78: 1 | F78: 1 | G78: 1 | H78: 1 | I78: 1 | J78: 1 | K78: 0 | L78: 0 | M78: 0 | N78: 1 | O78: Clarity: The stated amount '$187.250' is ambiguous—it's more typical and clearer in Singapore finance context to write this as $187.25 (two decimal places for currency). Using three decimal places for SGD in a real-world setting is not standard and likely to confuse students. | Conciseness and Relevance: The '.250' at the end introduces unnecessary complexity and is unrealistic for cash-related contexts, as Singapore dollars are not used in thousandths (no 0.001 cent coins or bills). | Language Quality: There are minor errors in usage of decimals and in the phrase 'saved $187.250 in her savings account' which would not be written like this in standard English. Standard usage would be 'saved $187.25'. | P78: 2.9410932
A79: Minh | B79: Question 29 | C79: 0 | D79: 1 | E79: 1 | F79: 1 | G79: 1 | H79: 1 | I79: 1 | J79: 1 | K79: 1 | L79: 1 | M79: 1 | N79: 1 | P79: 1.5208442
A80: Minh | B80: Question 30 | C80: 0 | D80: 1 | E80: 1 | F80: 1 | G80: 1 | H80: 1 | I80: 1 | J80: 1 | K80: 1 | L80: 1 | M80: 1 | N80: 1 | P80: 1.5996299
A81: Minh | B81: Question 31 | C81: 0 | D81: 1 | E81: 1 | F81: 1 | G81: 1 | H81: 1 | I81: 1 | J81: 1 | K81: 1 | L81: 1 | M81: 1 | N81: 1 | P81: 1.663348
A82: Minh | B82: Question 32 | C82: 0 | D82: 1 | E82: 1 | F82: 1 | G82: 1 | H82: 1 | I82: 1 | J82: 1 | K82: 1 | L82: 1 | M82: 1 | N82: 1 | P82: 1.2638826
A83: Minh | B83: Question 33 | C83: 0 | D83: 1 | E83: 1 | F83: 1 | G83: 0 | H83: 1 | I83: 1 | J83: 1 | K83: 1 | L83: 1 | M83: 1 | N83: 1 | O83: 4: The context is about sharing cake at a family gathering, which does not relate to household finance topics like income, utility bills, money, interest, savings, instalment, mortgage, or financial planning. | P83: 2.1638255
A84: Minh | B84: Question 34 | C84: 0 | D84: 1 | E84: 1 | F84: 1 | G84: 1 | H84: 1 | I84: 1 | J84: 1 | K84: 1 | L84: 1 | M84: 1 | N84: 1 | P84: 1.3982091
A85: Minh | B85: Question 35 | C85: 0 | D85: 1 | E85: 1 | F85: 1 | G85: 0 | H85: 1 | I85: 1 | J85: 1 | K85: 1 | L85: 1 | M85: 1 | N85: 1 | O85: 4: The problem is about repacking detergent, not household finance related to income, utility bills, money, interest, savings, instalment, mortgage, or financial planning. It does not fit the financial context specified in the intended topic (4). | P85: 3.0981777
A86: Minh | B86: Question 36 | C86: 0 | D86: 1 | E86: 1 | F86: 0 | G86: 1 | H86: 1 | I86: 1 | J86: 'NA | K86: 1 | L86: 1 | M86: 1 | N86: 1 | O86: Secondary KC Alignment (WHOLE NUMBERS | Subtraction) and Synergy: The word problem only requires the use of the percentage knowledge component to find the total utility bill (the whole), given a part and percentage. There is no need to perform any subtraction operation with whole numbers in both understanding or solving the question. Therefore, the problem does not involve the intended secondary KC (subtraction), and the primary and secondary KCs are not used in tandem. | P86: 2.1153598
A87: Minh | B87: Question 37 | C87: 0 | D87: 1 | E87: 1 | F87: 1 | G87: 1 | H87: 1 | I87: 1 | J87: 1 | K87: 1 | L87: 1 | M87: 1 | N87: 1 | P87: 1.0885086
A88: Minh | B88: Question 38 | C88: 0 | D88: 1 | E88: 1 | F88: 1 | G88: 1 | H88: 1 | I88: 1 | J88: 1 | K88: 1 | L88: 1 | M88: 1 | N88: 1 | P88: 1.6307824
A89: Minh | B89: Question 39 | C89: 0 | D89: 1 | E89: 1 | F89: 1 | G89: 1 | H89: 1 | I89: 1 | J89: 1 | K89: 1 | L89: 1 | M89: 1 | N89: 1 | P89: 1.9168434
A90: Minh | B90: Question 40 | C90: 0 | D90: 1 | E90: 1 | F90: 1 | G90: 1 | H90: 1 | I90: 1 | J90: 1 | K90: 1 | L90: 1 | M90: 1 | N90: 1 | P90: 1.4393291
A91: Minh | B91: Question 41 | C91: 0 | D91: 1 | E91: 1 | F91: 1 | G91: 1 | H91: 1 | I91: 1 | J91: 1 | K91: 1 | L91: 1 | M91: 1 | N91: 1 | P91: 1.2038677
A92: Minh | B92: Question 42 | C92: 0 | D92: 1 | E92: 1 | F92: 1 | G92: 1 | H92: 1 | I92: 1 | J92: 1 | K92: 1 | L92: 1 | M92: 1 | N92: 1 | P92: 1.5938606
A93: Minh | B93: Question 43 | C93: 0 | D93: 1 | E93: 1 | F93: 1 | G93: 1 | H93: 1 | I93: 1 | J93: 1 | K93: 1 | L93: 1 | M93: 1 | N93: 1 | P93: 2.0374875
A94: Minh | B94: Question 44 | C94: 0 | D94: 1 | E94: 1 | F94: 1 | G94: 1 | H94: 1 | I94: 1 | J94: 1 | K94: 1 | L94: 1 | M94: 1 | N94: 1 | P94: 1.3366125
A95: Minh | B95: Question 45 | C95: 0 | D95: 1 | E95: 1 | F95: 1 | G95: 1 | H95: 1 | I95: 1 | J95: 1 | K95: 1 | L95: 1 | M95: 1 | N95: 1 | P95: 1.5226862
A96: Minh | B96: Question 46 | C96: 0 | D96: 1 | E96: 1 | F96: 1 | G96: 1 | H96: 1 | I96: 1 | J96: 1 | K96: 1 | L96: 1 | M96: 1 | N96: 1 | P96: 1.3474913
A97: Minh | B97: Question 47 | C97: 0 | D97: 1 | E97: 1 | F97: 1 | G97: 1 | H97: 1 | I97: 1 | J97: 1 | K97: 1 | L97: 1 | M97: 1 | N97: 1 | P97: 1.1394651
A98: Minh | B98: Question 48 | C98: 0 | D98: 1 | E98: 1 | F98: 1 | G98: 1 | H98: 1 | I98: 1 | J98: 1 | K98: 1 | L98: 1 | M98: 1 | N98: 1 | P98: 2.1257
... A112: Minh | B112: Question 62 | C112: 0 | D112: 1 | E112: 1 | F112: 1 | G112: 1 | H112: 1 | I112: 1 | J112: 1 | K112: 1 | L112: 1 | M112: 1 | N112: 1 | P112: 1.2269514
A113: Minh | B113: Question 63 | C113: 0 | D113: 1 | E113: 1 | F113: 1 | G113: 1 | H113: 1 | I113: 1 | J113: 0 | K113: 1 | L113: 1 | M113: 1 | N113: 1 | O113: Synergy: The two parts (a) and (b) are independent; solving (a) does not provide any information required for solving (b), nor vice versa. Both are standalone probability questions. | P113: 1.7002456
...

Sheet householdfinance_v4_3
A1: Evaluator | B1: Question | C1: status | D1: answerability | E1: primary_kc_alignment | F1: secondary_kc_alignment | G1: topic_alignment | H1: grade_alignment | I1: real_world_feasibility | J1: synergy | K1: clarity | L1: conciseness_and_relevance | M1: language_quality | N1: content_appropriateness | O1: explanation | P1: response_time | Q1: language_quality1
A2: TD | B2: Question 1 | C2: 0 | D2: 1 | E2: 1 | F2: 1 | G2: 1 | H2: 1 | I2: 1 | J2: 1 | K2: 1 | L2: 1 | M2: 1 | N2: 1 | P2: 1.1645322
A3: TD | B3: Question 2 | C3: 0 | D3: 1 | E3: 1 | F3: 0 | G3: 1 | H3: 1 | I3: 1 | J3: 'NA | K3: 1 | L3: 1 | M3: 1 | N3: 1 | O3: Secondary KC Alignment: The problem only requires initial subtraction (2450-21535), so addition of whole numbers is not needed. Synergy: Only the primary KC is required, so both KCs are not used in tandem. | P3: 2.7829387
A4: TD | B4: Question 3 | C4: 0 | D4: 1 | E4: 1 | F4: 1 | G4: 0 | H4: 1 | I4: 1 | J4: 1 | K4: 1 | L4: 1 | M4: 1 | N4: 1 | O4: D4: The topic is household finance, involving money or financial planning, but the problem is about candies being distributed among children with no connection to financial concepts. | P4: 1.6966138
A5: TD | B5: Question 4 | C5: 0 | D5: 1 | E5: 1 | F5: 1 | G5: 1 | H5: 1 | I5: 1 | J5: 1 | K5: 1 | L5: 1 | M5: 1 | N5: 1 | P5: 1.0988777
A6: TD | B6: Question 5 | C6: 0 | D6: 1 | E6: 1 | F6: 1 | G6: 1 | H6: 1 | I6: 1 | J6: 1 | K6: 1 | L6: 1 | M6: 1 | N6: 1 | P6: 1.2089908
A7: TD | B7: Question 6 | C7: 0 | D7: 1 | E7: 1 | F7: 1 | G7: 1 | H7: 1 | I7: 1 | J7: 1 | K7: 1 | L7: 1 | M7: 1 | N7: 1 | P7: 1.2596488
A8: TD | B8: Question 7 | C8: 0 | D8: 1 | E8: 1 | F8: 1 | G8: 0 | H8: 1 | I8: 1 | J8: 1 | K8: 1 | L8: 1 | M8: 1 | N8: 1 | O8: 4: The context is buying light bulbs for a house, which is general shopping, not specifically household finance such as income, bills, interest, savings, instalment, mortgage, or financial planning. Therefore, it does not align with the intended topic. | P8: 3.3258212
A9: TD | B9: Question 8 | C9: 0 | D9: 1 | E9: 1 | F9: 1 | G9: 1 | H9: 1 | I9: 1 | J9: 1 | K9: 1 | L9: 1 | M9: 1 | N9: 1 | P9: 3.0744078
A10: TD | B10: Question 9 | C10: 0 | D10: 1 | E10: 1 | F10: 0 | G10: 1 | H10: 1 | I10: 1 | J10: 'NA | K10: 1 | L10: 1 | M10: 1 | N10: 1 | O10: secondary_kc_alignment- The use of subtraction (to subtract household expenses from monthly salary) is not required to find out how much each child receives; only division is necessary. synergy- Only the primary knowledge component (division) is required to answer the problem; there is no dependency between division and subtraction, nor is subtraction needed to solve for what each child received. | P10: 3.2832241
A11: TD | B11: Question 10 | C11: 0 | D11: 1 | E11: 1 | F11: 1 | G11: 1 | H11: 1 | I11: 1 | J11: 1 | K11: 1 | L11: 1 | M11: 1 | N11: 1 | P11: 1.2175198
A12: TD | B12: Question 11 | C12: 0 | D12: 1 | E12: 1 | F12: 1 | G12: 1 | H12: 1 | I12: 1 | J12: 1 | K12: 1 | L12: 1 | M12: 1 | N12: 1 | P12: 1.1791115
A13: TD | B13: Question 12 | C13: 0 | D13: 1 | E13: 1 | F13: 1 | G13: 1 | H13: 1 | I13: 1 | J13: 1 | K13: 1 | L13: 1 | M13: 1 | N13: 1 | P13: 2.0069952
A14: TD | B14: Question 13 | C14: 0 | D14: 1 | E14: 0 | F14: 0 | G14: 1 | H14: 'NA | I14: 0 | J14: 'NA | K14: 1 | L14: 1 | M14: 1 | N14: 1 | O14: Primary KC Alignment: Question (a) is aligned but question (b) presents a bill with three decimal places ($45.605) when all Singapore currency transactions are expressed up to 2 decimal places, making it misaligned with 'adding decimals (up to 2 decimal places)'.Secondary KC Alignment: Comparison involves 3 decimal places, but it is not relevant to actual currency context and exceeds the secondary KC expected difficulty and context for P4.Grade Alignment: The use of $45.605 is not appropriate for Primary 4 as Singapore currency and school curriculum always uses 2 decimal places for money; comparison beyond 2 dp is outside grade and context.Real-World Feasibility: Utility bills are never stated or paid to 3 decimal places for Singapore dollars ($45.605 impossible/illogical in real-life). | P14: 5.9032586
A15: TD | B15: Question 14 | C15: 0 | D15: 1 | E15: 1 | F15: 1 | G15: 1 | H15: 1 | I15: 1 | J15: 1 | K15: 1 | L15: 1 | M15: 1 | N15: 1 | P15: 1.295989
A16: TD | B16: Question 15 | C16: 0 | D16: 1 | E16: 1 | F16: 1 | G16: 1 | H16: 1 | I16: 1 | J16: 1 | K16: 1 | L16: 1 | M16: 1 | N16: 1 | P16: 1.4113255
A17: TD | B17: Question 16 | C17: 0 | D17: 1 | E17: 1 | F17: 1 | G17: 1 | H17: 1 | I17: 1 | J17: 1 | K17: 1 | L17: 1 | M17: 1 | N17: 1 | P17: 1.7385006
A18: TD | B18: Question 17 | C18: 0 | D18: 1 | E18: 1 | F18: 1 | G18: 1 | H18: 1 | I18: 1 | J18: 1 | K18: 1 | L18: 1 | M18: 1 | N18: 1 | P18: 1.3546555
A19: TD | B19: Question 18 | C19: 0 | D19: 1 | E19: 1 | F19: 1 | G19: 1 | H19: 1 | I19: 1 | J19: 1 | K19: 1 | L19: 1 | M19: 1 | N19: 1 | P19: 1.5273533
A20: TD | B20: Question 19 | C20: 0 | D20: 1 | E20: 1 | F20: 1 | G20: 1 | H20: 1 | I20: 1 | J20: 1 | K20: 1 | L20: 1 | M20: 1 | N20: 1 | P20: 1.1372061
A21: TD | B21: Question 20 | C21: 0 | D21: 1 | E21: 1 | F21: 1 | G21: 1 | H21: 1 | I21: 1 | J21: 1 | K21: 1 | L21: 1 | M21: 1 | N21: 1 | P21: 3.3776476
A22: TD | B22: Question 21 | C22: 0 | D22: 1 | E22: 1 | F22: 1 | G22: 1 | H22: 1 | I22: 1 | J22: 1 | K22: 1 | L22: 1 | M22: 1 | N22: 1 | P22: 1.6866493
A23: TD | B23: Question 22 | C23: 0 | D23: 1 | E23: 1 | F23: 0 | G23: 1 | H23: 1 | I23: 1 | J23: 'NA | K23: 1 | L23: 1 | M23: 1 | N23: 1 | O23: Secondary KC Alignment(0): The problem involves comparing two whole numbers (40 from savings, and 090), not comparing or ordering fractions. Synergy(0): The comparison step does not require explicit use of the secondary KC (comparing/ordering fractions), only the result of fraction multiplication is used. | P23: 2.1250935
A24: TD | B24: Question 23 | C24: 0 | D24: 1 | E24: 1 | F24: 1 | G24: 1 | H24: 1 | I24: 1 | J24: 1 | K24: 1 | L24: 1 | M24: 1 | N24: 1 | P24: 1.1742108
A25: TD | B25: Question 24 | C25: 0 | D25: 1 | E25: 1 | F25: 0 | G25: 1 | H25: 1 | I25: 1 | J25: 'NA | K25: 1 | L25: 1 | M25: 1 | N25: 1 | O25: Secondary KC Alignment (0): The problem only requires repeated multiplication of fractions and does not require addition of fractions at any point.///Synergy (0): Since only multiplication of fractions is used at each stage, there is no need to combine multiplication and addition of fractions to solve for the final answer. | P25: 1.8734167
A26: TD | B26: Question 25 | C26: 0 | D26: 1 | E26: 1 | F26: 1 | G26: 1 | H26: 1 | I26: 1 | J26: 1 | K26: 1 | L26: 1 | M26: 1 | N26: 1 | P26: 2.8625042
A27: TD | B27: Question 26 | C27: 0 | D27: 1 | E27: 0 | F27: 0 | G27: 0 | H27: 'NA | I27: 1 | J27: 'NA | K27: 1 | L27: 1 | M27: 1 | N27: 1 | O27: 2: The problem only requires multiplication of a fraction by a whole number, not multiplying two fractions together as intended in the primary KC. 3: No addition of fractions is necessary; the problem solely involves multiplication and subtraction. 4: The scenario is about fruit juice purchase/consumption, not about household finance matters such as bills or money. 7: The questions are sequential but do not require both intended KCs synergistically, as there is no required addition of fractions or multiplication of two fractions. | P27: 2.5133607
A28: TD | B28: Question 27 | C28: 0 | D28: 0 | E28: 'NA | F28: 'NA | G28: 'NA | H28: 'NA | I28: 'NA | J28: 'NA | K28: 'NA | L28: 'NA | M28: 1 | N28: 'NA | O28: A: The fractions \([FORMULA]\) and \([FORMULA]\) imply she spends more than her total savings (1 whole) on utilities or groceries, which is impossible and creates a logical conflict. B: To solve, direct multiplication with \([FORMULA]\) and \([FORMULA]\) is not appropriate, as they exceed 1, and thus do not align with the intended Knowledge Component of multiplying two improper fractions in a meaningful or logical way for P5 math. C: Subtraction of the 'utilities' and 'groceries' amounts does not require subtraction of fractions, since both are calculated as amounts in dollars. S: Even if calculations were possible, the fractions provided do not produce physically meaningful values, and the required operations (multiplying and subtracting fractions) are not appropriately integrated. G: Primary 5 students are not expected to work with improper fractions greater than 1 when representing parts of a whole, and the scenario is unrealistic for their level. R: No household would allocate more than 100% of savings to either utilities or groceries, so these numbers are not feasible. C: Ambiguity arises as the fractions exceed 1, causing confusion about how the money could be allocated. | P28: 4.1972029 | Q28: 'NA
A29: TD | B29: Question 28 | C29: 0 | D29: 1 | E29: 1 | F29: 1 | G29: 1 | H29: 1 | I29: 1 | J29: 1 | K29: 1 | L29: 1 | M29: 1 | N29: 1 | P29: 1.7419102
A30: TD | B30: Question 29 | C30: 0 | D30: 1 | E30: 1 | F30: 1 | G30: 0 | H30: 1 | I30: 1 | J30: 1 | K30: 1 | L30: 1 | M30: 1 | N30: 1 | O30: 4: The context is about baking and measuring chocolate, not on household finance (income, bills, savings etc), so it does not align with the intended topic. | P30: 1.6975362
A31: TD | B31: Question 30 | C31: 0 | D31: 1 | E31: 0 | F31: 1 | G31: 1 | H31: 'NA | I31: 1 | J31: 'NA | K31: 1 | L31: 1 | M31: 1 | N31: 1 | O31: Primary KC Alignment: The multiplication required is $3.75 [FORMULA] 0.174 [FORMULA] 100$, which involves multiplying decimals, but not specifically by 10, 100, 1000 and their multiples as per the intended Primary KC. The most challenging multiplication is not the focus skill intended. Synergy: The two parts (a) and (b) are independent and not linked; the answer from one is not required for the other. | P31: 2.8946471
A32: TD | B32: Question 31 | C32: 0 | D32: 1 | E32: 0 | F32: 1 | G32: 1 | H32: 'NA | I32: 1 | J32: 'NA | K32: 1 | L32: 1 | M32: 1 | N32: 1 | O32: Primary KC Alignment: The core multiplication done here is $73.245 [FORMULA] 0.15$, which does not qualify as 'multiplying decimals by 10, 100, 1000 or their multiples'; it is general decimal multiplication, not multiplication by powers of ten. Synergy: The subtraction of $1.80$ is not mathematically synergistic with the multiplication; the result of the multiplication is not needed to correctly perform the subtraction operation (the subtraction is said to be from his cost calculation, but the logic requires him to ADD the service fee, not subtract it, so the required relationship between KC's is not clearly aligned). | P32: 2.5113463
A33: TD | B33: Question 32 | C33: 0 | D33: 1 | E33: 1 | F33: 1 | G33: 1 | H33: 1 | I33: 1 | J33: 1 | K33: 1 | L33: 1 | M33: 1 | N33: 1 | P33: 2.1388664
A34: TD | B34: Question 33 | C34: 0 | D34: 1 | E34: 1 | F34: 1 | G34: 1 | H34: 1 | I34: 1 | J34: 1 | K34: 1 | L34: 1 | M34: 1 | N34: 1 | P34: 1.823765
A35: TD | B35: Question 34 | C35: 0 | D35: 1 | E35: 1 | F35: 1 | G35: 1 | H35: 1 | I35: 1 | J35: 1 | K35: 1 | L35: 1 | M35: 1 | N35: 1 | P35: 1.4226642
A36: TD | B36: Question 35 | C36: 0 | D36: 1 | E36: 1 | F36: 1 | G36: 1 | H36: 1 | I36: 1 | J36: 1 | K36: 1 | L36: 1 | M36: 1 | N36: 1 | P36: 1.078141
A37: TD | B37: Question 36 | C37: 0 | D37: 1 | E37: 1 | F37: 1 | G37: 1 | H37: 1 | I37: 1 | J37: 1 | K37: 1 | L37: 1 | M37: 1 | N37: 1 | P37: 2.9683318
A38: TD | B38: Question 37 | C38: 0 | D38: 1 | E38: 1 | F38: 1 | G38: 1 | H38: 1 | I38: 1 | J38: 1 | K38: 1 | L38: 1 | M38: 1 | N38: 1 | P38: 1.8440206
A39: TD | B39: Question 38 | C39: 0 | D39: 1 | E39: 1 | F39: 1 | G39: 0 | H39: 1 | I39: 1 | J39: 1 | K39: 1 | L39: 1 | M39: 1 | N39: 1 | O39: 4: The context is about baking for a school fundraiser and distributing cookies, not related to household finance or any of the listed financial topics (such as income, bills, or savings). | P39: 1.74123
A40: TD | B40: Question 39 | C40: 0 | D40: 1 | E40: 0 | F40: 0 | G40: 1 | H40: 'NA | I40: 1 | J40: 'NA | K40: 1 | L40: 1 | M40: 1 | N40: 1 | O40: Primary KC Alignment: The calculation required to find how many months $120 can pay for is $120 [FORMULA] (3/4 [FORMULA] 120)$, which simplifies to $120 [FORMULA] 90 = 1.33...$, and NOT a whole number divided by a proper fraction as specified. The phrasing and construction do not enforce the need to divide by a fraction. Secondary KC Alignment: The problem only requires simple subtraction of whole numbers ($120 - 2 [FORMULA] 90 = $ amount left) and NOT the explicit subtraction of fractions as a requisite. Synergy: The knowledge components (dividing a whole number by a fraction and subtracting fractions) are not used in tandem to produce an answer; instead, each operates in isolation if at all. | P40: 4.4487026
A41: TD | B41: Question 40 | C41: 0 | D41: 0 | E41: 'NA | F41: 'NA | G41: 'NA | H41: 'NA | I41: 'NA | J41: 'NA | K41: 'NA | L41: 'NA | M41: 0 | N41: 'NA | O41: answerability (Qb: 'divided by 3/4' illogical since child is receiving 3/4 of what was planned; question suggests more money than original; mismatched scenario)+primary_kc_alignment (no requirement to divide by a fraction in any step; only multiply by a fraction)+synergy (subquestion (b) does not logically follow from (a))/clarity (part b's intent is ambiguous and mathematically inconsistent)/conciseness_and_relevance (part b is not relevant to the scenario and introduces confusion)/language_quality (part b is grammatically and mathematically confusing)/ | P41: 3.3171818 | Q41: 'NA
A42: TD | B42: Question 41 | C42: 0 | D42: 1 | E42: 1 | F42: 0 | G42: 1 | H42: 1 | I42: 1 | J42: 'NA | K42: 1 | L42: 1 | M42: 1 | N42: 1 | O42: Secondary KC Alignment (0): The secondary knowledge component is 'adding whole numbers.' However, to answer the only question posed ('What is the total amount Alice spent on her household expenses this month?'), students only need to find the whole given a part and percentage—they do not have to add the amounts spent on groceries and transport, as these are distractions. There is no requirement to add multiple amounts to solve the problem. Synergy (0): Both the Primary and Secondary KCs are not used in tandem; only percentage calculation is needed, and the additional values (groceries, transport) are not required to solve the question. | P42: 4.8360677
A43: TD | B43: Question 42 | C43: 0 | D43: 1 | E43: 1 | F43: 1 | G43: 1 | H43: 1 | I43: 1 | J43: 1 | K43: 1 | L43: 1 | M43: 1 | N43: 1 | P43: 1.2423837
A44: TD | B44: Question 43 | C44: 0 | D44: 1 | E44: 1 | F44: 1 | G44: 1 | H44: 1 | I44: 1 | J44: 1 | K44: 1 | L44: 1 | M44: 1 | N44: 1 | P44: 1.5768292
A45: TD | B45: Question 44 | C45: 0 | D45: 1 | E45: 1 | F45: 1 | G45: 1 | H45: 1 | I45: 1 | J45: 1 | K45: 1 | L45: 1 | M45: 1 | N45: 1 | P45: 1.4506187
A46: TD | B46: Question 45 | C46: 0 | D46: 1 | E46: 1 | F46: 1 | G46: 1 | H46: 1 | I46: 1 | J46: 1 | K46: 1 | L46: 1 | M46: 1 | N46: 1 | P46: 1.1676159
A47: TD | B47: Question 46 | C47: 0 | D47: 1 | E47: 1 | F47: 1 | G47: 1 | H47: 1 | I47: 1 | J47: 1 | K47: 1 | L47: 1 | M47: 1 | N47: 1 | P47: 1.7574644
A48: TD | B48: Question 47 | C48: 0 | D48: 1 | E48: 1 | F48: 1 | G48: 1 | H48: 1 | I48: 1 | J48: 1 | K48: 1 | L48: 1 | M48: 1 | N48: 1 | P48: 1.6744878
A49: TD | B49: Question 48 | C49: 0 | D49: 1 | E49: 0 | F49: 1 | G49: 1 | H49: 'NA | I49: 1 | J49: 'NA | K49: 1 | L49: 1 | M49: 1 | N49: 1 | O49: primary_kc_alignment: The problem specifies 'multiplication of matrices' as the intended Primary KC, but the operation required is the element-wise (Hadamard) product, not the standard matrix multiplication. O-levels syllabus expects matrix multiplication in the sense of row-by-column, not Hadamard product (element-wise multiplication), so the primary KC is misaligned for Singapore's secondary curriculum. | P49: 4.2818387
A50: TD | B50: Question 49 | C50: 0 | D50: 1 | E50: 1 | F50: 1 | G50: 1 | H50: 1 | I50: 1 | J50: 1 | K50: 1 | L50: 1 | M50: 1 | N50: 1 | P50: 1.7394755
A51: Minh | B51: Question 1 | C51: 0 | D51: 1 | E51: 1 | F51: 1 | G51: 1 | H51: 1 | I51: 1 | J51: 1 | K51: 1 | L51: 1 | M51: 1 | N51: 1 | P51: 1.3353014
A52: Minh | B52: Question 2 | C52: 0 | D52: 1 | E52: 1 | F52: 1 | G52: 1 | H52: 1 | I52: 1 | J52: 1 | K52: 1 | L52: 1 | M52: 1 | N52: 1 | P52: 1.2394407
A53: Minh | B53: Question 3 | C53: 0 | D53: 1 | E53: 1 | F53: 1 | G53: 1 | H53: 1 | I53: 1 | J53: 1 | K53: 1 | L53: 1 | M53: 1 | N53: 1 | P53: 1.1495199
A54: Minh | B54: Question 4 | C54: 0 | D54: 1 | E54: 1 | F54: 1 | G54: 1 | H54: 1 | I54: 1 | J54: 1 | K54: 1 | L54: 1 | M54: 1 | N54: 1 | P54: 1.1261098
A55: Minh | B55: Question 5 | C55: 0 | D55: 1 | E55: 1 | F55: 1 | G55: 1 | H55: 1 | I55: 1 | J55: 1 | K55: 1 | L55: 1 | M55: 1 | N55: 1 | P55: 1.9189367
A56: Minh | B56: Question 6 | C56: 0 | D56: 1 | E56: 0 | F56: 1 | G56: 1 | H56: 'NA | I56: 1 | J56: 'NA | K56: 1 | L56: 1 | M56: 1 | N56: 1 | O56: primary_kc_alignment: The problem requires dividing 624 by 8. 624 is a 3-digit number, but in Singapore Primary 3 curriculum, division should be by a 1-digit number. While 624 ÷ 8 matches this, the context (using $624 and division to find price per chair) might be slightly abstract for P3 unless they have already seen such money problems; contextually it's on the high end of difficulty but technically matches the KC. However, generally, price per unit scenario in P3 is introduced in P4. To be strict, if only strictly dividing up to 3 digits by 1 digit is intended, this narrowly fits, but for full alignment considering curriculum progression, this is not always expected at this level. synergy: The solution process here requires division (to find the price per chair) and then multiplication (to find the cost for 6 chairs), but these do not depend on each other's final result to start the next calculation—the multiplication is a continuation after division. However, it is marginal; the multiplication step directly uses the result from division. If synergy is interpreted as 'must use both in sequence,' this does apply, but if it requires more deeply integrated reasoning, it's weaker, so stricter marking gives 0 if strict definition is used. | P56: 4.6449063
A57: Minh | B57: Question 7 | C57: 0 | D57: 1 | E57: 1 | F57: 1 | G57: 1 | H57: 1 | I57: 1 | J57: 1 | K57: 1 | L57: 1 | M57: 1 | N57: 1 | P57: 1.4189968
A58: Minh | B58: Question 8 | C58: 0 | D58: 1 | E58: 1 | F58: 1 | G58: 1 | H58: 1 | I58: 1 | J58: 1 | K58: 1 | L58: 1 | M58: 1 | N58: 1 | P58: 1.6930029
A59: Minh | B59: Question 9 | C59: 0 | D59: 1 | E59: 1 | F59: 1 | G59: 0 | H59: 1 | I59: 1 | J59: 1 | K59: 1 | L59: 1 | M59: 1 | N59: 1 | O59: D4: The context is about buying soap bars, which relates to shopping, not specifically to household finance topics such as income, bills, or financial planning. It does not involve any money, savings, or financial detail. | P59: 1.582597
A60: Minh | B60: Question 10 | C60: 0 | D60: 1 | E60: 1 | F60: 1 | G60: 1 | H60: 1 | I60: 1 | J60: 1 | K60: 1 | L60: 1 | M60: 1 | N60: 1 | P60: 1.6458054
A61: Minh | B61: Question 11 | C61: 0 | D61: 1 | E61: 1 | F61: 1 | G61: 1 | H61: 1 | I61: 1 | J61: 1 | K61: 1 | L61: 1 | M61: 1 | N61: 1 | P61: 1.48912
A62: Minh | B62: Question 12 | C62: 0 | D62: 1 | E62: 1 | F62: 1 | G62: 1 | H62: 1 | I62: 1 | J62: 1 | K62: 1 | L62: 1 | M62: 1 | N62: 1 | P62: 1.2657225
A63: Minh | B63: Question 13 | C63: 0 | D63: 1 | E63: 1 | F63: 1 | G63: 1 | H63: 1 | I63: 1 | J63: 1 | K63: 1 | L63: 1 | M63: 1 | N63: 1 | P63: 1.1045003
A64: Minh | B64: Question 14 | C64: 0 | D64: 1 | E64: 1 | F64: 1 | G64: 1 | H64: 1 | I64: 1 | J64: 0 | K64: 1 | L64: 1 | M64: 1 | N64: 1 | O64: Synergy=0: The two parts (a) and (b) are not connected; the answer to part (a) is not needed to solve part (b), nor vice versa. | P64: 4.2892621
A65: Minh | B65: Question 15 | C65: 0 | D65: 1 | E65: 1 | F65: 1 | G65: 1 | H65: 1 | I65: 1 | J65: 1 | K65: 1 | L65: 0 | M65: 1 | N65: 1 | O65: Conciseness and Relevance: The problem asks the student to round the total expense to three different formats (nearest dollar, 1 decimal place, 2 decimal places). For Primary 4 in Singapore, requiring three different rounding formats in one question may be excessive and could be considered as overloading with repetitive tasks; educationally, this could be streamlined to just one or two, improving conciseness and focus. | P65: 3.3739564
A66: Minh | B66: Question 16 | C66: 0 | D66: 1 | E66: 1 | F66: 1 | G66: 1 | H66: 1 | I66: 1 | J66: 1 | K66: 1 | L66: 1 | M66: 1 | N66: 1 | P66: 1.1211123
A67: Minh | B67: Question 17 | C67: 0 | D67: 1 | E67: 1 | F67: 1 | G67: 1 | H67: 1 | I67: 1 | J67: 1 | K67: 1 | L67: 1 | M67: 1 | N67: 1 | P67: 1.2423325
A68: Minh | B68: Question 18 | C68: 0 | D68: 1 | E68: 0 | F68: 1 | G68: 1 | H68: 'NA | I68: 1 | J68: 'NA | K68: 1 | L68: 1 | M68: 1 | N68: 1 | O68: Primary KC Alignment: The problem requires dividing 36.45 by 5, which results in 7.29 (two decimal places). However, Primary 4 Singapore syllabus typically restricts the division of decimals by whole numbers to at MOST 2 decimal places IN THE QUESTION (i.e., numbers such as 36.45 divided by 5 are not standard; they usually involve dividends with 1 or 2 decimal places which divide evenly, e.g., 36.40 ÷ 5 = 7.28, 36.50 ÷ 5 = 7.30). In addition, requiring students to understand and perform the calculation 36.45 ÷ 5 = 7.29 is marginal for Primary 4 based on current MOE guidelines, so this should not appear as a routine item at that grade. | P68: 4.509407
A69: Minh | B69: Question 19 | C69: 0 | D69: 1 | E69: 1 | F69: 1 | G69: 1 | H69: 1 | I69: 1 | J69: 1 | K69: 1 | L69: 1 | M69: 1 | N69: 1 | P69: 1.5955815
A70: Minh | B70: Question 20 | C70: 0 | D70: 1 | E70: 1 | F70: 1 | G70: 1 | H70: 1 | I70: 1 | J70: 1 | K70: 1 | L70: 1 | M70: 1 | N70: 1 | P70: 1.3021872
A71: Minh | B71: Question 21 | C71: 0 | D71: 1 | E71: 1 | F71: 0 | G71: 1 | H71: 1 | I71: 1 | J71: 'NA | K71: 1 | L71: 1 | M71: 1 | N71: 1 | O71: Secondary KC Alignment: Mrs Lim is to use 1/4 of her total earnings to pay her electricity bill, and the question asks 'How much money does Mrs Lim have left after paying the bill?'. This calculation only requires subtracting the amount paid (which is a whole number) from the total (also a whole number), not subtracting fractions from each other. Only multiplication of fractions and whole numbers is needed. Synergy: Since the subtraction is just total - amount paid (both whole numbers), the process does not require both multiplication and subtraction of fractions to be used together. | P71: 2.5408134
A72: Minh | B72: Question 22 | C72: 0 | D72: 1 | E72: 1 | F72: 1 | G72: 1 | H72: 1 | I72: 1 | J72: 1 | K72: 1 | L72: 1 | M72: 1 | N72: 1 | P72: 1.5579085
A73: Minh | B73: Question 23 | C73: 0 | D73: 1 | E73: 1 | F73: 1 | G73: 1 | H73: 1 | I73: 1 | J73: 1 | K73: 1 | L73: 1 | M73: 1 | N73: 1 | P73: 1.1720917
A74: Minh | B74: Question 24 | C74: 0 | D74: 1 | E74: 0 | F74: 0 | G74: 1 | H74: 'NA | I74: 1 | J74: 'NA | K74: 1 | L74: 1 | M74: 1 | N74: 1 | O74: Primary KC Alignment: The problem asks for 2.5 (mixed number) x $12 (whole number), but it is a mixed number times a whole number, not a mixed number times a whole number as specified in the prompt; it meets this but does not require students to perform multiplication by decomposing the mixed number which is expected depth for P5. Secondary KC Alignment: The comparison is between dollar amounts, not fractions or mixed numbers or their ordering, thus not exercising comparison and ordering of fractions. Synergy: The secondary KC is not needed to solve the main problem nor to interpret the result—the two parts of the question are related through context but not through the mathematical operations required. | P74: 6.3240974
A75: Minh | B75: Question 25 | C75: 0 | D75: 1 | E75: 1 | F75: 1 | G75: 1 | H75: 1 | I75: 1 | J75: 1 | K75: 1 | L75: 1 | M75: 1 | N75: 1 | P75: 1.7688134
A76: Minh | B76: Question 26 | C76: 0 | D76: 1 | E76: 1 | F76: 1 | G76: 0 | H76: 1 | I76: 1 | J76: 1 | K76: 1 | L76: 1 | M76: 1 | N76: 1 | O76: 4- The word problem is about buying rice for family use, but it does not relate to household finance topics such as income, bills, savings, financial planning, or similar. It is focused on quantity measurement rather than financial transactions or calculations. | P76: 3.3945732
A77: Minh | B77: Question 27 | C77: 0 | D77: 1 | E77: 0 | F77: 1 | G77: 1 | H77: 'NA | I77: 1 | J77: 'NA | K77: 1 | L77: 1 | M77: 1 | N77: 1 | O77: Primary KC Alignment: - The problem requires general multiplication with decimals (not necessarily by 10, 100, 1000 or their multiples, which is explicit in the intended primary knowledge component). Here, the multiplication is by 0.183, which is not a multiple of 10, 100, or 1000, so students are not required to use those specific strategies. Instead, it is just multiplying decimals generally. | P77: 2.3133929
A78: Minh | B78: Question 28 | C78: 0 | D78: 1 | E78: 1 | F78: 1 | G78: 1 | H78: 1 | I78: 1 | J78: 1 | K78: 1 | L78: 1 | M78: 0 | N78: 1 | O78: language_quality: The use of the value "$187.250" is not standard notation for money in Singapore or most countries. Typically, money is written as "$187.25" or "$187.25" (without the extra zero), as monetary values do not usually go to three decimal places. This could confuse students about proper decimal and financial notation. | P78: 1.9579649
A79: Minh | B79: Question 29 | C79: 0 | D79: 1 | E79: 1 | F79: 1 | G79: 1 | H79: 1 | I79: 1 | J79: 1 | K79: 1 | L79: 1 | M79: 1 | N79: 1 | P79: 1.50876
A80: Minh | B80: Question 30 | C80: 0 | D80: 1 | E80: 1 | F80: 1 | G80: 1 | H80: 1 | I80: 1 | J80: 1 | K80: 1 | L80: 1 | M80: 1 | N80: 1 | P80: 1.2272413
A81: Minh | B81: Question 31 | C81: 0 | D81: 1 | E81: 1 | F81: 1 | G81: 1 | H81: 1 | I81: 1 | J81: 1 | K81: 1 | L81: 1 | M81: 1 | N81: 1 | P81: 1.6360438
A82: Minh | B82: Question 32 | C82: 0 | D82: 1 | E82: 1 | F82: 1 | G82: 1 | H82: 1 | I82: 1 | J82: 1 | K82: 1 | L82: 1 | M82: 1 | N82: 1 | P82: 1.2221985
A83: Minh | B83: Question 33 | C83: 0 | D83: 1 | E83: 1 | F83: 1 | G83: 0 | H83: 1 | I83: 1 | J83: 1 | K83: 1 | L83: 1 | M83: 1 | N83: 1 | O83: 4: The context is not about household finance (income, bills, money, loans, financial planning, etc.), but about cake-sharing at a family gathering. | P83: 2.9778976
A84: Minh | B84: Question 34 | C84: 0 | D84: 1 | E84: 1 | F84: 1 | G84: 1 | H84: 1 | I84: 1 | J84: 1 | K84: 1 | L84: 1 | M84: 1 | N84: 1 | P84: 1.2916818
A85: Minh | B85: Question 35 | C85: 0 | D85: 1 | E85: 1 | F85: 1 | G85: 0 | H85: 1 | I85: 1 | J85: 1 | K85: 1 | L85: 1 | M85: 1 | N85: 1 | O85: 4- The problem concerns repacking detergent and does not relate to household finance topics such as income, bills, money, interest, savings, or financial planning, thus the topic alignment fails. | P85: 2.5405138
A86: Minh | B86: Question 36 | C86: 0 | D86: 1 | E86: 1 | F86: 0 | G86: 1 | H86: 1 | I86: 1 | J86: 'NA | K86: 1 | L86: 1 | M86: 1 | N86: 1 | O86: secondary_kc_alignment: The question only requires students to find the whole given a part and percentage, but there is no requirement for subtraction between whole numbers since it only asks for the total spent. synergy: Since subtraction is not required as part of the solution, Primary KC and Secondary KC cannot be used together in tandem. | P86: 5.1387165
A87: Minh | B87: Question 37 | C87: 0 | D87: 1 | E87: 1 | F87: 1 | G87: 1 | H87: 1 | I87: 1 | J87: 1 | K87: 1 | L87: 1 | M87: 1 | N87: 1 | P87: 1.2397883
A88: Minh | B88: Question 38 | C88: 0 | D88: 1 | E88: 1 | F88: 1 | G88: 1 | H88: 1 | I88: 1 | J88: 1 | K88: 1 | L88: 1 | M88: 1 | N88: 1 | P88: 1.849262
A89: Minh | B89: Question 39 | C89: 0 | D89: 1 | E89: 1 | F89: 1 | G89: 1 | H89: 1 | I89: 1 | J89: 1 | K89: 1 | L89: 1 | M89: 1 | N89: 1 | P89: 1.3283138
A90: Minh | B90: Question 40 | C90: 0 | D90: 1 | E90: 1 | F90: 1 | G90: 1 | H90: 1 | I90: 1 | J90: 1 | K90: 1 | L90: 1 | M90: 1 | N90: 1 | P90: 1.2056506
A91: Minh | B91: Question 41 | C91: 0 | D91: 1 | E91: 1 | F91: 1 | G91: 1 | H91: 1 | I91: 1 | J91: 1 | K91: 1 | L91: 1 | M91: 1 | N91: 1 | P91: 1.3783488
A92: Minh | B92: Question 42 | C92: 0 | D92: 1 | E92: 1 | F92: 1 | G92: 1 | H92: 1 | I92: 1 | J92: 1 | K92: 1 | L92: 1 | M92: 1 | N92: 1 | P92: 1.411845
A93: Minh | B93: Question 43 | C93: 0 | D93: 1 | E93: 1 | F93: 1 | G93: 1 | H93: 1 | I93: 1 | J93: 1 | K93: 1 | L93: 1 | M93: 1 | N93: 1 | P93: 5.3139522
A94: Minh | B94: Question 44 | C94: 0 | D94: 1 | E94: 1 | F94: 1 | G94: 1 | H94: 1 | I94: 1 | J94: 1 | K94: 1 | L94: 1 | M94: 1 | N94: 1 | P94: 1.8483503
A95: Minh | B95: Question 45 | C95: 0 | D95: 1 | E95: 1 | F95: 1 | G95: 1 | H95: 1 | I95: 1 | J95: 1 | K95: 1 | L95: 1 | M95: 1 | N95: 1 | P95: 1.1964595
A96: Minh | B96: Question 46 | C96: 0 | D96: 1 | E96: 1 | F96: 1 | G96: 1 | H96: 1 | I96: 1 | J96: 1 | K96: 1 | L96: 1 | M96: 1 | N96: 1 | P96: 1.8777051
A97: Minh | B97: Question 47 | C97: 0 | D97: 1 | E97: 1 | F97: 1 | G97: 1 | H97: 1 | I97: 1 | J97: 1 | K97: 1 | L97: 1 | M97: 1 | N97: 1 | P97: 1.1919971
A98: Minh | B98: Question 48 | C98: 0 | D98: 1 | E98: 1 | F98: 1 | G98: 1 | H98: 1 | I98: 1 | J98: 1 | K98: 1 | L98: 1 | M98: 1 | N98: 1 | P98: 1.3014591
... A103: Minh | B103: Question 53 | C103: 0 | D103: 1 | E103: 1 | F103: 1 | G103: 1 | H103: 1 | I103: 1 | J103: 1 | K103: 1 | L103: 1 | M103: 1 | N103: 1 | P103: 1.133533
A104: Minh | B104: Question 54 | C104: 0 | D104: 1 | E104: 1 | F104: 1 | G104: 1 | H104: 1 | I104: 1 | J104: 0 | K104: 1 | L104: 1 | M104: 1 | N104: 1 | O104: Synergy: 0. Both (a) and (b) are independent and do not require the result of one to solve the other. The answers to part (a) and (b) can be found separately without using information or answers from each other. | P104: 2.8147304
...

Sheet householdfinance_v4_4
A1: Evaluator | B1: Question | C1: status | D1: answerability | E1: primary_kc_alignment | F1: secondary_kc_alignment | G1: topic_alignment | H1: grade_alignment | I1: real_world_feasibility | J1: synergy | K1: clarity | L1: conciseness_and_relevance | M1: language_quality | N1: content_appropriateness | O1: explanation | P1: response_time | Q1: language_quality1
A2: TD | B2: Question 1 | C2: 0 | D2: 1 | E2: 1 | F2: 1 | G2: 1 | H2: 1 | I2: 1 | J2: 1 | K2: 1 | L2: 1 | M2: 1 | N2: 1 | P2: 1.2219443
A3: TD | B3: Question 2 | C3: 0 | D3: 1 | E3: 1 | F3: 0 | G3: 1 | H3: 1 | I3: 1 | J3: 'NA | K3: 1 | L3: 1 | M3: 1 | N3: 1 | O3: Secondary KC Alignment: The problem only requires subtraction to find how much Sarah spent before her father gave her more money. The additional $80 is mentioned but not needed for any calculation related to the question, so addition is not required nor tested for solving. Synergy: Only the subtraction operation is essential to solve the problem; addition is not required at all, so the KCs are not synergistic. | P3: 2.8440704
A4: TD | B4: Question 3 | C4: 0 | D4: 1 | E4: 1 | F4: 1 | G4: 0 | H4: 1 | I4: 1 | J4: 1 | K4: 1 | L4: 1 | M4: 1 | N4: 1 | O4: 4: The scenario is about sharing candies among children, which does not align with the intended topic of household finance (e.g., money, bills, savings, etc.). | P4: 1.688848
A5: TD | B5: Question 4 | C5: 0 | D5: 1 | E5: 1 | F5: 1 | G5: 1 | H5: 1 | I5: 1 | J5: 1 | K5: 1 | L5: 1 | M5: 1 | N5: 1 | P5: 1.4934435
A6: TD | B6: Question 5 | C6: 0 | D6: 1 | E6: 1 | F6: 1 | G6: 1 | H6: 1 | I6: 1 | J6: 1 | K6: 1 | L6: 1 | M6: 1 | N6: 1 | P6: 2.2394876
A7: TD | B7: Question 6 | C7: 0 | D7: 1 | E7: 1 | F7: 1 | G7: 1 | H7: 1 | I7: 1 | J7: 1 | K7: 1 | L7: 1 | M7: 1 | N7: 1 | P7: 1.2877691
A8: TD | B8: Question 7 | C8: 0 | D8: 1 | E8: 1 | F8: 1 | G8: 0 | H8: 1 | I8: 1 | J8: 1 | K8: 1 | L8: 1 | M8: 1 | N8: 1 | O8: 4- The context is bulk purchase of light bulbs for a new house, which is more closely related to household supplies rather than specific household finance topics such as income, utility bills, money, interest, savings, instalments, mortgage, or financial planning as listed in the intended topic metadata. | P8: 2.3983157
A9: TD | B9: Question 8 | C9: 0 | D9: 1 | E9: 1 | F9: 1 | G9: 1 | H9: 1 | I9: 1 | J9: 1 | K9: 1 | L9: 1 | M9: 1 | N9: 1 | P9: 1.2872007
A10: TD | B10: Question 9 | C10: 0 | D10: 1 | E10: 1 | F10: 0 | G10: 1 | H10: 1 | I10: 1 | J10: 'NA | K10: 1 | L10: 1 | M10: 1 | N10: 1 | O10: 3: Subtraction is not actually required to solve the problem as posed; students only need to subtract if they are determining how much is distributed to the children, but the direct question only asks for how much each child receives—which is solved directly by division. 7: The division and subtraction do not need to be used together in this problem—the subtraction (3872-320) is not needed for the main question. | P10: 2.3286996
A11: TD | B11: Question 10 | C11: 0 | D11: 1 | E11: 1 | F11: 1 | G11: 1 | H11: 1 | I11: 1 | J11: 1 | K11: 1 | L11: 1 | M11: 1 | N11: 1 | P11: 2.1397135
A12: TD | B12: Question 11 | C12: 0 | D12: 1 | E12: 1 | F12: 1 | G12: 1 | H12: 1 | I12: 1 | J12: 1 | K12: 1 | L12: 1 | M12: 1 | N12: 1 | P12: 1.1427646
A13: TD | B13: Question 12 | C13: 0 | D13: 1 | E13: 1 | F13: 1 | G13: 1 | H13: 1 | I13: 1 | J13: 1 | K13: 1 | L13: 1 | M13: 1 | N13: 1 | P13: 1.1573029
A14: TD | B14: Question 13 | C14: 0 | D14: 1 | E14: 0 | F14: 1 | G14: 1 | H14: 'NA | I14: 0 | J14: 'NA | K14: 1 | L14: 1 | M14: 1 | N14: 1 | O14: Primary KC Alignment: The electricity bill in part (b) uses 3 decimal places ($45.605$), which exceeds the intended KC of adding decimals up to 2 decimal places. Furthermore, addition in (a), although correct KC, is paired with (b) that requires understanding numbers with 3 decimal places, which is not expected at Primary 4 level. Grade Alignment: At Primary 4 in Singapore, students typically only work with decimals up to 2 places; using 3 decimal places (and especially for a monetary value) is not suitable for this level. Real-World Feasibility: Monetary amounts are never listed as $45.605$; actual bills would only be given in cents. Synergy: Part (b) is unrelated to the computation in (a) except for using the word 'electricity bill'; no result from (a) is used to answer (b). | P14: 3.3945925
A15: TD | B15: Question 14 | C15: 0 | D15: 1 | E15: 1 | F15: 1 | G15: 1 | H15: 1 | I15: 1 | J15: 1 | K15: 1 | L15: 1 | M15: 1 | N15: 1 | P15: 1.8518035
A16: TD | B16: Question 15 | C16: 0 | D16: 1 | E16: 1 | F16: 1 | G16: 1 | H16: 1 | I16: 1 | J16: 1 | K16: 1 | L16: 1 | M16: 1 | N16: 1 | P16: 1.1612937
A17: TD | B17: Question 16 | C17: 0 | D17: 1 | E17: 1 | F17: 1 | G17: 1 | H17: 1 | I17: 1 | J17: 0 | K17: 1 | L17: 1 | M17: 1 | N17: 1 | O17: Synergy = 0: The two questions (a and b) are not connected; the answer from part (a) is not needed for part (b) and vice versa. Each part can be completed independently; thus, no synergy between the primary and secondary KC. | P17: 3.2059748
A18: TD | B18: Question 17 | C18: 0 | D18: 1 | E18: 1 | F18: 1 | G18: 1 | H18: 1 | I18: 1 | J18: 1 | K18: 1 | L18: 1 | M18: 1 | N18: 1 | P18: 1.7473373
A19: TD | B19: Question 18 | C19: 0 | D19: 1 | E19: 1 | F19: 1 | G19: 1 | H19: 1 | I19: 1 | J19: 1 | K19: 1 | L19: 1 | M19: 1 | N19: 1 | P19: 4.708442
A20: TD | B20: Question 19 | C20: 0 | D20: 1 | E20: 1 | F20: 1 | G20: 1 | H20: 1 | I20: 1 | J20: 1 | K20: 1 | L20: 1 | M20: 1 | N20: 1 | P20: 1.8247626
A21: TD | B21: Question 20 | C21: 0 | D21: 1 | E21: 1 | F21: 1 | G21: 1 | H21: 1 | I21: 0 | J21: 1 | K21: 1 | L21: 1 | M21: 1 | N21: 1 | O21: 6: The fractions $1[FORMULA]$ and $2[FORMULA]$ both describe spending 'more than the whole budget' individually, which is unrealistic. In real household finance, fractions of a budget spent should each be less than or equal to 1 (100%), or at least the total should not exceed the budget by such a large amount. This situation is not feasible for a real-world household scenario. | P21: 3.1137216
A22: TD | B22: Question 21 | C22: 0 | D22: 1 | E22: 1 | F22: 1 | G22: 1 | H22: 1 | I22: 1 | J22: 1 | K22: 1 | L22: 1 | M22: 1 | N22: 1 | P22: 1.3676219
A23: TD | B23: Question 22 | C23: 0 | D23: 1 | E23: 1 | F23: 0 | G23: 1 | H23: 1 | I23: 1 | J23: 'NA | K23: 1 | L23: 1 | M23: 1 | N23: 1 | O23: Secondary KC Alignment (3): The problem only requires a direct comparison between two whole numbers (amount saved and $90). There is no need to compare or order two fractions as intended; the comparison is a simple greater/less than between whole numbers. Synergy (7): The solution does not integrate both the multiplication of fractions and the comparison and ordering of fractions, as intended by the Secondary Knowledge Component. Thus, the components are not used in tandem. | P23: 2.1229117
A24: TD | B24: Question 23 | C24: 0 | D24: 1 | E24: 1 | F24: 1 | G24: 1 | H24: 1 | I24: 1 | J24: 1 | K24: 1 | L24: 1 | M24: 1 | N24: 1 | P24: 1.6866653
A25: TD | B25: Question 24 | C25: 0 | D25: 1 | E25: 1 | F25: 0 | G25: 1 | H25: 1 | I25: 1 | J25: 'NA | K25: 1 | L25: 1 | M25: 1 | N25: 1 | O25: Secondary KC Alignment (Addition): The solution only requires multiplying by fractions at each step. At no point does the student need to add any fractions to determine the final answer, so the adding fractions knowledge component is not necessary. Synergy: Because addition of fractions is not required in this problem, the two KCs are not used in tandem. | P25: 2.9219103
A26: TD | B26: Question 25 | C26: 0 | D26: 1 | E26: 1 | F26: 1 | G26: 1 | H26: 1 | I26: 1 | J26: 1 | K26: 1 | L26: 1 | M26: 1 | N26: 1 | P26: 1.1313078
A27: TD | B27: Question 26 | C27: 0 | D27: 1 | E27: 0 | F27: 0 | G27: 0 | H27: 'NA | I27: 1 | J27: 'NA | K27: 1 | L27: 1 | M27: 1 | N27: 1 | O27: 2: Primary KC is multiplying improper fractions, but all multiplications are with a whole number (3) and an improper fraction, not two improper fractions. 3: Secondary KC is 'adding fractions', but the only calculations required are subtraction and multiplication, not addition of fractions. 4: Topic is household finance, but the problem is about food volume, specifically juice, not finances, expenses, or money. | P27: 4.7269297
A28: TD | B28: Question 27 | C28: 0 | D28: 0 | E28: 'NA | F28: 'NA | G28: 'NA | H28: 'NA | I28: 'NA | J28: 'NA | K28: 'NA | L28: 'NA | M28: 1 | N28: 'NA | O28: answerability: a) Fractions used (7/4 and 5/3) are greater than 1, which means more was spent than saved, leading to an illogical scenario for dividing up a whole into parts. b) The fractions do not represent parts of the whole, violating basic sense of partition.primary_kc_alignment: a) The solution requires multiplying a fraction by a whole number, not multiplying two fractions as required by the intended KC.secondary_kc_alignment: a) No actual fractional subtraction is required; subtraction is with whole numbers resulting from previous step, not between fractions, so intended KC is not well-aligned.grade_alignment: a) Problems expecting students to use improper fractions greater than 1 to represent partitions or allocations are not suitable for Primary 5 curriculum; b) Fractions >1 in real-life contexts like this are not typically introduced until secondary level.real_world_feasibility: a) It is not possible for someone to spend more than their total savings on separate expenses both exceeding the original amount.synergy: a) There is no real need to use both skills together—the setup is faulty.clarity: a) Ambiguity in partitioning savings, and confusing use of improper fractions greater than 1. | P28: 8.7780323 | Q28: 'NA
A29: TD | B29: Question 28 | C29: 0 | D29: 0 | E29: 'NA | F29: 'NA | G29: 'NA | H29: 'NA | I29: 'NA | J29: 'NA | K29: 'NA | L29: 'NA | M29: 1 | N29: 'NA | O29: A: Problem contains insufficient, unclear, or conflicting information. The relationships between budget, brushes, and paints are unclear for the required calculation; not enough information to find the actual fraction of budget used for brushes.* P: The requirement asks for 'fraction of her total budget used for brushes', but the only usable brush money is '6/5' of some amount, conflicting with real expenses. Calculation of brush spending out of total is unclear; multiplication of two improper fractions is not required to answer. G: The problem involves complicated ratio reasoning and multiple relationships, which is above Primary 5 standard for fractions and proportionality. S: The synergy is missing; the intended primary KC (multiplying two improper fractions) is not required to answer the question. CL: Ambiguity and lack of clarity regarding what '6/5 of the money she spent on brushes was actually used' refers to, and unclear steps to determine the answer. CR: Not all information is relevant or necessary, especially the difference between money set aside, spent, and used—it is not clear what to do with all quantities. | P29: 3.8203835 | Q29: 'NA
A30: TD | B30: Question 29 | C30: 0 | D30: 1 | E30: 1 | F30: 1 | G30: 0 | H30: 1 | I30: 1 | J30: 1 | K30: 1 | L30: 1 | M30: 1 | N30: 1 | O30: D- The topic is not aligned. The problem is about baking and using ingredients, but does NOT relate to the intended topic of household finance (income, bills, savings, etc.), although it could loosely connect if, for example, chocolate cost or income from sales were included, but as currently written it does not satisfy the specified finance context. | P30: 2.4234817
A31: TD | B31: Question 30 | C31: 0 | D31: 1 | E31: 0 | F31: 1 | G31: 1 | H31: 'NA | I31: 1 | J31: 'NA | K31: 1 | L31: 1 | M31: 1 | N31: 1 | O31: Primary KC Alignment: The core decimal multiplication required is $3.75 [FORMULA] 0.174 [FORMULA] 100$, but multiplying by 0.174 is not multiplying by 10, 100, 1000 or their multiples. The intended KC specifically requests multiplying decimals by those round numbers only, not by a general decimal. Thus, the word problem does not necessitate applying the intended decimal-multiplication-by-10/100/1000 skill as required. | P31: 2.1560471
A32: TD | B32: Question 31 | C32: 0 | D32: 0 | E32: 'NA | F32: 'NA | G32: 'NA | H32: 'NA | I32: 'NA | J32: 'NA | K32: 'NA | L32: 'NA | M32: 1 | N32: 'NA | O32: answerability: - The problem asks Mr Lim to 'subtract' the service fee from his cost calculation, but in real-world context, a service fee is added, not subtracted. This introduces a contradiction, making the intended solution unanswerable or misleading. primary_kc_alignment: - The multiplication is between 73.245 and 0.15, but this is not a multiplication by 10, 100, 1000 or their multiples. Instead, it is a multiplication of decimals by decimals (not specifically aligned with the intended primary KC). synergy: - The use of subtraction is not logically or procedurally dependent on the prior multiplication step because the problem incorrectly asks for subtraction of a fee rather than addition—steps cannot be used in tandem to reach a valid answer. | P32: 5.2156894 | Q32: 'NA
A33: TD | B33: Question 32 | C33: 0 | D33: 1 | E33: 1 | F33: 1 | G33: 1 | H33: 1 | I33: 1 | J33: 1 | K33: 1 | L33: 1 | M33: 1 | N33: 1 | P33: 1.3387184
A34: TD | B34: Question 33 | C34: 0 | D34: 1 | E34: 1 | F34: 1 | G34: 1 | H34: 1 | I34: 1 | J34: 1 | K34: 1 | L34: 1 | M34: 1 | N34: 1 | P34: 2.0605581
A35: TD | B35: Question 34 | C35: 0 | D35: 1 | E35: 1 | F35: 1 | G35: 1 | H35: 1 | I35: 1 | J35: 1 | K35: 1 | L35: 1 | M35: 1 | N35: 1 | P35: 1.2560349
A36: TD | B36: Question 35 | C36: 0 | D36: 1 | E36: 1 | F36: 1 | G36: 1 | H36: 1 | I36: 1 | J36: 1 | K36: 1 | L36: 1 | M36: 1 | N36: 1 | P36: 1.1417625
A37: TD | B37: Question 36 | C37: 0 | D37: 1 | E37: 1 | F37: 1 | G37: 1 | H37: 1 | I37: 1 | J37: 1 | K37: 1 | L37: 1 | M37: 1 | N37: 1 | P37: 1.2070439
A38: TD | B38: Question 37 | C38: 0 | D38: 1 | E38: 1 | F38: 1 | G38: 1 | H38: 1 | I38: 1 | J38: 1 | K38: 1 | L38: 1 | M38: 1 | N38: 1 | P38: 1.5221553
A39: TD | B39: Question 38 | C39: 0 | D39: 1 | E39: 1 | F39: 1 | G39: 0 | H39: 1 | I39: 1 | J39: 1 | K39: 1 | L39: 1 | M39: 1 | N39: 1 | O39: 4: The problem involves dividing trays of cookies for a fundraiser, which is not related to household finance topics like income, bills, savings, etc. The scenario is about charity and food distribution, not finance. | P39: 1.6308589
A40: TD | B40: Question 39 | C40: 0 | D40: 1 | E40: 0 | F40: 1 | G40: 1 | H40: 'NA | I40: 1 | J40: 'NA | K40: 1 | L40: 1 | M40: 1 | N40: 1 | O40: Primary KC Alignment: The main calculation for 'how many months of utility bills can Mrs Tan pay' (120 ÷ (3/4 * 120)) actually reduces to multiplication/division of whole numbers, not division by a proper fraction (it's division by a whole number using a fraction as a rate). The other calculation (money left after 2 months) is a subtraction of amounts, not fractions. Synergy: The questions are not dependent on each other—each can be solved independently; the result of one question is not needed as input for the other. | P40: 7.747385
A41: TD | B41: Question 40 | C41: 0 | D41: 1 | E41: 0 | F41: 0 | G41: 1 | H41: 'NA | I41: 1 | J41: 'NA | K41: 0 | L41: 0 | M41: 1 | N41: 1 | O41: 2: The problem only requires multiplication by $[FORMULA]$ to find the amount received—which is fraction of a whole (multiplication), not division by a fraction, which is the intended primary KC. 3: The answer to part (b) asks for 'divided by $[FORMULA]$' but this is misaligned—the context should be multiplying by $[FORMULA]$ as per the scenario described (how much each child receives), and the amount given is then expressed as a decimal; the transition is muddled as stated. 7: The questions are not well-connected: (a) and (b) are not sequentially linked as the answer to (a) is used, but (b) is worded confusingly and seems unnecessary; (c) again is a new calculation. 8: The phrasing in (b) 'when this amount is divided by $[FORMULA]$' is mathematically and contextually incorrect, and misleading. 9: There is unnecessary complexity or confusion in part (b) as the requirement does not fit the realistic scenario and may confuse students about what operation should be used. | P41: 4.1812832
A42: TD | B42: Question 41 | C42: 0 | D42: 1 | E42: 1 | F42: 0 | G42: 1 | H42: 1 | I42: 1 | J42: 'NA | K42: 1 | L42: 1 | M42: 1 | N42: 1 | O42: Secondary KC Alignment: 0: The problem does not require adding whole numbers to find the answer; it only asks for the total household expenses based on the percentage relationship given by the electricity bill. The other amounts (groceries and transport) are not used to answer the question, so addition is unnecessary. Synergy: 0: Since only the percentage skill is needed to answer the question, Primary and Secondary KCs are not used in tandem. | P42: 2.201961
A43: TD | B43: Question 42 | C43: 0 | D43: 1 | E43: 1 | F43: 1 | G43: 1 | H43: 1 | I43: 1 | J43: 1 | K43: 1 | L43: 1 | M43: 1 | N43: 1 | P43: 1.2026854
A44: TD | B44: Question 43 | C44: 0 | D44: 1 | E44: 1 | F44: 1 | G44: 1 | H44: 1 | I44: 1 | J44: 1 | K44: 1 | L44: 1 | M44: 1 | N44: 1 | P44: 1.7678509
A45: TD | B45: Question 44 | C45: 0 | D45: 1 | E45: 1 | F45: 1 | G45: 1 | H45: 1 | I45: 1 | J45: 1 | K45: 1 | L45: 1 | M45: 1 | N45: 1 | P45: 1.2582591
A46: TD | B46: Question 45 | C46: 0 | D46: 1 | E46: 1 | F46: 1 | G46: 1 | H46: 1 | I46: 1 | J46: 1 | K46: 1 | L46: 1 | M46: 1 | N46: 1 | P46: 1.3381815
A47: TD | B47: Question 46 | C47: 0 | D47: 1 | E47: 1 | F47: 1 | G47: 1 | H47: 1 | I47: 1 | J47: 1 | K47: 1 | L47: 1 | M47: 1 | N47: 1 | P47: 1.6521966
A48: TD | B48: Question 47 | C48: 0 | D48: 1 | E48: 1 | F48: 1 | G48: 0 | H48: 1 | I48: 1 | J48: 1 | K48: 1 | L48: 1 | M48: 1 | N48: 1 | O48: 4: The problem is framed in a household finance context (cost of gas and meals cooked), but the main focus is on the proportional relationship and multiplication. While there is mention of the total cost, there is no broader financial planning, management of bills, or budgeting element as intended by the topic specification. The context is very limited to a purchase, not exploring other aspects of household finance. | P48: 1.8935645
A49: TD | B49: Question 48 | C49: 0 | D49: 1 | E49: 0 | F49: 1 | G49: 1 | H49: 'NA | I49: 1 | J49: 'NA | K49: 1 | L49: 1 | M49: 1 | N49: 1 | O49: Primary KC Alignment: The question asks for the Hadamard (element-wise) product rather than conventional matrix multiplication as typically defined in secondary O-level (which usually means row-by-column multiplication). Thus, while matrix multiplication is invoked, it does not require column-by-row or dot product, but merely element-wise multiplication. In Singapore O-level, 'matrix multiplication' conventionally means the dot-product type, not the Hadamard product. It doesn't fully assess the intended component as such. | P49: 2.866637
A50: TD | B50: Question 49 | C50: 0 | D50: 1 | E50: 1 | F50: 1 | G50: 1 | H50: 1 | I50: 1 | J50: 1 | K50: 1 | L50: 1 | M50: 1 | N50: 1 | P50: 1.8178911
A51: Minh | B51: Question 1 | C51: 0 | D51: 1 | E51: 1 | F51: 1 | G51: 1 | H51: 1 | I51: 1 | J51: 1 | K51: 1 | L51: 1 | M51: 1 | N51: 1 | P51: 1.8606434
A52: Minh | B52: Question 2 | C52: 0 | D52: 1 | E52: 1 | F52: 1 | G52: 1 | H52: 1 | I52: 1 | J52: 1 | K52: 1 | L52: 1 | M52: 1 | N52: 1 | P52: 1.9095199
A53: Minh | B53: Question 3 | C53: 0 | D53: 1 | E53: 1 | F53: 1 | G53: 1 | H53: 1 | I53: 1 | J53: 1 | K53: 1 | L53: 1 | M53: 1 | N53: 1 | P53: 1.076683
A54: Minh | B54: Question 4 | C54: 0 | D54: 1 | E54: 1 | F54: 1 | G54: 1 | H54: 1 | I54: 1 | J54: 1 | K54: 1 | L54: 1 | M54: 1 | N54: 1 | P54: 1.6358821
A55: Minh | B55: Question 5 | C55: 0 | D55: 1 | E55: 1 | F55: 1 | G55: 1 | H55: 1 | I55: 1 | J55: 1 | K55: 1 | L55: 1 | M55: 1 | N55: 1 | P55: 2.4038422
A56: Minh | B56: Question 6 | C56: 0 | D56: 1 | E56: 0 | F56: 1 | G56: 1 | H56: 'NA | I56: 1 | J56: 'NA | K56: 1 | L56: 1 | M56: 1 | N56: 1 | O56: Primary KC Alignment (0): The intended primary KC is 'dividing whole numbers up to 3 digits by 1 digit.' Here, the problem requires dividing 624 (3 digit) by 8 (1 digit), which is expected. However, Primary 3 curriculum usually restricts division to 2-digit by 1-digit, and 624 ÷ 8 may be too demanding despite alignment. If curriculum allows, assign 1; if strictly by level, assign 0. Synergy (0): The division is used to find the price of one chair, then multiplication is used to find the cost for 6. However, these do not work together in tandem (e.g. the answer to the first is entirely independent of the second step except as an input value, which is a basic two-step problem, not a synergy as described in the criteria—for strong synergy, intermediate answers must be required to solve the next part rather than each part being isolated). | P56: 4.1135814
A57: Minh | B57: Question 7 | C57: 0 | D57: 1 | E57: 1 | F57: 1 | G57: 1 | H57: 1 | I57: 1 | J57: 1 | K57: 1 | L57: 1 | M57: 1 | N57: 1 | P57: 3.144984
A58: Minh | B58: Question 8 | C58: 0 | D58: 1 | E58: 1 | F58: 1 | G58: 0 | H58: 1 | I58: 1 | J58: 1 | K58: 1 | L58: 1 | M58: 1 | N58: 1 | O58: D4. Topic Alignment: The problem is about spending pocket money on snacks and a storybook, which is better categorised as personal expenditure/spending by children, not the intended topic of household finance (such as income, utility bills, savings, etc.). It does not explicitly involve broader household financial concepts. | P58: 1.9146452
A59: Minh | B59: Question 9 | C59: 0 | D59: 1 | E59: 1 | F59: 1 | G59: 0 | H59: 1 | I59: 1 | J59: 1 | K59: 1 | L59: 1 | M59: 1 | N59: 1 | O59: 4: The context relates to purchasing soap but does not involve any elements of 'household finance' such as budgeting, prices, income, expenses, or monetary calculation. The problem is about counting objects (bars of soap), not finance. | P59: 1.907527
A60: Minh | B60: Question 10 | C60: 0 | D60: 1 | E60: 1 | F60: 1 | G60: 1 | H60: 1 | I60: 1 | J60: 1 | K60: 1 | L60: 1 | M60: 1 | N60: 1 | P60: 1.20994
A61: Minh | B61: Question 11 | C61: 0 | D61: 1 | E61: 0 | F61: 1 | G61: 1 | H61: 'NA | I61: 1 | J61: 'NA | K61: 1 | L61: 1 | M61: 1 | N61: 1 | O61: Primary KC alignment = 0: The division step in the problem is dividing the total (48) by 3, which is a 2-digit number by 1-digit, not up to 4 digits by 1 digit as specified in the intended KC. The problem remains within lower complexity than intended. | P61: 1.868814
A62: Minh | B62: Question 12 | C62: 0 | D62: 1 | E62: 1 | F62: 1 | G62: 1 | H62: 1 | I62: 1 | J62: 1 | K62: 1 | L62: 1 | M62: 1 | N62: 1 | P62: 2.5002391
A63: Minh | B63: Question 13 | C63: 0 | D63: 1 | E63: 1 | F63: 1 | G63: 1 | H63: 1 | I63: 1 | J63: 1 | K63: 1 | L63: 1 | M63: 1 | N63: 1 | P63: 1.4183264
A64: Minh | B64: Question 14 | C64: 0 | D64: 1 | E64: 1 | F64: 1 | G64: 1 | H64: 1 | I64: 1 | J64: 1 | K64: 1 | L64: 1 | M64: 1 | N64: 1 | P64: 1.2126257
A65: Minh | B65: Question 15 | C65: 0 | D65: 1 | E65: 1 | F65: 1 | G65: 1 | H65: 1 | I65: 1 | J65: 1 | K65: 1 | L65: 1 | M65: 1 | N65: 1 | P65: 2.0729246
A66: Minh | B66: Question 16 | C66: 0 | D66: 1 | E66: 0 | F66: 1 | G66: 1 | H66: 'NA | I66: 1 | J66: 'NA | K66: 1 | L66: 1 | M66: 1 | N66: 1 | O66: Primary KC Alignment = 0: The main concept required to solve this problem is addition of decimals first, then subtraction, meaning addition is primary and subtraction is secondary in the solving process. To align to the intended Primary KC (subtraction of decimals), subtraction must be the central required step (e.g., direct calculation of difference), not addition. Thus, the ordering of KCs is reversed here. | P66: 2.1409945
A67: Minh | B67: Question 17 | C67: 0 | D67: 1 | E67: 1 | F67: 1 | G67: 1 | H67: 1 | I67: 1 | J67: 1 | K67: 1 | L67: 1 | M67: 1 | N67: 1 | P67: 1.7613444
A68: Minh | B68: Question 18 | C68: 0 | D68: 1 | E68: 1 | F68: 1 | G68: 1 | H68: 1 | I68: 1 | J68: 1 | K68: 1 | L68: 1 | M68: 1 | N68: 1 | P68: 1.2793024
A69: Minh | B69: Question 19 | C69: 0 | D69: 1 | E69: 1 | F69: 1 | G69: 1 | H69: 1 | I69: 1 | J69: 1 | K69: 1 | L69: 1 | M69: 1 | N69: 1 | P69: 2.3288519
A70: Minh | B70: Question 20 | C70: 0 | D70: 1 | E70: 1 | F70: 1 | G70: 1 | H70: 1 | I70: 1 | J70: 1 | K70: 1 | L70: 1 | M70: 1 | N70: 1 | P70: 2.6685188
A71: Minh | B71: Question 21 | C71: 0 | D71: 1 | E71: 1 | F71: 1 | G71: 1 | H71: 1 | I71: 1 | J71: 1 | K71: 1 | L71: 1 | M71: 1 | N71: 1 | P71: 1.7873244
A72: Minh | B72: Question 22 | C72: 0 | D72: 1 | E72: 1 | F72: 1 | G72: 1 | H72: 1 | I72: 1 | J72: 1 | K72: 1 | L72: 1 | M72: 1 | N72: 1 | P72: 1.3305023
A73: Minh | B73: Question 23 | C73: 0 | D73: 1 | E73: 1 | F73: 1 | G73: 1 | H73: 1 | I73: 1 | J73: 1 | K73: 1 | L73: 1 | M73: 1 | N73: 1 | P73: 1.1838202
A74: Minh | B74: Question 24 | C74: 0 | D74: 1 | E74: 0 | F74: 0 | G74: 1 | H74: 'NA | I74: 1 | J74: 'NA | K74: 1 | L74: 1 | M74: 1 | N74: 1 | O74: Primary KC Alignment: 0 - The problem only requires multiplying a whole number (12) by a mixed number (2 1/2), suitable for Primary 5, but the intended KC is to multiply a mixed number BY a whole number, not a whole number BY a mixed number. The focus is not clearly on the intended KC but more on a straightforward calculation. Secondary KC Alignment: 0 - The problem asks to compare two payment options, but both are whole numbers ($30 vs $32.50). No fraction comparison or ordering is required at any point, which was the intended KC. Synergy: 0 - The use of multiplication and comparison are not synergistic. The comparison step only involves whole numbers, and the fraction multiplication does not feed meaningfully into a fraction comparison or ordering step. | P74: 3.1314161
A75: Minh | B75: Question 25 | C75: 0 | D75: 1 | E75: 1 | F75: 1 | G75: 1 | H75: 1 | I75: 1 | J75: 1 | K75: 1 | L75: 1 | M75: 1 | N75: 1 | P75: 1.1726415
A76: Minh | B76: Question 26 | C76: 0 | D76: 1 | E76: 1 | F76: 1 | G76: 0 | H76: 1 | I76: 1 | J76: 1 | K76: 1 | L76: 1 | M76: 1 | N76: 1 | O76: D-Topic Alignment: The scenario deals with purchasing rice, but does not connect to 'household finance' such as income, utility bills, money, interest, savings, instalment, mortgage, financial planning, etc. It is about quantity/weight, not a direct financial context. | P76: 1.8821647
A77: Minh | B77: Question 27 | C77: 0 | D77: 1 | E77: 0 | F77: 1 | G77: 1 | H77: 'NA | I77: 1 | J77: 'NA | K77: 1 | L77: 1 | M77: 1 | N77: 1 | O77: Primary KC Alignment: The multiplication required is multiplying 132.768 by 0.183, which is not multiplying decimals by 10, 100, 1000 or their multiples, but rather multiplying by another decimal. The primary KC specifically targets multiplying by 10/100/1000/multiples, so this problem does not fully require that. | P77: 1.9344766
A78: Minh | B78: Question 28 | C78: 0 | D78: 1 | E78: 1 | F78: 1 | G78: 1 | H78: 1 | I78: 1 | J78: 1 | K78: 1 | L78: 1 | M78: 0 | N78: 1 | O78: language_quality: The dollar amount should not be written as $187.250, as standard financial notation uses up to 2 decimal places. It should be written as $187.25. | P78: 1.7196867
A79: Minh | B79: Question 29 | C79: 0 | D79: 1 | E79: 1 | F79: 1 | G79: 1 | H79: 1 | I79: 1 | J79: 1 | K79: 1 | L79: 1 | M79: 1 | N79: 1 | P79: 1.397505
A80: Minh | B80: Question 30 | C80: 0 | D80: 1 | E80: 1 | F80: 1 | G80: 1 | H80: 1 | I80: 1 | J80: 1 | K80: 1 | L80: 1 | M80: 1 | N80: 1 | P80: 1.8319795
A81: Minh | B81: Question 31 | C81: 0 | D81: 1 | E81: 1 | F81: 1 | G81: 1 | H81: 1 | I81: 1 | J81: 1 | K81: 1 | L81: 1 | M81: 1 | N81: 1 | P81: 1.5869462
A82: Minh | B82: Question 32 | C82: 0 | D82: 1 | E82: 1 | F82: 1 | G82: 1 | H82: 1 | I82: 1 | J82: 1 | K82: 1 | L82: 1 | M82: 1 | N82: 1 | P82: 1.1945879
A83: Minh | B83: Question 33 | C83: 0 | D83: 1 | E83: 1 | F83: 1 | G83: 0 | H83: 1 | I83: 1 | J83: 1 | K83: 1 | L83: 1 | M83: 1 | N83: 1 | O83: 4: The context of the word problem is sharing cake among children for a family gathering, which does not relate to household finance concepts such as income, utility bills, money, interest, savings, instalment, mortgage, or financial planning. | P83: 1.643055
A84: Minh | B84: Question 34 | C84: 0 | D84: 1 | E84: 1 | F84: 1 | G84: 1 | H84: 1 | I84: 1 | J84: 1 | K84: 1 | L84: 1 | M84: 1 | N84: 1 | P84: 1.2951145
A85: Minh | B85: Question 35 | C85: 0 | D85: 1 | E85: 1 | F85: 1 | G85: 0 | H85: 1 | I85: 1 | J85: 1 | K85: 1 | L85: 1 | M85: 1 | N85: 1 | O85: 4: The scenario is about repacking laundry detergent, a household activity, but does not relate to finance or any explicit aspect of the stated topic. There is no mention of money, costs, savings, or financial decision-making. | P85: 1.6464527
A86: Minh | B86: Question 36 | C86: 0 | D86: 1 | E86: 1 | F86: 0 | G86: 1 | H86: 1 | I86: 1 | J86: 'NA | K86: 1 | L86: 1 | M86: 1 | N86: 1 | O86: 3: Subtraction of whole numbers is not necessary to solve this problem. The problem only requires the use of percentage to find the whole from a part and its percentage. 7: The two knowledge components do not need to be used together; only the percentage knowledge is required to solve for the total. | P86: 1.9475782
A87: Minh | B87: Question 37 | C87: 0 | D87: 1 | E87: 1 | F87: 1 | G87: 1 | H87: 1 | I87: 1 | J87: 1 | K87: 1 | L87: 1 | M87: 1 | N87: 1 | P87: 1.1854601
A88: Minh | B88: Question 38 | C88: 0 | D88: 1 | E88: 1 | F88: 1 | G88: 1 | H88: 1 | I88: 1 | J88: 1 | K88: 1 | L88: 1 | M88: 1 | N88: 1 | P88: 1.3336837
A89: Minh | B89: Question 39 | C89: 0 | D89: 1 | E89: 1 | F89: 1 | G89: 1 | H89: 1 | I89: 1 | J89: 1 | K89: 1 | L89: 1 | M89: 1 | N89: 1 | P89: 1.1515923
A90: Minh | B90: Question 40 | C90: 0 | D90: 1 | E90: 1 | F90: 1 | G90: 1 | H90: 1 | I90: 1 | J90: 1 | K90: 1 | L90: 1 | M90: 1 | N90: 1 | P90: 1.2188499
A91: Minh | B91: Question 41 | C91: 0 | D91: 1 | E91: 1 | F91: 1 | G91: 1 | H91: 1 | I91: 1 | J91: 1 | K91: 1 | L91: 1 | M91: 1 | N91: 1 | P91: 1.7817936
A92: Minh | B92: Question 42 | C92: 0 | D92: 1 | E92: 1 | F92: 1 | G92: 1 | H92: 1 | I92: 1 | J92: 1 | K92: 1 | L92: 1 | M92: 1 | N92: 1 | P92: 1.5304925
A93: Minh | B93: Question 43 | C93: 0 | D93: 1 | E93: 1 | F93: 1 | G93: 1 | H93: 1 | I93: 1 | J93: 1 | K93: 1 | L93: 1 | M93: 1 | N93: 1 | P93: 1.133996
A94: Minh | B94: Question 44 | C94: 0 | D94: 1 | E94: 1 | F94: 1 | G94: 1 | H94: 1 | I94: 1 | J94: 1 | K94: 1 | L94: 1 | M94: 1 | N94: 1 | P94: 1.2808266
A95: Minh | B95: Question 45 | C95: 0 | D95: 1 | E95: 1 | F95: 1 | G95: 1 | H95: 1 | I95: 1 | J95: 1 | K95: 1 | L95: 1 | M95: 1 | N95: 1 | P95: 1.4850929
A96: Minh | B96: Question 46 | C96: 0 | D96: 1 | E96: 1 | F96: 1 | G96: 1 | H96: 1 | I96: 1 | J96: 1 | K96: 1 | L96: 1 | M96: 1 | N96: 1 | P96: 2.970247
A97: Minh | B97: Question 47 | C97: 0 | D97: 1 | E97: 1 | F97: 1 | G97: 1 | H97: 1 | I97: 1 | J97: 1 | K97: 1 | L97: 1 | M97: 1 | N97: 1 | P97: 1.518985
A98: Minh | B98: Question 48 | C98: 0 | D98: 1 | E98: 1 | F98: 1 | G98: 1 | H98: 1 | I98: 1 | J98: 1 | K98: 1 | L98: 1 | M98: 1 | N98: 1 | P98: 1.0999782
... A103: Minh | B103: Question 53 | C103: 0 | D103: 1 | E103: 1 | F103: 1 | G103: 1 | H103: 1 | I103: 1 | J103: 1 | K103: 1 | L103: 1 | M103: 1 | N103: 1 | P103: 1.1372139
A104: Minh | B104: Question 54 | C104: 0 | D104: 1 | E104: 1 | F104: 1 | G104: 1 | H104: 1 | I104: 1 | J104: 0 | K104: 1 | L104: 1 | M104: 1 | N104: 1 | O104: synergy=0: The two parts (a) and (b) are independent; the answer to (a) is not required to solve (b), and vice versa. For full synergy, the tasks should more directly depend on each other. | P104: 2.7263637
...

Sheet householdfinance_v4_5
A1: Evaluator | B1: Question | C1: status | D1: answerability | E1: primary_kc_alignment | F1: secondary_kc_alignment | G1: topic_alignment | H1: grade_alignment | I1: real_world_feasibility | J1: synergy | K1: clarity | L1: conciseness_and_relevance | M1: language_quality | N1: content_appropriateness | O1: explanation | P1: response_time | Q1: language_quality1
A2: TD | B2: Question 1 | C2: 0 | D2: 1 | E2: 1 | F2: 1 | G2: 1 | H2: 1 | I2: 1 | J2: 1 | K2: 1 | L2: 1 | M2: 1 | N2: 1 | P2: 1.1985626
A3: TD | B3: Question 2 | C3: 0 | D3: 1 | E3: 1 | F3: 0 | G3: 1 | H3: 1 | I3: 1 | J3: 'NA | K3: 1 | L3: 1 | M3: 1 | N3: 1 | O3: 3: The solution only requires subtraction (450-215) to find the amount spent before receiving the extra money. The intended secondary knowledge component, addition, is not necessary for this problem. 7: There is no need to combine subtraction and addition in tandem, as the question focuses solely on the spending before the new amount was added. | P3: 8.184953
A4: TD | B4: Question 3 | C4: 0 | D4: 1 | E4: 1 | F4: 1 | G4: 0 | H4: 1 | I4: 1 | J4: 1 | K4: 1 | L4: 1 | M4: 1 | N4: 1 | O4: 4- The context is about sharing candies among children, not a household finance scenario such as money, bills, or planning. While it is set in a household, it does not fit the intended topic of 'household finance' as defined in the examples. | P4: 3.5693607
A5: TD | B5: Question 4 | C5: 0 | D5: 1 | E5: 1 | F5: 1 | G5: 1 | H5: 1 | I5: 1 | J5: 1 | K5: 1 | L5: 1 | M5: 1 | N5: 1 | P5: 1.1780415
A6: TD | B6: Question 5 | C6: 0 | D6: 1 | E6: 1 | F6: 1 | G6: 1 | H6: 1 | I6: 1 | J6: 1 | K6: 1 | L6: 1 | M6: 1 | N6: 1 | P6: 1.191191
A7: TD | B7: Question 6 | C7: 0 | D7: 1 | E7: 1 | F7: 1 | G7: 1 | H7: 1 | I7: 1 | J7: 1 | K7: 1 | L7: 1 | M7: 1 | N7: 1 | P7: 1.4485931
A8: TD | B8: Question 7 | C8: 0 | D8: 1 | E8: 1 | F8: 1 | G8: 0 | H8: 1 | I8: 1 | J8: 1 | K8: 1 | L8: 1 | M8: 1 | N8: 1 | O8: 4- The context of buying light bulbs for a new house does not specifically fall under the specified household finance topics such as income, utility bills, money, interest, savings, instalment, mortgage, or financial planning. It is more related to purchasing goods rather than explicit finance topics. | P8: 4.9530828
A9: TD | B9: Question 8 | C9: 0 | D9: 1 | E9: 1 | F9: 1 | G9: 1 | H9: 1 | I9: 1 | J9: 1 | K9: 1 | L9: 1 | M9: 1 | N9: 1 | P9: 1.5795407
A10: TD | B10: Question 9 | C10: 0 | D10: 1 | E10: 1 | F10: 0 | G10: 1 | H10: 1 | I10: 1 | J10: 'NA | K10: 1 | L10: 1 | M10: 1 | N10: 1 | O10: Secondary KC Alignment=0: The problem can be solved directly by division (3872-320=3552, then 3552 divided by 4 is not required; rather, the way it's structured currently, the 320 leftover makes the correct process division first, then check the remainder, but only division is necessary as posed. Synergy=0: Subtraction is not required for the solution; the question only asks how much each child received, making only division needed. | P10: 2.5088558
A11: TD | B11: Question 10 | C11: 0 | D11: 1 | E11: 1 | F11: 1 | G11: 1 | H11: 1 | I11: 1 | J11: 1 | K11: 1 | L11: 1 | M11: 1 | N11: 1 | P11: 1.5113101
A12: TD | B12: Question 11 | C12: 0 | D12: 1 | E12: 1 | F12: 1 | G12: 1 | H12: 1 | I12: 1 | J12: 1 | K12: 1 | L12: 1 | M12: 1 | N12: 1 | P12: 1.6401429
A13: TD | B13: Question 12 | C13: 0 | D13: 1 | E13: 1 | F13: 1 | G13: 1 | H13: 1 | I13: 1 | J13: 1 | K13: 1 | L13: 1 | M13: 1 | N13: 1 | P13: 2.8631728
A14: TD | B14: Question 13 | C14: 0 | D14: 1 | E14: 0 | F14: 1 | G14: 1 | H14: 'NA | I14: 0 | J14: 'NA | K14: 1 | L14: 1 | M14: 1 | N14: 1 | O14: Primary KC Alignment: The second bill in part (b) uses 3 decimal places ($45.605), but the addition in (a) is only up to 2 decimal places, which matches the KC. However, (b) asks for comparison between 2- and 3-decimal numbers, focusing more on secondary KC. Part (a) could be done at lower skill. / Grade Alignment: Primary 4 students in Singapore typically deal with decimals only up to 2 decimal places, especially around money. The use of $45.605 is not grade-appropriate. / Real-World Feasibility: Household utility bills do not reasonably have 3 decimal places in currency; bills are always given to 2 decimal places for cents. / Synergy: The parts are independent; solving (a) does not help (b), which instead simply compares June's 2-decimal electricity bill with July's improper 3-decimal one. | P14: 3.5787127
A15: TD | B15: Question 14 | C15: 0 | D15: 1 | E15: 1 | F15: 1 | G15: 1 | H15: 1 | I15: 1 | J15: 1 | K15: 1 | L15: 1 | M15: 1 | N15: 1 | P15: 2.0902917
A16: TD | B16: Question 15 | C16: 0 | D16: 1 | E16: 1 | F16: 1 | G16: 1 | H16: 1 | I16: 1 | J16: 1 | K16: 1 | L16: 1 | M16: 1 | N16: 1 | P16: 1.583555
A17: TD | B17: Question 16 | C17: 0 | D17: 1 | E17: 1 | F17: 1 | G17: 1 | H17: 1 | I17: 1 | J17: 1 | K17: 1 | L17: 1 | M17: 1 | N17: 1 | P17: 1.4827096
A18: TD | B18: Question 17 | C18: 0 | D18: 1 | E18: 1 | F18: 1 | G18: 1 | H18: 1 | I18: 1 | J18: 1 | K18: 1 | L18: 1 | M18: 1 | N18: 1 | P18: 1.6765738
A19: TD | B19: Question 18 | C19: 0 | D19: 1 | E19: 1 | F19: 1 | G19: 1 | H19: 1 | I19: 1 | J19: 1 | K19: 1 | L19: 1 | M19: 1 | N19: 1 | P19: 2.2481956
A20: TD | B20: Question 19 | C20: 0 | D20: 1 | E20: 1 | F20: 1 | G20: 1 | H20: 1 | I20: 1 | J20: 1 | K20: 1 | L20: 1 | M20: 1 | N20: 1 | P20: 1.2345066
A21: TD | B21: Question 20 | C21: 0 | D21: 1 | E21: 1 | F21: 1 | G21: 1 | H21: 1 | I21: 1 | J21: 1 | K21: 1 | L21: 1 | M21: 0 | N21: 1 | O21: Language Quality: The amounts stated as '$1[FORMULA]$ of her budget' and '$2[FORMULA]$ of her budget' suggest that Mrs Tan spent more than her whole budget, which is not typical phrasing and could confuse students. Normally, fractions of a whole (i.e., less than 1) are expected for budget allocation. This distracts from proper interpretation and standard English phrasing. The wording should say, for example, 'She spent $[FORMULA]$ of her budget on groceries.' | P21: 3.9077153
A22: TD | B22: Question 21 | C22: 0 | D22: 1 | E22: 1 | F22: 1 | G22: 1 | H22: 1 | I22: 1 | J22: 1 | K22: 1 | L22: 1 | M22: 1 | N22: 1 | P22: 1.5684471
A23: TD | B23: Question 22 | C23: 0 | D23: 1 | E23: 1 | F23: 0 | G23: 1 | H23: 1 | I23: 1 | J23: 'NA | K23: 1 | L23: 1 | M23: 1 | N23: 1 | O23: secondary_kc_alignment: The comparison required is between Mrs Lim's savings (which is a whole number after multiplication) and $90, not between two fractions. Thus, comparing and ordering fractions is not strictly required. synergy: Only the multiplication of a fraction and a whole number is necessary; the answer is a whole number, and no fraction-to-fraction or combined-step comparison is actually performed. | P23: 2.0272243
A24: TD | B24: Question 23 | C24: 0 | D24: 1 | E24: 1 | F24: 1 | G24: 1 | H24: 1 | I24: 1 | J24: 1 | K24: 1 | L24: 1 | M24: 1 | N24: 1 | P24: 1.1869655
A25: TD | B25: Question 24 | C25: 0 | D25: 1 | E25: 1 | F25: 0 | G25: 1 | H25: 1 | I25: 1 | J25: 'NA | K25: 1 | L25: 1 | M25: 1 | N25: 1 | O25: Secondary KC Alignment (3): The solution only requires multiplying fractions repeatedly to find what is left at each stage and finally a fraction of the remainder. There is no need for addition of fractions, as all steps are subtraction and multiplication. Synergy (7): The problem does not truly require the interaction of both the KC components. Only the primary (multiplication of fractions) is genuinely needed. | P25: 2.5446959
A26: TD | B26: Question 25 | C26: 0 | D26: 1 | E26: 1 | F26: 1 | G26: 1 | H26: 1 | I26: 1 | J26: 1 | K26: 1 | L26: 1 | M26: 1 | N26: 1 | P26: 1.2667615
A27: TD | B27: Question 26 | C27: 0 | D27: 1 | E27: 0 | F27: 0 | G27: 0 | H27: 'NA | I27: 1 | J27: 'NA | K27: 1 | L27: 1 | M27: 1 | N27: 1 | O27: Primary KC Alignment: The main calculation steps require multiplying a whole number by an improper fraction (e.g., 3 x 9/4), not multiplying two improper fractions as the intended component specifies. Secondary KC Alignment: The question requires subtraction, not explicit addition of fractions. Topic Alignment: The context is not about household finance but rather about food consumption at a gathering (fruit juice). | P27: 3.1619444
A28: TD | B28: Question 27 | C28: 0 | D28: 0 | E28: 'NA | F28: 'NA | G28: 'NA | H28: 'NA | I28: 'NA | J28: 'NA | K28: 'NA | L28: 'NA | M28: 1 | N28: 'NA | O28: A1+: The fractions \([FORMULA]\) and \([FORMULA]\) exceed 1, meaning Mrs Tan is spending more than her total savings on utilities and groceries, which is illogical. There is not enough money to allocate, so the question cannot be solved. B2+: Multiplying improper fractions by the total savings does not make sense when the numerators are larger than denominators; it is not an intended or logical P5 application, so the question does not properly target multiplying two improper fractions. D5+: For Primary 5, it is not appropriate to use improper fractions as allocation amounts that are more than the whole, and such context does not suit the level. F6+: It is not realistic for someone to spend more than their total savings on these expenses. | P28: 3.1022379 | Q28: 'NA
A29: TD | B29: Question 28 | C29: 0 | D29: 1 | E29: 1 | F29: 1 | G29: 1 | H29: 1 | I29: 1 | J29: 1 | K29: 1 | L29: 1 | M29: 1 | N29: 1 | P29: 1.2000406
A30: TD | B30: Question 29 | C30: 0 | D30: 1 | E30: 1 | F30: 1 | G30: 0 | H30: 1 | I30: 1 | J30: 1 | K30: 1 | L30: 1 | M30: 1 | N30: 1 | O30: D4(-) The scenario is about baking and ingredient usage, but does not involve the intended topic of "Household finance" such as money, bills, savings, planning, etc. | P30: 3.0982623
A31: TD | B31: Question 30 | C31: 0 | D31: 1 | E31: 1 | F31: 1 | G31: 1 | H31: 1 | I31: 1 | J31: 1 | K31: 1 | L31: 1 | M31: 1 | N31: 1 | P31: 1.6406233
A32: TD | B32: Question 31 | C32: 0 | D32: 0 | E32: 'NA | F32: 'NA | G32: 'NA | H32: 'NA | I32: 'NA | J32: 'NA | K32: 'NA | L32: 'NA | M32: 1 | N32: 'NA | O32: answerability: There is a logical error. The problem says Mr Lim needs to 'subtract' the service fee from his cost calculation, but service fees are meant to be 'added'. This creates a conflict: if the intent is to add, but the question says subtract, it is not answerable as stated. primary_kc_alignment: The multiplication required is 73.245 × 0.15, which is not multiplying by 10, 100, 1000, or a multiple – it is multiplying by 0.15, not as per the intended KC. synergy: The subtraction (or rather, addition if correct) of the service fee is not logically necessary as a step after the multiplication, since the operation does not depend on the multiplication result's use in a specific way; also, the logical misstatement concerning 'subtracting' diminishes meaningful synergy. | P32: 3.1032391 | Q32: 'NA
A33: TD | B33: Question 32 | C33: 0 | D33: 1 | E33: 1 | F33: 1 | G33: 1 | H33: 1 | I33: 1 | J33: 1 | K33: 1 | L33: 1 | M33: 1 | N33: 1 | P33: 1.6171067
A34: TD | B34: Question 33 | C34: 0 | D34: 1 | E34: 1 | F34: 1 | G34: 1 | H34: 1 | I34: 1 | J34: 1 | K34: 1 | L34: 1 | M34: 1 | N34: 1 | P34: 5.7010026
A35: TD | B35: Question 34 | C35: 0 | D35: 1 | E35: 1 | F35: 1 | G35: 1 | H35: 1 | I35: 1 | J35: 1 | K35: 1 | L35: 1 | M35: 1 | N35: 1 | P35: 1.3015864
A36: TD | B36: Question 35 | C36: 0 | D36: 1 | E36: 1 | F36: 1 | G36: 1 | H36: 1 | I36: 1 | J36: 1 | K36: 1 | L36: 1 | M36: 1 | N36: 1 | P36: 1.390831
A37: TD | B37: Question 36 | C37: 0 | D37: 1 | E37: 1 | F37: 1 | G37: 1 | H37: 1 | I37: 1 | J37: 1 | K37: 1 | L37: 1 | M37: 1 | N37: 1 | P37: 1.1579452
A38: TD | B38: Question 37 | C38: 0 | D38: 1 | E38: 1 | F38: 1 | G38: 1 | H38: 1 | I38: 1 | J38: 1 | K38: 1 | L38: 1 | M38: 1 | N38: 1 | P38: 1.8534341
A39: TD | B39: Question 38 | C39: 0 | D39: 1 | E39: 0 | F39: 1 | G39: 0 | H39: 'NA | I39: 1 | J39: 'NA | K39: 1 | L39: 1 | M39: 1 | N39: 1 | O39: Primary KC Alignment (0): The problem involves dividing a mixed number (not a proper fraction) by a whole number, while the required KC is specifically dividing a proper fraction by a whole number. Topic Alignment (0): The problem is about distributing cookies (food), not household finance topics related to income, bills, or financial planning. | P39: 2.5971489
A40: TD | B40: Question 39 | C40: 0 | D40: 1 | E40: 0 | F40: 0 | G40: 1 | H40: 'NA | I40: 1 | J40: 'NA | K40: 1 | L40: 1 | M40: 1 | N40: 1 | O40: Primary KC Alignment: The word problem requires dividing $120 by (3/4)[FORMULA]120$ to get number of months, which is not dividing by a fraction, but dividing a whole number by another whole number. The main skill required is not dividing by a fraction, but rather multiplying by 3/4. Secondary KC Alignment: The word problem asks for subtraction of whole numbers/money, not fractions. Synergy: Both knowledge components are not required in tandem; the questions can be answered independently using simple arithmetic, not specifically dividing by fractions or subtracting fractions. | P40: 2.4320846
A41: TD | B41: Question 40 | C41: 0 | D41: 1 | E41: 0 | F41: 1 | G41: 1 | H41: 'NA | I41: 1 | J41: 'NA | K41: 1 | L41: 1 | M41: 1 | N41: 1 | O41: Primary KC Alignment: (a) and (c) use fraction multiplication, and (b) incorrectly asks for 'divided by $3/4$' (should be 'multiplied by $3/4$', or clearer wording). The intended KC is 'division by a fraction', but the actual calculation uses multiplication by a fraction, which is conceptually not the same. Synergy: The parts are not truly synergistic. (a) and (b) both derive from the same base amount but do not require results from one question to solve the next. (b) should refer clearly to part (a)'s answer as the amount to act on. | P41: 2.7715933
A42: TD | B42: Question 41 | C42: 0 | D42: 1 | E42: 1 | F42: 0 | G42: 1 | H42: 1 | I42: 1 | J42: 'NA | K42: 1 | L42: 1 | M42: 1 | N42: 1 | O42: C3: To solve the problem, it is only necessary to use percentage to find the total household expenses. The information about groceries and transport does not need to be added to solve the question, so addition of whole numbers is not required. C7: The two knowledge components are not used in tandem; either one is sufficient to solve, making them not synergistic. | P42: 3.071981
A43: TD | B43: Question 42 | C43: 0 | D43: 1 | E43: 1 | F43: 1 | G43: 1 | H43: 1 | I43: 1 | J43: 1 | K43: 1 | L43: 1 | M43: 1 | N43: 1 | P43: 1.5468595
A44: TD | B44: Question 43 | C44: 0 | D44: 1 | E44: 1 | F44: 1 | G44: 1 | H44: 1 | I44: 1 | J44: 1 | K44: 1 | L44: 1 | M44: 1 | N44: 1 | P44: 1.8396201
A45: TD | B45: Question 44 | C45: 0 | D45: 1 | E45: 1 | F45: 1 | G45: 1 | H45: 1 | I45: 1 | J45: 1 | K45: 1 | L45: 1 | M45: 1 | N45: 1 | P45: 1.9395127
A46: TD | B46: Question 45 | C46: 0 | D46: 1 | E46: 1 | F46: 1 | G46: 1 | H46: 1 | I46: 1 | J46: 1 | K46: 1 | L46: 1 | M46: 1 | N46: 1 | P46: 1.1042655
A47: TD | B47: Question 46 | C47: 0 | D47: 1 | E47: 1 | F47: 1 | G47: 1 | H47: 1 | I47: 1 | J47: 1 | K47: 1 | L47: 1 | M47: 1 | N47: 1 | P47: 1.1378403
A48: TD | B48: Question 47 | C48: 0 | D48: 1 | E48: 1 | F48: 1 | G48: 1 | H48: 1 | I48: 1 | J48: 1 | K48: 1 | L48: 1 | M48: 1 | N48: 1 | P48: 1.8708396
A49: TD | B49: Question 48 | C49: 0 | D49: 1 | E49: 0 | F49: 1 | G49: 1 | H49: 'NA | I49: 1 | J49: 'NA | K49: 1 | L49: 1 | M49: 1 | N49: 1 | O49: Primary KC Alignment: The problem requires the element-wise (Hadamard) product of matrices, not standard matrix multiplication, which is the expectation for the intended knowledge component of 'multiplication of matrices.' In the Singapore O-level mathematics syllabus, 'multiplication of matrices' refers to standard matrix multiplication (dot product), not element-wise multiplication. | P49: 2.9408238
A50: TD | B50: Question 49 | C50: 0 | D50: 1 | E50: 1 | F50: 1 | G50: 1 | H50: 1 | I50: 1 | J50: 1 | K50: 1 | L50: 1 | M50: 1 | N50: 1 | P50: 1.4536819
A51: Minh | B51: Question 1 | C51: 0 | D51: 1 | E51: 1 | F51: 1 | G51: 1 | H51: 1 | I51: 1 | J51: 1 | K51: 1 | L51: 1 | M51: 1 | N51: 1 | P51: 1.2480569
A52: Minh | B52: Question 2 | C52: 0 | D52: 1 | E52: 1 | F52: 1 | G52: 1 | H52: 1 | I52: 1 | J52: 1 | K52: 1 | L52: 1 | M52: 1 | N52: 1 | P52: 1.7110021
A53: Minh | B53: Question 3 | C53: 0 | D53: 1 | E53: 1 | F53: 1 | G53: 0 | H53: 1 | I53: 1 | J53: 1 | K53: 1 | L53: 1 | M53: 1 | N53: 1 | O53: 4: The context is about buying apples for neighbours, which is not directly relevant to household finance topics such as income, utility bills, money management, interest, or financial planning. The scenario is more related to a purchasing activity and sharing, not financial concepts. | P53: 1.7430613
A54: Minh | B54: Question 4 | C54: 0 | D54: 1 | E54: 1 | F54: 1 | G54: 1 | H54: 1 | I54: 1 | J54: 1 | K54: 1 | L54: 1 | M54: 1 | N54: 1 | P54: 1.6352966
A55: Minh | B55: Question 5 | C55: 0 | D55: 1 | E55: 1 | F55: 1 | G55: 1 | H55: 1 | I55: 1 | J55: 1 | K55: 1 | L55: 1 | M55: 1 | N55: 1 | P55: 1.2387507
A56: Minh | B56: Question 6 | C56: 0 | D56: 1 | E56: 0 | F56: 1 | G56: 1 | H56: 'NA | I56: 1 | J56: 'NA | K56: 1 | L56: 1 | M56: 1 | N56: 1 | O56: Primary KC Alignment = 0: The division required here is 624 divided by 8, which involves dividing a 3-digit number by a 1-digit number. However, based on the Singapore Primary 3 syllabus, students are typically expected to divide up to 3-digit numbers by 1-digit numbers only if the quotient results in a whole number and is within the scope of their learning. Here, 624 ÷ 8 = 78, which fits the requirement. However, the problem does not explicitly demand division skills as the main step; instead, students may be able to use repeated subtraction or multiplication (guess and check) if they try. The crux here is that it's not strictly necessary to demonstrate the division algorithm, compromising the intent.Synergy = 0: The operations (division to find 1 chair's price, multiplication to find total cost for 6 chairs) are present sequentially, but the synergy is weak: division gives a standalone answer, and multiplication is then applied, but the problem could be solved by setting up an equation directly (e.g., 624/8 × 6). The requirement that the result of one operation is a necessary input for the next, with both KCs essential, is not strongly enforced here. | P56: 4.1370251
A57: Minh | B57: Question 7 | C57: 0 | D57: 1 | E57: 1 | F57: 1 | G57: 1 | H57: 1 | I57: 1 | J57: 1 | K57: 1 | L57: 1 | M57: 1 | N57: 1 | P57: 1.692873
A58: Minh | B58: Question 8 | C58: 0 | D58: 1 | E58: 1 | F58: 1 | G58: 0 | H58: 1 | I58: 1 | J58: 1 | K58: 1 | L58: 1 | M58: 1 | N58: 1 | O58: D- The context of the problem is buying snacks and a storybook, which relates to personal spending but does not sufficiently fall under the strict scope of 'household finance' (e.g., income, bills, savings, financial planning). | P58: 1.7850695
A59: Minh | B59: Question 9 | C59: 0 | D59: 1 | E59: 1 | F59: 1 | G59: 0 | H59: 1 | I59: 1 | J59: 1 | K59: 1 | L59: 1 | M59: 1 | N59: 1 | O59: 4: The context is about buying soap in boxes and bags, which is relevant to shopping but does not involve any household finance concepts such as income, bills, savings or planning. The problem is about counting items (soap bars) rather than any finance-related topic. | P59: 1.710722
A60: Minh | B60: Question 10 | C60: 0 | D60: 1 | E60: 1 | F60: 1 | G60: 1 | H60: 1 | I60: 1 | J60: 1 | K60: 1 | L60: 1 | M60: 1 | N60: 1 | P60: 1.2419143
A61: Minh | B61: Question 11 | C61: 0 | D61: 1 | E61: 1 | F61: 1 | G61: 1 | H61: 1 | I61: 1 | J61: 1 | K61: 1 | L61: 1 | M61: 1 | N61: 1 | P61: 1.6234894
A62: Minh | B62: Question 12 | C62: 0 | D62: 0 | E62: 'NA | F62: 'NA | G62: 'NA | H62: 'NA | I62: 'NA | J62: 'NA | K62: 'NA | L62: 'NA | M62: 1 | N62: 'NA | O62: A+ The problem cannot be answered as written: the total monthly expenses of Mrs Lim is not given, and the amounts in dollars provided are not needed or relevant to the main calculation, since they are not required for adding the given fractions. The question should indicate whether to add the given fractions (5/12 + 1/6), or to calculate based on the dollar values (120+80 over total), but as worded, the question is incomplete and confusing. | P62: 4.4535751 | Q62: 'NA
A63: Minh | B63: Question 13 | C63: 0 | D63: 1 | E63: 1 | F63: 1 | G63: 1 | H63: 1 | I63: 1 | J63: 1 | K63: 1 | L63: 1 | M63: 1 | N63: 1 | P63: 2.8139217
A64: Minh | B64: Question 14 | C64: 0 | D64: 1 | E64: 1 | F64: 1 | G64: 1 | H64: 1 | I64: 1 | J64: 1 | K64: 1 | L64: 1 | M64: 1 | N64: 1 | P64: 1.1576219
A65: Minh | B65: Question 15 | C65: 0 | D65: 1 | E65: 1 | F65: 1 | G65: 1 | H65: 1 | I65: 1 | J65: 1 | K65: 1 | L65: 1 | M65: 1 | N65: 1 | P65: 1.3282309
A66: Minh | B66: Question 16 | C66: 0 | D66: 1 | E66: 1 | F66: 1 | G66: 1 | H66: 1 | I66: 1 | J66: 1 | K66: 1 | L66: 1 | M66: 1 | N66: 1 | P66: 1.6687791
A67: Minh | B67: Question 17 | C67: 0 | D67: 1 | E67: 1 | F67: 1 | G67: 1 | H67: 1 | I67: 1 | J67: 1 | K67: 1 | L67: 1 | M67: 1 | N67: 1 | P67: 1.4827006
A68: Minh | B68: Question 18 | C68: 0 | D68: 1 | E68: 1 | F68: 1 | G68: 1 | H68: 1 | I68: 1 | J68: 1 | K68: 1 | L68: 1 | M68: 1 | N68: 1 | P68: 1.2952015
A69: Minh | B69: Question 19 | C69: 0 | D69: 1 | E69: 1 | F69: 1 | G69: 1 | H69: 1 | I69: 1 | J69: 1 | K69: 1 | L69: 1 | M69: 1 | N69: 1 | P69: 1.5508447
A70: Minh | B70: Question 20 | C70: 0 | D70: 1 | E70: 1 | F70: 1 | G70: 1 | H70: 1 | I70: 1 | J70: 1 | K70: 1 | L70: 1 | M70: 1 | N70: 1 | P70: 1.1737185
A71: Minh | B71: Question 21 | C71: 0 | D71: 1 | E71: 1 | F71: 1 | G71: 1 | H71: 1 | I71: 1 | J71: 1 | K71: 1 | L71: 1 | M71: 1 | N71: 1 | P71: 1.4778116
A72: Minh | B72: Question 22 | C72: 0 | D72: 1 | E72: 1 | F72: 1 | G72: 1 | H72: 1 | I72: 1 | J72: 1 | K72: 1 | L72: 1 | M72: 1 | N72: 1 | P72: 1.6965227
A73: Minh | B73: Question 23 | C73: 0 | D73: 1 | E73: 1 | F73: 1 | G73: 1 | H73: 1 | I73: 1 | J73: 1 | K73: 1 | L73: 1 | M73: 1 | N73: 1 | P73: 1.8805666
A74: Minh | B74: Question 24 | C74: 0 | D74: 1 | E74: 0 | F74: 0 | G74: 1 | H74: 'NA | I74: 1 | J74: 'NA | K74: 1 | L74: 1 | M74: 1 | N74: 1 | O74: Primary KC (FRACTIONS | Multiplication | multiplying a mixed number and a whole number) is not tested: The problem requires multiplying $2[FORMULA]$ (a mixed number) by 12 (a whole number), so it superficially seems to match. However, in this context, students actually must multiply a mixed number by a whole number, so it should align, but the multiplication is the first part ($12 [FORMULA] 2[FORMULA]$). The question seems appropriate, but perhaps did not strictly require a teaching focus on the multiplication process (such as explicit step-by-step decomposition), but will accept alignment (if you want to be strict, it is aligned). Secondary KC (FRACTIONS | Comparison and ordering | comparing and ordering fractions) is missing: Students are not asked to compare or order any fractions—the payment options are decimals ($30$ and $3[FORMULA]10=30$). There is no fraction comparison or ordering required. Synergy: The two KCs do not operate in tandem; the second part only involves comparing whole numbers/money and does not depend on use of fractions, nor are the questions chained together mathematically. | P74: 4.0673988
A75: Minh | B75: Question 25 | C75: 0 | D75: 1 | E75: 1 | F75: 1 | G75: 1 | H75: 1 | I75: 1 | J75: 1 | K75: 1 | L75: 1 | M75: 1 | N75: 1 | P75: 1.1263931
A76: Minh | B76: Question 26 | C76: 0 | D76: 1 | E76: 1 | F76: 1 | G76: 0 | H76: 1 | I76: 1 | J76: 1 | K76: 1 | L76: 1 | M76: 1 | N76: 1 | O76: 4: The context is about purchasing rice quantity and weight, which is more about measurement (mass/weight) rather than household finance (money, savings, utility bills, etc.) as required by the specified topic. | P76: 1.6525486
A77: Minh | B77: Question 27 | C77: 0 | D77: 1 | E77: 0 | F77: 1 | G77: 1 | H77: 'NA | I77: 1 | J77: 'NA | K77: 1 | L77: 1 | M77: 1 | N77: 1 | O77: Primary KC Alignment: The question asks for multiplication of two decimals (one with 3 decimal places), but not by 10, 100, 1000, or their multiples. The multiplication is by 0.183, not a power of 10; therefore, it does not fully target the specified Primary Knowledge Component. | P77: 2.0760181
A78: Minh | B78: Question 28 | C78: 0 | D78: 1 | E78: 1 | F78: 1 | G78: 1 | H78: 1 | I78: 0 | J78: 1 | K78: 1 | L78: 1 | M78: 1 | N78: 1 | O78: F- The value $187.250 is not realistic for savings. In real life, people do not usually express money to three decimal places, as currency is handled in two decimal places at most; banks and households do not keep savings with mills. This makes the context unrealistic for Singaporean students. | P78: 4.2152431
A79: Minh | B79: Question 29 | C79: 0 | D79: 1 | E79: 1 | F79: 1 | G79: 1 | H79: 1 | I79: 1 | J79: 1 | K79: 1 | L79: 1 | M79: 1 | N79: 1 | P79: 1.2637439
A80: Minh | B80: Question 30 | C80: 0 | D80: 1 | E80: 1 | F80: 1 | G80: 1 | H80: 1 | I80: 1 | J80: 1 | K80: 1 | L80: 1 | M80: 1 | N80: 1 | P80: 1.0826242
A81: Minh | B81: Question 31 | C81: 0 | D81: 1 | E81: 1 | F81: 1 | G81: 1 | H81: 1 | I81: 1 | J81: 1 | K81: 1 | L81: 1 | M81: 1 | N81: 1 | P81: 1.2527325
A82: Minh | B82: Question 32 | C82: 0 | D82: 1 | E82: 1 | F82: 1 | G82: 1 | H82: 1 | I82: 1 | J82: 1 | K82: 1 | L82: 1 | M82: 1 | N82: 1 | P82: 1.3104239
A83: Minh | B83: Question 33 | C83: 0 | D83: 1 | E83: 1 | F83: 1 | G83: 0 | H83: 1 | I83: 1 | J83: 1 | K83: 1 | L83: 1 | M83: 1 | N83: 1 | O83: 4: The context of the word problem is sharing cake at a family gathering, not household finance (e.g., money management, bills, interest, etc.). | P83: 5.3446844
A84: Minh | B84: Question 34 | C84: 0 | D84: 1 | E84: 1 | F84: 1 | G84: 1 | H84: 1 | I84: 1 | J84: 1 | K84: 1 | L84: 1 | M84: 1 | N84: 1 | P84: 3.1459603
A85: Minh | B85: Question 35 | C85: 0 | D85: 1 | E85: 1 | F85: 1 | G85: 0 | H85: 1 | I85: 1 | J85: 1 | K85: 1 | L85: 1 | M85: 1 | N85: 1 | O85: 4- The problem is about repacking laundry detergent, which is a household chore, but does not specifically relate to finances (income, utility bills, money, interest, savings, instalment, mortgage, financial planning etc.) as required by the intended topic. | P85: 4.1579592
A86: Minh | B86: Question 36 | C86: 0 | D86: 1 | E86: 1 | F86: 0 | G86: 1 | H86: 1 | I86: 1 | J86: 'NA | K86: 1 | L86: 1 | M86: 1 | N86: 1 | O86: Secondary KC Alignment: 0 - The problem only requires finding the whole given a part and percentage (Percentage, not Subtraction). It does not require explicit subtraction of whole numbers, as the only operation needed is to find the total given a reduced percentage. Synergy: 0 - The problem does not require using subtraction in conjunction with the percentage calculation; only the percentage concept is used to find the answer. | P86: 3.1626437
A87: Minh | B87: Question 37 | C87: 0 | D87: 1 | E87: 1 | F87: 1 | G87: 1 | H87: 1 | I87: 1 | J87: 1 | K87: 1 | L87: 1 | M87: 1 | N87: 1 | P87: 2.0603189
A88: Minh | B88: Question 38 | C88: 0 | D88: 1 | E88: 1 | F88: 1 | G88: 1 | H88: 1 | I88: 1 | J88: 1 | K88: 1 | L88: 1 | M88: 1 | N88: 1 | P88: 1.2504866
A89: Minh | B89: Question 39 | C89: 0 | D89: 1 | E89: 1 | F89: 1 | G89: 1 | H89: 1 | I89: 1 | J89: 1 | K89: 1 | L89: 1 | M89: 1 | N89: 1 | P89: 1.3829458
A90: Minh | B90: Question 40 | C90: 0 | D90: 1 | E90: 1 | F90: 1 | G90: 1 | H90: 1 | I90: 1 | J90: 1 | K90: 1 | L90: 1 | M90: 1 | N90: 1 | P90: 1.1996846
A91: Minh | B91: Question 41 | C91: 0 | D91: 1 | E91: 1 | F91: 1 | G91: 1 | H91: 1 | I91: 1 | J91: 1 | K91: 1 | L91: 1 | M91: 1 | N91: 1 | P91: 2.0181222
A92: Minh | B92: Question 42 | C92: 0 | D92: 1 | E92: 1 | F92: 1 | G92: 1 | H92: 1 | I92: 1 | J92: 1 | K92: 1 | L92: 1 | M92: 1 | N92: 1 | P92: 2.0819528
A93: Minh | B93: Question 43 | C93: 0 | D93: 1 | E93: 1 | F93: 1 | G93: 1 | H93: 1 | I93: 1 | J93: 1 | K93: 1 | L93: 1 | M93: 1 | N93: 1 | P93: 1.2811036
A94: Minh | B94: Question 44 | C94: 0 | D94: 1 | E94: 1 | F94: 1 | G94: 1 | H94: 1 | I94: 1 | J94: 1 | K94: 1 | L94: 1 | M94: 1 | N94: 1 | P94: 1.3692305
A95: Minh | B95: Question 45 | C95: 0 | D95: 1 | E95: 1 | F95: 1 | G95: 1 | H95: 1 | I95: 1 | J95: 1 | K95: 1 | L95: 1 | M95: 1 | N95: 1 | P95: 2.4649756
A96: Minh | B96: Question 46 | C96: 0 | D96: 1 | E96: 1 | F96: 1 | G96: 1 | H96: 1 | I96: 1 | J96: 1 | K96: 1 | L96: 1 | M96: 1 | N96: 1 | P96: 1.2014215
A97: Minh | B97: Question 47 | C97: 0 | D97: 1 | E97: 1 | F97: 1 | G97: 1 | H97: 1 | I97: 1 | J97: 1 | K97: 1 | L97: 1 | M97: 1 | N97: 1 | P97: 1.8200362
A98: Minh | B98: Question 48 | C98: 0 | D98: 1 | E98: 1 | F98: 1 | G98: 1 | H98: 1 | I98: 1 | J98: 1 | K98: 1 | L98: 1 | M98: 1 | N98: 1 | P98: 1.9198017
... A103: Minh | B103: Question 53 | C103: 0 | D103: 1 | E103: 1 | F103: 1 | G103: 1 | H103: 1 | I103: 1 | J103: 1 | K103: 1 | L103: 1 | M103: 1 | N103: 1 | P103: 1.3620615
A104: Minh | B104: Question 54 | C104: 0 | D104: 1 | E104: 1 | F104: 1 | G104: 1 | H104: 1 | I104: 1 | J104: 0 | K104: 1 | L104: 1 | M104: 1 | N104: 1 | O104: 7. The median and mode questions are independent; finding the median does not require the mode or vice versa, so there is no synergy between the questions. | P104: 1.5470865
...

Sheet Compiled Votes
A1: Evaluator | B1: Question | C1: status | D1: answerability | E1: primary_kc_alignment | F1: secondary_kc_alignment | G1: topic_alignment | H1: grade_alignment | I1: real_world_feasibility | J1: synergy | K1: clarity | L1: conciseness_and_relevance | M1: language_quality | N1: content_appropriateness | O1: response_time
A2: TD | B2: Question 1 | C2: 0 | D2: =ROUND(SUM(householdfinance_v4_5!D2,householdfinance_v4_4!D2,householdfinance_v4_3!D2,householdfinance_v4_2!D2,householdfinance_v4_1!D2)/COUNT(householdfinance_v4_5!D2,householdfinance_v4_4!D2,householdfinance_v4_3!D2,householdfinance_v4_2!D2,householdfinance_v4_1!D2),0) -> 1 | E2: =IF($D2=1,ROUND(SUM(householdfinance_v4_5!E2,householdfinance_v4_4!E2,householdfinance_v4_3!E2,householdfinance_v4_2!E2,householdfinance_v4_1!E2)/COUNT(householdfinance_v4_5!E2,householdfinance_v4_4!E2,householdfinance_v4_3!E2,householdfinance_v4_2!E2,householdfinance_v4_1!E2),0),"NA") -> 1 | F2: =IF($D2=1,ROUND(SUM(householdfinance_v4_5!F2,householdfinance_v4_4!F2,householdfinance_v4_3!F2,householdfinance_v4_2!F2,householdfinance_v4_1!F2)/COUNT(householdfinance_v4_5!F2,householdfinance_v4_4!F2,householdfinance_v4_3!F2,householdfinance_v4_2!F2,householdfinance_v4_1!F2),0),"NA") -> 1 | G2: =IF($D2=1,ROUND(SUM(householdfinance_v4_5!G2,householdfinance_v4_4!G2,householdfinance_v4_3!G2,householdfinance_v4_2!G2,householdfinance_v4_1!G2)/COUNT(householdfinance_v4_5!G2,householdfinance_v4_4!G2,householdfinance_v4_3!G2,householdfinance_v4_2!G2,householdfinance_v4_1!G2),0),"NA") -> 1 | H2: =IF($E2=1,ROUND(SUM(householdfinance_v4_5!H2,householdfinance_v4_4!H2,householdfinance_v4_3!H2,householdfinance_v4_2!H2,householdfinance_v4_1!H2)/COUNT(householdfinance_v4_5!H2,householdfinance_v4_4!H2,householdfinance_v4_3!H2,householdfinance_v4_2!H2,householdfinance_v4_1!H2),0),"NA") -> 1 | I2: =IF($D2=1,ROUND(SUM(householdfinance_v4_5!I2,householdfinance_v4_4!I2,householdfinance_v4_3!I2,householdfinance_v4_2!I2,householdfinance_v4_1!I2)/COUNT(householdfinance_v4_5!I2,householdfinance_v4_4!I2,householdfinance_v4_3!I2,householdfinance_v4_2!I2,householdfinance_v4_1!I2),0),"NA") -> 1 | J2: =IF(AND($E2=1,$F2=1),ROUND(SUM(householdfinance_v4_5!J2,householdfinance_v4_4!J2,householdfinance_v4_3!J2,householdfinance_v4_2!J2,householdfinance_v4_1!J2)/COUNT(householdfinance_v4_5!J2,householdfinance_v4_4!J2,householdfinance_v4_3!J2,householdfinance_v4_2!J2,householdfinance_v4_1!J2),0),"NA") -> 1 | K2: =IF($D2=1,ROUND(SUM(householdfinance_v4_5!K2,householdfinance_v4_4!K2,householdfinance_v4_3!K2,householdfinance_v4_2!K2,householdfinance_v4_1!K2)/COUNT(householdfinance_v4_5!K2,householdfinance_v4_4!K2,householdfinance_v4_3!K2,householdfinance_v4_2!K2,householdfinance_v4_1!K2),0),"NA") -> 1 | L2: =IF($D2=1,ROUND(SUM(householdfinance_v4_5!L2,householdfinance_v4_4!L2,householdfinance_v4_3!L2,householdfinance_v4_2!L2,householdfinance_v4_1!L2)/COUNT(householdfinance_v4_5!L2,householdfinance_v4_4!L2,householdfinance_v4_3!L2,householdfinance_v4_2!L2,householdfinance_v4_1!L2),0),"NA") -> 1 | M2: =IF($D2=1,ROUND(SUM(householdfinance_v4_5!M2,householdfinance_v4_4!M2,householdfinance_v4_3!M2,householdfinance_v4_2!M2,householdfinance_v4_1!M2)/COUNT(householdfinance_v4_5!M2,householdfinance_v4_4!M2,householdfinance_v4_3!M2,householdfinance_v4_2!M2,householdfinance_v4_1!M2),0),"NA") -> 1 | N2: =IF($D2=1,ROUND(SUM(householdfinance_v4_5!N2,householdfinance_v4_4!N2,householdfinance_v4_3!N2,householdfinance_v4_2!N2,householdfinance_v4_1!N2)/COUNT(householdfinance_v4_5!N2,householdfinance_v4_4!N2,householdfinance_v4_3!N2,householdfinance_v4_2!N2,householdfinance_v4_1!N2),0),"NA") -> 1 | O2: 1.1985626
A3: TD | B3: Question 2 | C3: 0 | D3: =ROUND(SUM(householdfinance_v4_5!D3,householdfinance_v4_4!D3,householdfinance_v4_3!D3,householdfinance_v4_2!D3,householdfinance_v4_1!D3)/COUNT(householdfinance_v4_5!D3,householdfinance_v4_4!D3,householdfinance_v4_3!D3,householdfinance_v4_2!D3,householdfinance_v4_1!D3),0) -> 1 | E3: =IF($D3=1,ROUND(SUM(householdfinance_v4_5!E3,householdfinance_v4_4!E3,householdfinance_v4_3!E3,householdfinance_v4_2!E3,householdfinance_v4_1!E3)/COUNT(householdfinance_v4_5!E3,householdfinance_v4_4!E3,householdfinance_v4_3!E3,householdfinance_v4_2!E3,householdfinance_v4_1!E3),0),"NA") -> 1 | F3: =IF($D3=1,ROUND(SUM(householdfinance_v4_5!F3,householdfinance_v4_4!F3,householdfinance_v4_3!F3,householdfinance_v4_2!F3,householdfinance_v4_1!F3)/COUNT(householdfinance_v4_5!F3,householdfinance_v4_4!F3,householdfinance_v4_3!F3,householdfinance_v4_2!F3,householdfinance_v4_1!F3),0),"NA") -> 0 | G3: =IF($D3=1,ROUND(SUM(householdfinance_v4_5!G3,householdfinance_v4_4!G3,householdfinance_v4_3!G3,householdfinance_v4_2!G3,householdfinance_v4_1!G3)/COUNT(householdfinance_v4_5!G3,householdfinance_v4_4!G3,householdfinance_v4_3!G3,householdfinance_v4_2!G3,householdfinance_v4_1!G3),0),"NA") -> 1 | H3: =IF($E3=1,ROUND(SUM(householdfinance_v4_5!H3,householdfinance_v4_4!H3,householdfinance_v4_3!H3,householdfinance_v4_2!H3,householdfinance_v4_1!H3)/COUNT(householdfinance_v4_5!H3,householdfinance_v4_4!H3,householdfinance_v4_3!H3,householdfinance_v4_2!H3,householdfinance_v4_1!H3),0),"NA") -> 1 | I3: =IF($D3=1,ROUND(SUM(householdfinance_v4_5!I3,householdfinance_v4_4!I3,householdfinance_v4_3!I3,householdfinance_v4_2!I3,householdfinance_v4_1!I3)/COUNT(householdfinance_v4_5!I3,householdfinance_v4_4!I3,householdfinance_v4_3!I3,householdfinance_v4_2!I3,householdfinance_v4_1!I3),0),"NA") -> 1 | J3: =IF(AND($E3=1,$F3=1),ROUND(SUM(householdfinance_v4_5!J3,householdfinance_v4_4!J3,householdfinance_v4_3!J3,householdfinance_v4_2!J3,householdfinance_v4_1!J3)/COUNT(householdfinance_v4_5!J3,householdfinance_v4_4!J3,householdfinance_v4_3!J3,householdfinance_v4_2!J3,householdfinance_v4_1!J3),0),"NA") -> NA | K3: =IF($D3=1,ROUND(SUM(householdfinance_v4_5!K3,householdfinance_v4_4!K3,householdfinance_v4_3!K3,householdfinance_v4_2!K3,householdfinance_v4_1!K3)/COUNT(householdfinance_v4_5!K3,householdfinance_v4_4!K3,householdfinance_v4_3!K3,householdfinance_v4_2!K3,householdfinance_v4_1!K3),0),"NA") -> 1 | L3: =IF($D3=1,ROUND(SUM(householdfinance_v4_5!L3,householdfinance_v4_4!L3,householdfinance_v4_3!L3,householdfinance_v4_2!L3,householdfinance_v4_1!L3)/COUNT(householdfinance_v4_5!L3,householdfinance_v4_4!L3,householdfinance_v4_3!L3,householdfinance_v4_2!L3,householdfinance_v4_1!L3),0),"NA") -> 1 | M3: =IF($D3=1,ROUND(SUM(householdfinance_v4_5!M3,householdfinance_v4_4!M3,householdfinance_v4_3!M3,householdfinance_v4_2!M3,householdfinance_v4_1!M3)/COUNT(householdfinance_v4_5!M3,householdfinance_v4_4!M3,householdfinance_v4_3!M3,householdfinance_v4_2!M3,householdfinance_v4_1!M3),0),"NA") -> 1 | N3: =IF($D3=1,ROUND(SUM(householdfinance_v4_5!N3,householdfinance_v4_4!N3,householdfinance_v4_3!N3,householdfinance_v4_2!N3,householdfinance_v4_1!N3)/COUNT(householdfinance_v4_5!N3,householdfinance_v4_4!N3,householdfinance_v4_3!N3,householdfinance_v4_2!N3,householdfinance_v4_1!N3),0),"NA") -> 1 | O3: 8.184953
A4: TD | B4: Question 3 | C4: 0 | D4: =ROUND(SUM(householdfinance_v4_5!D4,householdfinance_v4_4!D4,householdfinance_v4_3!D4,householdfinance_v4_2!D4,householdfinance_v4_1!D4)/COUNT(householdfinance_v4_5!D4,householdfinance_v4_4!D4,householdfinance_v4_3!D4,householdfinance_v4_2!D4,householdfinance_v4_1!D4),0) -> 1 | E4: =IF($D4=1,ROUND(SUM(householdfinance_v4_5!E4,householdfinance_v4_4!E4,householdfinance_v4_3!E4,householdfinance_v4_2!E4,householdfinance_v4_1!E4)/COUNT(householdfinance_v4_5!E4,householdfinance_v4_4!E4,householdfinance_v4_3!E4,householdfinance_v4_2!E4,householdfinance_v4_1!E4),0),"NA") -> 1 | F4: =IF($D4=1,ROUND(SUM(householdfinance_v4_5!F4,householdfinance_v4_4!F4,householdfinance_v4_3!F4,householdfinance_v4_2!F4,householdfinance_v4_1!F4)/COUNT(householdfinance_v4_5!F4,householdfinance_v4_4!F4,householdfinance_v4_3!F4,householdfinance_v4_2!F4,householdfinance_v4_1!F4),0),"NA") -> 1 | G4: =IF($D4=1,ROUND(SUM(householdfinance_v4_5!G4,householdfinance_v4_4!G4,householdfinance_v4_3!G4,householdfinance_v4_2!G4,householdfinance_v4_1!G4)/COUNT(householdfinance_v4_5!G4,householdfinance_v4_4!G4,householdfinance_v4_3!G4,householdfinance_v4_2!G4,householdfinance_v4_1!G4),0),"NA") -> 0 | H4: =IF($E4=1,ROUND(SUM(householdfinance_v4_5!H4,householdfinance_v4_4!H4,householdfinance_v4_3!H4,householdfinance_v4_2!H4,householdfinance_v4_1!H4)/COUNT(householdfinance_v4_5!H4,householdfinance_v4_4!H4,householdfinance_v4_3!H4,householdfinance_v4_2!H4,householdfinance_v4_1!H4),0),"NA") -> 1 | I4: =IF($D4=1,ROUND(SUM(householdfinance_v4_5!I4,householdfinance_v4_4!I4,householdfinance_v4_3!I4,householdfinance_v4_2!I4,householdfinance_v4_1!I4)/COUNT(householdfinance_v4_5!I4,householdfinance_v4_4!I4,householdfinance_v4_3!I4,householdfinance_v4_2!I4,householdfinance_v4_1!I4),0),"NA") -> 1 | J4: =IF(AND($E4=1,$F4=1),ROUND(SUM(householdfinance_v4_5!J4,householdfinance_v4_4!J4,householdfinance_v4_3!J4,householdfinance_v4_2!J4,householdfinance_v4_1!J4)/COUNT(householdfinance_v4_5!J4,householdfinance_v4_4!J4,householdfinance_v4_3!J4,householdfinance_v4_2!J4,householdfinance_v4_1!J4),0),"NA") -> 1 | K4: =IF($D4=1,ROUND(SUM(householdfinance_v4_5!K4,householdfinance_v4_4!K4,householdfinance_v4_3!K4,householdfinance_v4_2!K4,householdfinance_v4_1!K4)/COUNT(householdfinance_v4_5!K4,householdfinance_v4_4!K4,householdfinance_v4_3!K4,householdfinance_v4_2!K4,householdfinance_v4_1!K4),0),"NA") -> 1 | L4: =IF($D4=1,ROUND(SUM(householdfinance_v4_5!L4,householdfinance_v4_4!L4,householdfinance_v4_3!L4,householdfinance_v4_2!L4,householdfinance_v4_1!L4)/COUNT(householdfinance_v4_5!L4,householdfinance_v4_4!L4,householdfinance_v4_3!L4,householdfinance_v4_2!L4,householdfinance_v4_1!L4),0),"NA") -> 1 | M4: =IF($D4=1,ROUND(SUM(householdfinance_v4_5!M4,householdfinance_v4_4!M4,householdfinance_v4_3!M4,householdfinance_v4_2!M4,householdfinance_v4_1!M4)/COUNT(householdfinance_v4_5!M4,householdfinance_v4_4!M4,householdfinance_v4_3!M4,householdfinance_v4_2!M4,householdfinance_v4_1!M4),0),"NA") -> 1 | N4: =IF($D4=1,ROUND(SUM(householdfinance_v4_5!N4,householdfinance_v4_4!N4,householdfinance_v4_3!N4,householdfinance_v4_2!N4,householdfinance_v4_1!N4)/COUNT(householdfinance_v4_5!N4,householdfinance_v4_4!N4,householdfinance_v4_3!N4,householdfinance_v4_2!N4,householdfinance_v4_1!N4),0),"NA") -> 1 | O4: 3.5693607
A5: TD | B5: Question 4 | C5: 0 | D5: =ROUND(SUM(householdfinance_v4_5!D5,householdfinance_v4_4!D5,householdfinance_v4_3!D5,householdfinance_v4_2!D5,householdfinance_v4_1!D5)/COUNT(householdfinance_v4_5!D5,householdfinance_v4_4!D5,householdfinance_v4_3!D5,householdfinance_v4_2!D5,householdfinance_v4_1!D5),0) -> 1 | E5: =IF($D5=1,ROUND(SUM(householdfinance_v4_5!E5,householdfinance_v4_4!E5,householdfinance_v4_3!E5,householdfinance_v4_2!E5,householdfinance_v4_1!E5)/COUNT(householdfinance_v4_5!E5,householdfinance_v4_4!E5,householdfinance_v4_3!E5,householdfinance_v4_2!E5,householdfinance_v4_1!E5),0),"NA") -> 1 | F5: =IF($D5=1,ROUND(SUM(householdfinance_v4_5!F5,householdfinance_v4_4!F5,householdfinance_v4_3!F5,householdfinance_v4_2!F5,householdfinance_v4_1!F5)/COUNT(householdfinance_v4_5!F5,householdfinance_v4_4!F5,householdfinance_v4_3!F5,householdfinance_v4_2!F5,householdfinance_v4_1!F5),0),"NA") -> 1 | G5: =IF($D5=1,ROUND(SUM(householdfinance_v4_5!G5,householdfinance_v4_4!G5,householdfinance_v4_3!G5,householdfinance_v4_2!G5,householdfinance_v4_1!G5)/COUNT(householdfinance_v4_5!G5,householdfinance_v4_4!G5,householdfinance_v4_3!G5,householdfinance_v4_2!G5,householdfinance_v4_1!G5),0),"NA") -> 1 | H5: =IF($E5=1,ROUND(SUM(householdfinance_v4_5!H5,householdfinance_v4_4!H5,householdfinance_v4_3!H5,householdfinance_v4_2!H5,householdfinance_v4_1!H5)/COUNT(householdfinance_v4_5!H5,householdfinance_v4_4!H5,householdfinance_v4_3!H5,householdfinance_v4_2!H5,householdfinance_v4_1!H5),0),"NA") -> 1 | I5: =IF($D5=1,ROUND(SUM(householdfinance_v4_5!I5,householdfinance_v4_4!I5,householdfinance_v4_3!I5,householdfinance_v4_2!I5,householdfinance_v4_1!I5)/COUNT(householdfinance_v4_5!I5,householdfinance_v4_4!I5,householdfinance_v4_3!I5,householdfinance_v4_2!I5,householdfinance_v4_1!I5),0),"NA") -> 1 | J5: =IF(AND($E5=1,$F5=1),ROUND(SUM(householdfinance_v4_5!J5,householdfinance_v4_4!J5,householdfinance_v4_3!J5,householdfinance_v4_2!J5,householdfinance_v4_1!J5)/COUNT(householdfinance_v4_5!J5,householdfinance_v4_4!J5,householdfinance_v4_3!J5,householdfinance_v4_2!J5,householdfinance_v4_1!J5),0),"NA") -> 1 | K5: =IF($D5=1,ROUND(SUM(householdfinance_v4_5!K5,householdfinance_v4_4!K5,householdfinance_v4_3!K5,householdfinance_v4_2!K5,householdfinance_v4_1!K5)/COUNT(householdfinance_v4_5!K5,householdfinance_v4_4!K5,householdfinance_v4_3!K5,householdfinance_v4_2!K5,householdfinance_v4_1!K5),0),"NA") -> 1 | L5: =IF($D5=1,ROUND(SUM(householdfinance_v4_5!L5,householdfinance_v4_4!L5,householdfinance_v4_3!L5,householdfinance_v4_2!L5,householdfinance_v4_1!L5)/COUNT(householdfinance_v4_5!L5,householdfinance_v4_4!L5,householdfinance_v4_3!L5,householdfinance_v4_2!L5,householdfinance_v4_1!L5),0),"NA") -> 1 | M5: =IF($D5=1,ROUND(SUM(householdfinance_v4_5!M5,householdfinance_v4_4!M5,householdfinance_v4_3!M5,householdfinance_v4_2!M5,householdfinance_v4_1!M5)/COUNT(householdfinance_v4_5!M5,householdfinance_v4_4!M5,householdfinance_v4_3!M5,householdfinance_v4_2!M5,householdfinance_v4_1!M5),0),"NA") -> 1 | N5: =IF($D5=1,ROUND(SUM(householdfinance_v4_5!N5,householdfinance_v4_4!N5,householdfinance_v4_3!N5,householdfinance_v4_2!N5,householdfinance_v4_1!N5)/COUNT(householdfinance_v4_5!N5,householdfinance_v4_4!N5,householdfinance_v4_3!N5,householdfinance_v4_2!N5,householdfinance_v4_1!N5),0),"NA") -> 1 | O5: 1.1780415
A6: TD | B6: Question 5 | C6: 0 | D6: =ROUND(SUM(householdfinance_v4_5!D6,householdfinance_v4_4!D6,householdfinance_v4_3!D6,householdfinance_v4_2!D6,householdfinance_v4_1!D6)/COUNT(householdfinance_v4_5!D6,householdfinance_v4_4!D6,householdfinance_v4_3!D6,householdfinance_v4_2!D6,householdfinance_v4_1!D6),0) -> 1 | E6: =IF($D6=1,ROUND(SUM(householdfinance_v4_5!E6,householdfinance_v4_4!E6,householdfinance_v4_3!E6,householdfinance_v4_2!E6,householdfinance_v4_1!E6)/COUNT(householdfinance_v4_5!E6,householdfinance_v4_4!E6,householdfinance_v4_3!E6,householdfinance_v4_2!E6,householdfinance_v4_1!E6),0),"NA") -> 1 | F6: =IF($D6=1,ROUND(SUM(householdfinance_v4_5!F6,householdfinance_v4_4!F6,householdfinance_v4_3!F6,householdfinance_v4_2!F6,householdfinance_v4_1!F6)/COUNT(householdfinance_v4_5!F6,householdfinance_v4_4!F6,householdfinance_v4_3!F6,householdfinance_v4_2!F6,householdfinance_v4_1!F6),0),"NA") -> 1 | G6: =IF($D6=1,ROUND(SUM(householdfinance_v4_5!G6,householdfinance_v4_4!G6,householdfinance_v4_3!G6,householdfinance_v4_2!G6,householdfinance_v4_1!G6)/COUNT(householdfinance_v4_5!G6,householdfinance_v4_4!G6,householdfinance_v4_3!G6,householdfinance_v4_2!G6,householdfinance_v4_1!G6),0),"NA") -> 1 | H6: =IF($E6=1,ROUND(SUM(householdfinance_v4_5!H6,householdfinance_v4_4!H6,householdfinance_v4_3!H6,householdfinance_v4_2!H6,householdfinance_v4_1!H6)/COUNT(householdfinance_v4_5!H6,householdfinance_v4_4!H6,householdfinance_v4_3!H6,householdfinance_v4_2!H6,householdfinance_v4_1!H6),0),"NA") -> 1 | I6: =IF($D6=1,ROUND(SUM(householdfinance_v4_5!I6,householdfinance_v4_4!I6,householdfinance_v4_3!I6,householdfinance_v4_2!I6,householdfinance_v4_1!I6)/COUNT(householdfinance_v4_5!I6,householdfinance_v4_4!I6,householdfinance_v4_3!I6,householdfinance_v4_2!I6,householdfinance_v4_1!I6),0),"NA") -> 1 | J6: =IF(AND($E6=1,$F6=1),ROUND(SUM(householdfinance_v4_5!J6,householdfinance_v4_4!J6,householdfinance_v4_3!J6,householdfinance_v4_2!J6,householdfinance_v4_1!J6)/COUNT(householdfinance_v4_5!J6,householdfinance_v4_4!J6,householdfinance_v4_3!J6,householdfinance_v4_2!J6,householdfinance_v4_1!J6),0),"NA") -> 1 | K6: =IF($D6=1,ROUND(SUM(householdfinance_v4_5!K6,householdfinance_v4_4!K6,householdfinance_v4_3!K6,householdfinance_v4_2!K6,householdfinance_v4_1!K6)/COUNT(householdfinance_v4_5!K6,householdfinance_v4_4!K6,householdfinance_v4_3!K6,householdfinance_v4_2!K6,householdfinance_v4_1!K6),0),"NA") -> 1 | L6: =IF($D6=1,ROUND(SUM(householdfinance_v4_5!L6,householdfinance_v4_4!L6,householdfinance_v4_3!L6,householdfinance_v4_2!L6,householdfinance_v4_1!L6)/COUNT(householdfinance_v4_5!L6,householdfinance_v4_4!L6,householdfinance_v4_3!L6,householdfinance_v4_2!L6,householdfinance_v4_1!L6),0),"NA") -> 1 | M6: =IF($D6=1,ROUND(SUM(householdfinance_v4_5!M6,householdfinance_v4_4!M6,householdfinance_v4_3!M6,householdfinance_v4_2!M6,householdfinance_v4_1!M6)/COUNT(householdfinance_v4_5!M6,householdfinance_v4_4!M6,householdfinance_v4_3!M6,householdfinance_v4_2!M6,householdfinance_v4_1!M6),0),"NA") -> 1 | N6: =IF($D6=1,ROUND(SUM(householdfinance_v4_5!N6,householdfinance_v4_4!N6,householdfinance_v4_3!N6,householdfinance_v4_2!N6,householdfinance_v4_1!N6)/COUNT(householdfinance_v4_5!N6,householdfinance_v4_4!N6,householdfinance_v4_3!N6,householdfinance_v4_2!N6,householdfinance_v4_1!N6),0),"NA") -> 1 | O6: 1.191191
A7: TD | B7: Question 6 | C7: 0 | D7: =ROUND(SUM(householdfinance_v4_5!D7,householdfinance_v4_4!D7,householdfinance_v4_3!D7,householdfinance_v4_2!D7,householdfinance_v4_1!D7)/COUNT(householdfinance_v4_5!D7,householdfinance_v4_4!D7,householdfinance_v4_3!D7,householdfinance_v4_2!D7,householdfinance_v4_1!D7),0) -> 1 | E7: =IF($D7=1,ROUND(SUM(householdfinance_v4_5!E7,householdfinance_v4_4!E7,householdfinance_v4_3!E7,householdfinance_v4_2!E7,householdfinance_v4_1!E7)/COUNT(householdfinance_v4_5!E7,householdfinance_v4_4!E7,householdfinance_v4_3!E7,householdfinance_v4_2!E7,householdfinance_v4_1!E7),0),"NA") -> 1 | F7: =IF($D7=1,ROUND(SUM(householdfinance_v4_5!F7,householdfinance_v4_4!F7,householdfinance_v4_3!F7,householdfinance_v4_2!F7,householdfinance_v4_1!F7)/COUNT(householdfinance_v4_5!F7,householdfinance_v4_4!F7,householdfinance_v4_3!F7,householdfinance_v4_2!F7,householdfinance_v4_1!F7),0),"NA") -> 1 | G7: =IF($D7=1,ROUND(SUM(householdfinance_v4_5!G7,householdfinance_v4_4!G7,householdfinance_v4_3!G7,householdfinance_v4_2!G7,householdfinance_v4_1!G7)/COUNT(householdfinance_v4_5!G7,householdfinance_v4_4!G7,householdfinance_v4_3!G7,householdfinance_v4_2!G7,householdfinance_v4_1!G7),0),"NA") -> 1 | H7: =IF($E7=1,ROUND(SUM(householdfinance_v4_5!H7,householdfinance_v4_4!H7,householdfinance_v4_3!H7,householdfinance_v4_2!H7,householdfinance_v4_1!H7)/COUNT(householdfinance_v4_5!H7,householdfinance_v4_4!H7,householdfinance_v4_3!H7,householdfinance_v4_2!H7,householdfinance_v4_1!H7),0),"NA") -> 1 | I7: =IF($D7=1,ROUND(SUM(householdfinance_v4_5!I7,householdfinance_v4_4!I7,householdfinance_v4_3!I7,householdfinance_v4_2!I7,householdfinance_v4_1!I7)/COUNT(householdfinance_v4_5!I7,householdfinance_v4_4!I7,householdfinance_v4_3!I7,householdfinance_v4_2!I7,householdfinance_v4_1!I7),0),"NA") -> 1 | J7: =IF(AND($E7=1,$F7=1),ROUND(SUM(householdfinance_v4_5!J7,householdfinance_v4_4!J7,householdfinance_v4_3!J7,householdfinance_v4_2!J7,householdfinance_v4_1!J7)/COUNT(householdfinance_v4_5!J7,householdfinance_v4_4!J7,householdfinance_v4_3!J7,householdfinance_v4_2!J7,householdfinance_v4_1!J7),0),"NA") -> 1 | K7: =IF($D7=1,ROUND(SUM(householdfinance_v4_5!K7,householdfinance_v4_4!K7,householdfinance_v4_3!K7,householdfinance_v4_2!K7,householdfinance_v4_1!K7)/COUNT(householdfinance_v4_5!K7,householdfinance_v4_4!K7,householdfinance_v4_3!K7,householdfinance_v4_2!K7,householdfinance_v4_1!K7),0),"NA") -> 1 | L7: =IF($D7=1,ROUND(SUM(householdfinance_v4_5!L7,householdfinance_v4_4!L7,householdfinance_v4_3!L7,householdfinance_v4_2!L7,householdfinance_v4_1!L7)/COUNT(householdfinance_v4_5!L7,householdfinance_v4_4!L7,householdfinance_v4_3!L7,householdfinance_v4_2!L7,householdfinance_v4_1!L7),0),"NA") -> 1 | M7: =IF($D7=1,ROUND(SUM(householdfinance_v4_5!M7,householdfinance_v4_4!M7,householdfinance_v4_3!M7,householdfinance_v4_2!M7,householdfinance_v4_1!M7)/COUNT(householdfinance_v4_5!M7,householdfinance_v4_4!M7,householdfinance_v4_3!M7,householdfinance_v4_2!M7,householdfinance_v4_1!M7),0),"NA") -> 1 | N7: =IF($D7=1,ROUND(SUM(householdfinance_v4_5!N7,householdfinance_v4_4!N7,householdfinance_v4_3!N7,householdfinance_v4_2!N7,householdfinance_v4_1!N7)/COUNT(householdfinance_v4_5!N7,householdfinance_v4_4!N7,householdfinance_v4_3!N7,householdfinance_v4_2!N7,householdfinance_v4_1!N7),0),"NA") -> 1 | O7: 1.4485931
A8: TD | B8: Question 7 | C8: 0 | D8: =ROUND(SUM(householdfinance_v4_5!D8,householdfinance_v4_4!D8,householdfinance_v4_3!D8,householdfinance_v4_2!D8,householdfinance_v4_1!D8)/COUNT(householdfinance_v4_5!D8,householdfinance_v4_4!D8,householdfinance_v4_3!D8,householdfinance_v4_2!D8,householdfinance_v4_1!D8),0) -> 1 | E8: =IF($D8=1,ROUND(SUM(householdfinance_v4_5!E8,householdfinance_v4_4!E8,householdfinance_v4_3!E8,householdfinance_v4_2!E8,householdfinance_v4_1!E8)/COUNT(householdfinance_v4_5!E8,householdfinance_v4_4!E8,householdfinance_v4_3!E8,householdfinance_v4_2!E8,householdfinance_v4_1!E8),0),"NA") -> 1 | F8: =IF($D8=1,ROUND(SUM(householdfinance_v4_5!F8,householdfinance_v4_4!F8,householdfinance_v4_3!F8,householdfinance_v4_2!F8,householdfinance_v4_1!F8)/COUNT(householdfinance_v4_5!F8,householdfinance_v4_4!F8,householdfinance_v4_3!F8,householdfinance_v4_2!F8,householdfinance_v4_1!F8),0),"NA") -> 1 | G8: =IF($D8=1,ROUND(SUM(householdfinance_v4_5!G8,householdfinance_v4_4!G8,householdfinance_v4_3!G8,householdfinance_v4_2!G8,householdfinance_v4_1!G8)/COUNT(householdfinance_v4_5!G8,householdfinance_v4_4!G8,householdfinance_v4_3!G8,householdfinance_v4_2!G8,householdfinance_v4_1!G8),0),"NA") -> 0 | H8: =IF($E8=1,ROUND(SUM(householdfinance_v4_5!H8,householdfinance_v4_4!H8,householdfinance_v4_3!H8,householdfinance_v4_2!H8,householdfinance_v4_1!H8)/COUNT(householdfinance_v4_5!H8,householdfinance_v4_4!H8,householdfinance_v4_3!H8,householdfinance_v4_2!H8,householdfinance_v4_1!H8),0),"NA") -> 1 | I8: =IF($D8=1,ROUND(SUM(householdfinance_v4_5!I8,householdfinance_v4_4!I8,householdfinance_v4_3!I8,householdfinance_v4_2!I8,householdfinance_v4_1!I8)/COUNT(householdfinance_v4_5!I8,householdfinance_v4_4!I8,householdfinance_v4_3!I8,householdfinance_v4_2!I8,householdfinance_v4_1!I8),0),"NA") -> 1 | J8: =IF(AND($E8=1,$F8=1),ROUND(SUM(householdfinance_v4_5!J8,householdfinance_v4_4!J8,householdfinance_v4_3!J8,householdfinance_v4_2!J8,householdfinance_v4_1!J8)/COUNT(householdfinance_v4_5!J8,householdfinance_v4_4!J8,householdfinance_v4_3!J8,householdfinance_v4_2!J8,householdfinance_v4_1!J8),0),"NA") -> 1 | K8: =IF($D8=1,ROUND(SUM(householdfinance_v4_5!K8,householdfinance_v4_4!K8,householdfinance_v4_3!K8,householdfinance_v4_2!K8,householdfinance_v4_1!K8)/COUNT(householdfinance_v4_5!K8,householdfinance_v4_4!K8,householdfinance_v4_3!K8,householdfinance_v4_2!K8,householdfinance_v4_1!K8),0),"NA") -> 1 | L8: =IF($D8=1,ROUND(SUM(householdfinance_v4_5!L8,householdfinance_v4_4!L8,householdfinance_v4_3!L8,householdfinance_v4_2!L8,householdfinance_v4_1!L8)/COUNT(householdfinance_v4_5!L8,householdfinance_v4_4!L8,householdfinance_v4_3!L8,householdfinance_v4_2!L8,householdfinance_v4_1!L8),0),"NA") -> 1 | M8: =IF($D8=1,ROUND(SUM(householdfinance_v4_5!M8,householdfinance_v4_4!M8,householdfinance_v4_3!M8,householdfinance_v4_2!M8,householdfinance_v4_1!M8)/COUNT(householdfinance_v4_5!M8,householdfinance_v4_4!M8,householdfinance_v4_3!M8,householdfinance_v4_2!M8,householdfinance_v4_1!M8),0),"NA") -> 1 | N8: =IF($D8=1,ROUND(SUM(householdfinance_v4_5!N8,householdfinance_v4_4!N8,householdfinance_v4_3!N8,householdfinance_v4_2!N8,householdfinance_v4_1!N8)/COUNT(householdfinance_v4_5!N8,householdfinance_v4_4!N8,householdfinance_v4_3!N8,householdfinance_v4_2!N8,householdfinance_v4_1!N8),0),"NA") -> 1 | O8: 4.9530828
A9: TD | B9: Question 8 | C9: 0 | D9: =ROUND(SUM(householdfinance_v4_5!D9,householdfinance_v4_4!D9,householdfinance_v4_3!D9,householdfinance_v4_2!D9,householdfinance_v4_1!D9)/COUNT(householdfinance_v4_5!D9,householdfinance_v4_4!D9,householdfinance_v4_3!D9,householdfinance_v4_2!D9,householdfinance_v4_1!D9),0) -> 1 | E9: =IF($D9=1,ROUND(SUM(householdfinance_v4_5!E9,householdfinance_v4_4!E9,householdfinance_v4_3!E9,householdfinance_v4_2!E9,householdfinance_v4_1!E9)/COUNT(householdfinance_v4_5!E9,householdfinance_v4_4!E9,householdfinance_v4_3!E9,householdfinance_v4_2!E9,householdfinance_v4_1!E9),0),"NA") -> 1 | F9: =IF($D9=1,ROUND(SUM(householdfinance_v4_5!F9,householdfinance_v4_4!F9,householdfinance_v4_3!F9,householdfinance_v4_2!F9,householdfinance_v4_1!F9)/COUNT(householdfinance_v4_5!F9,householdfinance_v4_4!F9,householdfinance_v4_3!F9,householdfinance_v4_2!F9,householdfinance_v4_1!F9),0),"NA") -> 1 | G9: =IF($D9=1,ROUND(SUM(householdfinance_v4_5!G9,householdfinance_v4_4!G9,householdfinance_v4_3!G9,householdfinance_v4_2!G9,householdfinance_v4_1!G9)/COUNT(householdfinance_v4_5!G9,householdfinance_v4_4!G9,householdfinance_v4_3!G9,householdfinance_v4_2!G9,householdfinance_v4_1!G9),0),"NA") -> 1 | H9: =IF($E9=1,ROUND(SUM(householdfinance_v4_5!H9,householdfinance_v4_4!H9,householdfinance_v4_3!H9,householdfinance_v4_2!H9,householdfinance_v4_1!H9)/COUNT(householdfinance_v4_5!H9,householdfinance_v4_4!H9,householdfinance_v4_3!H9,householdfinance_v4_2!H9,householdfinance_v4_1!H9),0),"NA") -> 1 | I9: =IF($D9=1,ROUND(SUM(householdfinance_v4_5!I9,householdfinance_v4_4!I9,householdfinance_v4_3!I9,householdfinance_v4_2!I9,householdfinance_v4_1!I9)/COUNT(householdfinance_v4_5!I9,householdfinance_v4_4!I9,householdfinance_v4_3!I9,householdfinance_v4_2!I9,householdfinance_v4_1!I9),0),"NA") -> 1 | J9: =IF(AND($E9=1,$F9=1),ROUND(SUM(householdfinance_v4_5!J9,householdfinance_v4_4!J9,householdfinance_v4_3!J9,householdfinance_v4_2!J9,householdfinance_v4_1!J9)/COUNT(householdfinance_v4_5!J9,householdfinance_v4_4!J9,householdfinance_v4_3!J9,householdfinance_v4_2!J9,householdfinance_v4_1!J9),0),"NA") -> 1 | K9: =IF($D9=1,ROUND(SUM(householdfinance_v4_5!K9,householdfinance_v4_4!K9,householdfinance_v4_3!K9,householdfinance_v4_2!K9,householdfinance_v4_1!K9)/COUNT(householdfinance_v4_5!K9,householdfinance_v4_4!K9,householdfinance_v4_3!K9,householdfinance_v4_2!K9,householdfinance_v4_1!K9),0),"NA") -> 1 | L9: =IF($D9=1,ROUND(SUM(householdfinance_v4_5!L9,householdfinance_v4_4!L9,householdfinance_v4_3!L9,householdfinance_v4_2!L9,householdfinance_v4_1!L9)/COUNT(householdfinance_v4_5!L9,householdfinance_v4_4!L9,householdfinance_v4_3!L9,householdfinance_v4_2!L9,householdfinance_v4_1!L9),0),"NA") -> 1 | M9: =IF($D9=1,ROUND(SUM(householdfinance_v4_5!M9,householdfinance_v4_4!M9,householdfinance_v4_3!M9,householdfinance_v4_2!M9,householdfinance_v4_1!M9)/COUNT(householdfinance_v4_5!M9,householdfinance_v4_4!M9,householdfinance_v4_3!M9,householdfinance_v4_2!M9,householdfinance_v4_1!M9),0),"NA") -> 1 | N9: =IF($D9=1,ROUND(SUM(householdfinance_v4_5!N9,householdfinance_v4_4!N9,householdfinance_v4_3!N9,householdfinance_v4_2!N9,householdfinance_v4_1!N9)/COUNT(householdfinance_v4_5!N9,householdfinance_v4_4!N9,householdfinance_v4_3!N9,householdfinance_v4_2!N9,householdfinance_v4_1!N9),0),"NA") -> 1 | O9: 1.5795407
A10: TD | B10: Question 9 | C10: 0 | D10: =ROUND(SUM(householdfinance_v4_5!D10,householdfinance_v4_4!D10,householdfinance_v4_3!D10,householdfinance_v4_2!D10,householdfinance_v4_1!D10)/COUNT(householdfinance_v4_5!D10,householdfinance_v4_4!D10,householdfinance_v4_3!D10,householdfinance_v4_2!D10,householdfinance_v4_1!D10),0) -> 1 | E10: =IF($D10=1,ROUND(SUM(householdfinance_v4_5!E10,householdfinance_v4_4!E10,householdfinance_v4_3!E10,householdfinance_v4_2!E10,householdfinance_v4_1!E10)/COUNT(householdfinance_v4_5!E10,householdfinance_v4_4!E10,householdfinance_v4_3!E10,householdfinance_v4_2!E10,householdfinance_v4_1!E10),0),"NA") -> 1 | F10: =IF($D10=1,ROUND(SUM(householdfinance_v4_5!F10,householdfinance_v4_4!F10,householdfinance_v4_3!F10,householdfinance_v4_2!F10,householdfinance_v4_1!F10)/COUNT(householdfinance_v4_5!F10,householdfinance_v4_4!F10,householdfinance_v4_3!F10,householdfinance_v4_2!F10,householdfinance_v4_1!F10),0),"NA") -> 0 | G10: =IF($D10=1,ROUND(SUM(householdfinance_v4_5!G10,householdfinance_v4_4!G10,householdfinance_v4_3!G10,householdfinance_v4_2!G10,householdfinance_v4_1!G10)/COUNT(householdfinance_v4_5!G10,householdfinance_v4_4!G10,householdfinance_v4_3!G10,householdfinance_v4_2!G10,householdfinance_v4_1!G10),0),"NA") -> 1 | H10: =IF($E10=1,ROUND(SUM(householdfinance_v4_5!H10,householdfinance_v4_4!H10,householdfinance_v4_3!H10,householdfinance_v4_2!H10,householdfinance_v4_1!H10)/COUNT(householdfinance_v4_5!H10,householdfinance_v4_4!H10,householdfinance_v4_3!H10,householdfinance_v4_2!H10,householdfinance_v4_1!H10),0),"NA") -> 1 | I10: =IF($D10=1,ROUND(SUM(householdfinance_v4_5!I10,householdfinance_v4_4!I10,householdfinance_v4_3!I10,householdfinance_v4_2!I10,householdfinance_v4_1!I10)/COUNT(householdfinance_v4_5!I10,householdfinance_v4_4!I10,householdfinance_v4_3!I10,householdfinance_v4_2!I10,householdfinance_v4_1!I10),0),"NA") -> 1 | J10: =IF(AND($E10=1,$F10=1),ROUND(SUM(householdfinance_v4_5!J10,householdfinance_v4_4!J10,householdfinance_v4_3!J10,householdfinance_v4_2!J10,householdfinance_v4_1!J10)/COUNT(householdfinance_v4_5!J10,householdfinance_v4_4!J10,householdfinance_v4_3!J10,householdfinance_v4_2!J10,householdfinance_v4_1!J10),0),"NA") -> NA | K10: =IF($D10=1,ROUND(SUM(householdfinance_v4_5!K10,householdfinance_v4_4!K10,householdfinance_v4_3!K10,householdfinance_v4_2!K10,householdfinance_v4_1!K10)/COUNT(householdfinance_v4_5!K10,householdfinance_v4_4!K10,householdfinance_v4_3!K10,householdfinance_v4_2!K10,householdfinance_v4_1!K10),0),"NA") -> 1 | L10: =IF($D10=1,ROUND(SUM(householdfinance_v4_5!L10,householdfinance_v4_4!L10,householdfinance_v4_3!L10,householdfinance_v4_2!L10,householdfinance_v4_1!L10)/COUNT(householdfinance_v4_5!L10,householdfinance_v4_4!L10,householdfinance_v4_3!L10,householdfinance_v4_2!L10,householdfinance_v4_1!L10),0),"NA") -> 1 | M10: =IF($D10=1,ROUND(SUM(householdfinance_v4_5!M10,householdfinance_v4_4!M10,householdfinance_v4_3!M10,householdfinance_v4_2!M10,householdfinance_v4_1!M10)/COUNT(householdfinance_v4_5!M10,householdfinance_v4_4!M10,householdfinance_v4_3!M10,householdfinance_v4_2!M10,householdfinance_v4_1!M10),0),"NA") -> 1 | N10: =IF($D10=1,ROUND(SUM(householdfinance_v4_5!N10,householdfinance_v4_4!N10,householdfinance_v4_3!N10,householdfinance_v4_2!N10,householdfinance_v4_1!N10)/COUNT(householdfinance_v4_5!N10,householdfinance_v4_4!N10,householdfinance_v4_3!N10,householdfinance_v4_2!N10,householdfinance_v4_1!N10),0),"NA") -> 1 | O10: 2.5088558
A11: TD | B11: Question 10 | C11: 0 | D11: =ROUND(SUM(householdfinance_v4_5!D11,householdfinance_v4_4!D11,householdfinance_v4_3!D11,householdfinance_v4_2!D11,householdfinance_v4_1!D11)/COUNT(householdfinance_v4_5!D11,householdfinance_v4_4!D11,householdfinance_v4_3!D11,householdfinance_v4_2!D11,householdfinance_v4_1!D11),0) -> 1 | E11: =IF($D11=1,ROUND(SUM(householdfinance_v4_5!E11,householdfinance_v4_4!E11,householdfinance_v4_3!E11,householdfinance_v4_2!E11,householdfinance_v4_1!E11)/COUNT(householdfinance_v4_5!E11,householdfinance_v4_4!E11,householdfinance_v4_3!E11,householdfinance_v4_2!E11,householdfinance_v4_1!E11),0),"NA") -> 1 | F11: =IF($D11=1,ROUND(SUM(householdfinance_v4_5!F11,householdfinance_v4_4!F11,householdfinance_v4_3!F11,householdfinance_v4_2!F11,householdfinance_v4_1!F11)/COUNT(householdfinance_v4_5!F11,householdfinance_v4_4!F11,householdfinance_v4_3!F11,householdfinance_v4_2!F11,householdfinance_v4_1!F11),0),"NA") -> 1 | G11: =IF($D11=1,ROUND(SUM(householdfinance_v4_5!G11,householdfinance_v4_4!G11,householdfinance_v4_3!G11,householdfinance_v4_2!G11,householdfinance_v4_1!G11)/COUNT(householdfinance_v4_5!G11,householdfinance_v4_4!G11,householdfinance_v4_3!G11,householdfinance_v4_2!G11,householdfinance_v4_1!G11),0),"NA") -> 1 | H11: =IF($E11=1,ROUND(SUM(householdfinance_v4_5!H11,householdfinance_v4_4!H11,householdfinance_v4_3!H11,householdfinance_v4_2!H11,householdfinance_v4_1!H11)/COUNT(householdfinance_v4_5!H11,householdfinance_v4_4!H11,householdfinance_v4_3!H11,householdfinance_v4_2!H11,householdfinance_v4_1!H11),0),"NA") -> 1 | I11: =IF($D11=1,ROUND(SUM(householdfinance_v4_5!I11,householdfinance_v4_4!I11,householdfinance_v4_3!I11,householdfinance_v4_2!I11,householdfinance_v4_1!I11)/COUNT(householdfinance_v4_5!I11,householdfinance_v4_4!I11,householdfinance_v4_3!I11,householdfinance_v4_2!I11,householdfinance_v4_1!I11),0),"NA") -> 1 | J11: =IF(AND($E11=1,$F11=1),ROUND(SUM(householdfinance_v4_5!J11,householdfinance_v4_4!J11,householdfinance_v4_3!J11,householdfinance_v4_2!J11,householdfinance_v4_1!J11)/COUNT(householdfinance_v4_5!J11,householdfinance_v4_4!J11,householdfinance_v4_3!J11,householdfinance_v4_2!J11,householdfinance_v4_1!J11),0),"NA") -> 1 | K11: =IF($D11=1,ROUND(SUM(householdfinance_v4_5!K11,householdfinance_v4_4!K11,householdfinance_v4_3!K11,householdfinance_v4_2!K11,householdfinance_v4_1!K11)/COUNT(householdfinance_v4_5!K11,householdfinance_v4_4!K11,householdfinance_v4_3!K11,householdfinance_v4_2!K11,householdfinance_v4_1!K11),0),"NA") -> 1 | L11: =IF($D11=1,ROUND(SUM(householdfinance_v4_5!L11,householdfinance_v4_4!L11,householdfinance_v4_3!L11,householdfinance_v4_2!L11,householdfinance_v4_1!L11)/COUNT(householdfinance_v4_5!L11,householdfinance_v4_4!L11,householdfinance_v4_3!L11,householdfinance_v4_2!L11,householdfinance_v4_1!L11),0),"NA") -> 1 | M11: =IF($D11=1,ROUND(SUM(householdfinance_v4_5!M11,householdfinance_v4_4!M11,householdfinance_v4_3!M11,householdfinance_v4_2!M11,householdfinance_v4_1!M11)/COUNT(householdfinance_v4_5!M11,householdfinance_v4_4!M11,householdfinance_v4_3!M11,householdfinance_v4_2!M11,householdfinance_v4_1!M11),0),"NA") -> 1 | N11: =IF($D11=1,ROUND(SUM(householdfinance_v4_5!N11,householdfinance_v4_4!N11,householdfinance_v4_3!N11,householdfinance_v4_2!N11,householdfinance_v4_1!N11)/COUNT(householdfinance_v4_5!N11,householdfinance_v4_4!N11,householdfinance_v4_3!N11,householdfinance_v4_2!N11,householdfinance_v4_1!N11),0),"NA") -> 1 | O11: 1.5113101
A12: TD | B12: Question 11 | C12: 0 | D12: =ROUND(SUM(householdfinance_v4_5!D12,householdfinance_v4_4!D12,householdfinance_v4_3!D12,householdfinance_v4_2!D12,householdfinance_v4_1!D12)/COUNT(householdfinance_v4_5!D12,householdfinance_v4_4!D12,householdfinance_v4_3!D12,householdfinance_v4_2!D12,householdfinance_v4_1!D12),0) -> 1 | E12: =IF($D12=1,ROUND(SUM(householdfinance_v4_5!E12,householdfinance_v4_4!E12,householdfinance_v4_3!E12,householdfinance_v4_2!E12,householdfinance_v4_1!E12)/COUNT(householdfinance_v4_5!E12,householdfinance_v4_4!E12,householdfinance_v4_3!E12,householdfinance_v4_2!E12,householdfinance_v4_1!E12),0),"NA") -> 1 | F12: =IF($D12=1,ROUND(SUM(householdfinance_v4_5!F12,householdfinance_v4_4!F12,householdfinance_v4_3!F12,householdfinance_v4_2!F12,householdfinance_v4_1!F12)/COUNT(householdfinance_v4_5!F12,householdfinance_v4_4!F12,householdfinance_v4_3!F12,householdfinance_v4_2!F12,householdfinance_v4_1!F12),0),"NA") -> 1 | G12: =IF($D12=1,ROUND(SUM(householdfinance_v4_5!G12,householdfinance_v4_4!G12,householdfinance_v4_3!G12,householdfinance_v4_2!G12,householdfinance_v4_1!G12)/COUNT(householdfinance_v4_5!G12,householdfinance_v4_4!G12,householdfinance_v4_3!G12,householdfinance_v4_2!G12,householdfinance_v4_1!G12),0),"NA") -> 1 | H12: =IF($E12=1,ROUND(SUM(householdfinance_v4_5!H12,householdfinance_v4_4!H12,householdfinance_v4_3!H12,householdfinance_v4_2!H12,householdfinance_v4_1!H12)/COUNT(householdfinance_v4_5!H12,householdfinance_v4_4!H12,householdfinance_v4_3!H12,householdfinance_v4_2!H12,householdfinance_v4_1!H12),0),"NA") -> 1 | I12: =IF($D12=1,ROUND(SUM(householdfinance_v4_5!I12,householdfinance_v4_4!I12,householdfinance_v4_3!I12,householdfinance_v4_2!I12,householdfinance_v4_1!I12)/COUNT(householdfinance_v4_5!I12,householdfinance_v4_4!I12,householdfinance_v4_3!I12,householdfinance_v4_2!I12,householdfinance_v4_1!I12),0),"NA") -> 1 | J12: =IF(AND($E12=1,$F12=1),ROUND(SUM(householdfinance_v4_5!J12,householdfinance_v4_4!J12,householdfinance_v4_3!J12,householdfinance_v4_2!J12,householdfinance_v4_1!J12)/COUNT(householdfinance_v4_5!J12,householdfinance_v4_4!J12,householdfinance_v4_3!J12,householdfinance_v4_2!J12,householdfinance_v4_1!J12),0),"NA") -> 1 | K12: =IF($D12=1,ROUND(SUM(householdfinance_v4_5!K12,householdfinance_v4_4!K12,householdfinance_v4_3!K12,householdfinance_v4_2!K12,householdfinance_v4_1!K12)/COUNT(householdfinance_v4_5!K12,householdfinance_v4_4!K12,householdfinance_v4_3!K12,householdfinance_v4_2!K12,householdfinance_v4_1!K12),0),"NA") -> 1 | L12: =IF($D12=1,ROUND(SUM(householdfinance_v4_5!L12,householdfinance_v4_4!L12,householdfinance_v4_3!L12,householdfinance_v4_2!L12,householdfinance_v4_1!L12)/COUNT(householdfinance_v4_5!L12,householdfinance_v4_4!L12,householdfinance_v4_3!L12,householdfinance_v4_2!L12,householdfinance_v4_1!L12),0),"NA") -> 1 | M12: =IF($D12=1,ROUND(SUM(householdfinance_v4_5!M12,householdfinance_v4_4!M12,householdfinance_v4_3!M12,householdfinance_v4_2!M12,householdfinance_v4_1!M12)/COUNT(householdfinance_v4_5!M12,householdfinance_v4_4!M12,householdfinance_v4_3!M12,householdfinance_v4_2!M12,householdfinance_v4_1!M12),0),"NA") -> 1 | N12: =IF($D12=1,ROUND(SUM(householdfinance_v4_5!N12,householdfinance_v4_4!N12,householdfinance_v4_3!N12,householdfinance_v4_2!N12,householdfinance_v4_1!N12)/COUNT(householdfinance_v4_5!N12,householdfinance_v4_4!N12,householdfinance_v4_3!N12,householdfinance_v4_2!N12,householdfinance_v4_1!N12),0),"NA") -> 1 | O12: 1.6401429
A13: TD | B13: Question 12 | C13: 0 | D13: =ROUND(SUM(householdfinance_v4_5!D13,householdfinance_v4_4!D13,householdfinance_v4_3!D13,householdfinance_v4_2!D13,householdfinance_v4_1!D13)/COUNT(householdfinance_v4_5!D13,householdfinance_v4_4!D13,householdfinance_v4_3!D13,householdfinance_v4_2!D13,householdfinance_v4_1!D13),0) -> 1 | E13: =IF($D13=1,ROUND(SUM(householdfinance_v4_5!E13,householdfinance_v4_4!E13,householdfinance_v4_3!E13,householdfinance_v4_2!E13,householdfinance_v4_1!E13)/COUNT(householdfinance_v4_5!E13,householdfinance_v4_4!E13,householdfinance_v4_3!E13,householdfinance_v4_2!E13,householdfinance_v4_1!E13),0),"NA") -> 1 | F13: =IF($D13=1,ROUND(SUM(householdfinance_v4_5!F13,householdfinance_v4_4!F13,householdfinance_v4_3!F13,householdfinance_v4_2!F13,householdfinance_v4_1!F13)/COUNT(householdfinance_v4_5!F13,householdfinance_v4_4!F13,householdfinance_v4_3!F13,householdfinance_v4_2!F13,householdfinance_v4_1!F13),0),"NA") -> 1 | G13: =IF($D13=1,ROUND(SUM(householdfinance_v4_5!G13,householdfinance_v4_4!G13,householdfinance_v4_3!G13,householdfinance_v4_2!G13,householdfinance_v4_1!G13)/COUNT(householdfinance_v4_5!G13,householdfinance_v4_4!G13,householdfinance_v4_3!G13,householdfinance_v4_2!G13,householdfinance_v4_1!G13),0),"NA") -> 1 | H13: =IF($E13=1,ROUND(SUM(householdfinance_v4_5!H13,householdfinance_v4_4!H13,householdfinance_v4_3!H13,householdfinance_v4_2!H13,householdfinance_v4_1!H13)/COUNT(householdfinance_v4_5!H13,householdfinance_v4_4!H13,householdfinance_v4_3!H13,householdfinance_v4_2!H13,householdfinance_v4_1!H13),0),"NA") -> 1 | I13: =IF($D13=1,ROUND(SUM(householdfinance_v4_5!I13,householdfinance_v4_4!I13,householdfinance_v4_3!I13,householdfinance_v4_2!I13,householdfinance_v4_1!I13)/COUNT(householdfinance_v4_5!I13,householdfinance_v4_4!I13,householdfinance_v4_3!I13,householdfinance_v4_2!I13,householdfinance_v4_1!I13),0),"NA") -> 1 | J13: =IF(AND($E13=1,$F13=1),ROUND(SUM(householdfinance_v4_5!J13,householdfinance_v4_4!J13,householdfinance_v4_3!J13,householdfinance_v4_2!J13,householdfinance_v4_1!J13)/COUNT(householdfinance_v4_5!J13,householdfinance_v4_4!J13,householdfinance_v4_3!J13,householdfinance_v4_2!J13,householdfinance_v4_1!J13),0),"NA") -> 1 | K13: =IF($D13=1,ROUND(SUM(householdfinance_v4_5!K13,householdfinance_v4_4!K13,householdfinance_v4_3!K13,householdfinance_v4_2!K13,householdfinance_v4_1!K13)/COUNT(householdfinance_v4_5!K13,householdfinance_v4_4!K13,householdfinance_v4_3!K13,householdfinance_v4_2!K13,householdfinance_v4_1!K13),0),"NA") -> 1 | L13: =IF($D13=1,ROUND(SUM(householdfinance_v4_5!L13,householdfinance_v4_4!L13,householdfinance_v4_3!L13,householdfinance_v4_2!L13,householdfinance_v4_1!L13)/COUNT(householdfinance_v4_5!L13,householdfinance_v4_4!L13,householdfinance_v4_3!L13,householdfinance_v4_2!L13,householdfinance_v4_1!L13),0),"NA") -> 1 | M13: =IF($D13=1,ROUND(SUM(householdfinance_v4_5!M13,householdfinance_v4_4!M13,householdfinance_v4_3!M13,householdfinance_v4_2!M13,householdfinance_v4_1!M13)/COUNT(householdfinance_v4_5!M13,householdfinance_v4_4!M13,householdfinance_v4_3!M13,householdfinance_v4_2!M13,householdfinance_v4_1!M13),0),"NA") -> 1 | N13: =IF($D13=1,ROUND(SUM(householdfinance_v4_5!N13,householdfinance_v4_4!N13,householdfinance_v4_3!N13,householdfinance_v4_2!N13,householdfinance_v4_1!N13)/COUNT(householdfinance_v4_5!N13,householdfinance_v4_4!N13,householdfinance_v4_3!N13,householdfinance_v4_2!N13,householdfinance_v4_1!N13),0),"NA") -> 1 | O13: 2.8631728
... A177: Sarah | B177: Question 64 | C177: 0 | D177: =ROUND(SUM(householdfinance_v4_5!D177,householdfinance_v4_4!D177,householdfinance_v4_3!D177,householdfinance_v4_2!D177,householdfinance_v4_1!D177)/COUNT(householdfinance_v4_5!D177,householdfinance_v4_4!D177,householdfinance_v4_3!D177,householdfinance_v4_2!D177,householdfinance_v4_1!D177),0) -> 1 | E177: =IF($D177=1,ROUND(SUM(householdfinance_v4_5!E177,householdfinance_v4_4!E177,householdfinance_v4_3!E177,householdfinance_v4_2!E177,householdfinance_v4_1!E177)/COUNT(householdfinance_v4_5!E177,householdfinance_v4_4!E177,householdfinance_v4_3!E177,householdfinance_v4_2!E177,householdfinance_v4_1!E177),0),"NA") -> 1 | F177: =IF($D177=1,ROUND(SUM(householdfinance_v4_5!F177,householdfinance_v4_4!F177,householdfinance_v4_3!F177,householdfinance_v4_2!F177,householdfinance_v4_1!F177)/COUNT(householdfinance_v4_5!F177,householdfinance_v4_4!F177,householdfinance_v4_3!F177,householdfinance_v4_2!F177,householdfinance_v4_1!F177),0),"NA") -> 1 | G177: =IF($D177=1,ROUND(SUM(householdfinance_v4_5!G177,householdfinance_v4_4!G177,householdfinance_v4_3!G177,householdfinance_v4_2!G177,householdfinance_v4_1!G177)/COUNT(householdfinance_v4_5!G177,householdfinance_v4_4!G177,householdfinance_v4_3!G177,householdfinance_v4_2!G177,householdfinance_v4_1!G177),0),"NA") -> 1 | H177: =IF($E177=1,ROUND(SUM(householdfinance_v4_5!H177,householdfinance_v4_4!H177,householdfinance_v4_3!H177,householdfinance_v4_2!H177,householdfinance_v4_1!H177)/COUNT(householdfinance_v4_5!H177,householdfinance_v4_4!H177,householdfinance_v4_3!H177,householdfinance_v4_2!H177,householdfinance_v4_1!H177),0),"NA") -> 1 | I177: =IF($D177=1,ROUND(SUM(householdfinance_v4_5!I177,householdfinance_v4_4!I177,householdfinance_v4_3!I177,householdfinance_v4_2!I177,householdfinance_v4_1!I177)/COUNT(householdfinance_v4_5!I177,householdfinance_v4_4!I177,householdfinance_v4_3!I177,householdfinance_v4_2!I177,householdfinance_v4_1!I177),0),"NA") -> 1 | J177: =IF(AND($E177=1,$F177=1),ROUND(SUM(householdfinance_v4_5!J177,householdfinance_v4_4!J177,householdfinance_v4_3!J177,householdfinance_v4_2!J177,householdfinance_v4_1!J177)/COUNT(householdfinance_v4_5!J177,householdfinance_v4_4!J177,householdfinance_v4_3!J177,householdfinance_v4_2!J177,householdfinance_v4_1!J177),0),"NA") -> 1 | K177: =IF($D177=1,ROUND(SUM(householdfinance_v4_5!K177,householdfinance_v4_4!K177,householdfinance_v4_3!K177,householdfinance_v4_2!K177,householdfinance_v4_1!K177)/COUNT(householdfinance_v4_5!K177,householdfinance_v4_4!K177,householdfinance_v4_3!K177,householdfinance_v4_2!K177,householdfinance_v4_1!K177),0),"NA") -> 1 | L177: =IF($D177=1,ROUND(SUM(householdfinance_v4_5!L177,householdfinance_v4_4!L177,householdfinance_v4_3!L177,householdfinance_v4_2!L177,householdfinance_v4_1!L177)/COUNT(householdfinance_v4_5!L177,householdfinance_v4_4!L177,householdfinance_v4_3!L177,householdfinance_v4_2!L177,householdfinance_v4_1!L177),0),"NA") -> 1 | M177: =IF($D177=1,ROUND(SUM(householdfinance_v4_5!M177,householdfinance_v4_4!M177,householdfinance_v4_3!M177,householdfinance_v4_2!M177,householdfinance_v4_1!M177)/COUNT(householdfinance_v4_5!M177,householdfinance_v4_4!M177,householdfinance_v4_3!M177,householdfinance_v4_2!M177,householdfinance_v4_1!M177),0),"NA") -> 1 | N177: =IF($D177=1,ROUND(SUM(householdfinance_v4_5!N177,householdfinance_v4_4!N177,householdfinance_v4_3!N177,householdfinance_v4_2!N177,householdfinance_v4_1!N177)/COUNT(householdfinance_v4_5!N177,householdfinance_v4_4!N177,householdfinance_v4_3!N177,householdfinance_v4_2!N177,householdfinance_v4_1!N177),0),"NA") -> 1 | O177: 1.8973668
